Workbook

Sheet Comparativo
A4: 1. VALUACIÓN (DCF, base FY2025) | B4: Soriana | C4: Walmex | D4: Chedraui | E4: La Comer
A5: WACC | B5: =Valuación!B15 -> 0.11919896 | C5: =Valuación!B53 -> 0.12228947 | D5: =Valuación!B91 -> 0.10091294 | E5: =Valuación!B129 -> 0.12085359
A6: Crecimiento perpetuo (g) | B6: =Valuación!B16 -> 0.035 | C6: =Valuación!B54 -> 0.035 | D6: =Valuación!B92 -> 0.035 | E6: =Valuación!B130 -> 0.035
A7: FCF 2025A (flujo libre de efectivo) | B7: =Valuación!B27 -> 6761.4 | C7: =Valuación!B65 -> 40916.76 | D7: =Valuación!B103 -> 12113.9 | E7: =Valuación!B141 -> 302.92442
A8: VPN de los FCF 2026E–2030E | B8: =Valuación!B31 -> 26403.824 | C8: =Valuación!B69 -> 161517.97 | D8: =Valuación!B107 -> 50520.788 | E8: =Valuación!B145 -> 1200.1425
A9: Valor terminal (TV) al 2030 | B9: =Valuación!B33 -> 96890.216 | C9: =Valuación!B71 -> 576210.9 | D9: =Valuación!B109 -> 225920.38 | E9: =Valuación!B147 -> 4337.2847
A10: Valor presente del TV | B10: =Valuación!B34 -> 55175.138 | C10: =Valuación!B72 -> 323636.15 | D10: =Valuación!B110 -> 139698.11 | E10: =Valuación!B148 -> 2451.7349
A11: Enterprise Value (EV) | B11: =Valuación!B35 -> 81578.962 | C11: =Valuación!B73 -> 485154.12 | D11: =Valuación!B111 -> 190218.9 | E11: =Valuación!B149 -> 3651.8774
A12: Deuda total (bancaria/bursátil + arrendamientos) | B12: =-Valuación!B36 -> 23618 | C12: =-Valuación!B74 -> 80848.1 | D12: =-Valuación!B112 -> 56744.34 | E12: =-Valuación!B150 -> 2441.8
A13: Efectivo y equivalentes | B13: =Valuación!B37 -> 9295 | C13: =Valuación!B75 -> 28591.2 | D13: =Valuación!B113 -> 14640.16 | E13: =Valuación!B151 -> 2962.8
A14: Equity Value (valor para los accionistas) | B14: =Valuación!B39 -> 67255.962 | C14: =Valuación!B77 -> 432897.22 | D14: =Valuación!B115 -> 148114.72 | E14: =Valuación!B153 -> 4172.8774
A15: Valor intrínseco por acción (MXN) | B15: =Valuación!B41 -> 37.364423 | C15: =Valuación!B79 -> 24.794063 | D15: =Valuación!B117 -> 154.24532 | E15: =Valuación!B155 -> 3.9153526
A16: Precio actual en bolsa (MXN) | B16: =Valuación!B42 -> 33.48 | C16: =Valuación!B80 -> 46.6 | D16: =Valuación!B118 -> 92.94 | E16: =Valuación!B156 -> 32.08
A17: Potencial de apreciación / (baja) | B17: =Valuación!B43 -> 0.11602221 | C17: =Valuación!B81 -> -0.46793856 | D17: =Valuación!B119 -> 0.65962259 | E17: =Valuación!B157 -> -0.87795036
A18: Precio objetivo consenso de analistas (MXN) | B18: =Generales!B24 -> 23.357 | C18: 60.094 | D18: 128.933 | E18: 47.67
A19: Recomendación consenso de analistas | B19: Venta (0 C / 1 M / 6 V) | C19: Neutral (5 C / 10 M / 3 V) | D19: Neutral (3 C / 12 M / 0 V) | E19: Compra (5 C / 4 M / 0 V)
A21: 2. RAZONES FINANCIERAS – PROMEDIO DE LOS ÚLTIMOS 5 TRIMESTRES | B21: Soriana | C21: Walmex | D21: Chedraui | E21: La Comer
A22: Circulante | B22: =Razones!G7 -> 1.2541889 | C22: =Razones!G23 -> 0.9768759 | D22: =Razones!G39 -> 0.933732 | E22: =Razones!G55 -> 1.2290463
A23: Prueba ácida | B23: =Razones!G8 -> 0.35473781 | C23: =Razones!G24 -> 0.34704511 | D23: =Razones!G40 -> 0.40675641 | E23: =Razones!G56 -> 0.48041577
A24: Deuda / Activo total | B24: =Razones!G9 -> 0.45505378 | C24: =Razones!G25 -> 0.52855776 | D24: =Razones!G41 -> 0.66310269 | E24: =Razones!G57 -> 0.2578378
A25: Capitalización a largo plazo | B25: =Razones!G10 -> 0.20654207 | C25: =Razones!G26 -> 0.18040972 | D25: =Razones!G42 -> 0.38012988 | E25: =Razones!G58 -> 0.064547002
A26: Cobertura de intereses | B26: =Razones!G11 -> 2.8984196 | C26: =Razones!G27 -> 6.6453315 | D26: =Razones!G43 -> 4.1504186 | E26: =Razones!G59 -> 11.844746
A27: Rotación del inventario (trimestral) | B27: =Razones!G12 -> 0.95612726 | C27: =Razones!G28 -> 1.7752133 | D27: =Razones!G44 -> 2.3833504 | E27: =Razones!G60 -> 1.3488695
A28: Rotación del inventario en días | B28: =Razones!G13 -> 96.032436 | C28: =Razones!G29 -> 51.658042 | D28: =Razones!G45 -> 38.380088 | E28: =Razones!G61 -> 67.850681
A29: Rotación del activo total (trimestral) | B29: =Razones!G14 -> 0.28166407 | C29: =Razones!G30 -> 0.51157675 | D29: =Razones!G46 -> 0.46365336 | E29: =Razones!G62 -> 0.2764494
A30: Margen bruto | B30: =Razones!G15 -> 0.24566153 | C30: =Razones!G31 -> 0.24235015 | D30: =Razones!G47 -> 0.23527548 | E30: =Razones!G63 -> 0.29672069
A31: Margen neto | B31: =Razones!G16 -> 0.020605935 | C31: =Razones!G32 -> 0.048260538 | D31: =Razones!G48 -> 0.023418786 | E31: =Razones!G64 -> 0.05488254
A32: ROA (trimestral) | B32: =Razones!G17 -> 0.005843019 | C32: =Razones!G33 -> 0.024728482 | D32: =Razones!G49 -> 0.010867202 | E32: =Razones!G65 -> 0.015156869
A33: ROE (trimestral) | B33: =Razones!G18 -> 0.010703389 | C33: =Razones!G34 -> 0.052476921 | D33: =Razones!G50 -> 0.032240332 | E33: =Razones!G66 -> 0.02043965
A34: ROI (trimestral) | B34: =Razones!G19 -> 0.012031436 | C34: =Razones!G35 -> 0.042432022 | D34: =Razones!G51 -> 0.024290294 | E34: =Razones!G67 -> 0.017861415
A36: 3. RAZONES FINANCIERAS ANUALES FY2025 (incluye Chedraui) | B36: Soriana | C36: Walmex | D36: Chedraui | E36: La Comer
A37: Circulante | B37: =IFERROR(Datos!G19/Datos!G21,"n.d.") -> 1.2373849 | C37: =IFERROR(Datos!G45/Datos!G47,"n.d.") -> 0.96696082 | D37: =IFERROR(Datos!G71/Datos!G73,"n.d.") -> 0.92079667 | E37: =IFERROR(Datos!G97/Datos!G99,"n.d.") -> 1.2070372
A38: Prueba ácida | B38: =IFERROR((Datos!G19-Datos!G18)/Datos!G21,"n.d.") -> 0.414238 | C38: =IFERROR((Datos!G45-Datos!G44)/Datos!G47,"n.d.") -> 0.33384163 | D38: =IFERROR((Datos!G71-Datos!G70)/Datos!G73,"n.d.") -> 0.43735523 | E38: =IFERROR((Datos!G97-Datos!G96)/Datos!G99,"n.d.") -> 0.50008921
A39: Deuda / Activo total | B39: =IFERROR(Datos!G23/Datos!G20,"n.d.") -> 0.45697843 | C39: =IFERROR(Datos!G49/Datos!G46,"n.d.") -> 0.52434323 | D39: =IFERROR(Datos!G75/Datos!G72,"n.d.") -> 0.67356639 | E39: =IFERROR(Datos!G101/Datos!G98,"n.d.") -> 0.2544825
A40: Capitalización a largo plazo | B40: =IFERROR(Datos!G22/Datos!G20,"n.d.") -> 0.2056294 | C40: =IFERROR(Datos!G48/Datos!G46,"n.d.") -> 0.1816704 | D40: =IFERROR(Datos!G74/Datos!G72,"n.d.") -> 0.37134872 | E40: =IFERROR(Datos!G100/Datos!G98,"n.d.") -> 0.06423617
A41: Cobertura de intereses | B41: =IFERROR(Datos!G9/Datos!G10,"n.d.") -> 2.4567339 | C41: =IFERROR(Datos!G35/Datos!G36,"n.d.") -> 6.8465638 | D41: =IFERROR(Datos!G61/Datos!G62,"n.d.") -> 3.9247028 | E41: =IFERROR(Datos!G87/Datos!G88,"n.d.") -> 13.400737
A42: Rotación del inventario (anual) | B42: =IFERROR(Datos!G7/Datos!G18,"n.d.") -> 4.1740854 | C42: =IFERROR(Datos!G33/Datos!G44,"n.d.") -> 7.1325601 | D42: =IFERROR(Datos!G59/Datos!G70,"n.d.") -> 9.7102302 | E42: =IFERROR(Datos!G85/Datos!G96,"n.d.") -> 5.6268631
A43: Rotación del inventario en días (365) | B43: =IFERROR(365*Datos!G18/Datos!G7,"n.d.") -> 87.444305 | C43: =IFERROR(365*Datos!G44/Datos!G33,"n.d.") -> 51.173772 | D43: =IFERROR(365*Datos!G70/Datos!G59,"n.d.") -> 37.589222 | E43: =IFERROR(365*Datos!G96/Datos!G85,"n.d.") -> 64.867404
A44: Rotación del activo total (anual) | B44: =IFERROR(Datos!G6/Datos!G20,"n.d.") -> 1.1376395 | C44: =IFERROR(Datos!G32/Datos!G46,"n.d.") -> 2.0425044 | D44: =IFERROR(Datos!G58/Datos!G72,"n.d.") -> 1.8415047 | E44: =IFERROR(Datos!G84/Datos!G98,"n.d.") -> 1.0755432
A45: Margen bruto | B45: =IFERROR(Datos!G8/Datos!G6,"n.d.") -> 0.24090359 | C45: =IFERROR(Datos!G34/Datos!G32,"n.d.") -> 0.24238672 | D45: =IFERROR(Datos!G60/Datos!G58,"n.d.") -> 0.22959264 | E45: =IFERROR(Datos!G86/Datos!G84,"n.d.") -> 0.29637336
A46: Margen neto | B46: =IFERROR(Datos!G13/Datos!G6,"n.d.") -> 0.018781511 | C46: =IFERROR(Datos!G39/Datos!G32,"n.d.") -> 0.049318707 | D46: =IFERROR(Datos!G65/Datos!G58,"n.d.") -> 0.022417013 | E46: =IFERROR(Datos!G91/Datos!G84,"n.d.") -> 0.05648874
A47: ROA (anual) | B47: =IFERROR(Datos!G13/Datos!G20,"n.d.") -> 0.02136659 | C47: =IFERROR(Datos!G39/Datos!G46,"n.d.") -> 0.10073368 | D47: =IFERROR(Datos!G65/Datos!G72,"n.d.") -> 0.041281034 | E47: =IFERROR(Datos!G91/Datos!G98,"n.d.") -> 0.060756079
A48: ROE (anual) | B48: =IFERROR(Datos!G13/Datos!G24,"n.d.") -> 0.03934759 | C48: =IFERROR(Datos!G39/Datos!G50,"n.d.") -> 0.21177807 | D48: =IFERROR(Datos!G65/Datos!G76,"n.d.") -> 0.12646073 | E48: =IFERROR(Datos!G91/Datos!G102,"n.d.") -> 0.081495175
A49: ROI (anual) | B49: =IFERROR(Datos!G9*(1-WACC!$B$10)/(Datos!G24+Datos!G29),"n.d.") -> 0.048790032 | C49: =IFERROR(Datos!G35*(1-WACC!$B$10)/(Datos!G50+Datos!G55),"n.d.") -> 0.17364337 | D49: =IFERROR(Datos!G61*(1-WACC!$B$10)/(Datos!G76+Datos!G81),"n.d.") -> 0.096876335 | E49: =IFERROR(Datos!G87*(1-WACC!$B$10)/(Datos!G102+Datos!G107),"n.d.") -> 0.070505439

Sheet Generales
A4: 1. INFORMACIÓN GENERAL DE LA EMPRESA | B4: Dato
A5: Clave de cotización | B5: SORIANA B (BMV, cotiza desde 1987)
A6: Fundación | B6: 1968, Torreón, Coahuila
A7: Sede corporativa | B7: Monterrey, Nuevo León
A8: Giro | B8: Tiendas de autoservicio y clubes de membresía (multiformato)
A9: Tiendas en operación (2T26) | B9: 812
A10: Colaboradores (jun-2026) | B10: 82064
A11: Acciones en circulación (millones) | B11: =WACC!B17 -> 1800
A12: Capitalización de mercado a precio actual (mdp) | B12: =WACC!B18 -> 60264
A14: 2. NOTICIAS Y ANÁLISIS RECIENTES | B14: Fecha
A15: Resultados 2T26: menos ventas, más utilidad | B15: 31-jul-2026
A16: Cierre de 20 tiendas en 2026 | B16: 26-ago-2026
A17: Reducción de plantilla y automatización | B17: 2-sep-2026
A18: Plan de inversión 2S26 | B18: sep-2026
A19: Sector: Walmart, Soriana y Chedraui sufren por ingresos e inflación | B19: 2026
A21: 3. CALIFICACIÓN Y CONSENSO DE ANALISTAS | B21: Dato
A22: Calificación crediticia (HR Ratings) | B22: HR+1 (corto plazo)
A23: Consenso de analistas | B23: Venta
A24: Precio objetivo promedio 12 meses (MXN) | B24: 23.357
A26: 4. ANÁLISIS FUNDAMENTAL – RESUMEN FINANCIERO FY2025 (mdp) | B26: Valor
A27: Ingresos totales | B27: =Datos!G6 -> 177515
A28: Utilidad bruta | B28: =Datos!G8 -> 42764
A29: Utilidad de operación (EBIT) | B29: =Datos!G9 -> 7552
A30: Utilidad neta consolidada | B30: =Datos!G13 -> 3334
A31: Margen bruto | B31: =Datos!G8/Datos!G6 -> 0.24090359
A32: Margen de operación | B32: =Datos!G9/Datos!G6 -> 0.042542884
A33: Margen neto | B33: =Datos!G13/Datos!G6 -> 0.018781511
A35: 5. CUENTA DE RESULTADOS – ÚLTIMO TRIMESTRE (2T26 vs 2T25, mdp) | B35: 2T26
A36: Ingresos totales | B36: =Datos!F6 -> 43559
A37: Costo de ventas | B37: =Datos!F7 -> 32919
A38: Utilidad bruta | B38: =Datos!F8 -> 10640
A39: Utilidad de operación | B39: =Datos!F9 -> 1855
A40: Gastos financieros | B40: =Datos!F10 -> 582
A41: Utilidad neta | B41: =Datos!F13 -> 1090
A43: 6. BALANCE (cierre 2025 vs 1T26, mdp) | B43: Dic-2025
A44: Activo total | B44: =Datos!G20 -> 156038
A45: Pasivo total | B45: =Datos!G23 -> 71306
A46: Capital contable | B46: =Datos!G24 -> 84732
A47: Deuda bancaria y bursátil | B47: =Datos!G25+Datos!G26 -> 11500
A48: Efectivo | B48: =Datos!G17 -> 9295
A50: 7. FLUJOS DE EFECTIVO FY2025 (mdp) | B50: Valor
A51: Flujo neto de operación (CFO) | B51: =Datos!G15 -> 13738
A52: Capex | B52: =Datos!G16 -> 2867
A53: Flujo libre (CFO − Capex) | B53: =B51-B52 -> 10871
A55: 8. ANÁLISIS FUNDAMENTAL – RATIOS DE MERCADO | B55: Valor
A56: P/U (precio / utilidad por acción) | B56: =WACC!B13/(Datos!G13/WACC!B17) -> 18.075585
A57: Valor en libros por acción (MXN) | B57: =Datos!G24/WACC!B17 -> 47.073333
A58: P/VL (precio / valor en libros) | B58: =WACC!B13/B57 -> 0.7112307
A59: ROE anual FY2025 | B59: =Comparativo!B48 -> 0.03934759
A61: 9. DIVIDENDOS | B61: Valor
A62: Último dividendo por acción (MXN) | B62: 0.5556
A63: Rendimiento por dividendo a precio actual | B63: =B62/WACC!B13 -> 0.016594982
A65: 10. REPORTE – PUNTOS CLAVE 2T26
A66: Ventas mismas tiendas 2T26 | B66: −4.5%
A67: Margen bruto 2T26 | B67: =Datos!F8/Datos!F6 -> 0.2442664
A68: Costo financiero neto 2T26 (mdp) | B68: 477
A69: Deuda neta bancaria y bursátil al 2T26 (mdp) | B69: =Datos!F25+Datos!F26-Datos!F17 -> 4624.616
A70: Capex acumulado 1S26 (mdp) | B70: =Datos!E16+Datos!F16 -> 1410.9
A72: 11. PREVISIÓN | B72: Valor
A73: Próximo reporte trimestral (3T26) | B73: 23-oct-2026
A74: Precio objetivo consenso vs precio actual | B74: =B24/WACC!B13-1 -> -0.30235962
A75: Proyección de ingresos 2027 HR Ratings (mdp) | B75: 196480
A77: 12. ANÁLISIS TÉCNICO | B77: Valor
A78: Precio de cierre (MXN) | B78: =WACC!B13 -> 33.48
A79: Rango de 52 semanas (MXN) | B79: 23.90 – 42.70
A80: Variación 1 año | B80: 0.2127
A81: Señal técnica resumen (diaria, semanal y mensual) | B81: Compra fuerte
A82: RSI (14) | B82: 75
A83: MACD (12,26) | B83: 1.154
A84: Media móvil 50 días (MXN) | B84: 29.68
A85: Media móvil 200 días (MXN) | B85: 29.71
A88: 13. COMPARATIVO BURSÁTIL DEL SECTOR | B88: Soriana | C88: Walmex | D88: Chedraui | E88: La Comer
A89: Precio actual (MXN) | B89: =WACC!B13 -> 33.48 | C89: =WACC!C13 -> 46.6 | D89: =WACC!D13 -> 92.94 | E89: =WACC!E13 -> 32.08
A90: P/U | B90: =B56 -> 18.075585 | C90: =WACC!C13/(Datos!G39/WACC!C17) -> 16.308102 | D90: =WACC!D13/(Datos!G65/WACC!D17) -> 13.481171 | E90: =WACC!E13/(Datos!G91/WACC!E17) -> 12.735034
A91: Rendimiento por dividendo | B91: =B63 -> 0.016594982 | C91: 0.0253 | D91: 0.0249 | E91: 0.0088
A92: Variación 1 año | B92: =B80 -> 0.2127 | C92: -0.1686 | D92: -0.4125 | E92: -0.2051
A93: Beta de regresión (referencia) | B93: -0.24 | C93: 0.03 | D93: -0.06 | E93: 0.17
A94: Señal técnica resumen (diaria) | B94: Compra fuerte | C94: Compra fuerte | D94: Compra fuerte | E94: Compra fuerte
A95: RSI (14) | B95: =B82 -> 75 | C95: 41.07 | D95: 60.23 | E95: 40.03
A96: Consenso de analistas | B96: Venta | C96: Neutral | D96: Neutral | E96: Compra
A97: Precio objetivo consenso (MXN) | B97: =Comparativo!B18 -> 23.357 | C97: =Comparativo!C18 -> 60.094 | D97: =Comparativo!D18 -> 128.933 | E97: =Comparativo!E18 -> 47.67
A98: Calificación crediticia | B98: HR+1 (HR Ratings, CP) | C98: n.d. | D98: AAA(mex) Fitch, perspectiva estable | E98: n.d.

Sheet Datos
A5: ORGANIZACIÓN SORIANA (SORIANA B) | B5: 2T25 | C5: 3T25 | D5: 4T25 | E5: 1T26 | F5: 2T26 | G5: FY2025
A6: Ingresos totales | B6: 45810 | C6: 42683 | D6: 47592 | E6: 40444 | F6: 43559 | G6: 177515
A7: Costo de ventas | B7: 34856 | C7: 31998 | D7: 35795 | E7: 30466 | F7: 32919 | G7: 134752
A8: Utilidad bruta | B8: 10954 | C8: 10685 | D8: 11797 | E8: 9978 | F8: 10640 | G8: 42764
A9: Utilidad de operación (EBIT) | B9: 1909 | C9: 1468 | D9: 2486 | E9: 1822 | F9: 1855 | G9: 7552
A10: Gastos financieros (intereses) | B10: 829 | C10: 786 | D10: 616 | E10: 588 | F10: 582 | G10: 3074
A11: Utilidad antes de impuestos | B11: 1203 | C11: 764 | D11: 1763 | E11: 1326 | F11: 1372 | G11: 4766
A12: Impuestos a la utilidad | B12: 461 | C12: 179 | D12: 455 | E12: 492 | F12: 282 | G12: 1433
A13: Utilidad neta consolidada | B13: 743 | C13: 584 | D13: 1308 | E13: 834 | F13: 1090 | G13: 3334
A14: Depreciación y amortización | B14: 1105.905 | C14: 1049.349 | D14: 1051 | E14: 1048.889 | F14: 1030.633 | G14: 4342
A15: Flujo neto de operación (CFO) | B15: 4013.113 | C15: -205.9 | D15: 13017 | E15: -3565.6 | F15: 3916.003 | G15: 13738
A16: Capex (inmuebles, equipo e intangibles) | B16: =SUM(B110:B112) -> 663.2 | C16: =SUM(C110:C112) -> 775.2 | D16: =SUM(D110:D112) -> 816 | E16: =SUM(E110:E112) -> 501 | F16: =SUM(F110:F112) -> 909.9 | G16: 2867
A17: Efectivo y equivalentes | B17: 7540 | C17: 5798 | D17: 9295 | E17: 4589 | F17: 6875.384 | G17: =D17 -> 9295
A18: Inventarios | B18: 37421 | C18: 36394 | D18: 32283 | E18: 32635 | F18: 35486.661 | G18: =D18 -> 32283
A19: Activo circulante | B19: 52131 | C19: 49767 | D19: 48529 | E19: 43562 | F19: 49259.847 | G19: =D19 -> 48529
A20: Activo total | B20: 159842 | C20: 157502 | D20: 156038 | E20: 150941 | F20: =F23+F24 -> 156813 | G20: =D20 -> 156038
A21: Pasivo circulante | B21: 41065 | C21: 38190 | D21: 39219 | E21: 33850 | F21: 41957.933 | G21: =D21 -> 39219
A22: Pasivo a largo plazo | B22: 34801 | C22: 34753 | D22: 32086 | E22: 31527 | F22: =F23-F21 -> 28201.067 | G22: =D22 -> 32086
A23: Pasivo total | B23: 75866 | C23: 72943 | D23: 71306 | E23: 65377 | F23: 70159 | G23: =D23 -> 71306
A24: Capital contable | B24: 83976 | C24: 84559 | D24: 84732 | E24: 85564 | F24: 86654 | G24: =D24 -> 84732
A25: Deuda bursátil y bancaria CP | B25: 6627 | C25: 6553 | D25: 3000 | E25: 3000 | F25: 6500 | G25: =D25 -> 3000
A26: Deuda bursátil y bancaria LP | B26: 11500 | C26: 11500 | D26: 8500 | E26: 8500 | F26: 5000 | G26: =D26 -> 8500
A27: Pasivo por arrendamiento CP | B27: 638 | C27: 659 | D27: 676 | E27: 683 | F27: 639.968 | G27: =D27 -> 676
A28: Pasivo por arrendamiento LP | B28: 11389 | C28: 11506 | D28: 11442 | E28: 11540 | F28: 11580.62 | G28: =D28 -> 11442
A29: Deuda total (financiera + arrendamientos) | B29: =IF(COUNT(B25:B28)=4,SUM(B25:B28),"n.d.") -> 30154 | C29: =IF(COUNT(C25:C28)=4,SUM(C25:C28),"n.d.") -> 30218 | D29: =IF(COUNT(D25:D28)=4,SUM(D25:D28),"n.d.") -> 23618 | E29: =IF(COUNT(E25:E28)=4,SUM(E25:E28),"n.d.") -> 23723 | F29: =IF(COUNT(F25:F28)=4,SUM(F25:F28),"n.d.") -> 23720.588 | G29: =IF(COUNT(G25:G28)=4,SUM(G25:G28),"n.d.") -> 23618
A31: WALMART DE MÉXICO (WALMEX) | B31: 2T25 | C31: 3T25 | D31: 4T25 | E31: 1T26 | F31: 2T26 | G31: FY2025
A32: Ingresos totales | B32: 246253.8 | C32: 241520.2 | D32: 282849.3 | E32: 245018.5 | F32: 250947.8 | G32: 1011597.9
A33: Costo de ventas | B33: 186848.1 | C33: 181746.3 | D33: 214905.4 | E33: 185425.3 | F33: 190822.8 | G33: 766400
A34: Utilidad bruta | B34: 59405.7 | C34: 59773.8 | D34: 67943.9 | E34: 59593.2 | F34: 60125 | G34: 245197.9
A35: Utilidad de operación (EBIT) | B35: 17267.1 | C35: 19020.8 | D35: 23317 | E35: 18471.6 | F35: 17019.7 | G35: 78493.8
A36: Gastos financieros (intereses) | B36: 2646.3 | C36: 3223.3 | D36: 2795.1 | E36: 2895.6 | F36: 2799.6 | G36: 11464.7
A37: Utilidad antes de impuestos | B37: 15076.8 | C37: 16328 | D37: 21053.3 | E37: 16176.4 | F37: 14754.6 | G37: 68876.6
A38: Impuestos a la utilidad | B38: 3849.9 | C38: 4580.7 | D38: 6453.5 | E38: 3676.9 | F38: 3602.2 | G38: 18985.9
A39: Utilidad neta consolidada | B39: 11226.9 | C39: 11747.3 | D39: 14599.8 | E39: 12499.6 | F39: 11152.4 | G39: 49890.7
A40: Depreciación y amortización | B40: 6227.732 | C40: 6245.37 | D40: 6277.929 | E40: 6506.919 | F40: 6620.741 | G40: 24953.1
A41: Flujo neto de operación (CFO) | B41: 21549.377 | C41: 22017.152 | D41: 43314.63 | E41: 4955.647 | F41: 18326.104 | G41: 82437.7
A42: Capex (inmuebles, equipo e intangibles) | B42: =SUM(B113:B115) -> 7989.7 | C42: =SUM(C113:C115) -> 11746.3 | D42: =SUM(D113:D115) -> 15831.8 | E42: =SUM(E113:E115) -> 2436.5 | F42: =SUM(F113:F115) -> 9264.9 | G42: 38982
A43: Efectivo y equivalentes | B43: 32443.8 | C43: 35181.7 | D43: 28591.2 | E43: 28085.1 | F43: 30118.3 | G43: =D43 -> 28591.2
A44: Inventarios | B44: 106742.4 | C44: 113238.4 | D44: 107450.9 | E44: 106202 | F44: 107528.9 | G44: =D44 -> 107450.9
A45: Activo circulante | B45: 166663.9 | C45: 176974.1 | D45: 164109.4 | E45: 163317.9 | F45: 168653.5 | G45: =D45 -> 164109.4
A46: Activo total | B46: 480957.5 | C46: 497334.5 | D46: 495273.3 | E46: 496840.7 | F46: 505946.6 | G46: =D46 -> 495273.3
A47: Pasivo circulante | B47: 177161.4 | C47: 186356.5 | D47: 169716.7 | E47: 153660.1 | F47: 174921.4 | G47: =D47 -> 169716.7
A48: Pasivo a largo plazo | B48: 86252.9 | C48: 87538.9 | D48: 89976.5 | E48: 90611.7 | F48: 92411.4 | G48: =D48 -> 89976.5
A49: Pasivo total | B49: 263414.3 | C49: 273895.4 | D49: 259693.2 | E49: 244271.8 | F49: 267332.8 | G49: =D49 -> 259693.2
A50: Capital contable | B50: 217543.2 | C50: 223439.1 | D50: 235580.1 | E50: 252568.9 | F50: 238613.8 | G50: =D50 -> 235580.1
A51: Deuda bursátil y bancaria CP | B51: 0 | C51: 0 | D51: 0 | E51: 0 | F51: 0 | G51: =D51 -> 0
A52: Deuda bursátil y bancaria LP | B52: 0 | C52: 0 | D52: 0 | E52: 0 | F52: 0 | G52: =D52 -> 0
A53: Pasivo por arrendamiento CP | B53: 4917.5 | C53: 4981.5 | D53: 5186.9 | E53: 5317.6 | F53: 5495.2 | G53: =D53 -> 5186.9
A54: Pasivo por arrendamiento LP | B54: 73863 | C54: 74013.7 | D54: 75661.2 | E54: 75952.9 | F54: 77602.9 | G54: =D54 -> 75661.2
A55: Deuda total (financiera + arrendamientos) | B55: =IF(COUNT(B51:B54)=4,SUM(B51:B54),"n.d.") -> 78780.5 | C55: =IF(COUNT(C51:C54)=4,SUM(C51:C54),"n.d.") -> 78995.2 | D55: =IF(COUNT(D51:D54)=4,SUM(D51:D54),"n.d.") -> 80848.1 | E55: =IF(COUNT(E51:E54)=4,SUM(E51:E54),"n.d.") -> 81270.5 | F55: =IF(COUNT(F51:F54)=4,SUM(F51:F54),"n.d.") -> 83098.1 | G55: =IF(COUNT(G51:G54)=4,SUM(G51:G54),"n.d.") -> 80848.1
A57: GRUPO COMERCIAL CHEDRAUI (CHDRAUI B) | B57: 2T25 | C57: 3T25 | D57: 4T25 | E57: 1T26 | F57: 2T26 | G57: FY2025 | I57: Aux. FY2025
A58: Ingresos totales | B58: 73883.849 | C58: 71768.073 | D58: 75221.137 | E58: 69795.808 | F58: 71034.917 | G58: 295313.65
A59: Costo de ventas | B59: 56049.956 | C59: 54122.158 | D59: 60335.176 | E59: 52843.176 | F59: 53394.045 | G59: 227511.81
A60: Utilidad bruta | B60: 17833.893 | C60: 17645.915 | D60: 14885.961 | E60: 16952.632 | F60: 17640.872 | G60: 67801.84
A61: Utilidad de operación (EBIT) | B61: 4247.997 | C61: 3745.26 | D61: 3402.984 | E61: 3680.616 | F61: 4016.894 | G61: 15097.9
A62: Gastos financieros (intereses) | B62: 880.6 | C62: 944.2 | D62: 1003.1 | E62: 904.7 | F62: 892.5 | G62: 3846.89
A63: Utilidad antes de impuestos | B63: 2986.855 | C63: 2417.756 | D63: 1813.805 | E63: 2306.498 | F63: 2653.783 | G63: 9508.62
A64: Impuestos a la utilidad | B64: 924.533 | C64: 771.393 | D64: 469.642 | E64: 723.238 | F64: 829.095 | G64: 2888.58
A65: Utilidad neta consolidada | B65: 2062.322 | C65: 1646.363 | D65: 1344.163 | E65: 1583.26 | F65: 1824.688 | G65: 6620.05
A66: Depreciación y amortización | B66: 2303.668 | C66: 2297.228 | D66: 2308.71 | E66: 2258.954 | F66: 2312.731 | G66: 9293.25
A67: Flujo neto de operación (CFO) | B67: 5617.816 | C67: 4366.019 | D67: 10197.404 | E67: -756.9 | F67: 5978.777 | G67: 18240.86
A68: Capex (inmuebles, equipo e intangibles) | B68: =SUM(B116:B118) -> 2185.9 | C68: =SUM(C116:C118) -> 2286.1 | D68: =SUM(D116:D118) -> 2688.875 | E68: =SUM(E116:E118) -> 2195.6 | F68: =SUM(F116:F118) -> 2859.1 | G68: =I68 -> 7747.88 | I68: 7747.88 | J68: Inversión neta (−flujo de inversión FY2025), proxy de capex
A69: Efectivo y equivalentes | B69: 9740.315 | C69: 9638.014 | D69: 14640.162 | E69: 10487.937 | F69: 8499.778 | G69: 14640.16
A70: Inventarios | B70: 22914.705 | C70: 23527.624 | D70: 23430.115 | E70: 23660.893 | F70: 22606.468 | G70: =D70 -> 23430.115
A71: Activo circulante | B71: 39608.185 | C71: 41642.553 | D71: 44626.647 | E71: 41294.339 | F71: 38968.064 | G71: 44626.65
A72: Activo total | B72: 154895.84 | C72: 155620.7 | D72: 160365.41 | E72: 156233.2 | F72: 152993.19 | G72: 160365.41
A73: Pasivo circulante | B73: 42247.697 | C73: 43507.303 | D73: 48465.257 | E73: 43264.981 | F73: 43358.105 | G73: 48465.26
A74: Pasivo a largo plazo | B74: =B75-B73 -> 61262.859 | C74: =C75-C73 -> 60415.588 | D74: =D75-D73 -> 59551.489 | E74: =E75-E73 -> 58979.77 | F74: =F75-F73 -> 56310.095 | G74: =G75-G73 -> 59551.49
A75: Pasivo total | B75: 103510.56 | C75: 103922.89 | D75: 108016.75 | E75: 102244.75 | F75: 99668.2 | G75: 108016.75
A76: Capital contable | B76: 51385.283 | C76: 51697.81 | D76: 52348.664 | E76: 53988.454 | F76: 53324.988 | G76: 52348.66
A77: Deuda bursátil y bancaria CP | B77: 1055.054 | C77: 1541.907 | D77: 530.018 | E77: 705.319 | F77: 1087.08 | G77: =D77 -> 530.018
A78: Deuda bursátil y bancaria LP | B78: 7557.12 | C78: 7353.001 | D78: 7186.68 | E78: 7226.68 | F78: 5241 | G78: =D78 -> 7186.68
A79: Pasivo por arrendamiento CP | B79: 2674.355 | C79: 2626.869 | D79: 2925.974 | E79: 3014.648 | F79: 3015.621 | G79: =D79 -> 2925.974
A80: Pasivo por arrendamiento LP | B80: 48473.083 | C80: 47033.289 | D80: 46631.683 | E80: 46405.889 | F80: 45276.747 | G80: =D80 -> 46631.683
A81: Deuda total (financiera + arrendamientos) | B81: =IF(COUNT(B77:B80)=4,SUM(B77:B80),"n.d.") -> 59759.612 | C81: =IF(COUNT(C77:C80)=4,SUM(C77:C80),"n.d.") -> 58555.066 | D81: =IF(COUNT(D77:D80)=4,SUM(D77:D80),"n.d.") -> 57274.355 | E81: =IF(COUNT(E77:E80)=4,SUM(E77:E80),"n.d.") -> 57352.536 | F81: =IF(COUNT(F77:F80)=4,SUM(F77:F80),"n.d.") -> 54620.448 | G81: 56744.34
A83: LA COMER (LACOMER UBC) | B83: 2T25 | C83: 3T25 | D83: 4T25 | E83: 1T26 | F83: 2T26 | G83: FY2025 | I83: 9M2025
A84: Ingresos totales | B84: 12232.6 | C84: 11813.2 | D84: =G84-I84 -> 12404.39 | E84: 12006.5 | F84: 12933.1 | G84: 47526.64 | I84: 35122.25
A85: Costo de ventas | B85: 8718.1 | C85: 8306.7 | D85: =G85-I85 -> 8694.29 | E85: 8328.1 | F85: 9130.7 | G85: 33441.01 | I85: 24746.72
A86: Utilidad bruta | B86: 3514.5 | C86: 3506.5 | D86: =G86-I86 -> 3710.1 | E86: 3678.4 | F86: 3802.4 | G86: 14085.63 | I86: 10375.53
A87: Utilidad de operación (EBIT) | B87: 1026.3 | C87: 839 | D87: =G87-I87 -> 712.57 | E87: 1001.4 | F87: 932.2 | G87: 3564.06 | I87: 2851.49
A88: Gastos financieros (intereses) | B88: 90.2 | C88: 76.7 | D88: 64.9 | E88: 73.3 | F88: 76 | G88: 265.96 | I88: 235.52
A89: Utilidad antes de impuestos | B89: 1003.4 | C89: 817 | D89: =G89-I89 -> 697.65 | E89: 992.7 | F89: 893.8 | G89: 3507.62 | I89: 2809.97
A90: Impuestos a la utilidad | B90: 200.4 | C90: 176.1 | D90: =G90-I90 -> 191.44 | E90: 250.5 | F90: 222.6 | G90: 822.9 | I90: 631.46
A91: Utilidad neta consolidada | B91: 803 | C91: 640.9 | D91: =G91-I91 -> 506.21 | E91: 742.2 | F91: 671.1 | G91: 2684.72 | I91: 2178.51
A92: Depreciación y amortización | B92: 407.835 | C92: 411.717 | D92: 397.26 | E92: 386.412 | F92: 399.125 | G92: =I92/I84*G84 -> 1650.7548 | I92: 1219.91
A93: Flujo neto de operación (CFO) | B93: 1576.03 | C93: 468.589 | D93: 1924.595 | E93: 583.825 | F93: 988.725 | G93: =744.022+B93+C93+D93 -> 4713.236 | I93: 2788.64
A94: Capex (inmuebles, equipo e intangibles) | B94: =SUM(B119:B121) -> 1484.5 | C94: =SUM(C119:C121) -> 912.2 | D94: =SUM(D119:D121) -> 1480.1 | E94: =SUM(E119:E121) -> 606.8 | F94: =SUM(F119:F121) -> 1670.1 | G94: =I94/I84*G84 -> 3842.6724 | I94: 2839.74
A95: Efectivo y equivalentes | B95: 3071.774 | C95: 2615.8 | D95: 2962.8 | E95: 2813 | F95: 1665.7 | G95: =D95 -> 2962.8
A96: Inventarios | B96: 6630.422 | C96: 6020.2 | D96: 5943.1 | E96: 6182.4 | F96: 7365.3 | G96: =D96 -> 5943.1
A97: Activo circulante | B97: 11202.654 | C97: 10026.3 | D97: 10147.2 | E97: 10422.3 | F97: 10810.2 | G97: =D97 -> 10147.2
A98: Activo total | B98: 43616.194 | C98: 42970.2 | D98: 44188.5 | E98: 44754.6 | F98: 46541.8 | G98: =D98 -> 44188.5
A99: Pasivo circulante | B99: 9031.024 | C99: 7608.5 | D99: 8406.7 | E99: 8294 | F99: 9623.2 | G99: =D99 -> 8406.7
A100: Pasivo a largo plazo | B100: =B101-B99 -> 2754.765 | C100: 2852.9 | D100: 2838.5 | E100: 2853 | F100: 3034.5 | G100: =D100 -> 2838.5
A101: Pasivo total | B101: 11785.789 | C101: 10461.4 | D101: 11245.2 | E101: 11147 | F101: 12657.7 | G101: =D101 -> 11245.2
A102: Capital contable | B102: 31830.405 | C102: 32508.8 | D102: 32943.3 | E102: 33607.6 | F102: 33884.1 | G102: =D102 -> 32943.3
A103: Deuda bursátil y bancaria CP | B103: 0 | C103: 0 | D103: 0 | E103: 0 | F103: 0 | G103: =D103 -> 0
A104: Deuda bursátil y bancaria LP | B104: 0 | C104: 0 | D104: 0 | E104: 0 | F104: 0 | G104: =D104 -> 0
A105: Pasivo por arrendamiento CP | B105: 93.389 | C105: 92.3 | D105: 98.3 | E105: 99.7 | F105: 105.6 | G105: =D105 -> 98.3
A106: Pasivo por arrendamiento LP | B106: 2260.347 | C106: 2272.5 | D106: 2343.5 | E106: 2344.7 | F106: 2443.7 | G106: =D106 -> 2343.5
A107: Deuda total (financiera + arrendamientos) | B107: =IF(COUNT(B103:B106)=4,SUM(B103:B106),"n.d.") -> 2353.736 | C107: =IF(COUNT(C103:C106)=4,SUM(C103:C106),"n.d.") -> 2364.8 | D107: =IF(COUNT(D103:D106)=4,SUM(D103:D106),"n.d.") -> 2441.8 | E107: =IF(COUNT(E103:E106)=4,SUM(E103:E106),"n.d.") -> 2444.4 | F107: =IF(COUNT(F103:F106)=4,SUM(F103:F106),"n.d.") -> 2549.3 | G107: =IF(COUNT(G103:G106)=4,SUM(G103:G106),"n.d.") -> 2441.8
...

Sheet Razones
A3: Días del trimestre | B3: 91.25
A6: ORGANIZACIÓN SORIANA | B6: 2T25 | C6: 3T25 | D6: 4T25 | E6: 1T26 | F6: 2T26 | G6: Promedio 5T
A7: Circulante | B7: =Datos!B19/Datos!B21 -> 1.2694752 | C7: =Datos!C19/Datos!C21 -> 1.3031422 | D7: =Datos!D19/Datos!D21 -> 1.2373849 | E7: =Datos!E19/Datos!E21 -> 1.2869129 | F7: =Datos!F19/Datos!F21 -> 1.1740294 | G7: =AVERAGE(B7:F7) -> 1.2541889
A8: Prueba ácida | B8: =(Datos!B19-Datos!B18)/Datos!B21 -> 0.35821259 | C8: =(Datos!C19-Datos!C18)/Datos!C21 -> 0.3501702 | D8: =(Datos!D19-Datos!D18)/Datos!D21 -> 0.414238 | E8: =(Datos!E19-Datos!E18)/Datos!E21 -> 0.3228065 | F8: =(Datos!F19-Datos!F18)/Datos!F21 -> 0.32826179 | G8: =AVERAGE(B8:F8) -> 0.35473781
A9: Deuda / Activo total | B9: =Datos!B23/Datos!B20 -> 0.4746312 | C9: =Datos!C23/Datos!C20 -> 0.46312428 | D9: =Datos!D23/Datos!D20 -> 0.45697843 | E9: =Datos!E23/Datos!E20 -> 0.4331295 | F9: =Datos!F23/Datos!F20 -> 0.44740551 | G9: =AVERAGE(B9:F9) -> 0.45505378
A10: Capitalización a largo plazo | B10: =Datos!B22/Datos!B20 -> 0.21772125 | C10: =Datos!C22/Datos!C20 -> 0.22065117 | D10: =Datos!D22/Datos!D20 -> 0.2056294 | E10: =Datos!E22/Datos!E20 -> 0.20886969 | F10: =Datos!F22/Datos!F20 -> 0.17983883 | G10: =AVERAGE(B10:F10) -> 0.20654207
A11: Cobertura de intereses | B11: =Datos!B9/Datos!B10 -> 2.3027744 | C11: =Datos!C9/Datos!C10 -> 1.8676845 | D11: =Datos!D9/Datos!D10 -> 4.0357143 | E11: =Datos!E9/Datos!E10 -> 3.0986395 | F11: =Datos!F9/Datos!F10 -> 3.1872852 | G11: =AVERAGE(B11:F11) -> 2.8984196
A12: Rotación del inventario | B12: =Datos!B7/Datos!B18 -> 0.9314556 | C12: =Datos!C7/Datos!C18 -> 0.87921086 | D12: =Datos!D7/Datos!D18 -> 1.1087879 | E12: =Datos!E7/Datos!E18 -> 0.93353761 | F12: =Datos!F7/Datos!F18 -> 0.92764433 | G12: =AVERAGE(B12:F12) -> 0.95612726
A13: Rotación del inventario en días | B13: =$B$3*Datos!B18/Datos!B7 -> 97.964949 | C13: =$B$3*Datos!C18/Datos!C7 -> 103.78625 | D13: =$B$3*Datos!D18/Datos!D7 -> 82.297074 | E13: =$B$3*Datos!E18/Datos!E7 -> 97.746463 | F13: =$B$3*Datos!F18/Datos!F7 -> 98.367442 | G13: =AVERAGE(B13:F13) -> 96.032436
A14: Rotación del activo total | B14: =Datos!B6/Datos!B20 -> 0.28659551 | C14: =Datos!C6/Datos!C20 -> 0.27099973 | D14: =Datos!D6/Datos!D20 -> 0.30500263 | E14: =Datos!E6/Datos!E20 -> 0.26794575 | F14: =Datos!F6/Datos!F20 -> 0.27777671 | G14: =AVERAGE(B14:F14) -> 0.28166407
A15: Margen bruto | B15: =Datos!B8/Datos!B6 -> 0.2391181 | C15: =Datos!C8/Datos!C6 -> 0.25033386 | D15: =Datos!D8/Datos!D6 -> 0.24787779 | E15: =Datos!E8/Datos!E6 -> 0.2467115 | F15: =Datos!F8/Datos!F6 -> 0.2442664 | G15: =AVERAGE(B15:F15) -> 0.24566153
A16: Margen neto | B16: =Datos!B13/Datos!B6 -> 0.016219166 | C16: =Datos!C13/Datos!C6 -> 0.013682262 | D16: =Datos!D13/Datos!D6 -> 0.027483611 | E16: =Datos!E13/Datos!E6 -> 0.020621106 | F16: =Datos!F13/Datos!F6 -> 0.025023531 | G16: =AVERAGE(B16:F16) -> 0.020605935
A17: Rentabilidad sobre activos (ROA) | B17: =Datos!B13/Datos!B20 -> 0.0046483402 | C17: =Datos!C13/Datos!C20 -> 0.0037078894 | D17: =Datos!D13/Datos!D20 -> 0.0083825735 | E17: =Datos!E13/Datos!E20 -> 0.0055253377 | F17: =Datos!F13/Datos!F20 -> 0.0069509543 | G17: =AVERAGE(B17:F17) -> 0.005843019
A18: Rentabilidad sobre capital (ROE) | B18: =Datos!B13/Datos!B24 -> 0.008847766 | C18: =Datos!C13/Datos!C24 -> 0.0069064204 | D18: =Datos!D13/Datos!D24 -> 0.015436907 | E18: =Datos!E13/Datos!E24 -> 0.0097470899 | F18: =Datos!F13/Datos!F24 -> 0.012578762 | G18: =AVERAGE(B18:F18) -> 0.010703389
A19: ROI (rendimiento sobre la inversión) | B19: =Datos!B9*(1-WACC!$B$10)/(Datos!B24+Datos!B29) -> 0.011708578 | C19: =Datos!C9*(1-WACC!$B$10)/(Datos!C24+Datos!C29) -> 0.0089530132 | D19: =Datos!D9*(1-WACC!$B$10)/(Datos!D24+Datos!D29) -> 0.016060914 | E19: =Datos!E9*(1-WACC!$B$10)/(Datos!E24+Datos!E29) -> 0.01167019 | F19: =Datos!F9*(1-WACC!$B$10)/(Datos!F24+Datos!F29) -> 0.011764483 | G19: =AVERAGE(B19:F19) -> 0.012031436
A22: WALMART DE MÉXICO | B22: 2T25 | C22: 3T25 | D22: 4T25 | E22: 1T26 | F22: 2T26 | G22: Promedio 5T
A23: Circulante | B23: =Datos!B45/Datos!B47 -> 0.94074612 | C23: =Datos!C45/Datos!C47 -> 0.94965349 | D23: =Datos!D45/Datos!D47 -> 0.96696082 | E23: =Datos!E45/Datos!E47 -> 1.0628517 | F23: =Datos!F45/Datos!F47 -> 0.96416733 | G23: =AVERAGE(B23:F23) -> 0.9768759
A24: Prueba ácida | B24: =(Datos!B45-Datos!B44)/Datos!B47 -> 0.33823113 | C24: =(Datos!C45-Datos!C44)/Datos!C47 -> 0.34200954 | D24: =(Datos!D45-Datos!D44)/Datos!D47 -> 0.33384163 | E24: =(Datos!E45-Datos!E44)/Datos!E47 -> 0.37170287 | F24: =(Datos!F45-Datos!F44)/Datos!F47 -> 0.34944038 | G24: =AVERAGE(B24:F24) -> 0.34704511
A25: Deuda / Activo total | B25: =Datos!B49/Datos!B46 -> 0.54768727 | C25: =Datos!C49/Datos!C46 -> 0.55072672 | D25: =Datos!D49/Datos!D46 -> 0.52434323 | E25: =Datos!E49/Datos!E46 -> 0.49165014 | F25: =Datos!F49/Datos!F46 -> 0.52838145 | G25: =AVERAGE(B25:F25) -> 0.52855776
A26: Capitalización a largo plazo | B26: =Datos!B48/Datos!B46 -> 0.1793358 | C26: =Datos!C48/Datos!C46 -> 0.17601614 | D26: =Datos!D48/Datos!D46 -> 0.1816704 | E26: =Datos!E48/Datos!E46 -> 0.18237576 | F26: =Datos!F48/Datos!F46 -> 0.1826505 | G26: =AVERAGE(B26:F26) -> 0.18040972
A27: Cobertura de intereses | B27: =Datos!B35/Datos!B36 -> 6.5249972 | C27: =Datos!C35/Datos!C36 -> 5.9010331 | D27: =Datos!D35/Datos!D36 -> 8.3420987 | E27: =Datos!E35/Datos!E36 -> 6.379196 | F27: =Datos!F35/Datos!F36 -> 6.0793328 | G27: =AVERAGE(B27:F27) -> 6.6453315
A28: Rotación del inventario | B28: =Datos!B33/Datos!B44 -> 1.7504581 | C28: =Datos!C33/Datos!C44 -> 1.6049882 | D28: =Datos!D33/Datos!D44 -> 2.0000335 | E28: =Datos!E33/Datos!E44 -> 1.7459681 | F28: =Datos!F33/Datos!F44 -> 1.7746187 | G28: =AVERAGE(B28:F28) -> 1.7752133
A29: Rotación del inventario en días | B29: =$B$3*Datos!B44/Datos!B33 -> 52.129211 | C29: =$B$3*Datos!C44/Datos!C33 -> 56.853999 | D29: =$B$3*Datos!D44/Datos!D33 -> 45.624236 | E29: =$B$3*Datos!E44/Datos!E33 -> 52.26327 | F29: =$B$3*Datos!F44/Datos!F33 -> 51.419496 | G29: =AVERAGE(B29:F29) -> 51.658042
A30: Rotación del activo total | B30: =Datos!B32/Datos!B46 -> 0.5120074 | C30: =Datos!C32/Datos!C46 -> 0.48562929 | D30: =Datos!D32/Datos!D46 -> 0.57109741 | E30: =Datos!E32/Datos!E46 -> 0.49315304 | F30: =Datos!F32/Datos!F46 -> 0.49599661 | G30: =AVERAGE(B30:F30) -> 0.51157675
A31: Margen bruto | B31: =Datos!B34/Datos!B32 -> 0.2412377 | C31: =Datos!C34/Datos!C32 -> 0.24748986 | D31: =Datos!D34/Datos!D32 -> 0.24021237 | E31: =Datos!E34/Datos!E32 -> 0.24321919 | F31: =Datos!F34/Datos!F32 -> 0.23959166 | G31: =AVERAGE(B31:F31) -> 0.24235015
A32: Margen neto | B32: =Datos!B39/Datos!B32 -> 0.045590769 | C32: =Datos!C39/Datos!C32 -> 0.048638996 | D32: =Datos!D39/Datos!D32 -> 0.051616886 | E32: =Datos!E39/Datos!E32 -> 0.051014923 | F32: =Datos!F39/Datos!F32 -> 0.044441115 | G32: =AVERAGE(B32:F32) -> 0.048260538
A33: Rentabilidad sobre activos (ROA) | B33: =Datos!B39/Datos!B46 -> 0.023342811 | C33: =Datos!C39/Datos!C46 -> 0.023620521 | D33: =Datos!D39/Datos!D46 -> 0.02947827 | E33: =Datos!E39/Datos!E46 -> 0.025158164 | F33: =Datos!F39/Datos!F46 -> 0.022042642 | G33: =AVERAGE(B33:F33) -> 0.024728482
A34: Rentabilidad sobre capital (ROE) | B34: =Datos!B39/Datos!B50 -> 0.051607681 | C34: =Datos!C39/Datos!C50 -> 0.052574952 | D34: =Datos!D39/Datos!D50 -> 0.061973825 | E34: =Datos!E39/Datos!E50 -> 0.049489862 | F34: =Datos!F39/Datos!F50 -> 0.046738286 | G34: =AVERAGE(B34:F34) -> 0.052476921
A35: ROI (rendimiento sobre la inversión) | B35: =Datos!B35*(1-WACC!$B$10)/(Datos!B50+Datos!B55) -> 0.040789751 | C35: =Datos!C35*(1-WACC!$B$10)/(Datos!C50+Datos!C55) -> 0.044024636 | D35: =Datos!D35*(1-WACC!$B$10)/(Datos!D50+Datos!D55) -> 0.051581686 | E35: =Datos!E35*(1-WACC!$B$10)/(Datos!E50+Datos!E55) -> 0.038731558 | F35: =Datos!F35*(1-WACC!$B$10)/(Datos!F50+Datos!F55) -> 0.037032482 | G35: =AVERAGE(B35:F35) -> 0.042432022
A38: GRUPO COMERCIAL CHEDRAUI | B38: 2T25 | C38: 3T25 | D38: 4T25 | E38: 1T26 | F38: 2T26 | G38: Promedio 5T
A39: Circulante | B39: =Datos!B71/Datos!B73 -> 0.93752294 | C39: =Datos!C71/Datos!C73 -> 0.95713938 | D39: =Datos!D71/Datos!D73 -> 0.92079666 | E39: =Datos!E71/Datos!E73 -> 0.9544518 | F39: =Datos!F71/Datos!F73 -> 0.89874924 | G39: =AVERAGE(B39:F39) -> 0.933732
A40: Prueba ácida | B40: =(Datos!B71-Datos!B70)/Datos!B73 -> 0.39513349 | C40: =(Datos!C71-Datos!C70)/Datos!C73 -> 0.41636525 | D40: =(Datos!D71-Datos!D70)/Datos!D73 -> 0.4373552 | E40: =(Datos!E71-Datos!E70)/Datos!E73 -> 0.40756856 | F40: =(Datos!F71-Datos!F70)/Datos!F73 -> 0.37735957 | G40: =AVERAGE(B40:F40) -> 0.40675641
A41: Deuda / Activo total | B41: =Datos!B75/Datos!B72 -> 0.66825911 | C41: =Datos!C75/Datos!C72 -> 0.66779606 | D41: =Datos!D75/Datos!D72 -> 0.67356636 | E41: =Datos!E75/Datos!E72 -> 0.65443675 | F41: =Datos!F75/Datos!F72 -> 0.65145515 | G41: =AVERAGE(B41:F41) -> 0.66310269
A42: Capitalización a largo plazo | B42: =Datos!B74/Datos!B72 -> 0.39551004 | C42: =Datos!C74/Datos!C72 -> 0.38822334 | D42: =Datos!D74/Datos!D72 -> 0.37134872 | E42: =Datos!E74/Datos!E72 -> 0.37751111 | F42: =Datos!F74/Datos!F72 -> 0.36805622 | G42: =AVERAGE(B42:F42) -> 0.38012988
A43: Cobertura de intereses | B43: =Datos!B61/Datos!B62 -> 4.8239802 | C43: =Datos!C61/Datos!C62 -> 3.9665961 | D43: =Datos!D61/Datos!D62 -> 3.3924674 | E43: =Datos!E61/Datos!E62 -> 4.0683276 | F43: =Datos!F61/Datos!F62 -> 4.5007216 | G43: =AVERAGE(B43:F43) -> 4.1504186
A44: Rotación del inventario | B44: =Datos!B59/Datos!B70 -> 2.4460256 | C44: =Datos!C59/Datos!C70 -> 2.3003665 | D44: =Datos!D59/Datos!D70 -> 2.5751122 | E44: =Datos!E59/Datos!E70 -> 2.2333551 | F44: =Datos!F59/Datos!F70 -> 2.3618924 | G44: =AVERAGE(B44:F44) -> 2.3833504
A45: Rotación del inventario en días | B45: =$B$3*Datos!B70/Datos!B59 -> 37.305414 | C45: =$B$3*Datos!C70/Datos!C59 -> 39.667592 | D45: =$B$3*Datos!D70/Datos!D59 -> 35.435349 | E45: =$B$3*Datos!E70/Datos!E59 -> 40.857811 | F45: =$B$3*Datos!F70/Datos!F59 -> 38.634275 | G45: =AVERAGE(B45:F45) -> 38.380088
A46: Rotación del activo total | B46: =Datos!B58/Datos!B72 -> 0.47699053 | C46: =Datos!C58/Datos!C72 -> 0.46117305 | D46: =Datos!D58/Datos!D72 -> 0.46906086 | E46: =Datos!E58/Datos!E72 -> 0.44674119 | F46: =Datos!F58/Datos!F72 -> 0.46430118 | G46: =AVERAGE(B46:F46) -> 0.46365336
A47: Margen bruto | B47: =Datos!B60/Datos!B58 -> 0.24137742 | C47: =Datos!C60/Datos!C58 -> 0.24587416 | D47: =Datos!D60/Datos!D58 -> 0.19789599 | E47: =Datos!E60/Datos!E58 -> 0.24288897 | F47: =Datos!F60/Datos!F58 -> 0.24834085 | G47: =AVERAGE(B47:F47) -> 0.23527548
A48: Margen neto | B48: =Datos!B65/Datos!B58 -> 0.027913029 | C48: =Datos!C65/Datos!C58 -> 0.022940047 | D48: =Datos!D65/Datos!D58 -> 0.017869485 | E48: =Datos!E65/Datos!E58 -> 0.02268417 | F48: =Datos!F65/Datos!F58 -> 0.025687198 | G48: =AVERAGE(B48:F48) -> 0.023418786
A49: Rentabilidad sobre activos (ROA) | B49: =Datos!B65/Datos!B72 -> 0.01331425 | C49: =Datos!C65/Datos!C72 -> 0.010579332 | D49: =Datos!D65/Datos!D72 -> 0.0083818761 | E49: =Datos!E65/Datos!E72 -> 0.010133953 | F49: =Datos!F65/Datos!F72 -> 0.011926596 | G49: =AVERAGE(B49:F49) -> 0.010867202
A50: Rentabilidad sobre capital (ROE) | B50: =Datos!B65/Datos!B76 -> 0.040134488 | C50: =Datos!C65/Datos!C76 -> 0.031845894 | D50: =Datos!D65/Datos!D76 -> 0.025677121 | E50: =Datos!E65/Datos!E76 -> 0.0293259 | F50: =Datos!F65/Datos!F76 -> 0.034218254 | G50: =AVERAGE(B50:F50) -> 0.032240332
A51: ROI (rendimiento sobre la inversión) | B51: =Datos!B61*(1-WACC!$B$10)/(Datos!B76+Datos!B81) -> 0.026754246 | C51: =Datos!C61*(1-WACC!$B$10)/(Datos!C76+Datos!C81) -> 0.023778808 | D51: =Datos!D61*(1-WACC!$B$10)/(Datos!D76+Datos!D81) -> 0.021729823 | E51: =Datos!E61*(1-WACC!$B$10)/(Datos!E76+Datos!E81) -> 0.023140006 | F51: =Datos!F61*(1-WACC!$B$10)/(Datos!F76+Datos!F81) -> 0.026048584 | G51: =AVERAGE(B51:F51) -> 0.024290294
A54: LA COMER | B54: 2T25 | C54: 3T25 | D54: 4T25 | E54: 1T26 | F54: 2T26 | G54: Promedio 5T
A55: Circulante | B55: =Datos!B97/Datos!B99 -> 1.2404633 | C55: =Datos!C97/Datos!C99 -> 1.3177762 | D55: =Datos!D97/Datos!D99 -> 1.2070372 | E55: =Datos!E97/Datos!E99 -> 1.2566072 | F55: =Datos!F97/Datos!F99 -> 1.1233477 | G55: =AVERAGE(B55:F55) -> 1.2290463
A56: Prueba ácida | B56: =(Datos!B97-Datos!B96)/Datos!B99 -> 0.50628057 | C56: =(Datos!C97-Datos!C96)/Datos!C99 -> 0.52652954 | D56: =(Datos!D97-Datos!D96)/Datos!D99 -> 0.50008921 | E56: =(Datos!E97-Datos!E96)/Datos!E99 -> 0.51120087 | F56: =(Datos!F97-Datos!F96)/Datos!F99 -> 0.35797863 | G56: =AVERAGE(B56:F56) -> 0.48041577
A57: Deuda / Activo total | B57: =Datos!B101/Datos!B98 -> 0.2702159 | C57: =Datos!C101/Datos!C98 -> 0.24345709 | D57: =Datos!D101/Datos!D98 -> 0.2544825 | E57: =Datos!E101/Datos!E98 -> 0.24906937 | F57: =Datos!F101/Datos!F98 -> 0.27196413 | G57: =AVERAGE(B57:F57) -> 0.2578378
A58: Capitalización a largo plazo | B58: =Datos!B100/Datos!B98 -> 0.063159225 | C58: =Datos!C100/Datos!C98 -> 0.066392523 | D58: =Datos!D100/Datos!D98 -> 0.06423617 | E58: =Datos!E100/Datos!E98 -> 0.063747637 | F58: =Datos!F100/Datos!F98 -> 0.065199455 | G58: =AVERAGE(B58:F58) -> 0.064547002
A59: Cobertura de intereses | B59: =Datos!B87/Datos!B88 -> 11.378049 | C59: =Datos!C87/Datos!C88 -> 10.938722 | D59: =Datos!D87/Datos!D88 -> 10.979507 | E59: =Datos!E87/Datos!E88 -> 13.661664 | F59: =Datos!F87/Datos!F88 -> 12.265789 | G59: =AVERAGE(B59:F59) -> 11.844746
A60: Rotación del inventario | B60: =Datos!B85/Datos!B96 -> 1.3148635 | C60: =Datos!C85/Datos!C96 -> 1.3798047 | D60: =Datos!D85/Datos!D96 -> 1.4629217 | E60: =Datos!E85/Datos!E96 -> 1.3470659 | F60: =Datos!F85/Datos!F96 -> 1.2396915 | G60: =AVERAGE(B60:F60) -> 1.3488695
A61: Rotación del inventario en días | B61: =$B$3*Datos!B96/Datos!B85 -> 69.398838 | C61: =$B$3*Datos!C96/Datos!C85 -> 66.13255 | D61: =$B$3*Datos!D96/Datos!D85 -> 62.375177 | E61: =$B$3*Datos!E96/Datos!E85 -> 67.739821 | F61: =$B$3*Datos!F96/Datos!F85 -> 73.607021 | G61: =AVERAGE(B61:F61) -> 67.850681
A62: Rotación del activo total | B62: =Datos!B84/Datos!B98 -> 0.28046005 | C62: =Datos!C84/Datos!C98 -> 0.2749161 | D62: =Datos!D84/Datos!D98 -> 0.28071534 | E62: =Datos!E84/Datos!E98 -> 0.2682741 | F62: =Datos!F84/Datos!F98 -> 0.27788139 | G62: =AVERAGE(B62:F62) -> 0.2764494
A63: Margen bruto | B63: =Datos!B86/Datos!B84 -> 0.28730605 | C63: =Datos!C86/Datos!C84 -> 0.29682897 | D63: =Datos!D86/Datos!D84 -> 0.29909572 | E63: =Datos!E86/Datos!E84 -> 0.30636738 | F63: =Datos!F86/Datos!F84 -> 0.2940053 | G63: =AVERAGE(B63:F63) -> 0.29672069
A64: Margen neto | B64: =Datos!B91/Datos!B84 -> 0.065644262 | C64: =Datos!C91/Datos!C84 -> 0.05425287 | D64: =Datos!D91/Datos!D84 -> 0.040808939 | E64: =Datos!E91/Datos!E84 -> 0.061816516 | F64: =Datos!F91/Datos!F84 -> 0.051890111 | G64: =AVERAGE(B64:F64) -> 0.05488254
A65: Rentabilidad sobre activos (ROA) | B65: =Datos!B91/Datos!B98 -> 0.018410593 | C65: =Datos!C91/Datos!C98 -> 0.014914988 | D65: =Datos!D91/Datos!D98 -> 0.011455695 | E65: =Datos!E91/Datos!E98 -> 0.01658377 | F65: =Datos!F91/Datos!F98 -> 0.014419296 | G65: =AVERAGE(B65:F65) -> 0.015156869
A66: Rentabilidad sobre capital (ROE) | B66: =Datos!B91/Datos!B102 -> 0.025227452 | C66: =Datos!C91/Datos!C102 -> 0.019714662 | D66: =Datos!D91/Datos!D102 -> 0.015366099 | E66: =Datos!E91/Datos!E102 -> 0.02208429 | F66: =Datos!F91/Datos!F102 -> 0.01980575 | G66: =AVERAGE(B66:F66) -> 0.02043965
A67: ROI (rendimiento sobre la inversión) | B67: =Datos!B87*(1-WACC!$B$10)/(Datos!B102+Datos!B107) -> 0.021015886 | C67: =Datos!C87*(1-WACC!$B$10)/(Datos!C102+Datos!C107) -> 0.016840819 | D67: =Datos!D87*(1-WACC!$B$10)/(Datos!D102+Datos!D107) -> 0.0140963 | E67: =Datos!E87*(1-WACC!$B$10)/(Datos!E102+Datos!E107) -> 0.019443581 | F67: =Datos!F87*(1-WACC!$B$10)/(Datos!F102+Datos!F107) -> 0.017910489 | G67: =AVERAGE(B67:F67) -> 0.017861415

Sheet WACC
A3: Concepto | B3: Soriana | C3: Walmex | D3: Chedraui | E3: La Comer
A4: PARÁMETROS DE MERCADO
A5: Tasa libre de riesgo (Bono M 10 años) | B5: 0.09517 | C5: =$B$5 -> 0.09517 | D5: =$B$5 -> 0.09517 | E5: =$B$5 -> 0.09517
A6: Prima de riesgo de mercado madura | B6: 0.0423 | C6: =$B$6 -> 0.0423 | D6: =$B$6 -> 0.0423 | E6: =$B$6 -> 0.0423
A7: Prima de riesgo país México (referencia) | B7: 0.0246 | C7: =$B$7 -> 0.0246 | D7: =$B$7 -> 0.0246 | E7: =$B$7 -> 0.0246
A8: Prima de riesgo de mercado aplicada (PRM) | B8: =B6 -> 0.0423 | C8: =C6 -> 0.0423 | D8: =D6 -> 0.0423 | E8: =E6 -> 0.0423
A9: Beta desapalancada del sector (Damodaran global ene-2026, Retail Grocery and Food; ver hoja 'Beta y Kd') — no es la beta histórica de Soriana | B9: ='Beta y Kd'!B28 -> 0.65 | C9: =$B$9 -> 0.65 | D9: =$B$9 -> 0.65 | E9: =$B$9 -> 0.65 | F9: Beta histórica del estudio (regresión): ver hoja Inflación, sección 6.
A10: Tasa de impuestos (ISR) | B10: 0.3 | C10: =$B$10 -> 0.3 | D10: =$B$10 -> 0.3 | E10: =$B$10 -> 0.3
A12: DATOS DE MERCADO
A13: Precio actual por acción (MXN) | B13: 33.48 | C13: 46.6 | D13: 92.94 | E13: 32.08
A14: Fecha del precio | B14: 46290 | C14: 46266 | D14: 21-ago-2026 | E14: 46266
A15: Capitalización de mercado reportada | B15: 54180 | C15: 801750 | D15: 89150 | E15: 34190
A16: Precio de cierre asociado a esa capitalización (MXN) | B16: 30.1 | C16: 45.92 | D16: 92.84 | E16: 32.08
A17: Acciones en circulación (millones) | B17: =B15/B16 -> 1800 | C17: =C15/C16 -> 17459.713 | D17: =D15/D16 -> 960.2542 | E17: =E15/E16 -> 1065.7731
A18: Valor de mercado del capital (E) | B18: =B17*B13 -> 60264 | C18: =C17*C13 -> 813622.6 | D18: =D17*D13 -> 89246.025 | E18: =E17*E13 -> 34190
A20: ESTRUCTURA DE CAPITAL (cierre 2025)
A21: Deuda total (D) = bancaria/bursátil + arrendamientos | B21: =Datos!G29 -> 23618 | C21: =Datos!G55 -> 80848.1 | D21: =Datos!G81 -> 56744.34 | E21: =Datos!G107 -> 2441.8
A22: Efectivo y equivalentes | B22: =Datos!G17 -> 9295 | C22: =Datos!G43 -> 28591.2 | D22: =Datos!G69 -> 14640.16 | E22: =Datos!G95 -> 2962.8
A23: D / E | B23: =B21/B18 -> 0.39190893 | C23: =C21/C18 -> 0.09936806 | D23: =D21/D18 -> 0.63581924 | E23: =E21/E18 -> 0.071418543
A24: Peso de la deuda D/(D+E) | B24: =B21/(B21+B18) -> 0.28156219 | C24: =C21/(C21+C18) -> 0.090386526 | D24: =D21/(D21+D18) -> 0.38868551 | E24: =E21/(E21+E18) -> 0.066657931
A25: Peso del capital E/(D+E) | B25: =B18/(B21+B18) -> 0.71843781 | C25: =C18/(C21+C18) -> 0.90961347 | D25: =D18/(D21+D18) -> 0.61131449 | E25: =E18/(E21+E18) -> 0.93334207
A27: COSTO DE CAPITAL
A28: Beta apalancada βL = βU × [1 + (1−t)·D/E] | B28: =B9*(1+(1-B10)*B23) -> 0.82831856 | C28: =C9*(1+(1-C10)*C23) -> 0.69521247 | D28: =D9*(1+(1-D10)*D23) -> 0.93929775 | E28: =E9*(1+(1-E10)*E23) -> 0.68249544
A29: Costo del capital propio Ke = Rf + βL × PRM | B29: =B5+B28*B8 -> 0.13020788 | C29: =C5+C28*C8 -> 0.12457749 | D29: =D5+D28*D8 -> 0.13490229 | E29: =E5+E28*E8 -> 0.12403956
A30: Gastos financieros FY2025 | B30: =Datos!G10 -> 3074 | C30: =Datos!G36 -> 11464.7 | D30: =Datos!G62 -> 3846.89 | E30: =Datos!G88 -> 265.96
A31: Costo de la deuda antes de impuestos Kd | B31: =B30/B21 -> 0.13015497 | C31: =C30/C21 -> 0.14180544 | D31: =D30/D21 -> 0.067793369 | E31: =E30/E21 -> 0.10891965
A32: Costo de la deuda después de impuestos Kd(1−t) | B32: =B31*(1-B10) -> 0.091108477 | C32: =C31*(1-C10) -> 0.099263805 | D32: =D31*(1-D10) -> 0.047455359 | E32: =E31*(1-E10) -> 0.076243755
A33: WACC = E/(D+E)·Ke + D/(D+E)·Kd(1−t) | B33: =B25*B29+B24*B32 -> 0.11919896 | C33: =C25*C29+C24*C32 -> 0.12228947 | D33: =D25*D29+D24*D32 -> 0.10091294 | E33: =E25*E29+E24*E32 -> 0.12085359

Sheet Valuación
A4: Crecimiento perpetuo (g) para valor terminal | B4: 0.035
A5: Crecimiento anual de ventas 2026E–2030E (supuesto base) | B5: 0.035
A8: ORGANIZACIÓN SORIANA | B8: 2025A | C8: 2026E | D8: 2027E | E8: 2028E | F8: 2029E | G8: 2030E
A9: Crecimiento anual de ventas (explícito) | B9: =$B$5 -> 0.035
A10: Margen EBIT | B10: =Datos!G9/Datos!G6 -> 0.042542884
A11: Depreciación y amortización (% ventas) | B11: =Datos!G14/Datos!G6 -> 0.024459905
A12: Capex (% ventas) | B12: =Datos!G16/Datos!G6 -> 0.016150748
A13: Inversión en capital de trabajo (% del incremento en ventas) | B13: =-SUM('Proyección Soriana'!C64:G64)/('Proyección Soriana'!G19-'Proyección Soriana'!B19) -> 0.020792609
A14: Tasa de impuestos | B14: =WACC!B10 -> 0.3
A15: WACC | B15: =WACC!B33 -> 0.11919896
A16: Crecimiento perpetuo (g) | B16: =$B$4 -> 0.035
A18: PROYECCIÓN DEL FLUJO LIBRE DE EFECTIVO (FCF) | B18: 2025A | C18: 2026E | D18: 2027E | E18: 2028E | F18: 2029E | G18: 2030E
A19: Periodo (n) | B19: 0 | C19: 1 | D19: 2 | E19: 3 | F19: 4 | G19: 5
A20: Ventas | B20: =Datos!G6 -> 177515 | C20: =B20*(1+$B$9) -> 183728.02 | D20: =C20*(1+$B$9) -> 190158.51 | E20: =D20*(1+$B$9) -> 196814.05 | F20: =E20*(1+$B$9) -> 203702.55 | G20: =F20*(1+$B$9) -> 210832.13
A21: Utilidad de operación (EBIT) | B21: =Datos!G9 -> 7552 | C21: =C20*$B$10 -> 7816.32 | D21: =D20*$B$10 -> 8089.8912 | E21: =E20*$B$10 -> 8373.0374 | F21: =F20*$B$10 -> 8666.0937 | G21: =G20*$B$10 -> 8969.407
A22: (−) Impuestos sobre EBIT | B22: =-B21*$B$14 -> -2265.6 | C22: =-C21*$B$14 -> -2344.896 | D22: =-D21*$B$14 -> -2426.9674 | E22: =-E21*$B$14 -> -2511.9112 | F22: =-F21*$B$14 -> -2599.8281 | G22: =-G21*$B$14 -> -2690.8221
A23: NOPAT (EBIT después de impuestos) | B23: =B21+B22 -> 5286.4 | C23: =C21+C22 -> 5471.424 | D23: =D21+D22 -> 5662.9238 | E23: =E21+E22 -> 5861.1262 | F23: =F21+F22 -> 6066.2656 | G23: =G21+G22 -> 6278.5849
A24: (+) Depreciación y amortización | B24: =Datos!G14 -> 4342 | C24: =C20*$B$11 -> 4493.97 | D24: =D20*$B$11 -> 4651.259 | E24: =E20*$B$11 -> 4814.053 | F24: =F20*$B$11 -> 4982.5449 | G24: =G20*$B$11 -> 5156.9339
A25: (−) Capex | B25: =-Datos!G16 -> -2867 | C25: =-C20*$B$12 -> -2967.345 | D25: =-D20*$B$12 -> -3071.2021 | E25: =-E20*$B$12 -> -3178.6941 | F25: =-F20*$B$12 -> -3289.9484 | G25: =-G20*$B$12 -> -3405.0966
A26: (−) Inversión en capital de trabajo | B26: 0 | C26: =-(C20-B20)*$B$13 -> -129.185 | D26: =-(D20-C20)*$B$13 -> -133.70648 | E26: =-(E20-D20)*$B$13 -> -138.3862 | F26: =-(F20-E20)*$B$13 -> -143.22972 | G26: =-(G20-F20)*$B$13 -> -148.24276
A27: FCF – Flujo libre de efectivo | B27: =B23+B24+B25+B26 -> 6761.4 | C27: =C23+C24+C25+C26 -> 6868.864 | D27: =D23+D24+D25+D26 -> 7109.2742 | E27: =E23+E24+E25+E26 -> 7358.0988 | F27: =F23+F24+F25+F26 -> 7615.6323 | G27: =G23+G24+G25+G26 -> 7882.1794
A28: Factor de descuento 1/(1+WACC)^n | C28: =1/(1+$B$15)^C19 -> 0.89349618 | D28: =1/(1+$B$15)^D19 -> 0.79833543 | E28: =1/(1+$B$15)^E19 -> 0.71330966 | F28: =1/(1+$B$15)^F19 -> 0.63733945 | G28: =1/(1+$B$15)^G19 -> 0.56946037
A29: Valor presente del FCF | C29: =C27*C28 -> 6137.3038 | D29: =D27*D28 -> 5675.5855 | E29: =E27*E28 -> 5248.603 | F29: =F27*F28 -> 4853.7429 | G29: =G27*G28 -> 4488.5888
A31: VPN de los FCF 2026E–2030E | B31: =SUM(C29:G29) -> 26403.824
A32: FCF del año 6 (2031E) | B32: =G27*(1+B16) -> 8158.0557
A33: Valor terminal (TV) al cierre de 2030 | B33: =B32/(B15-B16) -> 96890.216
A34: Valor presente del TV | B34: =B33*G28 -> 55175.138
A35: ENTERPRISE VALUE (EV) | B35: =B31+B34 -> 81578.962
A36: (−) Deuda total (bancaria/bursátil + arrendamientos) | B36: =-WACC!B21 -> -23618
A37: (+) Efectivo y equivalentes | B37: =WACC!B22 -> 9295
A38: Deuda neta | B38: =-(B36+B37) -> 14323
A39: EQUITY VALUE (valor para los accionistas) | B39: =B35+B36+B37 -> 67255.962
A40: Acciones en circulación (millones) | B40: =WACC!B17 -> 1800
A41: Valor intrínseco por acción (MXN) | B41: =B39/B40 -> 37.364423 | D41: Precio modelo integrado | E41: ='Proyección Soriana'!B85 -> 37.359643
A42: Precio actual en bolsa (MXN) | B42: =WACC!B13 -> 33.48 | D42: Diferencia vs integrado | E42: =B41-E41 -> 0.0047803439
A43: Potencial de apreciación / (baja) | B43: =B41/B42-1 -> 0.11602221 | D43: Diferencia (%) | E43: =B41/E41-1 -> 0.00012795475
A44: Peso del valor terminal en el EV | B44: =B34/B35 -> 0.67634028
A46: WALMART DE MÉXICO | B46: 2025A | C46: 2026E | D46: 2027E | E46: 2028E | F46: 2029E | G46: 2030E
A47: Crecimiento anual de ventas (explícito) | B47: =$B$5 -> 0.035
A48: Margen EBIT | B48: =Datos!G35/Datos!G32 -> 0.077593874
A49: Depreciación y amortización (% ventas) | B49: =Datos!G40/Datos!G32 -> 0.024667014
A50: Capex (% ventas) | B50: =Datos!G42/Datos!G32 -> 0.038535074
A51: Inversión en capital de trabajo (% del incremento en ventas) | B51: 0
A52: Tasa de impuestos | B52: =WACC!C10 -> 0.3
A53: WACC | B53: =WACC!C33 -> 0.12228947
A54: Crecimiento perpetuo (g) | B54: =$B$4 -> 0.035
A56: PROYECCIÓN DEL FLUJO LIBRE DE EFECTIVO (FCF) | B56: 2025A | C56: 2026E | D56: 2027E | E56: 2028E | F56: 2029E | G56: 2030E
A57: Periodo (n) | B57: 0 | C57: 1 | D57: 2 | E57: 3 | F57: 4 | G57: 5
A58: Ventas | B58: =Datos!G32 -> 1011597.9 | C58: =B58*(1+$B$47) -> 1047003.8 | D58: =C58*(1+$B$47) -> 1083649 | E58: =D58*(1+$B$47) -> 1121576.7 | F58: =E58*(1+$B$47) -> 1160831.9 | G58: =F58*(1+$B$47) -> 1201461
A59: Utilidad de operación (EBIT) | B59: =Datos!G35 -> 78493.8 | C59: =C58*$B$48 -> 81241.083 | D59: =D58*$B$48 -> 84084.521 | E59: =E58*$B$48 -> 87027.479 | F59: =F58*$B$48 -> 90073.441 | G59: =G58*$B$48 -> 93226.011
A60: (−) Impuestos sobre EBIT | B60: =-B59*$B$52 -> -23548.14 | C60: =-C59*$B$52 -> -24372.325 | D60: =-D59*$B$52 -> -25225.356 | E60: =-E59*$B$52 -> -26108.244 | F60: =-F59*$B$52 -> -27022.032 | G60: =-G59*$B$52 -> -27967.803
A61: NOPAT (EBIT después de impuestos) | B61: =B59+B60 -> 54945.66 | C61: =C59+C60 -> 56868.758 | D61: =D59+D60 -> 58859.165 | E61: =E59+E60 -> 60919.235 | F61: =F59+F60 -> 63051.409 | G61: =G59+G60 -> 65258.208
A62: (+) Depreciación y amortización | B62: =Datos!G40 -> 24953.1 | C62: =C58*$B$49 -> 25826.459 | D62: =D58*$B$49 -> 26730.385 | E62: =E58*$B$49 -> 27665.948 | F62: =F58*$B$49 -> 28634.256 | G62: =G58*$B$49 -> 29636.455
A63: (−) Capex | B63: =-Datos!G42 -> -38982 | C63: =-C58*$B$50 -> -40346.37 | D63: =-D58*$B$50 -> -41758.493 | E63: =-E58*$B$50 -> -43220.04 | F63: =-F58*$B$50 -> -44732.742 | G63: =-G58*$B$50 -> -46298.388
A64: (−) Inversión en capital de trabajo | B64: 0 | C64: =-(C58-B58)*$B$51 -> 0 | D64: =-(D58-C58)*$B$51 -> 0 | E64: =-(E58-D58)*$B$51 -> 0 | F64: =-(F58-E58)*$B$51 -> 0 | G64: =-(G58-F58)*$B$51 -> 0
A65: FCF – Flujo libre de efectivo | B65: =B61+B62+B63+B64 -> 40916.76 | C65: =C61+C62+C63+C64 -> 42348.847 | D65: =D61+D62+D63+D64 -> 43831.056 | E65: =E61+E62+E63+E64 -> 45365.143 | F65: =F61+F62+F63+F64 -> 46952.923 | G65: =G61+G62+G63+G64 -> 48596.276
A66: Factor de descuento 1/(1+WACC)^n | C66: =1/(1+$B$53)^C57 -> 0.89103571 | D66: =1/(1+$B$53)^D57 -> 0.79394464 | E66: =1/(1+$B$53)^E57 -> 0.70743303 | F66: =1/(1+$B$53)^F57 -> 0.6303481 | G66: =1/(1+$B$53)^G57 -> 0.56166267
A67: Valor presente del FCF | C67: =C65*C66 -> 37734.335 | D67: =D65*D66 -> 34799.432 | E67: =E65*E66 -> 32092.801 | F67: =F65*F66 -> 29596.686 | G67: =G65*G66 -> 27294.714
A69: VPN de los FCF 2026E–2030E | B69: =SUM(C67:G67) -> 161517.97
A70: FCF del año 6 (2031E) | B70: =G65*(1+B54) -> 50297.145
A71: Valor terminal (TV) al cierre de 2030 | B71: =B70/(B53-B54) -> 576210.9
A72: Valor presente del TV | B72: =B71*G66 -> 323636.15
A73: ENTERPRISE VALUE (EV) | B73: =B69+B72 -> 485154.12
A74: (−) Deuda total (bancaria/bursátil + arrendamientos) | B74: =-WACC!C21 -> -80848.1
A75: (+) Efectivo y equivalentes | B75: =WACC!C22 -> 28591.2
A76: Deuda neta | B76: =-(B74+B75) -> 52256.9
A77: EQUITY VALUE (valor para los accionistas) | B77: =B73+B74+B75 -> 432897.22
A78: Acciones en circulación (millones) | B78: =WACC!C17 -> 17459.713
A79: Valor intrínseco por acción (MXN) | B79: =B77/B78 -> 24.794063
A80: Precio actual en bolsa (MXN) | B80: =WACC!C13 -> 46.6
A81: Potencial de apreciación / (baja) | B81: =B79/B80-1 -> -0.46793856
A82: Peso del valor terminal en el EV | B82: =B72/B73 -> 0.66707906
A84: GRUPO COMERCIAL CHEDRAUI | B84: 2025A | C84: 2026E | D84: 2027E | E84: 2028E | F84: 2029E | G84: 2030E
A85: Crecimiento anual de ventas (explícito) | B85: =$B$5 -> 0.035
A86: Margen EBIT | B86: =Datos!G61/Datos!G58 -> 0.051124965
A87: Depreciación y amortización (% ventas) | B87: =Datos!G66/Datos!G58 -> 0.031469084
A88: Capex (% ventas) | B88: =Datos!G68/Datos!G58 -> 0.026236105
A89: Inversión en capital de trabajo (% del incremento en ventas) | B89: 0
A90: Tasa de impuestos | B90: =WACC!D10 -> 0.3
A91: WACC | B91: =WACC!D33 -> 0.10091294
A92: Crecimiento perpetuo (g) | B92: =$B$4 -> 0.035
A94: PROYECCIÓN DEL FLUJO LIBRE DE EFECTIVO (FCF) | B94: 2025A | C94: 2026E | D94: 2027E | E94: 2028E | F94: 2029E | G94: 2030E
A95: Periodo (n) | B95: 0 | C95: 1 | D95: 2 | E95: 3 | F95: 4 | G95: 5
A96: Ventas | B96: =Datos!G58 -> 295313.65 | C96: =B96*(1+$B$85) -> 305649.63 | D96: =C96*(1+$B$85) -> 316347.36 | E96: =D96*(1+$B$85) -> 327419.52 | F96: =E96*(1+$B$85) -> 338879.21 | G96: =F96*(1+$B$85) -> 350739.98
A97: Utilidad de operación (EBIT) | B97: =Datos!G61 -> 15097.9 | C97: =C96*$B$86 -> 15626.326 | D97: =D96*$B$86 -> 16173.248 | E97: =E96*$B$86 -> 16739.312 | F97: =F96*$B$86 -> 17325.188 | G97: =G96*$B$86 -> 17931.569
A98: (−) Impuestos sobre EBIT | B98: =-B97*$B$90 -> -4529.37 | C98: =-C97*$B$90 -> -4687.8979 | D98: =-D97*$B$90 -> -4851.9744 | E98: =-E97*$B$90 -> -5021.7935 | F98: =-F97*$B$90 -> -5197.5563 | G98: =-G97*$B$90 -> -5379.4707
A99: NOPAT (EBIT después de impuestos) | B99: =B97+B98 -> 10568.53 | C99: =C97+C98 -> 10938.429 | D99: =D97+D98 -> 11321.274 | E99: =E97+E98 -> 11717.518 | F99: =F97+F98 -> 12127.631 | G99: =G97+G98 -> 12552.098
A100: (+) Depreciación y amortización | B100: =Datos!G66 -> 9293.25 | C100: =C96*$B$87 -> 9618.5138 | D100: =D96*$B$87 -> 9955.1617 | E100: =E96*$B$87 -> 10303.592 | F100: =F96*$B$87 -> 10664.218 | G100: =G96*$B$87 -> 11037.466
A101: (−) Capex | B101: =-Datos!G68 -> -7747.88 | C101: =-C96*$B$88 -> -8019.0558 | D101: =-D96*$B$88 -> -8299.7228 | E101: =-E96*$B$88 -> -8590.213 | F101: =-F96*$B$88 -> -8890.8705 | G101: =-G96*$B$88 -> -9202.051
A102: (−) Inversión en capital de trabajo | B102: 0 | C102: =-(C96-B96)*$B$89 -> 0 | D102: =-(D96-C96)*$B$89 -> 0 | E102: =-(E96-D96)*$B$89 -> 0 | F102: =-(F96-E96)*$B$89 -> 0 | G102: =-(G96-F96)*$B$89 -> 0
A103: FCF – Flujo libre de efectivo | B103: =B99+B100+B101+B102 -> 12113.9 | C103: =C99+C100+C101+C102 -> 12537.887 | D103: =D99+D100+D101+D102 -> 12976.713 | E103: =E99+E100+E101+E102 -> 13430.897 | F103: =F99+F100+F101+F102 -> 13900.979 | G103: =G99+G100+G101+G102 -> 14387.513
A104: Factor de descuento 1/(1+WACC)^n | C104: =1/(1+$B$91)^C95 -> 0.90833704 | D104: =1/(1+$B$91)^D95 -> 0.82507618 | E104: =1/(1+$B$91)^E95 -> 0.74944726 | F104: =1/(1+$B$91)^F95 -> 0.6807507 | G104: =1/(1+$B$91)^G95 -> 0.61835108
A105: Valor presente del FCF | C105: =C103*C104 -> 11388.627 | D105: =D103*D104 -> 10706.776 | E105: =E103*E104 -> 10065.749 | F105: =F103*F104 -> 9463.1011 | G105: =G103*G104 -> 8896.5343
A107: VPN de los FCF 2026E–2030E | B107: =SUM(C105:G105) -> 50520.788
A108: FCF del año 6 (2031E) | B108: =G103*(1+B92) -> 14891.076
A109: Valor terminal (TV) al cierre de 2030 | B109: =B108/(B91-B92) -> 225920.38
A110: Valor presente del TV | B110: =B109*G104 -> 139698.11
A111: ENTERPRISE VALUE (EV) | B111: =B107+B110 -> 190218.9
A112: (−) Deuda total (bancaria/bursátil + arrendamientos) | B112: =-WACC!D21 -> -56744.34
A113: (+) Efectivo y equivalentes | B113: =WACC!D22 -> 14640.16
...

Sheet Proyección Soriana
A3: SUPUESTOS | B3: 2025A | C3: 2026E | D3: 2027E | E3: 2028E | F3: 2029E | G3: 2030E
A4: Crecimiento de ventas | C4: =Valuación!$B$9 -> 0.035 | D4: =Valuación!$B$9 -> 0.035 | E4: =Valuación!$B$9 -> 0.035 | F4: =Valuación!$B$9 -> 0.035 | G4: =Valuación!$B$9 -> 0.035
A5: Costo de ventas (% ventas) | B5: =-B20/B19 -> 0.75910205 | C5: =$B5 -> 0.75910205 | D5: =$B5 -> 0.75910205 | E5: =$B5 -> 0.75910205 | F5: =$B5 -> 0.75910205 | G5: =$B5 -> 0.75910205
A6: Gastos de operación sin D&A (% ventas) | B6: =-B22/B19 -> 0.1739008 | C6: =$B6 -> 0.1739008 | D6: =$B6 -> 0.1739008 | E6: =$B6 -> 0.1739008 | F6: =$B6 -> 0.1739008 | G6: =$B6 -> 0.1739008
A7: Depreciación y amortización (% ventas) | B7: =-B24/B19 -> 0.024459905 | C7: =$B7 -> 0.024459905 | D7: =$B7 -> 0.024459905 | E7: =$B7 -> 0.024459905 | F7: =$B7 -> 0.024459905 | G7: =$B7 -> 0.024459905
A8: Capex (% ventas) | B8: =Datos!G16/Datos!G6 -> 0.016150748 | C8: =$B8 -> 0.016150748 | D8: =$B8 -> 0.016150748 | E8: =$B8 -> 0.016150748 | F8: =$B8 -> 0.016150748 | G8: =$B8 -> 0.016150748
A9: Tasa de interés implícita (% deuda + arrendamientos) | B9: =-B26/(B41+B42) -> 0.13015497 | C9: =$B9 -> 0.13015497 | D9: =$B9 -> 0.13015497 | E9: =$B9 -> 0.13015497 | F9: =$B9 -> 0.13015497 | G9: =$B9 -> 0.13015497
A10: Tasa de impuestos | B10: =Valuación!$B$14 -> 0.3 | C10: =$B10 -> 0.3 | D10: =$B10 -> 0.3 | E10: =$B10 -> 0.3 | F10: =$B10 -> 0.3 | G10: =$B10 -> 0.3
A11: Días de inventario (sobre costo de ventas) | B11: =-B35/B20*365 -> 87.444305 | C11: =$B11 -> 87.444305 | D11: =$B11 -> 87.444305 | E11: =$B11 -> 87.444305 | F11: =$B11 -> 87.444305 | G11: =$B11 -> 87.444305
A12: Otros activos circulantes (% ventas) | B12: =B36/B19 -> 0.039157254 | C12: =$B12 -> 0.039157254 | D12: =$B12 -> 0.039157254 | E12: =$B12 -> 0.039157254 | F12: =$B12 -> 0.039157254 | G12: =$B12 -> 0.039157254
A13: Pasivo circulante operativo (% ventas) | B13: =B40/B19 -> 0.20022533 | C13: =$B13 -> 0.20022533 | D13: =$B13 -> 0.20022533 | E13: =$B13 -> 0.20022533 | F13: =$B13 -> 0.20022533 | G13: =$B13 -> 0.20022533
A14: Dividendos (% utilidad neta) | B14: =Generales!B62*Valuación!B40/B30 -> 0.30014406 | C14: =$B14 -> 0.30014406 | D14: =$B14 -> 0.30014406 | E14: =$B14 -> 0.30014406 | F14: =$B14 -> 0.30014406 | G14: =$B14 -> 0.30014406
A15: WACC | C15: =Valuación!$B$15 -> 0.11919896 | D15: =Valuación!$B$15 -> 0.11919896 | E15: =Valuación!$B$15 -> 0.11919896 | F15: =Valuación!$B$15 -> 0.11919896 | G15: =Valuación!$B$15 -> 0.11919896
A16: Crecimiento perpetuo (g) | C16: =Valuación!$B$16 -> 0.035 | D16: =Valuación!$B$16 -> 0.035 | E16: =Valuación!$B$16 -> 0.035 | F16: =Valuación!$B$16 -> 0.035 | G16: =Valuación!$B$16 -> 0.035
A18: 1. ESTADO DE RESULTADOS | B18: 2025A | C18: 2026E | D18: 2027E | E18: 2028E | F18: 2029E | G18: 2030E
A19: Ventas | B19: =Datos!G6 -> 177515 | C19: =B19*(1+C4) -> 183728.02 | D19: =C19*(1+D4) -> 190158.51 | E19: =D19*(1+E4) -> 196814.05 | F19: =E19*(1+F4) -> 203702.55 | G19: =F19*(1+G4) -> 210832.13
A20: Costo de ventas | B20: =-Datos!G7 -> -134752 | C20: =-C19*C5 -> -139468.32 | D20: =-D19*D5 -> -144349.71 | E20: =-E19*E5 -> -149401.95 | F20: =-F19*F5 -> -154631.02 | G20: =-G19*G5 -> -160043.11
A21: Utilidad bruta | B21: =B19+B20 -> 42763 | C21: =C19+C20 -> 44259.705 | D21: =D19+D20 -> 45808.795 | E21: =E19+E20 -> 47412.102 | F21: =F19+F20 -> 49071.526 | G21: =G19+G20 -> 50789.029
A22: Gastos de operación (sin D&A) | B22: =-(Datos!G8-Datos!G9-Datos!G14) -> -30870 | C22: =-C19*C6 -> -31950.45 | D22: =-D19*D6 -> -33068.716 | E22: =-E19*E6 -> -34226.121 | F22: =-F19*F6 -> -35424.035 | G22: =-G19*G6 -> -36663.876
A23: EBITDA | B23: =B21+B22 -> 11893 | C23: =C21+C22 -> 12309.255 | D23: =D21+D22 -> 12740.079 | E23: =E21+E22 -> 13185.982 | F23: =F21+F22 -> 13647.491 | G23: =G21+G22 -> 14125.153
A24: Depreciación y amortización | B24: =-Datos!G14 -> -4342 | C24: =-C19*C7 -> -4493.97 | D24: =-D19*D7 -> -4651.259 | E24: =-E19*E7 -> -4814.053 | F24: =-F19*F7 -> -4982.5449 | G24: =-G19*G7 -> -5156.9339
A25: Utilidad de operación (EBIT) | B25: =B23+B24 -> 7551 | C25: =C23+C24 -> 7815.285 | D25: =D23+D24 -> 8088.82 | E25: =E23+E24 -> 8371.9287 | F25: =F23+F24 -> 8664.9462 | G25: =G23+G24 -> 8968.2193
A26: Gastos financieros | B26: =-Datos!G10 -> -3074 | C26: =-C9*(B41+B42) -> -3074 | D26: =-D9*(C41+C42) -> -3074 | E26: =-E9*(D41+D42) -> -3074 | F26: =-F9*(E41+E42) -> -3074 | G26: =-G9*(F41+F42) -> -3074
A27: Otros ingresos (gastos) netos | B27: =Datos!G11-Datos!G9+Datos!G10 -> 288 | C27: 0 | D27: 0 | E27: 0 | F27: 0 | G27: 0
A28: Utilidad antes de impuestos | B28: =B25+B26+B27 -> 4765 | C28: =C25+C26+C27 -> 4741.285 | D28: =D25+D26+D27 -> 5014.82 | E28: =E25+E26+E27 -> 5297.9287 | F28: =F25+F26+F27 -> 5590.9462 | G28: =G25+G26+G27 -> 5894.2193
A29: Impuestos a la utilidad | B29: =-Datos!G12 -> -1433 | C29: =-C28*C10 -> -1422.3855 | D29: =-D28*D10 -> -1504.446 | E29: =-E28*E10 -> -1589.3786 | F29: =-F28*F10 -> -1677.2839 | G29: =-G28*G10 -> -1768.2658
A30: Utilidad neta | B30: =B28+B29 -> 3332 | C30: =C28+C29 -> 3318.8995 | D30: =D28+D29 -> 3510.374 | E30: =E28+E29 -> 3708.5501 | F30: =F28+F29 -> 3913.6623 | G30: =G28+G29 -> 4125.9535
A31: Dividendos pagados | C31: =-C30*C14 -> -996.14796 | D31: =-D30*D14 -> -1053.6179 | E31: =-E30*E14 -> -1113.0993 | F31: =-F30*F14 -> -1174.6625 | G31: =-G30*G14 -> -1238.3804
A33: 2. BALANCE GENERAL | B33: 2025A | C33: 2026E | D33: 2027E | E33: 2028E | F33: 2029E | G33: 2030E
A34: Efectivo y equivalentes | B34: =Datos!G17 -> 9295 | C34: =B34+C56 -> 13015.192 | D34: =C34+D56 -> 16918.298 | E34: =D34+E56 -> 21010.721 | F34: =E34+F56 -> 25299.088 | G34: =F34+G56 -> 29790.256
A35: Inventarios | B35: =Datos!G18 -> 32283 | C35: =-C20*C11/365 -> 33412.905 | D35: =-D20*D11/365 -> 34582.357 | E35: =-E20*E11/365 -> 35792.739 | F35: =-F20*F11/365 -> 37045.485 | G35: =-G20*G11/365 -> 38342.077
A36: Otros activos circulantes | B36: =Datos!G19-Datos!G17-Datos!G18 -> 6951 | C36: =C19*C12 -> 7194.285 | D36: =D19*D12 -> 7446.085 | E36: =E19*E12 -> 7706.6979 | F36: =F19*F12 -> 7976.4324 | G36: =G19*G12 -> 8255.6075
A37: Activo circulante | B37: =SUM(B34:B36) -> 48529 | C37: =SUM(C34:C36) -> 53622.382 | D37: =SUM(D34:D36) -> 58946.74 | E37: =SUM(E34:E36) -> 64510.159 | F37: =SUM(F34:F36) -> 70321.005 | G37: =SUM(G34:G36) -> 76387.94
A38: Activo no circulante | B38: =Datos!G20-Datos!G19 -> 107509 | C38: =B38-C54+C24 -> 105982.38 | D38: =C38-D54+D24 -> 104402.32 | E38: =D38-E54+E24 -> 102766.96 | F38: =E38-F54+F24 -> 101074.36 | G38: =F38-G54+G24 -> 99322.526
A39: Activo total | B39: =B37+B38 -> 156038 | C39: =C37+C38 -> 159604.76 | D39: =D37+D38 -> 163349.06 | E39: =E37+E38 -> 167277.12 | F39: =F37+F38 -> 171395.37 | G39: =G37+G38 -> 175710.47
A40: Pasivo circulante operativo (proveedores y otros) | B40: =Datos!G21-Datos!G25-Datos!G27 -> 35543 | C40: =C19*C13 -> 36787.005 | D40: =D19*D13 -> 38074.55 | E40: =E19*E13 -> 39407.159 | F40: =F19*F13 -> 40786.41 | G40: =G19*G13 -> 42213.934
A41: Deuda bursátil y bancaria | B41: =Datos!G25+Datos!G26 -> 11500 | C41: =B41 -> 11500 | D41: =C41 -> 11500 | E41: =D41 -> 11500 | F41: =E41 -> 11500 | G41: =F41 -> 11500
A42: Pasivo por arrendamiento | B42: =Datos!G27+Datos!G28 -> 12118 | C42: =B42 -> 12118 | D42: =C42 -> 12118 | E42: =D42 -> 12118 | F42: =E42 -> 12118 | G42: =F42 -> 12118
A43: Otros pasivos a largo plazo | B43: =Datos!G23-Datos!G21-Datos!G26-Datos!G28 -> 12145 | C43: =B43 -> 12145 | D43: =C43 -> 12145 | E43: =D43 -> 12145 | F43: =E43 -> 12145 | G43: =F43 -> 12145
A44: Pasivo total | B44: =SUM(B40:B43) -> 71306 | C44: =SUM(C40:C43) -> 72550.005 | D44: =SUM(D40:D43) -> 73837.55 | E44: =SUM(E40:E43) -> 75170.159 | F44: =SUM(F40:F43) -> 76549.41 | G44: =SUM(G40:G43) -> 77976.934
A45: Capital contable | B45: =Datos!G24 -> 84732 | C45: =B45+C30+C31 -> 87054.752 | D45: =C45+D30+D31 -> 89511.508 | E45: =D45+E30+E31 -> 92106.958 | F45: =E45+F30+F31 -> 94845.958 | G45: =F45+G30+G31 -> 97733.531
A46: Pasivo + capital | B46: =B44+B45 -> 156038 | C46: =C44+C45 -> 159604.76 | D46: =D44+D45 -> 163349.06 | E46: =E44+E45 -> 167277.12 | F46: =F44+F45 -> 171395.37 | G46: =G44+G45 -> 175710.47
A47: Comprobación (activo − pasivo − capital) | B47: =B39-B46 -> 0 | C47: =C39-C46 -> 0 | D47: =D39-D46 -> 0 | E47: =E39-E46 -> 0 | F47: =F39-F46 -> 0 | G47: =G39-G46 -> 0
A49: CONCILIACIÓN DE EFECTIVO | B49: 2025A | C49: 2026E | D49: 2027E | E49: 2028E | F49: 2029E | G49: 2030E
A50: Utilidad neta | C50: =C30 -> 3318.8995 | D50: =D30 -> 3510.374 | E50: =E30 -> 3708.5501 | F50: =F30 -> 3913.6623 | G50: =G30 -> 4125.9535
A51: (+) Depreciación y amortización | C51: =-C24 -> 4493.97 | D51: =-D24 -> 4651.259 | E51: =-E24 -> 4814.053 | F51: =-F24 -> 4982.5449 | G51: =-G24 -> 5156.9339
A52: (−) Aumento en inventarios | C52: =-(C35-B35) -> -1129.905 | D52: =-(D35-C35) -> -1169.4517 | E52: =-(E35-D35) -> -1210.3825 | F52: =-(F35-E35) -> -1252.7459 | G52: =-(G35-F35) -> -1296.592
A53: (−) Aumento en otros activos circulantes | C53: =-(C36-B36) -> -243.285 | D53: =-(D36-C36) -> -251.79997 | E53: =-(E36-D36) -> -260.61297 | F53: =-(F36-E36) -> -269.73443 | G53: =-(G36-F36) -> -279.17513
A54: (−) Capex | C54: =-C19*C8 -> -2967.345 | D54: =-D19*D8 -> -3071.2021 | E54: =-E19*E8 -> -3178.6941 | F54: =-F19*F8 -> -3289.9484 | G54: =-G19*G8 -> -3405.0966
A55: (+) Aumento en pasivo circulante operativo | C55: =C40-B40 -> 1244.005 | D55: =D40-C40 -> 1287.5452 | E55: =E40-D40 -> 1332.6093 | F55: =F40-E40 -> 1379.2506 | G55: =G40-F40 -> 1427.5244
A56: Cambio neto en efectivo (después de dividendos) | C56: =SUM(C50:C55)+C31 -> 3720.1915 | D56: =SUM(D50:D55)+D31 -> 3903.1065 | E56: =SUM(E50:E55)+E31 -> 4092.4235 | F56: =SUM(F50:F55)+F31 -> 4288.3665 | G56: =SUM(G50:G55)+G31 -> 4491.1676
A58: 3. FLUJO LIBRE DE EFECTIVO (FFL) | B58: 2025A | C58: 2026E | D58: 2027E | E58: 2028E | F58: 2029E | G58: 2030E
A59: Utilidad de operación (EBIT) | C59: =C25 -> 7815.285 | D59: =D25 -> 8088.82 | E59: =E25 -> 8371.9287 | F59: =F25 -> 8664.9462 | G59: =G25 -> 8968.2193
A60: (−) Impuestos sobre EBIT | C60: =-C59*C10 -> -2344.5855 | D60: =-D59*D10 -> -2426.646 | E60: =-E59*E10 -> -2511.5786 | F60: =-F59*F10 -> -2599.4839 | G60: =-G59*G10 -> -2690.4658
A61: NOPAT | C61: =C59+C60 -> 5470.6995 | D61: =D59+D60 -> 5662.174 | E61: =E59+E60 -> 5860.3501 | F61: =F59+F60 -> 6065.4623 | G61: =G59+G60 -> 6277.7535
A62: (+) Depreciación y amortización | C62: =C51 -> 4493.97 | D62: =D51 -> 4651.259 | E62: =E51 -> 4814.053 | F62: =F51 -> 4982.5449 | G62: =G51 -> 5156.9339
A63: (−) Capex | C63: =C54 -> -2967.345 | D63: =D54 -> -3071.2021 | E63: =E54 -> -3178.6941 | F63: =F54 -> -3289.9484 | G63: =G54 -> -3405.0966
A64: (−) Inversión en capital de trabajo | C64: =C52+C53+C55 -> -129.185 | D64: =D52+D53+D55 -> -133.70648 | E64: =E52+E53+E55 -> -138.3862 | F64: =F52+F53+F55 -> -143.22972 | G64: =G52+G53+G55 -> -148.24276
A65: Flujo libre de efectivo (FFL) | C65: =SUM(C61:C64) -> 6868.1395 | D65: =SUM(D61:D64) -> 7108.5244 | E65: =SUM(E61:E64) -> 7357.3227 | F65: =SUM(F61:F64) -> 7614.829 | G65: =SUM(G61:G64) -> 7881.348
A66: Periodo (n) | C66: 1 | D66: =C66+1 -> 2 | E66: =D66+1 -> 3 | F66: =E66+1 -> 4 | G66: =F66+1 -> 5
A67: Factor de descuento 1/(1+WACC)^n | C67: =1/(1+C15)^C66 -> 0.89349618 | D67: =1/(1+D15)^D66 -> 0.79833543 | E67: =1/(1+E15)^E66 -> 0.71330966 | F67: =1/(1+F15)^F66 -> 0.63733945 | G67: =1/(1+G15)^G66 -> 0.56946037
A68: Valor presente del FFL | C68: =C65*C67 -> 6136.6564 | D68: =D65*D67 -> 5674.9868 | E68: =E65*E67 -> 5248.0493 | F68: =F65*F67 -> 4853.231 | G68: =G65*G67 -> 4488.1154
A70: 4. VALOR TERMINAL Y VALOR DE LA EMPRESA | B70: Valor
A71: Suma VP de FFL 2026E–2030E | B71: =SUM(C68:G68) -> 26401.039
A72: FFL 2031E = FFL 2030E × (1+g) | B72: =G65*(1+G16) -> 8157.1952
A73: Valor terminal al cierre 2030 (Gordon) | B73: =B72/(G15-G16) -> 96879.997
A74: Valor presente del valor terminal | B74: =B73*G67 -> 55169.319
A75: Valor de la empresa (VE) | B75: =B71+B74 -> 81570.358
A76: Peso del valor terminal en el VE | B76: =B74/B75 -> 0.67634028
A78: 5. VALOR DEL CAPITAL Y PRECIO POR ACCIÓN | B78: Valor
A79: Valor de la empresa (VE) | B79: =B75 -> 81570.358
A80: (−) Deuda bursátil y bancaria (2025) | B80: =-B41 -> -11500
A81: (−) Pasivo por arrendamiento (2025) | B81: =-B42 -> -12118
A82: (+) Efectivo y equivalentes (2025) | B82: =B34 -> 9295
A83: Valor del capital | B83: =SUM(B79:B82) -> 67247.358
A84: Acciones en circulación (millones) | B84: =Valuación!B40 -> 1800
A85: Precio por acción (MXN) | B85: =B83/B84 -> 37.359643
A86: Precio actual en bolsa (MXN) | B86: =Valuación!B42 -> 33.48
A87: Potencial de apreciación / (baja) | B87: =B85/B86-1 -> 0.11587942

Sheet MC Soriana
A3: 1. FCFF PROYECTADO — MÍNIMOS CUADRADOS (sin ajustes externos)
A4: Concepto | B4: 3T26 | C4: 4T26 | D4: 1T27 | E4: 2T27 | F4: LTM proyectado (3T26–2T27) | G4: LTM actual (3T25–2T26) | H4: Variación vs. LTM actual
A5: X (pronóstico) | B5: =I39 -> 3 | C5: =I40 -> 4 | D5: =I41 -> 5 | E5: =I42 -> 6
A6: Ventas | B6: =J39 -> 41995.3 | C6: =J40 -> 41321.2 | D6: =J41 -> 40647.1 | E6: =J42 -> 39973 | F6: =SUM(B6:E6) -> 163936.6 | G6: =SUM(Datos!C6:F6) -> 174278 | H6: =IFERROR((F6-G6)/ABS(G6),"") -> -0.059338528
A7: Costos y gastos operativos | B7: =J56 -> 40013.5 | C7: =J57 -> 39314.8 | D7: =J58 -> 38616.1 | E7: =J59 -> 37917.4 | F7: =SUM(B7:E7) -> 155861.8 | G7: =SUM(Datos!C6:F6)-SUM(Datos!C9:F9) -> 166647 | H7: =IFERROR((F7-G7)/ABS(G7),"") -> -0.064718837
A8: EBIT | B8: =B6-B7 -> 1981.8 | C8: =C6-C7 -> 2006.4 | D8: =D6-D7 -> 2031 | E8: =E6-E7 -> 2055.6 | F8: =SUM(B8:E8) -> 8074.8 | G8: =G6-G7 -> 7631 | H8: =IFERROR((F8-G8)/ABS(G8),"") -> 0.058157515
A9: Margen EBIT | B9: =B8/B6 -> 0.047190995 | C9: =C8/C6 -> 0.048556189 | D9: =D8/D6 -> 0.049966664 | E9: =E8/E6 -> 0.051424712 | F9: =F8/F6 -> 0.049255627 | G9: =G8/G6 -> 0.043786364
A10: Tasa de impuesto | B10: =J73 -> 0.22485563 | C10: =J74 -> 0.20299653 | D10: =J75 -> 0.18113743 | E10: =J76 -> 0.15927832 | F10: =1-F11/F8 -> 0.19173401 | G10: =SUM(Datos!C12:F12)/SUM(Datos!C11:F11) -> 0.26947368
A11: EBIT (1 − T) | B11: =B8*(1-B10) -> 1536.1811 | C11: =C8*(1-C10) -> 1599.1078 | D11: =D8*(1-D10) -> 1663.1099 | E11: =E8*(1-E10) -> 1728.1875 | F11: =SUM(B11:E11) -> 6526.5862 | G11: =G8*(1-G10) -> 5574.6463 | H11: =IFERROR((F11-G11)/ABS(G11),"") -> 0.17076239
A12: (+) Depreciación y amortización | B12: =J90 -> 1011.854 | C12: =J91 -> 996.7536 | D12: =J92 -> 981.6532 | E12: =J93 -> 966.5528 | F12: =SUM(B12:E12) -> 3956.8136 | G12: =SUM(Datos!C14:F14) -> 4179.871 | H12: =IFERROR((F12-G12)/ABS(G12),"") -> -0.053364661
A13: (−) Capex | B13: =J107 -> 798.82 | C13: =J108 -> 820.74 | D13: =J109 -> 842.66 | E13: =J110 -> 864.58 | F13: =SUM(B13:E13) -> 3326.8 | G13: =SUM(Datos!C16:F16) -> 3002.1 | H13: =IFERROR((F13-G13)/ABS(G13),"") -> 0.10815762
A14: Capital de trabajo neto (cierre) | B14: =J124 -> 6975.4312 | C14: =J125 -> 6036.114 | D14: =J126 -> 5096.7968 | E14: =J127 -> 4157.4796 | F14: =E14 -> 4157.4796 | G14: =Datos!F19-Datos!F21 -> 7301.914
A15: (−) ΔNWC (cambio en capital de trabajo) | B15: =B14-(Datos!$F$19-Datos!$F$21) -> -326.4828 | C15: =C14-B14 -> -939.3172 | D15: =D14-C14 -> -939.3172 | E15: =E14-D14 -> -939.3172 | F15: =SUM(B15:E15) -> -3144.4344 | G15: =(Datos!F19-Datos!F21)-(Datos!B19-Datos!B21) -> -3764.086
A16: FCFF = EBIT(1−T) + D&A − Capex − ΔNWC | B16: =B11+B12-B13-B15 -> 2075.6979 | C16: =C11+C12-C13-C15 -> 2714.4386 | D16: =D11+D12-D13-D15 -> 2741.4203 | E16: =E11+E12-E13-E15 -> 2769.4775 | F16: =F11+F12-F13-F15 -> 10301.034 | G16: =G11+G12-G13-G15 -> 10516.503 | H16: =IFERROR((F16-G16)/ABS(G16),"") -> -0.020488662
A18: 2. FCFF PROYECTADO AJUSTADO POR VARIABLES EXTERNAS
A19: Ajuste neto a ventas | B19: ='Variables Externas'!H22 -> -0.009
A20: Ajuste neto a costos y gastos | B20: ='Variables Externas'!I22 -> 0.0052
A21: Ajuste neto a capex | B21: ='Variables Externas'!J22 -> 0.025
A23: Concepto | B23: 3T26 | C23: 4T26 | D23: 1T27 | E23: 2T27 | F23: LTM ajustado (3T26–2T27) | G23: LTM proyectado sin ajuste | H23: Variación vs. sin ajuste
A24: Ventas | B24: =B6*(1+$B$19) -> 41617.342 | C24: =C6*(1+$B$19) -> 40949.309 | D24: =D6*(1+$B$19) -> 40281.276 | E24: =E6*(1+$B$19) -> 39613.243 | F24: =SUM(B24:E24) -> 162461.17 | G24: =F6 -> 163936.6 | H24: =IFERROR((F24-G24)/ABS(G24),"") -> -0.009
A25: Costos y gastos operativos | B25: =B7*(1+$B$19)*(1+$B$20) -> 39859.576 | C25: =C7*(1+$B$19)*(1+$B$20) -> 39163.564 | D25: =D7*(1+$B$19)*(1+$B$20) -> 38467.552 | E25: =E7*(1+$B$19)*(1+$B$20) -> 37771.539 | F25: =SUM(B25:E25) -> 155262.23 | G25: =F7 -> 155861.8 | H25: =IFERROR((F25-G25)/ABS(G25),"") -> -0.0038468
A26: EBIT | B26: =B24-B25 -> 1757.7662 | C26: =C24-C25 -> 1785.7454 | D26: =D24-D25 -> 1813.7245 | E26: =E24-E25 -> 1841.7037 | F26: =SUM(B26:E26) -> 7198.9398 | G26: =F8 -> 8074.8 | H26: =IFERROR((F26-G26)/ABS(G26),"") -> -0.10846835
A27: Margen EBIT | B27: =B26/B24 -> 0.042236388 | C27: =C26/C24 -> 0.043608681 | D27: =D26/D24 -> 0.045026491 | E27: =E26/E24 -> 0.04649212 | F27: =F26/F24 -> 0.044311756 | G27: =F9 -> 0.049255627
A28: Tasa de impuesto | B28: =B10 -> 0.22485563 | C28: =C10 -> 0.20299653 | D28: =D10 -> 0.18113743 | E28: =E10 -> 0.15927832 | F28: =1-F29/F26 -> 0.19164219 | G28: =F10 -> 0.19173401
A29: EBIT (1 − T) | B29: =B26*(1-B28) -> 1362.5226 | C29: =C26*(1-C28) -> 1423.2453 | D29: =D26*(1-D28) -> 1485.1911 | E29: =E26*(1-E28) -> 1548.3602 | F29: =SUM(B29:E29) -> 5819.3192 | G29: =F11 -> 6526.5862 | H29: =IFERROR((F29-G29)/ABS(G29),"") -> -0.10836708
A30: (+) Depreciación y amortización | B30: =B12 -> 1011.854 | C30: =C12 -> 996.7536 | D30: =D12 -> 981.6532 | E30: =E12 -> 966.5528 | F30: =SUM(B30:E30) -> 3956.8136 | G30: =F12 -> 3956.8136 | H30: =IFERROR((F30-G30)/ABS(G30),"") -> 0
A31: (−) Capex | B31: =B13*(1+$B$21) -> 818.7905 | C31: =C13*(1+$B$21) -> 841.2585 | D31: =D13*(1+$B$21) -> 863.7265 | E31: =E13*(1+$B$21) -> 886.1945 | F31: =SUM(B31:E31) -> 3409.97 | G31: =F13 -> 3326.8 | H31: =IFERROR((F31-G31)/ABS(G31),"") -> 0.025
A32: (−) ΔNWC | B32: =B15 -> -326.4828 | C32: =C15 -> -939.3172 | D32: =D15 -> -939.3172 | E32: =E15 -> -939.3172 | F32: =SUM(B32:E32) -> -3144.4344 | G32: =F15 -> -3144.4344
A33: FCFF ajustado | B33: =B29+B30-B31-B32 -> 1882.0689 | C33: =C29+C30-C31-C32 -> 2518.0576 | D33: =D29+D30-D31-D32 -> 2542.435 | E33: =E29+E30-E31-E32 -> 2568.0357 | F33: =SUM(B33:E33) -> 9510.5972 | G33: =F16 -> 10301.034 | H33: =IFERROR((F33-G33)/ABS(G33),"") -> -0.076733759
A35: DETALLE DE MÍNIMOS CUADRADOS POR PARTIDA DEL FCFF
A37: 1. VENTAS (ingresos totales)
A38: Trimestre | B38: n | C38: X = n − (N+1)/2 | D38: Y (mdp) | E38: XY | F38: X² | H38: Trimestre a pronosticar | I38: X (pronóstico) | J38: Y pronosticada
A39: =Datos!B$5 -> 2T25 | B39: 1 | C39: =B39-(COUNT($B$39:$B$43)+1)/2 -> -2 | D39: =Datos!B6 -> 45810 | E39: =C39*D39 -> -91620 | F39: =C39^2 -> 4 | H39: 3T26 | I39: =MAX($C$39:$C$43)+1 -> 3 | J39: =$B$48+$B$47*I39 -> 41995.3
A40: =Datos!C$5 -> 3T25 | B40: 2 | C40: =B40-(COUNT($B$39:$B$43)+1)/2 -> -1 | D40: =Datos!C6 -> 42683 | E40: =C40*D40 -> -42683 | F40: =C40^2 -> 1 | H40: 4T26 | I40: =I39+1 -> 4 | J40: =$B$48+$B$47*I40 -> 41321.2
A41: =Datos!D$5 -> 4T25 | B41: 3 | C41: =B41-(COUNT($B$39:$B$43)+1)/2 -> 0 | D41: =Datos!D6 -> 47592 | E41: =C41*D41 -> 0 | F41: =C41^2 -> 0 | H41: 1T27 | I41: =I40+1 -> 5 | J41: =$B$48+$B$47*I41 -> 40647.1
A42: =Datos!E$5 -> 1T26 | B42: 4 | C42: =B42-(COUNT($B$39:$B$43)+1)/2 -> 1 | D42: =Datos!E6 -> 40444 | E42: =C42*D42 -> 40444 | F42: =C42^2 -> 1 | H42: 2T27 | I42: =I41+1 -> 6 | J42: =$B$48+$B$47*I42 -> 39973
A43: =Datos!F$5 -> 2T26 | B43: 5 | C43: =B43-(COUNT($B$39:$B$43)+1)/2 -> 2 | D43: =Datos!F6 -> 43559 | E43: =C43*D43 -> 87118 | F43: =C43^2 -> 4
A44: Σ (sumas) | C44: =SUM(C39:C43) -> 0 | D44: =SUM(D39:D43) -> 220088 | E44: =SUM(E39:E43) -> -6741 | F44: =SUM(F39:F43) -> 10 | H44: ="Ecuación: Y = "&TEXT(B48,"#,##0.0000")&" + ("&TEXT(B47,"#,##0.0000")&")·X" -> Ecuación: Y = 44,017.6000 + (-674.1000)·X
A45: N (trimestres) | B45: =COUNT(B39:B43) -> 5
A46: X̄ = ΣX / N | B46: =C44/B45 -> 0
A47: b = ΣXY / ΣX² | B47: =E44/F44 -> -674.1
A48: a = ΣY / N | B48: =D44/B45 -> 44017.6
A49: R² (ajuste) | B49: =RSQ(D39:D43,C39:C43) -> 0.14777049
A54: 2. COSTOS Y GASTOS OPERATIVOS (ventas − EBIT)
A55: Trimestre | B55: n | C55: X = n − (N+1)/2 | D55: Y (mdp) | E55: XY | F55: X² | H55: Trimestre a pronosticar | I55: X (pronóstico) | J55: Y pronosticada
A56: =Datos!B$5 -> 2T25 | B56: 1 | C56: =B56-(COUNT($B$56:$B$60)+1)/2 -> -2 | D56: =Datos!B6-Datos!B9 -> 43901 | E56: =C56*D56 -> -87802 | F56: =C56^2 -> 4 | H56: 3T26 | I56: =MAX($C$56:$C$60)+1 -> 3 | J56: =$B$65+$B$64*I56 -> 40013.5
A57: =Datos!C$5 -> 3T25 | B57: 2 | C57: =B57-(COUNT($B$56:$B$60)+1)/2 -> -1 | D57: =Datos!C6-Datos!C9 -> 41215 | E57: =C57*D57 -> -41215 | F57: =C57^2 -> 1 | H57: 4T26 | I57: =I56+1 -> 4 | J57: =$B$65+$B$64*I57 -> 39314.8
A58: =Datos!D$5 -> 4T25 | B58: 3 | C58: =B58-(COUNT($B$56:$B$60)+1)/2 -> 0 | D58: =Datos!D6-Datos!D9 -> 45106 | E58: =C58*D58 -> 0 | F58: =C58^2 -> 0 | H58: 1T27 | I58: =I57+1 -> 5 | J58: =$B$65+$B$64*I58 -> 38616.1
A59: =Datos!E$5 -> 1T26 | B59: 4 | C59: =B59-(COUNT($B$56:$B$60)+1)/2 -> 1 | D59: =Datos!E6-Datos!E9 -> 38622 | E59: =C59*D59 -> 38622 | F59: =C59^2 -> 1 | H59: 2T27 | I59: =I58+1 -> 6 | J59: =$B$65+$B$64*I59 -> 37917.4
A60: =Datos!F$5 -> 2T26 | B60: 5 | C60: =B60-(COUNT($B$56:$B$60)+1)/2 -> 2 | D60: =Datos!F6-Datos!F9 -> 41704 | E60: =C60*D60 -> 83408 | F60: =C60^2 -> 4
A61: Σ (sumas) | C61: =SUM(C56:C60) -> 0 | D61: =SUM(D56:D60) -> 210548 | E61: =SUM(E56:E60) -> -6987 | F61: =SUM(F56:F60) -> 10 | H61: ="Ecuación: Y = "&TEXT(B65,"#,##0.0000")&" + ("&TEXT(B64,"#,##0.0000")&")·X" -> Ecuación: Y = 42,109.6000 + (-698.7000)·X
A62: N (trimestres) | B62: =COUNT(B56:B60) -> 5
A63: X̄ = ΣX / N | B63: =C61/B62 -> 0
A64: b = ΣXY / ΣX² | B64: =E61/F61 -> -698.7
A65: a = ΣY / N | B65: =D61/B62 -> 42109.6
A66: R² (ajuste) | B66: =RSQ(D56:D60,C56:C60) -> 0.19283751
A71: 3. TASA DE IMPUESTO (impuestos / UAI)
A72: Trimestre | B72: n | C72: X = n − (N+1)/2 | D72: Y (tasa) | E72: XY | F72: X² | H72: Trimestre a pronosticar | I72: X (pronóstico) | J72: Y pronosticada
A73: =Datos!B$5 -> 2T25 | B73: 1 | C73: =B73-(COUNT($B$73:$B$77)+1)/2 -> -2 | D73: =Datos!B12/Datos!B11 -> 0.38320865 | E73: =C73*D73 -> -0.76641729 | F73: =C73^2 -> 4 | H73: 3T26 | I73: =MAX($C$73:$C$77)+1 -> 3 | J73: =$B$82+$B$81*I73 -> 0.22485563
A74: =Datos!C$5 -> 3T25 | B74: 2 | C74: =B74-(COUNT($B$73:$B$77)+1)/2 -> -1 | D74: =Datos!C12/Datos!C11 -> 0.23429319 | E74: =C74*D74 -> -0.23429319 | F74: =C74^2 -> 1 | H74: 4T26 | I74: =I73+1 -> 4 | J74: =$B$82+$B$81*I74 -> 0.20299653
A75: =Datos!D$5 -> 4T25 | B75: 3 | C75: =B75-(COUNT($B$73:$B$77)+1)/2 -> 0 | D75: =Datos!D12/Datos!D11 -> 0.25808281 | E75: =C75*D75 -> 0 | F75: =C75^2 -> 0 | H75: 1T27 | I75: =I74+1 -> 5 | J75: =$B$82+$B$81*I75 -> 0.18113743
A76: =Datos!E$5 -> 1T26 | B76: 4 | C76: =B76-(COUNT($B$73:$B$77)+1)/2 -> 1 | D76: =Datos!E12/Datos!E11 -> 0.37104072 | E76: =C76*D76 -> 0.37104072 | F76: =C76^2 -> 1 | H76: 2T27 | I76: =I75+1 -> 6 | J76: =$B$82+$B$81*I76 -> 0.15927832
A77: =Datos!F$5 -> 2T26 | B77: 5 | C77: =B77-(COUNT($B$73:$B$77)+1)/2 -> 2 | D77: =Datos!F12/Datos!F11 -> 0.20553936 | E77: =C77*D77 -> 0.41107872 | F77: =C77^2 -> 4
A78: Σ (sumas) | C78: =SUM(C73:C77) -> 0 | D78: =SUM(D73:D77) -> 1.4521647 | E78: =SUM(E73:E77) -> -0.21859104 | F78: =SUM(F73:F77) -> 10 | H78: ="Ecuación: Y = "&TEXT(B82,"#,##0.0000")&" + ("&TEXT(B81,"#,##0.0000")&")·X" -> Ecuación: Y = 0.2904 + (-0.0219)·X
A79: N (trimestres) | B79: =COUNT(B73:B77) -> 5
A80: X̄ = ΣX / N | B80: =C78/B79 -> 0
A81: b = ΣXY / ΣX² | B81: =E78/F78 -> -0.021859104
A82: a = ΣY / N | B82: =D78/B79 -> 0.29043295
A83: R² (ajuste) | B83: =RSQ(D73:D77,C73:C77) -> 0.18024112
A88: 4. DEPRECIACIÓN Y AMORTIZACIÓN
A89: Trimestre | B89: n | C89: X = n − (N+1)/2 | D89: Y (mdp) | E89: XY | F89: X² | H89: Trimestre a pronosticar | I89: X (pronóstico) | J89: Y pronosticada
A90: =Datos!B$5 -> 2T25 | B90: 1 | C90: =B90-(COUNT($B$90:$B$94)+1)/2 -> -2 | D90: =Datos!B14 -> 1105.905 | E90: =C90*D90 -> -2211.81 | F90: =C90^2 -> 4 | H90: 3T26 | I90: =MAX($C$90:$C$94)+1 -> 3 | J90: =$B$99+$B$98*I90 -> 1011.854
A91: =Datos!C$5 -> 3T25 | B91: 2 | C91: =B91-(COUNT($B$90:$B$94)+1)/2 -> -1 | D91: =Datos!C14 -> 1049.349 | E91: =C91*D91 -> -1049.349 | F91: =C91^2 -> 1 | H91: 4T26 | I91: =I90+1 -> 4 | J91: =$B$99+$B$98*I91 -> 996.7536
A92: =Datos!D$5 -> 4T25 | B92: 3 | C92: =B92-(COUNT($B$90:$B$94)+1)/2 -> 0 | D92: =Datos!D14 -> 1051 | E92: =C92*D92 -> 0 | F92: =C92^2 -> 0 | H92: 1T27 | I92: =I91+1 -> 5 | J92: =$B$99+$B$98*I92 -> 981.6532
A93: =Datos!E$5 -> 1T26 | B93: 4 | C93: =B93-(COUNT($B$90:$B$94)+1)/2 -> 1 | D93: =Datos!E14 -> 1048.889 | E93: =C93*D93 -> 1048.889 | F93: =C93^2 -> 1 | H93: 2T27 | I93: =I92+1 -> 6 | J93: =$B$99+$B$98*I93 -> 966.5528
A94: =Datos!F$5 -> 2T26 | B94: 5 | C94: =B94-(COUNT($B$90:$B$94)+1)/2 -> 2 | D94: =Datos!F14 -> 1030.633 | E94: =C94*D94 -> 2061.266 | F94: =C94^2 -> 4
A95: Σ (sumas) | C95: =SUM(C90:C94) -> 0 | D95: =SUM(D90:D94) -> 5285.776 | E95: =SUM(E90:E94) -> -151.004 | F95: =SUM(F90:F94) -> 10 | H95: ="Ecuación: Y = "&TEXT(B99,"#,##0.0000")&" + ("&TEXT(B98,"#,##0.0000")&")·X" -> Ecuación: Y = 1,057.1552 + (-15.1004)·X
A96: N (trimestres) | B96: =COUNT(B90:B94) -> 5
A97: X̄ = ΣX / N | B97: =C95/B96 -> 0
A98: b = ΣXY / ΣX² | B98: =E95/F95 -> -15.1004
A99: a = ΣY / N | B99: =D95/B96 -> 1057.1552
A100: R² (ajuste) | B100: =RSQ(D90:D94,C90:C94) -> 0.70222795
A105: 5. CAPEX (inmuebles, equipo e intangibles)
A106: Trimestre | B106: n | C106: X = n − (N+1)/2 | D106: Y (mdp) | E106: XY | F106: X² | H106: Trimestre a pronosticar | I106: X (pronóstico) | J106: Y pronosticada
A107: =Datos!B$5 -> 2T25 | B107: 1 | C107: =B107-(COUNT($B$107:$B$111)+1)/2 -> -2 | D107: =Datos!B16 -> 663.2 | E107: =C107*D107 -> -1326.4 | F107: =C107^2 -> 4 | H107: 3T26 | I107: =MAX($C$107:$C$111)+1 -> 3 | J107: =$B$116+$B$115*I107 -> 798.82
A108: =Datos!C$5 -> 3T25 | B108: 2 | C108: =B108-(COUNT($B$107:$B$111)+1)/2 -> -1 | D108: =Datos!C16 -> 775.2 | E108: =C108*D108 -> -775.2 | F108: =C108^2 -> 1 | H108: 4T26 | I108: =I107+1 -> 4 | J108: =$B$116+$B$115*I108 -> 820.74
A109: =Datos!D$5 -> 4T25 | B109: 3 | C109: =B109-(COUNT($B$107:$B$111)+1)/2 -> 0 | D109: =Datos!D16 -> 816 | E109: =C109*D109 -> 0 | F109: =C109^2 -> 0 | H109: 1T27 | I109: =I108+1 -> 5 | J109: =$B$116+$B$115*I109 -> 842.66
A110: =Datos!E$5 -> 1T26 | B110: 4 | C110: =B110-(COUNT($B$107:$B$111)+1)/2 -> 1 | D110: =Datos!E16 -> 501 | E110: =C110*D110 -> 501 | F110: =C110^2 -> 1 | H110: 2T27 | I110: =I109+1 -> 6 | J110: =$B$116+$B$115*I110 -> 864.58
A111: =Datos!F$5 -> 2T26 | B111: 5 | C111: =B111-(COUNT($B$107:$B$111)+1)/2 -> 2 | D111: =Datos!F16 -> 909.9 | E111: =C111*D111 -> 1819.8 | F111: =C111^2 -> 4
A112: Σ (sumas) | C112: =SUM(C107:C111) -> 0 | D112: =SUM(D107:D111) -> 3665.3 | E112: =SUM(E107:E111) -> 219.2 | F112: =SUM(F107:F111) -> 10 | H112: ="Ecuación: Y = "&TEXT(B116,"#,##0.0000")&" + ("&TEXT(B115,"#,##0.0000")&")·X" -> Ecuación: Y = 733.0600 + (21.9200)·X
A113: N (trimestres) | B113: =COUNT(B107:B111) -> 5
A114: X̄ = ΣX / N | B114: =C112/B113 -> 0
A115: b = ΣXY / ΣX² | B115: =E112/F112 -> 21.92
A116: a = ΣY / N | B116: =D112/B113 -> 733.06
A117: R² (ajuste) | B117: =RSQ(D107:D111,C107:C111) -> 0.048701497
A122: 6. CAPITAL DE TRABAJO NETO (activo circ. − pasivo circ.)
A123: Trimestre | B123: n | C123: X = n − (N+1)/2 | D123: Y (mdp) | E123: XY | F123: X² | H123: Trimestre a pronosticar | I123: X (pronóstico) | J123: Y pronosticada
A124: =Datos!B$5 -> 2T25 | B124: 1 | C124: =B124-(COUNT($B$124:$B$128)+1)/2 -> -2 | D124: =Datos!B19-Datos!B21 -> 11066 | E124: =C124*D124 -> -22132 | F124: =C124^2 -> 4 | H124: 3T26 | I124: =MAX($C$124:$C$128)+1 -> 3 | J124: =$B$133+$B$132*I124 -> 6975.4312
A125: =Datos!C$5 -> 3T25 | B125: 2 | C125: =B125-(COUNT($B$124:$B$128)+1)/2 -> -1 | D125: =Datos!C19-Datos!C21 -> 11577 | E125: =C125*D125 -> -11577 | F125: =C125^2 -> 1 | H125: 4T26 | I125: =I124+1 -> 4 | J125: =$B$133+$B$132*I125 -> 6036.114
A126: =Datos!D$5 -> 4T25 | B126: 3 | C126: =B126-(COUNT($B$124:$B$128)+1)/2 -> 0 | D126: =Datos!D19-Datos!D21 -> 9310 | E126: =C126*D126 -> 0 | F126: =C126^2 -> 0 | H126: 1T27 | I126: =I125+1 -> 5 | J126: =$B$133+$B$132*I126 -> 5096.7968
...

Sheet Variables Externas
A4: # | B4: Categoría | C4: Variable | D4: Dato observado | E4: Canal de transmisión a Soriana | F4: Partida del FCFF afectada | G4: Efecto | H4: Ajuste a ventas (%) | I4: Ajuste a costos y gastos (%) | J4: Ajuste a capex (%)
A5: 1 | B5: Macroeconomía México | C5: Crecimiento del PIB | D5: Banxico (Informe abr–jun 2026): PIB 2026 1.5% (rango 1.0–2.0%); 2027 2.0% (rango 1.2–2.8%) | E5: Banxico espera que el consumo privado retome tendencia positiva tras la debilidad de inicio de 2026: más volumen en autoservicio | F5: Ventas | G5: + | H5: 0.005 | I5: 0 | J5: 0
A6: 2 | B6: Macroeconomía México | C6: Inflación | D6: General 3.42% y subyacente 3.79% (1a quincena sep-2026); convergencia a 3% hasta 4T27 | E6: Eleva ventas nominales y costo de mercancía en proporción similar; efecto casi neutral en margen (ya capturado en la tendencia) | F6: Ventas y costos | G6: Neutral | H6: 0 | I6: 0 | J6: 0
A7: 3 | B7: Política monetaria | C7: Tasa objetivo Banxico / Fed | D7: Banxico mantuvo 6.50% (24-sep-2026, unánime); la Fed subió 25 pb en septiembre | E7: Afecta costo de deuda y WACC (descuento del FCFF), no el FCFF operativo; crédito al consumo sigue caro | F7: WACC / gastos financieros | G7: − (valuación) | H7: 0 | I7: 0 | J7: 0
A8: 4 | B8: Macroeconomía México | C8: Tipo de cambio | D8: 18.08 MXN/USD al cierre del 30-sep-2026; el peso perdió 6.38% en septiembre | E8: Encarece mercancía general importada (electrónica, línea blanca) y equipo/refrigeración del programa de capex | F8: Costos y capex | G8: − | H8: 0 | I8: 0.001 | J8: 0.01
A9: 5 | B9: Macroeconomía México | C9: Remesas | D9: 2025: USD 61,791 mm (−4.6%), primera caída anual en 11 años; 1T26 +1.4% | E9: Menor ingreso de hogares en Bajío, Occidente y Norte (regiones clave de Soriana) por política migratoria de EU | F9: Ventas | G9: − | H9: -0.003 | I9: 0 | J9: 0
A10: 6 | B10: Política México (laboral) | C10: Salario mínimo 2026 | D10: +13%: de 278.80 a 315.04 $/día (frontera norte +5%: 440.87 $/día); meta 2.5 canastas básicas a 2030 | E10: Sube la nómina operativa de tiendas, pero también el ingreso disponible del cliente de bajos ingresos | F10: Costos (+) y ventas (+) | G10: Mixto | H10: 0.002 | I10: 0.0015 | J10: 0
A11: 7 | B11: Política México (laboral) | C11: Jornada laboral de 40 horas | D11: Reducción gradual de 48 a 40 h; 2026 es periodo de adecuación y los cambios inician en 2027 | E11: Requiere más turnos/plantilla en tiendas de horario extendido o más automatización | F11: Costos | G11: − | H11: 0 | I11: 0.0005 | J11: 0
A12: 8 | B12: Política México (fiscal) | C12: IEPS a bebidas y tabaco | D12: Bebidas azucaradas de 1.64 a 3.08 $/litro; tabaco de 160% a 200% ad valorem (2026) | E12: Menor volumen en categorías de alta rotación (refrescos, tabaco) dentro del ticket del autoservicio | F12: Ventas | G12: − | H12: -0.002 | I12: 0 | J12: 0
A13: 9 | B13: Política comercial México | C13: Aranceles a países sin tratado | D13: Aranceles nuevos o mayores de hasta 50% a importaciones de China, Corea del Sur, India, Vietnam, etc. desde 1-ene-2026 | E13: Encarece ropa, juguetes, electrónicos y equipo de tienda de origen asiático | F13: Costos y capex | G13: − | H13: 0 | I13: 0.0005 | J13: 0.005
A14: 10 | B14: T-MEC | C14: Revisión del T-MEC | D14: EU activó el mecanismo de revisiones anuales (no hubo extensión en jul-2026); Banxico prevé inversión débil por la incertidumbre comercial | E14: Frena inversión y empleo formal en el Norte industrial, base de clientes de Soriana (Coahuila, NL, Chihuahua) | F14: Ventas | G14: − | H14: -0.003 | I14: 0 | J14: 0
A15: 11 | B15: T-MEC / aranceles de EU | C15: Aranceles de EU a sectores estratégicos | D15: Persisten aranceles de EU a acero, aluminio y automotriz; bienes con origen T-MEC conservan exención; exportaciones a EU +7.7% acumulado a mayo | E15: Presión sobre empleo manufacturero (autopartes, acero) en ciudades del Norte donde Soriana concentra tiendas | F15: Ventas | G15: − | H15: -0.002 | I15: 0 | J15: 0
A16: 12 | B16: Geopolítica | C16: Conflicto en Medio Oriente / petróleo | D16: Petróleo por encima de USD 100, dólar fuerte e incertidumbre geopolítica presionan al peso (sep-2026) | E16: Encarece energía de tiendas, diésel y fletes de la logística; riesgo inflacionario | F16: Costos | G16: − | H16: 0 | I16: 0.0005 | J16: 0
... A21: 17 | B21: Inmobiliario y arrendamientos | C21: Ocupación de centros comerciales (FIBRAs) | D21: Los 10 jugadores institucionales con ocupación arriba de 91% (algunos 99%) al 2T26, rentas al alza y spreads de renovación altos | E21: Alta demanda por espacio facilita monetizar/subarrendar las áreas liberadas por cierres y reducción de tiendas | F21: Ventas (otros ingresos) | G21: + | H21: 0.001 | I21: 0 | J21: 0
A22: TOTAL | C22: Ajuste neto aplicado a la proyección | H22: =SUM(H5:H21) -> -0.009 | I22: =SUM(I5:I21) -> 0.0052 | J22: =SUM(J5:J21) -> 0.025

Sheet Proyección Final Soriana
A5: A. PONDERACIÓN DE MÉTODOS | B5: 2025A | C5: 2026E | D5: 2027E | E5: 2028E | F5: 2029E | G5: 2030E
A6: Peso de variables externas | C6: 0.7 | D6: 0.7 | E6: 0.75 | F6: 0.8 | G6: 0.85
A7: Peso de mínimos cuadrados | C7: =1-C6 -> 0.3 | D7: =1-D6 -> 0.3 | E7: =1-E6 -> 0.25 | F7: =1-F6 -> 0.2 | G7: =1-G6 -> 0.15
A9: B. CRECIMIENTO DE VENTAS — VARIABLES EXTERNAS | B9: 2025A | C9: 2026E | D9: 2027E | E9: 2028E | F9: 2029E | G9: 2030E
A10: Inflación esperada (INPC) — escenario de la hoja Inflación | C10: =Inflación!B13 -> 0.0351 | D10: =Inflación!C13 -> 0.0351 | E10: =Inflación!D13 -> 0.0351 | F10: =Inflación!E13 -> 0.0351 | G10: =Inflación!F13 -> 0.0351
A11: Crecimiento real del PIB de México | C11: 0.014 | D11: 0.018 | E11: 0.02 | F11: 0.02 | G11: 0.02
A12: Elasticidad del volumen de autoservicio al PIB (x) | C12: 0.5 | D12: 0.5 | E12: 0.5 | F12: 0.5 | G12: 0.5
A13: Ajuste por debilidad del consumo | C13: -0.04 | D13: -0.015 | E13: -0.005 | F13: 0 | G13: 0
A14: Crecimiento nominal del mercado de autoservicio | C14: =C10+C11*C12+C13 -> 0.0021 | D14: =D10+D11*D12+D13 -> 0.0291 | E14: =E10+E11*E12+E13 -> 0.0401 | F14: =F10+F11*F12+F13 -> 0.0451 | G14: =G10+G11*G12+G13 -> 0.0451
A15: (±) Pérdida de participación (hard discount y competidores) | C15: -0.03 | D15: -0.02 | E15: -0.0125 | F15: -0.01 | G15: -0.0075
A16: (±) Cierre y reducción de tiendas | C16: -0.01 | D16: -0.005 | E16: 0 | F16: 0 | G16: 0
A17: (±) Remesas y política migratoria de EU | C17: -0.003 | D17: -0.002 | E17: -0.001 | F17: 0 | G17: 0
A18: (±) T-MEC y aranceles de EU (empleo industrial del Norte) | C18: -0.002 | D18: -0.003 | E18: -0.001 | F18: 0 | G18: 0
A19: (±) Programas sociales y salario mínimo (ingreso disponible) | C19: 0.002 | D19: 0.003 | E19: 0.003 | F19: 0.002 | G19: 0.002
A20: (±) Omnicanalidad y ventas digitales | C20: 0.003 | D20: 0.004 | E20: 0.005 | F20: 0.005 | G20: 0.005
A21: (±) PACIC e IEPS (precio tope y menor volumen) | C21: -0.002 | D21: -0.002 | E21: -0.001 | F21: 0 | G21: 0
A22: (±) Ingresos inmobiliarios y financieros (m² liberados, Sofipo) | C22: 0.001 | D22: 0.002 | E22: 0.002 | F22: 0.002 | G22: 0.002
A23: Crecimiento de ventas — variables externas | C23: =C14+SUM(C15:C22) -> -0.0389 | D23: =D14+SUM(D15:D22) -> 0.0061 | E23: =E14+SUM(E15:E22) -> 0.0346 | F23: =F14+SUM(F15:F22) -> 0.0441 | G23: =G14+SUM(G15:G22) -> 0.0466
A25: C. CRECIMIENTO DE VENTAS — MÍNIMOS CUADRADOS | B25: 2025A | C25: 2026E | D25: 2027E | E25: 2028E | F25: 2029E | G25: 2030E
A26: Ventas por mínimos cuadrados (trayectoria lineal anualizada, mdp) | B26: ='MC Soriana'!G6 -> 174278 | C26: ='MC Soriana'!F6 -> 163936.6 | D26: =C26+16*('MC Soriana'!$C$6-'MC Soriana'!$B$6) -> 153151 | E26: =D26+16*('MC Soriana'!$C$6-'MC Soriana'!$B$6) -> 142365.4 | F26: =E26+16*('MC Soriana'!$C$6-'MC Soriana'!$B$6) -> 131579.8 | G26: =F26+16*('MC Soriana'!$C$6-'MC Soriana'!$B$6) -> 120794.2
A27: Crecimiento de ventas — mínimos cuadrados | C27: =C26/B26-1 -> -0.059338528 | D27: =D26/C26-1 -> -0.065791288 | E27: =E26/D26-1 -> -0.070424614 | F27: =F26/E26-1 -> -0.075759981 | G27: =G26/F26-1 -> -0.081970029
A28: CRECIMIENTO DE VENTAS FINAL (ponderado) | C28: =C$6*C23+C$7*C27 -> -0.045031558 | D28: =D$6*D23+D$7*D27 -> -0.015467386 | E28: =E$6*E23+E$7*E27 -> 0.0083438466 | F28: =F$6*F23+F$7*F27 -> 0.020128004 | G28: =G$6*G23+G$7*G27 -> 0.027314496
A30: D. MARGEN EBIT | B30: 2025A | C30: 2026E | D30: 2027E | E30: 2028E | F30: 2029E | G30: 2030E
A31: Margen EBIT — variables externas (acumulado) | B31: =Valuación!B10 -> 0.042542884 | C31: =B31+SUM(C32:C39) -> 0.043742884 | D31: =C31+SUM(D32:D39) -> 0.043442884 | E31: =D31+SUM(E32:E39) -> 0.043742884 | F31: =E31+SUM(F32:F39) -> 0.044042884 | G31: =F31+SUM(G32:G39) -> 0.044342884
A32: (±) Austeridad, cierres y eficiencias | C32: 0.0055 | D32: 0.003 | E32: 0.002 | F32: 0.001 | G32: 0.001
A33: (±) Salario mínimo +13% y jornada de 40 h | C33: -0.001 | D33: -0.0015 | E33: -0.0015 | F33: -0.001 | G33: -0.001
A34: (±) Inversión en precio (hard discount, PACIC) | C34: -0.0015 | D34: -0.001 | E34: -0.001 | F34: -0.0005 | G34: 0
A35: (±) Tipo de cambio y aranceles a importaciones de Asia | C35: -0.0005 | D35: -0.0005 | E35: 0 | F35: 0 | G35: 0
A36: (±) Energía, combustibles y fletes | C36: -0.0005 | D36: -0.0005 | E36: 0 | F36: 0 | G36: 0
A37: (±) Rentas comerciales (tiendas arrendadas) | C37: -0.0003 | D37: -0.0003 | E37: -0.0002 | F37: -0.0002 | G37: -0.0002
A38: (±) Ingresos inmobiliarios y servicios financieros | C38: 0.0005 | D38: 0.001 | E38: 0.001 | F38: 0.001 | G38: 0.0005
A39: (±) Desapalancamiento operativo por menores ventas | C39: -0.001 | D39: -0.0005 | E39: 0 | F39: 0 | G39: 0
A40: Margen EBIT — mínimos cuadrados | C40: ='MC Soriana'!$F$9 -> 0.049255627 | D40: ='MC Soriana'!$F$9 -> 0.049255627 | E40: ='MC Soriana'!$F$9 -> 0.049255627 | F40: ='MC Soriana'!$F$9 -> 0.049255627 | G40: ='MC Soriana'!$F$9 -> 0.049255627
A41: MARGEN EBIT FINAL (ponderado) | C41: =C$6*C31+C$7*C40 -> 0.045396707 | D41: =D$6*D31+D$7*D40 -> 0.045186707 | E41: =E$6*E31+E$7*E40 -> 0.045121069 | F41: =F$6*F31+F$7*F40 -> 0.045085432 | G41: =G$6*G31+G$7*G40 -> 0.045079795
A43: E. OTROS SUPUESTOS (FCF Y ESTADOS FINANCIEROS) | B43: 2025A | C43: 2026E | D43: 2027E | E43: 2028E | F43: 2029E | G43: 2030E
A44: D&A (% ventas) — variables externas / histórico | C44: =Valuación!$B$11 -> 0.024459905 | D44: =Valuación!$B$11 -> 0.024459905 | E44: =Valuación!$B$11 -> 0.024459905 | F44: =Valuación!$B$11 -> 0.024459905 | G44: =Valuación!$B$11 -> 0.024459905
A45: D&A (% ventas) — mínimos cuadrados | C45: ='MC Soriana'!$F$12/'MC Soriana'!$F$6 -> 0.024136243 | D45: ='MC Soriana'!$F$12/'MC Soriana'!$F$6 -> 0.024136243 | E45: ='MC Soriana'!$F$12/'MC Soriana'!$F$6 -> 0.024136243 | F45: ='MC Soriana'!$F$12/'MC Soriana'!$F$6 -> 0.024136243 | G45: ='MC Soriana'!$F$12/'MC Soriana'!$F$6 -> 0.024136243
A46: D&A (% ventas) FINAL | C46: =C$6*C44+C$7*C45 -> 0.024362806 | D46: =D$6*D44+D$7*D45 -> 0.024362806 | E46: =E$6*E44+E$7*E45 -> 0.024378989 | F46: =F$6*F44+F$7*F45 -> 0.024395172 | G46: =G$6*G44+G$7*G45 -> 0.024411356
A47: Capex guía de Soriana 2026 (mdp) | C47: 4000
A48: (+) Inversión adicional en omnicanal y remodelación (% ventas) | D48: 0.003 | E48: 0.003 | F48: 0.003 | G48: 0.003
A49: Capex (% ventas) — variables externas | C49: =C47/C67 -> 0.023595866 | D49: =Valuación!$B$12*(1+'Variables Externas'!$J$22)+D48 -> 0.019554517 | E49: =Valuación!$B$12*(1+'Variables Externas'!$J$22)+E48 -> 0.019554517 | F49: =Valuación!$B$12*(1+'Variables Externas'!$J$22)+F48 -> 0.019554517 | G49: =Valuación!$B$12*(1+'Variables Externas'!$J$22)+G48 -> 0.019554517
A50: Capex (% ventas) — mínimos cuadrados | C50: ='MC Soriana'!$F$13/'MC Soriana'!$F$6 -> 0.020293211 | D50: ='MC Soriana'!$F$13/'MC Soriana'!$F$6 -> 0.020293211 | E50: ='MC Soriana'!$F$13/'MC Soriana'!$F$6 -> 0.020293211 | F50: ='MC Soriana'!$F$13/'MC Soriana'!$F$6 -> 0.020293211 | G50: ='MC Soriana'!$F$13/'MC Soriana'!$F$6 -> 0.020293211
A51: Capex (% ventas) FINAL | C51: =C$6*C49+C$7*C50 -> 0.022605069 | D51: =D$6*D49+D$7*D50 -> 0.019776125 | E51: =E$6*E49+E$7*E50 -> 0.01973919 | F51: =F$6*F49+F$7*F50 -> 0.019702255 | G51: =G$6*G49+G$7*G50 -> 0.019665321
A52: (+) Ajuste a la tasa por límite de deducciones (Paquete Económico 2027) | C52: 0 | D52: 0.005 | E52: 0.005 | F52: 0.005 | G52: 0.005
A53: Tasa de impuestos — variables externas | C53: =WACC!$B$10+C52 -> 0.3 | D53: =WACC!$B$10+D52 -> 0.305 | E53: =WACC!$B$10+E52 -> 0.305 | F53: =WACC!$B$10+F52 -> 0.305 | G53: =WACC!$B$10+G52 -> 0.305
A54: Tasa de impuestos — mínimos cuadrados | C54: ='MC Soriana'!$F$10 -> 0.19173401 | D54: ='MC Soriana'!$F$10 -> 0.19173401 | E54: ='MC Soriana'!$F$10 -> 0.19173401 | F54: ='MC Soriana'!$F$10 -> 0.19173401 | G54: ='MC Soriana'!$F$10 -> 0.19173401
A55: Tasa de impuestos FINAL | C55: =C$6*C53+C$7*C54 -> 0.2675202 | D55: =D$6*D53+D$7*D54 -> 0.2710202 | E55: =E$6*E53+E$7*E54 -> 0.2766835 | F55: =F$6*F53+F$7*F54 -> 0.2823468 | G55: =G$6*G53+G$7*G54 -> 0.2880101
A56: Días de inventario (sobre costo de ventas) | B56: =Datos!G18/Datos!G7*365 -> 87.444305 | C56: 88 | D56: 88 | E56: 87 | F56: 87 | G56: 87
A57: Otros activos circulantes (% ventas) | B57: =(Datos!G19-Datos!G17-Datos!G18)/Datos!G6 -> 0.039157254 | C57: =$B57 -> 0.039157254 | D57: =$B57 -> 0.039157254 | E57: =$B57 -> 0.039157254 | F57: =$B57 -> 0.039157254 | G57: =$B57 -> 0.039157254
A58: Pasivo circulante operativo (% ventas) | B58: =(Datos!G21-Datos!G25-Datos!G27)/Datos!G6 -> 0.20022533 | C58: =$B58 -> 0.20022533 | D58: =$B58 -> 0.20022533 | E58: =$B58 -> 0.20022533 | F58: =$B58 -> 0.20022533 | G58: =$B58 -> 0.20022533
A59: Costo de ventas (% ventas) | B59: =Datos!G7/Datos!G6 -> 0.75910205 | C59: 0.756 | D59: 0.757 | E59: 0.758 | F59: 0.758 | G59: 0.758
A60: Gastos de operación sin D&A (% ventas) | B60: =-B70/B67 -> 0.1739008 | C60: =1-C59-C46-C41 -> 0.17424049 | D60: =1-D59-D46-D41 -> 0.17345049 | E60: =1-E59-E46-E41 -> 0.17249994 | F60: =1-F59-F46-F41 -> 0.1725194 | G60: =1-G59-G46-G41 -> 0.17250885
A61: Tasa de interés implícita (% deuda + arrendamientos) | B61: =Datos!G10/(Datos!G25+Datos!G26+Datos!G27+Datos!G28) -> 0.13015497 | C61: 0.1 | D61: 0.0975 | E61: 0.0975 | F61: 0.0975 | G61: 0.0975
A62: Amortización neta de deuda bursátil y bancaria (mdp) | C62: 0 | D62: -1500 | E62: -1500 | F62: -1500 | G62: -1500
A63: Dividendos (% utilidad neta) | B63: ='Proyección Soriana'!B14 -> 0.30014406 | C63: =$B63 -> 0.30014406 | D63: =$B63 -> 0.30014406 | E63: =$B63 -> 0.30014406 | F63: =$B63 -> 0.30014406 | G63: =$B63 -> 0.30014406
A65: 1. PROYECCIÓN DE ESTADOS FINANCIEROS (mdp)
A66: 1.1 ESTADO DE RESULTADOS | B66: 2025A | C66: 2026E | D66: 2027E | E66: 2028E | F66: 2029E | G66: 2030E
A67: Ventas | B67: =Datos!G6 -> 177515 | C67: =B67*(1+C28) -> 169521.22 | D67: =C67*(1+D28) -> 166899.17 | E67: =D67*(1+E28) -> 168291.75 | F67: =E67*(1+F28) -> 171679.13 | G67: =F67*(1+G28) -> 176368.46
A68: Costo de ventas | B68: =-Datos!G7 -> -134752 | C68: =-C67*C59 -> -128158.04 | D68: =-D67*D59 -> -126342.67 | E68: =-E67*E59 -> -127565.15 | F68: =-F67*F59 -> -130132.78 | G68: =-G67*G59 -> -133687.29
A69: Utilidad bruta | B69: =B67+B68 -> 42763 | C69: =C67+C68 -> 41363.178 | D69: =D67+D68 -> 40556.499 | E69: =E67+E68 -> 40726.604 | F69: =F67+F68 -> 41546.35 | G69: =G67+G68 -> 42681.167
A70: Gastos de operación (sin D&A) | B70: =-(Datos!G8-Datos!G9-Datos!G14) -> -30870 | C70: =-C67*C60 -> -29537.46 | D70: =-D67*D60 -> -28948.743 | E70: =-E67*E60 -> -29030.318 | F70: =-F67*F60 -> -29617.98 | G70: =-G67*G60 -> -30425.12
A71: EBITDA | B71: =B69+B70 -> 11893 | C71: =C69+C70 -> 11825.718 | D71: =D69+D70 -> 11607.756 | E71: =E69+E70 -> 11696.287 | F71: =F69+F70 -> 11928.37 | G71: =G69+G70 -> 12256.047
A72: Depreciación y amortización | B72: =-Datos!G14 -> -4342 | C72: =-C67*C46 -> -4130.0127 | D72: =-D67*D46 -> -4066.1322 | E72: =-E67*E46 -> -4102.7829 | F72: =-F67*F46 -> -4188.142 | G72: =-G67*G46 -> -4305.3932
A73: Utilidad de operación (EBIT) | B73: =B71+B72 -> 7551 | C73: =C71+C72 -> 7695.7052 | D73: =D71+D72 -> 7541.624 | E73: =E71+E72 -> 7593.5039 | F73: =F71+F72 -> 7740.2278 | G73: =G71+G72 -> 7950.654
A74: Gastos financieros | B74: =-Datos!G10 -> -3074 | C74: =-C61*(B91+B92) -> -2361.8 | D74: =-D61*(C91+C92) -> -2302.755 | E74: =-E61*(D91+D92) -> -2156.505 | F74: =-F61*(E91+E92) -> -2010.255 | G74: =-G61*(F91+F92) -> -1864.005
A75: Otros ingresos (gastos) netos | B75: =Datos!G11-Datos!G9+Datos!G10 -> 288 | C75: 0 | D75: 0 | E75: 0 | F75: 0 | G75: 0
A76: Utilidad antes de impuestos | B76: =B73+B74+B75 -> 4765 | C76: =C73+C74+C75 -> 5333.9052 | D76: =D73+D74+D75 -> 5238.869 | E76: =E73+E74+E75 -> 5436.9989 | F76: =F73+F74+F75 -> 5729.9728 | G76: =G73+G74+G75 -> 6086.649
A77: Impuestos a la utilidad | B77: =-Datos!G12 -> -1433 | C77: =-C76*C55 -> -1426.9274 | D77: =-D76*D55 -> -1419.8393 | E77: =-E76*E55 -> -1504.3279 | F77: =-F76*F55 -> -1617.8395 | G77: =-G76*G55 -> -1753.0164
A78: Utilidad neta | B78: =B76+B77 -> 3332 | C78: =C76+C77 -> 3906.9778 | D78: =D76+D77 -> 3819.0296 | E78: =E76+E77 -> 3932.671 | F78: =F76+F77 -> 4112.1333 | G78: =G76+G77 -> 4333.6326
A79: Dividendos pagados | C79: =-C78*C63 -> -1172.6562 | D79: =-D78*D63 -> -1146.259 | E79: =-E78*E63 -> -1180.3678 | F79: =-F78*F63 -> -1234.2324 | G79: =-G78*G63 -> -1300.7141
A80: Margen EBITDA | B80: =B71/B67 -> 0.066997155 | C80: =C71/C67 -> 0.069759513 | D80: =D71/D67 -> 0.069549513 | E80: =E71/E67 -> 0.069500059 | F80: =F71/F67 -> 0.069480605 | G80: =G71/G67 -> 0.069491151
A81: Margen neto | B81: =B78/B67 -> 0.018770245 | C81: =C78/C67 -> 0.023047131 | D81: =D78/D67 -> 0.022882256 | E81: =E78/E67 -> 0.023368174 | F81: =F78/F67 -> 0.023952436 | G81: =G78/G67 -> 0.024571472
A83: 1.2 BALANCE GENERAL | B83: 2025A | C83: 2026E | D83: 2027E | E83: 2028E | F83: 2029E | G83: 2030E
A84: Efectivo y equivalentes | B84: =Datos!G17 -> 9295 | C84: =B84+C108 -> 12424.375 | D84: =C84+D108 -> 14378.009 | E84: =D84+E108 -> 16690.212 | F84: =E84+F108 -> 18807.376 | G84: =F84+G108 -> 21085.407
A85: Inventarios | B85: =Datos!G18 -> 32283 | C85: =-C68*C56/365 -> 30898.378 | D85: =-D68*D56/365 -> 30460.699 | E85: =-E68*E56/365 -> 30405.94 | F85: =-F68*F56/365 -> 31017.951 | G85: =-G68*G56/365 -> 31865.19
A86: Otros activos circulantes | B86: =Datos!G19-Datos!G17-Datos!G18 -> 6951 | C86: =C67*C57 -> 6637.9856 | D86: =D67*D57 -> 6535.3133 | E86: =E67*E57 -> 6589.843 | F86: =F67*F57 -> 6722.4834 | G86: =G67*G57 -> 6906.1046
A87: Activo circulante | B87: =SUM(B84:B86) -> 48529 | C87: =SUM(C84:C86) -> 49960.739 | D87: =SUM(D84:D86) -> 51374.022 | E87: =SUM(E84:E86) -> 53685.995 | F87: =SUM(F84:F86) -> 56547.81 | G87: =SUM(G84:G86) -> 59856.702
A88: Activo no circulante | B88: =Datos!G20-Datos!G19 -> 107509 | C88: =B88-C104+C72 -> 107211.03 | D88: =C88-D104+D72 -> 106445.51 | E88: =D88-E104+E72 -> 105664.67 | F88: =E88-F104+F72 -> 104859 | G88: =F88-G104+G72 -> 104021.95
A89: Activo total | B89: =B87+B88 -> 156038 | C89: =C87+C88 -> 157171.76 | D89: =D87+D88 -> 157819.53 | E89: =E87+E88 -> 159350.67 | F89: =F87+F88 -> 161406.81 | G89: =G87+G88 -> 163878.65
A90: Pasivo circulante operativo (proveedores y otros) | B90: =Datos!G21-Datos!G25-Datos!G27 -> 35543 | C90: =C67*C58 -> 33942.443 | D90: =D67*D58 -> 33417.442 | E90: =E67*E58 -> 33696.272 | F90: =F67*F58 -> 34374.511 | G90: =G67*G58 -> 35313.434
A91: Deuda bursátil y bancaria | B91: =Datos!G25+Datos!G26 -> 11500 | C91: =MAX(0,B91+C62) -> 11500 | D91: =MAX(0,C91+D62) -> 10000 | E91: =MAX(0,D91+E62) -> 8500 | F91: =MAX(0,E91+F62) -> 7000 | G91: =MAX(0,F91+G62) -> 5500
A92: Pasivo por arrendamiento | B92: =Datos!G27+Datos!G28 -> 12118 | C92: =B92 -> 12118 | D92: =C92 -> 12118 | E92: =D92 -> 12118 | F92: =E92 -> 12118 | G92: =F92 -> 12118
A93: Otros pasivos a largo plazo | B93: =Datos!G23-Datos!G21-Datos!G26-Datos!G28 -> 12145 | C93: =B93 -> 12145 | D93: =C93 -> 12145 | E93: =D93 -> 12145 | F93: =E93 -> 12145 | G93: =F93 -> 12145
A94: Pasivo total | B94: =SUM(B90:B93) -> 71306 | C94: =SUM(C90:C93) -> 69705.443 | D94: =SUM(D90:D93) -> 67680.442 | E94: =SUM(E90:E93) -> 66459.272 | F94: =SUM(F90:F93) -> 65637.511 | G94: =SUM(G90:G93) -> 65076.434
A95: Capital contable | B95: =Datos!G24 -> 84732 | C95: =B95+C78+C79 -> 87466.322 | D95: =C95+D78+D79 -> 90139.092 | E95: =D95+E78+E79 -> 92891.395 | F95: =E95+F78+F79 -> 95769.296 | G95: =F95+G78+G79 -> 98802.215
A96: Pasivo + capital | B96: =B94+B95 -> 156038 | C96: =C94+C95 -> 157171.76 | D96: =D94+D95 -> 157819.53 | E96: =E94+E95 -> 159350.67 | F96: =F94+F95 -> 161406.81 | G96: =G94+G95 -> 163878.65
A97: Comprobación (activo − pasivo − capital) | B97: =B89-B96 -> 0 | C97: =C89-C96 -> 0 | D97: =D89-D96 -> 0 | E97: =E89-E96 -> 0 | F97: =F89-F96 -> 0 | G97: =G89-G96 -> 0
A99: 1.3 CONCILIACIÓN DE EFECTIVO | B99: 2025A | C99: 2026E | D99: 2027E | E99: 2028E | F99: 2029E | G99: 2030E
A100: Utilidad neta | C100: =C78 -> 3906.9778 | D100: =D78 -> 3819.0296 | E100: =E78 -> 3932.671 | F100: =F78 -> 4112.1333 | G100: =G78 -> 4333.6326
A101: (+) Depreciación y amortización | C101: =-C72 -> 4130.0127 | D101: =-D72 -> 4066.1322 | E101: =-E72 -> 4102.7829 | F101: =-F72 -> 4188.142 | G101: =-G72 -> 4305.3932
A102: (−) Aumento en inventarios | C102: =-(C85-B85) -> 1384.6221 | D102: =-(D85-C85) -> 437.67844 | E102: =-(E85-D85) -> 54.759707 | F102: =-(F85-E85) -> -612.01087 | G102: =-(G85-F85) -> -847.23968
A103: (−) Aumento en otros activos circulantes | C103: =-(C86-B86) -> 313.01436 | D103: =-(D86-C86) -> 102.67229 | E103: =-(E86-D86) -> -54.529652 | F103: =-(F86-E86) -> -132.64038 | G103: =-(G86-F86) -> -183.62124
A104: (−) Capex | C104: =-C67*C51 -> -3832.039 | D104: =-D67*D51 -> -3300.6189 | E104: =-E67*E51 -> -3321.9429 | F104: =-F67*F51 -> -3382.4661 | G104: =-G67*G51 -> -3468.3423
A105: (+) Aumento en pasivo circulante operativo | C105: =C90-B90 -> -1600.5567 | D105: =D90-C90 -> -525.00088 | E105: =E90-D90 -> 278.83001 | F105: =F90-E90 -> 678.2387 | G105: =G90-F90 -> 938.92244
A106: (−) Dividendos pagados | C106: =C79 -> -1172.6562 | D106: =D79 -> -1146.259 | E106: =E79 -> -1180.3678 | F106: =F79 -> -1234.2324 | G106: =G79 -> -1300.7141
A107: (±) Amortización neta de deuda | C107: =C91-B91 -> 0 | D107: =D91-C91 -> -1500 | E107: =E91-D91 -> -1500 | F107: =F91-E91 -> -1500 | G107: =G91-F91 -> -1500
A108: Cambio neto en efectivo | C108: =SUM(C100:C107) -> 3129.3752 | D108: =SUM(D100:D107) -> 1953.6338 | E108: =SUM(E100:E107) -> 2312.2032 | F108: =SUM(F100:F107) -> 2117.1643 | G108: =SUM(G100:G107) -> 2278.0309
A110: 2. FLUJO LIBRE DE EFECTIVO (FCF) — 5 AÑOS | B110: 2025A | C110: 2026E | D110: 2027E | E110: 2028E | F110: 2029E | G110: 2030E
A111: Utilidad de operación (EBIT) | C111: =C73 -> 7695.7052 | D111: =D73 -> 7541.624 | E111: =E73 -> 7593.5039 | F111: =F73 -> 7740.2278 | G111: =G73 -> 7950.654
A112: (−) Impuestos sobre EBIT | C112: =-C111*C55 -> -2058.7566 | D112: =-D111*D55 -> -2043.9324 | E112: =-E111*E55 -> -2100.9973 | F112: =-F111*F55 -> -2185.4286 | G112: =-G111*G55 -> -2289.8687
...

Sheet Inflación
A1: INFLACIÓN — datos, modelos de clase, escenarios y transmisión al modelo
A2: Fuente de datos: Banco de México, serie SP74833 (INPC, variación anual, quincenal), consulta 07/10/2026, tomada de "MODELO DE INFLACION EN LA VALUACION DE EMPRESAS.xlsx" hoja INFLACION. Unidades: % anual.
A3: Convención de colores: amarillo = dato o supuesto capturado (con fuente) · verde = vínculo a otra hoja o archivo fuente · azul = resultado clave · blanco = cálculo.
A5: 1. ESCENARIO DE INFLACIÓN APLICADO AL MODELO (entra a Proyección Final Soriana, fila 10)
A6: Escenario oficial (1 = Cautela · 2 = Base · 3 = Alcista) · 0 = Trayectoria Citi — Referencia (no es escenario) | B6: 2 | C6: =CHOOSE(B6+1,"Trayectoria Citi — Referencia","Cautela","Base","Alcista") -> Base | H6: Decisión del proyecto: tres escenarios oficiales; Base por defecto. El valor 0 aplica la trayectoria Citi solo como referencia histórica (con la beta heredada reproduce el baseline $31.16).
A8: Concepto | B8: 2026E | C8: 2027E | D8: 2028E | E8: 2029E | F8: 2030E | H8: Fuente / naturaleza
A9: 0 · Trayectoria Citi — Referencia histórica (no es escenario) | B9: 0.0393 | C9: 0.0383 | D9: 0.0375 | E9: 0.0375 | F9: 0.0375 | H9: Encuesta Citi de Expectativas, 22-sep-2026: cierre 2026 3.93%, 2027 3.83%, promedio 2028–32 3.75% (comentario original de Proyección Final!C10). Pronóstico de consenso por año: REFERENCIA HISTÓRICA del modelo anterior, no escenario oficial.
A10: 1 · Cautela (constante) | B10: =$B$47 -> 0.0326 | C10: =$B$47 -> 0.0326 | D10: =$B$47 -> 0.0326 | E10: =$B$47 -> 0.0326 | F10: =$B$47 -> 0.0326 | H10: Ver sección 4: escenario derivado de la tendencia larga (no es pronóstico de modelo).
A11: 2 · Base (constante) | B11: =$B$48 -> 0.0351 | C11: =$B$48 -> 0.0351 | D11: =$B$48 -> 0.0351 | E11: =$B$48 -> 0.0351 | F11: =$B$48 -> 0.0351 | H11: Ver sección 4: resultado de modelo (pronóstico exponencial trimestral de clase).
A12: 3 · Alcista (constante) | B12: =$B$49 -> 0.04 | C12: =$B$49 -> 0.04 | D12: =$B$49 -> 0.04 | E12: =$B$49 -> 0.04 | F12: =$B$49 -> 0.04 | H12: Ver sección 4: supuesto de escenario (no es pronóstico estadístico).
A13: INFLACIÓN APLICADA AL MODELO | B13: =CHOOSE($B$6+1,B9,B10,B11,B12) -> 0.0351 | C13: =CHOOSE($B$6+1,C9,C10,C11,C12) -> 0.0351 | D13: =CHOOSE($B$6+1,D9,D10,D11,D12) -> 0.0351 | E13: =CHOOSE($B$6+1,E9,E10,E11,E12) -> 0.0351 | F13: =CHOOSE($B$6+1,F9,F10,F11,F12) -> 0.0351 | H13: Proyección Final Soriana!C10:G10 = esta fila. Los escenarios constantes extienden a 2026–2030 un pronóstico de un periodo: es un supuesto documentado.
A15: 2. CADENA DE TRANSMISIÓN DOCUMENTADA (solo relaciones sustentadas en el Excel)
A16: Eslabón | B16: Fórmula / regla | H16: Sustento
A17: Inflación (fila 13) → Proyección Final!C10:G10 | B17: Vínculo directo | H17: Antes: valores capturados de la Encuesta Citi.
A18: → Crecimiento nominal del mercado (C14) | B18: Crec. mercado = Inflación + PIB × elasticidad + ajuste de consumo | H18: Coeficiente 1.0 sobre la inflación (fórmula existente del Excel).
A19: → Crecimiento por variables externas (C23) | B19: C23 = C14 + Σ ajustes (filas 15–22) | H19: Ajustes documentados en comentarios de cada celda.
A20: → Crecimiento final de ventas (C28) | B20: C28 = peso externo × C23 + peso MC × C27 | H20: Traspaso a ventas = 70% / 70% / 75% / 80% / 85% (pesos de la fila 6).
A21: → Costo de ventas, gastos, D&A, capital de trabajo | B21: % de ventas / días sobre costo | H21: Variables Externas!E6: 'eleva ventas nominales y costo de mercancía en proporción similar; efecto casi neutral en margen'.
A22: → Margen EBIT | B22: Sin término de inflación | H22: Margen neutral (documentado).
A23: → Capex | B23: 2026 = 4,000 mdp (guía de Soriana, monto fijo); 2027–30 = % de ventas | H23: El capex 2026 no escala con la inflación.
A24: → FCFF → EV → Equity → precio | B24: Fórmulas existentes | H24: El WACC solo cambia por la iteración (peso del equity).
A25: NO transmitido (sin sustento documental) | B25: Rf / WACC, beta, g, traspaso diferencial a costos | H25: Limitación documentada: con WACC nominal fijo, mayor inflación eleva el valor (menor WACC real).
A30: 3. MODELOS EXPONENCIALES DE CLASE y = a·e^(b·x) (calculados en esta hoja: b = SLOPE(ln y, x), a = EXP(INTERCEPT(ln y, x)))
A31: Modelo | B31: n | C31: a | D31: b | E31: R² | F31: x siguiente | G31: Proyección | H31: Lectura
A32: Inmediata (quincenal, último año: sep-25 a sep-26) | B32: =COUNT(B148:B172) -> 25 | C32: =EXP(INTERCEPT(F148:F172,E148:E172)) -> 3.9951135 | D32: =SLOPE(F148:F172,E148:E172) -> -0.0050443032 | E32: =RSQ(F148:F172,E148:E172) -> 0.10389452 | F32: 26 | G32: =C32*EXP(D32*F32)/100 -> 0.035040523 | H32: Resultado de modelo. R² bajo (tendencia de corto plazo).
A33: Trimestral (4 promedios trimestrales del último año) | B33: =COUNT(B38:E38) -> 4 | C33: =EXP(INTERCEPT(B40:E40,B39:E39)) -> 4.0301899 | D33: =SLOPE(B40:E40,B39:E39) -> -0.0277128 | E33: =RSQ(B40:E40,B39:E39) -> 0.092082096 | F33: 5 | G33: =C33*EXP(D33*F33)/100 -> 0.035087136 | H33: Resultado de modelo → define el escenario BASE. Solo 4 puntos.
A34: Ventana larga quincenal 2023–2026 | B34: =COUNT(C84:C172) -> 89 | C34: =EXP(INTERCEPT(D84:D172,C84:C172)) -> 5.8811994 | D34: =SLOPE(D84:D172,C84:C172) -> -0.006333713 | E34: =RSQ(D84:D172,C84:C172) -> 0.62264862 | F34: 90 | G34: =C34*EXP(D34*F34)/100 -> 0.033258542 | H34: Resultado de modelo de tendencia larga.
A35: Libro de clase, ventana quincenal (coeficientes redondeados 5.8812, −0.006) | C35: 5.8812 | D35: -0.006 | F35: 90 | G35: =C35*EXP(D35*F35)/100 -> 0.03427259 | H35: Reproduce INFLACION!T28 = 3.427%. El exponente redondeado sobrestima la proyección frente a la fila 34.
A36: Construcción de clase INFLACION!S113 (5 quincenas jul–sep 2026 + proyección de la fila 35) | G36: =AVERAGE(B168:B172,G35*100)/100 -> 0.032678765 | H36: Es un promedio aritmético que mezcla datos observados y una proyección, no un modelo. Es la construcción más cercana al 3.26% documentado.
A38: Promedios trimestrales (6 quincenas) — libro de clase D19, D25, D31, D37 | B38: =AVERAGE(B148:B153) -> 3.7083333 | C38: =AVERAGE(B154:B159) -> 3.8366667 | D38: =AVERAGE(B160:B165) -> 4.3266667 | E38: =AVERAGE(B166:B171) -> 3.2483333
A39: x del promedio trimestral | B39: 1 | C39: 2 | D39: 3 | E39: 4
A40: ln del promedio trimestral | B40: =LN(B38) -> 1.3105825 | C40: =LN(C38) -> 1.3446039 | D40: =LN(D38) -> 1.4647974 | E40: =LN(E38) -> 1.178142
A43: 4. ESCENARIOS DOCUMENTADOS Y SU NATURALEZA
A44: Escenario | B44: Valor | C44: Naturaleza | H44: Origen y trazabilidad
A47: Cautela | B47: 0.0326 | C47: Escenario derivado de la tendencia larga (no es pronóstico de modelo) | H47: Valor documentado en el Dossier ("ventana 2023-2026, trimestral 3.26%") y en Avances (escenario Cautela). Construcción de clase más cercana: fila 36 (3.268%). Modelos de tendencia larga calculados aquí: fila 34.
A48: Base | B48: =ROUND(G33,4) -> 0.0351 | C48: Forecast / resultado de modelo: modelo exponencial trimestral de clase | H48: Fila 33 redondeada a 2 decimales en %. Reproduce el 3.51% del Dossier ("4.0327e^(−0.028x) → 3.51%") y de Avances. Horizonte: siguiente trimestre; su extensión a 2026–30 es un supuesto.
A49: Alcista | B49: 0.04 | C49: Supuesto de escenario (scenario assumption; no es pronóstico estadístico) | H49: Avances de valuación intrínseca: "Alcista: inflación 4.0%". No proviene de ningún modelo. Referencia de contexto: el promedio trimestral máximo del último año fue 4.33% (fila 38).
A51: Nota: el selector no admite valores libres. Solo existen los tres escenarios oficiales de esta tabla; la trayectoria Citi (fila 9) es una referencia histórica.
A58: 5. DATOS: INPC variación anual quincenal (Banxico SP74833) y columnas auxiliares de los modelos
A59: Quincena | B59: Inflación % | C59: x (2023–26) | D59: ln (2023–26) | E59: x (último año) | F59: ln (último año) | G59: Bloque trimestral
A60: 44562 | B60: 7.13
A61: 44577 | B61: 7.01
A62: 44593 | B62: 7.22
A63: 44608 | B63: 7.34
A64: 44621 | B64: 7.29
A65: 44636 | B65: 7.62
A66: 44652 | B66: 7.72
A67: 44667 | B67: 7.65
A68: 44682 | B68: 7.58
A69: 44697 | B69: 7.72
A70: 44713 | B70: 7.88
A71: 44728 | B71: 8.09
... A83: 44911 | B83: 7.86
A84: 44927 | B84: 7.94 | C84: 1 | D84: =LN(B84) -> 2.0719133
A85: 44942 | B85: 7.88 | C85: 2 | D85: =LN(B85) -> 2.0643279
A86: 44958 | B86: 7.76 | C86: 3 | D86: =LN(B86) -> 2.0489823
A87: 44973 | B87: 7.48 | C87: 4 | D87: =LN(B87) -> 2.0122328
A88: 44986 | B88: 7.12 | C88: 5 | D88: =LN(B88) -> 1.9629077
A89: 45001 | B89: 6.58 | C89: 6 | D89: =LN(B89) -> 1.8840347
A90: 45017 | B90: 6.24 | C90: 7 | D90: =LN(B90) -> 1.8309802
A91: 45032 | B91: 6.27 | C91: 8 | D91: =LN(B91) -> 1.8357764
A92: 45047 | B92: 6 | C92: 9 | D92: =LN(B92) -> 1.7917595
A93: 45062 | B93: 5.67 | C93: 10 | D93: =LN(B93) -> 1.7351891
A94: 45078 | B94: 5.18 | C94: 11 | D94: =LN(B94) -> 1.6448051
A95: 45093 | B95: 4.93 | C95: 12 | D95: =LN(B95) -> 1.595339
... A147: 45885 | B147: 3.65 | C147: 64 | D147: =LN(B147) -> 1.2947272
A148: 45901 | B148: 3.74 | C148: 65 | D148: =LN(B148) -> 1.3190856 | E148: 1 | F148: =LN(B148) -> 1.3190856 | G148: 1
A149: 45916 | B149: 3.78 | C149: 66 | D149: =LN(B149) -> 1.329724 | E149: 2 | F149: =LN(B149) -> 1.329724 | G149: 1
A150: 45931 | B150: 3.63 | C150: 67 | D150: =LN(B150) -> 1.2892326 | E150: 3 | F150: =LN(B150) -> 1.2892326 | G150: 1
A151: 45946 | B151: 3.5 | C151: 68 | D151: =LN(B151) -> 1.252763 | E151: 4 | F151: =LN(B151) -> 1.252763 | G151: 1
A152: 45962 | B152: 3.61 | C152: 69 | D152: =LN(B152) -> 1.2837078 | E152: 5 | F152: =LN(B152) -> 1.2837078 | G152: 1
A153: 45977 | B153: 3.99 | C153: 70 | D153: =LN(B153) -> 1.3837912 | E153: 6 | F153: =LN(B153) -> 1.3837912 | G153: 1
A154: 45992 | B154: 3.72 | C154: 71 | D154: =LN(B154) -> 1.3137237 | E154: 7 | F154: =LN(B154) -> 1.3137237 | G154: 2
A155: 46007 | B155: 3.66 | C155: 72 | D155: =LN(B155) -> 1.2974631 | E155: 8 | F155: =LN(B155) -> 1.2974631 | G155: 2
A156: 46023 | B156: 3.77 | C156: 73 | D156: =LN(B156) -> 1.327075 | E156: 9 | F156: =LN(B156) -> 1.327075 | G156: 2
A157: 46038 | B157: 3.82 | C157: 74 | D157: =LN(B157) -> 1.3402504 | E157: 10 | F157: =LN(B157) -> 1.3402504 | G157: 2
A158: 46054 | B158: 3.92 | C158: 75 | D158: =LN(B158) -> 1.3660917 | E158: 11 | F158: =LN(B158) -> 1.3660917 | G158: 2
A159: 46069 | B159: 4.13 | C159: 76 | D159: =LN(B159) -> 1.4182774 | E159: 12 | F159: =LN(B159) -> 1.4182774 | G159: 2
... A171: 46250 | B171: 3.26 | C171: 88 | D171: =LN(B171) -> 1.1817272 | E171: 24 | F171: =LN(B171) -> 1.1817272 | G171: 4
A172: 46266 | B172: 3.42 | C172: 89 | D172: =LN(B172) -> 1.2296406 | E172: 25 | F172: =LN(B172) -> 1.2296406
A176: 6. ESTUDIO DE MERCADO DE CLASE (referencia; NO alimenta el DCF) — correlaciones y beta histórica
A177: Mes | B177: Cierre mensual Soriana B (MXN) | C177: Inflación mensual %
A178: 45597 | B178: 30.5 | C178: 4.55
A179: 45627 | B179: 29.63 | C179: 4.215
A180: 45658 | B180: 29.18 | C180: 3.585
A181: 45689 | B181: 27.65 | C181: 3.775
A182: 45717 | B182: 27.7 | C182: 3.8
A183: 45748 | B183: 25.98 | C183: 3.93
A184: 45778 | B184: 27.51 | C184: 4.42
A185: 45809 | B185: 27.98 | C185: 4.32
A186: 45839 | B186: 25.96 | C186: 3.515
A187: 45870 | B187: 25.73 | C187: 3.57
A188: 45901 | B188: 25 | C188: 3.76
A189: 45931 | B189: 26.45 | C189: 3.565
... A200: 46266 | B200: 35 | C200: 3.42
A202: Correlación precio–inflación | B202: Valor | C202: Ventana
A203: Toda la muestra (23 meses) | B203: =CORREL(B178:B200,C178:C200) -> 0.19017444 | C203: =TEXT(A178,"mmm-yy")&" a "&TEXT(A200,"mmm-yy") -> Nov-24 a Sep-26
A204: Anual (ene–sep 2026) | B204: =CORREL(B192:B200,C192:C200) -> 0.66003908 | C204: =TEXT(A192,"mmm-yy")&" a "&TEXT(A200,"mmm-yy") -> Jan-26 a Sep-26
A205: Semestral (abr–sep 2026) | B205: =CORREL(B195:B200,C195:C200) -> 0.60296681 | C205: =TEXT(A195,"mmm-yy")&" a "&TEXT(A200,"mmm-yy") -> Apr-26 a Sep-26
A206: Trimestral (jul–sep 2026) | B206: =CORREL(B198:B200,C198:C200) -> 0.69505996 | C206: =TEXT(A198,"mmm-yy")&" a "&TEXT(A200,"mmm-yy") -> Jul-26 a Sep-26
...

Sheet Beta y Kd
A1: BETA Y COSTO DE LA DEUDA — insumos del WACC con fuente, tratamiento e impacto
A2: Beta sectorial de Damodaran (global, enero 2026) desapalancada y reapalancada con la estructura de capital de Soriana (Hamada). La beta histórica de regresión es otro concepto (hoja Inflación §6).
A3: Convención de colores: amarillo = dato o supuesto capturado (con fuente) · verde = vínculo a otra hoja o archivo fuente · azul = resultado clave · blanco = cálculo.
A5: 1. FUENTE EXTERNA: Damodaran, "Betas by Sector (Global)" — datos de enero de 2026
A6: Dato | B6: Valor | E6: Fuente / nota
A7: Fuente | B7: Aswath Damodaran, NYU Stern — Betas by Sector (Global) | E7: https://pages.stern.nyu.edu/~adamodar/New_Home_Page/datafile/BetasGlobal.html
A8: Fecha de los datos | B8: Enero de 2026 | E8: Actualización anual de enero 2026 (consulta: 08-oct-2026).
A9: Industria | B9: Retail (Grocery and Food) | E9: Industria de Damodaran equivalente a autoservicio / supermercados (Soriana).
A10: Número de empresas | B10: 215 | E10: Muestra global.
A11: Beta apalancada promedio de la industria (βL) | B11: 0.87 | E11: Refleja la estructura de capital PROMEDIO de la industria, no la de Soriana.
A12: D/E de la industria | B12: 0.4596 | E12: Deuda / capital de mercado de la industria.
A13: Tasa efectiva de la industria | B13: 0.2081 | E13: Referencia.
A14: Tasa marginal usada por Damodaran para desapalancar | B14: 0.2537 | E14: Promedio global de tasas marginales.
A15: Beta desapalancada de la industria (βU) | B15: 0.65 | E15: βU = βL / [1 + (1 − t) × D/E].
A16: Efectivo / valor de la empresa | B16: 0.0581 | E16: Referencia.
A17: Beta desapalancada corregida por caja | B17: 0.69 | E17: βU / (1 − caja/valor). Se documenta como sensibilidad; no se usa (ver sección 2).
A18: Control: βU recalculada = 0.87 / [1 + (1 − 0.2537) × 0.4596] | B18: =B11/(1+(1-B14)*B12) -> 0.64780368 | C18: =B18-B15 -> -0.002196324 | E18: La βU publicada (0.65) es consistente con la βL y la D/E publicadas (diferencia de redondeo).
A20: 2. TRATAMIENTO ELEGIDO: βU sectorial reapalancada con la estructura de capital de Soriana
A21: El WACC del modelo reapalanca la beta en cada paso: βL = βU × [1 + (1 − t) × D/E] (WACC!B28 a valor de mercado; Proyección Final!E214:E219 en la iteración al valor DCF).
A22: Por eso el insumo correcto es una beta DESAPALANCADA. Usar la βL de 0.87 en esa fórmula aplicaría el apalancamiento dos veces (el de la industria y el de Soriana).
A23: Se usa la βU sin corrección por caja (0.65): Damodaran la obtuvo con D/E bruta y el modelo reapalanca con deuda bruta (bancaria + arrendamientos), así el tratamiento es simétrico; el efectivo se suma por separado en el puente EV → capital.
A24: La beta heredada 0.80 no tenía fuente en el Excel; coincide con la βU de "Grocery and Food" del archivo de Estados Unidos de Damodaran (15 empresas), pero la muestra global (215 empresas) es más representativa para una empresa mexicana.
A26: Beta heredada del Excel anterior (solo para reproducir el baseline histórico) | B26: 0.8 | E26: Input del Excel definitivo anterior y del Material Maestro ("Sesión 2"), sin fuente documentada.
A27: Selector de beta (1 = Damodaran global, oficial · 0 = beta heredada 0.80, histórico) | B27: 1
A28: BETA DESAPALANCADA USADA EN EL WACC (βU) | B28: =CHOOSE(B27+1,B26,B15) -> 0.65 | E28: Alimenta WACC!B9 → WACC de mercado (WACC!B28:B33) e iteración (Proyección Final!B212).
A30: 3. REAPALANCAMIENTO CON LA ESTRUCTURA DE CAPITAL DE SORIANA (vivo, con la beta seleccionada)
A31: Concepto | B31: A valor de mercado | C31: Iterado al valor DCF | E31: Fórmula / origen
A32: Beta desapalancada βU | B32: =B28 -> 0.65 | C32: =B28 -> 0.65 | E32: Sección 2.
A33: D/E | B33: =WACC!B23 -> 0.39190893 | C33: ='Proyección Final Soriana'!D219 -> 0.40633099 | E33: Mercado: deuda 2025 / (precio × acciones). DCF: deuda / equity del DCF (última iteración).
A34: Tasa fiscal para reapalancar | B34: =WACC!B10 -> 0.3 | C34: ='Proyección Final Soriana'!B207 -> 0.2880101 | E34: Mercado: ISR 30%. Iteración: tasa proyectada 2030E (28.80%).
A35: Beta reapalancada βL = βU × [1 + (1 − t) × D/E] | B35: =B32*(1+(1-B34)*B33) -> 0.82831856 | C35: =C32*(1+(1-C34)*C33) -> 0.83804732 | E35: Fórmula de Hamada.
A36: Tasa libre de riesgo | B36: =WACC!B5 -> 0.09517 | C36: ='Proyección Final Soriana'!B210 -> 0.09517 | E36: WACC!B5.
A37: Prima de riesgo de mercado | B37: =WACC!B8 -> 0.0423 | C37: ='Proyección Final Soriana'!B211 -> 0.0423 | E37: WACC!B8.
A38: Ke = Rf + βL × PRM | B38: =B36+B35*B37 -> 0.13020788 | C38: =C36+C35*C37 -> 0.1306194 | E38: CAPM.
A39: WACC del modelo | B39: =WACC!B33 -> 0.11919896 | C39: ='Proyección Final Soriana'!B126 -> 0.11345107 | E39: Mercado: WACC!B33 (punto de partida de la iteración). DCF: WACC final.
A40: Control: βL de esta hoja = βL del modelo | B40: =B35-WACC!B28 -> 0 | C40: =C35-'Proyección Final Soriana'!E219 -> 0 | E40: Debe ser 0.
A41: Referencia (NO usada): Ke con la βL de la industria 0.87 sin reapalancar | B41: =WACC!B5+B11*WACC!B8 -> 0.131971 | E41: Ignora la estructura de capital propia de Soriana; se muestra solo como comparación.
A43: 4. IMPACTO DEL CAMBIO DE BETA (escenario Base; valores registrados al recalcular el libro con cada beta, tabla A de Validación)
A44: Concepto | B44: βU heredada 0.80 | C44: βU Damodaran 0.65 | D44: Cambio | E44: Lectura
A45: βU | B45: =Validación!H8 -> 0.8 | C45: =Validación!F8 -> 0.65 | D45: =C45-B45 -> -0.15 | E45: Menor βU → menor βL y Ke → menor WACC → mayor EV y precio. El cambio no altera los flujos (FCF) ni el puente.
A46: βL iterada | B46: =Validación!H14 -> 1.0507612 | C46: =Validación!F14 -> 0.83804732 | D46: =C46-B46 -> -0.21271392
A47: Ke iterado | B47: =Validación!H13 -> 0.1396172 | C47: =Validación!F13 -> 0.1306194 | D47: =C47-B47 -> -0.0089977987
A48: WACC iterado | B48: =Validación!H12 -> 0.11870348 | C48: =Validación!F12 -> 0.11345107 | D48: =C48-B48 -> -0.0052524105
A49: WACC a valor de mercado | B49: =Validación!H15 -> 0.12500801 | C49: =Validación!F15 -> 0.11919896 | D49: =C49-B49 -> -0.0058090464
A50: Ke a valor de mercado | B50: =Validación!H16 -> 0.13829354 | C50: =Validación!F16 -> 0.13020788 | D50: =C50-B50 -> -0.0080856635
A51: EV ponderado al cierre 2025 (mdp) | B51: =Validación!H11 -> 65689.36 | C51: =Validación!F11 -> 68563.605 | D51: =C51-B51 -> 2874.2449
A52: Equity a la fecha de valuación (mdp) | B52: =Validación!H10 -> 55497.6 | C52: =Validación!F10 -> 58346.569 | D52: =C52-B52 -> 2848.9693
A53: Precio DCF (MXN) | B53: =Validación!H9 -> 30.832 | C53: =Validación!F9 -> 32.414761 | D53: =C53-B53 -> 1.5827607
A54: Precio combinado (MXN) | B54: =Validación!H19 -> 32.16242 | C54: =Validación!F19 -> 32.953801 | D54: =C54-B54 -> 0.79138036
A56: 5. COSTO DE LA DEUDA (Kd) — se conserva 10% con su fuente
A57: Kd antes de impuestos usado en la iteración (Proyección Final!C61) | B57: ='Proyección Final Soriana'!C61 -> 0.1 | E57: Fuente (comentario original de la celda C61): Encuesta Citi — tasa Banxico 6.50% a fin de 2026 y 2027 (imagenradio.com.mx, 22-sep-2026) y gastos financieros 1S26 de la hoja Datos.
A58: Control: intereses 1S26 anualizados / deuda total 2T26 | B58: =(Datos!E10+Datos!F10)*2/Datos!F29 -> 0.098648482 | E58: (588 + 582) × 2 / 23,720.6 (deuda bancaria + arrendamientos al 2T26).
A59: Diferencia | B59: =B57-B58 -> 0.0013515179 | E59: El 10% es consistente con el costo observado del 1S26.
A60: Referencia (NO usada): tasa implícita FY2025 = gastos financieros / deuda (WACC!B31) | B60: =WACC!B31 -> 0.13015497 | E60: Incluye intereses de deuda ya amortizada en 2025; solo alimenta el WACC a valor de mercado (punto de partida).

Sheet Trading Comps
A1: TRADING COMPS — múltiplos de empresas públicas comparables (metodología de clase: CIQ Valuations, diap. 4–9 y 20)
A2: Fuente: S&P Capital IQ, "MULTIPLOS DE SORIANA Y COMPETIDORES.xls" (Quick Comparable Analysis, plantilla Capital IQ Default Comps), as-of 30-Jun-2026, USD al tipo de cambio del día de exportación. Los múltiplos no tienen unidades; las métricas de Soriana son MXN (mdp) del Excel.
A3: Convención de colores: amarillo = dato o supuesto capturado (con fuente) · verde = vínculo a otra hoja o archivo fuente · azul = resultado clave · blanco = cálculo.
A5: 1. GRUPO COMPARABLE: datos CIQ y revisión de comparabilidad
A6: Empresa (CIQ) | B6: País | C6: Industria primaria (CIQ) | D6: Modelo de negocio | E6: TEV USD mm | F6: Ventas LTM USD mm | G6: Mg EBITDA | H6: Crec. ventas | I6: Deuda/ EBITDA | J6: Clasificación | K6: Incluir (1/0) | L6: Razón | M6: EV/Ventas LTM | N6: EV/EBITDA LTM | O6: EV/EBIT LTM | P6: P/U LTM | Q6: P/VL tangible | R6: EV/EBITDA NTM | S6: P/U NTM
A7: Grupo Comercial Chedraui, S.A.B. de C.V. (BMV:CHDRAUI B) | B7: Mexico | C7: Food Retail | D7: Autoservicio multiformato | E7: 7428.7 | F7: 16018.2 | G7: 0.064 | H7: -0.0335 | I7: 2.5 | J7: Incluir | K7: 1 | L7: Par más cercano: mismo formato y país; margen EBITDA (6.4%) y crecimiento (−3.4%) casi iguales a los de Soriana. | M7: 0.5 | N7: 5.7 | O7: 8.8 | P7: 13.1 | Q7: 2 | R7: 5.17 | S7: 11.18
A8: Grupo Mateus S.A. (BOVESPA:GMAT3) | B8: Brazil | C8: Consumer Staples Merchandise Retail | D8: Supermercados y mayoreo | E8: 2853.8 | F8: 8146.6 | G8: 0.059 | H8: 0.1871 | I8: 2.6 | J8: Incluir con reserva | K8: 1 | L8: Formato comparable; geografía (Brasil) y crecimiento (18.7%) distintos; P/U 4.7x atípico. | M8: 0.4 | N8: 5.3 | O8: 6.6 | P8: 4.7 | Q8: 0.8 | R8: 5.04 | S8: 6.32
A9: El Puerto de Liverpool, S.A.B. de C.V. (BMV:LIVEPOL C-1) | B9: Mexico | C9: Broadline Retail | D9: Departamentales + crédito + inmobiliario | E9: 9571.4 | F9: 12791.2 | G9: 0.142 | H9: 0.0304 | I9: 1.6 | J9: Excluir | K9: 0 | L9: Industria distinta (Broadline Retail); negocio financiero; margen EBITDA del doble (14.2%). | M9: 0.8 | N9: 4.9 | O9: 5.9 | P9: 8.2 | Q9: 0.8 | R9: 4.69 | S9: 6.29
A10: Wal-Mart de México, S.A.B. de C.V. (BMV:WALMEX *) | B10: Mexico | C10: Consumer Staples Merchandise Retail | D10: Autoservicio, descuento y club | E10: 52191.3 | F10: 56741.1 | G10: 0.096 | H10: 0.0287 | I10: 0.8 | J10: Incluir con reserva | K10: 1 | L10: Competidor directo; 12 veces el tamaño de Soriana y líder del mercado (prima de múltiplo). | M10: 0.9 | N10: 9.1 | O10: 12 | P10: 17.8 | Q10: 4.3 | R10: 8.52 | S10: 16.13
A11: La Comer, S.A.B. de C.V. (BMV:LACOMER UBC) | B11: Mexico | C11: Food Retail | D11: Autoservicio premium | E11: 2140.3 | F11: 2735.8 | G11: 0.1 | H11: 0.086 | I11: 0.5 | J11: Incluir con reserva | K11: 1 | L11: Competidor directo; más pequeña, formato premium, más rentable (10.0%) y sin deuda neta. | M11: 0.8 | N11: 7.4 | O11: 10.7 | P11: 14.6 | Q11: 1.4 | R11: 7.07 | S11: 13.9
A12: Sendas Distribuidora S.A. (BOVESPA:ASAI3) | B12: Brazil | C12: Consumer Staples Merchandise Retail | D12: Mayoreo cash & carry | E12: 6909.1 | F12: 15576.1 | G12: 0.078 | H12: 0.0169 | I12: 4 | J12: Incluir con reserva | K12: 1 | L12: Formato comparable a City Club; Brasil; apalancamiento alto (4.0x) distorsiona P/U. | M12: 0.4 | N12: 5.5 | O12: 7.6 | P12: 16.8 | Q12: 17.1 | R12: 4.77 | S12: 11.68
A13: Cencosud S.A. (SNSE:CENCOSUD) | B13: Chile | C13: Consumer Staples Merchandise Retail | D13: Supermercados + mejoramiento del hogar + departamentales + centros comerciales | E13: 11831.7 | F13: 17028 | G13: 0.056 | H13: -0.016 | I13: 5.1 | J13: Incluir con reserva | K13: 1 | L13: Diversificada (Chile); EBITDA LTM −29.5% infla EV/EBITDA y EV/EBIT. | M13: 0.7 | N13: 9.3 | O13: 14 | P13: 21 | Q13: 2.7 | R13: 6.88 | S13: 15.27
A14: InRetail Perú Corp. (BVL:INRETC1) | B14: Peru | C14: Consumer Staples Merchandise Retail | D14: Supermercados, farmacias, centros comerciales | E14: 6092.8 | F14: 6992.8 | G14: 0.11 | H14: 0.0785 | I14: 3.2 | J14: Incluir con reserva | K14: 1 | L14: Multiformato (Perú) con negocios no comparables (farmacia, inmobiliario). | M14: 0.9 | N14: 7 | O14: 10 | P14: 13.6 | Q14: 4.2 | R14: 6.49 | S14: 13.1
A15: Fomento Económico Mexicano, S.A.B. de C.V. (BMV:FEMSA UBD) | B15: Mexico | C15: Soft Drinks and Non-alcoholic Beverages | D15: Embotellador Coca-Cola + OXXO + salud + combustible | E15: 49954.9 | F15: 48576.5 | G15: 0.118 | H15: 0.0745 | I15: 2.1 | J15: Excluir | K15: 0 | L15: Industria distinta (Soft Drinks); P/U 25.9x. | M15: 1.1 | N15: 7.5 | O15: 11.1 | P15: 25.9 | Q15: 11.6 | R15: 6.58 | S15: 20.88
A16: Falabella S.A. (SNSE:FALABELLA) | B16: Chile | C16: Broadline Retail | D16: Departamentales, mejoramiento del hogar, banca | E16: 20976.5 | F16: 14289.2 | G16: 0.127 | H16: 0.0894 | I16: 3 | J16: Excluir | K16: 0 | L16: Industria distinta (Broadline Retail); negocio financiero. | M16: 1.5 | N16: 10.4 | O16: 12.8 | P16: 10.4 | Q16: 2 | R16: 9.77 | S16: 18.33
A17: Organización Soriana, S. A. B. de C. V. (BMV:SORIANA B) — empresa objetivo (no forma parte de la muestra) | E17: 4103.2 | F17: 9502.5 | G17: 0.064 | H17: -0.0293 | I17: 2 | M17: 0.4 | N17: 6.3 | O17: 9.9 | P17: 15.7 | Q17: 0.8 | R17: 6.53 | S17: 15.08
A18: Industria primaria CIQ: hoja Credit Health Panel. Múltiplos: hoja Trading Multiples (publicados por CIQ, 1–2 decimales). No se recalculan: el EBITDA de la hoja Financial Data no reproduce el múltiplo LTM publicado (p. ej., Chedraui 7.24x vs 5.7x); el múltiplo publicado de Soriana (6.3x) es consistente con el EBITDA reportado con arrendamientos (~11,900 mdp), el mismo del Excel.
A20: Control de transcripción: media de CIQ (10 empresas, hoja Trading Multiples, fila Mean) | M20: 0.8 | N20: 7.2 | O20: 10 | P20: 14.6 | Q20: 4.7 | R20: 6.5 | S20: 13.31
A21: Media recalculada de los 10 múltiplos publicados | M21: =AVERAGE(M7:M16) -> 0.8 | N21: =AVERAGE(N7:N16) -> 7.21 | O21: =AVERAGE(O7:O16) -> 9.95 | P21: =AVERAGE(P7:P16) -> 14.61 | Q21: =AVERAGE(Q7:Q16) -> 4.69 | R21: =AVERAGE(R7:R16) -> 6.498 | S21: =AVERAGE(S7:S16) -> 13.308
A24: 2. MÉTRICAS DE SORIANA (MXN, LTM 3T25–2T26 = mismo corte que el as-of de CIQ) Y PUENTE EV → CAPITAL AL 2T26
A25: Ventas LTM (mdp) | B25: =SUM(Datos!C6:F6) -> 174278 | C25: Datos!C6:F6
A26: EBIT LTM (mdp) | B26: =SUM(Datos!C9:F9) -> 7631 | C26: Datos!C9:F9
A27: D&A LTM (mdp) | B27: =SUM(Datos!C14:F14) -> 4179.871 | C27: Datos!C14:F14
A28: EBITDA LTM (mdp) = EBIT + D&A | B28: =B26+B27 -> 11810.871 | C28: Cálculo (mismo EBITDA que el Excel: incluye D&A de arrendamientos)
A29: Utilidad neta LTM (mdp) | B29: =SUM(Datos!C13:F13) -> 3816 | C29: Datos!C13:F13
A30: Acciones en circulación (millones) | B30: =WACC!B17 -> 1800 | C30: WACC!B17
A31: UPA LTM (MXN) | B31: =B29/B30 -> 2.12 | C31: Cálculo
A32: (+) Efectivo y equivalentes 2T26 | B32: =Datos!F17 -> 6875.384 | C32: Datos!F17
A33: (−) Deuda bursátil y bancaria 2T26 | B33: =-(Datos!F25+Datos!F26) -> -11500 | C33: Datos!F25:F26
A34: (−) Pasivo por arrendamiento 2T26 | B34: =-(Datos!F27+Datos!F28) -> -12220.588 | C34: Datos!F27:F28 (arrendamientos como deuda, igual que el DCF y el TEV de CIQ)
A35: (−) Interés minoritario | B35: 0 | C35: NA en MXN: no está en el Excel. CIQ reporta 8.4 USD mm (≈0.3% del capital); convertirlo requeriría un tipo de cambio sin fuente. Se omite, igual que en el puente del DCF.
A36: (−) Capital preferente | B36: 0 | C36: Soriana no tiene capital preferente (CIQ: "-")
A37: Ajuste neto EV → capital (mdp) | B37: =SUM(B32:B36) -> -16845.204 | C37: Diap. 7: caja + inversiones CP − deuda − minoritarios − preferentes
A40: 3. MÚLTIPLOS: selección (NM = calculable pero sin utilidad analítica · NA = falta el dato)
A41: Múltiplo | B41: Tipo | C41: Métrica de Soriana | D41: Usar (1/0) | E41: Estado | F41: Justificación
A42: EV/EBITDA LTM | B42: EV | C42: =$B$28 -> 11810.871 | D42: 1 | E42: Usado | F42: Múltiplo central de retail; EBITDA comparable (con arrendamientos).
A43: EV/EBIT LTM | B43: EV | C43: =$B$26 -> 7631 | D43: 1 | E43: Usado | F43: Incorpora la intensidad de capital (D&A).
A44: P/U LTM | B44: P | C44: =$B$31 -> 2.12 | D44: 1 | E44: Usado | F44: Múltiplo de precio sobre UPA diluida (CIQ "P/Diluted EPS Before Extra").
A45: EV/Ventas LTM | B45: EV | C45: =$B$25 -> 174278 | D45: 0 | E45: Excluido | F45: No es NM ni NA: se excluye porque ignora el margen; los pares van de 5.6% a 11.0% de margen EBITDA y Soriana es de los más bajos, lo que sobrevaloraría el resultado.
A46: P/VL tangible | B46: P | C46: NA | D46: 0 | E46: NA | F46: El valor en libros tangible por acción de Soriana en MXN no está en el Excel; además el valor contable no explica el valor en retail (Sendas 17.1x).
A47: EV/EBITDA NTM | B47: EV | C47: NA | D47: 0 | E47: NA | F47: No existe EBITDA NTM de consenso para Soriana en MXN (CIQ lo da en USD; convertirlo requiere un tipo de cambio sin fuente).
A48: P/U NTM | B48: P | C48: NA | D48: 0 | E48: NA | F48: Ídem: UPA NTM de consenso solo en USD.
A51: 4. ESTADÍSTICOS DE LA MUESTRA (solo empresas con Incluir = 1) Y PRECIO IMPLÍCITO POR ACCIÓN (MXN)
A52: Muestra filtrada (helper): múltiplo si Incluir = 1, vacío si no
A53: Empresa | B53: EV/Ventas | C53: EV/EBITDA | D53: EV/EBIT | E53: P/U
A54: =A7 -> Grupo Comercial Chedraui, S.A.B. de C.V. (BMV:CHDRAUI B) | B54: =IF(AND($K$7=1,ISNUMBER(M7)),M7,"") -> 0.5 | C54: =IF(AND($K$7=1,ISNUMBER(N7)),N7,"") -> 5.7 | D54: =IF(AND($K$7=1,ISNUMBER(O7)),O7,"") -> 8.8 | E54: =IF(AND($K$7=1,ISNUMBER(P7)),P7,"") -> 13.1
A55: =A8 -> Grupo Mateus S.A. (BOVESPA:GMAT3) | B55: =IF(AND($K$8=1,ISNUMBER(M8)),M8,"") -> 0.4 | C55: =IF(AND($K$8=1,ISNUMBER(N8)),N8,"") -> 5.3 | D55: =IF(AND($K$8=1,ISNUMBER(O8)),O8,"") -> 6.6 | E55: =IF(AND($K$8=1,ISNUMBER(P8)),P8,"") -> 4.7
A56: =A9 -> El Puerto de Liverpool, S.A.B. de C.V. (BMV:LIVEPOL C-1) | B56: =IF(AND($K$9=1,ISNUMBER(M9)),M9,"") | C56: =IF(AND($K$9=1,ISNUMBER(N9)),N9,"") | D56: =IF(AND($K$9=1,ISNUMBER(O9)),O9,"") | E56: =IF(AND($K$9=1,ISNUMBER(P9)),P9,"")
A57: =A10 -> Wal-Mart de México, S.A.B. de C.V. (BMV:WALMEX *) | B57: =IF(AND($K$10=1,ISNUMBER(M10)),M10,"") -> 0.9 | C57: =IF(AND($K$10=1,ISNUMBER(N10)),N10,"") -> 9.1 | D57: =IF(AND($K$10=1,ISNUMBER(O10)),O10,"") -> 12 | E57: =IF(AND($K$10=1,ISNUMBER(P10)),P10,"") -> 17.8
A58: =A11 -> La Comer, S.A.B. de C.V. (BMV:LACOMER UBC) | B58: =IF(AND($K$11=1,ISNUMBER(M11)),M11,"") -> 0.8 | C58: =IF(AND($K$11=1,ISNUMBER(N11)),N11,"") -> 7.4 | D58: =IF(AND($K$11=1,ISNUMBER(O11)),O11,"") -> 10.7 | E58: =IF(AND($K$11=1,ISNUMBER(P11)),P11,"") -> 14.6
A59: =A12 -> Sendas Distribuidora S.A. (BOVESPA:ASAI3) | B59: =IF(AND($K$12=1,ISNUMBER(M12)),M12,"") -> 0.4 | C59: =IF(AND($K$12=1,ISNUMBER(N12)),N12,"") -> 5.5 | D59: =IF(AND($K$12=1,ISNUMBER(O12)),O12,"") -> 7.6 | E59: =IF(AND($K$12=1,ISNUMBER(P12)),P12,"") -> 16.8
A60: =A13 -> Cencosud S.A. (SNSE:CENCOSUD) | B60: =IF(AND($K$13=1,ISNUMBER(M13)),M13,"") -> 0.7 | C60: =IF(AND($K$13=1,ISNUMBER(N13)),N13,"") -> 9.3 | D60: =IF(AND($K$13=1,ISNUMBER(O13)),O13,"") -> 14 | E60: =IF(AND($K$13=1,ISNUMBER(P13)),P13,"") -> 21
A61: =A14 -> InRetail Perú Corp. (BVL:INRETC1) | B61: =IF(AND($K$14=1,ISNUMBER(M14)),M14,"") -> 0.9 | C61: =IF(AND($K$14=1,ISNUMBER(N14)),N14,"") -> 7 | D61: =IF(AND($K$14=1,ISNUMBER(O14)),O14,"") -> 10 | E61: =IF(AND($K$14=1,ISNUMBER(P14)),P14,"") -> 13.6
A62: =A15 -> Fomento Económico Mexicano, S.A.B. de C.V. (BMV:FEMSA UBD) | B62: =IF(AND($K$15=1,ISNUMBER(M15)),M15,"") | C62: =IF(AND($K$15=1,ISNUMBER(N15)),N15,"") | D62: =IF(AND($K$15=1,ISNUMBER(O15)),O15,"") | E62: =IF(AND($K$15=1,ISNUMBER(P15)),P15,"")
A63: =A16 -> Falabella S.A. (SNSE:FALABELLA) | B63: =IF(AND($K$16=1,ISNUMBER(M16)),M16,"") | C63: =IF(AND($K$16=1,ISNUMBER(N16)),N16,"") | D63: =IF(AND($K$16=1,ISNUMBER(O16)),O16,"") | E63: =IF(AND($K$16=1,ISNUMBER(P16)),P16,"")
A65: Estadístico (múltiplo) | B65: EV/Ventas | C65: EV/EBITDA | D65: EV/EBIT | E65: P/U | G65: Precio: EV/Ventas | H65: Precio: EV/EBITDA | I65: Precio: EV/EBIT | J65: Precio: P/U
A66: Mínimo | B66: =MIN(B54:B63) -> 0.4 | C66: =MIN(C54:C63) -> 5.3 | D66: =MIN(D54:D63) -> 6.6 | E66: =MIN(E54:E63) -> 4.7 | G66: =IF(B66*$B$25+$B$37>0,(B66*$B$25+$B$37)/$B$30,"NM") -> 29.369998 | H66: =IF(C66*$B$28+$B$37>0,(C66*$B$28+$B$37)/$B$30,"NM") -> 25.418007 | I66: =IF(D66*$B$26+$B$37>0,(D66*$B$26+$B$37)/$B$30,"NM") -> 18.621887 | J66: =IF(E66*$B$31>0,E66*$B$31,"NM") -> 9.964
A67: Percentil 25 | B67: =PERCENTILE(B54:B63,0.25) -> 0.45 | C67: =PERCENTILE(C54:C63,0.25) -> 5.6 | D67: =PERCENTILE(D54:D63,0.25) -> 8.2 | E67: =PERCENTILE(E54:E63,0.25) -> 13.35 | G67: =IF(B67*$B$25+$B$37>0,(B67*$B$25+$B$37)/$B$30,"NM") -> 34.211053 | H67: =IF(C67*$B$28+$B$37>0,(C67*$B$28+$B$37)/$B$30,"NM") -> 27.386485 | I67: =IF(D67*$B$26+$B$37>0,(D67*$B$26+$B$37)/$B$30,"NM") -> 25.404998 | J67: =IF(E67*$B$31>0,E67*$B$31,"NM") -> 28.302
A68: Media | B68: =AVERAGE(B54:B63) -> 0.65714286 | C68: =AVERAGE(C54:C63) -> 7.0428571 | D68: =AVERAGE(D54:D63) -> 9.9571429 | E68: =AVERAGE(E54:E63) -> 14.514286 | G68: =IF(B68*$B$25+$B$37>0,(B68*$B$25+$B$37)/$B$30,"NM") -> 54.266855 | H68: =IF(C68*$B$28+$B$37>0,(C68*$B$28+$B$37)/$B$30,"NM") -> 36.85393 | I68: =IF(D68*$B$26+$B$37>0,(D68*$B$26+$B$37)/$B$30,"NM") -> 32.854307 | J68: =IF(E68*$B$31>0,E68*$B$31,"NM") -> 30.770286
A69: Mediana | B69: =MEDIAN(B54:B63) -> 0.7 | C69: =MEDIAN(C54:C63) -> 7 | D69: =MEDIAN(D54:D63) -> 10 | E69: =MEDIAN(E54:E63) -> 14.6 | G69: =IF(B69*$B$25+$B$37>0,(B69*$B$25+$B$37)/$B$30,"NM") -> 58.416331 | H69: =IF(C69*$B$28+$B$37>0,(C69*$B$28+$B$37)/$B$30,"NM") -> 36.572718 | I69: =IF(D69*$B$26+$B$37>0,(D69*$B$26+$B$37)/$B$30,"NM") -> 33.035998 | J69: =IF(E69*$B$31>0,E69*$B$31,"NM") -> 30.952
A70: Percentil 75 | B70: =PERCENTILE(B54:B63,0.75) -> 0.85 | C70: =PERCENTILE(C54:C63,0.75) -> 8.25 | D70: =PERCENTILE(D54:D63,0.75) -> 11.35 | E70: =PERCENTILE(E54:E63,0.75) -> 17.3 | G70: =IF(B70*$B$25+$B$37>0,(B70*$B$25+$B$37)/$B$30,"NM") -> 72.939498 | H70: =IF(C70*$B$28+$B$37>0,(C70*$B$28+$B$37)/$B$30,"NM") -> 44.774712 | I70: =IF(D70*$B$26+$B$37>0,(D70*$B$26+$B$37)/$B$30,"NM") -> 38.759248 | J70: =IF(E70*$B$31>0,E70*$B$31,"NM") -> 36.676
A71: Máximo | B71: =MAX(B54:B63) -> 0.9 | C71: =MAX(C54:C63) -> 9.3 | D71: =MAX(D54:D63) -> 14 | E71: =MAX(E54:E63) -> 21 | G71: =IF(B71*$B$25+$B$37>0,(B71*$B$25+$B$37)/$B$30,"NM") -> 77.780553 | H71: =IF(C71*$B$28+$B$37>0,(C71*$B$28+$B$37)/$B$30,"NM") -> 51.664387 | I71: =IF(D71*$B$26+$B$37>0,(D71*$B$26+$B$37)/$B$30,"NM") -> 49.993776 | J71: =IF(E71*$B$31>0,E71*$B$31,"NM") -> 44.52
A72: n | B72: =COUNT(B54:B63) -> 7 | C72: =COUNT(C54:C63) -> 7 | D72: =COUNT(D54:D63) -> 7 | E72: =COUNT(E54:E63) -> 7
A73: Precio implícito (múltiplos EV) = (múltiplo × métrica + ajuste neto) ÷ acciones; (múltiplos de precio) = múltiplo × UPA. "NM" si el capital implícito es ≤ 0 (diap. 20). Percentiles con interpolación inclusiva (convención del ejemplo de clase, diap. 8).
A75: Detalle a la MEDIA | B75: EV/Ventas | C75: EV/EBITDA | D75: EV/EBIT | E75: P/U
A76: Métrica de Soriana (mdp o MXN/acción) | B76: =$B$25 -> 174278 | C76: =$B$28 -> 11810.871 | D76: =$B$26 -> 7631 | E76: =$B$31 -> 2.12
A77: EV implícito (mdp) | B77: =B68*$B$25 -> 114525.54 | C77: =C68*$B$28 -> 83182.277 | D77: =D68*$B$26 -> 75982.957 | E77: n.a. (múltiplo de precio)
A78: Equity Value implícito (mdp) | B78: =B77+$B$37 -> 97680.339 | C78: =C77+$B$37 -> 66337.073 | D78: =D77+$B$37 -> 59137.753 | E78: =E68*$B$31*$B$30 -> 55386.514
A79: Precio implícito (MXN/acción) | B79: =G68 -> 54.266855 | C79: =H68 -> 36.85393 | D79: =I68 -> 32.854307 | E79: =J68 -> 30.770286
A82: 5. VALOR DE TRADING COMPS (regla de clase, diap. 9: promedio simple de los precios implícitos con la MEDIA de cada múltiplo usado)
A83: TRADING COMPS — precio por acción (MXN) | B83: =IF((IF(AND($D$45=1,ISNUMBER(G68)),1,0)+IF(AND($D$42=1,ISNUMBER(H68)),1,0)+IF(AND($D$43=1,ISNUMBER(I68)),1,0)+IF(AND($D$44=1,ISNUMBER(J68)),1,0))=0,"NA",(IF(AND($D$45=1,ISNUMBER(G68)),G68,0)+IF(AND($D$42=1,ISNUMBER(H68)),H68,0)+IF(AND($D$43=1,ISNUMBER(I68)),I68,0)+IF(AND($D$44=1,ISNUMBER(J68)),J68,0))/(IF(AND($D$45=1,ISNUMBER(G68)),1,0)+IF(AND($D$42=1,ISNUMBER(H68)),1,0)+IF(AND($D$43=1,ISNUMBER(I68)),1,0)+IF(AND($D$44=1,ISNUMBER(J68)),1,0))) -> 33.492841
A84: Rango P25 (promedio de precios a P25 de los múltiplos usados) | B84: =IF((IF(AND($D$45=1,ISNUMBER(G67)),1,0)+IF(AND($D$42=1,ISNUMBER(H67)),1,0)+IF(AND($D$43=1,ISNUMBER(I67)),1,0)+IF(AND($D$44=1,ISNUMBER(J67)),1,0))=0,"NA",(IF(AND($D$45=1,ISNUMBER(G67)),G67,0)+IF(AND($D$42=1,ISNUMBER(H67)),H67,0)+IF(AND($D$43=1,ISNUMBER(I67)),I67,0)+IF(AND($D$44=1,ISNUMBER(J67)),J67,0))/(IF(AND($D$45=1,ISNUMBER(G67)),1,0)+IF(AND($D$42=1,ISNUMBER(H67)),1,0)+IF(AND($D$43=1,ISNUMBER(I67)),1,0)+IF(AND($D$44=1,ISNUMBER(J67)),1,0))) -> 27.031161
A85: Rango P75 (promedio de precios a P75 de los múltiplos usados) | B85: =IF((IF(AND($D$45=1,ISNUMBER(G70)),1,0)+IF(AND($D$42=1,ISNUMBER(H70)),1,0)+IF(AND($D$43=1,ISNUMBER(I70)),1,0)+IF(AND($D$44=1,ISNUMBER(J70)),1,0))=0,"NA",(IF(AND($D$45=1,ISNUMBER(G70)),G70,0)+IF(AND($D$42=1,ISNUMBER(H70)),H70,0)+IF(AND($D$43=1,ISNUMBER(I70)),I70,0)+IF(AND($D$44=1,ISNUMBER(J70)),J70,0))/(IF(AND($D$45=1,ISNUMBER(G70)),1,0)+IF(AND($D$42=1,ISNUMBER(H70)),1,0)+IF(AND($D$43=1,ISNUMBER(I70)),1,0)+IF(AND($D$44=1,ISNUMBER(J70)),1,0))) -> 40.069987
A86: Precio de mercado de referencia (MXN) | B86: =Valuación!B42 -> 33.48
A87: Potencial vs. precio | B87: =B83/B86-1 -> 0.00038353807
A88: Número de múltiplos usados | B88: =SUM(D42:D45) -> 3
A89: Fecha del valor: precios de mercado de los pares al 30-jun-2026 (as-of CIQ) y puente al 2T26. No se lleva a la fecha de valuación del DCF (01-oct-2026): la metodología de clase no lo prevé; la diferencia de fechas queda documentada.

Sheet Precedent Transactions
A1: PRECEDENT TRANSACTIONS — múltiplos de operaciones de M&A (metodología de clase: CIQ Valuations, diap. 10–11 y 20)
A2: Fuente: S&P Capital IQ, "TRANSACCIONES INDUSTRIA RETAIL.xls" (Comparable M&A Transactions para Soriana). TEV y tamaño en MXN mm; múltiplos implícitos de la transacción (publicados con 1 decimal).
A3: Convención de colores: amarillo = dato o supuesto capturado (con fuente) · verde = vínculo a otra hoja o archivo fuente · azul = resultado clave · blanco = cálculo.
A5: 1. PARÁMETROS DE SELECCIÓN (diap. 10)
A6: Fecha de valuación | C6: ='Proyección Final Soriana'!B252 -> 46296
A7: Ventana (años) | C7: 3 | D7: Diap. 10: "últimos tres años".
A8: Inicio de la ventana | C8: =EDATE(C6,-12*C7) -> 45200
A9: Geografía de la empresa objetivo | C9: México | D9: Diap. 10: "misma geografía". La ampliación de industria y luego global requiere otra búsqueda en CIQ, que no está disponible; no se inventan operaciones.
A10: Mínimo de múltiplos por operación | C10: 2 | D10: Diap. 10: "al menos dos múltiplos de valor".
A12: 2. OPERACIONES (datos CIQ) Y EVALUACIÓN DE CRITERIOS
A13: Anunciada | B13: ID CIQ | C13: Objetivo | D13: Comprador | E13: Vendedor | F13: TEV objetivo (MXN mm) | G13: Tamaño (MXN mm) | H13: EV/Ventas | I13: EV/EBITDA | J13: País del objetivo | K13: ¿Ventana? | L13: ¿Geografía? | M13: ¿≥2 múltiplos? | N13: ¿Control? | O13: Incluir (1/0) | P13: Observaciones | Q13: Industria del objetivo
A14: 45215 | B14: IQTR1859160803 | C14: Almacenes Éxito S.A. | D14: Super Selectos El Salvador | E14: Casino, Guichard-Perrachon S.A., Companhia Brasileira De Distribuicao, GÉAnt International B.V., Segisor S.A.S., Helicco Participações Ltda., GPA 2 Empreendimentos E Participacoes LTDA. | F14: 56675.3 | G14: 35348.1 | H14: 0.3 | I14: 5.2 | J14: Colombia | K14: =IF(A14>=$C$8,"Sí","No") -> Sí | L14: =IF(J14=$C$9,"Sí","No") -> No | M14: =IF(COUNT(H14:I14)>=$C$10,"Sí","No") -> Sí | N14: Sí | O14: 1 | P14: Oferta por el control de Éxito; varios vendedores del grupo Casino. Única operación dentro de la ventana (por 15 días). | Q14: Supermercados / autoservicio (Grupo Éxito)
A15: 43657 | B15: IQTR629442326 | C15: InRetail Perú Corp. | D15: - | E15: Nexus Group | F15: 116983.8 | G15: 4590.5 | H15: 1.5 | I15: 11.4 | J15: Perú | K15: =IF(A15>=$C$8,"Sí","No") -> No | L15: =IF(J15=$C$9,"Sí","No") -> No | M15: =IF(COUNT(H15:I15)>=$C$10,"Sí","No") -> Sí | N15: Dudoso | O15: 1 | P15: Comprador no identificado; tamaño 4,590 = 3.9% del TEV → probable venta minoritaria o secundaria, no de control. Fuera de la ventana. | Q15: Supermercados, farmacias y centros comerciales
A16: 43642 | B16: IQTR626096522 | C16: Almacenes Éxito S.A. | D16: Sendas Distribuidora S.A. | E16: Casino, Guichard-Perrachon S.A. | F16: 56675.3 | G16: 130645 | H16: 0.4 | I16: 6.3 | J16: Colombia | K16: =IF(A16>=$C$8,"Sí","No") -> No | L16: =IF(J16=$C$9,"Sí","No") -> No | M16: =IF(COUNT(H16:I16)>=$C$10,"Sí","No") -> Sí | N16: Dudoso | O16: 1 | P16: Vendedor Casino y comprador Sendas, ambos del grupo Casino según los datos → posible reestructura intra-grupo. Tamaño 130,645 > TEV 56,675 (dato inconsistente). Fuera de la ventana. | Q16: Supermercados / autoservicio (Grupo Éxito)
A17: Resumen CIQ del export (control) | H17: 0.7 | I17: 7.6 | J17: Media publicada (export, fila Mean)
A18: País del objetivo: dato público de las empresas (Almacenes Éxito, Colombia; InRetail Perú, Perú); el export CIQ no lo incluye. Incluir = 1 en las tres por decisión del proyecto ("usar las tres transacciones disponibles"), con sus limitaciones documentadas.
A20: Cumplen la ventana | C20: =COUNTIF(K14:K16,"Sí")&" de "&COUNTA(B14:B16) -> 1 de 3
A21: Cumplen la geografía | C21: =COUNTIF(L14:L16,"Sí")&" de "&COUNTA(B14:B16) -> 0 de 3
A22: Operaciones de control claras | C22: =COUNTIF(N14:N16,"Sí")&" de "&COUNTA(B14:B16) -> 1 de 3
A23: Margen EBITDA implícito del objetivo (EV/Ventas ÷ EV/EBITDA) | C23: =H14/I14 -> 0.057692308 | D23: =H15/I15 -> 0.13157895 | E23: =H16/I16 -> 0.063492063
A25: 3. ESTADÍSTICOS (operaciones con Incluir = 1) Y PRECIO IMPLÍCITO (mismo puente al 2T26 que Trading Comps)
A26: Muestra filtrada (helper)
A27: =C14 -> Almacenes Éxito S.A. | H27: =IF($O$14=1,H14,"") -> 0.3 | I27: =IF($O$14=1,I14,"") -> 5.2
A28: =C15 -> InRetail Perú Corp. | H28: =IF($O$15=1,H15,"") -> 1.5 | I28: =IF($O$15=1,I15,"") -> 11.4
A29: =C16 -> Almacenes Éxito S.A. | H29: =IF($O$16=1,H16,"") -> 0.4 | I29: =IF($O$16=1,I16,"") -> 6.3
A31: Estadístico | H31: EV/Ventas | I31: EV/EBITDA | J31: Precio EV/Ventas | K31: Precio EV/EBITDA
A32: Mínimo | H32: =MIN(H27:H29) -> 0.3 | I32: =MIN(I27:I29) -> 5.2 | J32: =IF(H32*'Trading Comps'!$B$25+'Trading Comps'!$B$37>0,(H32*'Trading Comps'!$B$25+'Trading Comps'!$B$37)/'Trading Comps'!$B$30,"NM") -> 19.687887 | K32: =IF(I32*'Trading Comps'!$B$28+'Trading Comps'!$B$37>0,(I32*'Trading Comps'!$B$28+'Trading Comps'!$B$37)/'Trading Comps'!$B$30,"NM") -> 24.761847
A33: Percentil 25 | H33: =PERCENTILE(H27:H29,0.25) -> 0.35 | I33: =PERCENTILE(I27:I29,0.25) -> 5.75 | J33: =IF(H33*'Trading Comps'!$B$25+'Trading Comps'!$B$37>0,(H33*'Trading Comps'!$B$25+'Trading Comps'!$B$37)/'Trading Comps'!$B$30,"NM") -> 24.528942 | K33: =IF(I33*'Trading Comps'!$B$28+'Trading Comps'!$B$37>0,(I33*'Trading Comps'!$B$28+'Trading Comps'!$B$37)/'Trading Comps'!$B$30,"NM") -> 28.370725
A34: Media | H34: =AVERAGE(H27:H29) -> 0.73333333 | I34: =AVERAGE(I27:I29) -> 7.6333333 | J34: =IF(H34*'Trading Comps'!$B$25+'Trading Comps'!$B$37>0,(H34*'Trading Comps'!$B$25+'Trading Comps'!$B$37)/'Trading Comps'!$B$30,"NM") -> 61.643701 | K34: =IF(I34*'Trading Comps'!$B$28+'Trading Comps'!$B$37>0,(I34*'Trading Comps'!$B$28+'Trading Comps'!$B$37)/'Trading Comps'!$B$30,"NM") -> 40.728395
A35: Mediana | H35: =MEDIAN(H27:H29) -> 0.4 | I35: =MEDIAN(I27:I29) -> 6.3 | J35: =IF(H35*'Trading Comps'!$B$25+'Trading Comps'!$B$37>0,(H35*'Trading Comps'!$B$25+'Trading Comps'!$B$37)/'Trading Comps'!$B$30,"NM") -> 29.369998 | K35: =IF(I35*'Trading Comps'!$B$28+'Trading Comps'!$B$37>0,(I35*'Trading Comps'!$B$28+'Trading Comps'!$B$37)/'Trading Comps'!$B$30,"NM") -> 31.979602
A36: Percentil 75 | H36: =PERCENTILE(H27:H29,0.75) -> 0.95 | I36: =PERCENTILE(I27:I29,0.75) -> 8.85 | J36: =IF(H36*'Trading Comps'!$B$25+'Trading Comps'!$B$37>0,(H36*'Trading Comps'!$B$25+'Trading Comps'!$B$37)/'Trading Comps'!$B$30,"NM") -> 82.621609 | K36: =IF(I36*'Trading Comps'!$B$28+'Trading Comps'!$B$37>0,(I36*'Trading Comps'!$B$28+'Trading Comps'!$B$37)/'Trading Comps'!$B$30,"NM") -> 48.711669
A37: Máximo | H37: =MAX(H27:H29) -> 1.5 | I37: =MAX(I27:I29) -> 11.4 | J37: =IF(H37*'Trading Comps'!$B$25+'Trading Comps'!$B$37>0,(H37*'Trading Comps'!$B$25+'Trading Comps'!$B$37)/'Trading Comps'!$B$30,"NM") -> 135.87322 | K37: =IF(I37*'Trading Comps'!$B$28+'Trading Comps'!$B$37>0,(I37*'Trading Comps'!$B$28+'Trading Comps'!$B$37)/'Trading Comps'!$B$30,"NM") -> 65.443736
A38: n | H38: =COUNT(H27:H29) -> 3 | I38: =COUNT(I27:I29) -> 3
A41: Detalle a la MEDIA | H41: EV/Ventas | I41: EV/EBITDA
A42: Múltiplo (media de la muestra) | H42: =H34 -> 0.73333333 | I42: =I34 -> 7.6333333
A43: Métrica de Soriana (mdp, LTM) | H43: ='Trading Comps'!$B$25 -> 174278 | I43: ='Trading Comps'!$B$28 -> 11810.871
A44: EV implícito (mdp) | H44: =H42*H43 -> 127803.87 | I44: =I42*I43 -> 90156.315
A45: (+/−) Ajuste neto EV → capital (mdp) | H45: ='Trading Comps'!$B$37 -> -16845.204 | I45: ='Trading Comps'!$B$37 -> -16845.204
A46: Equity Value implícito (mdp) | H46: =H44+H45 -> 110958.66 | I46: =I44+I45 -> 73311.111
A47: Precio implícito (MXN/acción) | H47: =J34 -> 61.643701 | I47: =K34 -> 40.728395
A49: 4. VALOR DE PRECEDENT TRANSACTIONS (método de REFERENCIA — muestra no defendible)
A50: Múltiplo | C50: Usar (1/0) | D50: Estado | E50: Justificación
A51: EV/EBITDA | C51: 1 | D51: Usado | E51: Mismo criterio que Trading Comps.
A52: EV/Ventas | C52: 0 | D52: Excluido | E52: Mismo criterio que Trading Comps: ignora el margen; los márgenes implícitos de los objetivos van de 5.8% a 13.2% (fila de margen implícito).
A54: PRECEDENT TRANSACTIONS — precio por acción (MXN) | E54: =IF((C51+C52)=0,"NA",(IF(C51=1,K34,0)+IF(C52=1,J34,0))/(C51+C52)) -> 40.728395
A55: Rango (mín–máx del EV/EBITDA) | E55: =K32 -> 24.761847 | F55: =K37 -> 65.443736
A57: ADVERTENCIA: solo 1 de 3 operaciones cumple la ventana de 3 años, ninguna la geografía, y 2 tienen carácter de control dudoso. Con n = 3 (o n = 1 dentro de la ventana) el resultado no es estadísticamente defendible. El método se calcula y se muestra como referencia, con peso 0% en la valuación combinada (decisión del proyecto). Las transacciones de control incluyen una prima de control (diap. 11, nota).

Sheet Valuación Combinada
A1: VALUACIÓN COMBINADA — DCF + Trading Comps + Precedent Transactions (metodología de clase, diap. 3 y 18)
A2: Precio combinado = Σ (peso × precio del método) / Σ pesos. Pesos visibles y editables (celdas amarillas).
A3: Convención de colores: amarillo = dato o supuesto capturado (con fuente) · verde = vínculo a otra hoja o archivo fuente · azul = resultado clave · blanco = cálculo.
A5: Método | B5: Precio por acción (MXN) | C5: Peso aplicado | D5: Peso regla de clase | E5: Contribución | F5: Origen del precio y del peso | G5: ¿Contribuye?
A6: DCF (ValuFlow, precio objetivo a la fecha de valuación) | B6: ='Proyección Final Soriana'!B265 -> 32.414761 | C6: 0.5 | D6: =1/3 -> 0.33333333 | E6: =IF(ISNUMBER(B6),B6*C6,0) -> 16.20738 | F6: Proyección Final Soriana!B265. Metodología principal existente. Peso: con Transactions en 0%, se conserva la regla de clase de pesos iguales entre los métodos activos (50/50). | G6: =IF(C6>0,"Sí","No (referencia)") -> Sí
A7: Trading Comps | B7: ='Trading Comps'!B83 -> 33.492841 | C7: 0.5 | D7: =1/3 -> 0.33333333 | E7: =IF(ISNUMBER(B7),B7*C7,0) -> 16.74642 | F7: Trading Comps (sección 5). Metodología complementaria. Peso igual al DCF por la regla de pesos iguales de la diap. 18. | G7: =IF(C7>0,"Sí","No (referencia)") -> Sí
A8: Precedent Transactions | B8: ='Precedent Transactions'!E54 -> 40.728395 | C8: 0 | D8: =1/3 -> 0.33333333 | E8: =IF(ISNUMBER(B8),B8*C8,0) -> 0 | F8: Precedent Transactions (sección 4). Peso 0% por decisión del proyecto: la muestra no es defendible. El método sigue calculándose. | G8: =IF(C8>0,"Sí","No (referencia)") -> No (referencia)
A9: Suma de pesos | C9: =SUM(C6:C8) -> 1 | D9: =SUM(D6:D8) -> 1
A11: PRECIO COMBINADO (MXN por acción) | B11: =IF(ABS(C9-1)>0.000000001,"Los pesos deben sumar 100%",IF(SUMPRODUCT((C6:C8>0)*(1-ISNUMBER(B6:B8)))>0,"NA: método con peso sin precio",SUMPRODUCT(B6:B8,C6:C8))) -> 32.953801 | F11: Regla: los pesos deben sumar exactamente 100%; un método con peso y sin precio deja el resultado en NA (no se toma como cero).
A12: Precio de mercado (MXN, 25-sep-2026) | B12: =Valuación!B42 -> 33.48
A13: Diferencia vs. precio (MXN) | B13: =B11-B12 -> -0.52619916
A14: Potencial / (baja) | B14: =B11/B12-1 -> -0.015716821
A16: Memo: resultado con la regla de clase (⅓ cada método) | B16: =SUMPRODUCT(B6:B8,D6:D8)/D9 -> 35.545332 | F16: Solo como referencia de la regla de pesos iguales: incluye la muestra de transacciones no defendible.
A18: RANGO POR MÉTODO (MXN por acción)
A19: Método | B19: Bajo | C19: Central | D19: Alto | F19: Definición del rango
A20: DCF | B20: =MIN(Validación!E9:G9) -> 32.127727 | C20: =B6 -> 32.414761 | D20: =MAX(Validación!E9:G9) -> 32.982614 | F20: Mínimo y máximo de los tres escenarios oficiales de inflación (Validación, tabla A; la referencia Citi no entra al rango).
A21: Trading Comps | B21: ='Trading Comps'!B84 -> 27.031161 | C21: =B7 -> 33.492841 | D21: ='Trading Comps'!B85 -> 40.069987 | F21: Promedio de los precios a P25 y P75 de los múltiplos usados (barra central del football field, diap. 19).
A22: Precedent Transactions (referencia) | B22: ='Precedent Transactions'!E55 -> 24.761847 | C22: =B8 -> 40.728395 | D22: ='Precedent Transactions'!F55 -> 65.443736 | F22: Mínimo y máximo del EV/EBITDA de las 3 operaciones.

Sheet Validación
A1: VALIDACIÓN — controles independientes del modelo integrado
A2: Cada control recalcula el resultado por una vía distinta y lo compara con el resultado del modelo. PASS = diferencia dentro de la tolerancia.
A3: Convención de colores: amarillo = dato o supuesto capturado (con fuente) · verde = vínculo a otra hoja o archivo fuente · azul = resultado clave · blanco = cálculo.
A5: A. TABLA DE ESCENARIOS (valores registrados al recalcular el libro con cada combinación de selectores)
A6: Combinación | B6: Celda de origen | C6: Histórico (Citi + βU 0.80) | D6: Referencia Citi (βU 0.65) | E6: Cautela | F6: Base (oficial) | G6: Alcista | H6: Base con βU 0.80 | I6: Nota
A7: Inflación aplicada 2026 | B7: 'Inflación'!B13 | C7: 0.0393 | D7: 0.0393 | E7: 0.0326 | F7: 0.0351 | G7: 0.04 | H7: 0.0351 | I7: Valores registrados al construir el libro: se recalcula el modelo completo con cada combinación (tools/excel/scenarios.py). El control "combinación activa = tabla" verifica que el modelo vivo coincide con su columna.
A8: βU usada | B8: 'Beta y Kd'!B28 | C8: 0.8 | D8: 0.65 | E8: 0.65 | F8: 0.65 | G8: 0.65 | H8: 0.8
A9: Precio DCF final (MXN) | B9: 'Proyección Final Soriana'!B265 | C9: 31.164416 | D9: 32.76267 | E9: 32.127727 | F9: 32.414761 | G9: 32.982614 | H9: 30.832
A10: Equity a la fecha de valuación (mdp) | B10: 'Proyección Final Soriana'!B263 | C10: 56095.95 | D10: 58972.806 | E10: 57829.908 | F10: 58346.569 | G10: 59368.706 | H10: 55497.6
A11: EV ponderado al cierre 2025 (mdp) | B11: 'Proyección Final Soriana'!B245 | C11: 66235.797 | D11: 69137.901 | E11: 68089.786 | F11: 68563.605 | G11: 69500.978 | H11: 65689.36
A12: WACC iterado | B12: 'Proyección Final Soriana'!B126 | C12: 0.11877344 | D12: 0.11351486 | E12: 0.11339819 | F12: 0.11345107 | G12: 0.11355386 | H12: 0.11870348
A13: Ke iterado | B13: 'Proyección Final Soriana'!B221 | C13: 0.13951381 | D13: 0.13054217 | E13: 0.13068376 | F13: 0.1306194 | G13: 0.13049517 | H13: 0.1396172
A14: βL iterada | B14: 'Proyección Final Soriana'!E219 | C14: 1.0483169 | D14: 0.83622157 | E14: 0.83956875 | F14: 0.83804732 | G14: 0.83511031 | H14: 1.0507612
A15: WACC a valor de mercado | B15: WACC!B33 | C15: 0.12500801 | D15: 0.11919896 | E15: 0.11919896 | F15: 0.11919896 | G15: 0.11919896 | H15: 0.12500801
A16: Ke a valor de mercado | B16: WACC!B29 | C16: 0.13829354 | D16: 0.13020788 | E16: 0.13020788 | F16: 0.13020788 | G16: 0.13020788 | H16: 0.13829354
A17: FCF 2030E (mdp) | B17: 'Proyección Final Soriana'!G117 | C17: 6469.9694 | D17: 6469.9694 | E17: 6352.1925 | F17: 6405.8977 | G17: 6512.2018 | H17: 6405.8977
A18: Ventas 2030E (mdp) | B18: 'Proyección Final Soriana'!G67 | C18: 178318.18 | D18: 178318.18 | E18: 174699.57 | F18: 176368.46 | G18: 179676.46 | H18: 176368.46
A19: Precio combinado (MXN) | B19: 'Valuación Combinada'!B11 | C19: 32.328629 | D19: 33.127755 | E19: 32.810284 | F19: 32.953801 | G19: 33.237728 | H19: 32.16242
A21: B. CONTROLES
A22: Control | B22: Valor del modelo | C22: Recalculo independiente / esperado | D22: Diferencia | E22: Tolerancia | G22: Estado | H22: Qué verifica
A23: DCF · balance proyectado cuadra 2025A–2030E | B23: =SUMPRODUCT(ABS('Proyección Final Soriana'!B97:G97)) -> 0 | C23: 0 | D23: =IF(AND(ISNUMBER(B23),ISNUMBER(C23)),B23-C23,"n/a") -> 0 | E23: 0.5 | G23: =IF(ISNUMBER(D23),IF(ABS(D23)<=E23,"PASS","FAIL"),"FAIL") -> PASS | H23: Activo − pasivo − capital = 0.
A24: DCF · WACC > g | B24: ='Proyección Final Soriana'!B126-'Proyección Final Soriana'!B123 -> 0.078451071 | C24: >0 | G24: =IF(B24>0,"PASS","FAIL") -> PASS | H24: Condición del modelo de Gordon.
A25: DCF · iteración del WACC convergió | B25: =ABS('Proyección Final Soriana'!G219-'Proyección Final Soriana'!G218) -> 7.1162087e-08 | C25: 0 | D25: =IF(AND(ISNUMBER(B25),ISNUMBER(C25)),B25-C25,"n/a") -> 7.1162087e-08 | E25: 1e-06 | G25: =IF(ISNUMBER(D25),IF(ABS(D25)<=E25,"PASS","FAIL"),"FAIL") -> PASS | H25: Última variación del WACC.
A26: DCF · Σ VP de FCF = SUMPRODUCT(FCF, factor) | B26: ='Proyección Final Soriana'!B134 -> 23066.291 | C26: =SUMPRODUCT('Proyección Final Soriana'!C117:G117,'Proyección Final Soriana'!C119:G119) -> 23066.291 | D26: =IF(AND(ISNUMBER(B26),ISNUMBER(C26)),B26-C26,"n/a") -> 0 | E26: 1e-06 | G26: =IF(ISNUMBER(D26),IF(ABS(D26)<=E26,"PASS","FAIL"),"FAIL") -> PASS | H26: Descuento de flujos.
A27: DCF · factor año 5 = 1/(1+WACC)^5 | B27: ='Proyección Final Soriana'!G119 -> 0.58431134 | C27: =1/(1+'Proyección Final Soriana'!B126)^5 -> 0.58431134 | D27: =IF(AND(ISNUMBER(B27),ISNUMBER(C27)),B27-C27,"n/a") -> 0 | E27: 1e-12 | G27: =IF(ISNUMBER(D27),IF(ABS(D27)<=E27,"PASS","FAIL"),"FAIL") -> PASS | H27: Fórmula de descuento.
A28: DCF · VT Gordon = FCF2030 × (1+g) / (WACC − g) | B28: ='Proyección Final Soriana'!B129 -> 84512.602 | C28: ='Proyección Final Soriana'!G117*(1+'Proyección Final Soriana'!B123)/('Proyección Final Soriana'!B126-'Proyección Final Soriana'!B123) -> 84512.602 | D28: =IF(AND(ISNUMBER(B28),ISNUMBER(C28)),B28-C28,"n/a") -> 0 | E28: 1e-06 | G28: =IF(ISNUMBER(D28),IF(ABS(D28)<=E28,"PASS","FAIL"),"FAIL") -> PASS | H28: Valor terminal.
A29: DCF · FCF2030 = NOPAT + D&A − Capex − ΔNWC | B29: ='Proyección Final Soriana'!G117 -> 6405.8977 | C29: ='Proyección Final Soriana'!G73*(1-'Proyección Final Soriana'!G55)-'Proyección Final Soriana'!G72+'Proyección Final Soriana'!G104+('Proyección Final Soriana'!G102+'Proyección Final Soriana'!G103+'Proyección Final Soriana'!G105) -> 6405.8977 | D29: =IF(AND(ISNUMBER(B29),ISNUMBER(C29)),B29-C29,"n/a") -> 0 | E29: 1e-06 | G29: =IF(ISNUMBER(D29),IF(ABS(D29)<=E29,"PASS","FAIL"),"FAIL") -> PASS | H29: Identidad del FCFF.
A30: DCF · Equity 2T26 = EV 2T26 − deuda − arrend. + caja | B30: ='Proyección Final Soriana'!B262 -> 56563.74 | C30: ='Proyección Final Soriana'!B258-(Datos!F25+Datos!F26)-(Datos!F27+Datos!F28)+Datos!F17 -> 56563.74 | D30: =IF(AND(ISNUMBER(B30),ISNUMBER(C30)),B30-C30,"n/a") -> 0 | E30: 1e-06 | G30: =IF(ISNUMBER(D30),IF(ABS(D30)<=E30,"PASS","FAIL"),"FAIL") -> PASS | H30: Puente EV → capital.
A31: DCF · FCF de 1S26 restado del EV (signo) | B31: ='Proyección Final Soriana'!B257 -> 1060.497 | C31: =-((Datos!E15+Datos!F15)-(Datos!E16+Datos!F16)) -> 1060.497 | D31: =IF(AND(ISNUMBER(B31),ISNUMBER(C31)),B31-C31,"n/a") -> 0 | E31: 1e-09 | G31: =IF(ISNUMBER(D31),IF(ABS(D31)<=E31,"PASS","FAIL"),"FAIL") -> PASS | H31: B257 = −(CFO − Capex) = +1,060.5 porque el FCF de 1S26 fue negativo.
A32: DCF · precio = Equity / acciones | B32: ='Proyección Final Soriana'!B265 -> 32.414761 | C32: ='Proyección Final Soriana'!B263/WACC!B17 -> 32.414761 | D32: =IF(AND(ISNUMBER(B32),ISNUMBER(C32)),B32-C32,"n/a") -> 0 | E32: 1e-09 | G32: =IF(ISNUMBER(D32),IF(ABS(D32)<=E32,"PASS","FAIL"),"FAIL") -> PASS | H32: Precio por acción.
A33: DCF · escenario activo = tabla de escenarios | B33: ='Proyección Final Soriana'!B265 -> 32.414761 | C33: =IF(AND(Inflación!$B$6=0,'Beta y Kd'!$B$27=0),C9,IF(AND(Inflación!$B$6=0,'Beta y Kd'!$B$27=1),D9,IF(AND(Inflación!$B$6=1,'Beta y Kd'!$B$27=1),E9,IF(AND(Inflación!$B$6=2,'Beta y Kd'!$B$27=1),F9,IF(AND(Inflación!$B$6=3,'Beta y Kd'!$B$27=1),G9,IF(AND(Inflación!$B$6=2,'Beta y Kd'!$B$27=0),H9,"sin registro")))))) -> 32.414761 | D33: =IF(AND(ISNUMBER(B33),ISNUMBER(C33)),B33-C33,"n/a") -> 0 | E33: 1e-06 | G33: =IF(ISNUMBER(D33),IF(ABS(D33)<=E33,"PASS","FAIL"),"FAIL") -> PASS | H33: El modelo vivo coincide con el valor registrado del escenario seleccionado.
A34: DCF · baseline histórico (Citi + βU 0.80) = $31.1644 | B34: =C9 -> 31.164416 | C34: 31.164416 | D34: =IF(AND(ISNUMBER(B34),ISNUMBER(C34)),B34-C34,"n/a") -> 0 | E34: 1e-06 | G34: =IF(ISNUMBER(D34),IF(ABS(D34)<=E34,"PASS","FAIL"),"FAIL") -> PASS | H34: El modelo anterior se reproduce exactamente con la trayectoria Citi y la beta heredada.
A35: DCF · escenarios ordenados: Cautela < Base < Alcista | B35: =IF(AND(E9<F9,F9<G9),1,0) -> 1 | C35: 1 | D35: =IF(AND(ISNUMBER(B35),ISNUMBER(C35)),B35-C35,"n/a") -> 0 | E35: 0 | G35: =IF(ISNUMBER(D35),IF(ABS(D35)<=E35,"PASS","FAIL"),"FAIL") -> PASS | H35: Con WACC nominal fijo, más inflación → más ventas nominales → más valor (limitación documentada).
A36: Beta · control Damodaran: 0.87 desapalancada = 0.65 | B36: ='Beta y Kd'!B18 -> 0.64780368 | C36: ='Beta y Kd'!B15 -> 0.65 | D36: =IF(AND(ISNUMBER(B36),ISNUMBER(C36)),B36-C36,"n/a") -> -0.002196324 | E36: 0.005 | G36: =IF(ISNUMBER(D36),IF(ABS(D36)<=E36,"PASS","FAIL"),"FAIL") -> PASS | H36: βU = βL / [1 + (1 − t) × D/E] con los datos publicados.
A37: Beta · βU usada = Damodaran global (selector oficial) | B37: ='Beta y Kd'!B28 -> 0.65 | C37: =IF('Beta y Kd'!$B$27=1,'Beta y Kd'!B15,'Beta y Kd'!B26) -> 0.65 | D37: =IF(AND(ISNUMBER(B37),ISNUMBER(C37)),B37-C37,"n/a") -> 0 | E37: 0 | G37: =IF(ISNUMBER(D37),IF(ABS(D37)<=E37,"PASS","FAIL"),"FAIL") -> PASS | H37: WACC!B9 toma la βU seleccionada.
A38: Beta · βL de mercado = βU × [1 + (1 − t) × D/E] | B38: =WACC!B28 -> 0.82831856 | C38: =WACC!B9*(1+(1-WACC!B10)*WACC!B23) -> 0.82831856 | D38: =IF(AND(ISNUMBER(B38),ISNUMBER(C38)),B38-C38,"n/a") -> 0 | E38: 1e-12 | G38: =IF(ISNUMBER(D38),IF(ABS(D38)<=E38,"PASS","FAIL"),"FAIL") -> PASS | H38: Reapalancamiento con la estructura de mercado.
A39: Beta · βL iterada = βU × [1 + (1 − t) × D/E del DCF] | B39: ='Proyección Final Soriana'!E219 -> 0.83804732 | C39: ='Proyección Final Soriana'!B212*(1+(1-'Proyección Final Soriana'!B207)*'Proyección Final Soriana'!B209/'Proyección Final Soriana'!C219) -> 0.83804732 | D39: =IF(AND(ISNUMBER(B39),ISNUMBER(C39)),B39-C39,"n/a") -> 0 | E39: 1e-12 | G39: =IF(ISNUMBER(D39),IF(ABS(D39)<=E39,"PASS","FAIL"),"FAIL") -> PASS | H39: Reapalancamiento con la estructura del DCF.
A40: Beta · Ke iterado = Rf + βL × PRM | B40: ='Proyección Final Soriana'!F219 -> 0.1306194 | C40: ='Proyección Final Soriana'!B210+'Proyección Final Soriana'!E219*'Proyección Final Soriana'!B211 -> 0.1306194 | D40: =IF(AND(ISNUMBER(B40),ISNUMBER(C40)),B40-C40,"n/a") -> 0 | E40: 1e-12 | G40: =IF(ISNUMBER(D40),IF(ABS(D40)<=E40,"PASS","FAIL"),"FAIL") -> PASS | H40: CAPM.
A41: Kd · 10% consistente con intereses 1S26 / deuda 2T26 (±0.5 pp) | B41: ='Proyección Final Soriana'!C61 -> 0.1 | C41: =(Datos!E10+Datos!F10)*2/Datos!F29 -> 0.098648482 | D41: =IF(AND(ISNUMBER(B41),ISNUMBER(C41)),B41-C41,"n/a") -> 0.0013515179 | E41: 0.005 | G41: =IF(ISNUMBER(D41),IF(ABS(D41)<=E41,"PASS","FAIL"),"FAIL") -> PASS | H41: Fuente del comentario de C61 y control con datos observados.
A42: Inflación · fila 10 del DCF = inflación aplicada | B42: =SUMPRODUCT(ABS('Proyección Final Soriana'!C10:G10-Inflación!B13:F13)) -> 0 | C42: 0 | D42: =IF(AND(ISNUMBER(B42),ISNUMBER(C42)),B42-C42,"n/a") -> 0 | E42: 1e-12 | G42: =IF(ISNUMBER(D42),IF(ABS(D42)<=E42,"PASS","FAIL"),"FAIL") -> PASS | H42: Vínculo de la inflación al modelo.
A43: Inflación · Base = modelo trimestral redondeado | B43: =Inflación!B48 -> 0.0351 | C43: =ROUND(Inflación!C33*EXP(Inflación!D33*5),2)/100 -> 0.0351 | D43: =IF(AND(ISNUMBER(B43),ISNUMBER(C43)),B43-C43,"n/a") -> 0 | E43: 1e-12 | G43: =IF(ISNUMBER(D43),IF(ABS(D43)<=E43,"PASS","FAIL"),"FAIL") -> PASS | H43: Base = resultado de modelo.
A44: Inflación · modelo trimestral reproduce el Dossier (3.51%) | B44: =Inflación!G33 -> 0.035087136 | C44: 0.0351 | D44: =IF(AND(ISNUMBER(B44),ISNUMBER(C44)),B44-C44,"n/a") -> -1.2863603e-05 | E44: 0.0001 | G44: =IF(ISNUMBER(D44),IF(ABS(D44)<=E44,"PASS","FAIL"),"FAIL") -> PASS | H44: Dossier: 4.0327e^(−0.028x) → 3.51%.
A45: Inflación · modelo inmediato reproduce el libro de clase (3.508%) | B45: =Inflación!G32 -> 0.035040523 | C45: 0.035080794 | D45: =IF(AND(ISNUMBER(B45),ISNUMBER(C45)),B45-C45,"n/a") -> -4.0270237e-05 | E45: 0.0001 | G45: =IF(ISNUMBER(D45),IF(ABS(D45)<=E45,"PASS","FAIL"),"FAIL") -> PASS | H45: Libro de clase INFLACION!H37.
A46: Inflación · construcción de clase S113 (3.268%) | B46: =Inflación!G36 -> 0.032678765 | C46: 0.032678767 | D46: =IF(AND(ISNUMBER(B46),ISNUMBER(C46)),B46-C46,"n/a") -> -2.07482e-09 | E46: 1e-08 | G46: =IF(ISNUMBER(D46),IF(ABS(D46)<=E46,"PASS","FAIL"),"FAIL") -> PASS | H46: Libro de clase INFLACION!S113.
A47: Mercado · beta histórica = regresión sin ×10 | B47: =VF_BETA_HISTORICA -> 0.041461957 | C47: 0.041461957 | D47: =IF(AND(ISNUMBER(B47),ISNUMBER(C47)),B47-C47,"n/a") -> 0 | E47: 1e-09 | G47: =IF(ISNUMBER(D47),IF(ABS(D47)<=E47,"PASS","FAIL"),"FAIL") -> PASS | H47: SORIANA!Y2 / 10.
A48: Comps · media de 10 empresas ≈ media publicada por CIQ (EV/EBITDA) | B48: ='Trading Comps'!N21 -> 7.21 | C48: ='Trading Comps'!N20 -> 7.2 | D48: =IF(AND(ISNUMBER(B48),ISNUMBER(C48)),B48-C48,"n/a") -> 0.01 | E48: 0.051 | G48: =IF(ISNUMBER(D48),IF(ABS(D48)<=E48,"PASS","FAIL"),"FAIL") -> PASS | H48: Transcripción correcta (CIQ redondea a 1 decimal).
A49: Comps · media de 10 empresas ≈ media publicada por CIQ (P/U) | B49: ='Trading Comps'!P21 -> 14.61 | C49: ='Trading Comps'!P20 -> 14.6 | D49: =IF(AND(ISNUMBER(B49),ISNUMBER(C49)),B49-C49,"n/a") -> 0.01 | E49: 0.051 | G49: =IF(ISNUMBER(D49),IF(ABS(D49)<=E49,"PASS","FAIL"),"FAIL") -> PASS | H49: Ídem.
A50: Comps · media muestra (EV/EBITDA) = SUMPRODUCT / SUM | B50: ='Trading Comps'!C68 -> 7.0428571 | C50: =SUMPRODUCT('Trading Comps'!N7:N16,'Trading Comps'!K7:K16)/SUM('Trading Comps'!K7:K16) -> 7.0428571 | D50: =IF(AND(ISNUMBER(B50),ISNUMBER(C50)),B50-C50,"n/a") -> 0 | E50: 1e-09 | G50: =IF(ISNUMBER(D50),IF(ABS(D50)<=E50,"PASS","FAIL"),"FAIL") -> PASS | H50: Estadístico recalculado por otra vía.
A51: Comps · precio EV/EBITDA recalculado | B51: ='Trading Comps'!H68 -> 36.85393 | C51: =('Trading Comps'!C68*'Trading Comps'!B28+'Trading Comps'!B37)/'Trading Comps'!B30 -> 36.85393 | D51: =IF(AND(ISNUMBER(B51),ISNUMBER(C51)),B51-C51,"n/a") -> 0 | E51: 1e-09 | G51: =IF(ISNUMBER(D51),IF(ABS(D51)<=E51,"PASS","FAIL"),"FAIL") -> PASS | H51: Puente al capital y división entre acciones.
A52: Comps · valor = promedio de 3 precios a la media | B52: ='Trading Comps'!B83 -> 33.492841 | C52: =AVERAGE('Trading Comps'!H68:J68) -> 33.492841 | D52: =IF(AND(ISNUMBER(B52),ISNUMBER(C52)),B52-C52,"n/a") -> 0 | E52: 1e-09 | G52: =IF(ISNUMBER(D52),IF(ABS(D52)<=E52,"PASS","FAIL"),"FAIL") -> PASS | H52: Regla de agregación de la diap. 9.
A53: Comps · n de la muestra = 7 | B53: ='Trading Comps'!C72 -> 7 | C53: 7 | D53: =IF(AND(ISNUMBER(B53),ISNUMBER(C53)),B53-C53,"n/a") -> 0 | E53: 0 | G53: =IF(ISNUMBER(D53),IF(ABS(D53)<=E53,"PASS","FAIL"),"FAIL") -> PASS | H53: Muestra depurada.
A54: Transactions · media EV/EBITDA ≈ media publicada por CIQ (7.6x) | B54: ='Precedent Transactions'!I34 -> 7.6333333 | C54: ='Precedent Transactions'!I17 -> 7.6 | D54: =IF(AND(ISNUMBER(B54),ISNUMBER(C54)),B54-C54,"n/a") -> 0.033333333 | E54: 0.051 | G54: =IF(ISNUMBER(D54),IF(ABS(D54)<=E54,"PASS","FAIL"),"FAIL") -> PASS | H54: Transcripción correcta.
A55: Transactions · media EV/Ventas ≈ media publicada por CIQ (0.7x) | B55: ='Precedent Transactions'!H34 -> 0.73333333 | C55: ='Precedent Transactions'!H17 -> 0.7 | D55: =IF(AND(ISNUMBER(B55),ISNUMBER(C55)),B55-C55,"n/a") -> 0.033333333 | E55: 0.051 | G55: =IF(ISNUMBER(D55),IF(ABS(D55)<=E55,"PASS","FAIL"),"FAIL") -> PASS | H55: Ídem.
A56: Combinada · pesos suman 100% | B56: ='Valuación Combinada'!C9 -> 1 | C56: 1 | D56: =IF(AND(ISNUMBER(B56),ISNUMBER(C56)),B56-C56,"n/a") -> 0 | E56: 1e-12 | G56: =IF(ISNUMBER(D56),IF(ABS(D56)<=E56,"PASS","FAIL"),"FAIL") -> PASS | H56: Pesos trazables.
A57: Combinada · precio = Σ peso × precio (recalculo) | B57: ='Valuación Combinada'!B11 -> 32.953801 | C57: ='Valuación Combinada'!B6*'Valuación Combinada'!C6+'Valuación Combinada'!B7*'Valuación Combinada'!C7+IF(ISNUMBER('Valuación Combinada'!B8),'Valuación Combinada'!B8*'Valuación Combinada'!C8,0) -> 32.953801 | D57: =IF(AND(ISNUMBER(B57),ISNUMBER(C57)),B57-C57,"n/a") -> 0 | E57: 1e-09 | G57: =IF(ISNUMBER(D57),IF(ABS(D57)<=E57,"PASS","FAIL"),"FAIL") -> PASS | H57: Combinación lineal con pesos que suman 100%.
A58: Transactions · precio EV/EBITDA = (múltiplo × EBITDA + ajuste) / acciones | B58: ='Precedent Transactions'!K34 -> 40.728395 | C58: =('Precedent Transactions'!I34*'Trading Comps'!B28+'Trading Comps'!B37)/'Trading Comps'!B30 -> 40.728395 | D58: =IF(AND(ISNUMBER(B58),ISNUMBER(C58)),B58-C58,"n/a") -> 0 | E58: 1e-09 | G58: =IF(ISNUMBER(D58),IF(ABS(D58)<=E58,"PASS","FAIL"),"FAIL") -> PASS | H58: Mismo puente que Trading Comps.
A59: Transactions · equity implícito = EV + ajuste | B59: ='Precedent Transactions'!I46 -> 73311.111 | C59: ='Precedent Transactions'!I44+'Trading Comps'!B37 -> 73311.111 | D59: =IF(AND(ISNUMBER(B59),ISNUMBER(C59)),B59-C59,"n/a") -> 0 | E59: 1e-09 | G59: =IF(ISNUMBER(D59),IF(ABS(D59)<=E59,"PASS","FAIL"),"FAIL") -> PASS | H59: Detalle a la media.
A60: Comps · equity implícito (EV/EBITDA) = EV + ajuste | B60: ='Trading Comps'!C78 -> 66337.073 | C60: ='Trading Comps'!C77+'Trading Comps'!B37 -> 66337.073 | D60: =IF(AND(ISNUMBER(B60),ISNUMBER(C60)),B60-C60,"n/a") -> 0 | E60: 1e-09 | G60: =IF(ISNUMBER(D60),IF(ABS(D60)<=E60,"PASS","FAIL"),"FAIL") -> PASS | H60: Detalle a la media.
A61: Combinada · Transactions con peso 0% | B61: ='Valuación Combinada'!C8 -> 0 | C61: 0 | D61: =IF(AND(ISNUMBER(B61),ISNUMBER(C61)),B61-C61,"n/a") -> 0 | E61: 0 | G61: =IF(ISNUMBER(D61),IF(ABS(D61)<=E61,"PASS","FAIL"),"FAIL") -> PASS | H61: Decisión del proyecto.
A63: RESUMEN | B63: =COUNTIF(G23:G61,"PASS")&" PASS de "&COUNTA(A23:A61) -> 39 PASS de 39

Sheet Fuentes
A1: FUENTES — registro de insumos del modelo integrado
A2: Tipo: Observado (dato publicado) · Modelo (resultado de un modelo) · Supuesto (decisión del analista con sustento) · Referencia (comparación, no escenario) · Pendiente (input heredado sin fuente verificada).
A3: Convención de colores: amarillo = dato o supuesto capturado (con fuente) · verde = vínculo a otra hoja o archivo fuente · azul = resultado clave · blanco = cálculo.
A5: Insumo | B5: Dónde se usa | C5: Valor | D5: Fecha | E5: Unidad / moneda | F5: Tipo | G5: Fuente
A6: Inflación INPC quincenal | B6: Inflación!A60:B172 | C6: 113 obs. | D6: 07-oct-2026 | E6: % anual | F6: Observado | G6: Banco de México, serie SP74833 (vía MODELO DE INFLACION EN LA VALUACION DE EMPRESAS.xlsx)
A7: Escenario Base 3.51% | B7: Inflación!B48 | C7: 3.51% | D7: 07-oct-2026 | E7: % anual | F7: Modelo | G7: Modelo exponencial trimestral de clase (calculado en Inflación!33)
A8: Escenario Cautela 3.26% | B8: Inflación!B47 | C8: 3.26% | D8: 07-oct-2026 | E8: % anual | F8: Supuesto | G8: Escenario derivado de la tendencia larga: Dossier de Soriana / Avances; construcción de clase más cercana Inflación!G36 (3.268%)
A9: Escenario Alcista 4.00% | B9: Inflación!B49 | C9: 4.00% | D9: — | E9: % anual | F9: Supuesto | G9: Supuesto de escenario de Avances de valuación intrínseca (no es pronóstico estadístico)
A10: Trayectoria Citi 2026–2030 — Referencia | B10: Inflación!B9:F9 | C10: 3.93/3.83/3.75% | D10: 22-sep-2026 | E10: % anual | F10: Referencia | G10: Encuesta Citi de Expectativas (comentario original de Proyección Final!C10). Referencia histórica del modelo anterior; no es escenario.
A11: Beta desapalancada sectorial (βU) | B11: WACC!B9 ← 'Beta y Kd'!B28 | C11: 0.65 | D11: ene-2026 | E11: x | F11: Observado | G11: Damodaran, Betas by Sector (Global), Retail (Grocery and Food): βL 0.87, D/E 45.96%, t marginal 25.37% → βU 0.65; reapalancada con la estructura de Soriana (Hamada).
A12: Beta heredada (histórico) | B12: 'Beta y Kd'!B26 | C12: 0.80 | D12: — | E12: x | F12: Referencia | G12: Excel anterior / Material Maestro; solo para reproducir el baseline $31.16.
A13: Kd antes de impuestos (iteración) | B13: Proyección Final!C61 | C13: 10.00% | D13: 22-sep-2026 | E13: % | F13: Supuesto | G13: Comentario original de C61: Encuesta Citi (tasa Banxico 6.50% a fin de 2026 y 2027) y gastos financieros 1S26. Control: intereses 1S26 anualizados / deuda 2T26 = 9.87% ('Beta y Kd'!B58).
A14: Rf Bono M 10 años | B14: WACC!B5 | C14: 9.517% | D14: — | E14: % | F14: Pendiente | G14: Input heredado; fecha y fuente exacta pendientes.
A15: Prima de riesgo de mercado | B15: WACC!B6 | C15: 4.23% | D15: — | E15: % | F15: Pendiente | G15: Input heredado ("madura"); fecha y fuente exacta pendientes.
A16: Crecimiento perpetuo g | B16: Proyección Final!B123 | C16: 3.50% | D16: — | E16: % | F16: Pendiente | G16: Input heredado; no ligado a la inflación (sin sustento documental).
... A20: Pesos de la combinada | B20: Valuación Combinada!C6:C8 | C20: 50/50/0 | D20: — | E20: % | F20: Supuesto | G20: Regla de pesos iguales de la diap. 18 entre métodos activos; Transactions 0% por decisión del proyecto.
A22: NOTAS METODOLÓGICAS
A23: DCF principal: el DCF de ValuFlow (Proyección Final Soriana): descuento de fin de periodo, valor terminal 50% Gordon / 50% múltiplo de salida, WACC iterado al valor DCF y traslado a la fecha de valuación.
A24: Referencia de Capital IQ (no reemplaza el DCF principal): la metodología de clase de CIQ usa convención de medio año (mid-year) y valor terminal por múltiplo de salida. Se documenta solo como referencia metodológica.
A25: Trading Comps y Precedent Transactions: metodología de la presentación de clase (CIQ Valuations): 6 estadísticos, percentiles inclusivos, puente EV → capital, NM/NA y promedio de precios implícitos a la media.
A26: Valuación combinada: DCF 50% + Trading Comps 50% + Precedent Transactions 0% (referencia). Los pesos son editables y deben sumar 100%.
