Workbook

Sheet Comparativo
A4: 1. VALUACIÓN (DCF, base FY2025) | B4: Soriana | C4: Walmex | D4: Chedraui | E4: La Comer
A5: WACC | B5: =Valuación!B15 -> 0.10063018 | C5: =Valuación!B53 -> 0.10255747 | D5: =Valuación!B91 -> 0.082995961 | E5: =Valuación!B129 -> 0.1009772
A6: Crecimiento perpetuo (g) | B6: =Valuación!B16 -> 0.035 | C6: =Valuación!B54 -> 0.035 | D6: =Valuación!B92 -> 0.035 | E6: =Valuación!B130 -> 0.035
A7: FCF 2025A (flujo libre de efectivo) | B7: =Valuación!B27 -> 6761.4 | C7: =Valuación!B65 -> 40916.76 | D7: =Valuación!B103 -> 12113.9 | E7: =Valuación!B141 -> 302.92442
A8: VPN de los FCF 2026E–2030E | B8: =Valuación!B31 -> 27698.206 | C8: =Valuación!B69 -> 169911.77 | D8: =Valuación!B107 -> 52976.897 | E8: =Valuación!B145 -> 1263.1284
A9: Valor terminal (TV) al 2030 | B9: =Valuación!B33 -> 124303.41 | C9: =Valuación!B71 -> 744509.04 | D9: =Valuación!B109 -> 310256.86 | E9: =Valuación!B147 -> 5643.9411
A10: Valor presente del TV | B10: =Valuación!B34 -> 76961.93 | C10: =Valuación!B72 -> 456944.87 | D10: =Valuación!B110 -> 208251.06 | E10: =Valuación!B148 -> 3488.9186
A11: Enterprise Value (EV) | B11: =Valuación!B35 -> 104660.14 | C11: =Valuación!B73 -> 626856.64 | D11: =Valuación!B111 -> 261227.95 | E11: =Valuación!B149 -> 4752.047
A12: Deuda total (bancaria/bursátil + arrendamientos) | B12: =-Valuación!B36 -> 23618 | C12: =-Valuación!B74 -> 80848.1 | D12: =-Valuación!B112 -> 56744.34 | E12: =-Valuación!B150 -> 2441.8
A13: Efectivo y equivalentes | B13: =Valuación!B37 -> 9295 | C13: =Valuación!B75 -> 28591.2 | D13: =Valuación!B113 -> 14640.16 | E13: =Valuación!B151 -> 2962.8
A14: Equity Value (valor para los accionistas) | B14: =Valuación!B39 -> 90337.136 | C14: =Valuación!B77 -> 574599.74 | D14: =Valuación!B115 -> 219123.77 | E14: =Valuación!B153 -> 5273.047
A15: Valor intrínseco por acción (MXN) | B15: =Valuación!B41 -> 50.187298 | C15: =Valuación!B79 -> 32.910034 | D15: =Valuación!B117 -> 228.19351 | E15: =Valuación!B155 -> 4.9476264
A16: Precio actual en bolsa (MXN) | B16: =Valuación!B42 -> 33.48 | C16: =Valuación!B80 -> 46.6 | D16: =Valuación!B118 -> 92.94 | E16: =Valuación!B156 -> 32.08
A17: Potencial de apreciación / (baja) | B17: =Valuación!B43 -> 0.49902323 | C17: =Valuación!B81 -> -0.29377609 | D17: =Valuación!B119 -> 1.4552777 | E17: =Valuación!B157 -> -0.84577224
A18: Precio objetivo consenso de analistas (MXN) | B18: =Generales!B24 -> 23.357 | C18: 60.094 | D18: 128.933 | E18: 47.67
A19: Recomendación consenso de analistas | B19: Venta (0 C / 1 M / 6 V) | C19: Neutral (5 C / 10 M / 3 V) | D19: Neutral (3 C / 12 M / 0 V) | E19: Compra (5 C / 4 M / 0 V)
A21: 2. RAZONES FINANCIERAS – PROMEDIO DE LOS ÚLTIMOS 5 TRIMESTRES | B21: Soriana | C21: Walmex | D21: Chedraui | E21: La Comer
A22: Circulante | B22: =Razones!G7 -> 1.2541889 | C22: =Razones!G23 -> 0.9768759 | D22: =Razones!G39 -> 0.933732 | E22: =Razones!G55 -> 1.2290463
A23: Prueba ácida | B23: =Razones!G8 -> 0.35473781 | C23: =Razones!G24 -> 0.34704511 | D23: =Razones!G40 -> 0.40675641 | E23: =Razones!G56 -> 0.48041577
A24: Deuda / Activo total | B24: =Razones!G9 -> 0.45505378 | C24: =Razones!G25 -> 0.52855776 | D24: =Razones!G41 -> 0.66310269 | E24: =Razones!G57 -> 0.2578378
A25: Capitalización a largo plazo | B25: =Razones!G10 -> 0.20654207 | C25: =Razones!G26 -> 0.18040972 | D25: =Razones!G42 -> 0.38012988 | E25: =Razones!G58 -> 0.064547002
A26: Cobertura de intereses | B26: =Razones!G11 -> 2.8984196 | C26: =Razones!G27 -> 6.6453315 | D26: =Razones!G43 -> 4.1504186 | E26: =Razones!G59 -> 11.844746
A27: Rotación del inventario (trimestral) | B27: =Razones!G12 -> 0.95612726 | C27: =Razones!G28 -> 1.7752133 | D27: =Razones!G44 -> 2.3833504 | E27: =Razones!G60 -> 1.3488695
A28: Rotación del inventario en días | B28: =Razones!G13 -> 96.032436 | C28: =Razones!G29 -> 51.658042 | D28: =Razones!G45 -> 38.380088 | E28: =Razones!G61 -> 67.850681
A29: Rotación del activo total (trimestral) | B29: =Razones!G14 -> 0.28166407 | C29: =Razones!G30 -> 0.51157675 | D29: =Razones!G46 -> 0.46365336 | E29: =Razones!G62 -> 0.2764494
A30: Margen bruto | B30: =Razones!G15 -> 0.24566153 | C30: =Razones!G31 -> 0.24235015 | D30: =Razones!G47 -> 0.23527548 | E30: =Razones!G63 -> 0.29672069
A31: Margen neto | B31: =Razones!G16 -> 0.020605935 | C31: =Razones!G32 -> 0.048260538 | D31: =Razones!G48 -> 0.023418786 | E31: =Razones!G64 -> 0.05488254
A32: ROA (trimestral) | B32: =Razones!G17 -> 0.005843019 | C32: =Razones!G33 -> 0.024728482 | D32: =Razones!G49 -> 0.010867202 | E32: =Razones!G65 -> 0.015156869
A33: ROE (trimestral) | B33: =Razones!G18 -> 0.010703389 | C33: =Razones!G34 -> 0.052476921 | D33: =Razones!G50 -> 0.032240332 | E33: =Razones!G66 -> 0.02043965
A34: ROI (trimestral) | B34: =Razones!G19 -> 0.012031436 | C34: =Razones!G35 -> 0.042432022 | D34: =Razones!G51 -> 0.024290294 | E34: =Razones!G67 -> 0.017861415
A36: 3. RAZONES FINANCIERAS ANUALES FY2025 (incluye Chedraui) | B36: Soriana | C36: Walmex | D36: Chedraui | E36: La Comer
A37: Circulante | B37: =IFERROR(Datos!G19/Datos!G21,"n.d.") -> 1.2373849 | C37: =IFERROR(Datos!G45/Datos!G47,"n.d.") -> 0.96696082 | D37: =IFERROR(Datos!G71/Datos!G73,"n.d.") -> 0.92079667 | E37: =IFERROR(Datos!G97/Datos!G99,"n.d.") -> 1.2070372
A38: Prueba ácida | B38: =IFERROR((Datos!G19-Datos!G18)/Datos!G21,"n.d.") -> 0.414238 | C38: =IFERROR((Datos!G45-Datos!G44)/Datos!G47,"n.d.") -> 0.33384163 | D38: =IFERROR((Datos!G71-Datos!G70)/Datos!G73,"n.d.") -> 0.43735523 | E38: =IFERROR((Datos!G97-Datos!G96)/Datos!G99,"n.d.") -> 0.50008921
A39: Deuda / Activo total | B39: =IFERROR(Datos!G23/Datos!G20,"n.d.") -> 0.45697843 | C39: =IFERROR(Datos!G49/Datos!G46,"n.d.") -> 0.52434323 | D39: =IFERROR(Datos!G75/Datos!G72,"n.d.") -> 0.67356639 | E39: =IFERROR(Datos!G101/Datos!G98,"n.d.") -> 0.2544825
A40: Capitalización a largo plazo | B40: =IFERROR(Datos!G22/Datos!G20,"n.d.") -> 0.2056294 | C40: =IFERROR(Datos!G48/Datos!G46,"n.d.") -> 0.1816704 | D40: =IFERROR(Datos!G74/Datos!G72,"n.d.") -> 0.37134872 | E40: =IFERROR(Datos!G100/Datos!G98,"n.d.") -> 0.06423617
A41: Cobertura de intereses | B41: =IFERROR(Datos!G9/Datos!G10,"n.d.") -> 2.4567339 | C41: =IFERROR(Datos!G35/Datos!G36,"n.d.") -> 6.8465638 | D41: =IFERROR(Datos!G61/Datos!G62,"n.d.") -> 3.9247028 | E41: =IFERROR(Datos!G87/Datos!G88,"n.d.") -> 13.400737
A42: Rotación del inventario (anual) | B42: =IFERROR(Datos!G7/Datos!G18,"n.d.") -> 4.1740854 | C42: =IFERROR(Datos!G33/Datos!G44,"n.d.") -> 7.1325601 | D42: =IFERROR(Datos!G59/Datos!G70,"n.d.") -> 9.7102302 | E42: =IFERROR(Datos!G85/Datos!G96,"n.d.") -> 5.6268631
A43: Rotación del inventario en días (365) | B43: =IFERROR(365*Datos!G18/Datos!G7,"n.d.") -> 87.444305 | C43: =IFERROR(365*Datos!G44/Datos!G33,"n.d.") -> 51.173772 | D43: =IFERROR(365*Datos!G70/Datos!G59,"n.d.") -> 37.589222 | E43: =IFERROR(365*Datos!G96/Datos!G85,"n.d.") -> 64.867404
A44: Rotación del activo total (anual) | B44: =IFERROR(Datos!G6/Datos!G20,"n.d.") -> 1.1376395 | C44: =IFERROR(Datos!G32/Datos!G46,"n.d.") -> 2.0425044 | D44: =IFERROR(Datos!G58/Datos!G72,"n.d.") -> 1.8415047 | E44: =IFERROR(Datos!G84/Datos!G98,"n.d.") -> 1.0755432
A45: Margen bruto | B45: =IFERROR(Datos!G8/Datos!G6,"n.d.") -> 0.24090359 | C45: =IFERROR(Datos!G34/Datos!G32,"n.d.") -> 0.24238672 | D45: =IFERROR(Datos!G60/Datos!G58,"n.d.") -> 0.22959264 | E45: =IFERROR(Datos!G86/Datos!G84,"n.d.") -> 0.29637336
A46: Margen neto | B46: =IFERROR(Datos!G13/Datos!G6,"n.d.") -> 0.018781511 | C46: =IFERROR(Datos!G39/Datos!G32,"n.d.") -> 0.049318707 | D46: =IFERROR(Datos!G65/Datos!G58,"n.d.") -> 0.022417013 | E46: =IFERROR(Datos!G91/Datos!G84,"n.d.") -> 0.05648874
A47: ROA (anual) | B47: =IFERROR(Datos!G13/Datos!G20,"n.d.") -> 0.02136659 | C47: =IFERROR(Datos!G39/Datos!G46,"n.d.") -> 0.10073368 | D47: =IFERROR(Datos!G65/Datos!G72,"n.d.") -> 0.041281034 | E47: =IFERROR(Datos!G91/Datos!G98,"n.d.") -> 0.060756079
A48: ROE (anual) | B48: =IFERROR(Datos!G13/Datos!G24,"n.d.") -> 0.03934759 | C48: =IFERROR(Datos!G39/Datos!G50,"n.d.") -> 0.21177807 | D48: =IFERROR(Datos!G65/Datos!G76,"n.d.") -> 0.12646073 | E48: =IFERROR(Datos!G91/Datos!G102,"n.d.") -> 0.081495175
A49: ROI (anual) | B49: =IFERROR(Datos!G9*(1-WACC!$B$10)/(Datos!G24+Datos!G29),"n.d.") -> 0.048790032 | C49: =IFERROR(Datos!G35*(1-WACC!$B$10)/(Datos!G50+Datos!G55),"n.d.") -> 0.17364337 | D49: =IFERROR(Datos!G61*(1-WACC!$B$10)/(Datos!G76+Datos!G81),"n.d.") -> 0.096876335 | E49: =IFERROR(Datos!G87*(1-WACC!$B$10)/(Datos!G102+Datos!G107),"n.d.") -> 0.070505439

Sheet Generales
A4: 1. INFORMACIÓN GENERAL DE LA EMPRESA | B4: Dato
A5: Clave de cotización | B5: SORIANA B (BMV, cotiza desde 1987)
A6: Fundación | B6: 1968, Torreón, Coahuila
A7: Sede corporativa | B7: Monterrey, Nuevo León
A8: Giro | B8: Tiendas de autoservicio y clubes de membresía (multiformato)
A9: Tiendas en operación (2T26) | B9: 812
A10: Colaboradores (jun-2026) | B10: 82064
A11: Acciones en circulación (millones) | B11: =WACC!B17 -> 1800
A12: Capitalización de mercado a precio actual (mdp) | B12: =WACC!B18 -> 60264
A14: 2. NOTICIAS Y ANÁLISIS RECIENTES | B14: Fecha
A15: Resultados 2T26: menos ventas, más utilidad | B15: 31-jul-2026
A16: Cierre de 20 tiendas en 2026 | B16: 26-ago-2026
A17: Reducción de plantilla y automatización | B17: 2-sep-2026
A18: Plan de inversión 2S26 | B18: sep-2026
A19: Sector: Walmart, Soriana y Chedraui sufren por ingresos e inflación | B19: 2026
A21: 3. CALIFICACIÓN Y CONSENSO DE ANALISTAS | B21: Dato
A22: Calificación crediticia (HR Ratings) | B22: HR+1 (corto plazo)
A23: Consenso de analistas | B23: Venta
A24: Precio objetivo promedio 12 meses (MXN) | B24: 23.357
A26: 4. ANÁLISIS FUNDAMENTAL – RESUMEN FINANCIERO FY2025 (mdp) | B26: Valor
A27: Ingresos totales | B27: =Datos!G6 -> 177515
A28: Utilidad bruta | B28: =Datos!G8 -> 42764
A29: Utilidad de operación (EBIT) | B29: =Datos!G9 -> 7552
A30: Utilidad neta consolidada | B30: =Datos!G13 -> 3334
A31: Margen bruto | B31: =Datos!G8/Datos!G6 -> 0.24090359
A32: Margen de operación | B32: =Datos!G9/Datos!G6 -> 0.042542884
A33: Margen neto | B33: =Datos!G13/Datos!G6 -> 0.018781511
A35: 5. CUENTA DE RESULTADOS – ÚLTIMO TRIMESTRE (2T26 vs 2T25, mdp) | B35: 2T26
A36: Ingresos totales | B36: =Datos!F6 -> 43559
A37: Costo de ventas | B37: =Datos!F7 -> 32919
A38: Utilidad bruta | B38: =Datos!F8 -> 10640
A39: Utilidad de operación | B39: =Datos!F9 -> 1855
A40: Gastos financieros | B40: =Datos!F10 -> 582
A41: Utilidad neta | B41: =Datos!F13 -> 1090
A43: 6. BALANCE (cierre 2025 vs 1T26, mdp) | B43: Dic-2025
A44: Activo total | B44: =Datos!G20 -> 156038
A45: Pasivo total | B45: =Datos!G23 -> 71306
A46: Capital contable | B46: =Datos!G24 -> 84732
A47: Deuda bancaria y bursátil | B47: =Datos!G25+Datos!G26 -> 11500
A48: Efectivo | B48: =Datos!G17 -> 9295
A50: 7. FLUJOS DE EFECTIVO FY2025 (mdp) | B50: Valor
A51: Flujo neto de operación (CFO) | B51: =Datos!G15 -> 13738
A52: Capex | B52: =Datos!G16 -> 2867
A53: Flujo libre (CFO − Capex) | B53: =B51-B52 -> 10871
A55: 8. ANÁLISIS FUNDAMENTAL – RATIOS DE MERCADO | B55: Valor
A56: P/U (precio / utilidad por acción) | B56: =WACC!B13/(Datos!G13/WACC!B17) -> 18.075585
A57: Valor en libros por acción (MXN) | B57: =Datos!G24/WACC!B17 -> 47.073333
A58: P/VL (precio / valor en libros) | B58: =WACC!B13/B57 -> 0.7112307
A59: ROE anual FY2025 | B59: =Comparativo!B48 -> 0.03934759
A61: 9. DIVIDENDOS | B61: Valor
A62: Último dividendo por acción (MXN) | B62: 0.5556
A63: Rendimiento por dividendo a precio actual | B63: =B62/WACC!B13 -> 0.016594982
A65: 10. REPORTE – PUNTOS CLAVE 2T26
A66: Ventas mismas tiendas 2T26 | B66: −4.5%
A67: Margen bruto 2T26 | B67: =Datos!F8/Datos!F6 -> 0.2442664
A68: Costo financiero neto 2T26 (mdp) | B68: 477
A69: Deuda neta bancaria y bursátil al 2T26 (mdp) | B69: =Datos!F25+Datos!F26-Datos!F17 -> 4624.616
A70: Capex acumulado 1S26 (mdp) | B70: =Datos!E16+Datos!F16 -> 1410.9
A72: 11. PREVISIÓN | B72: Valor
A73: Próximo reporte trimestral (3T26) | B73: 23-oct-2026
A74: Precio objetivo consenso vs precio actual | B74: =B24/WACC!B13-1 -> -0.30235962
A75: Proyección de ingresos 2027 HR Ratings (mdp) | B75: 196480
A77: 12. ANÁLISIS TÉCNICO | B77: Valor
A78: Precio de cierre (MXN) | B78: =WACC!B13 -> 33.48
A79: Rango de 52 semanas (MXN) | B79: 23.90 – 42.70
A80: Variación 1 año | B80: 0.2127
A81: Señal técnica resumen (diaria, semanal y mensual) | B81: Compra fuerte
A82: RSI (14) | B82: 75
A83: MACD (12,26) | B83: 1.154
A84: Media móvil 50 días (MXN) | B84: 29.68
A85: Media móvil 200 días (MXN) | B85: 29.71
A88: 13. COMPARATIVO BURSÁTIL DEL SECTOR | B88: Soriana | C88: Walmex | D88: Chedraui | E88: La Comer
A89: Precio actual (MXN) | B89: =WACC!B13 -> 33.48 | C89: =WACC!C13 -> 46.6 | D89: =WACC!D13 -> 92.94 | E89: =WACC!E13 -> 32.08
A90: P/U | B90: =B56 -> 18.075585 | C90: =WACC!C13/(Datos!G39/WACC!C17) -> 16.308102 | D90: =WACC!D13/(Datos!G65/WACC!D17) -> 13.481171 | E90: =WACC!E13/(Datos!G91/WACC!E17) -> 12.735034
A91: Rendimiento por dividendo | B91: =B63 -> 0.016594982 | C91: 0.0253 | D91: 0.0249 | E91: 0.0088
A92: Variación 1 año | B92: =B80 -> 0.2127 | C92: -0.1686 | D92: -0.4125 | E92: -0.2051
A93: Beta de regresión (referencia) | B93: -0.24 | C93: 0.03 | D93: -0.06 | E93: 0.17
A94: Señal técnica resumen (diaria) | B94: Compra fuerte | C94: Compra fuerte | D94: Compra fuerte | E94: Compra fuerte
A95: RSI (14) | B95: =B82 -> 75 | C95: 41.07 | D95: 60.23 | E95: 40.03
A96: Consenso de analistas | B96: Venta | C96: Neutral | D96: Neutral | E96: Compra
A97: Precio objetivo consenso (MXN) | B97: =Comparativo!B18 -> 23.357 | C97: =Comparativo!C18 -> 60.094 | D97: =Comparativo!D18 -> 128.933 | E97: =Comparativo!E18 -> 47.67
A98: Calificación crediticia | B98: HR+1 (HR Ratings, CP) | C98: n.d. | D98: AAA(mex) Fitch, perspectiva estable | E98: n.d.

Sheet Datos
A5: ORGANIZACIÓN SORIANA (SORIANA B) | B5: 2T25 | C5: 3T25 | D5: 4T25 | E5: 1T26 | F5: 2T26 | G5: FY2025
A6: Ingresos totales | B6: 45810 | C6: 42683 | D6: 47592 | E6: 40444 | F6: 43559 | G6: 177515
A7: Costo de ventas | B7: 34856 | C7: 31998 | D7: 35795 | E7: 30466 | F7: 32919 | G7: 134752
A8: Utilidad bruta | B8: 10954 | C8: 10685 | D8: 11797 | E8: 9978 | F8: 10640 | G8: 42764
A9: Utilidad de operación (EBIT) | B9: 1909 | C9: 1468 | D9: 2486 | E9: 1822 | F9: 1855 | G9: 7552
A10: Gastos financieros (intereses) | B10: 829 | C10: 786 | D10: 616 | E10: 588 | F10: 582 | G10: 3074
A11: Utilidad antes de impuestos | B11: 1203 | C11: 764 | D11: 1763 | E11: 1326 | F11: 1372 | G11: 4766
A12: Impuestos a la utilidad | B12: 461 | C12: 179 | D12: 455 | E12: 492 | F12: 282 | G12: 1433
A13: Utilidad neta consolidada | B13: 743 | C13: 584 | D13: 1308 | E13: 834 | F13: 1090 | G13: 3334
A14: Depreciación y amortización | B14: 1105.905 | C14: 1049.349 | D14: 1051 | E14: 1048.889 | F14: 1030.633 | G14: 4342
A15: Flujo neto de operación (CFO) | B15: 4013.113 | C15: -205.9 | D15: 13017 | E15: -3565.6 | F15: 3916.003 | G15: 13738
A16: Capex (inmuebles, equipo e intangibles) | B16: =SUM(B110:B112) -> 663.2 | C16: =SUM(C110:C112) -> 775.2 | D16: =SUM(D110:D112) -> 816 | E16: =SUM(E110:E112) -> 501 | F16: =SUM(F110:F112) -> 909.9 | G16: 2867
A17: Efectivo y equivalentes | B17: 7540 | C17: 5798 | D17: 9295 | E17: 4589 | F17: 6875.384 | G17: =D17 -> 9295
A18: Inventarios | B18: 37421 | C18: 36394 | D18: 32283 | E18: 32635 | F18: 35486.661 | G18: =D18 -> 32283
A19: Activo circulante | B19: 52131 | C19: 49767 | D19: 48529 | E19: 43562 | F19: 49259.847 | G19: =D19 -> 48529
A20: Activo total | B20: 159842 | C20: 157502 | D20: 156038 | E20: 150941 | F20: =F23+F24 -> 156813 | G20: =D20 -> 156038
A21: Pasivo circulante | B21: 41065 | C21: 38190 | D21: 39219 | E21: 33850 | F21: 41957.933 | G21: =D21 -> 39219
A22: Pasivo a largo plazo | B22: 34801 | C22: 34753 | D22: 32086 | E22: 31527 | F22: =F23-F21 -> 28201.067 | G22: =D22 -> 32086
A23: Pasivo total | B23: 75866 | C23: 72943 | D23: 71306 | E23: 65377 | F23: 70159 | G23: =D23 -> 71306
A24: Capital contable | B24: 83976 | C24: 84559 | D24: 84732 | E24: 85564 | F24: 86654 | G24: =D24 -> 84732
A25: Deuda bursátil y bancaria CP | B25: 6627 | C25: 6553 | D25: 3000 | E25: 3000 | F25: 6500 | G25: =D25 -> 3000
A26: Deuda bursátil y bancaria LP | B26: 11500 | C26: 11500 | D26: 8500 | E26: 8500 | F26: 5000 | G26: =D26 -> 8500
A27: Pasivo por arrendamiento CP | B27: 638 | C27: 659 | D27: 676 | E27: 683 | F27: 639.968 | G27: =D27 -> 676
A28: Pasivo por arrendamiento LP | B28: 11389 | C28: 11506 | D28: 11442 | E28: 11540 | F28: 11580.62 | G28: =D28 -> 11442
A29: Deuda total (financiera + arrendamientos) | B29: =IF(COUNT(B25:B28)=4,SUM(B25:B28),"n.d.") -> 30154 | C29: =IF(COUNT(C25:C28)=4,SUM(C25:C28),"n.d.") -> 30218 | D29: =IF(COUNT(D25:D28)=4,SUM(D25:D28),"n.d.") -> 23618 | E29: =IF(COUNT(E25:E28)=4,SUM(E25:E28),"n.d.") -> 23723 | F29: =IF(COUNT(F25:F28)=4,SUM(F25:F28),"n.d.") -> 23720.588 | G29: =IF(COUNT(G25:G28)=4,SUM(G25:G28),"n.d.") -> 23618
A31: WALMART DE MÉXICO (WALMEX) | B31: 2T25 | C31: 3T25 | D31: 4T25 | E31: 1T26 | F31: 2T26 | G31: FY2025
A32: Ingresos totales | B32: 246253.8 | C32: 241520.2 | D32: 282849.3 | E32: 245018.5 | F32: 250947.8 | G32: 1011597.9
A33: Costo de ventas | B33: 186848.1 | C33: 181746.3 | D33: 214905.4 | E33: 185425.3 | F33: 190822.8 | G33: 766400
A34: Utilidad bruta | B34: 59405.7 | C34: 59773.8 | D34: 67943.9 | E34: 59593.2 | F34: 60125 | G34: 245197.9
A35: Utilidad de operación (EBIT) | B35: 17267.1 | C35: 19020.8 | D35: 23317 | E35: 18471.6 | F35: 17019.7 | G35: 78493.8
A36: Gastos financieros (intereses) | B36: 2646.3 | C36: 3223.3 | D36: 2795.1 | E36: 2895.6 | F36: 2799.6 | G36: 11464.7
A37: Utilidad antes de impuestos | B37: 15076.8 | C37: 16328 | D37: 21053.3 | E37: 16176.4 | F37: 14754.6 | G37: 68876.6
A38: Impuestos a la utilidad | B38: 3849.9 | C38: 4580.7 | D38: 6453.5 | E38: 3676.9 | F38: 3602.2 | G38: 18985.9
A39: Utilidad neta consolidada | B39: 11226.9 | C39: 11747.3 | D39: 14599.8 | E39: 12499.6 | F39: 11152.4 | G39: 49890.7
A40: Depreciación y amortización | B40: 6227.732 | C40: 6245.37 | D40: 6277.929 | E40: 6506.919 | F40: 6620.741 | G40: 24953.1
A41: Flujo neto de operación (CFO) | B41: 21549.377 | C41: 22017.152 | D41: 43314.63 | E41: 4955.647 | F41: 18326.104 | G41: 82437.7
A42: Capex (inmuebles, equipo e intangibles) | B42: =SUM(B113:B115) -> 7989.7 | C42: =SUM(C113:C115) -> 11746.3 | D42: =SUM(D113:D115) -> 15831.8 | E42: =SUM(E113:E115) -> 2436.5 | F42: =SUM(F113:F115) -> 9264.9 | G42: 38982
A43: Efectivo y equivalentes | B43: 32443.8 | C43: 35181.7 | D43: 28591.2 | E43: 28085.1 | F43: 30118.3 | G43: =D43 -> 28591.2
A44: Inventarios | B44: 106742.4 | C44: 113238.4 | D44: 107450.9 | E44: 106202 | F44: 107528.9 | G44: =D44 -> 107450.9
A45: Activo circulante | B45: 166663.9 | C45: 176974.1 | D45: 164109.4 | E45: 163317.9 | F45: 168653.5 | G45: =D45 -> 164109.4
A46: Activo total | B46: 480957.5 | C46: 497334.5 | D46: 495273.3 | E46: 496840.7 | F46: 505946.6 | G46: =D46 -> 495273.3
A47: Pasivo circulante | B47: 177161.4 | C47: 186356.5 | D47: 169716.7 | E47: 153660.1 | F47: 174921.4 | G47: =D47 -> 169716.7
A48: Pasivo a largo plazo | B48: 86252.9 | C48: 87538.9 | D48: 89976.5 | E48: 90611.7 | F48: 92411.4 | G48: =D48 -> 89976.5
A49: Pasivo total | B49: 263414.3 | C49: 273895.4 | D49: 259693.2 | E49: 244271.8 | F49: 267332.8 | G49: =D49 -> 259693.2
A50: Capital contable | B50: 217543.2 | C50: 223439.1 | D50: 235580.1 | E50: 252568.9 | F50: 238613.8 | G50: =D50 -> 235580.1
A51: Deuda bursátil y bancaria CP | B51: 0 | C51: 0 | D51: 0 | E51: 0 | F51: 0 | G51: =D51 -> 0
A52: Deuda bursátil y bancaria LP | B52: 0 | C52: 0 | D52: 0 | E52: 0 | F52: 0 | G52: =D52 -> 0
A53: Pasivo por arrendamiento CP | B53: 4917.5 | C53: 4981.5 | D53: 5186.9 | E53: 5317.6 | F53: 5495.2 | G53: =D53 -> 5186.9
A54: Pasivo por arrendamiento LP | B54: 73863 | C54: 74013.7 | D54: 75661.2 | E54: 75952.9 | F54: 77602.9 | G54: =D54 -> 75661.2
A55: Deuda total (financiera + arrendamientos) | B55: =IF(COUNT(B51:B54)=4,SUM(B51:B54),"n.d.") -> 78780.5 | C55: =IF(COUNT(C51:C54)=4,SUM(C51:C54),"n.d.") -> 78995.2 | D55: =IF(COUNT(D51:D54)=4,SUM(D51:D54),"n.d.") -> 80848.1 | E55: =IF(COUNT(E51:E54)=4,SUM(E51:E54),"n.d.") -> 81270.5 | F55: =IF(COUNT(F51:F54)=4,SUM(F51:F54),"n.d.") -> 83098.1 | G55: =IF(COUNT(G51:G54)=4,SUM(G51:G54),"n.d.") -> 80848.1
A57: GRUPO COMERCIAL CHEDRAUI (CHDRAUI B) | B57: 2T25 | C57: 3T25 | D57: 4T25 | E57: 1T26 | F57: 2T26 | G57: FY2025 | I57: Aux. FY2025
A58: Ingresos totales | B58: 73883.849 | C58: 71768.073 | D58: 75221.137 | E58: 69795.808 | F58: 71034.917 | G58: 295313.65
A59: Costo de ventas | B59: 56049.956 | C59: 54122.158 | D59: 60335.176 | E59: 52843.176 | F59: 53394.045 | G59: 227511.81
A60: Utilidad bruta | B60: 17833.893 | C60: 17645.915 | D60: 14885.961 | E60: 16952.632 | F60: 17640.872 | G60: 67801.84
A61: Utilidad de operación (EBIT) | B61: 4247.997 | C61: 3745.26 | D61: 3402.984 | E61: 3680.616 | F61: 4016.894 | G61: 15097.9
A62: Gastos financieros (intereses) | B62: 880.6 | C62: 944.2 | D62: 1003.1 | E62: 904.7 | F62: 892.5 | G62: 3846.89
A63: Utilidad antes de impuestos | B63: 2986.855 | C63: 2417.756 | D63: 1813.805 | E63: 2306.498 | F63: 2653.783 | G63: 9508.62
A64: Impuestos a la utilidad | B64: 924.533 | C64: 771.393 | D64: 469.642 | E64: 723.238 | F64: 829.095 | G64: 2888.58
A65: Utilidad neta consolidada | B65: 2062.322 | C65: 1646.363 | D65: 1344.163 | E65: 1583.26 | F65: 1824.688 | G65: 6620.05
A66: Depreciación y amortización | B66: 2303.668 | C66: 2297.228 | D66: 2308.71 | E66: 2258.954 | F66: 2312.731 | G66: 9293.25
A67: Flujo neto de operación (CFO) | B67: 5617.816 | C67: 4366.019 | D67: 10197.404 | E67: -756.9 | F67: 5978.777 | G67: 18240.86
A68: Capex (inmuebles, equipo e intangibles) | B68: =SUM(B116:B118) -> 2185.9 | C68: =SUM(C116:C118) -> 2286.1 | D68: =SUM(D116:D118) -> 2688.875 | E68: =SUM(E116:E118) -> 2195.6 | F68: =SUM(F116:F118) -> 2859.1 | G68: =I68 -> 7747.88 | I68: 7747.88 | J68: Inversión neta (−flujo de inversión FY2025), proxy de capex
A69: Efectivo y equivalentes | B69: 9740.315 | C69: 9638.014 | D69: 14640.162 | E69: 10487.937 | F69: 8499.778 | G69: 14640.16
A70: Inventarios | B70: 22914.705 | C70: 23527.624 | D70: 23430.115 | E70: 23660.893 | F70: 22606.468 | G70: =D70 -> 23430.115
A71: Activo circulante | B71: 39608.185 | C71: 41642.553 | D71: 44626.647 | E71: 41294.339 | F71: 38968.064 | G71: 44626.65
A72: Activo total | B72: 154895.84 | C72: 155620.7 | D72: 160365.41 | E72: 156233.2 | F72: 152993.19 | G72: 160365.41
A73: Pasivo circulante | B73: 42247.697 | C73: 43507.303 | D73: 48465.257 | E73: 43264.981 | F73: 43358.105 | G73: 48465.26
A74: Pasivo a largo plazo | B74: =B75-B73 -> 61262.859 | C74: =C75-C73 -> 60415.588 | D74: =D75-D73 -> 59551.489 | E74: =E75-E73 -> 58979.77 | F74: =F75-F73 -> 56310.095 | G74: =G75-G73 -> 59551.49
A75: Pasivo total | B75: 103510.56 | C75: 103922.89 | D75: 108016.75 | E75: 102244.75 | F75: 99668.2 | G75: 108016.75
A76: Capital contable | B76: 51385.283 | C76: 51697.81 | D76: 52348.664 | E76: 53988.454 | F76: 53324.988 | G76: 52348.66
A77: Deuda bursátil y bancaria CP | B77: 1055.054 | C77: 1541.907 | D77: 530.018 | E77: 705.319 | F77: 1087.08 | G77: =D77 -> 530.018
A78: Deuda bursátil y bancaria LP | B78: 7557.12 | C78: 7353.001 | D78: 7186.68 | E78: 7226.68 | F78: 5241 | G78: =D78 -> 7186.68
A79: Pasivo por arrendamiento CP | B79: 2674.355 | C79: 2626.869 | D79: 2925.974 | E79: 3014.648 | F79: 3015.621 | G79: =D79 -> 2925.974
A80: Pasivo por arrendamiento LP | B80: 48473.083 | C80: 47033.289 | D80: 46631.683 | E80: 46405.889 | F80: 45276.747 | G80: =D80 -> 46631.683
A81: Deuda total (financiera + arrendamientos) | B81: =IF(COUNT(B77:B80)=4,SUM(B77:B80),"n.d.") -> 59759.612 | C81: =IF(COUNT(C77:C80)=4,SUM(C77:C80),"n.d.") -> 58555.066 | D81: =IF(COUNT(D77:D80)=4,SUM(D77:D80),"n.d.") -> 57274.355 | E81: =IF(COUNT(E77:E80)=4,SUM(E77:E80),"n.d.") -> 57352.536 | F81: =IF(COUNT(F77:F80)=4,SUM(F77:F80),"n.d.") -> 54620.448 | G81: 56744.34
A83: LA COMER (LACOMER UBC) | B83: 2T25 | C83: 3T25 | D83: 4T25 | E83: 1T26 | F83: 2T26 | G83: FY2025 | I83: 9M2025
A84: Ingresos totales | B84: 12232.6 | C84: 11813.2 | D84: =G84-I84 -> 12404.39 | E84: 12006.5 | F84: 12933.1 | G84: 47526.64 | I84: 35122.25
A85: Costo de ventas | B85: 8718.1 | C85: 8306.7 | D85: =G85-I85 -> 8694.29 | E85: 8328.1 | F85: 9130.7 | G85: 33441.01 | I85: 24746.72
A86: Utilidad bruta | B86: 3514.5 | C86: 3506.5 | D86: =G86-I86 -> 3710.1 | E86: 3678.4 | F86: 3802.4 | G86: 14085.63 | I86: 10375.53
A87: Utilidad de operación (EBIT) | B87: 1026.3 | C87: 839 | D87: =G87-I87 -> 712.57 | E87: 1001.4 | F87: 932.2 | G87: 3564.06 | I87: 2851.49
A88: Gastos financieros (intereses) | B88: 90.2 | C88: 76.7 | D88: 64.9 | E88: 73.3 | F88: 76 | G88: 265.96 | I88: 235.52
A89: Utilidad antes de impuestos | B89: 1003.4 | C89: 817 | D89: =G89-I89 -> 697.65 | E89: 992.7 | F89: 893.8 | G89: 3507.62 | I89: 2809.97
A90: Impuestos a la utilidad | B90: 200.4 | C90: 176.1 | D90: =G90-I90 -> 191.44 | E90: 250.5 | F90: 222.6 | G90: 822.9 | I90: 631.46
A91: Utilidad neta consolidada | B91: 803 | C91: 640.9 | D91: =G91-I91 -> 506.21 | E91: 742.2 | F91: 671.1 | G91: 2684.72 | I91: 2178.51
A92: Depreciación y amortización | B92: 407.835 | C92: 411.717 | D92: 397.26 | E92: 386.412 | F92: 399.125 | G92: =I92/I84*G84 -> 1650.7548 | I92: 1219.91
A93: Flujo neto de operación (CFO) | B93: 1576.03 | C93: 468.589 | D93: 1924.595 | E93: 583.825 | F93: 988.725 | G93: =744.022+B93+C93+D93 -> 4713.236 | I93: 2788.64
A94: Capex (inmuebles, equipo e intangibles) | B94: =SUM(B119:B121) -> 1484.5 | C94: =SUM(C119:C121) -> 912.2 | D94: =SUM(D119:D121) -> 1480.1 | E94: =SUM(E119:E121) -> 606.8 | F94: =SUM(F119:F121) -> 1670.1 | G94: =I94/I84*G84 -> 3842.6724 | I94: 2839.74
A95: Efectivo y equivalentes | B95: 3071.774 | C95: 2615.8 | D95: 2962.8 | E95: 2813 | F95: 1665.7 | G95: =D95 -> 2962.8
A96: Inventarios | B96: 6630.422 | C96: 6020.2 | D96: 5943.1 | E96: 6182.4 | F96: 7365.3 | G96: =D96 -> 5943.1
A97: Activo circulante | B97: 11202.654 | C97: 10026.3 | D97: 10147.2 | E97: 10422.3 | F97: 10810.2 | G97: =D97 -> 10147.2
A98: Activo total | B98: 43616.194 | C98: 42970.2 | D98: 44188.5 | E98: 44754.6 | F98: 46541.8 | G98: =D98 -> 44188.5
A99: Pasivo circulante | B99: 9031.024 | C99: 7608.5 | D99: 8406.7 | E99: 8294 | F99: 9623.2 | G99: =D99 -> 8406.7
A100: Pasivo a largo plazo | B100: =B101-B99 -> 2754.765 | C100: 2852.9 | D100: 2838.5 | E100: 2853 | F100: 3034.5 | G100: =D100 -> 2838.5
A101: Pasivo total | B101: 11785.789 | C101: 10461.4 | D101: 11245.2 | E101: 11147 | F101: 12657.7 | G101: =D101 -> 11245.2
A102: Capital contable | B102: 31830.405 | C102: 32508.8 | D102: 32943.3 | E102: 33607.6 | F102: 33884.1 | G102: =D102 -> 32943.3
A103: Deuda bursátil y bancaria CP | B103: 0 | C103: 0 | D103: 0 | E103: 0 | F103: 0 | G103: =D103 -> 0
A104: Deuda bursátil y bancaria LP | B104: 0 | C104: 0 | D104: 0 | E104: 0 | F104: 0 | G104: =D104 -> 0
A105: Pasivo por arrendamiento CP | B105: 93.389 | C105: 92.3 | D105: 98.3 | E105: 99.7 | F105: 105.6 | G105: =D105 -> 98.3
A106: Pasivo por arrendamiento LP | B106: 2260.347 | C106: 2272.5 | D106: 2343.5 | E106: 2344.7 | F106: 2443.7 | G106: =D106 -> 2343.5
A107: Deuda total (financiera + arrendamientos) | B107: =IF(COUNT(B103:B106)=4,SUM(B103:B106),"n.d.") -> 2353.736 | C107: =IF(COUNT(C103:C106)=4,SUM(C103:C106),"n.d.") -> 2364.8 | D107: =IF(COUNT(D103:D106)=4,SUM(D103:D106),"n.d.") -> 2441.8 | E107: =IF(COUNT(E103:E106)=4,SUM(E103:E106),"n.d.") -> 2444.4 | F107: =IF(COUNT(F103:F106)=4,SUM(F103:F106),"n.d.") -> 2549.3 | G107: =IF(COUNT(G103:G106)=4,SUM(G103:G106),"n.d.") -> 2441.8
...

Sheet Razones
A3: Días del trimestre | B3: 91.25
A6: ORGANIZACIÓN SORIANA | B6: 2T25 | C6: 3T25 | D6: 4T25 | E6: 1T26 | F6: 2T26 | G6: Promedio 5T
A7: Circulante | B7: =Datos!B19/Datos!B21 -> 1.2694752 | C7: =Datos!C19/Datos!C21 -> 1.3031422 | D7: =Datos!D19/Datos!D21 -> 1.2373849 | E7: =Datos!E19/Datos!E21 -> 1.2869129 | F7: =Datos!F19/Datos!F21 -> 1.1740294 | G7: =AVERAGE(B7:F7) -> 1.2541889
A8: Prueba ácida | B8: =(Datos!B19-Datos!B18)/Datos!B21 -> 0.35821259 | C8: =(Datos!C19-Datos!C18)/Datos!C21 -> 0.3501702 | D8: =(Datos!D19-Datos!D18)/Datos!D21 -> 0.414238 | E8: =(Datos!E19-Datos!E18)/Datos!E21 -> 0.3228065 | F8: =(Datos!F19-Datos!F18)/Datos!F21 -> 0.32826179 | G8: =AVERAGE(B8:F8) -> 0.35473781
A9: Deuda / Activo total | B9: =Datos!B23/Datos!B20 -> 0.4746312 | C9: =Datos!C23/Datos!C20 -> 0.46312428 | D9: =Datos!D23/Datos!D20 -> 0.45697843 | E9: =Datos!E23/Datos!E20 -> 0.4331295 | F9: =Datos!F23/Datos!F20 -> 0.44740551 | G9: =AVERAGE(B9:F9) -> 0.45505378
A10: Capitalización a largo plazo | B10: =Datos!B22/Datos!B20 -> 0.21772125 | C10: =Datos!C22/Datos!C20 -> 0.22065117 | D10: =Datos!D22/Datos!D20 -> 0.2056294 | E10: =Datos!E22/Datos!E20 -> 0.20886969 | F10: =Datos!F22/Datos!F20 -> 0.17983883 | G10: =AVERAGE(B10:F10) -> 0.20654207
A11: Cobertura de intereses | B11: =Datos!B9/Datos!B10 -> 2.3027744 | C11: =Datos!C9/Datos!C10 -> 1.8676845 | D11: =Datos!D9/Datos!D10 -> 4.0357143 | E11: =Datos!E9/Datos!E10 -> 3.0986395 | F11: =Datos!F9/Datos!F10 -> 3.1872852 | G11: =AVERAGE(B11:F11) -> 2.8984196
A12: Rotación del inventario | B12: =Datos!B7/Datos!B18 -> 0.9314556 | C12: =Datos!C7/Datos!C18 -> 0.87921086 | D12: =Datos!D7/Datos!D18 -> 1.1087879 | E12: =Datos!E7/Datos!E18 -> 0.93353761 | F12: =Datos!F7/Datos!F18 -> 0.92764433 | G12: =AVERAGE(B12:F12) -> 0.95612726
A13: Rotación del inventario en días | B13: =$B$3*Datos!B18/Datos!B7 -> 97.964949 | C13: =$B$3*Datos!C18/Datos!C7 -> 103.78625 | D13: =$B$3*Datos!D18/Datos!D7 -> 82.297074 | E13: =$B$3*Datos!E18/Datos!E7 -> 97.746463 | F13: =$B$3*Datos!F18/Datos!F7 -> 98.367442 | G13: =AVERAGE(B13:F13) -> 96.032436
A14: Rotación del activo total | B14: =Datos!B6/Datos!B20 -> 0.28659551 | C14: =Datos!C6/Datos!C20 -> 0.27099973 | D14: =Datos!D6/Datos!D20 -> 0.30500263 | E14: =Datos!E6/Datos!E20 -> 0.26794575 | F14: =Datos!F6/Datos!F20 -> 0.27777671 | G14: =AVERAGE(B14:F14) -> 0.28166407
A15: Margen bruto | B15: =Datos!B8/Datos!B6 -> 0.2391181 | C15: =Datos!C8/Datos!C6 -> 0.25033386 | D15: =Datos!D8/Datos!D6 -> 0.24787779 | E15: =Datos!E8/Datos!E6 -> 0.2467115 | F15: =Datos!F8/Datos!F6 -> 0.2442664 | G15: =AVERAGE(B15:F15) -> 0.24566153
A16: Margen neto | B16: =Datos!B13/Datos!B6 -> 0.016219166 | C16: =Datos!C13/Datos!C6 -> 0.013682262 | D16: =Datos!D13/Datos!D6 -> 0.027483611 | E16: =Datos!E13/Datos!E6 -> 0.020621106 | F16: =Datos!F13/Datos!F6 -> 0.025023531 | G16: =AVERAGE(B16:F16) -> 0.020605935
A17: Rentabilidad sobre activos (ROA) | B17: =Datos!B13/Datos!B20 -> 0.0046483402 | C17: =Datos!C13/Datos!C20 -> 0.0037078894 | D17: =Datos!D13/Datos!D20 -> 0.0083825735 | E17: =Datos!E13/Datos!E20 -> 0.0055253377 | F17: =Datos!F13/Datos!F20 -> 0.0069509543 | G17: =AVERAGE(B17:F17) -> 0.005843019
A18: Rentabilidad sobre capital (ROE) | B18: =Datos!B13/Datos!B24 -> 0.008847766 | C18: =Datos!C13/Datos!C24 -> 0.0069064204 | D18: =Datos!D13/Datos!D24 -> 0.015436907 | E18: =Datos!E13/Datos!E24 -> 0.0097470899 | F18: =Datos!F13/Datos!F24 -> 0.012578762 | G18: =AVERAGE(B18:F18) -> 0.010703389
A19: ROI (rendimiento sobre la inversión) | B19: =Datos!B9*(1-WACC!$B$10)/(Datos!B24+Datos!B29) -> 0.011708578 | C19: =Datos!C9*(1-WACC!$B$10)/(Datos!C24+Datos!C29) -> 0.0089530132 | D19: =Datos!D9*(1-WACC!$B$10)/(Datos!D24+Datos!D29) -> 0.016060914 | E19: =Datos!E9*(1-WACC!$B$10)/(Datos!E24+Datos!E29) -> 0.01167019 | F19: =Datos!F9*(1-WACC!$B$10)/(Datos!F24+Datos!F29) -> 0.011764483 | G19: =AVERAGE(B19:F19) -> 0.012031436
A22: WALMART DE MÉXICO | B22: 2T25 | C22: 3T25 | D22: 4T25 | E22: 1T26 | F22: 2T26 | G22: Promedio 5T
A23: Circulante | B23: =Datos!B45/Datos!B47 -> 0.94074612 | C23: =Datos!C45/Datos!C47 -> 0.94965349 | D23: =Datos!D45/Datos!D47 -> 0.96696082 | E23: =Datos!E45/Datos!E47 -> 1.0628517 | F23: =Datos!F45/Datos!F47 -> 0.96416733 | G23: =AVERAGE(B23:F23) -> 0.9768759
A24: Prueba ácida | B24: =(Datos!B45-Datos!B44)/Datos!B47 -> 0.33823113 | C24: =(Datos!C45-Datos!C44)/Datos!C47 -> 0.34200954 | D24: =(Datos!D45-Datos!D44)/Datos!D47 -> 0.33384163 | E24: =(Datos!E45-Datos!E44)/Datos!E47 -> 0.37170287 | F24: =(Datos!F45-Datos!F44)/Datos!F47 -> 0.34944038 | G24: =AVERAGE(B24:F24) -> 0.34704511
A25: Deuda / Activo total | B25: =Datos!B49/Datos!B46 -> 0.54768727 | C25: =Datos!C49/Datos!C46 -> 0.55072672 | D25: =Datos!D49/Datos!D46 -> 0.52434323 | E25: =Datos!E49/Datos!E46 -> 0.49165014 | F25: =Datos!F49/Datos!F46 -> 0.52838145 | G25: =AVERAGE(B25:F25) -> 0.52855776
A26: Capitalización a largo plazo | B26: =Datos!B48/Datos!B46 -> 0.1793358 | C26: =Datos!C48/Datos!C46 -> 0.17601614 | D26: =Datos!D48/Datos!D46 -> 0.1816704 | E26: =Datos!E48/Datos!E46 -> 0.18237576 | F26: =Datos!F48/Datos!F46 -> 0.1826505 | G26: =AVERAGE(B26:F26) -> 0.18040972
A27: Cobertura de intereses | B27: =Datos!B35/Datos!B36 -> 6.5249972 | C27: =Datos!C35/Datos!C36 -> 5.9010331 | D27: =Datos!D35/Datos!D36 -> 8.3420987 | E27: =Datos!E35/Datos!E36 -> 6.379196 | F27: =Datos!F35/Datos!F36 -> 6.0793328 | G27: =AVERAGE(B27:F27) -> 6.6453315
A28: Rotación del inventario | B28: =Datos!B33/Datos!B44 -> 1.7504581 | C28: =Datos!C33/Datos!C44 -> 1.6049882 | D28: =Datos!D33/Datos!D44 -> 2.0000335 | E28: =Datos!E33/Datos!E44 -> 1.7459681 | F28: =Datos!F33/Datos!F44 -> 1.7746187 | G28: =AVERAGE(B28:F28) -> 1.7752133
A29: Rotación del inventario en días | B29: =$B$3*Datos!B44/Datos!B33 -> 52.129211 | C29: =$B$3*Datos!C44/Datos!C33 -> 56.853999 | D29: =$B$3*Datos!D44/Datos!D33 -> 45.624236 | E29: =$B$3*Datos!E44/Datos!E33 -> 52.26327 | F29: =$B$3*Datos!F44/Datos!F33 -> 51.419496 | G29: =AVERAGE(B29:F29) -> 51.658042
A30: Rotación del activo total | B30: =Datos!B32/Datos!B46 -> 0.5120074 | C30: =Datos!C32/Datos!C46 -> 0.48562929 | D30: =Datos!D32/Datos!D46 -> 0.57109741 | E30: =Datos!E32/Datos!E46 -> 0.49315304 | F30: =Datos!F32/Datos!F46 -> 0.49599661 | G30: =AVERAGE(B30:F30) -> 0.51157675
A31: Margen bruto | B31: =Datos!B34/Datos!B32 -> 0.2412377 | C31: =Datos!C34/Datos!C32 -> 0.24748986 | D31: =Datos!D34/Datos!D32 -> 0.24021237 | E31: =Datos!E34/Datos!E32 -> 0.24321919 | F31: =Datos!F34/Datos!F32 -> 0.23959166 | G31: =AVERAGE(B31:F31) -> 0.24235015
A32: Margen neto | B32: =Datos!B39/Datos!B32 -> 0.045590769 | C32: =Datos!C39/Datos!C32 -> 0.048638996 | D32: =Datos!D39/Datos!D32 -> 0.051616886 | E32: =Datos!E39/Datos!E32 -> 0.051014923 | F32: =Datos!F39/Datos!F32 -> 0.044441115 | G32: =AVERAGE(B32:F32) -> 0.048260538
A33: Rentabilidad sobre activos (ROA) | B33: =Datos!B39/Datos!B46 -> 0.023342811 | C33: =Datos!C39/Datos!C46 -> 0.023620521 | D33: =Datos!D39/Datos!D46 -> 0.02947827 | E33: =Datos!E39/Datos!E46 -> 0.025158164 | F33: =Datos!F39/Datos!F46 -> 0.022042642 | G33: =AVERAGE(B33:F33) -> 0.024728482
A34: Rentabilidad sobre capital (ROE) | B34: =Datos!B39/Datos!B50 -> 0.051607681 | C34: =Datos!C39/Datos!C50 -> 0.052574952 | D34: =Datos!D39/Datos!D50 -> 0.061973825 | E34: =Datos!E39/Datos!E50 -> 0.049489862 | F34: =Datos!F39/Datos!F50 -> 0.046738286 | G34: =AVERAGE(B34:F34) -> 0.052476921
A35: ROI (rendimiento sobre la inversión) | B35: =Datos!B35*(1-WACC!$B$10)/(Datos!B50+Datos!B55) -> 0.040789751 | C35: =Datos!C35*(1-WACC!$B$10)/(Datos!C50+Datos!C55) -> 0.044024636 | D35: =Datos!D35*(1-WACC!$B$10)/(Datos!D50+Datos!D55) -> 0.051581686 | E35: =Datos!E35*(1-WACC!$B$10)/(Datos!E50+Datos!E55) -> 0.038731558 | F35: =Datos!F35*(1-WACC!$B$10)/(Datos!F50+Datos!F55) -> 0.037032482 | G35: =AVERAGE(B35:F35) -> 0.042432022
A38: GRUPO COMERCIAL CHEDRAUI | B38: 2T25 | C38: 3T25 | D38: 4T25 | E38: 1T26 | F38: 2T26 | G38: Promedio 5T
A39: Circulante | B39: =Datos!B71/Datos!B73 -> 0.93752294 | C39: =Datos!C71/Datos!C73 -> 0.95713938 | D39: =Datos!D71/Datos!D73 -> 0.92079666 | E39: =Datos!E71/Datos!E73 -> 0.9544518 | F39: =Datos!F71/Datos!F73 -> 0.89874924 | G39: =AVERAGE(B39:F39) -> 0.933732
A40: Prueba ácida | B40: =(Datos!B71-Datos!B70)/Datos!B73 -> 0.39513349 | C40: =(Datos!C71-Datos!C70)/Datos!C73 -> 0.41636525 | D40: =(Datos!D71-Datos!D70)/Datos!D73 -> 0.4373552 | E40: =(Datos!E71-Datos!E70)/Datos!E73 -> 0.40756856 | F40: =(Datos!F71-Datos!F70)/Datos!F73 -> 0.37735957 | G40: =AVERAGE(B40:F40) -> 0.40675641
A41: Deuda / Activo total | B41: =Datos!B75/Datos!B72 -> 0.66825911 | C41: =Datos!C75/Datos!C72 -> 0.66779606 | D41: =Datos!D75/Datos!D72 -> 0.67356636 | E41: =Datos!E75/Datos!E72 -> 0.65443675 | F41: =Datos!F75/Datos!F72 -> 0.65145515 | G41: =AVERAGE(B41:F41) -> 0.66310269
A42: Capitalización a largo plazo | B42: =Datos!B74/Datos!B72 -> 0.39551004 | C42: =Datos!C74/Datos!C72 -> 0.38822334 | D42: =Datos!D74/Datos!D72 -> 0.37134872 | E42: =Datos!E74/Datos!E72 -> 0.37751111 | F42: =Datos!F74/Datos!F72 -> 0.36805622 | G42: =AVERAGE(B42:F42) -> 0.38012988
A43: Cobertura de intereses | B43: =Datos!B61/Datos!B62 -> 4.8239802 | C43: =Datos!C61/Datos!C62 -> 3.9665961 | D43: =Datos!D61/Datos!D62 -> 3.3924674 | E43: =Datos!E61/Datos!E62 -> 4.0683276 | F43: =Datos!F61/Datos!F62 -> 4.5007216 | G43: =AVERAGE(B43:F43) -> 4.1504186
A44: Rotación del inventario | B44: =Datos!B59/Datos!B70 -> 2.4460256 | C44: =Datos!C59/Datos!C70 -> 2.3003665 | D44: =Datos!D59/Datos!D70 -> 2.5751122 | E44: =Datos!E59/Datos!E70 -> 2.2333551 | F44: =Datos!F59/Datos!F70 -> 2.3618924 | G44: =AVERAGE(B44:F44) -> 2.3833504
A45: Rotación del inventario en días | B45: =$B$3*Datos!B70/Datos!B59 -> 37.305414 | C45: =$B$3*Datos!C70/Datos!C59 -> 39.667592 | D45: =$B$3*Datos!D70/Datos!D59 -> 35.435349 | E45: =$B$3*Datos!E70/Datos!E59 -> 40.857811 | F45: =$B$3*Datos!F70/Datos!F59 -> 38.634275 | G45: =AVERAGE(B45:F45) -> 38.380088
A46: Rotación del activo total | B46: =Datos!B58/Datos!B72 -> 0.47699053 | C46: =Datos!C58/Datos!C72 -> 0.46117305 | D46: =Datos!D58/Datos!D72 -> 0.46906086 | E46: =Datos!E58/Datos!E72 -> 0.44674119 | F46: =Datos!F58/Datos!F72 -> 0.46430118 | G46: =AVERAGE(B46:F46) -> 0.46365336
A47: Margen bruto | B47: =Datos!B60/Datos!B58 -> 0.24137742 | C47: =Datos!C60/Datos!C58 -> 0.24587416 | D47: =Datos!D60/Datos!D58 -> 0.19789599 | E47: =Datos!E60/Datos!E58 -> 0.24288897 | F47: =Datos!F60/Datos!F58 -> 0.24834085 | G47: =AVERAGE(B47:F47) -> 0.23527548
A48: Margen neto | B48: =Datos!B65/Datos!B58 -> 0.027913029 | C48: =Datos!C65/Datos!C58 -> 0.022940047 | D48: =Datos!D65/Datos!D58 -> 0.017869485 | E48: =Datos!E65/Datos!E58 -> 0.02268417 | F48: =Datos!F65/Datos!F58 -> 0.025687198 | G48: =AVERAGE(B48:F48) -> 0.023418786
A49: Rentabilidad sobre activos (ROA) | B49: =Datos!B65/Datos!B72 -> 0.01331425 | C49: =Datos!C65/Datos!C72 -> 0.010579332 | D49: =Datos!D65/Datos!D72 -> 0.0083818761 | E49: =Datos!E65/Datos!E72 -> 0.010133953 | F49: =Datos!F65/Datos!F72 -> 0.011926596 | G49: =AVERAGE(B49:F49) -> 0.010867202
A50: Rentabilidad sobre capital (ROE) | B50: =Datos!B65/Datos!B76 -> 0.040134488 | C50: =Datos!C65/Datos!C76 -> 0.031845894 | D50: =Datos!D65/Datos!D76 -> 0.025677121 | E50: =Datos!E65/Datos!E76 -> 0.0293259 | F50: =Datos!F65/Datos!F76 -> 0.034218254 | G50: =AVERAGE(B50:F50) -> 0.032240332
A51: ROI (rendimiento sobre la inversión) | B51: =Datos!B61*(1-WACC!$B$10)/(Datos!B76+Datos!B81) -> 0.026754246 | C51: =Datos!C61*(1-WACC!$B$10)/(Datos!C76+Datos!C81) -> 0.023778808 | D51: =Datos!D61*(1-WACC!$B$10)/(Datos!D76+Datos!D81) -> 0.021729823 | E51: =Datos!E61*(1-WACC!$B$10)/(Datos!E76+Datos!E81) -> 0.023140006 | F51: =Datos!F61*(1-WACC!$B$10)/(Datos!F76+Datos!F81) -> 0.026048584 | G51: =AVERAGE(B51:F51) -> 0.024290294
A54: LA COMER | B54: 2T25 | C54: 3T25 | D54: 4T25 | E54: 1T26 | F54: 2T26 | G54: Promedio 5T
A55: Circulante | B55: =Datos!B97/Datos!B99 -> 1.2404633 | C55: =Datos!C97/Datos!C99 -> 1.3177762 | D55: =Datos!D97/Datos!D99 -> 1.2070372 | E55: =Datos!E97/Datos!E99 -> 1.2566072 | F55: =Datos!F97/Datos!F99 -> 1.1233477 | G55: =AVERAGE(B55:F55) -> 1.2290463
A56: Prueba ácida | B56: =(Datos!B97-Datos!B96)/Datos!B99 -> 0.50628057 | C56: =(Datos!C97-Datos!C96)/Datos!C99 -> 0.52652954 | D56: =(Datos!D97-Datos!D96)/Datos!D99 -> 0.50008921 | E56: =(Datos!E97-Datos!E96)/Datos!E99 -> 0.51120087 | F56: =(Datos!F97-Datos!F96)/Datos!F99 -> 0.35797863 | G56: =AVERAGE(B56:F56) -> 0.48041577
A57: Deuda / Activo total | B57: =Datos!B101/Datos!B98 -> 0.2702159 | C57: =Datos!C101/Datos!C98 -> 0.24345709 | D57: =Datos!D101/Datos!D98 -> 0.2544825 | E57: =Datos!E101/Datos!E98 -> 0.24906937 | F57: =Datos!F101/Datos!F98 -> 0.27196413 | G57: =AVERAGE(B57:F57) -> 0.2578378
A58: Capitalización a largo plazo | B58: =Datos!B100/Datos!B98 -> 0.063159225 | C58: =Datos!C100/Datos!C98 -> 0.066392523 | D58: =Datos!D100/Datos!D98 -> 0.06423617 | E58: =Datos!E100/Datos!E98 -> 0.063747637 | F58: =Datos!F100/Datos!F98 -> 0.065199455 | G58: =AVERAGE(B58:F58) -> 0.064547002
A59: Cobertura de intereses | B59: =Datos!B87/Datos!B88 -> 11.378049 | C59: =Datos!C87/Datos!C88 -> 10.938722 | D59: =Datos!D87/Datos!D88 -> 10.979507 | E59: =Datos!E87/Datos!E88 -> 13.661664 | F59: =Datos!F87/Datos!F88 -> 12.265789 | G59: =AVERAGE(B59:F59) -> 11.844746
A60: Rotación del inventario | B60: =Datos!B85/Datos!B96 -> 1.3148635 | C60: =Datos!C85/Datos!C96 -> 1.3798047 | D60: =Datos!D85/Datos!D96 -> 1.4629217 | E60: =Datos!E85/Datos!E96 -> 1.3470659 | F60: =Datos!F85/Datos!F96 -> 1.2396915 | G60: =AVERAGE(B60:F60) -> 1.3488695
A61: Rotación del inventario en días | B61: =$B$3*Datos!B96/Datos!B85 -> 69.398838 | C61: =$B$3*Datos!C96/Datos!C85 -> 66.13255 | D61: =$B$3*Datos!D96/Datos!D85 -> 62.375177 | E61: =$B$3*Datos!E96/Datos!E85 -> 67.739821 | F61: =$B$3*Datos!F96/Datos!F85 -> 73.607021 | G61: =AVERAGE(B61:F61) -> 67.850681
A62: Rotación del activo total | B62: =Datos!B84/Datos!B98 -> 0.28046005 | C62: =Datos!C84/Datos!C98 -> 0.2749161 | D62: =Datos!D84/Datos!D98 -> 0.28071534 | E62: =Datos!E84/Datos!E98 -> 0.2682741 | F62: =Datos!F84/Datos!F98 -> 0.27788139 | G62: =AVERAGE(B62:F62) -> 0.2764494
A63: Margen bruto | B63: =Datos!B86/Datos!B84 -> 0.28730605 | C63: =Datos!C86/Datos!C84 -> 0.29682897 | D63: =Datos!D86/Datos!D84 -> 0.29909572 | E63: =Datos!E86/Datos!E84 -> 0.30636738 | F63: =Datos!F86/Datos!F84 -> 0.2940053 | G63: =AVERAGE(B63:F63) -> 0.29672069
A64: Margen neto | B64: =Datos!B91/Datos!B84 -> 0.065644262 | C64: =Datos!C91/Datos!C84 -> 0.05425287 | D64: =Datos!D91/Datos!D84 -> 0.040808939 | E64: =Datos!E91/Datos!E84 -> 0.061816516 | F64: =Datos!F91/Datos!F84 -> 0.051890111 | G64: =AVERAGE(B64:F64) -> 0.05488254
A65: Rentabilidad sobre activos (ROA) | B65: =Datos!B91/Datos!B98 -> 0.018410593 | C65: =Datos!C91/Datos!C98 -> 0.014914988 | D65: =Datos!D91/Datos!D98 -> 0.011455695 | E65: =Datos!E91/Datos!E98 -> 0.01658377 | F65: =Datos!F91/Datos!F98 -> 0.014419296 | G65: =AVERAGE(B65:F65) -> 0.015156869
A66: Rentabilidad sobre capital (ROE) | B66: =Datos!B91/Datos!B102 -> 0.025227452 | C66: =Datos!C91/Datos!C102 -> 0.019714662 | D66: =Datos!D91/Datos!D102 -> 0.015366099 | E66: =Datos!E91/Datos!E102 -> 0.02208429 | F66: =Datos!F91/Datos!F102 -> 0.01980575 | G66: =AVERAGE(B66:F66) -> 0.02043965
A67: ROI (rendimiento sobre la inversión) | B67: =Datos!B87*(1-WACC!$B$10)/(Datos!B102+Datos!B107) -> 0.021015886 | C67: =Datos!C87*(1-WACC!$B$10)/(Datos!C102+Datos!C107) -> 0.016840819 | D67: =Datos!D87*(1-WACC!$B$10)/(Datos!D102+Datos!D107) -> 0.0140963 | E67: =Datos!E87*(1-WACC!$B$10)/(Datos!E102+Datos!E107) -> 0.019443581 | F67: =Datos!F87*(1-WACC!$B$10)/(Datos!F102+Datos!F107) -> 0.017910489 | G67: =AVERAGE(B67:F67) -> 0.017861415

Sheet WACC
A3: Concepto | B3: Soriana | C3: Walmex | D3: Chedraui | E3: La Comer
A4: PARÁMETROS DE MERCADO
A5: Tasa libre de riesgo (Bono M 10 años) | B5: 0.09517 | C5: =$B$5 -> 0.09517 | D5: =$B$5 -> 0.09517 | E5: =$B$5 -> 0.09517
A6: Prima de riesgo de mercado madura | B6: 0.0423 | C6: =$B$6 -> 0.0423 | D6: =$B$6 -> 0.0423 | E6: =$B$6 -> 0.0423
A7: Prima de riesgo país México (referencia) | B7: 0.0246 | C7: =$B$7 -> 0.0246 | D7: =$B$7 -> 0.0246 | E7: =$B$7 -> 0.0246
A8: Prima de riesgo de mercado aplicada (PRM) | B8: =B6 -> 0.0423 | C8: =C6 -> 0.0423 | D8: =D6 -> 0.0423 | E8: =E6 -> 0.0423
A9: Beta desapalancada usada (regresión semanal Soriana B vs. IPC, desapalancada; ver hoja 'Beta y Kd' §2). Damodaran 0.69 queda como referencia | B9: ='Beta y Kd'!B19 -> 0.17052082 | C9: =$B$9 -> 0.17052082 | D9: =$B$9 -> 0.17052082 | E9: =$B$9 -> 0.17052082 | F9: Beta histórica del estudio (regresión): ver hoja Inflación, sección 6.
A10: Tasa de impuestos (ISR) | B10: 0.3 | C10: =$B$10 -> 0.3 | D10: =$B$10 -> 0.3 | E10: =$B$10 -> 0.3
A12: DATOS DE MERCADO
A13: Precio actual por acción (MXN) | B13: 33.48 | C13: 46.6 | D13: 92.94 | E13: 32.08
A14: Fecha del precio | B14: 46290 | C14: 46266 | D14: 21-ago-2026 | E14: 46266
A15: Capitalización de mercado reportada | B15: 54180 | C15: 801750 | D15: 89150 | E15: 34190
A16: Precio de cierre asociado a esa capitalización (MXN) | B16: 30.1 | C16: 45.92 | D16: 92.84 | E16: 32.08
A17: Acciones en circulación (millones) | B17: =B15/B16 -> 1800 | C17: =C15/C16 -> 17459.713 | D17: =D15/D16 -> 960.2542 | E17: =E15/E16 -> 1065.7731
A18: Valor de mercado del capital (E) | B18: =B17*B13 -> 60264 | C18: =C17*C13 -> 813622.6 | D18: =D17*D13 -> 89246.025 | E18: =E17*E13 -> 34190
A20: ESTRUCTURA DE CAPITAL (cierre 2025)
A21: Deuda total (D) = bancaria/bursátil + arrendamientos | B21: =Datos!G29 -> 23618 | C21: =Datos!G55 -> 80848.1 | D21: =Datos!G81 -> 56744.34 | E21: =Datos!G107 -> 2441.8
A22: Efectivo y equivalentes | B22: =Datos!G17 -> 9295 | C22: =Datos!G43 -> 28591.2 | D22: =Datos!G69 -> 14640.16 | E22: =Datos!G95 -> 2962.8
A23: D / E | B23: =B21/B18 -> 0.39190893 | C23: =C21/C18 -> 0.09936806 | D23: =D21/D18 -> 0.63581924 | E23: =E21/E18 -> 0.071418543
A24: Peso de la deuda D/(D+E) | B24: =B21/(B21+B18) -> 0.28156219 | C24: =C21/(C21+C18) -> 0.090386526 | D24: =D21/(D21+D18) -> 0.38868551 | E24: =E21/(E21+E18) -> 0.066657931
A25: Peso del capital E/(D+E) | B25: =B18/(B21+B18) -> 0.71843781 | C25: =C18/(C21+C18) -> 0.90961347 | D25: =D18/(D21+D18) -> 0.61131449 | E25: =E18/(E21+E18) -> 0.93334207
A27: COSTO DE CAPITAL
A28: Beta apalancada βL = βU × [1 + (1−t)·D/E] | B28: =B9*(1+(1-B10)*B23) -> 0.21730086 | C28: =C9*(1+(1-C10)*C23) -> 0.18238184 | D28: =D9*(1+(1-D10)*D23) -> 0.24641511 | E28: =E9*(1+(1-E10)*E23) -> 0.17904566
A29: Costo del capital propio Ke = Rf + βL × PRM | B29: =B5+B28*B8 -> 0.10436183 | C29: =C5+C28*C8 -> 0.10288475 | D29: =D5+D28*D8 -> 0.10559336 | E29: =E5+E28*E8 -> 0.10274363
A30: Gastos financieros FY2025 | B30: =Datos!G10 -> 3074 | C30: =Datos!G36 -> 11464.7 | D30: =Datos!G62 -> 3846.89 | E30: =Datos!G88 -> 265.96
A31: Costo de la deuda antes de impuestos Kd | B31: =B30/B21 -> 0.13015497 | C31: =C30/C21 -> 0.14180544 | D31: =D30/D21 -> 0.067793369 | E31: =E30/E21 -> 0.10891965
A32: Costo de la deuda después de impuestos Kd(1−t) | B32: =B31*(1-B10) -> 0.091108477 | C32: =C31*(1-C10) -> 0.099263805 | D32: =D31*(1-D10) -> 0.047455359 | E32: =E31*(1-E10) -> 0.076243755
A33: WACC = E/(D+E)·Ke + D/(D+E)·Kd(1−t) | B33: =B25*B29+B24*B32 -> 0.10063018 | C33: =C25*C29+C24*C32 -> 0.10255747 | D33: =D25*D29+D24*D32 -> 0.082995961 | E33: =E25*E29+E24*E32 -> 0.1009772
A35: CONCILIACIÓN CON EL WACC OFICIAL DEL DCF
A36: WACC oficial (iterado al valor DCF, Kd prospectivo) — usado en la valuación | B36: ='Proyección Final Soriana'!B126 -> 0.095627784
A37: WACC de referencia a valor de mercado (esta hoja, Kd histórico) | B37: =B33 -> 0.10063018
A38: Diferencia (referencia − oficial) | B38: =B37-B36 -> 0.0050023999
A39: Kd histórico FY2025 = gastos financieros / deuda | B39: =B31 -> 0.13015497
A40: Kd prospectivo usado en el DCF | B40: ='Proyección Final Soriana'!B206 -> 0.1
A41: Kd implícito 1S26 = (intereses 1T26 + 2T26) × 2 / deuda | B41: =(Datos!E10+Datos!F10)*2/B21 -> 0.099076975
A42: Lectura: el WACC oficial es el iterado. El de esta hoja usa pesos de mercado y el Kd de 2025 (tasas más altas); el Kd implícito del 1S26 respalda el 10% prospectivo.

Sheet Valuación
A4: Crecimiento perpetuo (g) para valor terminal | B4: 0.035
A5: Crecimiento anual de ventas 2026E–2030E (supuesto base) | B5: 0.035
A8: ORGANIZACIÓN SORIANA | B8: 2025A | C8: 2026E | D8: 2027E | E8: 2028E | F8: 2029E | G8: 2030E
A9: Crecimiento anual de ventas (explícito) | B9: =$B$5 -> 0.035
A10: Margen EBIT | B10: =Datos!G9/Datos!G6 -> 0.042542884
A11: Depreciación y amortización (% ventas) | B11: =Datos!G14/Datos!G6 -> 0.024459905
A12: Capex (% ventas) | B12: =Datos!G16/Datos!G6 -> 0.016150748
A13: Inversión en capital de trabajo (% del incremento en ventas) | B13: =-SUM('Proyección Soriana'!C64:G64)/('Proyección Soriana'!G19-'Proyección Soriana'!B19) -> 0.020792609
A14: Tasa de impuestos | B14: =WACC!B10 -> 0.3
A15: WACC | B15: =WACC!B33 -> 0.10063018
A16: Crecimiento perpetuo (g) | B16: =$B$4 -> 0.035
A18: PROYECCIÓN DEL FLUJO LIBRE DE EFECTIVO (FCF) | B18: 2025A | C18: 2026E | D18: 2027E | E18: 2028E | F18: 2029E | G18: 2030E
A19: Periodo (n) | B19: 0 | C19: 1 | D19: 2 | E19: 3 | F19: 4 | G19: 5
A20: Ventas | B20: =Datos!G6 -> 177515 | C20: =B20*(1+$B$9) -> 183728.02 | D20: =C20*(1+$B$9) -> 190158.51 | E20: =D20*(1+$B$9) -> 196814.05 | F20: =E20*(1+$B$9) -> 203702.55 | G20: =F20*(1+$B$9) -> 210832.13
A21: Utilidad de operación (EBIT) | B21: =Datos!G9 -> 7552 | C21: =C20*$B$10 -> 7816.32 | D21: =D20*$B$10 -> 8089.8912 | E21: =E20*$B$10 -> 8373.0374 | F21: =F20*$B$10 -> 8666.0937 | G21: =G20*$B$10 -> 8969.407
A22: (−) Impuestos sobre EBIT | B22: =-B21*$B$14 -> -2265.6 | C22: =-C21*$B$14 -> -2344.896 | D22: =-D21*$B$14 -> -2426.9674 | E22: =-E21*$B$14 -> -2511.9112 | F22: =-F21*$B$14 -> -2599.8281 | G22: =-G21*$B$14 -> -2690.8221
A23: NOPAT (EBIT después de impuestos) | B23: =B21+B22 -> 5286.4 | C23: =C21+C22 -> 5471.424 | D23: =D21+D22 -> 5662.9238 | E23: =E21+E22 -> 5861.1262 | F23: =F21+F22 -> 6066.2656 | G23: =G21+G22 -> 6278.5849
A24: (+) Depreciación y amortización | B24: =Datos!G14 -> 4342 | C24: =C20*$B$11 -> 4493.97 | D24: =D20*$B$11 -> 4651.259 | E24: =E20*$B$11 -> 4814.053 | F24: =F20*$B$11 -> 4982.5449 | G24: =G20*$B$11 -> 5156.9339
A25: (−) Capex | B25: =-Datos!G16 -> -2867 | C25: =-C20*$B$12 -> -2967.345 | D25: =-D20*$B$12 -> -3071.2021 | E25: =-E20*$B$12 -> -3178.6941 | F25: =-F20*$B$12 -> -3289.9484 | G25: =-G20*$B$12 -> -3405.0966
A26: (−) Inversión en capital de trabajo | B26: 0 | C26: =-(C20-B20)*$B$13 -> -129.185 | D26: =-(D20-C20)*$B$13 -> -133.70648 | E26: =-(E20-D20)*$B$13 -> -138.3862 | F26: =-(F20-E20)*$B$13 -> -143.22972 | G26: =-(G20-F20)*$B$13 -> -148.24276
A27: FCF – Flujo libre de efectivo | B27: =B23+B24+B25+B26 -> 6761.4 | C27: =C23+C24+C25+C26 -> 6868.864 | D27: =D23+D24+D25+D26 -> 7109.2742 | E27: =E23+E24+E25+E26 -> 7358.0988 | F27: =F23+F24+F25+F26 -> 7615.6323 | G27: =G23+G24+G25+G26 -> 7882.1794
A28: Factor de descuento 1/(1+WACC)^n | C28: =1/(1+$B$15)^C19 -> 0.90857039 | D28: =1/(1+$B$15)^D19 -> 0.82550016 | E28: =1/(1+$B$15)^E19 -> 0.75002501 | F28: =1/(1+$B$15)^F19 -> 0.68145052 | G28: =1/(1+$B$15)^G19 -> 0.61914576
A29: Valor presente del FCF | C29: =C27*C28 -> 6240.8465 | D29: =D27*D28 -> 5868.707 | E29: =E27*E28 -> 5518.7581 | F29: =F27*F28 -> 5189.6766 | G29: =G27*G28 -> 4880.218
A31: VPN de los FCF 2026E–2030E | B31: =SUM(C29:G29) -> 27698.206
A32: FCF del año 6 (2031E) | B32: =G27*(1+B16) -> 8158.0557
A33: Valor terminal (TV) al cierre de 2030 | B33: =B32/(B15-B16) -> 124303.41
A34: Valor presente del TV | B34: =B33*G28 -> 76961.93
A35: ENTERPRISE VALUE (EV) | B35: =B31+B34 -> 104660.14
A36: (−) Deuda total (bancaria/bursátil + arrendamientos) | B36: =-WACC!B21 -> -23618
A37: (+) Efectivo y equivalentes | B37: =WACC!B22 -> 9295
A38: Deuda neta | B38: =-(B36+B37) -> 14323
A39: EQUITY VALUE (valor para los accionistas) | B39: =B35+B36+B37 -> 90337.136
A40: Acciones en circulación (millones) | B40: =WACC!B17 -> 1800
A41: Valor intrínseco por acción (MXN) | B41: =B39/B40 -> 50.187298 | D41: Precio modelo integrado | E41: ='Proyección Soriana'!B85 -> 50.181165
A42: Precio actual en bolsa (MXN) | B42: =WACC!B13 -> 33.48 | D42: Diferencia vs integrado | E42: =B41-E41 -> 0.0061328489
A43: Potencial de apreciación / (baja) | B43: =B41/B42-1 -> 0.49902323 | D43: Diferencia (%) | E43: =B41/E41-1 -> 0.00012221416
A44: Peso del valor terminal en el EV | B44: =B34/B35 -> 0.73535094
A46: WALMART DE MÉXICO | B46: 2025A | C46: 2026E | D46: 2027E | E46: 2028E | F46: 2029E | G46: 2030E
A47: Crecimiento anual de ventas (explícito) | B47: =$B$5 -> 0.035
A48: Margen EBIT | B48: =Datos!G35/Datos!G32 -> 0.077593874
A49: Depreciación y amortización (% ventas) | B49: =Datos!G40/Datos!G32 -> 0.024667014
A50: Capex (% ventas) | B50: =Datos!G42/Datos!G32 -> 0.038535074
A51: Inversión en capital de trabajo (% del incremento en ventas) | B51: 0
A52: Tasa de impuestos | B52: =WACC!C10 -> 0.3
A53: WACC | B53: =WACC!C33 -> 0.10255747
A54: Crecimiento perpetuo (g) | B54: =$B$4 -> 0.035
A56: PROYECCIÓN DEL FLUJO LIBRE DE EFECTIVO (FCF) | B56: 2025A | C56: 2026E | D56: 2027E | E56: 2028E | F56: 2029E | G56: 2030E
A57: Periodo (n) | B57: 0 | C57: 1 | D57: 2 | E57: 3 | F57: 4 | G57: 5
A58: Ventas | B58: =Datos!G32 -> 1011597.9 | C58: =B58*(1+$B$47) -> 1047003.8 | D58: =C58*(1+$B$47) -> 1083649 | E58: =D58*(1+$B$47) -> 1121576.7 | F58: =E58*(1+$B$47) -> 1160831.9 | G58: =F58*(1+$B$47) -> 1201461
A59: Utilidad de operación (EBIT) | B59: =Datos!G35 -> 78493.8 | C59: =C58*$B$48 -> 81241.083 | D59: =D58*$B$48 -> 84084.521 | E59: =E58*$B$48 -> 87027.479 | F59: =F58*$B$48 -> 90073.441 | G59: =G58*$B$48 -> 93226.011
A60: (−) Impuestos sobre EBIT | B60: =-B59*$B$52 -> -23548.14 | C60: =-C59*$B$52 -> -24372.325 | D60: =-D59*$B$52 -> -25225.356 | E60: =-E59*$B$52 -> -26108.244 | F60: =-F59*$B$52 -> -27022.032 | G60: =-G59*$B$52 -> -27967.803
A61: NOPAT (EBIT después de impuestos) | B61: =B59+B60 -> 54945.66 | C61: =C59+C60 -> 56868.758 | D61: =D59+D60 -> 58859.165 | E61: =E59+E60 -> 60919.235 | F61: =F59+F60 -> 63051.409 | G61: =G59+G60 -> 65258.208
A62: (+) Depreciación y amortización | B62: =Datos!G40 -> 24953.1 | C62: =C58*$B$49 -> 25826.459 | D62: =D58*$B$49 -> 26730.385 | E62: =E58*$B$49 -> 27665.948 | F62: =F58*$B$49 -> 28634.256 | G62: =G58*$B$49 -> 29636.455
A63: (−) Capex | B63: =-Datos!G42 -> -38982 | C63: =-C58*$B$50 -> -40346.37 | D63: =-D58*$B$50 -> -41758.493 | E63: =-E58*$B$50 -> -43220.04 | F63: =-F58*$B$50 -> -44732.742 | G63: =-G58*$B$50 -> -46298.388
A64: (−) Inversión en capital de trabajo | B64: 0 | C64: =-(C58-B58)*$B$51 -> 0 | D64: =-(D58-C58)*$B$51 -> 0 | E64: =-(E58-D58)*$B$51 -> 0 | F64: =-(F58-E58)*$B$51 -> 0 | G64: =-(G58-F58)*$B$51 -> 0
A65: FCF – Flujo libre de efectivo | B65: =B61+B62+B63+B64 -> 40916.76 | C65: =C61+C62+C63+C64 -> 42348.847 | D65: =D61+D62+D63+D64 -> 43831.056 | E65: =E61+E62+E63+E64 -> 45365.143 | F65: =F61+F62+F63+F64 -> 46952.923 | G65: =G61+G62+G63+G64 -> 48596.276
A66: Factor de descuento 1/(1+WACC)^n | C66: =1/(1+$B$53)^C57 -> 0.9069822 | D66: =1/(1+$B$53)^D57 -> 0.82261672 | E66: =1/(1+$B$53)^E57 -> 0.74609872 | F66: =1/(1+$B$53)^F57 -> 0.67669826 | G66: =1/(1+$B$53)^G57 -> 0.61375328
A67: Valor presente del FCF | C67: =C65*C66 -> 38409.65 | D67: =D65*D66 -> 36056.16 | E67: =E65*E66 -> 33846.875 | F67: =F65*F66 -> 31772.961 | G67: =G65*G66 -> 29826.123
A69: VPN de los FCF 2026E–2030E | B69: =SUM(C67:G67) -> 169911.77
A70: FCF del año 6 (2031E) | B70: =G65*(1+B54) -> 50297.145
A71: Valor terminal (TV) al cierre de 2030 | B71: =B70/(B53-B54) -> 744509.04
A72: Valor presente del TV | B72: =B71*G66 -> 456944.87
A73: ENTERPRISE VALUE (EV) | B73: =B69+B72 -> 626856.64
A74: (−) Deuda total (bancaria/bursátil + arrendamientos) | B74: =-WACC!C21 -> -80848.1
A75: (+) Efectivo y equivalentes | B75: =WACC!C22 -> 28591.2
A76: Deuda neta | B76: =-(B74+B75) -> 52256.9
A77: EQUITY VALUE (valor para los accionistas) | B77: =B73+B74+B75 -> 574599.74
A78: Acciones en circulación (millones) | B78: =WACC!C17 -> 17459.713
A79: Valor intrínseco por acción (MXN) | B79: =B77/B78 -> 32.910034
A80: Precio actual en bolsa (MXN) | B80: =WACC!C13 -> 46.6
A81: Potencial de apreciación / (baja) | B81: =B79/B80-1 -> -0.29377609
A82: Peso del valor terminal en el EV | B82: =B72/B73 -> 0.72894637
A84: GRUPO COMERCIAL CHEDRAUI | B84: 2025A | C84: 2026E | D84: 2027E | E84: 2028E | F84: 2029E | G84: 2030E
A85: Crecimiento anual de ventas (explícito) | B85: =$B$5 -> 0.035
A86: Margen EBIT | B86: =Datos!G61/Datos!G58 -> 0.051124965
A87: Depreciación y amortización (% ventas) | B87: =Datos!G66/Datos!G58 -> 0.031469084
A88: Capex (% ventas) | B88: =Datos!G68/Datos!G58 -> 0.026236105
A89: Inversión en capital de trabajo (% del incremento en ventas) | B89: 0
A90: Tasa de impuestos | B90: =WACC!D10 -> 0.3
A91: WACC | B91: =WACC!D33 -> 0.082995961
A92: Crecimiento perpetuo (g) | B92: =$B$4 -> 0.035
A94: PROYECCIÓN DEL FLUJO LIBRE DE EFECTIVO (FCF) | B94: 2025A | C94: 2026E | D94: 2027E | E94: 2028E | F94: 2029E | G94: 2030E
A95: Periodo (n) | B95: 0 | C95: 1 | D95: 2 | E95: 3 | F95: 4 | G95: 5
A96: Ventas | B96: =Datos!G58 -> 295313.65 | C96: =B96*(1+$B$85) -> 305649.63 | D96: =C96*(1+$B$85) -> 316347.36 | E96: =D96*(1+$B$85) -> 327419.52 | F96: =E96*(1+$B$85) -> 338879.21 | G96: =F96*(1+$B$85) -> 350739.98
A97: Utilidad de operación (EBIT) | B97: =Datos!G61 -> 15097.9 | C97: =C96*$B$86 -> 15626.326 | D97: =D96*$B$86 -> 16173.248 | E97: =E96*$B$86 -> 16739.312 | F97: =F96*$B$86 -> 17325.188 | G97: =G96*$B$86 -> 17931.569
A98: (−) Impuestos sobre EBIT | B98: =-B97*$B$90 -> -4529.37 | C98: =-C97*$B$90 -> -4687.8979 | D98: =-D97*$B$90 -> -4851.9744 | E98: =-E97*$B$90 -> -5021.7935 | F98: =-F97*$B$90 -> -5197.5563 | G98: =-G97*$B$90 -> -5379.4707
A99: NOPAT (EBIT después de impuestos) | B99: =B97+B98 -> 10568.53 | C99: =C97+C98 -> 10938.429 | D99: =D97+D98 -> 11321.274 | E99: =E97+E98 -> 11717.518 | F99: =F97+F98 -> 12127.631 | G99: =G97+G98 -> 12552.098
A100: (+) Depreciación y amortización | B100: =Datos!G66 -> 9293.25 | C100: =C96*$B$87 -> 9618.5138 | D100: =D96*$B$87 -> 9955.1617 | E100: =E96*$B$87 -> 10303.592 | F100: =F96*$B$87 -> 10664.218 | G100: =G96*$B$87 -> 11037.466
A101: (−) Capex | B101: =-Datos!G68 -> -7747.88 | C101: =-C96*$B$88 -> -8019.0558 | D101: =-D96*$B$88 -> -8299.7228 | E101: =-E96*$B$88 -> -8590.213 | F101: =-F96*$B$88 -> -8890.8705 | G101: =-G96*$B$88 -> -9202.051
A102: (−) Inversión en capital de trabajo | B102: 0 | C102: =-(C96-B96)*$B$89 -> 0 | D102: =-(D96-C96)*$B$89 -> 0 | E102: =-(E96-D96)*$B$89 -> 0 | F102: =-(F96-E96)*$B$89 -> 0 | G102: =-(G96-F96)*$B$89 -> 0
A103: FCF – Flujo libre de efectivo | B103: =B99+B100+B101+B102 -> 12113.9 | C103: =C99+C100+C101+C102 -> 12537.887 | D103: =D99+D100+D101+D102 -> 12976.713 | E103: =E99+E100+E101+E102 -> 13430.897 | F103: =F99+F100+F101+F102 -> 13900.979 | G103: =G99+G100+G101+G102 -> 14387.513
A104: Factor de descuento 1/(1+WACC)^n | C104: =1/(1+$B$91)^C95 -> 0.92336448 | D104: =1/(1+$B$91)^D95 -> 0.85260196 | E104: =1/(1+$B$91)^E95 -> 0.78726236 | F104: =1/(1+$B$91)^F95 -> 0.7269301 | G104: =1/(1+$B$91)^G95 -> 0.67122143
A105: Valor presente del FCF | C105: =C103*C104 -> 11577.039 | D105: =D103*D104 -> 11063.971 | E105: =E103*E104 -> 10573.64 | F105: =F103*F104 -> 10105.04 | G105: =G103*G104 -> 9657.2072
A107: VPN de los FCF 2026E–2030E | B107: =SUM(C105:G105) -> 52976.897
A108: FCF del año 6 (2031E) | B108: =G103*(1+B92) -> 14891.076
A109: Valor terminal (TV) al cierre de 2030 | B109: =B108/(B91-B92) -> 310256.86
A110: Valor presente del TV | B110: =B109*G104 -> 208251.06
A111: ENTERPRISE VALUE (EV) | B111: =B107+B110 -> 261227.95
A112: (−) Deuda total (bancaria/bursátil + arrendamientos) | B112: =-WACC!D21 -> -56744.34
A113: (+) Efectivo y equivalentes | B113: =WACC!D22 -> 14640.16
...

Sheet Proyección Soriana
A3: SUPUESTOS | B3: 2025A | C3: 2026E | D3: 2027E | E3: 2028E | F3: 2029E | G3: 2030E
A4: Crecimiento de ventas | C4: =Valuación!$B$9 -> 0.035 | D4: =Valuación!$B$9 -> 0.035 | E4: =Valuación!$B$9 -> 0.035 | F4: =Valuación!$B$9 -> 0.035 | G4: =Valuación!$B$9 -> 0.035
A5: Costo de ventas (% ventas) | B5: =-B20/B19 -> 0.75910205 | C5: =$B5 -> 0.75910205 | D5: =$B5 -> 0.75910205 | E5: =$B5 -> 0.75910205 | F5: =$B5 -> 0.75910205 | G5: =$B5 -> 0.75910205
A6: Gastos de operación sin D&A (% ventas) | B6: =-B22/B19 -> 0.1739008 | C6: =$B6 -> 0.1739008 | D6: =$B6 -> 0.1739008 | E6: =$B6 -> 0.1739008 | F6: =$B6 -> 0.1739008 | G6: =$B6 -> 0.1739008
A7: Depreciación y amortización (% ventas) | B7: =-B24/B19 -> 0.024459905 | C7: =$B7 -> 0.024459905 | D7: =$B7 -> 0.024459905 | E7: =$B7 -> 0.024459905 | F7: =$B7 -> 0.024459905 | G7: =$B7 -> 0.024459905
A8: Capex (% ventas) | B8: =Datos!G16/Datos!G6 -> 0.016150748 | C8: =$B8 -> 0.016150748 | D8: =$B8 -> 0.016150748 | E8: =$B8 -> 0.016150748 | F8: =$B8 -> 0.016150748 | G8: =$B8 -> 0.016150748
A9: Tasa de interés implícita (% deuda + arrendamientos) | B9: =-B26/(B41+B42) -> 0.13015497 | C9: =$B9 -> 0.13015497 | D9: =$B9 -> 0.13015497 | E9: =$B9 -> 0.13015497 | F9: =$B9 -> 0.13015497 | G9: =$B9 -> 0.13015497
A10: Tasa de impuestos | B10: =Valuación!$B$14 -> 0.3 | C10: =$B10 -> 0.3 | D10: =$B10 -> 0.3 | E10: =$B10 -> 0.3 | F10: =$B10 -> 0.3 | G10: =$B10 -> 0.3
A11: Días de inventario (sobre costo de ventas) | B11: =-B35/B20*365 -> 87.444305 | C11: =$B11 -> 87.444305 | D11: =$B11 -> 87.444305 | E11: =$B11 -> 87.444305 | F11: =$B11 -> 87.444305 | G11: =$B11 -> 87.444305
A12: Otros activos circulantes (% ventas) | B12: =B36/B19 -> 0.039157254 | C12: =$B12 -> 0.039157254 | D12: =$B12 -> 0.039157254 | E12: =$B12 -> 0.039157254 | F12: =$B12 -> 0.039157254 | G12: =$B12 -> 0.039157254
A13: Pasivo circulante operativo (% ventas) | B13: =B40/B19 -> 0.20022533 | C13: =$B13 -> 0.20022533 | D13: =$B13 -> 0.20022533 | E13: =$B13 -> 0.20022533 | F13: =$B13 -> 0.20022533 | G13: =$B13 -> 0.20022533
A14: Dividendos (% utilidad neta) | B14: =Generales!B62*Valuación!B40/B30 -> 0.30014406 | C14: =$B14 -> 0.30014406 | D14: =$B14 -> 0.30014406 | E14: =$B14 -> 0.30014406 | F14: =$B14 -> 0.30014406 | G14: =$B14 -> 0.30014406
A15: WACC | C15: =Valuación!$B$15 -> 0.10063018 | D15: =Valuación!$B$15 -> 0.10063018 | E15: =Valuación!$B$15 -> 0.10063018 | F15: =Valuación!$B$15 -> 0.10063018 | G15: =Valuación!$B$15 -> 0.10063018
A16: Crecimiento perpetuo (g) | C16: =Valuación!$B$16 -> 0.035 | D16: =Valuación!$B$16 -> 0.035 | E16: =Valuación!$B$16 -> 0.035 | F16: =Valuación!$B$16 -> 0.035 | G16: =Valuación!$B$16 -> 0.035
A18: 1. ESTADO DE RESULTADOS | B18: 2025A | C18: 2026E | D18: 2027E | E18: 2028E | F18: 2029E | G18: 2030E
A19: Ventas | B19: =Datos!G6 -> 177515 | C19: =B19*(1+C4) -> 183728.02 | D19: =C19*(1+D4) -> 190158.51 | E19: =D19*(1+E4) -> 196814.05 | F19: =E19*(1+F4) -> 203702.55 | G19: =F19*(1+G4) -> 210832.13
A20: Costo de ventas | B20: =-Datos!G7 -> -134752 | C20: =-C19*C5 -> -139468.32 | D20: =-D19*D5 -> -144349.71 | E20: =-E19*E5 -> -149401.95 | F20: =-F19*F5 -> -154631.02 | G20: =-G19*G5 -> -160043.11
A21: Utilidad bruta | B21: =B19+B20 -> 42763 | C21: =C19+C20 -> 44259.705 | D21: =D19+D20 -> 45808.795 | E21: =E19+E20 -> 47412.102 | F21: =F19+F20 -> 49071.526 | G21: =G19+G20 -> 50789.029
A22: Gastos de operación (sin D&A) | B22: =-(Datos!G8-Datos!G9-Datos!G14) -> -30870 | C22: =-C19*C6 -> -31950.45 | D22: =-D19*D6 -> -33068.716 | E22: =-E19*E6 -> -34226.121 | F22: =-F19*F6 -> -35424.035 | G22: =-G19*G6 -> -36663.876
A23: EBITDA | B23: =B21+B22 -> 11893 | C23: =C21+C22 -> 12309.255 | D23: =D21+D22 -> 12740.079 | E23: =E21+E22 -> 13185.982 | F23: =F21+F22 -> 13647.491 | G23: =G21+G22 -> 14125.153
A24: Depreciación y amortización | B24: =-Datos!G14 -> -4342 | C24: =-C19*C7 -> -4493.97 | D24: =-D19*D7 -> -4651.259 | E24: =-E19*E7 -> -4814.053 | F24: =-F19*F7 -> -4982.5449 | G24: =-G19*G7 -> -5156.9339
A25: Utilidad de operación (EBIT) | B25: =B23+B24 -> 7551 | C25: =C23+C24 -> 7815.285 | D25: =D23+D24 -> 8088.82 | E25: =E23+E24 -> 8371.9287 | F25: =F23+F24 -> 8664.9462 | G25: =G23+G24 -> 8968.2193
A26: Gastos financieros | B26: =-Datos!G10 -> -3074 | C26: =-C9*(B41+B42) -> -3074 | D26: =-D9*(C41+C42) -> -3074 | E26: =-E9*(D41+D42) -> -3074 | F26: =-F9*(E41+E42) -> -3074 | G26: =-G9*(F41+F42) -> -3074
A27: Otros ingresos (gastos) netos | B27: =Datos!G11-Datos!G9+Datos!G10 -> 288 | C27: 0 | D27: 0 | E27: 0 | F27: 0 | G27: 0
A28: Utilidad antes de impuestos | B28: =B25+B26+B27 -> 4765 | C28: =C25+C26+C27 -> 4741.285 | D28: =D25+D26+D27 -> 5014.82 | E28: =E25+E26+E27 -> 5297.9287 | F28: =F25+F26+F27 -> 5590.9462 | G28: =G25+G26+G27 -> 5894.2193
A29: Impuestos a la utilidad | B29: =-Datos!G12 -> -1433 | C29: =-C28*C10 -> -1422.3855 | D29: =-D28*D10 -> -1504.446 | E29: =-E28*E10 -> -1589.3786 | F29: =-F28*F10 -> -1677.2839 | G29: =-G28*G10 -> -1768.2658
A30: Utilidad neta | B30: =B28+B29 -> 3332 | C30: =C28+C29 -> 3318.8995 | D30: =D28+D29 -> 3510.374 | E30: =E28+E29 -> 3708.5501 | F30: =F28+F29 -> 3913.6623 | G30: =G28+G29 -> 4125.9535
A31: Dividendos pagados | C31: =-C30*C14 -> -996.14796 | D31: =-D30*D14 -> -1053.6179 | E31: =-E30*E14 -> -1113.0993 | F31: =-F30*F14 -> -1174.6625 | G31: =-G30*G14 -> -1238.3804
A33: 2. BALANCE GENERAL | B33: 2025A | C33: 2026E | D33: 2027E | E33: 2028E | F33: 2029E | G33: 2030E
A34: Efectivo y equivalentes | B34: =Datos!G17 -> 9295 | C34: =B34+C56 -> 13015.192 | D34: =C34+D56 -> 16918.298 | E34: =D34+E56 -> 21010.721 | F34: =E34+F56 -> 25299.088 | G34: =F34+G56 -> 29790.256
A35: Inventarios | B35: =Datos!G18 -> 32283 | C35: =-C20*C11/365 -> 33412.905 | D35: =-D20*D11/365 -> 34582.357 | E35: =-E20*E11/365 -> 35792.739 | F35: =-F20*F11/365 -> 37045.485 | G35: =-G20*G11/365 -> 38342.077
A36: Otros activos circulantes | B36: =Datos!G19-Datos!G17-Datos!G18 -> 6951 | C36: =C19*C12 -> 7194.285 | D36: =D19*D12 -> 7446.085 | E36: =E19*E12 -> 7706.6979 | F36: =F19*F12 -> 7976.4324 | G36: =G19*G12 -> 8255.6075
A37: Activo circulante | B37: =SUM(B34:B36) -> 48529 | C37: =SUM(C34:C36) -> 53622.382 | D37: =SUM(D34:D36) -> 58946.74 | E37: =SUM(E34:E36) -> 64510.159 | F37: =SUM(F34:F36) -> 70321.005 | G37: =SUM(G34:G36) -> 76387.94
A38: Activo no circulante | B38: =Datos!G20-Datos!G19 -> 107509 | C38: =B38-C54+C24 -> 105982.38 | D38: =C38-D54+D24 -> 104402.32 | E38: =D38-E54+E24 -> 102766.96 | F38: =E38-F54+F24 -> 101074.36 | G38: =F38-G54+G24 -> 99322.526
A39: Activo total | B39: =B37+B38 -> 156038 | C39: =C37+C38 -> 159604.76 | D39: =D37+D38 -> 163349.06 | E39: =E37+E38 -> 167277.12 | F39: =F37+F38 -> 171395.37 | G39: =G37+G38 -> 175710.47
A40: Pasivo circulante operativo (proveedores y otros) | B40: =Datos!G21-Datos!G25-Datos!G27 -> 35543 | C40: =C19*C13 -> 36787.005 | D40: =D19*D13 -> 38074.55 | E40: =E19*E13 -> 39407.159 | F40: =F19*F13 -> 40786.41 | G40: =G19*G13 -> 42213.934
A41: Deuda bursátil y bancaria | B41: =Datos!G25+Datos!G26 -> 11500 | C41: =B41 -> 11500 | D41: =C41 -> 11500 | E41: =D41 -> 11500 | F41: =E41 -> 11500 | G41: =F41 -> 11500
A42: Pasivo por arrendamiento | B42: =Datos!G27+Datos!G28 -> 12118 | C42: =B42 -> 12118 | D42: =C42 -> 12118 | E42: =D42 -> 12118 | F42: =E42 -> 12118 | G42: =F42 -> 12118
A43: Otros pasivos a largo plazo | B43: =Datos!G23-Datos!G21-Datos!G26-Datos!G28 -> 12145 | C43: =B43 -> 12145 | D43: =C43 -> 12145 | E43: =D43 -> 12145 | F43: =E43 -> 12145 | G43: =F43 -> 12145
A44: Pasivo total | B44: =SUM(B40:B43) -> 71306 | C44: =SUM(C40:C43) -> 72550.005 | D44: =SUM(D40:D43) -> 73837.55 | E44: =SUM(E40:E43) -> 75170.159 | F44: =SUM(F40:F43) -> 76549.41 | G44: =SUM(G40:G43) -> 77976.934
A45: Capital contable | B45: =Datos!G24 -> 84732 | C45: =B45+C30+C31 -> 87054.752 | D45: =C45+D30+D31 -> 89511.508 | E45: =D45+E30+E31 -> 92106.958 | F45: =E45+F30+F31 -> 94845.958 | G45: =F45+G30+G31 -> 97733.531
A46: Pasivo + capital | B46: =B44+B45 -> 156038 | C46: =C44+C45 -> 159604.76 | D46: =D44+D45 -> 163349.06 | E46: =E44+E45 -> 167277.12 | F46: =F44+F45 -> 171395.37 | G46: =G44+G45 -> 175710.47
A47: Comprobación (activo − pasivo − capital) | B47: =B39-B46 -> 0 | C47: =C39-C46 -> 0 | D47: =D39-D46 -> 0 | E47: =E39-E46 -> 0 | F47: =F39-F46 -> 0 | G47: =G39-G46 -> 0
A49: CONCILIACIÓN DE EFECTIVO | B49: 2025A | C49: 2026E | D49: 2027E | E49: 2028E | F49: 2029E | G49: 2030E
A50: Utilidad neta | C50: =C30 -> 3318.8995 | D50: =D30 -> 3510.374 | E50: =E30 -> 3708.5501 | F50: =F30 -> 3913.6623 | G50: =G30 -> 4125.9535
A51: (+) Depreciación y amortización | C51: =-C24 -> 4493.97 | D51: =-D24 -> 4651.259 | E51: =-E24 -> 4814.053 | F51: =-F24 -> 4982.5449 | G51: =-G24 -> 5156.9339
A52: (−) Aumento en inventarios | C52: =-(C35-B35) -> -1129.905 | D52: =-(D35-C35) -> -1169.4517 | E52: =-(E35-D35) -> -1210.3825 | F52: =-(F35-E35) -> -1252.7459 | G52: =-(G35-F35) -> -1296.592
A53: (−) Aumento en otros activos circulantes | C53: =-(C36-B36) -> -243.285 | D53: =-(D36-C36) -> -251.79997 | E53: =-(E36-D36) -> -260.61297 | F53: =-(F36-E36) -> -269.73443 | G53: =-(G36-F36) -> -279.17513
A54: (−) Capex | C54: =-C19*C8 -> -2967.345 | D54: =-D19*D8 -> -3071.2021 | E54: =-E19*E8 -> -3178.6941 | F54: =-F19*F8 -> -3289.9484 | G54: =-G19*G8 -> -3405.0966
A55: (+) Aumento en pasivo circulante operativo | C55: =C40-B40 -> 1244.005 | D55: =D40-C40 -> 1287.5452 | E55: =E40-D40 -> 1332.6093 | F55: =F40-E40 -> 1379.2506 | G55: =G40-F40 -> 1427.5244
A56: Cambio neto en efectivo (después de dividendos) | C56: =SUM(C50:C55)+C31 -> 3720.1915 | D56: =SUM(D50:D55)+D31 -> 3903.1065 | E56: =SUM(E50:E55)+E31 -> 4092.4235 | F56: =SUM(F50:F55)+F31 -> 4288.3665 | G56: =SUM(G50:G55)+G31 -> 4491.1676
A58: 3. FLUJO LIBRE DE EFECTIVO (FFL) | B58: 2025A | C58: 2026E | D58: 2027E | E58: 2028E | F58: 2029E | G58: 2030E
A59: Utilidad de operación (EBIT) | C59: =C25 -> 7815.285 | D59: =D25 -> 8088.82 | E59: =E25 -> 8371.9287 | F59: =F25 -> 8664.9462 | G59: =G25 -> 8968.2193
A60: (−) Impuestos sobre EBIT | C60: =-C59*C10 -> -2344.5855 | D60: =-D59*D10 -> -2426.646 | E60: =-E59*E10 -> -2511.5786 | F60: =-F59*F10 -> -2599.4839 | G60: =-G59*G10 -> -2690.4658
A61: NOPAT | C61: =C59+C60 -> 5470.6995 | D61: =D59+D60 -> 5662.174 | E61: =E59+E60 -> 5860.3501 | F61: =F59+F60 -> 6065.4623 | G61: =G59+G60 -> 6277.7535
A62: (+) Depreciación y amortización | C62: =C51 -> 4493.97 | D62: =D51 -> 4651.259 | E62: =E51 -> 4814.053 | F62: =F51 -> 4982.5449 | G62: =G51 -> 5156.9339
A63: (−) Capex | C63: =C54 -> -2967.345 | D63: =D54 -> -3071.2021 | E63: =E54 -> -3178.6941 | F63: =F54 -> -3289.9484 | G63: =G54 -> -3405.0966
A64: (−) Inversión en capital de trabajo | C64: =C52+C53+C55 -> -129.185 | D64: =D52+D53+D55 -> -133.70648 | E64: =E52+E53+E55 -> -138.3862 | F64: =F52+F53+F55 -> -143.22972 | G64: =G52+G53+G55 -> -148.24276
A65: Flujo libre de efectivo (FFL) | C65: =SUM(C61:C64) -> 6868.1395 | D65: =SUM(D61:D64) -> 7108.5244 | E65: =SUM(E61:E64) -> 7357.3227 | F65: =SUM(F61:F64) -> 7614.829 | G65: =SUM(G61:G64) -> 7881.348
A66: Periodo (n) | C66: 1 | D66: =C66+1 -> 2 | E66: =D66+1 -> 3 | F66: =E66+1 -> 4 | G66: =F66+1 -> 5
A67: Factor de descuento 1/(1+WACC)^n | C67: =1/(1+C15)^C66 -> 0.90857039 | D67: =1/(1+D15)^D66 -> 0.82550016 | E67: =1/(1+E15)^E66 -> 0.75002501 | F67: =1/(1+F15)^F66 -> 0.68145052 | G67: =1/(1+G15)^G66 -> 0.61914576
A68: Valor presente del FFL | C68: =C65*C67 -> 6240.1882 | D68: =D65*D67 -> 5868.088 | E68: =E65*E67 -> 5518.176 | F68: =F65*F67 -> 5189.1292 | G68: =G65*G67 -> 4879.7033
A70: 4. VALOR TERMINAL Y VALOR DE LA EMPRESA | B70: Valor
A71: Suma VP de FFL 2026E–2030E | B71: =SUM(C68:G68) -> 27695.285
A72: FFL 2031E = FFL 2030E × (1+g) | B72: =G65*(1+G16) -> 8157.1952
A73: Valor terminal al cierre 2030 (Gordon) | B73: =B72/(G15-G16) -> 124290.3
A74: Valor presente del valor terminal | B74: =B73*G67 -> 76953.812
A75: Valor de la empresa (VE) | B75: =B71+B74 -> 104649.1
A76: Peso del valor terminal en el VE | B76: =B74/B75 -> 0.73535094
A78: 5. VALOR DEL CAPITAL Y PRECIO POR ACCIÓN | B78: Valor
A79: Valor de la empresa (VE) | B79: =B75 -> 104649.1
A80: (−) Deuda bursátil y bancaria (2025) | B80: =-B41 -> -11500
A81: (−) Pasivo por arrendamiento (2025) | B81: =-B42 -> -12118
A82: (+) Efectivo y equivalentes (2025) | B82: =B34 -> 9295
A83: Valor del capital | B83: =SUM(B79:B82) -> 90326.097
A84: Acciones en circulación (millones) | B84: =Valuación!B40 -> 1800
A85: Precio por acción (MXN) | B85: =B83/B84 -> 50.181165
A86: Precio actual en bolsa (MXN) | B86: =Valuación!B42 -> 33.48
A87: Potencial de apreciación / (baja) | B87: =B85/B86-1 -> 0.49884005

Sheet MC Soriana
A3: 1. FCFF PROYECTADO — MÍNIMOS CUADRADOS (sin ajustes externos)
A4: Concepto | B4: 3T26 | C4: 4T26 | D4: 1T27 | E4: 2T27 | F4: LTM proyectado (3T26–2T27) | G4: LTM actual (3T25–2T26) | H4: Variación vs. LTM actual
A5: X (pronóstico) | B5: =I39 -> 3 | C5: =I40 -> 4 | D5: =I41 -> 5 | E5: =I42 -> 6
A6: Ventas | B6: =J39 -> 41995.3 | C6: =J40 -> 41321.2 | D6: =J41 -> 40647.1 | E6: =J42 -> 39973 | F6: =SUM(B6:E6) -> 163936.6 | G6: =SUM(Datos!C6:F6) -> 174278 | H6: =IFERROR((F6-G6)/ABS(G6),"") -> -0.059338528
A7: Costos y gastos operativos | B7: =J56 -> 40013.5 | C7: =J57 -> 39314.8 | D7: =J58 -> 38616.1 | E7: =J59 -> 37917.4 | F7: =SUM(B7:E7) -> 155861.8 | G7: =SUM(Datos!C6:F6)-SUM(Datos!C9:F9) -> 166647 | H7: =IFERROR((F7-G7)/ABS(G7),"") -> -0.064718837
A8: EBIT | B8: =B6-B7 -> 1981.8 | C8: =C6-C7 -> 2006.4 | D8: =D6-D7 -> 2031 | E8: =E6-E7 -> 2055.6 | F8: =SUM(B8:E8) -> 8074.8 | G8: =G6-G7 -> 7631 | H8: =IFERROR((F8-G8)/ABS(G8),"") -> 0.058157515
A9: Margen EBIT | B9: =B8/B6 -> 0.047190995 | C9: =C8/C6 -> 0.048556189 | D9: =D8/D6 -> 0.049966664 | E9: =E8/E6 -> 0.051424712 | F9: =F8/F6 -> 0.049255627 | G9: =G8/G6 -> 0.043786364
A10: Tasa de impuesto | B10: =J73 -> 0.22485563 | C10: =J74 -> 0.20299653 | D10: =J75 -> 0.18113743 | E10: =J76 -> 0.15927832 | F10: =1-F11/F8 -> 0.19173401 | G10: =SUM(Datos!C12:F12)/SUM(Datos!C11:F11) -> 0.26947368
A11: EBIT (1 − T) | B11: =B8*(1-B10) -> 1536.1811 | C11: =C8*(1-C10) -> 1599.1078 | D11: =D8*(1-D10) -> 1663.1099 | E11: =E8*(1-E10) -> 1728.1875 | F11: =SUM(B11:E11) -> 6526.5862 | G11: =G8*(1-G10) -> 5574.6463 | H11: =IFERROR((F11-G11)/ABS(G11),"") -> 0.17076239
A12: (+) Depreciación y amortización | B12: =J90 -> 1011.854 | C12: =J91 -> 996.7536 | D12: =J92 -> 981.6532 | E12: =J93 -> 966.5528 | F12: =SUM(B12:E12) -> 3956.8136 | G12: =SUM(Datos!C14:F14) -> 4179.871 | H12: =IFERROR((F12-G12)/ABS(G12),"") -> -0.053364661
A13: (−) Capex | B13: =J107 -> 798.82 | C13: =J108 -> 820.74 | D13: =J109 -> 842.66 | E13: =J110 -> 864.58 | F13: =SUM(B13:E13) -> 3326.8 | G13: =SUM(Datos!C16:F16) -> 3002.1 | H13: =IFERROR((F13-G13)/ABS(G13),"") -> 0.10815762
A14: Capital de trabajo neto (cierre) | B14: =J124 -> 6975.4312 | C14: =J125 -> 6036.114 | D14: =J126 -> 5096.7968 | E14: =J127 -> 4157.4796 | F14: =E14 -> 4157.4796 | G14: =Datos!F19-Datos!F21 -> 7301.914
A15: (−) ΔNWC (cambio en capital de trabajo) | B15: =B14-(Datos!$F$19-Datos!$F$21) -> -326.4828 | C15: =C14-B14 -> -939.3172 | D15: =D14-C14 -> -939.3172 | E15: =E14-D14 -> -939.3172 | F15: =SUM(B15:E15) -> -3144.4344 | G15: =(Datos!F19-Datos!F21)-(Datos!B19-Datos!B21) -> -3764.086
A16: FCFF = EBIT(1−T) + D&A − Capex − ΔNWC | B16: =B11+B12-B13-B15 -> 2075.6979 | C16: =C11+C12-C13-C15 -> 2714.4386 | D16: =D11+D12-D13-D15 -> 2741.4203 | E16: =E11+E12-E13-E15 -> 2769.4775 | F16: =F11+F12-F13-F15 -> 10301.034 | G16: =G11+G12-G13-G15 -> 10516.503 | H16: =IFERROR((F16-G16)/ABS(G16),"") -> -0.020488662
A18: 2. FCFF PROYECTADO AJUSTADO POR VARIABLES EXTERNAS
A19: Ajuste neto a ventas | B19: ='Variables Externas'!H22 -> -0.009
A20: Ajuste neto a costos y gastos | B20: ='Variables Externas'!I22 -> 0.0052
A21: Ajuste neto a capex | B21: ='Variables Externas'!J22 -> 0.025
A23: Concepto | B23: 3T26 | C23: 4T26 | D23: 1T27 | E23: 2T27 | F23: LTM ajustado (3T26–2T27) | G23: LTM proyectado sin ajuste | H23: Variación vs. sin ajuste
A24: Ventas | B24: =B6*(1+$B$19) -> 41617.342 | C24: =C6*(1+$B$19) -> 40949.309 | D24: =D6*(1+$B$19) -> 40281.276 | E24: =E6*(1+$B$19) -> 39613.243 | F24: =SUM(B24:E24) -> 162461.17 | G24: =F6 -> 163936.6 | H24: =IFERROR((F24-G24)/ABS(G24),"") -> -0.009
A25: Costos y gastos operativos | B25: =B7*(1+$B$19)*(1+$B$20) -> 39859.576 | C25: =C7*(1+$B$19)*(1+$B$20) -> 39163.564 | D25: =D7*(1+$B$19)*(1+$B$20) -> 38467.552 | E25: =E7*(1+$B$19)*(1+$B$20) -> 37771.539 | F25: =SUM(B25:E25) -> 155262.23 | G25: =F7 -> 155861.8 | H25: =IFERROR((F25-G25)/ABS(G25),"") -> -0.0038468
A26: EBIT | B26: =B24-B25 -> 1757.7662 | C26: =C24-C25 -> 1785.7454 | D26: =D24-D25 -> 1813.7245 | E26: =E24-E25 -> 1841.7037 | F26: =SUM(B26:E26) -> 7198.9398 | G26: =F8 -> 8074.8 | H26: =IFERROR((F26-G26)/ABS(G26),"") -> -0.10846835
A27: Margen EBIT | B27: =B26/B24 -> 0.042236388 | C27: =C26/C24 -> 0.043608681 | D27: =D26/D24 -> 0.045026491 | E27: =E26/E24 -> 0.04649212 | F27: =F26/F24 -> 0.044311756 | G27: =F9 -> 0.049255627
A28: Tasa de impuesto | B28: =B10 -> 0.22485563 | C28: =C10 -> 0.20299653 | D28: =D10 -> 0.18113743 | E28: =E10 -> 0.15927832 | F28: =1-F29/F26 -> 0.19164219 | G28: =F10 -> 0.19173401
A29: EBIT (1 − T) | B29: =B26*(1-B28) -> 1362.5226 | C29: =C26*(1-C28) -> 1423.2453 | D29: =D26*(1-D28) -> 1485.1911 | E29: =E26*(1-E28) -> 1548.3602 | F29: =SUM(B29:E29) -> 5819.3192 | G29: =F11 -> 6526.5862 | H29: =IFERROR((F29-G29)/ABS(G29),"") -> -0.10836708
A30: (+) Depreciación y amortización | B30: =B12 -> 1011.854 | C30: =C12 -> 996.7536 | D30: =D12 -> 981.6532 | E30: =E12 -> 966.5528 | F30: =SUM(B30:E30) -> 3956.8136 | G30: =F12 -> 3956.8136 | H30: =IFERROR((F30-G30)/ABS(G30),"") -> 0
A31: (−) Capex | B31: =B13*(1+$B$21) -> 818.7905 | C31: =C13*(1+$B$21) -> 841.2585 | D31: =D13*(1+$B$21) -> 863.7265 | E31: =E13*(1+$B$21) -> 886.1945 | F31: =SUM(B31:E31) -> 3409.97 | G31: =F13 -> 3326.8 | H31: =IFERROR((F31-G31)/ABS(G31),"") -> 0.025
A32: (−) ΔNWC | B32: =B15 -> -326.4828 | C32: =C15 -> -939.3172 | D32: =D15 -> -939.3172 | E32: =E15 -> -939.3172 | F32: =SUM(B32:E32) -> -3144.4344 | G32: =F15 -> -3144.4344
A33: FCFF ajustado | B33: =B29+B30-B31-B32 -> 1882.0689 | C33: =C29+C30-C31-C32 -> 2518.0576 | D33: =D29+D30-D31-D32 -> 2542.435 | E33: =E29+E30-E31-E32 -> 2568.0357 | F33: =SUM(B33:E33) -> 9510.5972 | G33: =F16 -> 10301.034 | H33: =IFERROR((F33-G33)/ABS(G33),"") -> -0.076733759
A35: DETALLE DE MÍNIMOS CUADRADOS POR PARTIDA DEL FCFF
A37: 1. VENTAS (ingresos totales)
A38: Trimestre | B38: n | C38: X = n − (N+1)/2 | D38: Y (mdp) | E38: XY | F38: X² | H38: Trimestre a pronosticar | I38: X (pronóstico) | J38: Y pronosticada
A39: =Datos!B$5 -> 2T25 | B39: 1 | C39: =B39-(COUNT($B$39:$B$43)+1)/2 -> -2 | D39: =Datos!B6 -> 45810 | E39: =C39*D39 -> -91620 | F39: =C39^2 -> 4 | H39: 3T26 | I39: =MAX($C$39:$C$43)+1 -> 3 | J39: =$B$48+$B$47*I39 -> 41995.3
A40: =Datos!C$5 -> 3T25 | B40: 2 | C40: =B40-(COUNT($B$39:$B$43)+1)/2 -> -1 | D40: =Datos!C6 -> 42683 | E40: =C40*D40 -> -42683 | F40: =C40^2 -> 1 | H40: 4T26 | I40: =I39+1 -> 4 | J40: =$B$48+$B$47*I40 -> 41321.2
A41: =Datos!D$5 -> 4T25 | B41: 3 | C41: =B41-(COUNT($B$39:$B$43)+1)/2 -> 0 | D41: =Datos!D6 -> 47592 | E41: =C41*D41 -> 0 | F41: =C41^2 -> 0 | H41: 1T27 | I41: =I40+1 -> 5 | J41: =$B$48+$B$47*I41 -> 40647.1
A42: =Datos!E$5 -> 1T26 | B42: 4 | C42: =B42-(COUNT($B$39:$B$43)+1)/2 -> 1 | D42: =Datos!E6 -> 40444 | E42: =C42*D42 -> 40444 | F42: =C42^2 -> 1 | H42: 2T27 | I42: =I41+1 -> 6 | J42: =$B$48+$B$47*I42 -> 39973
A43: =Datos!F$5 -> 2T26 | B43: 5 | C43: =B43-(COUNT($B$39:$B$43)+1)/2 -> 2 | D43: =Datos!F6 -> 43559 | E43: =C43*D43 -> 87118 | F43: =C43^2 -> 4
A44: Σ (sumas) | C44: =SUM(C39:C43) -> 0 | D44: =SUM(D39:D43) -> 220088 | E44: =SUM(E39:E43) -> -6741 | F44: =SUM(F39:F43) -> 10 | H44: ="Ecuación: Y = "&TEXT(B48,"#,##0.0000")&" + ("&TEXT(B47,"#,##0.0000")&")·X" -> Ecuación: Y = 44,017.6000 + (-674.1000)·X
A45: N (trimestres) | B45: =COUNT(B39:B43) -> 5
A46: X̄ = ΣX / N | B46: =C44/B45 -> 0
A47: b = ΣXY / ΣX² | B47: =E44/F44 -> -674.1
A48: a = ΣY / N | B48: =D44/B45 -> 44017.6
A49: R² (ajuste) | B49: =RSQ(D39:D43,C39:C43) -> 0.14777049
A54: 2. COSTOS Y GASTOS OPERATIVOS (ventas − EBIT)
A55: Trimestre | B55: n | C55: X = n − (N+1)/2 | D55: Y (mdp) | E55: XY | F55: X² | H55: Trimestre a pronosticar | I55: X (pronóstico) | J55: Y pronosticada
A56: =Datos!B$5 -> 2T25 | B56: 1 | C56: =B56-(COUNT($B$56:$B$60)+1)/2 -> -2 | D56: =Datos!B6-Datos!B9 -> 43901 | E56: =C56*D56 -> -87802 | F56: =C56^2 -> 4 | H56: 3T26 | I56: =MAX($C$56:$C$60)+1 -> 3 | J56: =$B$65+$B$64*I56 -> 40013.5
A57: =Datos!C$5 -> 3T25 | B57: 2 | C57: =B57-(COUNT($B$56:$B$60)+1)/2 -> -1 | D57: =Datos!C6-Datos!C9 -> 41215 | E57: =C57*D57 -> -41215 | F57: =C57^2 -> 1 | H57: 4T26 | I57: =I56+1 -> 4 | J57: =$B$65+$B$64*I57 -> 39314.8
A58: =Datos!D$5 -> 4T25 | B58: 3 | C58: =B58-(COUNT($B$56:$B$60)+1)/2 -> 0 | D58: =Datos!D6-Datos!D9 -> 45106 | E58: =C58*D58 -> 0 | F58: =C58^2 -> 0 | H58: 1T27 | I58: =I57+1 -> 5 | J58: =$B$65+$B$64*I58 -> 38616.1
A59: =Datos!E$5 -> 1T26 | B59: 4 | C59: =B59-(COUNT($B$56:$B$60)+1)/2 -> 1 | D59: =Datos!E6-Datos!E9 -> 38622 | E59: =C59*D59 -> 38622 | F59: =C59^2 -> 1 | H59: 2T27 | I59: =I58+1 -> 6 | J59: =$B$65+$B$64*I59 -> 37917.4
A60: =Datos!F$5 -> 2T26 | B60: 5 | C60: =B60-(COUNT($B$56:$B$60)+1)/2 -> 2 | D60: =Datos!F6-Datos!F9 -> 41704 | E60: =C60*D60 -> 83408 | F60: =C60^2 -> 4
A61: Σ (sumas) | C61: =SUM(C56:C60) -> 0 | D61: =SUM(D56:D60) -> 210548 | E61: =SUM(E56:E60) -> -6987 | F61: =SUM(F56:F60) -> 10 | H61: ="Ecuación: Y = "&TEXT(B65,"#,##0.0000")&" + ("&TEXT(B64,"#,##0.0000")&")·X" -> Ecuación: Y = 42,109.6000 + (-698.7000)·X
A62: N (trimestres) | B62: =COUNT(B56:B60) -> 5
A63: X̄ = ΣX / N | B63: =C61/B62 -> 0
A64: b = ΣXY / ΣX² | B64: =E61/F61 -> -698.7
A65: a = ΣY / N | B65: =D61/B62 -> 42109.6
A66: R² (ajuste) | B66: =RSQ(D56:D60,C56:C60) -> 0.19283751
A71: 3. TASA DE IMPUESTO (impuestos / UAI)
A72: Trimestre | B72: n | C72: X = n − (N+1)/2 | D72: Y (tasa) | E72: XY | F72: X² | H72: Trimestre a pronosticar | I72: X (pronóstico) | J72: Y pronosticada
A73: =Datos!B$5 -> 2T25 | B73: 1 | C73: =B73-(COUNT($B$73:$B$77)+1)/2 -> -2 | D73: =Datos!B12/Datos!B11 -> 0.38320865 | E73: =C73*D73 -> -0.76641729 | F73: =C73^2 -> 4 | H73: 3T26 | I73: =MAX($C$73:$C$77)+1 -> 3 | J73: =$B$82+$B$81*I73 -> 0.22485563
A74: =Datos!C$5 -> 3T25 | B74: 2 | C74: =B74-(COUNT($B$73:$B$77)+1)/2 -> -1 | D74: =Datos!C12/Datos!C11 -> 0.23429319 | E74: =C74*D74 -> -0.23429319 | F74: =C74^2 -> 1 | H74: 4T26 | I74: =I73+1 -> 4 | J74: =$B$82+$B$81*I74 -> 0.20299653
A75: =Datos!D$5 -> 4T25 | B75: 3 | C75: =B75-(COUNT($B$73:$B$77)+1)/2 -> 0 | D75: =Datos!D12/Datos!D11 -> 0.25808281 | E75: =C75*D75 -> 0 | F75: =C75^2 -> 0 | H75: 1T27 | I75: =I74+1 -> 5 | J75: =$B$82+$B$81*I75 -> 0.18113743
A76: =Datos!E$5 -> 1T26 | B76: 4 | C76: =B76-(COUNT($B$73:$B$77)+1)/2 -> 1 | D76: =Datos!E12/Datos!E11 -> 0.37104072 | E76: =C76*D76 -> 0.37104072 | F76: =C76^2 -> 1 | H76: 2T27 | I76: =I75+1 -> 6 | J76: =$B$82+$B$81*I76 -> 0.15927832
A77: =Datos!F$5 -> 2T26 | B77: 5 | C77: =B77-(COUNT($B$73:$B$77)+1)/2 -> 2 | D77: =Datos!F12/Datos!F11 -> 0.20553936 | E77: =C77*D77 -> 0.41107872 | F77: =C77^2 -> 4
A78: Σ (sumas) | C78: =SUM(C73:C77) -> 0 | D78: =SUM(D73:D77) -> 1.4521647 | E78: =SUM(E73:E77) -> -0.21859104 | F78: =SUM(F73:F77) -> 10 | H78: ="Ecuación: Y = "&TEXT(B82,"#,##0.0000")&" + ("&TEXT(B81,"#,##0.0000")&")·X" -> Ecuación: Y = 0.2904 + (-0.0219)·X
A79: N (trimestres) | B79: =COUNT(B73:B77) -> 5
A80: X̄ = ΣX / N | B80: =C78/B79 -> 0
A81: b = ΣXY / ΣX² | B81: =E78/F78 -> -0.021859104
A82: a = ΣY / N | B82: =D78/B79 -> 0.29043295
A83: R² (ajuste) | B83: =RSQ(D73:D77,C73:C77) -> 0.18024112
A88: 4. DEPRECIACIÓN Y AMORTIZACIÓN
A89: Trimestre | B89: n | C89: X = n − (N+1)/2 | D89: Y (mdp) | E89: XY | F89: X² | H89: Trimestre a pronosticar | I89: X (pronóstico) | J89: Y pronosticada
A90: =Datos!B$5 -> 2T25 | B90: 1 | C90: =B90-(COUNT($B$90:$B$94)+1)/2 -> -2 | D90: =Datos!B14 -> 1105.905 | E90: =C90*D90 -> -2211.81 | F90: =C90^2 -> 4 | H90: 3T26 | I90: =MAX($C$90:$C$94)+1 -> 3 | J90: =$B$99+$B$98*I90 -> 1011.854
A91: =Datos!C$5 -> 3T25 | B91: 2 | C91: =B91-(COUNT($B$90:$B$94)+1)/2 -> -1 | D91: =Datos!C14 -> 1049.349 | E91: =C91*D91 -> -1049.349 | F91: =C91^2 -> 1 | H91: 4T26 | I91: =I90+1 -> 4 | J91: =$B$99+$B$98*I91 -> 996.7536
A92: =Datos!D$5 -> 4T25 | B92: 3 | C92: =B92-(COUNT($B$90:$B$94)+1)/2 -> 0 | D92: =Datos!D14 -> 1051 | E92: =C92*D92 -> 0 | F92: =C92^2 -> 0 | H92: 1T27 | I92: =I91+1 -> 5 | J92: =$B$99+$B$98*I92 -> 981.6532
A93: =Datos!E$5 -> 1T26 | B93: 4 | C93: =B93-(COUNT($B$90:$B$94)+1)/2 -> 1 | D93: =Datos!E14 -> 1048.889 | E93: =C93*D93 -> 1048.889 | F93: =C93^2 -> 1 | H93: 2T27 | I93: =I92+1 -> 6 | J93: =$B$99+$B$98*I93 -> 966.5528
A94: =Datos!F$5 -> 2T26 | B94: 5 | C94: =B94-(COUNT($B$90:$B$94)+1)/2 -> 2 | D94: =Datos!F14 -> 1030.633 | E94: =C94*D94 -> 2061.266 | F94: =C94^2 -> 4
A95: Σ (sumas) | C95: =SUM(C90:C94) -> 0 | D95: =SUM(D90:D94) -> 5285.776 | E95: =SUM(E90:E94) -> -151.004 | F95: =SUM(F90:F94) -> 10 | H95: ="Ecuación: Y = "&TEXT(B99,"#,##0.0000")&" + ("&TEXT(B98,"#,##0.0000")&")·X" -> Ecuación: Y = 1,057.1552 + (-15.1004)·X
A96: N (trimestres) | B96: =COUNT(B90:B94) -> 5
A97: X̄ = ΣX / N | B97: =C95/B96 -> 0
A98: b = ΣXY / ΣX² | B98: =E95/F95 -> -15.1004
A99: a = ΣY / N | B99: =D95/B96 -> 1057.1552
A100: R² (ajuste) | B100: =RSQ(D90:D94,C90:C94) -> 0.70222795
A105: 5. CAPEX (inmuebles, equipo e intangibles)
A106: Trimestre | B106: n | C106: X = n − (N+1)/2 | D106: Y (mdp) | E106: XY | F106: X² | H106: Trimestre a pronosticar | I106: X (pronóstico) | J106: Y pronosticada
A107: =Datos!B$5 -> 2T25 | B107: 1 | C107: =B107-(COUNT($B$107:$B$111)+1)/2 -> -2 | D107: =Datos!B16 -> 663.2 | E107: =C107*D107 -> -1326.4 | F107: =C107^2 -> 4 | H107: 3T26 | I107: =MAX($C$107:$C$111)+1 -> 3 | J107: =$B$116+$B$115*I107 -> 798.82
A108: =Datos!C$5 -> 3T25 | B108: 2 | C108: =B108-(COUNT($B$107:$B$111)+1)/2 -> -1 | D108: =Datos!C16 -> 775.2 | E108: =C108*D108 -> -775.2 | F108: =C108^2 -> 1 | H108: 4T26 | I108: =I107+1 -> 4 | J108: =$B$116+$B$115*I108 -> 820.74
A109: =Datos!D$5 -> 4T25 | B109: 3 | C109: =B109-(COUNT($B$107:$B$111)+1)/2 -> 0 | D109: =Datos!D16 -> 816 | E109: =C109*D109 -> 0 | F109: =C109^2 -> 0 | H109: 1T27 | I109: =I108+1 -> 5 | J109: =$B$116+$B$115*I109 -> 842.66
A110: =Datos!E$5 -> 1T26 | B110: 4 | C110: =B110-(COUNT($B$107:$B$111)+1)/2 -> 1 | D110: =Datos!E16 -> 501 | E110: =C110*D110 -> 501 | F110: =C110^2 -> 1 | H110: 2T27 | I110: =I109+1 -> 6 | J110: =$B$116+$B$115*I110 -> 864.58
A111: =Datos!F$5 -> 2T26 | B111: 5 | C111: =B111-(COUNT($B$107:$B$111)+1)/2 -> 2 | D111: =Datos!F16 -> 909.9 | E111: =C111*D111 -> 1819.8 | F111: =C111^2 -> 4
A112: Σ (sumas) | C112: =SUM(C107:C111) -> 0 | D112: =SUM(D107:D111) -> 3665.3 | E112: =SUM(E107:E111) -> 219.2 | F112: =SUM(F107:F111) -> 10 | H112: ="Ecuación: Y = "&TEXT(B116,"#,##0.0000")&" + ("&TEXT(B115,"#,##0.0000")&")·X" -> Ecuación: Y = 733.0600 + (21.9200)·X
A113: N (trimestres) | B113: =COUNT(B107:B111) -> 5
A114: X̄ = ΣX / N | B114: =C112/B113 -> 0
A115: b = ΣXY / ΣX² | B115: =E112/F112 -> 21.92
A116: a = ΣY / N | B116: =D112/B113 -> 733.06
A117: R² (ajuste) | B117: =RSQ(D107:D111,C107:C111) -> 0.048701497
A122: 6. CAPITAL DE TRABAJO NETO (activo circ. − pasivo circ.)
A123: Trimestre | B123: n | C123: X = n − (N+1)/2 | D123: Y (mdp) | E123: XY | F123: X² | H123: Trimestre a pronosticar | I123: X (pronóstico) | J123: Y pronosticada
A124: =Datos!B$5 -> 2T25 | B124: 1 | C124: =B124-(COUNT($B$124:$B$128)+1)/2 -> -2 | D124: =Datos!B19-Datos!B21 -> 11066 | E124: =C124*D124 -> -22132 | F124: =C124^2 -> 4 | H124: 3T26 | I124: =MAX($C$124:$C$128)+1 -> 3 | J124: =$B$133+$B$132*I124 -> 6975.4312
A125: =Datos!C$5 -> 3T25 | B125: 2 | C125: =B125-(COUNT($B$124:$B$128)+1)/2 -> -1 | D125: =Datos!C19-Datos!C21 -> 11577 | E125: =C125*D125 -> -11577 | F125: =C125^2 -> 1 | H125: 4T26 | I125: =I124+1 -> 4 | J125: =$B$133+$B$132*I125 -> 6036.114
A126: =Datos!D$5 -> 4T25 | B126: 3 | C126: =B126-(COUNT($B$124:$B$128)+1)/2 -> 0 | D126: =Datos!D19-Datos!D21 -> 9310 | E126: =C126*D126 -> 0 | F126: =C126^2 -> 0 | H126: 1T27 | I126: =I125+1 -> 5 | J126: =$B$133+$B$132*I126 -> 5096.7968
...

Sheet Variables Externas
A4: # | B4: Categoría | C4: Variable | D4: Dato observado | E4: Canal de transmisión a Soriana | F4: Partida del FCFF afectada | G4: Efecto | H4: Ajuste a ventas (%) | I4: Ajuste a costos y gastos (%) | J4: Ajuste a capex (%)
A5: 1 | B5: Macroeconomía México | C5: Crecimiento del PIB | D5: Banxico (Informe abr–jun 2026): PIB 2026 1.5% (rango 1.0–2.0%); 2027 2.0% (rango 1.2–2.8%) | E5: Banxico espera que el consumo privado retome tendencia positiva tras la debilidad de inicio de 2026: más volumen en autoservicio | F5: Ventas | G5: + | H5: 0.005 | I5: 0 | J5: 0
A6: 2 | B6: Macroeconomía México | C6: Inflación | D6: General 3.42% y subyacente 3.79% (1a quincena sep-2026); convergencia a 3% hasta 4T27 | E6: Eleva ventas nominales y costo de mercancía en proporción similar; efecto casi neutral en margen (ya capturado en la tendencia) | F6: Ventas y costos | G6: Neutral | H6: 0 | I6: 0 | J6: 0
A7: 3 | B7: Política monetaria | C7: Tasa objetivo Banxico / Fed | D7: Banxico mantuvo 6.50% (24-sep-2026, unánime); la Fed subió 25 pb en septiembre | E7: Afecta costo de deuda y WACC (descuento del FCFF), no el FCFF operativo; crédito al consumo sigue caro | F7: WACC / gastos financieros | G7: − (valuación) | H7: 0 | I7: 0 | J7: 0
A8: 4 | B8: Macroeconomía México | C8: Tipo de cambio | D8: 18.08 MXN/USD al cierre del 30-sep-2026; el peso perdió 6.38% en septiembre | E8: Encarece mercancía general importada (electrónica, línea blanca) y equipo/refrigeración del programa de capex | F8: Costos y capex | G8: − | H8: 0 | I8: 0.001 | J8: 0.01
A9: 5 | B9: Macroeconomía México | C9: Remesas | D9: 2025: USD 61,791 mm (−4.6%), primera caída anual en 11 años; 1T26 +1.4% | E9: Menor ingreso de hogares en Bajío, Occidente y Norte (regiones clave de Soriana) por política migratoria de EU | F9: Ventas | G9: − | H9: -0.003 | I9: 0 | J9: 0
A10: 6 | B10: Política México (laboral) | C10: Salario mínimo 2026 | D10: +13%: de 278.80 a 315.04 $/día (frontera norte +5%: 440.87 $/día); meta 2.5 canastas básicas a 2030 | E10: Sube la nómina operativa de tiendas, pero también el ingreso disponible del cliente de bajos ingresos | F10: Costos (+) y ventas (+) | G10: Mixto | H10: 0.002 | I10: 0.0015 | J10: 0
A11: 7 | B11: Política México (laboral) | C11: Jornada laboral de 40 horas | D11: Reducción gradual de 48 a 40 h; 2026 es periodo de adecuación y los cambios inician en 2027 | E11: Requiere más turnos/plantilla en tiendas de horario extendido o más automatización | F11: Costos | G11: − | H11: 0 | I11: 0.0005 | J11: 0
A12: 8 | B12: Política México (fiscal) | C12: IEPS a bebidas y tabaco | D12: Bebidas azucaradas de 1.64 a 3.08 $/litro; tabaco de 160% a 200% ad valorem (2026) | E12: Menor volumen en categorías de alta rotación (refrescos, tabaco) dentro del ticket del autoservicio | F12: Ventas | G12: − | H12: -0.002 | I12: 0 | J12: 0
A13: 9 | B13: Política comercial México | C13: Aranceles a países sin tratado | D13: Aranceles nuevos o mayores de hasta 50% a importaciones de China, Corea del Sur, India, Vietnam, etc. desde 1-ene-2026 | E13: Encarece ropa, juguetes, electrónicos y equipo de tienda de origen asiático | F13: Costos y capex | G13: − | H13: 0 | I13: 0.0005 | J13: 0.005
A14: 10 | B14: T-MEC | C14: Revisión del T-MEC | D14: EU activó el mecanismo de revisiones anuales (no hubo extensión en jul-2026); Banxico prevé inversión débil por la incertidumbre comercial | E14: Frena inversión y empleo formal en el Norte industrial, base de clientes de Soriana (Coahuila, NL, Chihuahua) | F14: Ventas | G14: − | H14: -0.003 | I14: 0 | J14: 0
A15: 11 | B15: T-MEC / aranceles de EU | C15: Aranceles de EU a sectores estratégicos | D15: Persisten aranceles de EU a acero, aluminio y automotriz; bienes con origen T-MEC conservan exención; exportaciones a EU +7.7% acumulado a mayo | E15: Presión sobre empleo manufacturero (autopartes, acero) en ciudades del Norte donde Soriana concentra tiendas | F15: Ventas | G15: − | H15: -0.002 | I15: 0 | J15: 0
A16: 12 | B16: Geopolítica | C16: Conflicto en Medio Oriente / petróleo | D16: Petróleo por encima de USD 100, dólar fuerte e incertidumbre geopolítica presionan al peso (sep-2026) | E16: Encarece energía de tiendas, diésel y fletes de la logística; riesgo inflacionario | F16: Costos | G16: − | H16: 0 | I16: 0.0005 | J16: 0
... A21: 17 | B21: Inmobiliario y arrendamientos | C21: Ocupación de centros comerciales (FIBRAs) | D21: Los 10 jugadores institucionales con ocupación arriba de 91% (algunos 99%) al 2T26, rentas al alza y spreads de renovación altos | E21: Alta demanda por espacio facilita monetizar/subarrendar las áreas liberadas por cierres y reducción de tiendas | F21: Ventas (otros ingresos) | G21: + | H21: 0.001 | I21: 0 | J21: 0
A22: TOTAL | C22: Ajuste neto aplicado a la proyección | H22: =SUM(H5:H21) -> -0.009 | I22: =SUM(I5:I21) -> 0.0052 | J22: =SUM(J5:J21) -> 0.025

Sheet Proyección Final Soriana
A5: A. PONDERACIÓN DE MÉTODOS | B5: 2025A | C5: 2026E | D5: 2027E | E5: 2028E | F5: 2029E | G5: 2030E
A6: Peso de variables externas | C6: 0.7 | D6: 0.7 | E6: 0.75 | F6: 0.8 | G6: 0.85
A7: Peso de mínimos cuadrados | C7: =1-C6 -> 0.3 | D7: =1-D6 -> 0.3 | E7: =1-E6 -> 0.25 | F7: =1-F6 -> 0.2 | G7: =1-G6 -> 0.15
A9: B. CRECIMIENTO DE VENTAS — VARIABLES EXTERNAS | B9: 2025A | C9: 2026E | D9: 2027E | E9: 2028E | F9: 2029E | G9: 2030E
A10: Inflación esperada (INPC) — escenario de la hoja Inflación | C10: =Inflación!B13 -> 0.0351 | D10: =Inflación!C13 -> 0.0351 | E10: =Inflación!D13 -> 0.0351 | F10: =Inflación!E13 -> 0.0351 | G10: =Inflación!F13 -> 0.0351
A11: Crecimiento real del PIB de México | C11: 0.014 | D11: 0.018 | E11: 0.02 | F11: 0.02 | G11: 0.02
A12: Elasticidad del volumen de autoservicio al PIB (x) | C12: 0.5 | D12: 0.5 | E12: 0.5 | F12: 0.5 | G12: 0.5
A13: Ajuste por debilidad del consumo | C13: -0.04 | D13: -0.015 | E13: -0.005 | F13: 0 | G13: 0
A14: Crecimiento nominal del mercado de autoservicio | C14: =C10+C11*C12+C13 -> 0.0021 | D14: =D10+D11*D12+D13 -> 0.0291 | E14: =E10+E11*E12+E13 -> 0.0401 | F14: =F10+F11*F12+F13 -> 0.0451 | G14: =G10+G11*G12+G13 -> 0.0451
A15: (±) Pérdida de participación (hard discount y competidores) | C15: -0.03 | D15: -0.02 | E15: -0.0125 | F15: -0.01 | G15: -0.0075
A16: (±) Cierre y reducción de tiendas | C16: -0.01 | D16: -0.005 | E16: 0 | F16: 0 | G16: 0
A17: (±) Remesas y política migratoria de EU | C17: -0.003 | D17: -0.002 | E17: -0.001 | F17: 0 | G17: 0
A18: (±) T-MEC y aranceles de EU (empleo industrial del Norte) | C18: -0.002 | D18: -0.003 | E18: -0.001 | F18: 0 | G18: 0
A19: (±) Programas sociales y salario mínimo (ingreso disponible) | C19: 0.002 | D19: 0.003 | E19: 0.003 | F19: 0.002 | G19: 0.002
A20: (±) Omnicanalidad y ventas digitales | C20: 0.003 | D20: 0.004 | E20: 0.005 | F20: 0.005 | G20: 0.005
A21: (±) PACIC e IEPS (precio tope y menor volumen) | C21: -0.002 | D21: -0.002 | E21: -0.001 | F21: 0 | G21: 0
A22: (±) Ingresos inmobiliarios y financieros (m² liberados, Sofipo) | C22: 0.001 | D22: 0.002 | E22: 0.002 | F22: 0.002 | G22: 0.002
A23: Crecimiento de ventas — variables externas | C23: =C14+SUM(C15:C22) -> -0.0389 | D23: =D14+SUM(D15:D22) -> 0.0061 | E23: =E14+SUM(E15:E22) -> 0.0346 | F23: =F14+SUM(F15:F22) -> 0.0441 | G23: =G14+SUM(G15:G22) -> 0.0466
A25: C. CRECIMIENTO DE VENTAS — MÍNIMOS CUADRADOS | B25: 2025A | C25: 2026E | D25: 2027E | E25: 2028E | F25: 2029E | G25: 2030E
A26: Ventas por mínimos cuadrados (regresión solo 2026E; 2027E–2030E crecen con la inflación) | B26: ='MC Soriana'!G6 -> 174278 | C26: ='MC Soriana'!F24 -> 162461.17 | D26: =C26*(1+D10) -> 168163.56 | E26: =D26*(1+E10) -> 174066.1 | F26: =E26*(1+F10) -> 180175.82 | G26: =F26*(1+G10) -> 186499.99
A27: Crecimiento de ventas — mínimos cuadrados | C27: =C26/B26-1 -> -0.067804481 | D27: =D26/C26-1 -> 0.0351 | E27: =E26/D26-1 -> 0.0351 | F27: =F26/E26-1 -> 0.0351 | G27: =G26/F26-1 -> 0.0351
A28: CRECIMIENTO DE VENTAS FINAL (ponderado) | C28: =C$6*C23+C$7*C27 -> -0.047571344 | D28: =D$6*D23+D$7*D27 -> 0.0148 | E28: =E$6*E23+E$7*E27 -> 0.034725 | F28: =F$6*F23+F$7*F27 -> 0.0423 | G28: =G$6*G23+G$7*G27 -> 0.044875
A30: D. MARGEN EBIT | B30: 2025A | C30: 2026E | D30: 2027E | E30: 2028E | F30: 2029E | G30: 2030E
A31: Margen EBIT — variables externas (acumulado) | B31: =Valuación!B10 -> 0.042542884 | C31: =B31+SUM(C32:C39) -> 0.043742884 | D31: =C31+SUM(D32:D39) -> 0.043442884 | E31: =D31+SUM(E32:E39) -> 0.043742884 | F31: =E31+SUM(F32:F39) -> 0.044042884 | G31: =F31+SUM(G32:G39) -> 0.044342884
A32: (±) Austeridad, cierres y eficiencias | C32: 0.0055 | D32: 0.003 | E32: 0.002 | F32: 0.001 | G32: 0.001
A33: (±) Salario mínimo +13% y jornada de 40 h | C33: -0.001 | D33: -0.0015 | E33: -0.0015 | F33: -0.001 | G33: -0.001
A34: (±) Inversión en precio (hard discount, PACIC) | C34: -0.0015 | D34: -0.001 | E34: -0.001 | F34: -0.0005 | G34: 0
A35: (±) Tipo de cambio y aranceles a importaciones de Asia | C35: -0.0005 | D35: -0.0005 | E35: 0 | F35: 0 | G35: 0
A36: (±) Energía, combustibles y fletes | C36: -0.0005 | D36: -0.0005 | E36: 0 | F36: 0 | G36: 0
A37: (±) Rentas comerciales (tiendas arrendadas) | C37: -0.0003 | D37: -0.0003 | E37: -0.0002 | F37: -0.0002 | G37: -0.0002
A38: (±) Ingresos inmobiliarios y servicios financieros | C38: 0.0005 | D38: 0.001 | E38: 0.001 | F38: 0.001 | G38: 0.0005
A39: (±) Desapalancamiento operativo por menores ventas | C39: -0.001 | D39: -0.0005 | E39: 0 | F39: 0 | G39: 0
A40: Margen EBIT — mínimos cuadrados ajustado por variables externas | C40: ='MC Soriana'!$F$27 -> 0.044311756 | D40: ='MC Soriana'!$F$27 -> 0.044311756 | E40: ='MC Soriana'!$F$27 -> 0.044311756 | F40: ='MC Soriana'!$F$27 -> 0.044311756 | G40: ='MC Soriana'!$F$27 -> 0.044311756
A41: MARGEN EBIT FINAL (ponderado) | C41: =C$6*C31+C$7*C40 -> 0.043913545 | D41: =D$6*D31+D$7*D40 -> 0.043703545 | E41: =E$6*E31+E$7*E40 -> 0.043885102 | F41: =F$6*F31+F$7*F40 -> 0.044096658 | G41: =G$6*G31+G$7*G40 -> 0.044338215
A43: E. OTROS SUPUESTOS (FCF Y ESTADOS FINANCIEROS) | B43: 2025A | C43: 2026E | D43: 2027E | E43: 2028E | F43: 2029E | G43: 2030E
A44: D&A (% ventas) — variables externas / histórico | C44: =Valuación!$B$11 -> 0.024459905 | D44: =Valuación!$B$11 -> 0.024459905 | E44: =Valuación!$B$11 -> 0.024459905 | F44: =Valuación!$B$11 -> 0.024459905 | G44: =Valuación!$B$11 -> 0.024459905
A45: D&A (% ventas) — mínimos cuadrados | C45: ='MC Soriana'!$F$30/'MC Soriana'!$F$24 -> 0.024355442 | D45: ='MC Soriana'!$F$30/'MC Soriana'!$F$24 -> 0.024355442 | E45: ='MC Soriana'!$F$30/'MC Soriana'!$F$24 -> 0.024355442 | F45: ='MC Soriana'!$F$30/'MC Soriana'!$F$24 -> 0.024355442 | G45: ='MC Soriana'!$F$30/'MC Soriana'!$F$24 -> 0.024355442
A46: D&A (% ventas) FINAL | C46: =C$6*C44+C$7*C45 -> 0.024428566 | D46: =D$6*D44+D$7*D45 -> 0.024428566 | E46: =E$6*E44+E$7*E45 -> 0.024433789 | F46: =F$6*F44+F$7*F45 -> 0.024439012 | G46: =G$6*G44+G$7*G45 -> 0.024444235
A47: Capex guía de Soriana 2026 (mdp) | C47: 4000
A48: (+) Inversión adicional en omnicanal y remodelación (% ventas) | D48: 0.003 | E48: 0.003 | F48: 0.003 | G48: 0.003
A49: Capex (% ventas) — variables externas | C49: =C47/C67 -> 0.023658787 | D49: =Valuación!$B$12*(1+'Variables Externas'!$J$22)+D48 -> 0.019554517 | E49: =Valuación!$B$12*(1+'Variables Externas'!$J$22)+E48 -> 0.019554517 | F49: =Valuación!$B$12*(1+'Variables Externas'!$J$22)+F48 -> 0.019554517 | G49: =Valuación!$B$12*(1+'Variables Externas'!$J$22)+G48 -> 0.019554517
A50: Capex (% ventas) — mínimos cuadrados | C50: ='MC Soriana'!$F$31/'MC Soriana'!$F$24 -> 0.020989446 | D50: ='MC Soriana'!$F$31/'MC Soriana'!$F$24 -> 0.020989446 | E50: ='MC Soriana'!$F$31/'MC Soriana'!$F$24 -> 0.020989446 | F50: ='MC Soriana'!$F$31/'MC Soriana'!$F$24 -> 0.020989446 | G50: ='MC Soriana'!$F$31/'MC Soriana'!$F$24 -> 0.020989446
A51: Capex (% ventas) FINAL | C51: =C$6*C49+C$7*C50 -> 0.022857985 | D51: =D$6*D49+D$7*D50 -> 0.019984995 | E51: =E$6*E49+E$7*E50 -> 0.019913249 | F51: =F$6*F49+F$7*F50 -> 0.019841502 | G51: =G$6*G49+G$7*G50 -> 0.019769756
A52: (+) Ajuste a la tasa por límite de deducciones (Paquete Económico 2027) | C52: 0 | D52: 0.005 | E52: 0.005 | F52: 0.005 | G52: 0.005
A53: Tasa de impuestos — variables externas | C53: =WACC!$B$10+C52 -> 0.3 | D53: =WACC!$B$10+D52 -> 0.305 | E53: =WACC!$B$10+E52 -> 0.305 | F53: =WACC!$B$10+F52 -> 0.305 | G53: =WACC!$B$10+G52 -> 0.305
A54: Tasa de impuestos — efectiva FY2025 (sustituye la tendencia lineal de MC) | C54: =Datos!$G$12/Datos!$G$11 -> 0.30067142 | D54: =Datos!$G$12/Datos!$G$11 -> 0.30067142 | E54: =Datos!$G$12/Datos!$G$11 -> 0.30067142 | F54: =Datos!$G$12/Datos!$G$11 -> 0.30067142 | G54: =Datos!$G$12/Datos!$G$11 -> 0.30067142
A55: Tasa de impuestos FINAL | C55: =C$6*C53+C$7*C54 -> 0.30020143 | D55: =D$6*D53+D$7*D54 -> 0.30370143 | E55: =E$6*E53+E$7*E54 -> 0.30391786 | F55: =F$6*F53+F$7*F54 -> 0.30413428 | G55: =G$6*G53+G$7*G54 -> 0.30435071
A56: Días de inventario (sobre costo de ventas) | B56: =Datos!G18/Datos!G7*365 -> 87.444305 | C56: 88 | D56: 88 | E56: 87 | F56: 87 | G56: 87
A57: Otros activos circulantes (% ventas) | B57: =(Datos!G19-Datos!G17-Datos!G18)/Datos!G6 -> 0.039157254 | C57: =$B57 -> 0.039157254 | D57: =$B57 -> 0.039157254 | E57: =$B57 -> 0.039157254 | F57: =$B57 -> 0.039157254 | G57: =$B57 -> 0.039157254
A58: Pasivo circulante operativo (% ventas) | B58: =(Datos!G21-Datos!G25-Datos!G27)/Datos!G6 -> 0.20022533 | C58: =$B58 -> 0.20022533 | D58: =$B58 -> 0.20022533 | E58: =$B58 -> 0.20022533 | F58: =$B58 -> 0.20022533 | G58: =$B58 -> 0.20022533
A59: Costo de ventas (% ventas) | B59: =Datos!G7/Datos!G6 -> 0.75910205 | C59: 0.756 | D59: 0.757 | E59: 0.758 | F59: 0.758 | G59: 0.758
A60: Gastos de operación sin D&A (% ventas) | B60: =-B70/B67 -> 0.1739008 | C60: =1-C59-C46-C41 -> 0.17565789 | D60: =1-D59-D46-D41 -> 0.17486789 | E60: =1-E59-E46-E41 -> 0.17368111 | F60: =1-F59-F46-F41 -> 0.17346433 | G60: =1-G59-G46-G41 -> 0.17321755
A61: Tasa de interés implícita (% deuda + arrendamientos) | B61: =Datos!G10/(Datos!G25+Datos!G26+Datos!G27+Datos!G28) -> 0.13015497 | C61: 0.1 | D61: 0.0975 | E61: 0.0975 | F61: 0.0975 | G61: 0.0975
A62: Amortización neta de deuda bursátil y bancaria (mdp) | C62: 0 | D62: -1500 | E62: -1500 | F62: -1500 | G62: -1500
A63: Dividendos (% utilidad neta) | B63: ='Proyección Soriana'!B14 -> 0.30014406 | C63: =$B63 -> 0.30014406 | D63: =$B63 -> 0.30014406 | E63: =$B63 -> 0.30014406 | F63: =$B63 -> 0.30014406 | G63: =$B63 -> 0.30014406
A65: 1. PROYECCIÓN DE ESTADOS FINANCIEROS (mdp)
A66: 1.1 ESTADO DE RESULTADOS | B66: 2025A | C66: 2026E | D66: 2027E | E66: 2028E | F66: 2029E | G66: 2030E
A67: Ventas | B67: =Datos!G6 -> 177515 | C67: =B67*(1+C28) -> 169070.37 | D67: =C67*(1+D28) -> 171572.61 | E67: =D67*(1+E28) -> 177530.47 | F67: =E67*(1+F28) -> 185040.01 | G67: =F67*(1+G28) -> 193343.68
A68: Costo de ventas | B68: =-Datos!G7 -> -134752 | C68: =-C67*C59 -> -127817.2 | D68: =-D67*D59 -> -129880.47 | E68: =-E67*E59 -> -134568.1 | F68: =-F67*F59 -> -140260.33 | G68: =-G67*G59 -> -146554.51
A69: Utilidad bruta | B69: =B67+B68 -> 42763 | C69: =C67+C68 -> 41253.171 | D69: =D67+D68 -> 41692.145 | E69: =E67+E68 -> 42962.375 | F69: =F67+F68 -> 44779.683 | G69: =G67+G68 -> 46789.171
A70: Gastos de operación (sin D&A) | B70: =-(Datos!G8-Datos!G9-Datos!G14) -> -30870 | C70: =-C67*C60 -> -29698.545 | D70: =-D67*D60 -> -30002.541 | E70: =-E67*E60 -> -30833.69 | F70: =-F67*F60 -> -32097.842 | G70: =-G67*G60 -> -33490.519
A71: EBITDA | B71: =B69+B70 -> 11893 | C71: =C69+C70 -> 11554.626 | D71: =D69+D70 -> 11689.604 | E71: =E69+E70 -> 12128.685 | F71: =F69+F70 -> 12681.841 | G71: =G69+G70 -> 13298.652
A72: Depreciación y amortización | B72: =-Datos!G14 -> -4342 | C72: =-C67*C46 -> -4130.1467 | D72: =-D67*D46 -> -4191.2729 | E72: =-E67*E46 -> -4337.7421 | F72: =-F67*F46 -> -4522.1951 | G72: =-G67*G46 -> -4726.1385
A73: Utilidad de operación (EBIT) | B73: =B71+B72 -> 7551 | C73: =C71+C72 -> 7424.4795 | D73: =D71+D72 -> 7498.3315 | E73: =E71+E72 -> 7790.9429 | F73: =F71+F72 -> 8159.6462 | G73: =G71+G72 -> 8572.5137
A74: Gastos financieros | B74: =-Datos!G10 -> -3074 | C74: =-C61*(B91+B92) -> -2361.8 | D74: =-D61*(C91+C92) -> -2302.755 | E74: =-E61*(D91+D92) -> -2156.505 | F74: =-F61*(E91+E92) -> -2010.255 | G74: =-G61*(F91+F92) -> -1864.005
A75: Otros ingresos (gastos) netos | B75: =Datos!G11-Datos!G9+Datos!G10 -> 288 | C75: 0 | D75: 0 | E75: 0 | F75: 0 | G75: 0
A76: Utilidad antes de impuestos | B76: =B73+B74+B75 -> 4765 | C76: =C73+C74+C75 -> 5062.6795 | D76: =D73+D74+D75 -> 5195.5765 | E76: =E73+E74+E75 -> 5634.4379 | F76: =F73+F74+F75 -> 6149.3912 | G76: =G73+G74+G75 -> 6708.5087
A77: Impuestos a la utilidad | B77: =-Datos!G12 -> -1433 | C77: =-C76*C55 -> -1519.8236 | D77: =-D76*D55 -> -1577.904 | E77: =-E76*E55 -> -1712.4063 | F77: =-F76*F55 -> -1870.2407 | G77: =-G76*G55 -> -2041.7394
A78: Utilidad neta | B78: =B76+B77 -> 3332 | C78: =C76+C77 -> 3542.8559 | D78: =D76+D77 -> 3617.6725 | E78: =E76+E77 -> 3922.0316 | F78: =F76+F77 -> 4279.1505 | G78: =G76+G77 -> 4666.7693
A79: Dividendos pagados | C79: =-C78*C63 -> -1063.3671 | D79: =-D78*D63 -> -1085.8229 | E79: =-E78*E63 -> -1177.1745 | F79: =-F78*F63 -> -1284.3616 | G79: =-G78*G63 -> -1400.7031
A80: Margen EBITDA | B80: =B71/B67 -> 0.066997155 | C80: =C71/C67 -> 0.068342111 | D80: =D71/D67 -> 0.068132111 | E80: =E71/E67 -> 0.068318891 | F80: =F71/F67 -> 0.06853567 | G80: =G71/G67 -> 0.06878245
A81: Margen neto | B81: =B78/B67 -> 0.018770245 | C81: =C78/C67 -> 0.020954919 | D81: =D78/D67 -> 0.021085373 | E81: =E78/E67 -> 0.02209216 | F81: =F78/F67 -> 0.023125542 | G81: =G78/G67 -> 0.02413717
A83: 1.2 BALANCE GENERAL | B83: 2025A | C83: 2026E | D83: 2027E | E83: 2028E | F83: 2029E | G83: 2030E
A84: Efectivo y equivalentes | B84: =Datos!G17 -> 9295 | C84: =B84+C108 -> 12146.665 | D84: =C84+D108 -> 13846.496 | E84: =D84+E108 -> 16092.019 | F84: =E84+F108 -> 18290.3 | G84: =F84+G108 -> 20797.347
A85: Inventarios | B85: =Datos!G18 -> 32283 | C85: =-C68*C56/365 -> 30816.202 | D85: =-D68*D56/365 -> 31313.647 | E85: =-E68*E56/365 -> 32075.136 | F85: =-F68*F56/365 -> 33431.914 | G85: =-G68*G56/365 -> 34932.171
A86: Otros activos circulantes | B86: =Datos!G19-Datos!G17-Datos!G18 -> 6951 | C86: =C67*C57 -> 6620.3316 | D86: =D67*D57 -> 6718.3125 | E86: =E67*E57 -> 6951.6059 | F86: =F67*F57 -> 7245.6588 | G86: =G67*G57 -> 7570.8078
A87: Activo circulante | B87: =SUM(B84:B86) -> 48529 | C87: =SUM(C84:C86) -> 49583.199 | D87: =SUM(D84:D86) -> 51878.456 | E87: =SUM(E84:E86) -> 55118.761 | F87: =SUM(F84:F86) -> 58967.873 | G87: =SUM(G84:G86) -> 63300.326
A88: Activo no circulante | B88: =Datos!G20-Datos!G19 -> 107509 | C88: =B88-C104+C72 -> 107243.46 | D88: =C88-D104+D72 -> 106481.07 | E88: =D88-E104+E72 -> 105678.53 | F88: =E88-F104+F72 -> 104827.81 | G88: =F88-G104+G72 -> 103924.03
A89: Activo total | B89: =B87+B88 -> 156038 | C89: =C87+C88 -> 156826.66 | D89: =D87+D88 -> 158359.52 | E89: =E87+E88 -> 160797.29 | F89: =F87+F88 -> 163795.68 | G89: =G87+G88 -> 167224.35
A90: Pasivo circulante operativo (proveedores y otros) | B90: =Datos!G21-Datos!G25-Datos!G27 -> 35543 | C90: =C67*C58 -> 33852.172 | D90: =D67*D58 -> 34353.184 | E90: =E67*E58 -> 35546.098 | F90: =F67*F58 -> 37049.698 | G90: =G67*G58 -> 38712.303
A91: Deuda bursátil y bancaria | B91: =Datos!G25+Datos!G26 -> 11500 | C91: =MAX(0,B91+C62) -> 11500 | D91: =MAX(0,C91+D62) -> 10000 | E91: =MAX(0,D91+E62) -> 8500 | F91: =MAX(0,E91+F62) -> 7000 | G91: =MAX(0,F91+G62) -> 5500
A92: Pasivo por arrendamiento | B92: =Datos!G27+Datos!G28 -> 12118 | C92: =B92 -> 12118 | D92: =C92 -> 12118 | E92: =D92 -> 12118 | F92: =E92 -> 12118 | G92: =F92 -> 12118
A93: Otros pasivos a largo plazo | B93: =Datos!G23-Datos!G21-Datos!G26-Datos!G28 -> 12145 | C93: =B93 -> 12145 | D93: =C93 -> 12145 | E93: =D93 -> 12145 | F93: =E93 -> 12145 | G93: =F93 -> 12145
A94: Pasivo total | B94: =SUM(B90:B93) -> 71306 | C94: =SUM(C90:C93) -> 69615.172 | D94: =SUM(D90:D93) -> 68616.184 | E94: =SUM(E90:E93) -> 68309.098 | F94: =SUM(F90:F93) -> 68312.698 | G94: =SUM(G90:G93) -> 68475.303
A95: Capital contable | B95: =Datos!G24 -> 84732 | C95: =B95+C78+C79 -> 87211.489 | D95: =C95+D78+D79 -> 89743.338 | E95: =D95+E78+E79 -> 92488.195 | F95: =E95+F78+F79 -> 95482.984 | G95: =F95+G78+G79 -> 98749.051
A96: Pasivo + capital | B96: =B94+B95 -> 156038 | C96: =C94+C95 -> 156826.66 | D96: =D94+D95 -> 158359.52 | E96: =E94+E95 -> 160797.29 | F96: =F94+F95 -> 163795.68 | G96: =G94+G95 -> 167224.35
A97: Comprobación (activo − pasivo − capital) | B97: =B89-B96 -> 0 | C97: =C89-C96 -> 0 | D97: =D89-D96 -> 0 | E97: =E89-E96 -> 0 | F97: =F89-F96 -> 0 | G97: =G89-G96 -> 0
A99: 1.3 CONCILIACIÓN DE EFECTIVO | B99: 2025A | C99: 2026E | D99: 2027E | E99: 2028E | F99: 2029E | G99: 2030E
A100: Utilidad neta | C100: =C78 -> 3542.8559 | D100: =D78 -> 3617.6725 | E100: =E78 -> 3922.0316 | F100: =F78 -> 4279.1505 | G100: =G78 -> 4666.7693
A101: (+) Depreciación y amortización | C101: =-C72 -> 4130.1467 | D101: =-D72 -> 4191.2729 | E101: =-E72 -> 4337.7421 | F101: =-F72 -> 4522.1951 | G101: =-G72 -> 4726.1385
A102: (−) Aumento en inventarios | C102: =-(C85-B85) -> 1466.7979 | D102: =-(D85-C85) -> -497.44524 | E102: =-(E85-D85) -> -761.48855 | F102: =-(F85-E85) -> -1356.7782 | G102: =-(G85-F85) -> -1500.2571
A103: (−) Aumento en otros activos circulantes | C103: =-(C86-B86) -> 330.66841 | D103: =-(D86-C86) -> -97.980907 | E103: =-(E86-D86) -> -233.2934 | F103: =-(F86-E86) -> -294.05293 | G103: =-(G86-F86) -> -325.14894
A104: (−) Capex | C104: =-C67*C51 -> -3864.608 | D104: =-D67*D51 -> -3428.8779 | E104: =-E67*E51 -> -3535.2085 | F104: =-F67*F51 -> -3671.4719 | G104: =-G67*G51 -> -3822.3574
A105: (+) Aumento en pasivo circulante operativo | C105: =C90-B90 -> -1690.8283 | D105: =D90-C90 -> 501.01214 | E105: =E90-D90 -> 1192.9143 | F105: =F90-E90 -> 1503.6 | G105: =G90-F90 -> 1662.6052
A106: (−) Dividendos pagados | C106: =C79 -> -1063.3671 | D106: =D79 -> -1085.8229 | E106: =E79 -> -1177.1745 | F106: =F79 -> -1284.3616 | G106: =G79 -> -1400.7031
A107: (±) Amortización neta de deuda | C107: =C91-B91 -> 0 | D107: =D91-C91 -> -1500 | E107: =E91-D91 -> -1500 | F107: =F91-E91 -> -1500 | G107: =G91-F91 -> -1500
A108: Cambio neto en efectivo | C108: =SUM(C100:C107) -> 2851.6655 | D108: =SUM(D100:D107) -> 1699.8306 | E108: =SUM(E100:E107) -> 2245.5231 | F108: =SUM(F100:F107) -> 2198.2809 | G108: =SUM(G100:G107) -> 2507.0464
A110: 2. FLUJO LIBRE DE EFECTIVO (FCF) — 5 AÑOS | B110: 2025A | C110: 2026E | D110: 2027E | E110: 2028E | F110: 2029E | G110: 2030E
A111: Utilidad de operación (EBIT) | C111: =C73 -> 7424.4795 | D111: =D73 -> 7498.3315 | E111: =E73 -> 7790.9429 | F111: =F73 -> 8159.6462 | G111: =G73 -> 8572.5137
A112: (−) Impuestos sobre EBIT | C112: =-C111*C55 -> -2228.8393 | D112: =-D111*D55 -> -2277.254 | E112: =-E111*E55 -> -2367.8067 | F112: =-F111*F55 -> -2481.6282 | G112: =-G111*G55 -> -2609.0507
...

Sheet Inflación
A5: 1. ESCENARIO DE INFLACIÓN APLICADO AL MODELO (entra a Proyección Final Soriana, fila 10)
A6: Escenario oficial (1 = Cautela · 2 = Base · 3 = Alcista) | E6: 2 | F6: =CHOOSE(E6+1,"Trayectoria Citi — Referencia","Cautela","Base","Alcista") -> Base | H6: Decisión del proyecto: tres escenarios oficiales; Base por defecto. El valor 0 aplica la trayectoria Citi solo como referencia histórica (con la beta heredada reproduce el baseline $31.16).
A8: Concepto | B8: 2026E | C8: 2027E | D8: 2028E | E8: 2029E | F8: 2030E | H8: Fuente / naturaleza
A9: 0 · Trayectoria Citi — Referencia histórica (no es escenario) | B9: 0.0393 | C9: 0.0383 | D9: 0.0375 | E9: 0.0375 | F9: 0.0375 | H9: Encuesta Citi de Expectativas, 22-sep-2026: cierre 2026 3.93%, 2027 3.83%, promedio 2028–32 3.75% (comentario original de Proyección Final!C10). Pronóstico de consenso por año: REFERENCIA HISTÓRICA del modelo anterior, no escenario oficial.
A10: 1 · Cautela (constante) | B10: =$B$33 -> 0.0326 | C10: =$B$33 -> 0.0326 | D10: =$B$33 -> 0.0326 | E10: =$B$33 -> 0.0326 | F10: =$B$33 -> 0.0326 | H10: Ver sección 4: escenario derivado de la tendencia larga (no es pronóstico de modelo).
A11: 2 · Base (constante) | B11: =$B$34 -> 0.0351 | C11: =$B$34 -> 0.0351 | D11: =$B$34 -> 0.0351 | E11: =$B$34 -> 0.0351 | F11: =$B$34 -> 0.0351 | H11: Ver sección 4: resultado de modelo (pronóstico exponencial trimestral de clase).
A12: 3 · Alcista (constante) | B12: =$B$35 -> 0.04 | C12: =$B$35 -> 0.04 | D12: =$B$35 -> 0.04 | E12: =$B$35 -> 0.04 | F12: =$B$35 -> 0.04 | H12: Ver sección 4: supuesto de escenario (no es pronóstico estadístico).
A13: INFLACIÓN APLICADA AL MODELO | B13: =CHOOSE($E$6+1,B9,B10,B11,B12) -> 0.0351 | C13: =CHOOSE($E$6+1,C9,C10,C11,C12) -> 0.0351 | D13: =CHOOSE($E$6+1,D9,D10,D11,D12) -> 0.0351 | E13: =CHOOSE($E$6+1,E9,E10,E11,E12) -> 0.0351 | F13: =CHOOSE($E$6+1,F9,F10,F11,F12) -> 0.0351 | H13: Proyección Final Soriana!C10:G10 = esta fila. Los escenarios constantes extienden a 2026–2030 un pronóstico de un periodo: es un supuesto documentado.
A18: 2. MODELOS EXPONENCIALES
A19: Modelo | B19: n | C19: a | D19: b | E19: R² | F19: x siguiente | G19: Proyección | H19: Lectura
A20: Inmediata (quincenal, último año: sep-25 a sep-26) | B20: =COUNT(B134:B158) -> 25 | C20: =EXP(INTERCEPT(F134:F158,E134:E158)) -> 3.9951135 | D20: =SLOPE(F134:F158,E134:E158) -> -0.0050443032 | E20: =RSQ(F134:F158,E134:E158) -> 0.10389452 | F20: 26 | G20: =C20*EXP(D20*F20)/100 -> 0.035040523 | H20: Resultado de modelo. R² bajo (tendencia de corto plazo).
A21: Trimestral (4 promedios trimestrales del último año) | B21: =COUNT(B26:E26) -> 4 | C21: =EXP(INTERCEPT(B28:E28,B27:E27)) -> 4.0301899 | D21: =SLOPE(B28:E28,B27:E27) -> -0.0277128 | E21: =RSQ(B28:E28,B27:E27) -> 0.092082096 | F21: 5 | G21: =C21*EXP(D21*F21)/100 -> 0.035087136 | H21: Resultado de modelo → define el escenario BASE. Solo 4 puntos.
A22: Ventana larga quincenal 2023–2026 | B22: =COUNT(C70:C158) -> 89 | C22: =EXP(INTERCEPT(D70:D158,C70:C158)) -> 5.8811994 | D22: =SLOPE(D70:D158,C70:C158) -> -0.006333713 | E22: =RSQ(D70:D158,C70:C158) -> 0.62264862 | F22: 90 | G22: =C22*EXP(D22*F22)/100 -> 0.033258542 | H22: Resultado de modelo de tendencia larga.
A23: Libro de clase, ventana quincenal (coeficientes redondeados 5.8812, −0.006) | C23: 5.8812 | D23: -0.006 | F23: 90 | G23: =C23*EXP(D23*F23)/100 -> 0.03427259 | H23: Reproduce INFLACION!T28 = 3.427%. El exponente redondeado sobrestima la proyección frente a la fila 34.
A24: Construcción de clase INFLACION!S113 (5 quincenas jul–sep 2026 + proyección de la fila 35) | G24: =AVERAGE(B154:B158,G23*100)/100 -> 0.032678765 | H24: Es un promedio aritmético que mezcla datos observados y una proyección, no un modelo. Es la construcción más cercana al 3.26% documentado.
A26: Promedios trimestrales (6 quincenas) — libro de clase D19, D25, D31, D37 | B26: =AVERAGE(B134:B139) -> 3.7083333 | C26: =AVERAGE(B140:B145) -> 3.8366667 | D26: =AVERAGE(B146:B151) -> 4.3266667 | E26: =AVERAGE(B152:B157) -> 3.2483333
A27: x del promedio trimestral | B27: 1 | C27: 2 | D27: 3 | E27: 4
A28: ln del promedio trimestral | B28: =LN(B26) -> 1.3105825 | C28: =LN(C26) -> 1.3446039 | D28: =LN(D26) -> 1.4647974 | E28: =LN(E26) -> 1.178142
A31: 4. ESCENARIOS DOCUMENTADOS Y SU NATURALEZA
A32: Escenario | B32: Valor | C32: Naturaleza | H32: Origen y trazabilidad
A33: Cautela | B33: 0.0326 | C33: Escenario derivado de la tendencia larga (no es pronóstico de modelo) | H33: Valor documentado en el Dossier ("ventana 2023-2026, trimestral 3.26%") y en Avances (escenario Cautela). Construcción de clase más cercana: fila 36 (3.268%). Modelos de tendencia larga calculados aquí: fila 34.
A34: Base | B34: =ROUND(G21,4) -> 0.0351 | C34: Forecast / resultado de modelo: modelo exponencial trimestral de clase | H34: Fila 33 redondeada a 2 decimales en %. Reproduce el 3.51% del Dossier ("4.0327e^(−0.028x) → 3.51%") y de Avances. Horizonte: siguiente trimestre; su extensión a 2026–30 es un supuesto.
A35: Alcista | B35: 0.04 | C35: Supuesto de escenario (scenario assumption; no es pronóstico estadístico) | H35: Avances de valuación intrínseca: "Alcista: inflación 4.0%". No proviene de ningún modelo. Referencia de contexto: el promedio trimestral máximo del último año fue 4.33% (fila 38).
A44: 5. DATOS: INPC variación anual quincenal
A45: Quincena | B45: Inflación %
A46: 44562 | B46: 7.13
A47: 44577 | B47: 7.01
A48: 44593 | B48: 7.22
A49: 44608 | B49: 7.34
A50: 44621 | B50: 7.29
A51: 44636 | B51: 7.62
A52: 44652 | B52: 7.72
A53: 44667 | B53: 7.65
A54: 44682 | B54: 7.58
A55: 44697 | B55: 7.72
A56: 44713 | B56: 7.88
A57: 44728 | B57: 8.09
... A69: 44911 | B69: 7.86
A70: 44927 | B70: 7.94 | C70: 1 | D70: =LN(B70) -> 2.0719133
A71: 44942 | B71: 7.88 | C71: 2 | D71: =LN(B71) -> 2.0643279
A72: 44958 | B72: 7.76 | C72: 3 | D72: =LN(B72) -> 2.0489823
A73: 44973 | B73: 7.48 | C73: 4 | D73: =LN(B73) -> 2.0122328
A74: 44986 | B74: 7.12 | C74: 5 | D74: =LN(B74) -> 1.9629077
A75: 45001 | B75: 6.58 | C75: 6 | D75: =LN(B75) -> 1.8840347
A76: 45017 | B76: 6.24 | C76: 7 | D76: =LN(B76) -> 1.8309802
A77: 45032 | B77: 6.27 | C77: 8 | D77: =LN(B77) -> 1.8357764
A78: 45047 | B78: 6 | C78: 9 | D78: =LN(B78) -> 1.7917595
A79: 45062 | B79: 5.67 | C79: 10 | D79: =LN(B79) -> 1.7351891
A80: 45078 | B80: 5.18 | C80: 11 | D80: =LN(B80) -> 1.6448051
A81: 45093 | B81: 4.93 | C81: 12 | D81: =LN(B81) -> 1.595339
... A133: 45885 | B133: 3.65 | C133: 64 | D133: =LN(B133) -> 1.2947272
A134: 45901 | B134: 3.74 | C134: 65 | D134: =LN(B134) -> 1.3190856 | E134: 1 | F134: =LN(B134) -> 1.3190856 | G134: 1
A135: 45916 | B135: 3.78 | C135: 66 | D135: =LN(B135) -> 1.329724 | E135: 2 | F135: =LN(B135) -> 1.329724 | G135: 1
A136: 45931 | B136: 3.63 | C136: 67 | D136: =LN(B136) -> 1.2892326 | E136: 3 | F136: =LN(B136) -> 1.2892326 | G136: 1
A137: 45946 | B137: 3.5 | C137: 68 | D137: =LN(B137) -> 1.252763 | E137: 4 | F137: =LN(B137) -> 1.252763 | G137: 1
A138: 45962 | B138: 3.61 | C138: 69 | D138: =LN(B138) -> 1.2837078 | E138: 5 | F138: =LN(B138) -> 1.2837078 | G138: 1
A139: 45977 | B139: 3.99 | C139: 70 | D139: =LN(B139) -> 1.3837912 | E139: 6 | F139: =LN(B139) -> 1.3837912 | G139: 1
A140: 45992 | B140: 3.72 | C140: 71 | D140: =LN(B140) -> 1.3137237 | E140: 7 | F140: =LN(B140) -> 1.3137237 | G140: 2
A141: 46007 | B141: 3.66 | C141: 72 | D141: =LN(B141) -> 1.2974631 | E141: 8 | F141: =LN(B141) -> 1.2974631 | G141: 2
A142: 46023 | B142: 3.77 | C142: 73 | D142: =LN(B142) -> 1.327075 | E142: 9 | F142: =LN(B142) -> 1.327075 | G142: 2
A143: 46038 | B143: 3.82 | C143: 74 | D143: =LN(B143) -> 1.3402504 | E143: 10 | F143: =LN(B143) -> 1.3402504 | G143: 2
A144: 46054 | B144: 3.92 | C144: 75 | D144: =LN(B144) -> 1.3660917 | E144: 11 | F144: =LN(B144) -> 1.3660917 | G144: 2
A145: 46069 | B145: 4.13 | C145: 76 | D145: =LN(B145) -> 1.4182774 | E145: 12 | F145: =LN(B145) -> 1.4182774 | G145: 2
... A157: 46250 | B157: 3.26 | C157: 88 | D157: =LN(B157) -> 1.1817272 | E157: 24 | F157: =LN(B157) -> 1.1817272 | G157: 4
A158: 46266 | B158: 3.42 | C158: 89 | D158: =LN(B158) -> 1.2296406 | E158: 25 | F158: =LN(B158) -> 1.2296406
A162: 6. ESTUDIO DE MERCADO DE CLASE (referencia; NO alimenta el DCF) — correlaciones y beta histórica
A163: Mes | B163: Cierre mensual Soriana B (MXN) | C163: Inflación mensual %
A164: 45597 | B164: 30.5 | C164: 4.55
A165: 45627 | B165: 29.63 | C165: 4.215
A166: 45658 | B166: 29.18 | C166: 3.585
A167: 45689 | B167: 27.65 | C167: 3.775
A168: 45717 | B168: 27.7 | C168: 3.8
A169: 45748 | B169: 25.98 | C169: 3.93
A170: 45778 | B170: 27.51 | C170: 4.42
A171: 45809 | B171: 27.98 | C171: 4.32
A172: 45839 | B172: 25.96 | C172: 3.515
A173: 45870 | B173: 25.73 | C173: 3.57
A174: 45901 | B174: 25 | C174: 3.76
A175: 45931 | B175: 26.45 | C175: 3.565
... A186: 46266 | B186: 35 | C186: 3.42
A188: Correlación precio–inflación | B188: Valor | C188: Ventana
A189: Toda la muestra (23 meses) | B189: =CORREL(B164:B186,C164:C186) -> 0.19017444 | C189: =CHOOSE(MONTH(A164),"ene","feb","mar","abr","may","jun","jul","ago","sep","oct","nov","dic")&"-"&RIGHT(YEAR(A164),2)&" a "&CHOOSE(MONTH(A186),"ene","feb","mar","abr","may","jun","jul","ago","sep","oct","nov","dic")&"-"&RIGHT(YEAR(A186),2) -> nov-24 a sep-26
A190: Anual (ene–sep 2026) | B190: =CORREL(B178:B186,C178:C186) -> 0.66003908 | C190: =CHOOSE(MONTH(A178),"ene","feb","mar","abr","may","jun","jul","ago","sep","oct","nov","dic")&"-"&RIGHT(YEAR(A178),2)&" a "&CHOOSE(MONTH(A186),"ene","feb","mar","abr","may","jun","jul","ago","sep","oct","nov","dic")&"-"&RIGHT(YEAR(A186),2) -> ene-26 a sep-26
A191: Semestral (abr–sep 2026) | B191: =CORREL(B181:B186,C181:C186) -> 0.60296681 | C191: =CHOOSE(MONTH(A181),"ene","feb","mar","abr","may","jun","jul","ago","sep","oct","nov","dic")&"-"&RIGHT(YEAR(A181),2)&" a "&CHOOSE(MONTH(A186),"ene","feb","mar","abr","may","jun","jul","ago","sep","oct","nov","dic")&"-"&RIGHT(YEAR(A186),2) -> abr-26 a sep-26
A192: Trimestral (jul–sep 2026) | B192: =CORREL(B184:B186,C184:C186) -> 0.69505996 | C192: =CHOOSE(MONTH(A184),"ene","feb","mar","abr","may","jun","jul","ago","sep","oct","nov","dic")&"-"&RIGHT(YEAR(A184),2)&" a "&CHOOSE(MONTH(A186),"ene","feb","mar","abr","may","jun","jul","ago","sep","oct","nov","dic")&"-"&RIGHT(YEAR(A186),2) -> jul-26 a sep-26
A193: El Dossier reporta 0.26 / 0.61 / 0.65 / 0.70; el libro de clase da los valores de esta tabla (diferencias documentadas en la auditoría).
A195: Fecha | B195: Rend. diario Soriana B | C195: Rend. diario IPC
A196: 46204 | B196: 0.003 | C196: 0.0042
A197: 46205 | B197: 0.0119 | C197: -0.0026
A198: 46206 | B198: -0.0257 | C198: -0.0002
A199: 46209 | B199: -0.0104 | C199: 0.0061
A200: 46210 | B200: 0.0233 | C200: -0.0117
A201: 46211 | B201: -0.0096 | C201: -0.001
A202: 46212 | B202: 0.0253 | C202: -0.0075
A203: 46213 | B203: -0.0052 | C203: 0.0059
A204: 46216 | B204: -0.0196 | C204: -0.0079
A205: 46218 | B205: 0.0013 | C205: -0.0017
A206: 46219 | B206: -0.0027 | C206: -0.0007
A207: 46220 | B207: 0.0103 | C207: 0.0042
... A257: 46301 | B257: -0.0201 | C257: 0.0052
...

Sheet Beta y Kd
A1: 1. FUENTE EXTERNA: Damodaran (REFERENCIA; no es la beta oficial desde el 19-oct-2026) | G1: 2. BETA DE REGRESIÓN (OFICIAL desde el 19-oct-2026)
A2: Dato | B2: Valor | G2: Dato | H2: Valor | I2: Fuente
A3: Fuente | B3: Aswath Damodaran, NYU Stern Betas by Sector | G3: Beta apalancada observada (βL): pendiente de la regresión semanal de rendimientos Soriana B vs. S&P/BMV IPC | H3: 0.21783791 | I3: Regresión semanal (Investing.com); error típico 0.1269, t 1.716, p 0.0874, IC 95% −0.032 a 0.468
A4: Fecha de los datos | B4: Enero de 2026 | G4: Deuda usada para desapalancar (mdp) | H4: =WACC!B21 -> 23618 | I4: Deuda total al cierre 2025 (WACC!B21)
A5: Industria | B5: Retail (Grocery and Food) | G5: Capitalización usada para desapalancar (mdp) | H5: 59580 | I5: 33.10 MXN (cierre 7-oct-2026) × 1,800 mm de acciones
A6: Número de empresas | B6: 215 | G6: D/E de la regresión | H6: =H4/H5 -> 0.39640819 | I6: Deuda ÷ capitalización
A7: Beta apalancada promedio de la industria (βL) | B7: 0.87 | G7: Tasa para desapalancar | H7: 0.3 | I7: ISR 30%
A8: D/E de la industria | B8: 0.4596 | G8: Beta desapalancada derivada βU = βL / [1 + (1 − t) × D/E] | H8: =H3/(1+(1-H7)*H6) -> 0.17052082 | I8: Supuesto OFICIAL del WACC (B16 → B19)
A9: Tasa efectiva de la industria | B9: 0.2081 | G9: Control: βL observada ÷ βU − 1 = (1 − t) × D/E | H9: =H3/H8-1-(1-H7)*H6 -> 0 | I9: Debe ser 0
A10: Tasa marginal usada por Damodaran para desapalancar | B10: 0.2537
A11: Beta desapalancada de la industria (βU) | B11: 0.65
A12: Efectivo / valor de la empresa | B12: 0.0581
A13: Beta desapalancada corregida por caja | B13: 0.69
A14: Control: βU recalculada = 0.87 / [1 + (1 − 0.2537) × 0.4596] | B14: =B7/(1+(1-B10)*B8) -> 0.64780368 | C14: =B14-B11 -> -0.002196324
A15: Beta apalancada observada en la regresión semanal (βL; no se usa directamente: se desapalanca) | B15: =H3 -> 0.21783791
A16: Beta desapalancada derivada de la regresión (βU, OFICIAL) | B16: =H8 -> 0.17052082
A17: Beta heredada del Excel anterior (solo para reproducir el baseline histórico) | B17: 0.8
A18: Selector de beta (2 = regresión desapalancada, OFICIAL · 1 = Damodaran 0.69, referencia · 0 = heredada 0.80, histórico) | B18: 2
A19: BETA DESAPALANCADA USADA EN EL WACC (βU) — regresión semanal desapalancada | B19: =CHOOSE(B18+1,B17,B13,B16) -> 0.17052082
A21: 3. REAPALANCAMIENTO CON LA ESTRUCTURA DE CAPITAL DE SORIANA
A22: Concepto | B22: A valor de mercado | C22: Iterado al valor DCF
A23: Beta desapalancada βU | B23: =B19 -> 0.17052082 | C23: =B19 -> 0.17052082
A24: D/E | B24: =WACC!B23 -> 0.39190893 | C24: ='Proyección Final Soriana'!D219 -> 0.32826459
A25: Tasa fiscal para reapalancar | B25: =WACC!B10 -> 0.3 | C25: ='Proyección Final Soriana'!B207 -> 0.3
A26: Beta reapalancada βL = βU × [1 + (1 − t) × D/E] | B26: =B23*(1+(1-B25)*B24) -> 0.21730086 | C26: =C23*(1+(1-C25)*C24) -> 0.20970398
A27: Tasa libre de riesgo | B27: =WACC!B5 -> 0.09517 | C27: ='Proyección Final Soriana'!B210 -> 0.09517
A28: Prima de riesgo de mercado | B28: =WACC!B8 -> 0.0423 | C28: ='Proyección Final Soriana'!B211 -> 0.0423
A29: Ke = Rf + βL × PRM | B29: =B27+B26*B28 -> 0.10436183 | C29: =C27+C26*C28 -> 0.10404048
A30: WACC del modelo | B30: =WACC!B33 -> 0.10063018 | C30: ='Proyección Final Soriana'!B126 -> 0.095627784
A31: Control: βL de esta hoja = βL del modelo | B31: =B26-WACC!B28 -> 0 | C31: =C26-'Proyección Final Soriana'!E219 -> 0
A32: Referencia (NO usada): Ke con la βL de la industria 0.87 sin reapalancar | B32: =WACC!B5+B7*WACC!B8 -> 0.131971
A34: 4. IMPACTO DEL CAMBIO DE BETA
A35: Concepto | B35: βU Damodaran 0.69 (referencia) | C35: βU regresión 0.1705 (oficial) | D35: Cambio | E35: Lectura
A36: βU | B36: =Validación!H8 -> 0.69 | C36: =Validación!F8 -> 0.17052082 | D36: =C36-B36 -> -0.51947918 | E36: Menor βU → menor βL y Ke → menor WACC → mayor EV y precio. El cambio no altera los flujos (FCF) ni el puente. La βU de regresión se reapalanca con la D/E de este libro; la βL observada (0.2178) no se usa directamente.
A37: βL iterada | B37: =Validación!H14 -> 0.9070862 | C37: =Validación!F14 -> 0.20970398 | D37: =C37-B37 -> -0.69738223
A38: Ke iterado | B38: =Validación!H13 -> 0.13353975 | C38: =Validación!F13 -> 0.10404048 | D38: =C38-B38 -> -0.029499268
A39: WACC iterado | B39: =Validación!H12 -> 0.11383703 | C39: =Validación!F12 -> 0.095627784 | D39: =C39-B39 -> -0.018209242
A40: WACC a valor de mercado | B40: =Validación!H15 -> 0.12074804 | C40: =Validación!F15 -> 0.10063018 | D40: =C40-B40 -> -0.020117858
A41: Ke a valor de mercado | B41: =Validación!H16 -> 0.13236405 | C41: =Validación!F16 -> 0.10436183 | D41: =C41-B41 -> -0.028002226
A42: EV ponderado al cierre 2025 (mdp) | B42: =Validación!H11 -> 67198.429 | C42: =Validación!F11 -> 79382.697 | D42: =C42-B42 -> 12184.268
A43: Equity a la fecha de valuación (mdp) | B43: =Validación!H10 -> 56910.402 | C43: =Validación!F10 -> 69012.141 | D43: =C43-B43 -> 12101.739
A44: Precio DCF (MXN) | B44: =Validación!H9 -> 31.61689 | C44: =Validación!F9 -> 38.340078 | D44: =C44-B44 -> 6.7231882
A45: Precio combinado (MXN) | B45: =Validación!H19 -> 32.554865 | C45: =Validación!F19 -> 35.91646 | D45: =C45-B45 -> 3.3615941
A47: 5. COSTO DE LA DEUDA (Kd) — se conserva 10% con su fuente
A48: Kd antes de impuestos usado en la iteración (Proyección Final!C61) | B48: ='Proyección Final Soriana'!C61 -> 0.1 | E48: Fuente (comentario original de la celda C61): Encuesta Citi — tasa Banxico 6.50% a fin de 2026 y 2027 (imagenradio.com.mx, 22-sep-2026) y gastos financieros 1S26 de la hoja Datos.
A49: Control: intereses 1S26 anualizados / deuda total 2T26 | B49: =(Datos!E10+Datos!F10)*2/Datos!F29 -> 0.098648482 | E49: (588 + 582) × 2 / 23,720.6 (deuda bancaria + arrendamientos al 2T26).
A50: Diferencia | B50: =B48-B49 -> 0.0013515179 | E50: El 10% es consistente con el costo observado del 1S26.
A51: Referencia (NO usada): tasa implícita FY2025 = gastos financieros / deuda (WACC!B31) | B51: =WACC!B31 -> 0.13015497 | E51: Incluye intereses de deuda ya amortizada en 2025; solo alimenta el WACC a valor de mercado (punto de partida).

Sheet Multiplos
A1: TRADING COMPS (múltiplos de empresas públicas comparables)
A3: 1. GRUPO COMPARABLE: datos CIQ y revisión de comparabilidad
A4: Empresa (CIQ) | B4: País | C4: Industria primaria (CIQ) | D4: Modelo de negocio | E4: TEV USD mm | F4: Ventas LTM USD mm | G4: Mg EBITDA | H4: Crec. ventas | I4: Deuda/ EBITDA | J4: Clasificación | K4: Incluir (1/0) | L4: Razón | M4: EV/Ventas LTM | N4: EV/EBITDA LTM | O4: EV/EBIT LTM | P4: P/U LTM | Q4: P/VL tangible | R4: EV/EBITDA NTM | S4: P/U NTM
A5: Grupo Comercial Chedraui, S.A.B. de C.V. (BMV:CHDRAUI B) | B5: Mexico | C5: Food Retail | D5: Autoservicio multiformato | E5: 7428.7 | F5: 16018.2 | G5: 0.064 | H5: -0.0335 | I5: 2.5 | J5: Incluir | K5: 1 | L5: Par más cercano: mismo formato y país; margen EBITDA (6.4%) y crecimiento (−3.4%) casi iguales a los de Soriana. | M5: 0.5 | N5: 5.7 | O5: 8.8 | P5: 13.1 | Q5: 2 | R5: 5.17 | S5: 11.18
A6: Grupo Mateus S.A. (BOVESPA:GMAT3) | B6: Brazil | C6: Consumer Staples Merchandise Retail | D6: Supermercados y mayoreo | E6: 2853.8 | F6: 8146.6 | G6: 0.059 | H6: 0.1871 | I6: 2.6 | J6: Incluir con reserva | K6: 1 | L6: Formato comparable; geografía (Brasil) y crecimiento (18.7%) distintos; P/U 4.7x atípico. | M6: 0.4 | N6: 5.3 | O6: 6.6 | P6: 4.7 | Q6: 0.8 | R6: 5.04 | S6: 6.32
A7: El Puerto de Liverpool, S.A.B. de C.V. (BMV:LIVEPOL C-1) | B7: Mexico | C7: Broadline Retail | D7: Departamentales + crédito + inmobiliario | E7: 9571.4 | F7: 12791.2 | G7: 0.142 | H7: 0.0304 | I7: 1.6 | J7: Excluir | K7: 0 | L7: Industria distinta (Broadline Retail); negocio financiero; margen EBITDA del doble (14.2%). | M7: 0.8 | N7: 4.9 | O7: 5.9 | P7: 8.2 | Q7: 0.8 | R7: 4.69 | S7: 6.29
A8: Wal-Mart de México, S.A.B. de C.V. (BMV:WALMEX *) | B8: Mexico | C8: Consumer Staples Merchandise Retail | D8: Autoservicio, descuento y club | E8: 52191.3 | F8: 56741.1 | G8: 0.096 | H8: 0.0287 | I8: 0.8 | J8: Incluir con reserva | K8: 1 | L8: Competidor directo; 12 veces el tamaño de Soriana y líder del mercado (prima de múltiplo). | M8: 0.9 | N8: 9.1 | O8: 12 | P8: 17.8 | Q8: 4.3 | R8: 8.52 | S8: 16.13
A9: La Comer, S.A.B. de C.V. (BMV:LACOMER UBC) | B9: Mexico | C9: Food Retail | D9: Autoservicio premium | E9: 2140.3 | F9: 2735.8 | G9: 0.1 | H9: 0.086 | I9: 0.5 | J9: Incluir con reserva | K9: 1 | L9: Competidor directo; más pequeña, formato premium, más rentable (10.0%) y sin deuda neta. | M9: 0.8 | N9: 7.4 | O9: 10.7 | P9: 14.6 | Q9: 1.4 | R9: 7.07 | S9: 13.9
A10: Sendas Distribuidora S.A. (BOVESPA:ASAI3) | B10: Brazil | C10: Consumer Staples Merchandise Retail | D10: Mayoreo cash & carry | E10: 6909.1 | F10: 15576.1 | G10: 0.078 | H10: 0.0169 | I10: 4 | J10: Incluir con reserva | K10: 1 | L10: Formato comparable a City Club; Brasil; apalancamiento alto (4.0x) distorsiona P/U. | M10: 0.4 | N10: 5.5 | O10: 7.6 | P10: 16.8 | Q10: 17.1 | R10: 4.77 | S10: 11.68
A11: Cencosud S.A. (SNSE:CENCOSUD) | B11: Chile | C11: Consumer Staples Merchandise Retail | D11: Supermercados + mejoramiento del hogar + departamentales + centros comerciales | E11: 11831.7 | F11: 17028 | G11: 0.056 | H11: -0.016 | I11: 5.1 | J11: Incluir con reserva | K11: 1 | L11: Diversificada (Chile); EBITDA LTM −29.5% infla EV/EBITDA y EV/EBIT. | M11: 0.7 | N11: 9.3 | O11: 14 | P11: 21 | Q11: 2.7 | R11: 6.88 | S11: 15.27
A12: InRetail Perú Corp. (BVL:INRETC1) | B12: Peru | C12: Consumer Staples Merchandise Retail | D12: Supermercados, farmacias, centros comerciales | E12: 6092.8 | F12: 6992.8 | G12: 0.11 | H12: 0.0785 | I12: 3.2 | J12: Incluir con reserva | K12: 1 | L12: Multiformato (Perú) con negocios no comparables (farmacia, inmobiliario). | M12: 0.9 | N12: 7 | O12: 10 | P12: 13.6 | Q12: 4.2 | R12: 6.49 | S12: 13.1
A13: Fomento Económico Mexicano, S.A.B. de C.V. (BMV:FEMSA UBD) | B13: Mexico | C13: Soft Drinks and Non-alcoholic Beverages | D13: Embotellador Coca-Cola + OXXO + salud + combustible | E13: 49954.9 | F13: 48576.5 | G13: 0.118 | H13: 0.0745 | I13: 2.1 | J13: Excluir | K13: 0 | L13: Industria distinta (Soft Drinks); P/U 25.9x. | M13: 1.1 | N13: 7.5 | O13: 11.1 | P13: 25.9 | Q13: 11.6 | R13: 6.58 | S13: 20.88
A14: Falabella S.A. (SNSE:FALABELLA) | B14: Chile | C14: Broadline Retail | D14: Departamentales, mejoramiento del hogar, banca | E14: 20976.5 | F14: 14289.2 | G14: 0.127 | H14: 0.0894 | I14: 3 | J14: Excluir | K14: 0 | L14: Industria distinta (Broadline Retail); negocio financiero. | M14: 1.5 | N14: 10.4 | O14: 12.8 | P14: 10.4 | Q14: 2 | R14: 9.77 | S14: 18.33
A15: Organización Soriana, S. A. B. de C. V. (BMV:SORIANA B) - empresa objetivo (no forma parte de la muestra) | E15: 4103.2 | F15: 9502.5 | G15: 0.064 | H15: -0.0293 | I15: 2 | M15: 0.4 | N15: 6.3 | O15: 9.9 | P15: 15.7 | Q15: 0.8 | R15: 6.53 | S15: 15.08
A17: 2. MÉTRICAS DE SORIANA
A18: Ventas LTM (mdp) | B18: =SUM(Datos!C6:F6) -> 174278
A19: EBIT LTM (mdp) | B19: =SUM(Datos!C9:F9) -> 7631
A20: D&A LTM (mdp) | B20: =SUM(Datos!C14:F14) -> 4179.871
A21: EBITDA LTM (mdp) = EBIT + D&A | B21: =B19+B20 -> 11810.871
A22: Utilidad neta LTM (mdp) | B22: =SUM(Datos!C13:F13) -> 3816
A23: Acciones en circulación (millones) | B23: =WACC!B17 -> 1800
A24: UPA LTM (MXN) | B24: =B22/B23 -> 2.12
A25: (+) Efectivo y equivalentes 2T26 | B25: =Datos!F17 -> 6875.384
A26: (−) Deuda bursátil y bancaria 2T26 | B26: =-(Datos!F25+Datos!F26) -> -11500
A27: (−) Pasivo por arrendamiento 2T26 | B27: =-(Datos!F27+Datos!F28) -> -12220.588
A28: (−) Interés minoritario | B28: 0
A29: (−) Capital preferente | B29: 0
A30: Ajuste neto EV → capital (mdp) | B30: =SUM(B25:B29) -> -16845.204
A32: MÚLTIPLOS: selección
A33: Múltiplo | B33: Tipo | C33: Métrica de Soriana | D33: Usar (1/0) | E33: Estado
A34: EV/EBITDA LTM | B34: EV | C34: =$B$21 -> 11810.871 | D34: 1 | E34: Usado
A35: EV/EBIT LTM | B35: EV | C35: =$B$19 -> 7631 | D35: 1 | E35: Usado
A36: P/U LTM | B36: P | C36: =$B$24 -> 2.12 | D36: 1 | E36: Usado
A37: EV/Ventas LTM | B37: EV | C37: =$B$18 -> 174278 | D37: 0 | E37: Excluido
A38: P/VL tangible | B38: P | C38: NA | D38: 0 | E38: NA
A39: EV/EBITDA NTM | B39: EV | C39: NA | D39: 0 | E39: NA
A40: P/U NTM | B40: P | C40: NA | D40: 0 | E40: NA
A43: ESTADÍSTICOS DE LA MUESTRA
A44: Empresa | B44: EV/Ventas | C44: EV/EBITDA | D44: EV/EBIT | E44: P/U
A45: =A5 -> Grupo Comercial Chedraui, S.A.B. de C.V. (BMV:CHDRAUI B) | B45: =IF(AND($K$5=1,ISNUMBER(M5)),M5,"") -> 0.5 | C45: =IF(AND($K$5=1,ISNUMBER(N5)),N5,"") -> 5.7 | D45: =IF(AND($K$5=1,ISNUMBER(O5)),O5,"") -> 8.8 | E45: =IF(AND($K$5=1,ISNUMBER(P5)),P5,"") -> 13.1
A46: =A6 -> Grupo Mateus S.A. (BOVESPA:GMAT3) | B46: =IF(AND($K$6=1,ISNUMBER(M6)),M6,"") -> 0.4 | C46: =IF(AND($K$6=1,ISNUMBER(N6)),N6,"") -> 5.3 | D46: =IF(AND($K$6=1,ISNUMBER(O6)),O6,"") -> 6.6 | E46: =IF(AND($K$6=1,ISNUMBER(P6)),P6,"") -> 4.7
A47: =A7 -> El Puerto de Liverpool, S.A.B. de C.V. (BMV:LIVEPOL C-1) | B47: =IF(AND($K$7=1,ISNUMBER(M7)),M7,"") | C47: =IF(AND($K$7=1,ISNUMBER(N7)),N7,"") | D47: =IF(AND($K$7=1,ISNUMBER(O7)),O7,"") | E47: =IF(AND($K$7=1,ISNUMBER(P7)),P7,"")
A48: =A8 -> Wal-Mart de México, S.A.B. de C.V. (BMV:WALMEX *) | B48: =IF(AND($K$8=1,ISNUMBER(M8)),M8,"") -> 0.9 | C48: =IF(AND($K$8=1,ISNUMBER(N8)),N8,"") -> 9.1 | D48: =IF(AND($K$8=1,ISNUMBER(O8)),O8,"") -> 12 | E48: =IF(AND($K$8=1,ISNUMBER(P8)),P8,"") -> 17.8
A49: =A9 -> La Comer, S.A.B. de C.V. (BMV:LACOMER UBC) | B49: =IF(AND($K$9=1,ISNUMBER(M9)),M9,"") -> 0.8 | C49: =IF(AND($K$9=1,ISNUMBER(N9)),N9,"") -> 7.4 | D49: =IF(AND($K$9=1,ISNUMBER(O9)),O9,"") -> 10.7 | E49: =IF(AND($K$9=1,ISNUMBER(P9)),P9,"") -> 14.6
A50: =A10 -> Sendas Distribuidora S.A. (BOVESPA:ASAI3) | B50: =IF(AND($K$10=1,ISNUMBER(M10)),M10,"") -> 0.4 | C50: =IF(AND($K$10=1,ISNUMBER(N10)),N10,"") -> 5.5 | D50: =IF(AND($K$10=1,ISNUMBER(O10)),O10,"") -> 7.6 | E50: =IF(AND($K$10=1,ISNUMBER(P10)),P10,"") -> 16.8
A51: =A11 -> Cencosud S.A. (SNSE:CENCOSUD) | B51: =IF(AND($K$11=1,ISNUMBER(M11)),M11,"") -> 0.7 | C51: =IF(AND($K$11=1,ISNUMBER(N11)),N11,"") -> 9.3 | D51: =IF(AND($K$11=1,ISNUMBER(O11)),O11,"") -> 14 | E51: =IF(AND($K$11=1,ISNUMBER(P11)),P11,"") -> 21
A52: =A12 -> InRetail Perú Corp. (BVL:INRETC1) | B52: =IF(AND($K$12=1,ISNUMBER(M12)),M12,"") -> 0.9 | C52: =IF(AND($K$12=1,ISNUMBER(N12)),N12,"") -> 7 | D52: =IF(AND($K$12=1,ISNUMBER(O12)),O12,"") -> 10 | E52: =IF(AND($K$12=1,ISNUMBER(P12)),P12,"") -> 13.6
A53: =A13 -> Fomento Económico Mexicano, S.A.B. de C.V. (BMV:FEMSA UBD) | B53: =IF(AND($K$13=1,ISNUMBER(M13)),M13,"") | C53: =IF(AND($K$13=1,ISNUMBER(N13)),N13,"") | D53: =IF(AND($K$13=1,ISNUMBER(O13)),O13,"") | E53: =IF(AND($K$13=1,ISNUMBER(P13)),P13,"")
A54: =A14 -> Falabella S.A. (SNSE:FALABELLA) | B54: =IF(AND($K$14=1,ISNUMBER(M14)),M14,"") | C54: =IF(AND($K$14=1,ISNUMBER(N14)),N14,"") | D54: =IF(AND($K$14=1,ISNUMBER(O14)),O14,"") | E54: =IF(AND($K$14=1,ISNUMBER(P14)),P14,"")
A56: PRECIOS IMPLICITOS POR ACCION
A57: Estadístico (múltiplo) | B57: EV/Ventas | C57: EV/EBITDA | D57: EV/EBIT | E57: P/U | G57: Precio: EV/Ventas | H57: Precio: EV/EBITDA | I57: Precio: EV/EBIT | J57: Precio: P/U
A58: Mínimo | B58: =MIN(B45:B54) -> 0.4 | C58: =MIN(C45:C54) -> 5.3 | D58: =MIN(D45:D54) -> 6.6 | E58: =MIN(E45:E54) -> 4.7 | G58: =IF(B58*$B$18+$B$30>0,(B58*$B$18+$B$30)/$B$23,"NM") -> 29.369998 | H58: =IF(C58*$B$21+$B$30>0,(C58*$B$21+$B$30)/$B$23,"NM") -> 25.418007 | I58: =IF(D58*$B$19+$B$30>0,(D58*$B$19+$B$30)/$B$23,"NM") -> 18.621887 | J58: =IF(E58*$B$24>0,E58*$B$24,"NM") -> 9.964
A59: Percentil 25 | B59: =PERCENTILE(B45:B54,0.25) -> 0.45 | C59: =PERCENTILE(C45:C54,0.25) -> 5.6 | D59: =PERCENTILE(D45:D54,0.25) -> 8.2 | E59: =PERCENTILE(E45:E54,0.25) -> 13.35 | G59: =IF(B59*$B$18+$B$30>0,(B59*$B$18+$B$30)/$B$23,"NM") -> 34.211053 | H59: =IF(C59*$B$21+$B$30>0,(C59*$B$21+$B$30)/$B$23,"NM") -> 27.386485 | I59: =IF(D59*$B$19+$B$30>0,(D59*$B$19+$B$30)/$B$23,"NM") -> 25.404998 | J59: =IF(E59*$B$24>0,E59*$B$24,"NM") -> 28.302
A60: Media | B60: =AVERAGE(B45:B54) -> 0.65714286 | C60: =AVERAGE(C45:C54) -> 7.0428571 | D60: =AVERAGE(D45:D54) -> 9.9571429 | E60: =AVERAGE(E45:E54) -> 14.514286 | G60: =IF(B60*$B$18+$B$30>0,(B60*$B$18+$B$30)/$B$23,"NM") -> 54.266855 | H60: =IF(C60*$B$21+$B$30>0,(C60*$B$21+$B$30)/$B$23,"NM") -> 36.85393 | I60: =IF(D60*$B$19+$B$30>0,(D60*$B$19+$B$30)/$B$23,"NM") -> 32.854307 | J60: =IF(E60*$B$24>0,E60*$B$24,"NM") -> 30.770286
A61: Mediana | B61: =MEDIAN(B45:B54) -> 0.7 | C61: =MEDIAN(C45:C54) -> 7 | D61: =MEDIAN(D45:D54) -> 10 | E61: =MEDIAN(E45:E54) -> 14.6 | G61: =IF(B61*$B$18+$B$30>0,(B61*$B$18+$B$30)/$B$23,"NM") -> 58.416331 | H61: =IF(C61*$B$21+$B$30>0,(C61*$B$21+$B$30)/$B$23,"NM") -> 36.572718 | I61: =IF(D61*$B$19+$B$30>0,(D61*$B$19+$B$30)/$B$23,"NM") -> 33.035998 | J61: =IF(E61*$B$24>0,E61*$B$24,"NM") -> 30.952
A62: Percentil 75 | B62: =PERCENTILE(B45:B54,0.75) -> 0.85 | C62: =PERCENTILE(C45:C54,0.75) -> 8.25 | D62: =PERCENTILE(D45:D54,0.75) -> 11.35 | E62: =PERCENTILE(E45:E54,0.75) -> 17.3 | G62: =IF(B62*$B$18+$B$30>0,(B62*$B$18+$B$30)/$B$23,"NM") -> 72.939498 | H62: =IF(C62*$B$21+$B$30>0,(C62*$B$21+$B$30)/$B$23,"NM") -> 44.774712 | I62: =IF(D62*$B$19+$B$30>0,(D62*$B$19+$B$30)/$B$23,"NM") -> 38.759248 | J62: =IF(E62*$B$24>0,E62*$B$24,"NM") -> 36.676
A63: Máximo | B63: =MAX(B45:B54) -> 0.9 | C63: =MAX(C45:C54) -> 9.3 | D63: =MAX(D45:D54) -> 14 | E63: =MAX(E45:E54) -> 21 | G63: =IF(B63*$B$18+$B$30>0,(B63*$B$18+$B$30)/$B$23,"NM") -> 77.780553 | H63: =IF(C63*$B$21+$B$30>0,(C63*$B$21+$B$30)/$B$23,"NM") -> 51.664387 | I63: =IF(D63*$B$19+$B$30>0,(D63*$B$19+$B$30)/$B$23,"NM") -> 49.993776 | J63: =IF(E63*$B$24>0,E63*$B$24,"NM") -> 44.52
A64: n | B64: =COUNT(B45:B54) -> 7 | C64: =COUNT(C45:C54) -> 7 | D64: =COUNT(D45:D54) -> 7 | E64: =COUNT(E45:E54) -> 7
A66: Detalle a la MEDIA | B66: EV/Ventas | C66: EV/EBITDA | D66: EV/EBIT | E66: P/U
A67: Métrica de Soriana (mdp o MXN/acción) | B67: =$B$18 -> 174278 | C67: =$B$21 -> 11810.871 | D67: =$B$19 -> 7631 | E67: =$B$24 -> 2.12
A68: EV implícito (mdp) | B68: =B60*$B$18 -> 114525.54 | C68: =C60*$B$21 -> 83182.277 | D68: =D60*$B$19 -> 75982.957 | E68: n.a. (múltiplo de precio)
A69: Equity Value implícito (mdp) | B69: =B68+$B$30 -> 97680.339 | C69: =C68+$B$30 -> 66337.073 | D69: =D68+$B$30 -> 59137.753 | E69: =E60*$B$24*$B$23 -> 55386.514
A70: Precio implícito (MXN/acción) | B70: =G60 -> 54.266855 | C70: =H60 -> 36.85393 | D70: =I60 -> 32.854307 | E70: =J60 -> 30.770286
A72: VALOR DE TRADING COMPS
A73: TRADING COMPS — precio por acción (MXN) | D73: =IF((IF(AND($D$37=1,ISNUMBER(G60)),1,0)+IF(AND($D$34=1,ISNUMBER(H60)),1,0)+IF(AND($D$35=1,ISNUMBER(I60)),1,0)+IF(AND($D$36=1,ISNUMBER(J60)),1,0))=0,"NA",(IF(AND($D$37=1,ISNUMBER(G60)),G60,0)+IF(AND($D$34=1,ISNUMBER(H60)),H60,0)+IF(AND($D$35=1,ISNUMBER(I60)),I60,0)+IF(AND($D$36=1,ISNUMBER(J60)),J60,0))/(IF(AND($D$37=1,ISNUMBER(G60)),1,0)+IF(AND($D$34=1,ISNUMBER(H60)),1,0)+IF(AND($D$35=1,ISNUMBER(I60)),1,0)+IF(AND($D$36=1,ISNUMBER(J60)),1,0))) -> 33.492841
A74: Rango P25 (promedio de precios a P25 de los múltiplos usados) | D74: =IF((IF(AND($D$37=1,ISNUMBER(G59)),1,0)+IF(AND($D$34=1,ISNUMBER(H59)),1,0)+IF(AND($D$35=1,ISNUMBER(I59)),1,0)+IF(AND($D$36=1,ISNUMBER(J59)),1,0))=0,"NA",(IF(AND($D$37=1,ISNUMBER(G59)),G59,0)+IF(AND($D$34=1,ISNUMBER(H59)),H59,0)+IF(AND($D$35=1,ISNUMBER(I59)),I59,0)+IF(AND($D$36=1,ISNUMBER(J59)),J59,0))/(IF(AND($D$37=1,ISNUMBER(G59)),1,0)+IF(AND($D$34=1,ISNUMBER(H59)),1,0)+IF(AND($D$35=1,ISNUMBER(I59)),1,0)+IF(AND($D$36=1,ISNUMBER(J59)),1,0))) -> 27.031161
A75: Rango P75 (promedio de precios a P75 de los múltiplos usados) | D75: =IF((IF(AND($D$37=1,ISNUMBER(G62)),1,0)+IF(AND($D$34=1,ISNUMBER(H62)),1,0)+IF(AND($D$35=1,ISNUMBER(I62)),1,0)+IF(AND($D$36=1,ISNUMBER(J62)),1,0))=0,"NA",(IF(AND($D$37=1,ISNUMBER(G62)),G62,0)+IF(AND($D$34=1,ISNUMBER(H62)),H62,0)+IF(AND($D$35=1,ISNUMBER(I62)),I62,0)+IF(AND($D$36=1,ISNUMBER(J62)),J62,0))/(IF(AND($D$37=1,ISNUMBER(G62)),1,0)+IF(AND($D$34=1,ISNUMBER(H62)),1,0)+IF(AND($D$35=1,ISNUMBER(I62)),1,0)+IF(AND($D$36=1,ISNUMBER(J62)),1,0))) -> 40.069987
A76: Precio de mercado de referencia (MXN) | D76: =Valuación!B42 -> 33.48
A77: Potencial vs. precio | D77: =D73/D76-1 -> 0.00038353807
A78: Número de múltiplos usados | D78: =SUM(D34:D37) -> 3

Sheet Transacciones
A1: VALUACION POR TRANSACCIONES
A3: PARÁMETROS DE SELECCIÓN
A4: Fecha de valuación | C4: ='Proyección Final Soriana'!B252 -> 46296
A5: Ventana (años) | C5: 3
A6: Inicio de la ventana | C6: =EDATE(C4,-12*C5) -> 45200
A7: Geografía de la empresa objetivo | C7: México
A8: Mínimo de múltiplos por operación | C8: 2
A10: 2. OPERACIONES (datos CIQ) Y EVALUACIÓN DE CRITERIOS
A11: Anunciada | B11: ID CIQ | C11: Objetivo | D11: Comprador | E11: Vendedor | F11: TEV objetivo (MXN mm) | G11: Tamaño (MXN mm) | H11: EV/Ventas | I11: EV/EBITDA | J11: País del objetivo | K11: ¿Ventana? | L11: ¿Geografía? | M11: ¿≥2 múltiplos? | N11: ¿Control? | O11: Incluir (1/0) | P11: Observaciones | Q11: Industria del objetivo
A12: 45215 | B12: IQTR1859160803 | C12: Almacenes Éxito S.A. | D12: Super Selectos El Salvador | E12: Casino, Guichard-Perrachon S.A., Companhia Brasileira De Distribuicao, GÉAnt International B.V., Segisor S.A.S., Helicco Participações Ltda., GPA 2 Empreendimentos E Participacoes LTDA. | F12: 56675.3 | G12: 35348.1 | H12: 0.3 | I12: 5.2 | J12: Colombia | K12: =IF(A12>=$C$6,"Sí","No") -> Sí | L12: =IF(J12=$C$7,"Sí","No") -> No | M12: =IF(COUNT(H12:I12)>=$C$8,"Sí","No") -> Sí | N12: Sí | O12: 1 | P12: Oferta por el control de Éxito; varios vendedores del grupo Casino. Única operación dentro de la ventana (por 15 días). | Q12: Supermercados / autoservicio (Grupo Éxito)
A13: 43657 | B13: IQTR629442326 | C13: InRetail Perú Corp. | D13: - | E13: Nexus Group | F13: 116983.8 | G13: 4590.5 | H13: 1.5 | I13: 11.4 | J13: Perú | K13: =IF(A13>=$C$6,"Sí","No") -> No | L13: =IF(J13=$C$7,"Sí","No") -> No | M13: =IF(COUNT(H13:I13)>=$C$8,"Sí","No") -> Sí | N13: Dudoso | O13: 1 | P13: Comprador no identificado; tamaño 4,590 = 3.9% del TEV → probable venta minoritaria o secundaria, no de control. Fuera de la ventana. | Q13: Supermercados, farmacias y centros comerciales
A14: 43642 | B14: IQTR626096522 | C14: Almacenes Éxito S.A. | D14: Sendas Distribuidora S.A. | E14: Casino, Guichard-Perrachon S.A. | F14: 56675.3 | G14: 130645 | H14: 0.4 | I14: 6.3 | J14: Colombia | K14: =IF(A14>=$C$6,"Sí","No") -> No | L14: =IF(J14=$C$7,"Sí","No") -> No | M14: =IF(COUNT(H14:I14)>=$C$8,"Sí","No") -> Sí | N14: Dudoso | O14: 1 | P14: Vendedor Casino y comprador Sendas, ambos del grupo Casino según los datos → posible reestructura intra-grupo. Tamaño 130,645 > TEV 56,675 (dato inconsistente). Fuera de la ventana. | Q14: Supermercados / autoservicio (Grupo Éxito)
H15: 0.7 | I15: 7.6
A16: Cumplen la ventana | C16: =COUNTIF(K12:K14,"Sí")&" de "&COUNTA(B12:B14) -> 1 de 3
A17: Cumplen la geografía | C17: =COUNTIF(L12:L14,"Sí")&" de "&COUNTA(B12:B14) -> 0 de 3
A18: Operaciones de control claras | C18: =COUNTIF(N12:N14,"Sí")&" de "&COUNTA(B12:B14) -> 1 de 3
A19: Margen EBITDA implícito del objetivo (EV/Ventas ÷ EV/EBITDA) | C19: =H12/I12 -> 0.057692308 | D19: =H13/I13 -> 0.13157895 | E19: =H14/I14 -> 0.063492063
A21: 3. ESTADÍSTICOS (operaciones con Incluir = 1) Y PRECIO IMPLÍCITO (mismo puente al 2T26 que Trading Comps)
A22: Muestra filtrada (helper)
A23: =C12 -> Almacenes Éxito S.A. | B23: =IF($O$12=1,H12,"") -> 0.3 | C23: =IF($O$12=1,I12,"") -> 5.2
A24: =C13 -> InRetail Perú Corp. | B24: =IF($O$13=1,H13,"") -> 1.5 | C24: =IF($O$13=1,I13,"") -> 11.4
A25: =C14 -> Almacenes Éxito S.A. | B25: =IF($O$14=1,H14,"") -> 0.4 | C25: =IF($O$14=1,I14,"") -> 6.3
A27: Estadístico | B27: EV/Ventas | C27: EV/EBITDA | D27: Precio EV/Ventas | E27: Precio EV/EBITDA
A28: Mínimo | B28: =MIN(B23:B25) -> 0.3 | C28: =MIN(C23:C25) -> 5.2 | D28: =IF(B28*Multiplos!$B$18+Multiplos!$B$30>0,(B28*Multiplos!$B$18+Multiplos!$B$30)/Multiplos!$B$23,"NM") -> 19.687887 | E28: =IF(C28*Multiplos!$B$21+Multiplos!$B$30>0,(C28*Multiplos!$B$21+Multiplos!$B$30)/Multiplos!$B$23,"NM") -> 24.761847
A29: Percentil 25 | B29: =PERCENTILE(B23:B25,0.25) -> 0.35 | C29: =PERCENTILE(C23:C25,0.25) -> 5.75 | D29: =IF(B29*Multiplos!$B$18+Multiplos!$B$30>0,(B29*Multiplos!$B$18+Multiplos!$B$30)/Multiplos!$B$23,"NM") -> 24.528942 | E29: =IF(C29*Multiplos!$B$21+Multiplos!$B$30>0,(C29*Multiplos!$B$21+Multiplos!$B$30)/Multiplos!$B$23,"NM") -> 28.370725
A30: Media | B30: =AVERAGE(B23:B25) -> 0.73333333 | C30: =AVERAGE(C23:C25) -> 7.6333333 | D30: =IF(B30*Multiplos!$B$18+Multiplos!$B$30>0,(B30*Multiplos!$B$18+Multiplos!$B$30)/Multiplos!$B$23,"NM") -> 61.643701 | E30: =IF(C30*Multiplos!$B$21+Multiplos!$B$30>0,(C30*Multiplos!$B$21+Multiplos!$B$30)/Multiplos!$B$23,"NM") -> 40.728395
A31: Mediana | B31: =MEDIAN(B23:B25) -> 0.4 | C31: =MEDIAN(C23:C25) -> 6.3 | D31: =IF(B31*Multiplos!$B$18+Multiplos!$B$30>0,(B31*Multiplos!$B$18+Multiplos!$B$30)/Multiplos!$B$23,"NM") -> 29.369998 | E31: =IF(C31*Multiplos!$B$21+Multiplos!$B$30>0,(C31*Multiplos!$B$21+Multiplos!$B$30)/Multiplos!$B$23,"NM") -> 31.979602
A32: Percentil 75 | B32: =PERCENTILE(B23:B25,0.75) -> 0.95 | C32: =PERCENTILE(C23:C25,0.75) -> 8.85 | D32: =IF(B32*Multiplos!$B$18+Multiplos!$B$30>0,(B32*Multiplos!$B$18+Multiplos!$B$30)/Multiplos!$B$23,"NM") -> 82.621609 | E32: =IF(C32*Multiplos!$B$21+Multiplos!$B$30>0,(C32*Multiplos!$B$21+Multiplos!$B$30)/Multiplos!$B$23,"NM") -> 48.711669
A33: Máximo | B33: =MAX(B23:B25) -> 1.5 | C33: =MAX(C23:C25) -> 11.4 | D33: =IF(B33*Multiplos!$B$18+Multiplos!$B$30>0,(B33*Multiplos!$B$18+Multiplos!$B$30)/Multiplos!$B$23,"NM") -> 135.87322 | E33: =IF(C33*Multiplos!$B$21+Multiplos!$B$30>0,(C33*Multiplos!$B$21+Multiplos!$B$30)/Multiplos!$B$23,"NM") -> 65.443736
A34: n | B34: =COUNT(B23:B25) -> 3 | C34: =COUNT(C23:C25) -> 3
A36: Detalle a la MEDIA | B36: EV/Ventas | C36: EV/EBITDA
A37: Múltiplo (media de la muestra) | B37: =B30 -> 0.73333333 | C37: =C30 -> 7.6333333
A38: Métrica de Soriana (mdp, LTM) | B38: =Multiplos!$B$18 -> 174278 | C38: =Multiplos!$B$21 -> 11810.871
A39: EV implícito (mdp) | B39: =B37*B38 -> 127803.87 | C39: =C37*C38 -> 90156.315
A40: (+/−) Ajuste neto EV → capital (mdp) | B40: =Multiplos!$B$30 -> -16845.204 | C40: =Multiplos!$B$30 -> -16845.204
A41: Equity Value implícito (mdp) | B41: =B39+B40 -> 110958.66 | C41: =C39+C40 -> 73311.111
A42: Precio implícito (MXN/acción) | B42: =D30 -> 61.643701 | C42: =E30 -> 40.728395
A44: 4. VALOR DE PRECEDENT TRANSACTIONS
A45: Múltiplo | C45: Usar (1/0) | D45: Estado | E45: Justificación
A46: EV/EBITDA | C46: 1 | D46: Usado | E46: Mismo criterio que Trading Comps.
A47: EV/Ventas | C47: 0 | D47: Excluido | E47: Mismo criterio que Trading Comps: ignora el margen; los márgenes implícitos de los objetivos van de 5.8% a 13.2% (fila de margen implícito).
A49: PRECEDENT TRANSACTIONS — precio por acción (MXN) | E49: =IF((C46+C47)=0,"NA",(IF(C46=1,E30,0)+IF(C47=1,D30,0))/(C46+C47)) -> 40.728395
A50: Rango (mín–máx del EV/EBITDA) | E50: =E28 -> 24.761847 | F50: =E33 -> 65.443736
A52: Solo 1 de 3 operaciones cumple la ventana de 3 años, ninguna la geografía, y 2 tienen carácter de control dudoso. Con n = 3 (o n = 1 dentro de la ventana) el resultado no es estadísticamente defendible. El método se calcula y se muestra como referencia, con peso 0% en la valuación combinada (decisión del proyecto)

Sheet Valuación Combinada
A1: VALUACIÓN COMBINADA. DCF , Trading Comps y Precedent Transactions.
A3: Método | B3: Precio por acción (MXN) | C3: Peso aplicado | D3: Peso regla de clase | E3: Contribución | F3: Origen del precio y del peso | G3: ¿Contribuye?
A4: DCF (ValuFlow, precio objetivo a la fecha de valuación) | B4: ='Proyección Final Soriana'!B265 -> 38.340078 | C4: 0.5 | D4: =1/3 -> 0.33333333 | E4: =IF(ISNUMBER(B4),B4*C4,0) -> 19.170039 | F4: Proyección Final Soriana!B265. Metodología principal existente. Peso: con Transactions en 0%, se conserva la regla de clase de pesos iguales entre los métodos activos (50/50). | G4: =IF(C4>0,"Sí","No (referencia)") -> Sí
A5: Trading Comps | B5: =Multiplos!D73 -> 33.492841 | C5: 0.5 | D5: =1/3 -> 0.33333333 | E5: =IF(ISNUMBER(B5),B5*C5,0) -> 16.74642 | F5: Trading Comps (sección 5). Metodología complementaria. Peso igual al DCF por la regla de pesos iguales de la diap. 18. | G5: =IF(C5>0,"Sí","No (referencia)") -> Sí
A6: Precedent Transactions (LSEG/SDC, mediana EV/EBITDA) | B6: ='Transacciones SDC'!F75 -> 23.7448 | C6: 0 | D6: =1/3 -> 0.33333333 | E6: =IF(ISNUMBER(B6),B6*C6,0) -> 0 | F6: Transacciones SDC (auditada): mediana de EV/EBITDA de las operaciones elegibles. Peso 0%: muestra global, sin operaciones mexicanas, control mixto y dispersión amplia. Se calcula y se muestra como referencia. La muestra CIQ (3 operaciones) queda como histórico. | G6: =IF(C6>0,"Sí","No (referencia)") -> No (referencia)
A7: Suma de pesos | C7: =SUM(C4:C6) -> 1 | D7: =SUM(D4:D6) -> 1
A9: PRECIO COMBINADO (MXN por acción) | B9: =IF(ABS(C7-1)>0.000000001,"Los pesos deben sumar 100%",IF(SUMPRODUCT((C4:C6>0)*(1-ISNUMBER(B4:B6)))>0,"NA: método con peso sin precio",SUMPRODUCT(B4:B6,C4:C6))) -> 35.91646
A10: Precio de mercado (MXN, 25-sep-2026) | B10: =Valuación!B42 -> 33.48
A11: Diferencia vs. precio (MXN) | B11: =B9-B10 -> 2.4364596
A12: Potencial / (baja) | B12: =B9/B10-1 -> 0.072773584
A14: Memo: resultado con la regla de clase (⅓ cada método) | B14: =SUMPRODUCT(B4:B6,D4:D6)/D7 -> 31.85924 | F14: Solo como referencia de la regla de pesos iguales (⅓): incluye Precedent Transactions SDC (mediana), que no forma parte del precio oficial.
A16: RANGO POR MÉTODO (MXN por acción)
A17: Método | B17: Bajo | C17: Central | D17: Alto
A18: DCF | B18: =MIN(Validación!E9:G9) -> 37.934854 | C18: =B4 -> 38.340078 | D18: =MAX(Validación!E9:G9) -> 39.143424
A19: Trading Comps | B19: =Multiplos!D74 -> 27.031161 | C19: =B5 -> 33.492841 | D19: =Multiplos!D75 -> 40.069987
A20: Precedent Transactions (referencia SDC · P25–P75) | B20: ='Transacciones SDC'!F51 -> 20.414791 | C20: =B6 -> 23.7448 | D20: ='Transacciones SDC'!F54 -> 49.187385
A21: Memo · Precedent Transactions CIQ (histórico, no defendible; 3 operaciones, media) | B21: =Transacciones!E28 -> 24.761847 | C21: =Transacciones!E49 -> 40.728395 | D21: =Transacciones!E33 -> 65.443736

Sheet Transacciones SDC
A1: VALUACIÓN POR TRANSACCIONES PRECEDENTES — muestra LSEG/SDC (pantalla del 19-oct-2026) · versión auditada
A2: Fuente: LSEG/SDC (Refinitiv), "GridExport_October_19_2026_9_29_57.pdf", Current Screen Template del 19-oct-2026 09:29:57, 166 operaciones, 23 columnas. Montos en USD mm tal como la pantalla; múltiplos en veces (x); precios en MXN por acción.
A3: Colores: amarillo = dato copiado de la pantalla (nombre de columna de origen en el encabezado) · naranja = juicio del analista · blanco = fórmula · azul = resultado. "NA" = dato no disponible en la fuente (nunca se trata como cero).
A5: 1. PARÁMETROS Y PROCEDIMIENTO DE SELECCIÓN (metodología S&P, art. 000045604, p. 9)
A6: Fecha de valuación (fin de la ventana) | C6: ='Proyección Final Soriana'!B252 -> 46296
A7: Ventana (años) | C7: =Transacciones!C5 -> 3
A8: Inicio de la ventana | C8: =Transacciones!C6 -> 45200
A9: Mínimo de múltiplos de valor por operación | C9: =Transacciones!C8 -> 2
A10: Tipo de cambio de referencia (MXN por USD) | C10: 18.48
A11: Fecha y fuente del tipo de cambio | C11: Implícito en S&P Capital IQ: capitalización 59,580 mdp / 3,223.7 USD mm al cierre del 7-oct-2026 (reporte comparativo, p. 1 y 25). Equivalente MXN solo informativo: los múltiplos no requieren conversión.
A13: Paso | C13: Criterio | H13: Resultado con la base SDC
A14: Búsqueda inicial | C14: M&A de los últimos 3 años, autoservicio en México | H14: 0 operaciones con múltiplos: solo FEMSA como comprador (Delek, objetivo en EE.UU.) y Nutrisa, sin múltiplos.
A15: Primera ampliación | C15: Subir un nivel en la industria (Retail: Food & Beverage + Discount and Department Store) | H15: Sigue sin operaciones mexicanas con múltiplos.
A16: Segunda ampliación | C16: Eliminar el filtro geográfico → pantalla global | H16: 166 operaciones en la pantalla (Retail: Food & Beverage Retailing 130, Discount and Department Store Retailing 34, Food & Beverage 2). La subindustria de SDC mezcla restaurantes, servicios de alimentos y departamentales.
A17: Filtro del analista | C17: Objetivo que opera autoservicio, supermercados o mayoreo de alimentos | H17: 23 operaciones evaluadas abajo (19 de la versión original + 4 agregadas en la auditoría).
A18: Criterios objetivos | C18: Ventana de 3 años, ≥ 2 múltiplos, no recompra propia | H18: Columnas X–Z (fórmulas).
A19: Juicio del analista | C19: Adquisición real con control o participación estratégica relevante; calidad del dato; sin sanciones ni reestructura judicial | H19: Columna AA (naranja) y motivo.
A21: 2. OPERACIONES EVALUADAS: DATOS DE LA PANTALLA LSEG/SDC Y CRITERIOS
A22: M&A SDC Deal Number | B22: Date Announced | C22: Target Full Name | D22: Target Nation | E22: Target Mid Industry | F22: Target Public Status | G22: Acquiror Full Name | H22: Acquiror Nation | I22: Deal Status | J22: Rank Value inc. Net Debt of Target (USD mm) — valor de la operación | K22: Enterprise Value at Announcement (USD mm) | L22: Valor de la operación (MXN mm, informativo) | M22: EV al anuncio (MXN mm, informativo) | N22: Ratio of EV to EBITDA (x) | O22: Ratio of Offer Price to EPS (x) | P22: Ratio of EV to Sales (x) | Q22: Premium Paid 1 Day Prior (%) | R22: Premium Paid 4 Weeks Prior (%) | S22: Target Net Sales LTM (USD mm) | T22: # múltiplos disponibles | U22: ¿Ventana? | V22: ¿≥ 2 múltiplos? | W22: Autoservicio / alimentos (juicio) | X22: ¿Recompra propia? | Y22: ¿Dentro de la ventana y ≥ 2 múlt.? | Z22: Naturaleza de la operación (juicio) | AA22: Juicio del analista | AB22: Incluir (1/0) | AC22: Motivo / observaciones | AD22: Cambio en la auditoría | AE22: EV/EBITDA elegible | AF22: EV/Ventas elegible | AG22: P/E elegible | AH22: EV/EBITDA sin atípicos | AI22: EV/Ventas sin atípicos | AJ22: P/E sin atípicos | AK22: Sens.: Muestra auditada (oficial) | AL22: Sens.: Sin Sun Art (empresa en dificultad) | AM22: Sens.: Sin participaciones no de control (Lawson 50%, Yonghui ~29%) | AN22: Sens.: Sin Chengdu Hongqi (control no verificable en la pantalla)
A23: 4144889040 | B23: 45215 | C23: Almacenes Exito SA | D23: Colombia | E23: Discount and Department Store Retailing | F23: Public | G23: Cama Commercial Group Corp | H23: Panama | I23: Completed | J23: 1019.99 | K23: 1744.4697 | L23: =IF(ISNUMBER(J23),J23*$C$10,"NA") -> 18849.415 | M23: =IF(ISNUMBER(K23),K23*$C$10,"NA") -> 32237.799 | N23: 4.98 | O23: NA | P23: 0.34 | Q23: 41.93 | R23: 39.35 | S23: 5375.07 | T23: =COUNT(N23:P23) -> 2 | U23: =IF(AND(B23>=$C$8,B23<=$C$6),"Sí","No") -> Sí | V23: =IF(T23>=$C$9,"Sí","No") -> Sí | W23: Sí | X23: =IF(UPPER(TRIM(C23))=UPPER(TRIM(G23)),"Sí","No") -> No | Y23: =IF(AND(U23="Sí",V23="Sí"),"Sí","No") -> Sí | Z23: Control (OPA) | AA23: Elegible | AB23: =IF(AND(U23="Sí",V23="Sí",W23="Sí",X23="No",AA23="Elegible"),1,0) -> 1 | AC23: OPA por el control de Éxito (hiper y supermercados); vendedor grupo Casino. Comprador: Cama Commercial Group (vehículo de Grupo Calleja / Super Selectos). SDC clasifica al objetivo como "Discount and Department Store Retailing". Misma operación que la muestra CIQ. | AE23: =IF(AND(AB23=1,ISNUMBER(N23)),N23,"") -> 4.98 | AF23: =IF(AND(AB23=1,ISNUMBER(P23)),P23,"") -> 0.34 | AG23: =IF(AND(AB23=1,ISNUMBER(O23)),O23,"") | AH23: =IF(ISNUMBER(AE23),IF(AND(AE23<=C$58,AE23>=C$57),AE23,""),"") -> 4.98 | AI23: =IF(ISNUMBER(AF23),IF(AND(AF23<=D$58,AF23>=D$57),AF23,""),"") -> 0.34 | AJ23: =IF(ISNUMBER(AG23),IF(AND(AG23<=E$58,AG23>=E$57),AG23,""),"") | AK23: =AE23 -> 4.98 | AL23: =AE23 -> 4.98 | AM23: =AE23 -> 4.98 | AN23: =AE23 -> 4.98
A24: 4150545040 | B24: 45229 | C24: Profi Rom Food Srl | D24: Romania | E24: Food & Beverage Retailing | F24: Subsidiary | G24: Koninklijke Ahold Delhaize NV | H24: Netherlands | I24: Completed | J24: 1703.42 | K24: 1711.6877 | L24: =IF(ISNUMBER(J24),J24*$C$10,"NA") -> 31479.202 | M24: =IF(ISNUMBER(K24),K24*$C$10,"NA") -> 31631.989 | N24: 21.31 | O24: NA | P24: 0.69 | Q24: NA | R24: NA | S24: 2526.08 | T24: =COUNT(N24:P24) -> 2 | U24: =IF(AND(B24>=$C$8,B24<=$C$6),"Sí","No") -> Sí | V24: =IF(T24>=$C$9,"Sí","No") -> Sí | W24: Sí | X24: =IF(UPPER(TRIM(C24))=UPPER(TRIM(G24)),"Sí","No") -> No | Y24: =IF(AND(U24="Sí",V24="Sí"),"Sí","No") -> Sí | Z24: Control (100%) | AA24: Elegible | AB24: =IF(AND(U24="Sí",V24="Sí",W24="Sí",X24="No",AA24="Elegible"),1,0) -> 1 | AC24: Compra del 100% de la cadena de supermercados Profi (Rumania). Múltiplo alto por crecimiento y sinergias: atípico estadístico (ver sección 3). | AE24: =IF(AND(AB24=1,ISNUMBER(N24)),N24,"") -> 21.31 | AF24: =IF(AND(AB24=1,ISNUMBER(P24)),P24,"") -> 0.69 | AG24: =IF(AND(AB24=1,ISNUMBER(O24)),O24,"") | AH24: =IF(ISNUMBER(AE24),IF(AND(AE24<=C$58,AE24>=C$57),AE24,""),"") | AI24: =IF(ISNUMBER(AF24),IF(AND(AF24<=D$58,AF24>=D$57),AF24,""),"") -> 0.69 | AJ24: =IF(ISNUMBER(AG24),IF(AND(AG24<=E$58,AG24>=E$57),AG24,""),"") | AK24: =AE24 -> 21.31 | AL24: =AE24 -> 21.31 | AM24: =AE24 -> 21.31 | AN24: =AE24 -> 21.31
A25: 4191742040 | B25: 45328 | C25: Lawson Inc | D25: Japan | E25: Food & Beverage Retailing | F25: Public | G25: KDDI CORP | H25: Japan | I25: Completed | J25: 3339.55 | K25: 11027.053 | L25: =IF(ISNUMBER(J25),J25*$C$10,"NA") -> 61714.884 | M25: =IF(ISNUMBER(K25),K25*$C$10,"NA") -> 203779.94 | N25: 3.24 | O25: 13.72 | P25: 0.9 | Q25: NA | R25: NA | S25: 12244.6 | T25: =COUNT(N25:P25) -> 3 | U25: =IF(AND(B25>=$C$8,B25<=$C$6),"Sí","No") -> Sí | V25: =IF(T25>=$C$9,"Sí","No") -> Sí | W25: Sí | X25: =IF(UPPER(TRIM(C25))=UPPER(TRIM(G25)),"Sí","No") -> No | Y25: =IF(AND(U25="Sí",V25="Sí"),"Sí","No") -> Sí | Z25: Estratégica (control conjunto 50%) | AA25: Elegible | AB25: =IF(AND(U25="Sí",V25="Sí",W25="Sí",X25="No",AA25="Elegible"),1,0) -> 1 | AC25: OPA de KDDI; control conjunto 50/50 con Mitsubishi. Tiendas de conveniencia (formato de proximidad): comparabilidad con reserva. | AE25: =IF(AND(AB25=1,ISNUMBER(N25)),N25,"") -> 3.24 | AF25: =IF(AND(AB25=1,ISNUMBER(P25)),P25,"") -> 0.9 | AG25: =IF(AND(AB25=1,ISNUMBER(O25)),O25,"") -> 13.72 | AH25: =IF(ISNUMBER(AE25),IF(AND(AE25<=C$58,AE25>=C$57),AE25,""),"") -> 3.24 | AI25: =IF(ISNUMBER(AF25),IF(AND(AF25<=D$58,AF25>=D$57),AF25,""),"") -> 0.9 | AJ25: =IF(ISNUMBER(AG25),IF(AND(AG25<=E$58,AG25>=E$57),AG25,""),"") -> 13.72 | AK25: =AE25 -> 3.24 | AL25: =AE25 -> 3.24 | AM25: ="" | AN25: =AE25 -> 3.24
A26: 4234985040 | B26: 45427 | C26: KANSAI FOOD MARKET LTD | D26: Japan | E26: Food & Beverage Retailing | F26: Public | G26: H2O RETAILING CORP | H26: Japan | I26: Completed | J26: 234.33 | K26: 700.28122 | L26: =IF(ISNUMBER(J26),J26*$C$10,"NA") -> 4330.4184 | M26: =IF(ISNUMBER(K26),K26*$C$10,"NA") -> 12941.197 | N26: 7.64 | O26: 18.52 | P26: 0.28 | Q26: -3.23 | R26: -6.59 | S26: 2544.58 | T26: =COUNT(N26:P26) -> 3 | U26: =IF(AND(B26>=$C$8,B26<=$C$6),"Sí","No") -> Sí | V26: =IF(T26>=$C$9,"Sí","No") -> Sí | W26: Sí | X26: =IF(UPPER(TRIM(C26))=UPPER(TRIM(G26)),"Sí","No") -> No | Y26: =IF(AND(U26="Sí",V26="Sí"),"Sí","No") -> Sí | Z26: Control (OPA) | AA26: Elegible | AB26: =IF(AND(U26="Sí",V26="Sí",W26="Sí",X26="No",AA26="Elegible"),1,0) -> 1 | AC26: OPA de H2O Retailing para consolidar el control del supermercado. | AE26: =IF(AND(AB26=1,ISNUMBER(N26)),N26,"") -> 7.64 | AF26: =IF(AND(AB26=1,ISNUMBER(P26)),P26,"") -> 0.28 | AG26: =IF(AND(AB26=1,ISNUMBER(O26)),O26,"") -> 18.52 | AH26: =IF(ISNUMBER(AE26),IF(AND(AE26<=C$58,AE26>=C$57),AE26,""),"") -> 7.64 | AI26: =IF(ISNUMBER(AF26),IF(AND(AF26<=D$58,AF26>=D$57),AF26,""),"") -> 0.28 | AJ26: =IF(ISNUMBER(AG26),IF(AND(AG26<=E$58,AG26>=E$57),AG26,""),"") -> 18.52 | AK26: =AE26 -> 7.64 | AL26: =AE26 -> 7.64 | AM26: =AE26 -> 7.64 | AN26: =AE26 -> 7.64
A27: 4291087040 | B27: 45558 | C27: Yonghui Superstores Co Ltd | D27: China (Mainland) | E27: Food & Beverage Retailing | F27: Public | G27: Guangdong Juncai International Trading Co Ltd | H27: China (Mainland) | I27: Completed | J27: 889.32 | K27: 5614.0797 | L27: =IF(ISNUMBER(J27),J27*$C$10,"NA") -> 16434.634 | M27: =IF(ISNUMBER(K27),K27*$C$10,"NA") -> 103748.19 | N27: 12.77 | O27: NA | P27: 0.53 | Q27: 3.07 | R27: 5.86 | S27: 10235.95 | T27: =COUNT(N27:P27) -> 2 | U27: =IF(AND(B27>=$C$8,B27<=$C$6),"Sí","No") -> Sí | V27: =IF(T27>=$C$9,"Sí","No") -> Sí | W27: Sí | X27: =IF(UPPER(TRIM(C27))=UPPER(TRIM(G27)),"Sí","No") -> No | Y27: =IF(AND(U27="Sí",V27="Sí"),"Sí","No") -> Sí | Z27: Estratégica (~29%) | AA27: Elegible | AB27: =IF(AND(U27="Sí",V27="Sí",W27="Sí",X27="No",AA27="Elegible"),1,0) -> 1 | AC27: Compra de ~29% por Guangdong Juncai (filial de Miniso); queda como mayor accionista. Participación estratégica relevante, no control pleno. | AE27: =IF(AND(AB27=1,ISNUMBER(N27)),N27,"") -> 12.77 | AF27: =IF(AND(AB27=1,ISNUMBER(P27)),P27,"") -> 0.53 | AG27: =IF(AND(AB27=1,ISNUMBER(O27)),O27,"") | AH27: =IF(ISNUMBER(AE27),IF(AND(AE27<=C$58,AE27>=C$57),AE27,""),"") -> 12.77 | AI27: =IF(ISNUMBER(AF27),IF(AND(AF27<=D$58,AF27>=D$57),AF27,""),"") -> 0.53 | AJ27: =IF(ISNUMBER(AG27),IF(AND(AG27<=E$58,AG27>=E$57),AG27,""),"") | AK27: =AE27 -> 12.77 | AL27: =AE27 -> 12.77 | AM27: ="" | AN27: =AE27 -> 12.77
A28: 4338758040 | B28: 45658 | C28: Sun Art Retail Group Ltd | D28: Hong Kong | E28: Food & Beverage Retailing | F28: Public | G28: Paragon Shine Ltd | H28: Hong Kong | I28: Completed | J28: 1333.8 | K28: 824.10101 | L28: =IF(ISNUMBER(J28),J28*$C$10,"NA") -> 24648.624 | M28: =IF(ISNUMBER(K28),K28*$C$10,"NA") -> 15229.387 | N28: 2.2 | O28: NA | P28: 0.08 | Q28: -44.35 | R28: -43.9 | S28: 10128.92 | T28: =COUNT(N28:P28) -> 2 | U28: =IF(AND(B28>=$C$8,B28<=$C$6),"Sí","No") -> Sí | V28: =IF(T28>=$C$9,"Sí","No") -> Sí | W28: Sí | X28: =IF(UPPER(TRIM(C28))=UPPER(TRIM(G28)),"Sí","No") -> No | Y28: =IF(AND(U28="Sí",V28="Sí"),"Sí","No") -> Sí | Z28: Control (empresa en dificultad) | AA28: Elegible | AB28: =IF(AND(U28="Sí",V28="Sí",W28="Sí",X28="No",AA28="Elegible"),1,0) -> 1 | AC28: Compra de control a Alibaba con descuento (prima 1 día −44.4%): operación en dificultad; se conserva y se cuantifica su efecto en la sección 4. | AE28: =IF(AND(AB28=1,ISNUMBER(N28)),N28,"") -> 2.2 | AF28: =IF(AND(AB28=1,ISNUMBER(P28)),P28,"") -> 0.08 | AG28: =IF(AND(AB28=1,ISNUMBER(O28)),O28,"") | AH28: =IF(ISNUMBER(AE28),IF(AND(AE28<=C$58,AE28>=C$57),AE28,""),"") -> 2.2 | AI28: =IF(ISNUMBER(AF28),IF(AND(AF28<=D$58,AF28>=D$57),AF28,""),"") -> 0.08 | AJ28: =IF(ISNUMBER(AG28),IF(AND(AG28<=E$58,AG28>=E$57),AG28,""),"") | AK28: =AE28 -> 2.2 | AL28: ="" | AM28: =AE28 -> 2.2 | AN28: =AE28 -> 2.2
A29: 4353024040 | B29: 45693 | C29: METRO AG | D29: Germany | E29: Food & Beverage Retailing | F29: Public | G29: EP Global Commerce GmbH | H29: Germany | I29: Completed | J29: 294.05 | K29: 5048.5763 | L29: =IF(ISNUMBER(J29),J29*$C$10,"NA") -> 5434.044 | M29: =IF(ISNUMBER(K29),K29*$C$10,"NA") -> 93297.691 | N29: 5.11 | O29: NA | P29: 0.16 | Q29: 38.8 | R29: 26.45 | S29: 32597.58 | T29: =COUNT(N29:P29) -> 2 | U29: =IF(AND(B29>=$C$8,B29<=$C$6),"Sí","No") -> Sí | V29: =IF(T29>=$C$9,"Sí","No") -> Sí | W29: Sí | X29: =IF(UPPER(TRIM(C29))=UPPER(TRIM(G29)),"Sí","No") -> No | Y29: =IF(AND(U29="Sí",V29="Sí"),"Sí","No") -> Sí | Z29: Control (oferta y exclusión de bolsa) | AA29: Elegible | AB29: =IF(AND(U29="Sí",V29="Sí",W29="Sí",X29="No",AA29="Elegible"),1,0) -> 1 | AC29: Oferta de EP Global Commerce (prima 1 día +38.8%). Mayoreo de alimentos (cash & carry), comparable con City Club. | AE29: =IF(AND(AB29=1,ISNUMBER(N29)),N29,"") -> 5.11 | AF29: =IF(AND(AB29=1,ISNUMBER(P29)),P29,"") -> 0.16 | AG29: =IF(AND(AB29=1,ISNUMBER(O29)),O29,"") | AH29: =IF(ISNUMBER(AE29),IF(AND(AE29<=C$58,AE29>=C$57),AE29,""),"") -> 5.11 | AI29: =IF(ISNUMBER(AF29),IF(AND(AF29<=D$58,AF29>=D$57),AF29,""),"") -> 0.16 | AJ29: =IF(ISNUMBER(AG29),IF(AND(AG29<=E$58,AG29>=E$57),AG29,""),"") | AK29: =AE29 -> 5.11 | AL29: =AE29 -> 5.11 | AM29: =AE29 -> 5.11 | AN29: =AE29 -> 5.11
A30: 4340542040 | B30: 45721 | C30: Seiyu Co Ltd | D30: Japan | E30: Food & Beverage Retailing | F30: Subsidiary | G30: Trial Holdings Inc | H30: Japan | I30: Completed | J30: 2536.72 | K30: 2552.3912 | L30: =IF(ISNUMBER(J30),J30*$C$10,"NA") -> 46878.586 | M30: =IF(ISNUMBER(K30),K30*$C$10,"NA") -> 47168.189 | N30: NA | O30: 3.88 | P30: 0.69 | Q30: NA | R30: NA | S30: 3508.95 | T30: =COUNT(N30:P30) -> 2 | U30: =IF(AND(B30>=$C$8,B30<=$C$6),"Sí","No") -> Sí | V30: =IF(T30>=$C$9,"Sí","No") -> Sí | W30: Sí | X30: =IF(UPPER(TRIM(C30))=UPPER(TRIM(G30)),"Sí","No") -> No | Y30: =IF(AND(U30="Sí",V30="Sí"),"Sí","No") -> Sí | Z30: Control (vendedor KKR/Walmart) | AA30: Elegible | AB30: =IF(AND(U30="Sí",V30="Sí",W30="Sí",X30="No",AA30="Elegible"),1,0) -> 1 | AC30: Compra de control por Trial Holdings. Sin EV/EBITDA: solo aporta EV/Ventas (no usado en el precio). P/E 3.88x distorsionado. | AE30: =IF(AND(AB30=1,ISNUMBER(N30)),N30,"") | AF30: =IF(AND(AB30=1,ISNUMBER(P30)),P30,"") -> 0.69 | AG30: =IF(AND(AB30=1,ISNUMBER(O30)),O30,"") -> 3.88 | AH30: =IF(ISNUMBER(AE30),IF(AND(AE30<=C$58,AE30>=C$57),AE30,""),"") | AI30: =IF(ISNUMBER(AF30),IF(AND(AF30<=D$58,AF30>=D$57),AF30,""),"") -> 0.69 | AJ30: =IF(ISNUMBER(AG30),IF(AND(AG30<=E$58,AG30>=E$57),AG30,""),"") | AK30: =AE30 | AL30: =AE30 | AM30: =AE30 | AN30: =AE30
A31: 4172416040 | B31: 45281 | C31: Chengdu Hongqi Chain Co Ltd | D31: China (Mainland) | E31: Food & Beverage Retailing | F31: Public | G31: Sichuan Shangtou Investment Co Ltd | H31: China (Mainland) | I31: Completed | J31: 182.33 | K31: 957.34243 | L31: =IF(ISNUMBER(J31),J31*$C$10,"NA") -> 3369.4584 | M31: =IF(ISNUMBER(K31),K31*$C$10,"NA") -> 17691.688 | N31: 4.97 | O31: 13.41 | P31: 0.67 | Q31: NA | R31: 7.79 | S31: 1419.49 | T31: =COUNT(N31:P31) -> 3 | U31: =IF(AND(B31>=$C$8,B31<=$C$6),"Sí","No") -> Sí | V31: =IF(T31>=$C$9,"Sí","No") -> Sí | W31: Sí | X31: =IF(UPPER(TRIM(C31))=UPPER(TRIM(G31)),"Sí","No") -> No | Y31: =IF(AND(U31="Sí",V31="Sí"),"Sí","No") -> Sí | Z31: Cambio de control (inversionista estatal) | AA31: Elegible | AB31: =IF(AND(U31="Sí",V31="Sí",W31="Sí",X31="No",AA31="Elegible"),1,0) -> 1 | AC31: CORRECCIÓN: el objetivo es Chengdu Hongqi Chain (cadena de conveniencia y supermercados de Sichuan), no "Chongqing Department Store". Sichuan Shangtou Investment pasa a ser el accionista de control. La pantalla no reporta el % adquirido: decisión del analista con base en el anuncio. | AD31: Corregido | AE31: =IF(AND(AB31=1,ISNUMBER(N31)),N31,"") -> 4.97 | AF31: =IF(AND(AB31=1,ISNUMBER(P31)),P31,"") -> 0.67 | AG31: =IF(AND(AB31=1,ISNUMBER(O31)),O31,"") -> 13.41 | AH31: =IF(ISNUMBER(AE31),IF(AND(AE31<=C$58,AE31>=C$57),AE31,""),"") -> 4.97 | AI31: =IF(ISNUMBER(AF31),IF(AND(AF31<=D$58,AF31>=D$57),AF31,""),"") -> 0.67 | AJ31: =IF(ISNUMBER(AG31),IF(AND(AG31<=E$58,AG31>=E$57),AG31,""),"") -> 13.41 | AK31: =AE31 -> 4.97 | AL31: =AE31 -> 4.97 | AM31: =AE31 -> 4.97 | AN31: =""
A32: 4163818040 | B32: 45260 | C32: Seven & i Holdings Co Ltd | D32: Japan | E32: Food & Beverage Retailing | F32: Public | G32: Seven & i Holdings Co Ltd | H32: Japan | I32: Completed | J32: 747.08 | K32: 23898.264 | L32: =IF(ISNUMBER(J32),J32*$C$10,"NA") -> 13806.038 | M32: =IF(ISNUMBER(K32),K32*$C$10,"NA") -> 441639.91 | N32: 3.36 | O32: 11.07 | P32: 0.31 | Q32: NA | R32: NA | S32: 76488.55 | T32: =COUNT(N32:P32) -> 3 | U32: =IF(AND(B32>=$C$8,B32<=$C$6),"Sí","No") -> Sí | V32: =IF(T32>=$C$9,"Sí","No") -> Sí | W32: Sí | X32: =IF(UPPER(TRIM(C32))=UPPER(TRIM(G32)),"Sí","No") -> Sí | Y32: =IF(AND(U32="Sí",V32="Sí"),"Sí","No") -> Sí | Z32: Recompra propia | AA32: No elegible | AB32: =IF(AND(U32="Sí",V32="Sí",W32="Sí",X32="No",AA32="Elegible"),1,0) -> 0 | AC32: Recompra propia: no hay cambio de control. | AE32: =IF(AND(AB32=1,ISNUMBER(N32)),N32,"") | AF32: =IF(AND(AB32=1,ISNUMBER(P32)),P32,"") | AG32: =IF(AND(AB32=1,ISNUMBER(O32)),O32,"") | AH32: =IF(ISNUMBER(AE32),IF(AND(AE32<=C$58,AE32>=C$57),AE32,""),"") | AI32: =IF(ISNUMBER(AF32),IF(AND(AF32<=D$58,AF32>=D$57),AF32,""),"") | AJ32: =IF(ISNUMBER(AG32),IF(AND(AG32<=E$58,AG32>=E$57),AG32,""),"") | AK32: =AE32 | AL32: =AE32 | AM32: =AE32 | AN32: =AE32
A33: 4220226040 | B33: 45377 | C33: Carrefour SA | D33: France | E33: Food & Beverage Retailing | F33: Public | G33: Carrefour SA | H33: France | I33: Completed | J33: 395.51 | K33: 25430.571 | L33: =IF(ISNUMBER(J33),J33*$C$10,"NA") -> 7309.0248 | M33: =IF(ISNUMBER(K33),K33*$C$10,"NA") -> 469956.94 | N33: 5.16 | O33: 11.59 | P33: 0.28 | Q33: NA | R33: NA | S33: 93703.99 | T33: =COUNT(N33:P33) -> 3 | U33: =IF(AND(B33>=$C$8,B33<=$C$6),"Sí","No") -> Sí | V33: =IF(T33>=$C$9,"Sí","No") -> Sí | W33: Sí | X33: =IF(UPPER(TRIM(C33))=UPPER(TRIM(G33)),"Sí","No") -> Sí | Y33: =IF(AND(U33="Sí",V33="Sí"),"Sí","No") -> Sí | Z33: Recompra propia | AA33: No elegible | AB33: =IF(AND(U33="Sí",V33="Sí",W33="Sí",X33="No",AA33="Elegible"),1,0) -> 0 | AC33: Recompra propia: no hay cambio de control. | AE33: =IF(AND(AB33=1,ISNUMBER(N33)),N33,"") | AF33: =IF(AND(AB33=1,ISNUMBER(P33)),P33,"") | AG33: =IF(AND(AB33=1,ISNUMBER(O33)),O33,"") | AH33: =IF(ISNUMBER(AE33),IF(AND(AE33<=C$58,AE33>=C$57),AE33,""),"") | AI33: =IF(ISNUMBER(AF33),IF(AND(AF33<=D$58,AF33>=D$57),AF33,""),"") | AJ33: =IF(ISNUMBER(AG33),IF(AND(AG33<=E$58,AG33>=E$57),AG33,""),"") | AK33: =AE33 | AL33: =AE33 | AM33: =AE33 | AN33: =AE33
A34: 4382315040 | B34: 45756 | C34: Seven & i Holdings Co Ltd | D34: Japan | E34: Food & Beverage Retailing | F34: Public | G34: Seven & i Holdings Co Ltd | H34: Japan | I34: Completed | J34: 4101.72 | K34: 57481.831 | L34: =IF(ISNUMBER(J34),J34*$C$10,"NA") -> 75799.786 | M34: =IF(ISNUMBER(K34),K34*$C$10,"NA") -> 1062264.2 | N34: 8.74 | O34: 17.36 | P34: 0.78 | Q34: NA | R34: NA | S34: 70151.19 | T34: =COUNT(N34:P34) -> 3 | U34: =IF(AND(B34>=$C$8,B34<=$C$6),"Sí","No") -> Sí | V34: =IF(T34>=$C$9,"Sí","No") -> Sí | W34: Sí | X34: =IF(UPPER(TRIM(C34))=UPPER(TRIM(G34)),"Sí","No") -> Sí | Y34: =IF(AND(U34="Sí",V34="Sí"),"Sí","No") -> Sí | Z34: Recompra propia | AA34: No elegible | AB34: =IF(AND(U34="Sí",V34="Sí",W34="Sí",X34="No",AA34="Elegible"),1,0) -> 0 | AC34: Recompra propia: no hay cambio de control. | AE34: =IF(AND(AB34=1,ISNUMBER(N34)),N34,"") | AF34: =IF(AND(AB34=1,ISNUMBER(P34)),P34,"") | AG34: =IF(AND(AB34=1,ISNUMBER(O34)),O34,"") | AH34: =IF(ISNUMBER(AE34),IF(AND(AE34<=C$58,AE34>=C$57),AE34,""),"") | AI34: =IF(ISNUMBER(AF34),IF(AND(AF34<=D$58,AF34>=D$57),AF34,""),"") | AJ34: =IF(ISNUMBER(AG34),IF(AND(AG34<=E$58,AG34>=E$57),AG34,""),"") | AK34: =AE34 | AL34: =AE34 | AM34: =AE34 | AN34: =AE34
A35: 4488172040 | B35: 45968 | C35: J Sainsbury PLC | D35: United Kingdom | E35: Food & Beverage Retailing | F35: Public | G35: J Sainsbury PLC | H35: United Kingdom | I35: Completed | J35: 120.85 | K35: 13917.256 | L35: =IF(ISNUMBER(J35),J35*$C$10,"NA") -> 2233.308 | M35: =IF(ISNUMBER(K35),K35*$C$10,"NA") -> 257190.89 | N35: 4.71 | O35: 17.52 | P35: 0.32 | Q35: NA | R35: NA | S35: 41267.77 | T35: =COUNT(N35:P35) -> 3 | U35: =IF(AND(B35>=$C$8,B35<=$C$6),"Sí","No") -> Sí | V35: =IF(T35>=$C$9,"Sí","No") -> Sí | W35: Sí | X35: =IF(UPPER(TRIM(C35))=UPPER(TRIM(G35)),"Sí","No") -> Sí | Y35: =IF(AND(U35="Sí",V35="Sí"),"Sí","No") -> Sí | Z35: Recompra propia | AA35: No elegible | AB35: =IF(AND(U35="Sí",V35="Sí",W35="Sí",X35="No",AA35="Elegible"),1,0) -> 0 | AC35: Recompra propia: no hay cambio de control. | AE35: =IF(AND(AB35=1,ISNUMBER(N35)),N35,"") | AF35: =IF(AND(AB35=1,ISNUMBER(P35)),P35,"") | AG35: =IF(AND(AB35=1,ISNUMBER(O35)),O35,"") | AH35: =IF(ISNUMBER(AE35),IF(AND(AE35<=C$58,AE35>=C$57),AE35,""),"") | AI35: =IF(ISNUMBER(AF35),IF(AND(AF35<=D$58,AF35>=D$57),AF35,""),"") | AJ35: =IF(ISNUMBER(AG35),IF(AND(AG35<=E$58,AG35>=E$57),AG35,""),"") | AK35: =AE35 | AL35: =AE35 | AM35: =AE35 | AN35: =AE35
A36: 4343070040 | B36: 45671 | C36: YAOKO Co Ltd | D36: Japan | E36: Food & Beverage Retailing | F36: Public | G36: YAOKO Co Ltd | H36: Japan | I36: Completed | J36: 2412.71 | K36: 2864.3014 | L36: =IF(ISNUMBER(J36),J36*$C$10,"NA") -> 44586.881 | M36: =IF(ISNUMBER(K36),K36*$C$10,"NA") -> 52932.289 | N36: 10.68 | O36: 20.83 | P36: 0.73 | Q36: NA | R36: -1.64 | S36: 4094.82 | T36: =COUNT(N36:P36) -> 3 | U36: =IF(AND(B36>=$C$8,B36<=$C$6),"Sí","No") -> Sí | V36: =IF(T36>=$C$9,"Sí","No") -> Sí | W36: Sí | X36: =IF(UPPER(TRIM(C36))=UPPER(TRIM(G36)),"Sí","No") -> Sí | Y36: =IF(AND(U36="Sí",V36="Sí"),"Sí","No") -> Sí | Z36: Recompra propia | AA36: No elegible | AB36: =IF(AND(U36="Sí",V36="Sí",W36="Sí",X36="No",AA36="Elegible"),1,0) -> 0 | AC36: Recompra propia de YAOKO (supermercados, Japón): no hay cambio de control. | AD36: Agregada | AE36: =IF(AND(AB36=1,ISNUMBER(N36)),N36,"") | AF36: =IF(AND(AB36=1,ISNUMBER(P36)),P36,"") | AG36: =IF(AND(AB36=1,ISNUMBER(O36)),O36,"") | AH36: =IF(ISNUMBER(AE36),IF(AND(AE36<=C$58,AE36>=C$57),AE36,""),"") | AI36: =IF(ISNUMBER(AF36),IF(AND(AF36<=D$58,AF36>=D$57),AF36,""),"") | AJ36: =IF(ISNUMBER(AG36),IF(AND(AG36<=E$58,AG36>=E$57),AG36,""),"") | AK36: =AE36 | AL36: =AE36 | AM36: =AE36 | AN36: =AE36
A37: 4143788040 | B37: 45209 | C37: Magnit PJSC | D37: Russia | E37: Food & Beverage Retailing | F37: Public | G37: Magnit PJSC | H37: Russia | I37: Completed | J37: 180.44 | K37: 7977.494 | L37: =IF(ISNUMBER(J37),J37*$C$10,"NA") -> 3334.5312 | M37: =IF(ISNUMBER(K37),K37*$C$10,"NA") -> 147424.09 | N37: 3.63 | O37: 6.67 | P37: 0.32 | Q37: -59.55 | R37: -61.42 | S37: 28121.76 | T37: =COUNT(N37:P37) -> 3 | U37: =IF(AND(B37>=$C$8,B37<=$C$6),"Sí","No") -> Sí | V37: =IF(T37>=$C$9,"Sí","No") -> Sí | W37: Sí | X37: =IF(UPPER(TRIM(C37))=UPPER(TRIM(G37)),"Sí","No") -> Sí | Y37: =IF(AND(U37="Sí",V37="Sí"),"Sí","No") -> Sí | Z37: Recompra propia | AA37: No elegible | AB37: =IF(AND(U37="Sí",V37="Sí",W37="Sí",X37="No",AA37="Elegible"),1,0) -> 0 | AC37: Recompra propia en un mercado con sanciones (Rusia). | AE37: =IF(AND(AB37=1,ISNUMBER(N37)),N37,"") | AF37: =IF(AND(AB37=1,ISNUMBER(P37)),P37,"") | AG37: =IF(AND(AB37=1,ISNUMBER(O37)),O37,"") | AH37: =IF(ISNUMBER(AE37),IF(AND(AE37<=C$58,AE37>=C$57),AE37,""),"") | AI37: =IF(ISNUMBER(AF37),IF(AND(AF37<=D$58,AF37>=D$57),AF37,""),"") | AJ37: =IF(ISNUMBER(AG37),IF(AND(AG37<=E$58,AG37>=E$57),AG37,""),"") | AK37: =AE37 | AL37: =AE37 | AM37: =AE37 | AN37: =AE37
A38: 4391691040 | B38: 45777 | C38: Gorodskoi Supermarket OOO | D38: Russia | E38: Food & Beverage Retailing | F38: Private | G38: Tander AO | H38: Russia | I38: Completed | J38: 361.67 | K38: 478.10036 | L38: =IF(ISNUMBER(J38),J38*$C$10,"NA") -> 6683.6616 | M38: =IF(ISNUMBER(K38),K38*$C$10,"NA") -> 8835.2946 | N38: NA | O38: 44.78 | P38: 0.45 | Q38: NA | R38: NA | S38: 966.99 | T38: =COUNT(N38:P38) -> 2 | U38: =IF(AND(B38>=$C$8,B38<=$C$6),"Sí","No") -> Sí | V38: =IF(T38>=$C$9,"Sí","No") -> Sí | W38: Sí | X38: =IF(UPPER(TRIM(C38))=UPPER(TRIM(G38)),"Sí","No") -> No | Y38: =IF(AND(U38="Sí",V38="Sí"),"Sí","No") -> Sí | Z38: Control (Rusia) | AA38: No elegible | AB38: =IF(AND(U38="Sí",V38="Sí",W38="Sí",X38="No",AA38="Elegible"),1,0) -> 0 | AC38: Rusia: valuaciones distorsionadas por sanciones; además sin EV/EBITDA. | AE38: =IF(AND(AB38=1,ISNUMBER(N38)),N38,"") | AF38: =IF(AND(AB38=1,ISNUMBER(P38)),P38,"") | AG38: =IF(AND(AB38=1,ISNUMBER(O38)),O38,"") | AH38: =IF(ISNUMBER(AE38),IF(AND(AE38<=C$58,AE38>=C$57),AE38,""),"") | AI38: =IF(ISNUMBER(AF38),IF(AND(AF38<=D$58,AF38>=D$57),AF38,""),"") | AJ38: =IF(ISNUMBER(AG38),IF(AND(AG38<=E$58,AG38>=E$57),AG38,""),"") | AK38: =AE38 | AL38: =AE38 | AM38: =AE38 | AN38: =AE38
A39: 4228856040 | B39: 45391 | C39: Better Life Commercial Chain Share Co Ltd | D39: China (Mainland) | E39: Food & Beverage Retailing | F39: Public | G39: Investor Group | H39: China (Mainland) | I39: Completed | J39: 345.7 | K39: 2318.2596 | L39: =IF(ISNUMBER(J39),J39*$C$10,"NA") -> 6388.536 | M39: =IF(ISNUMBER(K39),K39*$C$10,"NA") -> 42841.438 | N39: 45.98 | O39: NA | P39: 5.64 | Q39: NA | R39: NA | S39: 411.61 | T39: =COUNT(N39:P39) -> 2 | U39: =IF(AND(B39>=$C$8,B39<=$C$6),"Sí","No") -> Sí | V39: =IF(T39>=$C$9,"Sí","No") -> Sí | W39: Sí | X39: =IF(UPPER(TRIM(C39))=UPPER(TRIM(G39)),"Sí","No") -> No | Y39: =IF(AND(U39="Sí",V39="Sí"),"Sí","No") -> Sí | Z39: Reestructura por insolvencia | AA39: No elegible | AB39: =IF(AND(U39="Sí",V39="Sí",W39="Sí",X39="No",AA39="Elegible"),1,0) -> 0 | AC39: Better Life Commercial Chain (Bubugao, supermercados de Hunan) en reestructura judicial: EV/EBITDA 46.0x y EV/Ventas 5.6x no representan una adquisición en marcha. | AD39: Agregada | AE39: =IF(AND(AB39=1,ISNUMBER(N39)),N39,"") | AF39: =IF(AND(AB39=1,ISNUMBER(P39)),P39,"") | AG39: =IF(AND(AB39=1,ISNUMBER(O39)),O39,"") | AH39: =IF(ISNUMBER(AE39),IF(AND(AE39<=C$58,AE39>=C$57),AE39,""),"") | AI39: =IF(ISNUMBER(AF39),IF(AND(AF39<=D$58,AF39>=D$57),AF39,""),"") | AJ39: =IF(ISNUMBER(AG39),IF(AND(AG39<=E$58,AG39>=E$57),AG39,""),"") | AK39: =AE39 | AL39: =AE39 | AM39: =AE39 | AN39: =AE39
A40: 4292215040 | B40: 45539 | C40: Wincommerce General Commercial Services JSC | D40: Vietnam | E40: Food & Beverage Retailing | F40: Subsidiary | G40: Masan Consumer Holdings Co Ltd | H40: Vietnam | I40: Completed | J40: 200 | K40: 2951.1146 | L40: =IF(ISNUMBER(J40),J40*$C$10,"NA") -> 3696 | M40: =IF(ISNUMBER(K40),K40*$C$10,"NA") -> 54536.598 | N40: 323.13 | O40: NA | P40: 2.45 | Q40: NA | R40: NA | S40: 1235 | T40: =COUNT(N40:P40) -> 2 | U40: =IF(AND(B40>=$C$8,B40<=$C$6),"Sí","No") -> Sí | V40: =IF(T40>=$C$9,"Sí","No") -> Sí | W40: Sí | X40: =IF(UPPER(TRIM(C40))=UPPER(TRIM(G40)),"Sí","No") -> No | Y40: =IF(AND(U40="Sí",V40="Sí"),"Sí","No") -> Sí | Z40: Reorganización intragrupo | AA40: No elegible | AB40: =IF(AND(U40="Sí",V40="Sí",W40="Sí",X40="No",AA40="Elegible"),1,0) -> 0 | AC40: Wincommerce (WinMart, Vietnam) adquirida por otra empresa del grupo Masan: reorganización intragrupo; EV/EBITDA 323.1x por EBITDA cercano a cero. | AD40: Agregada | AE40: =IF(AND(AB40=1,ISNUMBER(N40)),N40,"") | AF40: =IF(AND(AB40=1,ISNUMBER(P40)),P40,"") | AG40: =IF(AND(AB40=1,ISNUMBER(O40)),O40,"") | AH40: =IF(ISNUMBER(AE40),IF(AND(AE40<=C$58,AE40>=C$57),AE40,""),"") | AI40: =IF(ISNUMBER(AF40),IF(AND(AF40<=D$58,AF40>=D$57),AF40,""),"") | AJ40: =IF(ISNUMBER(AG40),IF(AND(AG40<=E$58,AG40>=E$57),AG40,""),"") | AK40: =AE40 | AL40: =AE40 | AM40: =AE40 | AN40: =AE40
A41: 4467353040 | B41: 46007 | C41: Prosol Gestion SAS | D41: France | E41: Food & Beverage Retailing | F41: Subsidiary | G41: Apollo Global Management Inc | H41: United States | I41: Completed | J41: 1727.54 | K41: 2464.1464 | L41: =IF(ISNUMBER(J41),J41*$C$10,"NA") -> 31924.939 | M41: =IF(ISNUMBER(K41),K41*$C$10,"NA") -> 45537.425 | N41: NA | O41: 33.81 | P41: 44.45 | Q41: NA | R41: NA | S41: 52.55 | T41: =COUNT(N41:P41) -> 2 | U41: =IF(AND(B41>=$C$8,B41<=$C$6),"Sí","No") -> Sí | V41: =IF(T41>=$C$9,"Sí","No") -> Sí | W41: Sí | X41: =IF(UPPER(TRIM(C41))=UPPER(TRIM(G41)),"Sí","No") -> No | Y41: =IF(AND(U41="Sí",V41="Sí"),"Sí","No") -> Sí | Z41: Control (fondo) | AA41: No elegible | AB41: =IF(AND(U41="Sí",V41="Sí",W41="Sí",X41="No",AA41="Elegible"),1,0) -> 0 | AC41: Prosol (Grand Frais, alimentos frescos) adquirida por Apollo. Sin EV/EBITDA y EV/Ventas 44.5x incongruente con un minorista de alimentos: dato no confiable. | AD41: Agregada | AE41: =IF(AND(AB41=1,ISNUMBER(N41)),N41,"") | AF41: =IF(AND(AB41=1,ISNUMBER(P41)),P41,"") | AG41: =IF(AND(AB41=1,ISNUMBER(O41)),O41,"") | AH41: =IF(ISNUMBER(AE41),IF(AND(AE41<=C$58,AE41>=C$57),AE41,""),"") | AI41: =IF(ISNUMBER(AF41),IF(AND(AF41<=D$58,AF41>=D$57),AF41,""),"") | AJ41: =IF(ISNUMBER(AG41),IF(AND(AG41<=E$58,AG41>=E$57),AG41,""),"") | AK41: =AE41 | AL41: =AE41 | AM41: =AE41 | AN41: =AE41
A42: 4069894040 | B42: 45041 | C42: Inageya Co Ltd | D42: Japan | E42: Food & Beverage Retailing | F42: Public | G42: AEON CO LTD | H42: Japan | I42: Completed | J42: 170.08 | K42: 463.75651 | L42: =IF(ISNUMBER(J42),J42*$C$10,"NA") -> 3143.0784 | M42: =IF(ISNUMBER(K42),K42*$C$10,"NA") -> 8570.2203 | N42: 10.27 | O42: NA | P42: 0.24 | Q42: 25.88 | R42: 27.27 | S42: 1704.63 | T42: =COUNT(N42:P42) -> 2 | U42: =IF(AND(B42>=$C$8,B42<=$C$6),"Sí","No") -> No | V42: =IF(T42>=$C$9,"Sí","No") -> Sí | W42: Sí | X42: =IF(UPPER(TRIM(C42))=UPPER(TRIM(G42)),"Sí","No") -> No | Y42: =IF(AND(U42="Sí",V42="Sí"),"Sí","No") -> No | Z42: Control | AA42: Elegible | AB42: =IF(AND(U42="Sí",V42="Sí",W42="Sí",X42="No",AA42="Elegible"),1,0) -> 0 | AC42: Fuera de la ventana de 3 años. | AE42: =IF(AND(AB42=1,ISNUMBER(N42)),N42,"") | AF42: =IF(AND(AB42=1,ISNUMBER(P42)),P42,"") | AG42: =IF(AND(AB42=1,ISNUMBER(O42)),O42,"") | AH42: =IF(ISNUMBER(AE42),IF(AND(AE42<=C$58,AE42>=C$57),AE42,""),"") | AI42: =IF(ISNUMBER(AF42),IF(AND(AF42<=D$58,AF42>=D$57),AF42,""),"") | AJ42: =IF(ISNUMBER(AG42),IF(AND(AG42<=E$58,AG42>=E$57),AG42,""),"") | AK42: =AE42 | AL42: =AE42 | AM42: =AE42 | AN42: =AE42
A43: 4069904040 | B43: 45040 | C43: Casino Guichard-Perrachon SA | D43: France | E43: Discount and Department Store Retailing | F43: Public | G43: Investor Group | H43: Czech Republic | I43: Completed | J43: 1347.24 | K43: 12843.134 | L43: =IF(ISNUMBER(J43),J43*$C$10,"NA") -> 24896.995 | M43: =IF(ISNUMBER(K43),K43*$C$10,"NA") -> 237341.11 | N43: 6.38 | O43: NA | P43: 0.4 | Q43: NA | R43: NA | S43: 31598.64 | T43: =COUNT(N43:P43) -> 2 | U43: =IF(AND(B43>=$C$8,B43<=$C$6),"Sí","No") -> No | V43: =IF(T43>=$C$9,"Sí","No") -> Sí | W43: Sí | X43: =IF(UPPER(TRIM(C43))=UPPER(TRIM(G43)),"Sí","No") -> No | Y43: =IF(AND(U43="Sí",V43="Sí"),"Sí","No") -> No | Z43: Control (reestructura de deuda) | AA43: Elegible | AB43: =IF(AND(U43="Sí",V43="Sí",W43="Sí",X43="No",AA43="Elegible"),1,0) -> 0 | AC43: Fuera de la ventana; reestructura de deuda. | AE43: =IF(AND(AB43=1,ISNUMBER(N43)),N43,"") | AF43: =IF(AND(AB43=1,ISNUMBER(P43)),P43,"") | AG43: =IF(AND(AB43=1,ISNUMBER(O43)),O43,"") | AH43: =IF(ISNUMBER(AE43),IF(AND(AE43<=C$58,AE43>=C$57),AE43,""),"") | AI43: =IF(ISNUMBER(AF43),IF(AND(AF43<=D$58,AF43>=D$57),AF43,""),"") | AJ43: =IF(ISNUMBER(AG43),IF(AND(AG43<=E$58,AG43>=E$57),AG43,""),"") | AK43: =AE43 | AL43: =AE43 | AM43: =AE43 | AN43: =AE43
A44: 4115751040 | B44: 45141 | C44: Dia Portugal Supermercados SA | D44: Portugal | E44: Food & Beverage Retailing | F44: Subsidiary | G44: Auchan Retail Portugal Sa | H44: Portugal | I44: Completed | J44: 186.02 | K44: 186.16127 | L44: =IF(ISNUMBER(J44),J44*$C$10,"NA") -> 3437.6496 | M44: =IF(ISNUMBER(K44),K44*$C$10,"NA") -> 3440.2603 | N44: 46.78 | O44: NA | P44: 0.29 | Q44: NA | R44: NA | S44: 625.09 | T44: =COUNT(N44:P44) -> 2 | U44: =IF(AND(B44>=$C$8,B44<=$C$6),"Sí","No") -> No | V44: =IF(T44>=$C$9,"Sí","No") -> Sí | W44: Sí | X44: =IF(UPPER(TRIM(C44))=UPPER(TRIM(G44)),"Sí","No") -> No | Y44: =IF(AND(U44="Sí",V44="Sí"),"Sí","No") -> No | Z44: Control | AA44: Elegible | AB44: =IF(AND(U44="Sí",V44="Sí",W44="Sí",X44="No",AA44="Elegible"),1,0) -> 0 | AC44: Fuera de la ventana; EBITDA deprimido (46.8x). | AE44: =IF(AND(AB44=1,ISNUMBER(N44)),N44,"") | AF44: =IF(AND(AB44=1,ISNUMBER(P44)),P44,"") | AG44: =IF(AND(AB44=1,ISNUMBER(O44)),O44,"") | AH44: =IF(ISNUMBER(AE44),IF(AND(AE44<=C$58,AE44>=C$57),AE44,""),"") | AI44: =IF(ISNUMBER(AF44),IF(AND(AF44<=D$58,AF44>=D$57),AF44,""),"") | AJ44: =IF(ISNUMBER(AG44),IF(AND(AG44<=E$58,AG44>=E$57),AG44,""),"") | AK44: =AE44 | AL44: =AE44 | AM44: =AE44 | AN44: =AE44
A45: 4364904040 | B45: 45721 | C45: Rimi Baltic AB | D45: Latvia | E45: Food & Beverage Retailing | F45: Subsidiary | G45: Salling Group A/S | H45: Denmark | I45: Completed | J45: 1381.11 | K45: NA | L45: =IF(ISNUMBER(J45),J45*$C$10,"NA") -> 25522.913 | M45: =IF(ISNUMBER(K45),K45*$C$10,"NA") -> NA | N45: NA | O45: 27.76 | P45: NA | Q45: NA | R45: NA | S45: NA | T45: =COUNT(N45:P45) -> 1 | U45: =IF(AND(B45>=$C$8,B45<=$C$6),"Sí","No") -> Sí | V45: =IF(T45>=$C$9,"Sí","No") -> No | W45: Sí | X45: =IF(UPPER(TRIM(C45))=UPPER(TRIM(G45)),"Sí","No") -> No | Y45: =IF(AND(U45="Sí",V45="Sí"),"Sí","No") -> No | Z45: Control | AA45: Elegible | AB45: =IF(AND(U45="Sí",V45="Sí",W45="Sí",X45="No",AA45="Elegible"),1,0) -> 0 | AC45: Solo 1 múltiplo disponible. | AE45: =IF(AND(AB45=1,ISNUMBER(N45)),N45,"") | AF45: =IF(AND(AB45=1,ISNUMBER(P45)),P45,"") | AG45: =IF(AND(AB45=1,ISNUMBER(O45)),O45,"") | AH45: =IF(ISNUMBER(AE45),IF(AND(AE45<=C$58,AE45>=C$57),AE45,""),"") | AI45: =IF(ISNUMBER(AF45),IF(AND(AF45<=D$58,AF45>=D$57),AF45,""),"") | AJ45: =IF(ISNUMBER(AG45),IF(AND(AG45<=E$58,AG45>=E$57),AG45,""),"") | AK45: =AE45 | AL45: =AE45 | AM45: =AE45 | AN45: =AE45
A46: =COUNTIF($AB$23:$AB$45,1)&" de "&COUNTA($A$23:$A$45)&" operaciones evaluadas cumplen todos los criterios" -> 9 de 23 operaciones evaluadas cumplen todos los criterios
A48: 3. ESTADÍSTICOS (operaciones con Incluir = 1; NA excluido) Y PRECIO IMPLÍCITO — mismo puente EV → capital que Trading Comps
A49: Estadístico | C49: EV/EBITDA (x) | D49: EV/Ventas (x) | E49: P/E (x) | F49: Precio implícito EV/EBITDA (MXN) | G49: Potencial vs. mercado | H49: Precio implícito EV/Ventas (MXN, referencia)
A50: Mínimo | C50: =IF(COUNT($AE$23:$AE$45)>0,MIN($AE$23:$AE$45),"NA") -> 2.2 | D50: =IF(COUNT($AF$23:$AF$45)>0,MIN($AF$23:$AF$45),"NA") -> 0.08 | E50: =IF(COUNT($AG$23:$AG$45)>0,MIN($AG$23:$AG$45),"NA") -> 3.88 | F50: =IF(ISNUMBER(C50),IF(C50*Multiplos!$B$21+Multiplos!$B$30>0,(C50*Multiplos!$B$21+Multiplos!$B$30)/Multiplos!$B$23,"NM"),"NA") -> 5.0770623 | G50: =IFERROR(F50/'Valuación Combinada'!$B$10-1,"NM") -> -0.84835537 | H50: =IF(ISNUMBER(D50),IF(D50*Multiplos!$B$18+Multiplos!$B$30>0,(D50*Multiplos!$B$18+Multiplos!$B$30)/Multiplos!$B$23,"NM"),"NA") -> NM
A51: Percentil 25 | C51: =IF(COUNT($AE$23:$AE$45)>0,PERCENTILE($AE$23:$AE$45,0.25),"NA") -> 4.5375 | D51: =IF(COUNT($AF$23:$AF$45)>0,PERCENTILE($AF$23:$AF$45,0.25),"NA") -> 0.28 | E51: =IF(COUNT($AG$23:$AG$45)>0,PERCENTILE($AG$23:$AG$45,0.25),"NA") -> 11.0275 | F51: =IF(ISNUMBER(C51),IF(C51*Multiplos!$B$21+Multiplos!$B$30>0,(C51*Multiplos!$B$21+Multiplos!$B$30)/Multiplos!$B$23,"NM"),"NA") -> 20.414791 | G51: =IFERROR(F51/'Valuación Combinada'!$B$10-1,"NM") -> -0.39023923 | H51: =IF(ISNUMBER(D51),IF(D51*Multiplos!$B$18+Multiplos!$B$30>0,(D51*Multiplos!$B$18+Multiplos!$B$30)/Multiplos!$B$23,"NM"),"NA") -> 17.751464
A52: Media | C52: =IF(COUNT($AE$23:$AE$45)>0,AVERAGE($AE$23:$AE$45),"NA") -> 7.7775 | D52: =IF(COUNT($AF$23:$AF$45)>0,AVERAGE($AF$23:$AF$45),"NA") -> 0.48222222 | E52: =IF(COUNT($AG$23:$AG$45)>0,AVERAGE($AG$23:$AG$45),"NA") -> 12.3825 | F52: =IF(ISNUMBER(C52),IF(C52*Multiplos!$B$21+Multiplos!$B$30>0,(C52*Multiplos!$B$21+Multiplos!$B$30)/Multiplos!$B$23,"NM"),"NA") -> 41.674358 | G52: =IFERROR(F52/'Valuación Combinada'!$B$10-1,"NM") -> 0.24475384 | H52: =IF(ISNUMBER(D52),IF(D52*Multiplos!$B$18+Multiplos!$B$30>0,(D52*Multiplos!$B$18+Multiplos!$B$30)/Multiplos!$B$23,"NM"),"NA") -> 37.330845
A53: Mediana | C53: =IF(COUNT($AE$23:$AE$45)>0,MEDIAN($AE$23:$AE$45),"NA") -> 5.045 | D53: =IF(COUNT($AF$23:$AF$45)>0,MEDIAN($AF$23:$AF$45),"NA") -> 0.53 | E53: =IF(COUNT($AG$23:$AG$45)>0,MEDIAN($AG$23:$AG$45),"NA") -> 13.565 | F53: =IF(ISNUMBER(C53),IF(C53*Multiplos!$B$21+Multiplos!$B$30>0,(C53*Multiplos!$B$21+Multiplos!$B$30)/Multiplos!$B$23,"NM"),"NA") -> 23.7448 | G53: =IFERROR(F53/'Valuación Combinada'!$B$10-1,"NM") -> -0.29077658 | H53: =IF(ISNUMBER(D53),IF(D53*Multiplos!$B$18+Multiplos!$B$30>0,(D53*Multiplos!$B$18+Multiplos!$B$30)/Multiplos!$B$23,"NM"),"NA") -> 41.956742
A54: Percentil 75 | C54: =IF(COUNT($AE$23:$AE$45)>0,PERCENTILE($AE$23:$AE$45,0.75),"NA") -> 8.9225 | D54: =IF(COUNT($AF$23:$AF$45)>0,PERCENTILE($AF$23:$AF$45,0.75),"NA") -> 0.69 | E54: =IF(COUNT($AG$23:$AG$45)>0,PERCENTILE($AG$23:$AG$45,0.75),"NA") -> 14.92 | F54: =IF(ISNUMBER(C54),IF(C54*Multiplos!$B$21+Multiplos!$B$30>0,(C54*Multiplos!$B$21+Multiplos!$B$30)/Multiplos!$B$23,"NM"),"NA") -> 49.187385 | G54: =IFERROR(F54/'Valuación Combinada'!$B$10-1,"NM") -> 0.46915725 | H54: =IF(ISNUMBER(D54),IF(D54*Multiplos!$B$18+Multiplos!$B$30>0,(D54*Multiplos!$B$18+Multiplos!$B$30)/Multiplos!$B$23,"NM"),"NA") -> 57.44812
A55: Máximo | C55: =IF(COUNT($AE$23:$AE$45)>0,MAX($AE$23:$AE$45),"NA") -> 21.31 | D55: =IF(COUNT($AF$23:$AF$45)>0,MAX($AF$23:$AF$45),"NA") -> 0.9 | E55: =IF(COUNT($AG$23:$AG$45)>0,MAX($AG$23:$AG$45),"NA") -> 18.52 | F55: =IF(ISNUMBER(C55),IF(C55*Multiplos!$B$21+Multiplos!$B$30>0,(C55*Multiplos!$B$21+Multiplos!$B$30)/Multiplos!$B$23,"NM"),"NA") -> 130.46914 | G55: =IFERROR(F55/'Valuación Combinada'!$B$10-1,"NM") -> 2.8969278 | H55: =IF(ISNUMBER(D55),IF(D55*Multiplos!$B$18+Multiplos!$B$30>0,(D55*Multiplos!$B$18+Multiplos!$B$30)/Multiplos!$B$23,"NM"),"NA") -> 77.780553
A56: n (observaciones) | C56: =COUNT($AE$23:$AE$45) -> 8 | D56: =COUNT($AF$23:$AF$45) -> 9 | E56: =COUNT($AG$23:$AG$45) -> 4
A57: Límite inferior de atípicos (P25 − 1.5 × RIC) | C57: =IF(ISNUMBER(C51),C51-1.5*(C54-C51),"NA") -> -2.04 | D57: =IF(ISNUMBER(D51),D51-1.5*(D54-D51),"NA") -> -0.335 | E57: =IF(ISNUMBER(E51),E51-1.5*(E54-E51),"NA") -> 5.18875
A58: Límite superior de atípicos (P75 + 1.5 × RIC) | C58: =IF(ISNUMBER(C54),C54+1.5*(C54-C51),"NA") -> 15.5 | D58: =IF(ISNUMBER(D54),D54+1.5*(D54-D51),"NA") -> 1.305 | E58: =IF(ISNUMBER(E54),E54+1.5*(E54-E51),"NA") -> 20.75875
A59: Atípicos detectados (n) | C59: =IF(ISNUMBER(C58),COUNTIF($AE$23:$AE$45,">"&C58)+COUNTIF($AE$23:$AE$45,"<"&C57),0) -> 1 | D59: =IF(ISNUMBER(D58),COUNTIF($AF$23:$AF$45,">"&D58)+COUNTIF($AF$23:$AF$45,"<"&D57),0) -> 0 | E59: =IF(ISNUMBER(E58),COUNTIF($AG$23:$AG$45,">"&E58)+COUNTIF($AG$23:$AG$45,"<"&E57),0) -> 1
A60: Media sin atípicos | C60: =IF(ISNUMBER(C58),AVERAGEIFS($AE$23:$AE$45,$AE$23:$AE$45,"<="&C58,$AE$23:$AE$45,">="&C57),"NA") -> 5.8442857 | D60: =IF(ISNUMBER(D58),AVERAGEIFS($AF$23:$AF$45,$AF$23:$AF$45,"<="&D58,$AF$23:$AF$45,">="&D57),"NA") -> 0.48222222 | E60: =IF(ISNUMBER(E58),AVERAGEIFS($AG$23:$AG$45,$AG$23:$AG$45,"<="&E58,$AG$23:$AG$45,">="&E57),"NA") -> 15.216667 | F60: =IF(ISNUMBER(C60),IF(C60*Multiplos!$B$21+Multiplos!$B$30>0,(C60*Multiplos!$B$21+Multiplos!$B$30)/Multiplos!$B$23,"NM"),"NA") -> 28.989389 | G60: =IFERROR(F60/'Valuación Combinada'!$B$10-1,"NM") -> -0.13412816 | H60: =IF(ISNUMBER(D60),IF(D60*Multiplos!$B$18+Multiplos!$B$30>0,(D60*Multiplos!$B$18+Multiplos!$B$30)/Multiplos!$B$23,"NM"),"NA") -> 37.330845
A61: Mediana sin atípicos | C61: =IF(COUNT($AH$23:$AH$45)>0,MEDIAN($AH$23:$AH$45),"NA") -> 4.98 | D61: =IF(COUNT($AI$23:$AI$45)>0,MEDIAN($AI$23:$AI$45),"NA") -> 0.53 | E61: =IF(COUNT($AJ$23:$AJ$45)>0,MEDIAN($AJ$23:$AJ$45),"NA") -> 13.72 | F61: =IF(ISNUMBER(C61),IF(C61*Multiplos!$B$21+Multiplos!$B$30>0,(C61*Multiplos!$B$21+Multiplos!$B$30)/Multiplos!$B$23,"NM"),"NA") -> 23.318296 | G61: =IFERROR(F61/'Valuación Combinada'!$B$10-1,"NM") -> -0.30351564
A62: P/E: no se usa en el precio (pocas observaciones y utilidades distorsionadas en operaciones de control); se muestra para trazabilidad.
A63: EV/Ventas: excluido del precio por el mismo criterio que Trading Comps (ignora el margen). Se muestra como referencia.
A65: 4. SENSIBILIDAD DE LA MUESTRA (efecto de las operaciones que requieren juicio) — EV/EBITDA
A66: Caso | C66: n | D66: Mediana (x) | E66: Precio implícito mediana (MXN) | F66: Media sin atípicos (x) | G66: Precio implícito media sin atípicos (MXN) | H66: Operaciones retiradas
A67: Muestra auditada (oficial) | C67: =COUNT($AK$23:$AK$45) -> 8 | D67: =MEDIAN($AK$23:$AK$45) -> 5.045 | E67: =IF(ISNUMBER(D67),IF(D67*Multiplos!$B$21+Multiplos!$B$30>0,(D67*Multiplos!$B$21+Multiplos!$B$30)/Multiplos!$B$23,"NM"),"NA") -> 23.7448 | F67: =AVERAGEIFS($AK$23:$AK$45,$AK$23:$AK$45,"<="&(PERCENTILE($AK$23:$AK$45,0.75)+1.5*(PERCENTILE($AK$23:$AK$45,0.75)-PERCENTILE($AK$23:$AK$45,0.25))),$AK$23:$AK$45,">="&(PERCENTILE($AK$23:$AK$45,0.25)-1.5*(PERCENTILE($AK$23:$AK$45,0.75)-PERCENTILE($AK$23:$AK$45,0.25)))) -> 5.8442857 | G67: =IF(ISNUMBER(F67),IF(F67*Multiplos!$B$21+Multiplos!$B$30>0,(F67*Multiplos!$B$21+Multiplos!$B$30)/Multiplos!$B$23,"NM"),"NA") -> 28.989389 | H67: —
A68: Sin Sun Art (empresa en dificultad) | C68: =COUNT($AL$23:$AL$45) -> 7 | D68: =MEDIAN($AL$23:$AL$45) -> 5.11 | E68: =IF(ISNUMBER(D68),IF(D68*Multiplos!$B$21+Multiplos!$B$30>0,(D68*Multiplos!$B$21+Multiplos!$B$30)/Multiplos!$B$23,"NM"),"NA") -> 24.171304 | F68: =AVERAGEIFS($AL$23:$AL$45,$AL$23:$AL$45,"<="&(PERCENTILE($AL$23:$AL$45,0.75)+1.5*(PERCENTILE($AL$23:$AL$45,0.75)-PERCENTILE($AL$23:$AL$45,0.25))),$AL$23:$AL$45,">="&(PERCENTILE($AL$23:$AL$45,0.25)-1.5*(PERCENTILE($AL$23:$AL$45,0.75)-PERCENTILE($AL$23:$AL$45,0.25)))) -> 6.4516667 | G68: =IF(ISNUMBER(F68),IF(F68*Multiplos!$B$21+Multiplos!$B$30>0,(F68*Multiplos!$B$21+Multiplos!$B$30)/Multiplos!$B$23,"NM"),"NA") -> 32.974777 | H68: Sun Art Retail Group Ltd
A69: Sin participaciones no de control (Lawson 50%, Yonghui ~29%) | C69: =COUNT($AM$23:$AM$45) -> 6 | D69: =MEDIAN($AM$23:$AM$45) -> 5.045 | E69: =IF(ISNUMBER(D69),IF(D69*Multiplos!$B$21+Multiplos!$B$30>0,(D69*Multiplos!$B$21+Multiplos!$B$30)/Multiplos!$B$23,"NM"),"NA") -> 23.7448 | F69: =AVERAGEIFS($AM$23:$AM$45,$AM$23:$AM$45,"<="&(PERCENTILE($AM$23:$AM$45,0.75)+1.5*(PERCENTILE($AM$23:$AM$45,0.75)-PERCENTILE($AM$23:$AM$45,0.25))),$AM$23:$AM$45,">="&(PERCENTILE($AM$23:$AM$45,0.25)-1.5*(PERCENTILE($AM$23:$AM$45,0.75)-PERCENTILE($AM$23:$AM$45,0.25)))) -> 4.98 | G69: =IF(ISNUMBER(F69),IF(F69*Multiplos!$B$21+Multiplos!$B$30>0,(F69*Multiplos!$B$21+Multiplos!$B$30)/Multiplos!$B$23,"NM"),"NA") -> 23.318296 | H69: Lawson Inc, Yonghui Superstores Co Ltd
A70: Sin Chengdu Hongqi (control no verificable en la pantalla) | C70: =COUNT($AN$23:$AN$45) -> 7 | D70: =MEDIAN($AN$23:$AN$45) -> 5.11 | E70: =IF(ISNUMBER(D70),IF(D70*Multiplos!$B$21+Multiplos!$B$30>0,(D70*Multiplos!$B$21+Multiplos!$B$30)/Multiplos!$B$23,"NM"),"NA") -> 24.171304 | F70: =AVERAGEIFS($AN$23:$AN$45,$AN$23:$AN$45,"<="&(PERCENTILE($AN$23:$AN$45,0.75)+1.5*(PERCENTILE($AN$23:$AN$45,0.75)-PERCENTILE($AN$23:$AN$45,0.25))),$AN$23:$AN$45,">="&(PERCENTILE($AN$23:$AN$45,0.25)-1.5*(PERCENTILE($AN$23:$AN$45,0.75)-PERCENTILE($AN$23:$AN$45,0.25)))) -> 5.99 | G70: =IF(ISNUMBER(F70),IF(F70*Multiplos!$B$21+Multiplos!$B$30>0,(F70*Multiplos!$B$21+Multiplos!$B$30)/Multiplos!$B$23,"NM"),"NA") -> 29.945507 | H70: Chengdu Hongqi Chain Co Ltd
A71: Versión original del libro PRO (EV/EBITDA, n = 7, sin Hongqi) | C71: 7 | D71: 5.11 | E71: =IF(ISNUMBER(D71),IF(D71*Multiplos!$B$21+Multiplos!$B$30>0,(D71*Multiplos!$B$21+Multiplos!$B$30)/Multiplos!$B$23,"NM"),"NA") -> 24.171304 | F71: 5.99 | G71: =IF(ISNUMBER(F71),IF(F71*Multiplos!$B$21+Multiplos!$B$30>0,(F71*Multiplos!$B$21+Multiplos!$B$30)/Multiplos!$B$23,"NM"),"NA") -> 29.945507 | H71: Valores registrados del libro original (mediana 5.11x → $24.17; media sin atípicos 5.99x → $29.95)
A73: 5. VALOR DE PRECEDENT TRANSACTIONS (referencia) Y PESO EN LA VALUACIÓN COMBINADA
A74: Estadístico oficial | F74: Mediana de EV/EBITDA
A75: PRECEDENT TRANSACTIONS — precio de referencia (MXN por acción) | F75: =F53 -> 23.7448
A76: Rango (P25 – P75 de EV/EBITDA) — bajo | F76: =F51 -> 20.414791
A77: Rango (P25 – P75 de EV/EBITDA) — alto | F77: =F54 -> 49.187385
A78: Alternativa: media sin atípicos (MXN) | F78: =F60 -> 28.989389
A79: Peso en la valuación combinada | F79: ='Valuación Combinada'!C6 -> 0
A80: Decisión: peso 0%. La muestra es global (ninguna operación mexicana), mezcla control pleno con participaciones estratégicas, incluye una operación en dificultad y un atípico, y su dispersión es muy amplia (P25–P75 de EV/EBITDA). El EBITDA de SDC no es homogéneo (normas locales; tratamiento de arrendamientos no verificable). Se usa como referencia de mercado y método de contraste; su conclusión (precio por debajo del mercado) es coherente con el consenso de analistas, pero no se incorpora al precio objetivo.
A81: Mediana (estadístico central robusto) en lugar de la media: con n pequeño y un atípico (Profi 21.3x) la media se desplaza al alza.
A83: 6. TRIANGULACIÓN: MODELO, TRANSACCIONES Y OPINIÓN DE LOS EXPERTOS
A84: Fuente / método | C84: Precio (MXN) | D84: Potencial vs. mercado | E84: Lectura
A85: DCF (ValuFlow) | C85: ='Valuación Combinada'!B4 -> 38.340078 | D85: =C85/$C$93-1 -> 0.14516363 | E85: Valor intrínseco del modelo del equipo.
A86: Trading Comps | C86: ='Valuación Combinada'!B5 -> 33.492841 | D86: =C86/$C$93-1 -> 0.00038353807 | E86: Múltiplos de empresas comparables (CIQ).
A87: Transacciones CIQ (hoja Transacciones, media, n = 3) — histórico | C87: =Transacciones!E49 -> 40.728395 | D87: =C87/$C$93-1 -> 0.21649926 | E87: Muestra no defendible (1 de 3 en ventana); incluye prima de control.
A88: Transacciones SDC — mediana (referencia oficial) | C88: =F53 -> 23.7448 | D88: =C88/$C$93-1 -> -0.29077658 | E88: Estadístico central robusto de la muestra auditada.
A89: Transacciones SDC — media sin atípicos | C89: =F60 -> 28.989389 | D89: =C89/$C$93-1 -> -0.13412816 | E89: Excluye atípicos por RIC.
A90: Consenso de analistas (precio objetivo, S&P Capital IQ) | C90: =Comparativo!B18 -> 23.357 | D90: =C90/$C$93-1 -> -0.30235962 | E90: ="Expertos: "&Comparativo!B19&" — sesgo vendedor." -> Expertos: Venta (0 C / 1 M / 6 V) — sesgo vendedor.
A91: Valuación combinada del proyecto (DCF 50% / Comps 50%) | C91: ='Valuación Combinada'!B9 -> 35.91646 | D91: =C91/$C$93-1 -> 0.072773584 | E91: Precio objetivo del proyecto.
A92: Sensibilidad: DCF, Comps y Transacciones SDC (mediana) a ⅓ | C92: =AVERAGE(C85,C86,C88) -> 31.85924 | D92: =C92/$C$93-1 -> -0.048409804 | E92: Si se diera peso a transacciones con la nueva muestra.
A93: Precio de mercado de referencia (25-sep-2026) | C93: ='Valuación Combinada'!B10 -> 33.48
A95: 7. CONCLUSIÓN, VALUACIÓN Y RECOMENDACIÓN
A96: Umbral para COMPRAR (potencial mayor a) | C96: 0.1
A97: Umbral para VENDER (potencial menor a) | C97: -0.1
A98: Precio objetivo (valuación combinada) | C98: =C91 -> 35.91646
A99: Potencial / (baja) vs. mercado | C99: =C98/C93-1 -> 0.072773584
A100: Recomendación según el modelo | C100: =IF(C99>C96,"COMPRAR",IF(C99<C97,"VENDER","MANTENER")) -> MANTENER
A101: Recomendación de los expertos | C101: =Comparativo!B19 -> Venta (0 C / 1 M / 6 V)
A102: Rango de valor razonable — bajo (mín. de DCF, Comps y SDC sin atípicos) | C102: =MIN(C85,C86,C89) -> 28.989389
A103: Rango de valor razonable — alto | C103: =MAX(C85,C86,C89) -> 38.340078
A104: Precio objetivo de consenso de analistas | C104: =C90 -> 23.357

Sheet Contraste externo
A1: CONTRASTE EXTERNO — S&P Capital IQ, LSEG Refinitiv y modelos propios (referencias; no entran al precio oficial salvo DCF y Trading Comps)
A2: Fuente: Soriana_Reporte_Valuacion_CapitalIQ_Refinitiv.pdf (19-oct-2026). Cifras tal como se reportan; las del modelo del equipo se vinculan a este libro. Potencial calculado contra el precio de referencia de cada fila.
