Workbook

Sheet Comparativo
A4: 1. VALUACIÓN (DCF, base FY2025) | B4: Soriana | C4: Walmex | D4: Chedraui | E4: La Comer
A5: WACC | B5: =Valuación!B15 -> 0.10061577 | C5: =Valuación!B53 -> 0.12228947 | D5: =Valuación!B91 -> 0.10091294 | E5: =Valuación!B129 -> 0.12085359
A6: Crecimiento perpetuo (g) | B6: =Valuación!B16 -> 0.035 | C6: =Valuación!B54 -> 0.035 | D6: =Valuación!B92 -> 0.035 | E6: =Valuación!B130 -> 0.035
A7: FCF 2025A (flujo libre de efectivo) | B7: =Valuación!B27 -> 6761.4 | C7: =Valuación!B65 -> 40916.76 | D7: =Valuación!B103 -> 12113.9 | E7: =Valuación!B141 -> 302.92442
A8: VPN de los FCF 2026E–2030E | B8: =Valuación!B31 -> 27699.25 | C8: =Valuación!B69 -> 161517.97 | D8: =Valuación!B107 -> 50520.788 | E8: =Valuación!B145 -> 1200.1425
A9: Valor terminal (TV) al 2030 | B9: =Valuación!B33 -> 124330.71 | C9: =Valuación!B71 -> 576210.9 | D9: =Valuación!B109 -> 225920.38 | E9: =Valuación!B147 -> 4337.2847
A10: Valor presente del TV | B10: =Valuación!B34 -> 76983.872 | C10: =Valuación!B72 -> 323636.15 | D10: =Valuación!B110 -> 139698.11 | E10: =Valuación!B148 -> 2451.7349
A11: Enterprise Value (EV) | B11: =Valuación!B35 -> 104683.12 | C11: =Valuación!B73 -> 485154.12 | D11: =Valuación!B111 -> 190218.9 | E11: =Valuación!B149 -> 3651.8774
A12: Deuda total (bancaria/bursátil + arrendamientos) | B12: =-Valuación!B36 -> 23618 | C12: =-Valuación!B74 -> 80848.1 | D12: =-Valuación!B112 -> 56744.34 | E12: =-Valuación!B150 -> 2441.8
A13: Efectivo y equivalentes | B13: =Valuación!B37 -> 9295 | C13: =Valuación!B75 -> 28591.2 | D13: =Valuación!B113 -> 14640.16 | E13: =Valuación!B151 -> 2962.8
A14: Equity Value (valor para los accionistas) | B14: =Valuación!B39 -> 90360.122 | C14: =Valuación!B77 -> 432897.22 | D14: =Valuación!B115 -> 148114.72 | E14: =Valuación!B153 -> 4172.8774
A15: Valor intrínseco por acción (MXN) | B15: =Valuación!B41 -> 50.200068 | C15: =Valuación!B79 -> 24.794063 | D15: =Valuación!B117 -> 154.24532 | E15: =Valuación!B155 -> 3.9153526
A16: Precio actual en bolsa (MXN) | B16: =Valuación!B42 -> 33.1 | C16: =Valuación!B80 -> 46.6 | D16: =Valuación!B118 -> 92.94 | E16: =Valuación!B156 -> 32.08
A17: Potencial de apreciación / (baja) | B17: =Valuación!B43 -> 0.51661836 | C17: =Valuación!B81 -> -0.46793856 | D17: =Valuación!B119 -> 0.65962259 | E17: =Valuación!B157 -> -0.87795036
A18: Precio objetivo consenso de analistas (MXN) | B18: =Generales!B24 -> 23.357 | C18: 60.094 | D18: 128.933 | E18: 47.67
A19: Recomendación consenso de analistas | B19: Venta (0 C / 1 M / 6 V) | C19: Neutral (5 C / 10 M / 3 V) | D19: Neutral (3 C / 12 M / 0 V) | E19: Compra (5 C / 4 M / 0 V)
A21: 2. RAZONES FINANCIERAS – PROMEDIO DE LOS ÚLTIMOS 5 TRIMESTRES | B21: Soriana | C21: Walmex | D21: Chedraui | E21: La Comer
A22: Circulante | B22: =Razones!G7 -> 1.2541889 | C22: =Razones!G23 -> 0.9768759 | D22: =Razones!G39 -> 0.933732 | E22: =Razones!G55 -> 1.2290463
A23: Prueba ácida | B23: =Razones!G8 -> 0.35473781 | C23: =Razones!G24 -> 0.34704511 | D23: =Razones!G40 -> 0.40675641 | E23: =Razones!G56 -> 0.48041577
A24: Deuda / Activo total | B24: =Razones!G9 -> 0.45505378 | C24: =Razones!G25 -> 0.52855776 | D24: =Razones!G41 -> 0.66310269 | E24: =Razones!G57 -> 0.2578378
A25: Capitalización a largo plazo | B25: =Razones!G10 -> 0.20654207 | C25: =Razones!G26 -> 0.18040972 | D25: =Razones!G42 -> 0.38012988 | E25: =Razones!G58 -> 0.064547002
A26: Cobertura de intereses | B26: =Razones!G11 -> 2.8984196 | C26: =Razones!G27 -> 6.6453315 | D26: =Razones!G43 -> 4.1504186 | E26: =Razones!G59 -> 11.844746
A27: Rotación del inventario (trimestral) | B27: =Razones!G12 -> 0.95612726 | C27: =Razones!G28 -> 1.7752133 | D27: =Razones!G44 -> 2.3833504 | E27: =Razones!G60 -> 1.3488695
A28: Rotación del inventario en días | B28: =Razones!G13 -> 96.032436 | C28: =Razones!G29 -> 51.658042 | D28: =Razones!G45 -> 38.380088 | E28: =Razones!G61 -> 67.850681
A29: Rotación del activo total (trimestral) | B29: =Razones!G14 -> 0.28166407 | C29: =Razones!G30 -> 0.51157675 | D29: =Razones!G46 -> 0.46365336 | E29: =Razones!G62 -> 0.2764494
A30: Margen bruto | B30: =Razones!G15 -> 0.24566153 | C30: =Razones!G31 -> 0.24235015 | D30: =Razones!G47 -> 0.23527548 | E30: =Razones!G63 -> 0.29672069
A31: Margen neto | B31: =Razones!G16 -> 0.020605935 | C31: =Razones!G32 -> 0.048260538 | D31: =Razones!G48 -> 0.023418786 | E31: =Razones!G64 -> 0.05488254
A32: ROA (trimestral) | B32: =Razones!G17 -> 0.005843019 | C32: =Razones!G33 -> 0.024728482 | D32: =Razones!G49 -> 0.010867202 | E32: =Razones!G65 -> 0.015156869
A33: ROE (trimestral) | B33: =Razones!G18 -> 0.010703389 | C33: =Razones!G34 -> 0.052476921 | D33: =Razones!G50 -> 0.032240332 | E33: =Razones!G66 -> 0.02043965
A34: ROI (trimestral) | B34: =Razones!G19 -> 0.012031436 | C34: =Razones!G35 -> 0.042432022 | D34: =Razones!G51 -> 0.024290294 | E34: =Razones!G67 -> 0.017861415
A36: 3. RAZONES FINANCIERAS ANUALES FY2025 (incluye Chedraui) | B36: Soriana | C36: Walmex | D36: Chedraui | E36: La Comer
A37: Circulante | B37: =IFERROR(Datos!G19/Datos!G21,"n.d.") -> 1.2373849 | C37: =IFERROR(Datos!G45/Datos!G47,"n.d.") -> 0.96696082 | D37: =IFERROR(Datos!G71/Datos!G73,"n.d.") -> 0.92079667 | E37: =IFERROR(Datos!G97/Datos!G99,"n.d.") -> 1.2070372
A38: Prueba ácida | B38: =IFERROR((Datos!G19-Datos!G18)/Datos!G21,"n.d.") -> 0.414238 | C38: =IFERROR((Datos!G45-Datos!G44)/Datos!G47,"n.d.") -> 0.33384163 | D38: =IFERROR((Datos!G71-Datos!G70)/Datos!G73,"n.d.") -> 0.43735523 | E38: =IFERROR((Datos!G97-Datos!G96)/Datos!G99,"n.d.") -> 0.50008921
A39: Deuda / Activo total | B39: =IFERROR(Datos!G23/Datos!G20,"n.d.") -> 0.45697843 | C39: =IFERROR(Datos!G49/Datos!G46,"n.d.") -> 0.52434323 | D39: =IFERROR(Datos!G75/Datos!G72,"n.d.") -> 0.67356639 | E39: =IFERROR(Datos!G101/Datos!G98,"n.d.") -> 0.2544825
A40: Capitalización a largo plazo | B40: =IFERROR(Datos!G22/Datos!G20,"n.d.") -> 0.2056294 | C40: =IFERROR(Datos!G48/Datos!G46,"n.d.") -> 0.1816704 | D40: =IFERROR(Datos!G74/Datos!G72,"n.d.") -> 0.37134872 | E40: =IFERROR(Datos!G100/Datos!G98,"n.d.") -> 0.06423617
A41: Cobertura de intereses | B41: =IFERROR(Datos!G9/Datos!G10,"n.d.") -> 2.4567339 | C41: =IFERROR(Datos!G35/Datos!G36,"n.d.") -> 6.8465638 | D41: =IFERROR(Datos!G61/Datos!G62,"n.d.") -> 3.9247028 | E41: =IFERROR(Datos!G87/Datos!G88,"n.d.") -> 13.400737
A42: Rotación del inventario (anual) | B42: =IFERROR(Datos!G7/Datos!G18,"n.d.") -> 4.1740854 | C42: =IFERROR(Datos!G33/Datos!G44,"n.d.") -> 7.1325601 | D42: =IFERROR(Datos!G59/Datos!G70,"n.d.") -> 9.7102302 | E42: =IFERROR(Datos!G85/Datos!G96,"n.d.") -> 5.6268631
A43: Rotación del inventario en días (365) | B43: =IFERROR(365*Datos!G18/Datos!G7,"n.d.") -> 87.444305 | C43: =IFERROR(365*Datos!G44/Datos!G33,"n.d.") -> 51.173772 | D43: =IFERROR(365*Datos!G70/Datos!G59,"n.d.") -> 37.589222 | E43: =IFERROR(365*Datos!G96/Datos!G85,"n.d.") -> 64.867404
A44: Rotación del activo total (anual) | B44: =IFERROR(Datos!G6/Datos!G20,"n.d.") -> 1.1376395 | C44: =IFERROR(Datos!G32/Datos!G46,"n.d.") -> 2.0425044 | D44: =IFERROR(Datos!G58/Datos!G72,"n.d.") -> 1.8415047 | E44: =IFERROR(Datos!G84/Datos!G98,"n.d.") -> 1.0755432
A45: Margen bruto | B45: =IFERROR(Datos!G8/Datos!G6,"n.d.") -> 0.24090359 | C45: =IFERROR(Datos!G34/Datos!G32,"n.d.") -> 0.24238672 | D45: =IFERROR(Datos!G60/Datos!G58,"n.d.") -> 0.22959264 | E45: =IFERROR(Datos!G86/Datos!G84,"n.d.") -> 0.29637336
A46: Margen neto | B46: =IFERROR(Datos!G13/Datos!G6,"n.d.") -> 0.018781511 | C46: =IFERROR(Datos!G39/Datos!G32,"n.d.") -> 0.049318707 | D46: =IFERROR(Datos!G65/Datos!G58,"n.d.") -> 0.022417013 | E46: =IFERROR(Datos!G91/Datos!G84,"n.d.") -> 0.05648874
A47: ROA (anual) | B47: =IFERROR(Datos!G13/Datos!G20,"n.d.") -> 0.02136659 | C47: =IFERROR(Datos!G39/Datos!G46,"n.d.") -> 0.10073368 | D47: =IFERROR(Datos!G65/Datos!G72,"n.d.") -> 0.041281034 | E47: =IFERROR(Datos!G91/Datos!G98,"n.d.") -> 0.060756079
A48: ROE (anual) | B48: =IFERROR(Datos!G13/Datos!G24,"n.d.") -> 0.03934759 | C48: =IFERROR(Datos!G39/Datos!G50,"n.d.") -> 0.21177807 | D48: =IFERROR(Datos!G65/Datos!G76,"n.d.") -> 0.12646073 | E48: =IFERROR(Datos!G91/Datos!G102,"n.d.") -> 0.081495175
A49: ROI (anual) | B49: =IFERROR(Datos!G9*(1-WACC!$B$10)/(Datos!G24+Datos!G29),"n.d.") -> 0.048790032 | C49: =IFERROR(Datos!G35*(1-WACC!$B$10)/(Datos!G50+Datos!G55),"n.d.") -> 0.17364337 | D49: =IFERROR(Datos!G61*(1-WACC!$B$10)/(Datos!G76+Datos!G81),"n.d.") -> 0.096876335 | E49: =IFERROR(Datos!G87*(1-WACC!$B$10)/(Datos!G102+Datos!G107),"n.d.") -> 0.070505439

Sheet Generales
A4: 1. INFORMACIÓN GENERAL DE LA EMPRESA | B4: Dato
A5: Clave de cotización | B5: SORIANA B (BMV, cotiza desde 1987)
A6: Fundación | B6: 1968, Torreón, Coahuila
A7: Sede corporativa | B7: Monterrey, Nuevo León
A8: Giro | B8: Tiendas de autoservicio y clubes de membresía (multiformato)
A9: Tiendas en operación (2T26) | B9: 812
A10: Colaboradores (jun-2026) | B10: 82064
A11: Acciones en circulación (millones) | B11: =WACC!B17 -> 1800
A12: Capitalización de mercado a precio actual (mdp) | B12: =WACC!B18 -> 59580
A14: 2. NOTICIAS Y ANÁLISIS RECIENTES | B14: Fecha
A15: Resultados 2T26: menos ventas, más utilidad | B15: 31-jul-2026
A16: Cierre de 20 tiendas en 2026 | B16: 26-ago-2026
A17: Reducción de plantilla y automatización | B17: 2-sep-2026
A18: Plan de inversión 2S26 | B18: sep-2026
A19: Sector: Walmart, Soriana y Chedraui sufren por ingresos e inflación | B19: 2026
A21: 3. CALIFICACIÓN Y CONSENSO DE ANALISTAS | B21: Dato
A22: Calificación crediticia (HR Ratings) | B22: HR+1 (corto plazo)
A23: Consenso de analistas | B23: Venta
A24: Precio objetivo promedio 12 meses (MXN) | B24: 23.357
A26: 4. ANÁLISIS FUNDAMENTAL – RESUMEN FINANCIERO FY2025 (mdp) | B26: Valor
A27: Ingresos totales | B27: =Datos!G6 -> 177515
A28: Utilidad bruta | B28: =Datos!G8 -> 42764
A29: Utilidad de operación (EBIT) | B29: =Datos!G9 -> 7552
A30: Utilidad neta consolidada | B30: =Datos!G13 -> 3334
A31: Margen bruto | B31: =Datos!G8/Datos!G6 -> 0.24090359
A32: Margen de operación | B32: =Datos!G9/Datos!G6 -> 0.042542884
A33: Margen neto | B33: =Datos!G13/Datos!G6 -> 0.018781511
A35: 5. CUENTA DE RESULTADOS – ÚLTIMO TRIMESTRE (2T26 vs 2T25, mdp) | B35: 2T26
A36: Ingresos totales | B36: =Datos!F6 -> 43559
A37: Costo de ventas | B37: =Datos!F7 -> 32919
A38: Utilidad bruta | B38: =Datos!F8 -> 10640
A39: Utilidad de operación | B39: =Datos!F9 -> 1855
A40: Gastos financieros | B40: =Datos!F10 -> 582
A41: Utilidad neta | B41: =Datos!F13 -> 1090
A43: 6. BALANCE (cierre 2025 vs 1T26, mdp) | B43: Dic-2025
A44: Activo total | B44: =Datos!G20 -> 156038
A45: Pasivo total | B45: =Datos!G23 -> 71306
A46: Capital contable | B46: =Datos!G24 -> 84732
A47: Deuda bancaria y bursátil | B47: =Datos!G25+Datos!G26 -> 11500
A48: Efectivo | B48: =Datos!G17 -> 9295
A50: 7. FLUJOS DE EFECTIVO FY2025 (mdp) | B50: Valor
A51: Flujo neto de operación (CFO) | B51: =Datos!G15 -> 13738
A52: Capex | B52: =Datos!G16 -> 2867
A53: Flujo libre (CFO - Capex) | B53: =B51-B52 -> 10871
A55: 8. ANÁLISIS FUNDAMENTAL – RATIOS DE MERCADO | B55: Valor
A56: P/U (precio / utilidad por acción) | B56: =WACC!B13/(Datos!G13/WACC!B17) -> 17.870426
A57: Valor en libros por acción (MXN) | B57: =Datos!G24/WACC!B17 -> 47.073333
A58: P/VL (precio / valor en libros) | B58: =WACC!B13/B57 -> 0.70315819
A59: ROE anual FY2025 | B59: =Comparativo!B48 -> 0.03934759
A61: 9. DIVIDENDOS | B61: Valor
A62: Último dividendo por acción (MXN) | B62: 0.5556
A63: Rendimiento por dividendo a precio actual | B63: =B62/WACC!B13 -> 0.016785498
A65: 10. REPORTE – PUNTOS CLAVE 2T26
A66: Ventas mismas tiendas 2T26 | B66: -4.5%
A67: Margen bruto 2T26 | B67: =Datos!F8/Datos!F6 -> 0.2442664
A68: Costo financiero neto 2T26 (mdp) | B68: 477
A69: Deuda neta bancaria y bursátil al 2T26 (mdp) | B69: =Datos!F25+Datos!F26-Datos!F17 -> 4624.616
A70: Capex acumulado 1S26 (mdp) | B70: =Datos!E16+Datos!F16 -> 1410.9
A72: 11. PREVISIÓN | B72: Valor
A73: Próximo reporte trimestral (3T26) | B73: 23-oct-2026
A74: Precio objetivo consenso vs precio actual | B74: =B24/WACC!B13-1 -> -0.29435045
A75: Proyección de ingresos 2027 HR Ratings (mdp) | B75: 196480
A77: 12. ANÁLISIS TÉCNICO | B77: Valor
A78: Precio de cierre (MXN) | B78: =WACC!B13 -> 33.1
A79: Rango de 52 semanas (MXN) | B79: 23.90 – 42.70
A80: Variación 1 año | B80: 0.2127
A81: Señal técnica resumen (diaria, semanal y mensual) | B81: Compra fuerte
A82: RSI (14) | B82: 75
A83: MACD (12,26) | B83: 1.154
A84: Media móvil 50 días (MXN) | B84: 29.68
A85: Media móvil 200 días (MXN) | B85: 29.71
A88: 13. COMPARATIVO BURSÁTIL DEL SECTOR | B88: Soriana | C88: Walmex | D88: Chedraui | E88: La Comer
A89: Precio actual (MXN) | B89: =WACC!B13 -> 33.1 | C89: =WACC!C13 -> 46.6 | D89: =WACC!D13 -> 92.94 | E89: =WACC!E13 -> 32.08
A90: P/U | B90: =B56 -> 17.870426 | C90: =WACC!C13/(Datos!G39/WACC!C17) -> 16.308102 | D90: =WACC!D13/(Datos!G65/WACC!D17) -> 13.481171 | E90: =WACC!E13/(Datos!G91/WACC!E17) -> 12.735034
A91: Rendimiento por dividendo | B91: =B63 -> 0.016785498 | C91: 0.0253 | D91: 0.0249 | E91: 0.0088
A92: Variación 1 año | B92: =B80 -> 0.2127 | C92: -0.1686 | D92: -0.4125 | E92: -0.2051
A93: Beta de regresión semanal (Soriana: hoja Beta Regresión; resto: referencia) | B93: =IF('Beta Regresión'!B7>2,'Beta Regresión'!B30,"n.d. (pega datos)") -> 0.21783791 | C93: 0.03 | D93: -0.06 | E93: 0.17
A94: Señal técnica resumen (diaria) | B94: Compra fuerte | C94: Compra fuerte | D94: Compra fuerte | E94: Compra fuerte
A95: RSI (14) | B95: =B82 -> 75 | C95: 41.07 | D95: 60.23 | E95: 40.03
A96: Consenso de analistas | B96: Venta | C96: Neutral | D96: Neutral | E96: Compra
A97: Precio objetivo consenso (MXN) | B97: =Comparativo!B18 -> 23.357 | C97: =Comparativo!C18 -> 60.094 | D97: =Comparativo!D18 -> 128.933 | E97: =Comparativo!E18 -> 47.67
A98: Calificación crediticia | B98: HR+1 (HR Ratings, CP) | C98: n.d. | D98: AAA(mex) Fitch, perspectiva estable | E98: n.d.

Sheet Datos
A5: ORGANIZACIÓN SORIANA (SORIANA B) | B5: 2T25 | C5: 3T25 | D5: 4T25 | E5: 1T26 | F5: 2T26 | G5: FY2025
A6: Ingresos totales | B6: 45810 | C6: 42683 | D6: 47592 | E6: 40444 | F6: 43559 | G6: 177515
A7: Costo de ventas | B7: 34856 | C7: 31998 | D7: 35795 | E7: 30466 | F7: 32919 | G7: 134752
A8: Utilidad bruta | B8: 10954 | C8: 10685 | D8: 11797 | E8: 9978 | F8: 10640 | G8: 42764
A9: Utilidad de operación (EBIT) | B9: 1909 | C9: 1468 | D9: 2486 | E9: 1822 | F9: 1855 | G9: 7552
A10: Gastos financieros (intereses) | B10: 829 | C10: 786 | D10: 616 | E10: 588 | F10: 582 | G10: 3074
A11: Utilidad antes de impuestos | B11: 1203 | C11: 764 | D11: 1763 | E11: 1326 | F11: 1372 | G11: 4766
A12: Impuestos a la utilidad | B12: 461 | C12: 179 | D12: 455 | E12: 492 | F12: 282 | G12: 1433
A13: Utilidad neta consolidada | B13: 743 | C13: 584 | D13: 1308 | E13: 834 | F13: 1090 | G13: 3334
A14: Depreciación y amortización | B14: 1105.905 | C14: 1049.349 | D14: 1051 | E14: 1048.889 | F14: 1030.633 | G14: 4342
A15: Flujo neto de operación (CFO) | B15: 4013.113 | C15: -205.9 | D15: 13017 | E15: -3565.6 | F15: 3916.003 | G15: 13738
A16: Capex (inmuebles, equipo e intangibles) | B16: =SUM(B110:B112) -> 663.2 | C16: =SUM(C110:C112) -> 775.2 | D16: =SUM(D110:D112) -> 816 | E16: =SUM(E110:E112) -> 501 | F16: =SUM(F110:F112) -> 909.9 | G16: 2867
A17: Efectivo y equivalentes | B17: 7540 | C17: 5798 | D17: 9295 | E17: 4589 | F17: 6875.384 | G17: =D17 -> 9295
A18: Inventarios | B18: 37421 | C18: 36394 | D18: 32283 | E18: 32635 | F18: 35486.661 | G18: =D18 -> 32283
A19: Activo circulante | B19: 52131 | C19: 49767 | D19: 48529 | E19: 43562 | F19: 49259.847 | G19: =D19 -> 48529
A20: Activo total | B20: 159842 | C20: 157502 | D20: 156038 | E20: 150941 | F20: =F23+F24 -> 156813 | G20: =D20 -> 156038
A21: Pasivo circulante | B21: 41065 | C21: 38190 | D21: 39219 | E21: 33850 | F21: 41957.933 | G21: =D21 -> 39219
A22: Pasivo a largo plazo | B22: 34801 | C22: 34753 | D22: 32086 | E22: 31527 | F22: =F23-F21 -> 28201.067 | G22: =D22 -> 32086
A23: Pasivo total | B23: 75866 | C23: 72943 | D23: 71306 | E23: 65377 | F23: 70159 | G23: =D23 -> 71306
A24: Capital contable | B24: 83976 | C24: 84559 | D24: 84732 | E24: 85564 | F24: 86654 | G24: =D24 -> 84732
A25: Deuda bursátil y bancaria CP | B25: 6627 | C25: 6553 | D25: 3000 | E25: 3000 | F25: 6500 | G25: =D25 -> 3000
A26: Deuda bursátil y bancaria LP | B26: 11500 | C26: 11500 | D26: 8500 | E26: 8500 | F26: 5000 | G26: =D26 -> 8500
A27: Pasivo por arrendamiento CP | B27: 638 | C27: 659 | D27: 676 | E27: 683 | F27: 639.968 | G27: =D27 -> 676
A28: Pasivo por arrendamiento LP | B28: 11389 | C28: 11506 | D28: 11442 | E28: 11540 | F28: 11580.62 | G28: =D28 -> 11442
A29: Deuda total (financiera + arrendamientos) | B29: =IF(COUNT(B25:B28)=4,SUM(B25:B28),"n.d.") -> 30154 | C29: =IF(COUNT(C25:C28)=4,SUM(C25:C28),"n.d.") -> 30218 | D29: =IF(COUNT(D25:D28)=4,SUM(D25:D28),"n.d.") -> 23618 | E29: =IF(COUNT(E25:E28)=4,SUM(E25:E28),"n.d.") -> 23723 | F29: =IF(COUNT(F25:F28)=4,SUM(F25:F28),"n.d.") -> 23720.588 | G29: =IF(COUNT(G25:G28)=4,SUM(G25:G28),"n.d.") -> 23618
A31: WALMART DE MÉXICO (WALMEX) | B31: 2T25 | C31: 3T25 | D31: 4T25 | E31: 1T26 | F31: 2T26 | G31: FY2025
A32: Ingresos totales | B32: 246253.8 | C32: 241520.2 | D32: 282849.3 | E32: 245018.5 | F32: 250947.8 | G32: 1011597.9
A33: Costo de ventas | B33: 186848.1 | C33: 181746.3 | D33: 214905.4 | E33: 185425.3 | F33: 190822.8 | G33: 766400
A34: Utilidad bruta | B34: 59405.7 | C34: 59773.8 | D34: 67943.9 | E34: 59593.2 | F34: 60125 | G34: 245197.9
A35: Utilidad de operación (EBIT) | B35: 17267.1 | C35: 19020.8 | D35: 23317 | E35: 18471.6 | F35: 17019.7 | G35: 78493.8
A36: Gastos financieros (intereses) | B36: 2646.3 | C36: 3223.3 | D36: 2795.1 | E36: 2895.6 | F36: 2799.6 | G36: 11464.7
A37: Utilidad antes de impuestos | B37: 15076.8 | C37: 16328 | D37: 21053.3 | E37: 16176.4 | F37: 14754.6 | G37: 68876.6
A38: Impuestos a la utilidad | B38: 3849.9 | C38: 4580.7 | D38: 6453.5 | E38: 3676.9 | F38: 3602.2 | G38: 18985.9
A39: Utilidad neta consolidada | B39: 11226.9 | C39: 11747.3 | D39: 14599.8 | E39: 12499.6 | F39: 11152.4 | G39: 49890.7
A40: Depreciación y amortización | B40: 6227.732 | C40: 6245.37 | D40: 6277.929 | E40: 6506.919 | F40: 6620.741 | G40: 24953.1
A41: Flujo neto de operación (CFO) | B41: 21549.377 | C41: 22017.152 | D41: 43314.63 | E41: 4955.647 | F41: 18326.104 | G41: 82437.7
A42: Capex (inmuebles, equipo e intangibles) | B42: =SUM(B113:B115) -> 7989.7 | C42: =SUM(C113:C115) -> 11746.3 | D42: =SUM(D113:D115) -> 15831.8 | E42: =SUM(E113:E115) -> 2436.5 | F42: =SUM(F113:F115) -> 9264.9 | G42: 38982
A43: Efectivo y equivalentes | B43: 32443.8 | C43: 35181.7 | D43: 28591.2 | E43: 28085.1 | F43: 30118.3 | G43: =D43 -> 28591.2
A44: Inventarios | B44: 106742.4 | C44: 113238.4 | D44: 107450.9 | E44: 106202 | F44: 107528.9 | G44: =D44 -> 107450.9
A45: Activo circulante | B45: 166663.9 | C45: 176974.1 | D45: 164109.4 | E45: 163317.9 | F45: 168653.5 | G45: =D45 -> 164109.4
A46: Activo total | B46: 480957.5 | C46: 497334.5 | D46: 495273.3 | E46: 496840.7 | F46: 505946.6 | G46: =D46 -> 495273.3
A47: Pasivo circulante | B47: 177161.4 | C47: 186356.5 | D47: 169716.7 | E47: 153660.1 | F47: 174921.4 | G47: =D47 -> 169716.7
A48: Pasivo a largo plazo | B48: 86252.9 | C48: 87538.9 | D48: 89976.5 | E48: 90611.7 | F48: 92411.4 | G48: =D48 -> 89976.5
A49: Pasivo total | B49: 263414.3 | C49: 273895.4 | D49: 259693.2 | E49: 244271.8 | F49: 267332.8 | G49: =D49 -> 259693.2
A50: Capital contable | B50: 217543.2 | C50: 223439.1 | D50: 235580.1 | E50: 252568.9 | F50: 238613.8 | G50: =D50 -> 235580.1
A51: Deuda bursátil y bancaria CP | B51: 0 | C51: 0 | D51: 0 | E51: 0 | F51: 0 | G51: =D51 -> 0
A52: Deuda bursátil y bancaria LP | B52: 0 | C52: 0 | D52: 0 | E52: 0 | F52: 0 | G52: =D52 -> 0
A53: Pasivo por arrendamiento CP | B53: 4917.5 | C53: 4981.5 | D53: 5186.9 | E53: 5317.6 | F53: 5495.2 | G53: =D53 -> 5186.9
A54: Pasivo por arrendamiento LP | B54: 73863 | C54: 74013.7 | D54: 75661.2 | E54: 75952.9 | F54: 77602.9 | G54: =D54 -> 75661.2
A55: Deuda total (financiera + arrendamientos) | B55: =IF(COUNT(B51:B54)=4,SUM(B51:B54),"n.d.") -> 78780.5 | C55: =IF(COUNT(C51:C54)=4,SUM(C51:C54),"n.d.") -> 78995.2 | D55: =IF(COUNT(D51:D54)=4,SUM(D51:D54),"n.d.") -> 80848.1 | E55: =IF(COUNT(E51:E54)=4,SUM(E51:E54),"n.d.") -> 81270.5 | F55: =IF(COUNT(F51:F54)=4,SUM(F51:F54),"n.d.") -> 83098.1 | G55: =IF(COUNT(G51:G54)=4,SUM(G51:G54),"n.d.") -> 80848.1
A57: GRUPO COMERCIAL CHEDRAUI (CHDRAUI B) | B57: 2T25 | C57: 3T25 | D57: 4T25 | E57: 1T26 | F57: 2T26 | G57: FY2025 | I57: Aux. FY2025
A58: Ingresos totales | B58: 73883.849 | C58: 71768.073 | D58: 75221.137 | E58: 69795.808 | F58: 71034.917 | G58: 295313.65
A59: Costo de ventas | B59: 56049.956 | C59: 54122.158 | D59: 60335.176 | E59: 52843.176 | F59: 53394.045 | G59: 227511.81
A60: Utilidad bruta | B60: 17833.893 | C60: 17645.915 | D60: 14885.961 | E60: 16952.632 | F60: 17640.872 | G60: 67801.84
A61: Utilidad de operación (EBIT) | B61: 4247.997 | C61: 3745.26 | D61: 3402.984 | E61: 3680.616 | F61: 4016.894 | G61: 15097.9
A62: Gastos financieros (intereses) | B62: 880.6 | C62: 944.2 | D62: 1003.1 | E62: 904.7 | F62: 892.5 | G62: 3846.89
A63: Utilidad antes de impuestos | B63: 2986.855 | C63: 2417.756 | D63: 1813.805 | E63: 2306.498 | F63: 2653.783 | G63: 9508.62
A64: Impuestos a la utilidad | B64: 924.533 | C64: 771.393 | D64: 469.642 | E64: 723.238 | F64: 829.095 | G64: 2888.58
A65: Utilidad neta consolidada | B65: 2062.322 | C65: 1646.363 | D65: 1344.163 | E65: 1583.26 | F65: 1824.688 | G65: 6620.05
A66: Depreciación y amortización | B66: 2303.668 | C66: 2297.228 | D66: 2308.71 | E66: 2258.954 | F66: 2312.731 | G66: 9293.25
A67: Flujo neto de operación (CFO) | B67: 5617.816 | C67: 4366.019 | D67: 10197.404 | E67: -756.9 | F67: 5978.777 | G67: 18240.86
A68: Capex (inmuebles, equipo e intangibles) | B68: =SUM(B116:B118) -> 2185.9 | C68: =SUM(C116:C118) -> 2286.1 | D68: =SUM(D116:D118) -> 2688.875 | E68: =SUM(E116:E118) -> 2195.6 | F68: =SUM(F116:F118) -> 2859.1 | G68: =I68 -> 7747.88 | I68: 7747.88 | J68: Inversión neta (−flujo de inversión FY2025), proxy de capex
A69: Efectivo y equivalentes | B69: 9740.315 | C69: 9638.014 | D69: 14640.162 | E69: 10487.937 | F69: 8499.778 | G69: 14640.16
A70: Inventarios | B70: 22914.705 | C70: 23527.624 | D70: 23430.115 | E70: 23660.893 | F70: 22606.468 | G70: =D70 -> 23430.115
A71: Activo circulante | B71: 39608.185 | C71: 41642.553 | D71: 44626.647 | E71: 41294.339 | F71: 38968.064 | G71: 44626.65
A72: Activo total | B72: 154895.84 | C72: 155620.7 | D72: 160365.41 | E72: 156233.2 | F72: 152993.19 | G72: 160365.41
A73: Pasivo circulante | B73: 42247.697 | C73: 43507.303 | D73: 48465.257 | E73: 43264.981 | F73: 43358.105 | G73: 48465.26
A74: Pasivo a largo plazo | B74: =B75-B73 -> 61262.859 | C74: =C75-C73 -> 60415.588 | D74: =D75-D73 -> 59551.489 | E74: =E75-E73 -> 58979.77 | F74: =F75-F73 -> 56310.095 | G74: =G75-G73 -> 59551.49
A75: Pasivo total | B75: 103510.56 | C75: 103922.89 | D75: 108016.75 | E75: 102244.75 | F75: 99668.2 | G75: 108016.75
A76: Capital contable | B76: 51385.283 | C76: 51697.81 | D76: 52348.664 | E76: 53988.454 | F76: 53324.988 | G76: 52348.66
A77: Deuda bursátil y bancaria CP | B77: 1055.054 | C77: 1541.907 | D77: 530.018 | E77: 705.319 | F77: 1087.08 | G77: =D77 -> 530.018
A78: Deuda bursátil y bancaria LP | B78: 7557.12 | C78: 7353.001 | D78: 7186.68 | E78: 7226.68 | F78: 5241 | G78: =D78 -> 7186.68
A79: Pasivo por arrendamiento CP | B79: 2674.355 | C79: 2626.869 | D79: 2925.974 | E79: 3014.648 | F79: 3015.621 | G79: =D79 -> 2925.974
A80: Pasivo por arrendamiento LP | B80: 48473.083 | C80: 47033.289 | D80: 46631.683 | E80: 46405.889 | F80: 45276.747 | G80: =D80 -> 46631.683
A81: Deuda total (financiera + arrendamientos) | B81: =IF(COUNT(B77:B80)=4,SUM(B77:B80),"n.d.") -> 59759.612 | C81: =IF(COUNT(C77:C80)=4,SUM(C77:C80),"n.d.") -> 58555.066 | D81: =IF(COUNT(D77:D80)=4,SUM(D77:D80),"n.d.") -> 57274.355 | E81: =IF(COUNT(E77:E80)=4,SUM(E77:E80),"n.d.") -> 57352.536 | F81: =IF(COUNT(F77:F80)=4,SUM(F77:F80),"n.d.") -> 54620.448 | G81: 56744.34
A83: LA COMER (LACOMER UBC) | B83: 2T25 | C83: 3T25 | D83: 4T25 | E83: 1T26 | F83: 2T26 | G83: FY2025 | I83: 9M2025
A84: Ingresos totales | B84: 12232.6 | C84: 11813.2 | D84: =G84-I84 -> 12404.39 | E84: 12006.5 | F84: 12933.1 | G84: 47526.64 | I84: 35122.25
A85: Costo de ventas | B85: 8718.1 | C85: 8306.7 | D85: =G85-I85 -> 8694.29 | E85: 8328.1 | F85: 9130.7 | G85: 33441.01 | I85: 24746.72
A86: Utilidad bruta | B86: 3514.5 | C86: 3506.5 | D86: =G86-I86 -> 3710.1 | E86: 3678.4 | F86: 3802.4 | G86: 14085.63 | I86: 10375.53
A87: Utilidad de operación (EBIT) | B87: 1026.3 | C87: 839 | D87: =G87-I87 -> 712.57 | E87: 1001.4 | F87: 932.2 | G87: 3564.06 | I87: 2851.49
A88: Gastos financieros (intereses) | B88: 90.2 | C88: 76.7 | D88: 64.9 | E88: 73.3 | F88: 76 | G88: 265.96 | I88: 235.52
A89: Utilidad antes de impuestos | B89: 1003.4 | C89: 817 | D89: =G89-I89 -> 697.65 | E89: 992.7 | F89: 893.8 | G89: 3507.62 | I89: 2809.97
A90: Impuestos a la utilidad | B90: 200.4 | C90: 176.1 | D90: =G90-I90 -> 191.44 | E90: 250.5 | F90: 222.6 | G90: 822.9 | I90: 631.46
A91: Utilidad neta consolidada | B91: 803 | C91: 640.9 | D91: =G91-I91 -> 506.21 | E91: 742.2 | F91: 671.1 | G91: 2684.72 | I91: 2178.51
A92: Depreciación y amortización | B92: 407.835 | C92: 411.717 | D92: 397.26 | E92: 386.412 | F92: 399.125 | G92: =I92/I84*G84 -> 1650.7548 | I92: 1219.91
A93: Flujo neto de operación (CFO) | B93: 1576.03 | C93: 468.589 | D93: 1924.595 | E93: 583.825 | F93: 988.725 | G93: =744.022+B93+C93+D93 -> 4713.236 | I93: 2788.64
A94: Capex (inmuebles, equipo e intangibles) | B94: =SUM(B119:B121) -> 1484.5 | C94: =SUM(C119:C121) -> 912.2 | D94: =SUM(D119:D121) -> 1480.1 | E94: =SUM(E119:E121) -> 606.8 | F94: =SUM(F119:F121) -> 1670.1 | G94: =I94/I84*G84 -> 3842.6724 | I94: 2839.74
A95: Efectivo y equivalentes | B95: 3071.774 | C95: 2615.8 | D95: 2962.8 | E95: 2813 | F95: 1665.7 | G95: =D95 -> 2962.8
A96: Inventarios | B96: 6630.422 | C96: 6020.2 | D96: 5943.1 | E96: 6182.4 | F96: 7365.3 | G96: =D96 -> 5943.1
A97: Activo circulante | B97: 11202.654 | C97: 10026.3 | D97: 10147.2 | E97: 10422.3 | F97: 10810.2 | G97: =D97 -> 10147.2
A98: Activo total | B98: 43616.194 | C98: 42970.2 | D98: 44188.5 | E98: 44754.6 | F98: 46541.8 | G98: =D98 -> 44188.5
A99: Pasivo circulante | B99: 9031.024 | C99: 7608.5 | D99: 8406.7 | E99: 8294 | F99: 9623.2 | G99: =D99 -> 8406.7
A100: Pasivo a largo plazo | B100: =B101-B99 -> 2754.765 | C100: 2852.9 | D100: 2838.5 | E100: 2853 | F100: 3034.5 | G100: =D100 -> 2838.5
A101: Pasivo total | B101: 11785.789 | C101: 10461.4 | D101: 11245.2 | E101: 11147 | F101: 12657.7 | G101: =D101 -> 11245.2
A102: Capital contable | B102: 31830.405 | C102: 32508.8 | D102: 32943.3 | E102: 33607.6 | F102: 33884.1 | G102: =D102 -> 32943.3
A103: Deuda bursátil y bancaria CP | B103: 0 | C103: 0 | D103: 0 | E103: 0 | F103: 0 | G103: =D103 -> 0
A104: Deuda bursátil y bancaria LP | B104: 0 | C104: 0 | D104: 0 | E104: 0 | F104: 0 | G104: =D104 -> 0
A105: Pasivo por arrendamiento CP | B105: 93.389 | C105: 92.3 | D105: 98.3 | E105: 99.7 | F105: 105.6 | G105: =D105 -> 98.3
A106: Pasivo por arrendamiento LP | B106: 2260.347 | C106: 2272.5 | D106: 2343.5 | E106: 2344.7 | F106: 2443.7 | G106: =D106 -> 2343.5
A107: Deuda total (financiera + arrendamientos) | B107: =IF(COUNT(B103:B106)=4,SUM(B103:B106),"n.d.") -> 2353.736 | C107: =IF(COUNT(C103:C106)=4,SUM(C103:C106),"n.d.") -> 2364.8 | D107: =IF(COUNT(D103:D106)=4,SUM(D103:D106),"n.d.") -> 2441.8 | E107: =IF(COUNT(E103:E106)=4,SUM(E103:E106),"n.d.") -> 2444.4 | F107: =IF(COUNT(F103:F106)=4,SUM(F103:F106),"n.d.") -> 2549.3 | G107: =IF(COUNT(G103:G106)=4,SUM(G103:G106),"n.d.") -> 2441.8
...

Sheet Base de Datos
A1: BASE DE DATOS DE MERCADO
B3: =COUNT(Rendimientos!$AD$10:$AD$509) -> 63 | C3: Última fecha | D3: =IF(COUNT(Rendimientos!$AD$10:$AD$509)=0,"sin datos",MAX(Rendimientos!$AD$10:$AD$509)) -> 46302 | J3: =COUNT(Rendimientos!$AF$10:$AF$509) -> 73 | K3: Última fecha | L3: =IF(COUNT(Rendimientos!$AF$10:$AF$509)=0,"sin datos",MAX(Rendimientos!$AF$10:$AF$509)) -> 46307 | R3: =COUNT(Rendimientos!$AH$10:$AH$409) -> 259 | S3: Última fecha | T3: =IF(COUNT(Rendimientos!$AH$10:$AH$409)=0,"sin datos",MAX(Rendimientos!$AH$10:$AH$409)) -> 46299 | Z3: =COUNT(Rendimientos!$AJ$10:$AJ$409) -> 261 | AA3: Última fecha | AB3: =IF(COUNT(Rendimientos!$AJ$10:$AJ$409)=0,"sin datos",MAX(Rendimientos!$AJ$10:$AJ$409)) -> 46306 | AG3: Obs. válidas | AH3: =COUNT(Inflación!$CH$10:$CH$309) -> 113 | AI3: Última quincena | AJ3: =MAX(Inflación!$CH$10:$CH$309) -> 46266
A4: SORIANA DIARIO | I4: IPC DIARIO | Q4: SORIANA SEMANAL | Y4: IPC SEMANAL | AG4: INPC, variación anual quincenal (%). Banxico SIE, serie SP74833
A5: Fecha | B5: Último | C5: Apertura | D5: Máximo | E5: Mínimo | F5: Vol. | G5: % var. | I5: Fecha | J5: Último | K5: Apertura | L5: Máximo | M5: Mínimo | N5: Vol. | O5: % var. | Q5: Fecha | R5: Último | S5: Apertura | T5: Máximo | U5: Mínimo | V5: Vol. | W5: % var. | Y5: Fecha | Z5: Último | AA5: Apertura | AB5: Máximo | AC5: Mínimo | AD5: Vol. | AE5: % var. | AG5: Quincena | AH5: Inflación anual (%)
A6: 46029 | B6: 30.34 | C6: 29.64 | D6: 30.34 | E6: 29.5 | F6: 3.40K | G6: 0.003 | I6: 01.07.2026 | J6: 67247.79 | K6: 66966.68 | L6: 67435.72 | M6: 66614.42 | N6: 162.40M | O6: 0.0042 | Q6: 10/17/2021 | R6: 25 | S6: 25.29 | T6: 25.7 | U6: 24.15 | V6: 1.05M | W6: -0.0192 | Y6: 17.10.2021 | Z6: 51889.66 | AA6: 52834.71 | AB6: 52942.26 | AC6: 51521.94 | AD6: 699.14M | AE6: -0.0172 | AG6: 44562 | AH6: 7.13
A7: 46060 | B7: 30.7 | C7: 29.73 | D7: 30.9 | E7: 29.73 | F7: 3.17K | G7: 0.0119 | I7: 02.07.2026 | J7: 67071.11 | K7: 66990.87 | L7: 68044.67 | M7: 66976.91 | N7: 102.82M | O7: -0.0026 | Q7: 10/24/2021 | R7: 24.77 | S7: 24.4 | T7: 25.5 | U7: 23.6 | V7: 174.31K | W7: -0.0092 | Y7: 24.10.2021 | Z7: 51309.84 | AA7: 51892.32 | AB7: 52244.72 | AC7: 50997.11 | AD7: 678.31M | AE7: -0.0112 | AG7: 44577 | AH7: 7.01
A8: 46088 | B8: 29.91 | C8: 30.08 | D8: 30.08 | E8: 29.91 | F8: 1.20K | G8: -0.0257 | I8: 03.07.2026 | J8: 67060.49 | K8: 67352.67 | L8: 67402.75 | M8: 66816.77 | N8: 28.96M | O8: -0.0002 | Q8: 10/31/2021 | R8: 24.48 | S8: 24.77 | T8: 24.77 | U8: 24.02 | V8: 48.46K | W8: -0.0117 | Y8: 31.10.2021 | Z8: 51977.96 | AA8: 51353.61 | AB8: 52220.4 | AC8: 51338.69 | AD8: 674.32M | AE8: 0.013 | AG8: 44593 | AH8: 7.22
A9: 46180 | B9: 29.6 | C9: 30 | D9: 30 | E9: 29.51 | F9: 2.36K | G9: -0.0104 | I9: 06.07.2026 | J9: 67466.46 | K9: 67132.1 | L9: 67780.34 | M9: 67099.66 | N9: 154.90M | O9: 0.0061 | Q9: 44388 | R9: 23.77 | S9: 24.4 | T9: 24.5 | U9: 23.5 | V9: 104.02K | W9: -0.029 | Y9: 07.11.2021 | Z9: 51432.54 | AA9: 52000.21 | AB9: 52577.33 | AC9: 51350.36 | AD9: 831.59M | AE9: -0.0105 | AG9: 44608 | AH9: 7.34
A10: 46210 | B10: 30.29 | C10: 29.6 | D10: 30.49 | E10: 29.6 | F10: 0.85K | G10: 0.0233 | I10: 07.07.2026 | J10: 66674.7 | K10: 67450.26 | L10: 67666.07 | M10: 66526.12 | N10: 128.25M | O10: -0.0117 | Q10: 11/14/2021 | R10: 22.99 | S10: 23.99 | T10: 24.13 | U10: 22.92 | V10: 88.93K | W10: -0.0328 | Y10: 14.11.2021 | Z10: 50811.3 | AA10: 51422.13 | AB10: 51585.64 | AC10: 50535.11 | AD10: 652.74M | AE10: -0.0121 | AG10: 44621 | AH10: 7.29
A11: 46241 | B11: 30 | C11: 29.68 | D11: 30.65 | E11: 29.68 | F11: 1.26K | G11: -0.0096 | I11: 08.07.2026 | J11: 66609.64 | K11: 66526.65 | L11: 66763.02 | M11: 65846.95 | N11: 105.53M | O11: -0.001 | Q11: 11/21/2021 | R11: 22.73 | S11: 22.8 | T11: 24 | U11: 21.76 | V11: 228.56K | W11: -0.0113 | Y11: 21.11.2021 | Z11: 49492.52 | AA11: 50864.01 | AB11: 51236.58 | AC11: 49064.67 | AD11: 690.57M | AE11: -0.026 | AG11: 44636 | AH11: 7.62
A12: 46272 | B12: 30.76 | C12: 30.6 | D12: 30.76 | E12: 30.6 | F12: 0.83K | G12: 0.0253 | I12: 09.07.2026 | J12: 66107.28 | K12: 66831.04 | L12: 66945.12 | M12: 66019.15 | N12: 142.19M | O12: -0.0075 | Q12: 11/28/2021 | R12: 23.94 | S12: 22.7 | T12: 24.49 | U12: 22.54 | V12: 162.78K | W12: 0.0532 | Y12: 28.11.2021 | Z12: 50597.29 | AA12: 49520.3 | AB12: 51413.06 | AC12: 49116.94 | AD12: 1.65B | AE12: 0.0223 | AG12: 44652 | AH12: 7.72
A13: 46302 | B13: 30.6 | C13: 30.14 | D13: 30.65 | E13: 30.14 | F13: 1.12K | G13: -0.0052 | I13: 10.07.2026 | J13: 66496.1 | K13: 66140.53 | L13: 66798.05 | M13: 66140.53 | N13: 127.90M | O13: 0.0059 | Q13: 44328 | R13: 23.26 | S13: 23.9 | T13: 23.98 | U13: 22.82 | V13: 314.98K | W13: -0.0284 | Y13: 05.12.2021 | Z13: 51213.48 | AA13: 50590.86 | AB13: 51305.44 | AC13: 50445.25 | AD13: 720.22M | AE13: 0.0122 | AG13: 44667 | AH13: 7.65
A14: 07/13/2026 | B14: 30 | C14: 30.46 | D14: 30.57 | E14: 30 | F14: 1.75K | G14: -0.0196 | I14: 13.07.2026 | J14: 65973.08 | K14: 66345.02 | L14: 66614.98 | M14: 65875.46 | N14: 124.72M | O14: -0.0079 | Q14: 44542 | R14: 22.59 | S14: 23.44 | T14: 23.44 | U14: 22.19 | V14: 578.94K | W14: -0.0288 | Y14: 12.12.2021 | Z14: 52379.37 | AA14: 51214.61 | AB14: 52477.83 | AC14: 50291.02 | AD14: 1.32B | AE14: 0.0228 | AG14: 44682 | AH14: 7.58
A15: 07/15/2026 | B15: 30.04 | C15: 29.61 | D15: 30.2 | E15: 29.5 | F15: 1.37K | G15: 0.0013 | I15: 14.07.2026 | J15: 66514.3 | K15: 65930.2 | L15: 66984.89 | M15: 65930.2 | N15: 130.40M | O15: 0.0082 | Q15: 12/19/2021 | R15: 24.8 | S15: 22.59 | T15: 24.8 | U15: 22.33 | V15: 252.84K | W15: 0.0978 | Y15: 19.12.2021 | Z15: 52853.38 | AA15: 52333.26 | AB15: 52901.72 | AC15: 51319.55 | AD15: 481.82M | AE15: 0.009 | AG15: 44697 | AH15: 7.72
A16: 07/16/2026 | B16: 29.96 | C16: 30.18 | D16: 30.58 | E16: 29.96 | F16: 1.50K | G16: -0.0027 | I16: 15.07.2026 | J16: 66399.71 | K16: 66688.79 | L16: 66807.81 | M16: 66269.87 | N16: 134.99M | O16: -0.0017 | Q16: 12/26/2021 | R16: 25.98 | S16: 24.6 | T16: 26.15 | U16: 24.5 | V16: 228.19K | W16: 0.0476 | Y16: 26.12.2021 | Z16: 53272.44 | AA16: 52853.66 | AB16: 53630.53 | AC16: 52558.85 | AD16: 334.71M | AE16: 0.0079 | AG16: 44713 | AH16: 7.88
A17: 07/17/2026 | B17: 30.27 | C17: 30.27 | D17: 30.27 | E17: 30.27 | F17: 0.58K | G17: 0.0103 | I17: 16.07.2026 | J17: 66356.09 | K17: 66338.62 | L17: 66717.57 | M17: 65999.7 | N17: 113.88M | O17: -0.0007 | Q17: 44593 | R17: 24.04 | S17: 26.2 | T17: 26.2 | U17: 23.5 | V17: 162.67K | W17: -0.0747 | Y17: 02.01.2022 | Z17: 53202.11 | AA17: 53278.11 | AB17: 53603.83 | AC17: 52768.81 | AD17: 522.29M | AE17: -0.0013 | AG17: 44728 | AH17: 8.09
A18: 07/21/2026 | B18: 29.8 | C18: 29.99 | D18: 29.99 | E18: 29.8 | F18: 1.65K | G18: -0.0155 | I18: 17.07.2026 | J18: 66634.23 | K18: 66328.36 | L18: 66822.62 | M18: 65997.21 | N18: 140.85M | O18: 0.0042 | Q18: 44805 | R18: 23.98 | S18: 23.57 | T18: 24.9 | U18: 23.11 | V18: 62.43K | W18: -0.0025 | Y18: 09.01.2022 | Z18: 53744.92 | AA18: 53202.84 | AB18: 54102.49 | AC18: 52740.35 | AD18: 754.89M | AE18: 0.0102 | AG18: 44743 | AH18: 8.16
A19: 07/22/2026 | B19: 29.3 | C19: 29.3 | D19: 29.3 | E19: 29.3 | F19: 0.46K | G19: -0.0168 | I19: 20.07.2026 | J19: 66122.78 | K19: 66605.9 | L19: 67001.16 | M19: 66094.86 | N19: 111.58M | O19: -0.0077 | Q19: 01/16/2022 | R19: 22.92 | S19: 24.9 | T19: 24.9 | U19: 22.61 | V19: 30.66K | W19: -0.0442 | Y19: 16.01.2022 | Z19: 51599.38 | AA19: 53742.37 | AB19: 54219.14 | AC19: 51386.68 | AD19: 673.67M | AE19: -0.0399 | AG19: 44758 | AH19: 8.14
A20: 07/24/2026 | B20: 29.41 | C20: 30.26 | D20: 30.26 | E20: 29.41 | F20: 1.36K | G20: 0.0038 | I20: 21.07.2026 | J20: 66713.83 | K20: 66129.07 | L20: 66809.65 | M20: 66101.66 | N20: 109.35M | O20: 0.0089 | Q20: 01/23/2022 | R20: 22.39 | S20: 22.5 | T20: 23 | U20: 21.83 | V20: 534.04K | W20: -0.0231 | Y20: 23.01.2022 | Z20: 50661.86 | AA20: 51578.42 | AB20: 51578.42 | AC20: 49673.64 | AD20: 1.05B | AE20: -0.0182 | AG20: 44774 | AH20: 8.62
A21: 07/27/2026 | B21: 29.03 | C21: 29.35 | D21: 29.35 | E21: 29.03 | F21: 0.78K | G21: -0.0129 | I21: 22.07.2026 | J21: 67303.83 | K21: 66683.27 | L21: 67656.3 | M21: 66634.23 | N21: 115.68M | O21: 0.0088 | Q21: 01/30/2022 | R21: 23.24 | S21: 22.39 | T21: 23.31 | U21: 22.33 | V21: 99.04K | W21: 0.038 | Y21: 30.01.2022 | Z21: 51255.31 | AA21: 50670.28 | AB21: 52120.64 | AC21: 50631.62 | AD21: 647.19M | AE21: 0.0117 | AG21: 44789 | AH21: 8.77
A22: 07/28/2026 | B22: 29.5 | C22: 29.61 | D22: 29.61 | E22: 29.5 | F22: 1.09K | G22: 0.0162 | I22: 23.07.2026 | J22: 66266.01 | K22: 67369.19 | L22: 67369.19 | M22: 66181.08 | N22: 142.31M | O22: -0.0154 | Q22: 44714 | R22: 22.57 | S22: 22.78 | T22: 23 | U22: 21.98 | V22: 104.46K | W22: -0.0288 | Y22: 06.02.2022 | Z22: 53229.26 | AA22: 51281.26 | AB22: 53630.05 | AC22: 51011.87 | AD22: 798.15M | AE22: 0.0385 | AG22: 44805 | AH22: 8.76
A23: 07/29/2026 | B23: 29.6 | C23: 29.6 | D23: 29.6 | E23: 29.55 | F23: 0.83K | G23: 0.0034 | I23: 24.07.2026 | J23: 66383.26 | K23: 66290.18 | L23: 66748.08 | M23: 65759.85 | N23: 111.29M | O23: 0.0018 | Q23: 02/13/2022 | R23: 23.11 | S23: 22.26 | T23: 23.27 | U23: 22 | V23: 85.82K | W23: 0.0239 | Y23: 13.02.2022 | Z23: 52281.53 | AA23: 53232.26 | AB23: 53901.91 | AC23: 52161.67 | AD23: 853.91M | AE23: -0.0178 | AG23: 44820 | AH23: 8.64
A24: 07/31/2026 | B24: 29.59 | C24: 29.82 | D24: 29.82 | E24: 29.59 | F24: 1.36K | G24: -0.0003 | I24: 27.07.2026 | J24: 67157.91 | K24: 66342.71 | L24: 67427.57 | M24: 66342.71 | N24: 101.99M | O24: 0.0117 | Q24: 02/20/2022 | R24: 23.25 | S24: 23.29 | T24: 24.2 | U24: 22.75 | V24: 100.05K | W24: 0.0061 | Y24: 20.02.2022 | Z24: 52555.6 | AA24: 52281.53 | AB24: 52664.38 | AC24: 50003.09 | AD24: 927.82M | AE24: 0.0052 | AG24: 44835 | AH24: 8.53
A25: 46089 | B25: 29.8 | C25: 29.1 | D25: 29.8 | E25: 29.1 | F25: 0.80K | G25: 0.0071 | I25: 28.07.2026 | J25: 67307.54 | K25: 66998.96 | L25: 68457.09 | M25: 66676.41 | N25: 118.94M | O25: 0.0022 | Q25: 02/27/2022 | R25: 22.91 | S25: 22.85 | T25: 24.4 | U25: 22.71 | V25: 130.61K | W25: -0.0146 | Y25: 27.02.2022 | Z25: 53322.05 | AA25: 52528.71 | AB25: 54095.65 | AC25: 51990.91 | AD25: 1.78B | AE25: 0.0146 | AG25: 44850 | AH25: 8.28
A26: 46150 | B26: 29 | C26: 29.21 | D26: 29.21 | E26: 29 | F26: 1.77K | G26: -0.0268 | I26: 29.07.2026 | J26: 66479.89 | K26: 67332.48 | L26: 67432.33 | M26: 66353.78 | N26: 170.04M | O26: -0.0123 | Q26: 44715 | R26: 22.7 | S26: 23.19 | T26: 23.47 | U26: 22.2 | V26: 120.75K | W26: -0.0092 | Y26: 06.03.2022 | Z26: 53300.7 | AA26: 53354.94 | AB26: 54019.43 | AC26: 51884.08 | AD26: 1.07B | AE26: -0.0004 | AG26: 44866 | AH26: 8.14
A27: 46181 | B27: 29 | C27: 29.01 | D27: 29.01 | E27: 29 | F27: 1.00K | G27: 0 | I27: 30.07.2026 | J27: 67290.4 | K27: 66527.56 | L27: 67467.66 | M27: 66472.21 | N27: 112.07M | O27: 0.0122 | Q27: 03/13/2022 | R27: 21.62 | S27: 23.07 | T27: 23.07 | U27: 21 | V27: 181.81K | W27: -0.0476 | Y27: 13.03.2022 | Z27: 55467.06 | AA27: 53300.7 | AB27: 55788.87 | AC27: 52427.58 | AD27: 1.76B | AE27: 0.0406 | AG27: 44881 | AH27: 7.46
A28: 46211 | B28: 29.47 | C28: 29.45 | D28: 29.47 | E28: 29.45 | F28: 1.19K | G28: 0.0162 | I28: 31.07.2026 | J28: 66936.99 | K28: 67302.17 | L28: 67613.02 | M28: 66832.91 | N28: 138.50M | O28: -0.0053 | Q28: 03/20/2022 | R28: 22.13 | S28: 21.63 | T28: 22.7 | U28: 21.41 | V28: 276.61K | W28: 0.0236 | Y28: 20.03.2022 | Z28: 55436.05 | AA28: 55468.11 | AB28: 55907.49 | AC28: 54990.07 | AD28: 709.14M | AE28: -0.0006 | AG28: 44896 | AH28: 7.77
A29: 46303 | B29: 29.36 | C29: 29 | D29: 29.45 | E29: 29 | F29: 2.26K | G29: -0.0037 | I29: 03.08.2026 | J29: 66697.22 | K29: 66933.91 | L29: 67087.56 | M29: 66429.74 | N29: 96.86M | O29: -0.0036 | Q29: 03/27/2022 | R29: 22.31 | S29: 22.15 | T29: 22.5 | U29: 21.83 | V29: 363.74K | W29: 0.0081 | Y29: 27.03.2022 | Z29: 56609.54 | AA29: 55436.45 | AB29: 57064.16 | AC29: 55335.86 | AD29: 991.94M | AE29: 0.0212 | AG29: 44911 | AH29: 7.86
A30: 46334 | B30: 28.75 | C30: 29 | D30: 29 | E30: 28.71 | F30: 1.10K | G30: -0.0208 | I30: 04.08.2026 | J30: 66833.16 | K30: 66814.85 | L30: 67668.58 | M30: 66622.25 | N30: 119.77M | O30: 0.002 | Q30: 44624 | R30: 21.58 | S30: 22.07 | T30: 22.3 | U30: 21.2 | V30: 85.49K | W30: -0.0327 | Y30: 03.04.2022 | Z30: 54687.25 | AA30: 56610.03 | AB30: 56783.68 | AC30: 54591.73 | AD30: 829.89M | AE30: -0.034 | AG30: 44927 | AH30: 7.94
A31: 46364 | B31: 28.75 | C31: 28.75 | D31: 28.75 | E31: 28.75 | F31: 0.73K | G31: 0 | I31: 05.08.2026 | J31: 66525.18 | K31: 66833.38 | L31: 67168.39 | M31: 66432.18 | N31: 134.78M | O31: -0.0046 | Q31: 44838 | R31: 21.68 | S31: 21.56 | T31: 21.9 | U31: 21.19 | V31: 45.68K | W31: 0.0046 | Y31: 10.04.2022 | Z31: 54172.62 | AA31: 54678.05 | AB31: 54809.11 | AC31: 53697.42 | AD31: 403.99M | AE31: -0.0094 | AG31: 44942 | AH31: 7.88
A32: 08/13/2026 | B32: 27.95 | C32: 28.75 | D32: 28.75 | E32: 27.61 | F32: 10.40K | G32: -0.0278 | I32: 06.08.2026 | J32: 66396.15 | K32: 66432.36 | L32: 67247.56 | M32: 66336.76 | N32: 129.95M | O32: -0.0019 | Q32: 04/17/2022 | R32: 21.01 | S32: 21.72 | T32: 21.74 | U32: 21 | V32: 26.94K | W32: -0.0309 | Y32: 17.04.2022 | Z32: 53191.78 | AA32: 54172.62 | AB32: 54718.34 | AC32: 53027.2 | AD32: 739.48M | AE32: -0.0181 | AG32: 44958 | AH32: 7.76
A33: 08/14/2026 | B33: 27.5 | C33: 27.01 | D33: 27.93 | E33: 27.01 | F33: 5.43K | G33: -0.0161 | I33: 07.08.2026 | J33: 66938.64 | K33: 66394.89 | L33: 67185.88 | M33: 66394.89 | N33: 113.36M | O33: 0.0082 | Q33: 04/24/2022 | R33: 23.56 | S33: 21.01 | T33: 23.75 | U33: 21.01 | V33: 268.82K | W33: 0.1214 | Y33: 24.04.2022 | Z33: 51417.97 | AA33: 53183.12 | AB33: 53183.12 | AC33: 51315.04 | AD33: 975.60M | AE33: -0.0333 | AG33: 44973 | AH33: 7.48
A34: 08/17/2026 | B34: 27.5 | C34: 27.5 | D34: 27.5 | E34: 27.5 | F34: 0.61K | G34: 0 | I34: 10.08.2026 | J34: 66438.58 | K34: 66933.01 | L34: 66955.02 | M34: 66247 | N34: 97.22M | O34: -0.0075 | Q34: 44566 | R34: 22.07 | S34: 23.68 | T34: 23.68 | U34: 21.45 | V34: 35.68K | W34: -0.0632 | Y34: 01.05.2022 | Z34: 49541.81 | AA34: 51426.27 | AB34: 51922.71 | AC34: 49451.28 | AD34: 805.17M | AE34: -0.0365 | AG34: 44986 | AH34: 7.12
A35: 08/18/2026 | B35: 27.5 | C35: 27.5 | D35: 27.5 | E35: 27.5 | F35: 0.42K | G35: 0 | I35: 11.08.2026 | J35: 65564.76 | K35: 66398.29 | L35: 66459.17 | M35: 65509.9 | N35: 105.48M | O35: -0.0132 | Q35: 44778 | R35: 22 | S35: 21.52 | T35: 22.03 | U35: 20.97 | V35: 20.98K | W35: -0.0032 | Y35: 08.05.2022 | Z35: 49579.9 | AA35: 49419.02 | AB35: 49732.05 | AC35: 48669.21 | AD35: 1.12B | AE35: 0.0008 | AG35: 45001 | AH35: 6.58
A36: 08/19/2026 | B36: 27.49 | C36: 27.99 | D36: 27.99 | E36: 27.49 | F36: 0.79K | G36: -0.0004 | I36: 12.08.2026 | J36: 65755.97 | K36: 65746.89 | L36: 66120.72 | M36: 65404.51 | N36: 187.04M | O36: 0.0029 | Q36: 05/15/2022 | R36: 21.35 | S36: 21.5 | T36: 22.5 | U36: 21.04 | V36: 190.80K | W36: -0.0295 | Y36: 15.05.2022 | Z36: 51518.3 | AA36: 49604.95 | AB36: 51868.44 | AC36: 49472.51 | AD36: 1.13B | AE36: 0.0391 | AG36: 45017 | AH36: 6.24
A37: 08/20/2026 | B37: 27.49 | C37: 27.49 | D37: 27.49 | E37: 27.49 | F37: 0.94K | G37: 0 | I37: 13.08.2026 | J37: 64826.39 | K37: 65890.72 | L37: 65890.72 | M37: 64750.07 | N37: 204.09M | O37: -0.0141 | Q37: 05/22/2022 | R37: 21.34 | S37: 21.35 | T37: 22.12 | U37: 21.2 | V37: 125.95K | W37: -0.0005 | Y37: 22.05.2022 | Z37: 52463.55 | AA37: 51621.72 | AB37: 52617.31 | AC37: 50866.15 | AD37: 1.02B | AE37: 0.0183 | AG37: 45032 | AH37: 6.27
A38: 08/21/2026 | B38: 27.08 | C38: 27.4 | D38: 27.4 | E38: 26.6 | F38: 2.01K | G38: -0.0149 | I38: 14.08.2026 | J38: 64397.45 | K38: 65038.55 | L38: 65038.55 | M38: 64329.53 | N38: 93.51M | O38: -0.0066 | Q38: 05/29/2022 | R38: 21.27 | S38: 22.14 | T38: 22.14 | U38: 20.78 | V38: 118.27K | W38: -0.0033 | Y38: 29.05.2022 | Z38: 50689.05 | AA38: 52438.79 | AB38: 52745.98 | AC38: 50482.85 | AD38: 1.95B | AE38: -0.0338 | AG38: 45047 | AH38: 6
A39: 08/24/2026 | B39: 27.08 | C39: 27 | D39: 27.08 | E39: 27 | F39: 0.41K | G39: 0 | I39: 17.08.2026 | J39: 64254.98 | K39: 64457.26 | L39: 64534.98 | M39: 64024 | N39: 69.01M | O39: -0.0022 | Q39: 44687 | R39: 21.06 | S39: 21.29 | T39: 21.32 | U39: 20.86 | V39: 38.05K | W39: -0.0099 | Y39: 05.06.2022 | Z39: 48471.52 | AA39: 50723.91 | AB39: 51029.28 | AC39: 48398.78 | AD39: 711.74M | AE39: -0.0437 | AG39: 45062 | AH39: 5.67
A40: 08/25/2026 | B40: 27.29 | C40: 27.5 | D40: 27.5 | E40: 27.17 | F40: 1.40K | G40: 0.0078 | I40: 18.08.2026 | J40: 63933.69 | K40: 64289.47 | L40: 64665.94 | M40: 63841.29 | N40: 102.63M | O40: -0.005 | Q40: 44901 | R40: 19.21 | S40: 21 | T40: 21 | U40: 19.02 | V40: 158.20K | W40: -0.0878 | Y40: 12.06.2022 | Z40: 48016.23 | AA40: 48408.2 | AB40: 48717.67 | AC40: 47323.36 | AD40: 1.56B | AE40: -0.0094 | AG40: 45078 | AH40: 5.18
A41: 08/26/2026 | B41: 27.29 | C41: 26.51 | D41: 27.29 | E41: 26.51 | F41: 0.91K | G41: 0 | I41: 19.08.2026 | J41: 63999.26 | K41: 63990.05 | L41: 64584.42 | M41: 63924.2 | N41: 93.95M | O41: 0.001 | Q41: 06/19/2022 | R41: 21.24 | S41: 19 | T41: 21.35 | U41: 18.96 | V41: 421.74K | W41: 0.1057 | Y41: 19.06.2022 | Z41: 47741.5 | AA41: 47996.72 | AB41: 48321.17 | AC41: 46344.94 | AD41: 651.65M | AE41: -0.0057 | AG41: 45093 | AH41: 4.93
A42: 08/27/2026 | B42: 27.07 | C42: 27.49 | D42: 27.49 | E42: 27.07 | F42: 1.03K | G42: -0.0081 | I42: 20.08.2026 | J42: 64349.8 | K42: 64007.42 | L42: 64547.11 | M42: 63937.99 | N42: 109.72M | O42: 0.0055 | Q42: 06/26/2022 | R42: 22.45 | S42: 21.05 | T42: 22.5 | U42: 20.36 | V42: 345.90K | W42: 0.057 | Y42: 26.06.2022 | Z42: 47743.15 | AA42: 47781.35 | AB42: 48796.23 | AC42: 47135.18 | AD42: 800.48M | AE42: 0 | AG42: 45108 | AH42: 4.79
A43: 08/28/2026 | B43: 27.07 | C43: 27.56 | D43: 27.56 | E43: 27.07 | F43: 0.87K | G43: 0 | I43: 21.08.2026 | J43: 65729.18 | K43: 64559.79 | L43: 66082.15 | M43: 64559.79 | N43: 152.83M | O43: 0.0214 | Q43: 44627 | R43: 22.7 | S43: 22.19 | T43: 23 | U43: 21.5 | V43: 461.32K | W43: 0.0111 | Y43: 03.07.2022 | Z43: 47582.11 | AA43: 47740.32 | AB43: 48584.14 | AC43: 46927.07 | AD43: 640.60M | AE43: -0.0034 | AG43: 45123 | AH43: 4.78
A44: 08/31/2026 | B44: 27.06 | C44: 27.5 | D44: 27.54 | E44: 27.06 | F44: 1.18K | G44: -0.0004 | I44: 24.08.2026 | J44: 65770.85 | K44: 65751.65 | L44: 66152.15 | M44: 65510.82 | N44: 113.34M | O44: 0.0006 | Q44: 44841 | R44: 22.83 | S44: 22.5 | T44: 23.02 | U44: 22.1 | V44: 239.01K | W44: 0.0057 | Y44: 10.07.2022 | Z44: 47075.87 | AA44: 47541.46 | AB44: 47800.36 | AC44: 46581.32 | AD44: 676.86M | AE44: -0.0106 | AG44: 45139 | AH44: 4.67
A45: 46031 | B45: 26.92 | C45: 26.6 | D45: 26.92 | E45: 26.6 | F45: 0.51K | G45: -0.0052 | I45: 25.08.2026 | J45: 66293.07 | K45: 65750.89 | L45: 66359.58 | M45: 65019.88 | N45: 92.47M | O45: 0.0079 | Q45: 07/17/2022 | R45: 23.6 | S45: 22.63 | T45: 24 | U45: 22.5 | V45: 273.05K | W45: 0.0337 | Y45: 17.07.2022 | Z45: 47264.86 | AA45: 47198.01 | AB45: 47595.79 | AC45: 46767.74 | AD45: 545.04M | AE45: 0.004 | AG45: 45154 | AH45: 4.6
A46: 46062 | B46: 26.75 | C46: 26.38 | D46: 26.86 | E46: 26.38 | F46: 1.40K | G46: -0.0063 | I46: 26.08.2026 | J46: 66191.11 | K46: 66146.09 | L46: 66823.1 | M46: 66107.32 | N46: 108.51M | O46: -0.0015 | Q46: 07/24/2022 | R46: 22.64 | S46: 23.71 | T46: 23.71 | U46: 22.21 | V46: 518.38K | W46: -0.0407 | Y46: 24.07.2022 | Z46: 48144.33 | AA46: 47254.55 | AB46: 48338.9 | AC46: 46164.27 | AD46: 801.82M | AE46: 0.0186 | AG46: 45170 | AH46: 4.44
A47: 46090 | B47: 26.75 | C47: 26.75 | D47: 26.75 | E47: 26.75 | F47: 0.37K | G47: 0 | I47: 27.08.2026 | J47: 65829.98 | K47: 66096.55 | L47: 66239.84 | M47: 65649.86 | N47: 93.21M | O47: -0.0055 | Q47: 07/31/2022 | R47: 22.8 | S47: 22.7 | T47: 23.01 | U47: 22.51 | V47: 879.30K | W47: 0.0071 | Y47: 31.07.2022 | Z47: 46723.43 | AA47: 48094.47 | AB47: 48417.03 | AC47: 46283.75 | AD47: 808.83M | AE47: -0.0295 | AG47: 45185 | AH47: 4.47
A48: 46121 | B48: 26 | C48: 27.2 | D48: 27.2 | E48: 26 | F48: 2.99K | G48: -0.028 | I48: 28.08.2026 | J48: 65484.32 | K48: 65876.02 | L48: 65964.57 | M48: 65202.8 | N48: 98.33M | O48: -0.0053 | Q48: 44750 | R48: 22.75 | S48: 22.8 | T48: 22.84 | U48: 22.32 | V48: 129.35K | W48: -0.0022 | Y48: 07.08.2022 | Z48: 48853.37 | AA48: 46787.91 | AB48: 48909.17 | AC48: 46787.91 | AD48: 810.01M | AE48: 0.0456 | AG48: 45200 | AH48: 4.27
A49: 46243 | B49: 26.25 | C49: 26.25 | D49: 26.25 | E49: 26.25 | F49: 0.35K | G49: 0.0096 | I49: 31.08.2026 | J49: 65430.32 | K49: 65325.71 | L49: 65570.92 | M49: 64913.8 | N49: 452.10M | O49: -0.0008 | Q49: 08/14/2022 | R49: 22.75 | S49: 22.73 | T49: 22.75 | U49: 22.1 | V49: 183.08K | W49: 0 | Y49: 14.08.2022 | Z49: 48463.26 | AA49: 48770.31 | AB49: 48944.49 | AC49: 48270.23 | AD49: 574.42M | AE49: -0.008 | AG49: 45215 | AH49: 4.25
A50: 46274 | B50: 26.5 | C50: 26.5 | D50: 26.52 | E50: 26.5 | F50: 1.44K | G50: 0.0095 | I50: 01.09.2026 | J50: 64514.25 | K50: 65348.35 | L50: 65743.72 | M50: 64393.19 | N50: 141.53M | O50: -0.014 | Q50: 08/21/2022 | R50: 22.74 | S50: 22.75 | T50: 22.75 | U50: 22.61 | V50: 126.58K | W50: -0.0004 | Y50: 21.08.2022 | Z50: 47272.11 | AA50: 48366.14 | AB50: 48464.22 | AC50: 46992.75 | AD50: 564.56M | AE50: -0.0246 | AG50: 45231 | AH50: 4.32
A51: 46304 | B51: 25.56 | C51: 26.06 | D51: 26.06 | E51: 25.56 | F51: 2.63K | G51: -0.0355 | I51: 02.09.2026 | J51: 64884.28 | K51: 64500.71 | L51: 65088.9 | M51: 64312.59 | N51: 151.59M | O51: 0.0057 | Q51: 08/28/2022 | R51: 22.75 | S51: 22.5 | T51: 22.75 | U51: 22.36 | V51: 35.02K | W51: 0.0004 | Y51: 28.08.2022 | Z51: 45888.63 | AA51: 47105.9 | AB51: 47105.9 | AC51: 44518.73 | AD51: 1.08B | AE51: -0.0293 | AG51: 45246 | AH51: 4.33
A52: 46335 | B52: 26 | C52: 25.5 | D52: 26.49 | E52: 25.5 | F52: 3.28K | G52: 0.0172 | I52: 03.09.2026 | J52: 65436.16 | K52: 65031.95 | L52: 65689.15 | M52: 65024.32 | N52: 198.90M | O52: 0.0085 | Q52: 44660 | R52: 23.29 | S52: 22.2 | T52: 23.29 | U52: 22.2 | V52: 195.29K | W52: 0.0237 | Y52: 04.09.2022 | Z52: 47042.94 | AA52: 45905.86 | AB52: 47072.99 | AC52: 45482.77 | AD52: 532.32M | AE52: 0.0252 | AG52: 45261 | AH52: 4.46
A53: 09/14/2026 | B53: 27.56 | C53: 26.52 | D53: 27.56 | E53: 26.52 | F53: 1.96K | G53: 0.06 | I53: 04.09.2026 | J53: 64866.61 | K53: 65248.38 | L53: 65451.49 | M53: 64768.5 | N53: 167.94M | O53: -0.0087 | Q53: 44874 | R53: 24.99 | S53: 23.3 | T53: 25 | U53: 23.3 | V53: 67.35K | W53: 0.073 | Y53: 11.09.2022 | Z53: 46769.78 | AA53: 47168.11 | AB53: 47944.6 | AC53: 46545.13 | AD53: 1.25B | AE53: -0.0058 | AG53: 45276 | AH53: 4.86
A54: 09/15/2026 | B54: 29.66 | C54: 27.89 | D54: 30.4 | E54: 27.89 | F54: 19.02K | G54: 0.0762 | I54: 07.09.2026 | J54: 64727.54 | K54: 64972.75 | L54: 65019.23 | M54: 64525.23 | N54: 30.48M | O54: -0.0021 | Q54: 09/18/2022 | R54: 26.2 | S54: 24.9 | T54: 26.2 | U54: 23.79 | V54: 222.76K | W54: 0.0484 | Y54: 18.09.2022 | Z54: 45395.94 | AA54: 46712.13 | AB54: 47432.52 | AC54: 45069.02 | AD54: 909.42M | AE54: -0.0294 | AG54: 45292 | AH54: 4.9
A55: 09/17/2026 | B55: 30.02 | C55: 30.25 | D55: 30.25 | E55: 29.5 | F55: 18.42K | G55: 0.0121 | I55: 08.09.2026 | J55: 65065.56 | K55: 64707.67 | L55: 65153.75 | M55: 64554.17 | N55: 138.99M | O55: 0.0052 | Q55: 09/25/2022 | R55: 26.2 | S55: 26 | T55: 26.2 | U55: 25.76 | V55: 453.66K | W55: 0 | Y55: 25.09.2022 | Z55: 44626.8 | AA55: 45410.86 | AB55: 45826.95 | AC55: 44558.81 | AD55: 806.44M | AE55: -0.0169 | AG55: 45307 | AH55: 4.87
A56: 09/18/2026 | B56: 30.24 | C56: 30.1 | D56: 30.29 | E56: 30.1 | F56: 8.53K | G56: 0.0073 | I56: 09.09.2026 | J56: 64814.97 | K56: 64905.29 | L56: 65263.32 | M56: 64682.05 | N56: 169.80M | O56: -0.0039 | Q56: 44602 | R56: 26.43 | S56: 26.5 | T56: 28 | U56: 26 | V56: 58.24K | W56: 0.0088 | Y56: 02.10.2022 | Z56: 45728.87 | AA56: 44779.2 | AB56: 46654.91 | AC56: 44686.64 | AD56: 877.75M | AE56: 0.0247 | AG56: 45323 | AH56: 4.45
A57: 09/21/2026 | B57: 30.1 | C57: 30.2 | D57: 30.22 | E57: 30.1 | F57: 6.90K | G57: -0.0046 | I57: 10.09.2026 | J57: 64106.82 | K57: 64529.27 | L57: 64675.47 | M57: 64023.32 | N57: 114.90M | O57: -0.0109 | Q57: 44814 | R57: 26.5 | S57: 26.4 | T57: 26.8 | U57: 25.9 | V57: 29.87K | W57: 0.0026 | Y57: 09.10.2022 | Z57: 45443.35 | AA57: 45688.15 | AB57: 46245.02 | AC57: 45026.43 | AD57: 831.94M | AE57: -0.0062 | AG57: 45338 | AH57: 4.35
A58: 09/23/2026 | B58: 30.8 | C58: 30.1 | D58: 30.8 | E58: 30.1 | F58: 1.02K | G58: 0.0233 | I58: 11.09.2026 | J58: 63924.77 | K58: 64210.93 | L58: 64454.3 | M58: 63768.4 | N58: 100.92M | O58: -0.0028 | Q58: 10/16/2022 | R58: 27.7 | S58: 26.13 | T58: 27.97 | U58: 25.98 | V58: 78.29K | W58: 0.0453 | Y58: 16.10.2022 | Z58: 47120.08 | AA58: 45633.3 | AB58: 47172.33 | AC58: 45616 | AD58: 1.07B | AE58: 0.0369 | AG58: 45352 | AH58: 4.48
A59: 09/24/2026 | B59: 32.9 | C59: 30.18 | D59: 32.9 | E59: 30.18 | F59: 14.62K | G59: 0.0682 | I59: 14.09.2026 | J59: 64216.98 | K59: 63863.57 | L59: 64301.09 | M59: 63509.34 | N59: 107.09M | O59: 0.0046 | Q59: 10/23/2022 | R59: 30.43 | S59: 27.94 | T59: 30.63 | U59: 27 | V59: 323.35K | W59: 0.0986 | Y59: 23.10.2022 | Z59: 49086.3 | AA59: 47088.17 | AB59: 49408.27 | AC59: 47065.42 | AD59: 1.11B | AE59: 0.0417 | AG59: 45367 | AH59: 4.37
A60: 09/25/2026 | B60: 33.48 | C60: 32.9 | D60: 33.5 | E60: 32.5 | F60: 15.41K | G60: 0.0176 | I60: 15.09.2026 | J60: 63507.11 | K60: 64260.84 | L60: 64375.85 | M60: 63375.52 | N60: 136.87M | O60: -0.0111 | Q60: 10/30/2022 | R60: 30.04 | S60: 30 | T60: 30.48 | U60: 29.6 | V60: 147.25K | W60: -0.0128 | Y60: 30.10.2022 | Z60: 51173.75 | AA60: 49110.67 | AB60: 51319.88 | AC60: 48873.17 | AD60: 775.53M | AE60: 0.0425 | AG60: 45383 | AH60: 4.63
A61: 09/28/2026 | B61: 33.85 | C61: 33.48 | D61: 33.85 | E61: 33.48 | F61: 10.19K | G61: 0.0111 | I61: 17.09.2026 | J61: 63873.32 | K61: 63666.04 | L61: 63979.43 | M61: 63464.96 | N61: 129.22M | O61: 0.0058 | Q61: 44723 | R61: 29.95 | S61: 30.23 | T61: 30.25 | U61: 29 | V61: 70.15K | W61: -0.003 | Y61: 06.11.2022 | Z61: 51959.2 | AA61: 51166.86 | AB61: 52126.9 | AC61: 50333.12 | AD61: 920.79M | AE61: 0.0153 | AG61: 45398 | AH61: 4.67
A62: 09/29/2026 | B62: 34.5 | C62: 34 | D62: 34.5 | E62: 33.82 | F62: 12.53K | G62: 0.0192 | I62: 18.09.2026 | J62: 63375.93 | K62: 63909.05 | L62: 64020.04 | M62: 63296.67 | N62: 931.78M | O62: -0.0078 | Q62: 11/13/2022 | R62: 30.2 | S62: 29.64 | T62: 30.49 | U62: 29.09 | V62: 125.13K | W62: 0.0083 | Y62: 13.11.2022 | Z62: 51569.72 | AA62: 51915.63 | AB62: 52457.14 | AC62: 51057.38 | AD62: 926.38M | AE62: -0.0075 | AG62: 45413 | AH62: 4.78
A63: 09/30/2026 | B63: 35 | C63: 33.81 | D63: 35 | E63: 33.81 | F63: 54.99K | G63: 0.0145 | I63: 21.09.2026 | J63: 63536.96 | K63: 63741.55 | L63: 63741.55 | M63: 63059.32 | N63: 142.88M | O63: 0.0025 | Q63: 11/20/2022 | R63: 30.45 | S63: 30.39 | T63: 30.48 | U63: 30.17 | V63: 74.19K | W63: 0.0083 | Y63: 20.11.2022 | Z63: 51668.64 | AA63: 51614.16 | AB63: 52371.02 | AC63: 51289.91 | AD63: 484.82M | AE63: 0.0019 | AG63: 45428 | AH63: 4.59
A64: 46032 | B64: 34 | C64: 35 | D64: 35 | E64: 34 | F64: 3.66K | G64: -0.0286 | I64: 22.09.2026 | J64: 64456.59 | K64: 63598.64 | L64: 64477.59 | M64: 63505.34 | N64: 145.33M | O64: 0.0145 | Q64: 11/27/2022 | R64: 28.56 | S64: 30.45 | T64: 30.45 | U64: 27.71 | V64: 16.92K | W64: -0.0621 | Y64: 27.11.2022 | Z64: 51234.37 | AA64: 51619.81 | AB64: 52120.23 | AC64: 50111.49 | AD64: 1.38B | AE64: -0.0084 | AG64: 45444 | AH64: 4.78
A65: 46063 | B65: 34.1 | C65: 34.97 | D65: 35 | E65: 34 | F65: 6.12K | G65: 0.0029 | I65: 23.09.2026 | J65: 64276.72 | K65: 64295.29 | L65: 64525.3 | M65: 64003.79 | N65: 132.96M | O65: -0.0028 | Q65: 44663 | R65: 30.43 | S65: 28.56 | T65: 30.43 | U65: 28.5 | V65: 71.25K | W65: 0.0655 | Y65: 04.12.2022 | Z65: 50466.25 | AA65: 51197.73 | AB65: 51481.81 | AC65: 50423.74 | AD65: 640.75M | AE65: -0.015 | AG65: 45459 | AH65: 5.17
A66: 46152 | B66: 33.79 | C66: 34.48 | D66: 34.48 | E66: 33.4 | F66: 2.29K | G66: -0.0091 | I66: 24.09.2026 | J66: 64264.16 | K66: 64044.17 | L66: 64327.02 | M66: 63806.19 | N66: 140.78M | O66: -0.0002 | Q66: 44877 | R66: 30.63 | S66: 30.49 | T66: 30.63 | U66: 29.99 | V66: 12.99K | W66: 0.0066 | Y66: 11.12.2022 | Z66: 49630.15 | AA66: 50638.82 | AB66: 51084.44 | AC66: 49113.71 | AD66: 1.11B | AE66: -0.0166 | AG66: 45474 | AH66: 5.61
A67: 46183 | B67: 33.11 | C67: 32.85 | D67: 33.11 | E67: 32.85 | F67: 0.66K | G67: -0.0201 | I67: 25.09.2026 | J67: 64992.23 | K67: 64205.49 | L67: 65035.96 | M67: 64205.49 | N67: 107.33M | O67: 0.0113 | Q67: 12/18/2022 | R67: 30.83 | S67: 30.6 | T67: 30.83 | U67: 30.55 | V67: 20.13K | W67: 0.0065 | Y67: 18.12.2022 | Z67: 50578.09 | AA67: 49694.69 | AB67: 50791.38 | AC67: 49534.65 | AD67: 453.77M | AE67: 0.0191 | AG67: 45489 | AH67: 5.52
A68: 46213 | B68: 33.1 | C68: 33.1 | D68: 33.1 | E68: 33.1 | F68: 0.69K | G68: -0.0003 | I68: 28.09.2026 | J68: 64944.41 | K68: 64803.3 | L68: 65127.99 | M68: 64621.9 | N68: 130.60M | O68: -0.0007 | Q68: 12/25/2022 | R68: 31.28 | S68: 30.99 | T68: 31.32 | U68: 30.61 | V68: 192.86K | W68: 0.0146 | Y68: 25.12.2022 | Z68: 48463.86 | AA68: 50530.63 | AB68: 50838.65 | AC68: 48383.2 | AD68: 323.26M | AE68: -0.0418 | AG68: 45505 | AH68: 5.16
I69: 29.09.2026 | J69: 65110.57 | K69: 64988.34 | L69: 65565.2 | M69: 64817.06 | N69: 159.54M | O69: 0.0026 | Q69: 44927 | R69: 31.65 | S69: 31.59 | T69: 31.78 | U69: 31.3 | V69: 32.44K | W69: 0.0118 | Y69: 01.01.2023 | Z69: 51730.5 | AA69: 48506.04 | AB69: 52004.83 | AC69: 48478.94 | AD69: 437.49M | AE69: 0.0674 | AG69: 45520 | AH69: 4.83
I70: 30.09.2026 | J70: 64214.36 | K70: 65185.46 | L70: 65185.46 | M70: 64145.55 | N70: 224.11M | O70: -0.0138 | Q70: 45139 | R70: 30.99 | S70: 31.23 | T70: 31.23 | U70: 30 | V70: 29.17K | W70: -0.0209 | Y70: 08.01.2023 | Z70: 53576.72 | AA70: 51770.1 | AB70: 53903.9 | AC70: 51744.84 | AD70: 715.81M | AE70: 0.0357 | AG70: 45536 | AH70: 4.66
I71: 01.10.2026 | J71: 63828.6 | K71: 64208.95 | L71: 64219.68 | M71: 63294.94 | N71: 151.90M | O71: -0.006 | Q71: 01/15/2023 | R71: 30.77 | S71: 30.7 | T71: 30.9 | U71: 29.63 | V71: 25.59K | W71: -0.0071 | Y71: 15.01.2023 | Z71: 53947.04 | AA71: 53591.88 | AB71: 54112.36 | AC71: 52936.91 | AD71: 588.07M | AE71: 0.0069 | AG71: 45551 | AH71: 4.5
I72: 02.10.2026 | J72: 64531.68 | K72: 63796.86 | L72: 64723.05 | M72: 63219.85 | N72: 171.20M | O72: 0.011 | Q72: 01/22/2023 | R72: 31.12 | S72: 30.71 | T72: 31.3 | U72: 29 | V72: 32.85K | W72: 0.0114 | Y72: 22.01.2023 | Z72: 54774.91 | AA72: 53965.28 | AB72: 55309.97 | AC72: 53943 | AD72: 681.60M | AE72: 0.0153 | AG72: 45566 | AH72: 4.69
I73: 05.10.2026 | J73: 64975.08 | K73: 64783.18 | L73: 65117.63 | M73: 64162.09 | N73: 138.67M | O73: 0.0069 | Q73: 01/29/2023 | R73: 30.02 | S73: 31.3 | T73: 31.83 | U73: 30 | V73: 24.96K | W73: -0.0353 | Y73: 29.01.2023 | Z73: 54049.05 | AA73: 54767.41 | AB73: 55173.58 | AC73: 53733.7 | AD73: 862.01M | AE73: -0.0133 | AG73: 45581 | AH73: 4.83
I74: 06.10.2026 | J74: 65312.46 | K74: 64894.31 | L74: 65520.17 | M74: 64669.02 | N74: 189.98M | O74: 0.0052 | Q74: 45048 | R74: 30.69 | S74: 29.5 | T74: 30.7 | U74: 29.5 | V74: 13.04K | W74: 0.0223 | Y74: 05.02.2023 | Z74: 52482.02 | AA74: 54001.56 | AB74: 54079.49 | AC74: 52141.14 | AD74: 650.63M | AE74: -0.029 | AG74: 45597 | AH74: 4.56
I75: 07.10.2026 | J75: 64653.33 | K75: 65284.36 | L75: 65284.36 | M75: 64381.75 | N75: 145.82M | O75: -0.0101 | Q75: 45262 | R75: 29.8 | S75: 30.3 | T75: 30.67 | U75: 28.2 | V75: 52.45K | W75: -0.029 | Y75: 12.02.2023 | Z75: 53789.64 | AA75: 52476.29 | AB75: 54143.61 | AC75: 52463.89 | AD75: 886.11M | AE75: 0.0249 | AG75: 45612 | AH75: 4.54
I76: 08.10.2026 | J76: 64986.91 | K76: 64660.37 | L76: 65045.3 | M76: 64498.93 | N76: 142.42M | O76: 0.0052 | Q76: 02/19/2023 | R76: 30.2 | S76: 30.1 | T76: 30.49 | U76: 29.9 | V76: 8.15K | W76: 0.0134 | Y76: 19.02.2023 | Z76: 52686.24 | AA76: 53832.19 | AB76: 54087.19 | AC76: 52420.64 | AD76: 713.12M | AE76: -0.0205 | AG76: 45627 | AH76: 4.44
I77: 09.10.2026 | J77: 66048.57 | K77: 64934.81 | L77: 66176.26 | M77: 64934.81 | N77: 144.17M | O77: 0.0163 | Q77: 02/26/2023 | R77: 30.7 | S77: 30.19 | T77: 30.75 | U77: 29.1 | V77: 54.29K | W77: 0.0166 | Y77: 26.02.2023 | Z77: 54182.27 | AA77: 52739.42 | AB77: 54409.37 | AC77: 52495.86 | AD77: 1.20B | AE77: 0.0284 | AG77: 45642 | AH77: 3.99
I78: 12.10.2026 | J78: 66746.78 | K78: 65930.45 | L78: 66867.88 | M78: 65869.03 | N78: 112.87M | O78: 0.0106 | Q78: 45049 | R78: 30.1 | S78: 30.46 | T78: 30.85 | U78: 29.57 | V78: 30.36K | W78: -0.0195 | Y78: 05.03.2023 | Z78: 52794.53 | AA78: 54146.1 | AB78: 54326.11 | AC78: 52716.96 | AD78: 797.66M | AE78: -0.0256 | AG78: 45658 | AH78: 3.69
Q79: 45263 | R79: 30.51 | S79: 30.08 | T79: 30.95 | U79: 29 | V79: 85.68K | W79: 0.0136 | Y79: 12.03.2023 | Z79: 51925.61 | AA79: 52788.29 | AB79: 53615.08 | AC79: 51814.68 | AD79: 1.46B | AE79: -0.0165 | AG79: 45673 | AH79: 3.48
Q80: 03/19/2023 | R80: 30.51 | S80: 30.56 | T80: 31.31 | U80: 29.92 | V80: 92.46K | W80: 0 | Y80: 19.03.2023 | Z80: 52771.12 | AA80: 52282.98 | AB80: 53089.11 | AC80: 52131.38 | AD80: 624.52M | AE80: 0.0163 | AG80: 45689 | AH80: 3.74
Q81: 03/26/2023 | R81: 30.97 | S81: 30.52 | T81: 31 | U81: 29.84 | V81: 45.18K | W81: 0.0151 | Y81: 26.03.2023 | Z81: 53904 | AA81: 52792.75 | AB81: 54604.07 | AC81: 52740.78 | AD81: 930.49M | AE81: 0.0215 | AG81: 45704 | AH81: 3.81
Q82: 44961 | R82: 30.6 | S82: 30.36 | T82: 31 | U82: 30.1 | V82: 8.08K | W82: -0.0119 | Y82: 02.04.2023 | Z82: 53498.39 | AA82: 54037.67 | AB82: 54532.08 | AC82: 53308.07 | AD82: 145.69M | AE82: -0.0075 | AG82: 45717 | AH82: 3.67
Q83: 45173 | R83: 31 | S83: 30.67 | T83: 31 | U83: 30.6 | V83: 25.57K | W83: 0.0131 | Y83: 09.04.2023 | Z83: 54460.06 | AA83: 53473.71 | AB83: 54908.53 | AC83: 53446.67 | AD83: 528.00M | AE83: 0.018 | AG83: 45732 | AH83: 3.93
Q84: 04/16/2023 | R84: 30.94 | S84: 31 | T84: 31 | U84: 30.5 | V84: 17.69K | W84: -0.0019 | Y84: 16.04.2023 | Z84: 54175.28 | AA84: 54444.68 | AB84: 54924.75 | AC84: 53662.91 | AD84: 855.20M | AE84: -0.0052 | AG84: 45748 | AH84: 3.96
Q85: 04/23/2023 | R85: 31.13 | S85: 31 | T85: 31.5 | U85: 30.35 | V85: 22.61K | W85: 0.0061 | Y85: 23.04.2023 | Z85: 55121.22 | AA85: 54203.8 | AB85: 55178.62 | AC85: 53902.05 | AD85: 868.05M | AE85: 0.0175 | AG85: 45763 | AH85: 3.9
Q86: 04/30/2023 | R86: 31.28 | S86: 30.98 | T86: 31.76 | U86: 30.98 | V86: 12.02K | W86: 0.0048 | Y86: 30.04.2023 | Z86: 54937.39 | AA86: 55059.26 | AB86: 55323.65 | AC86: 54593.06 | AD86: 786.48M | AE86: -0.0033 | AG86: 45778 | AH86: 4.22
Q87: 45112 | R87: 30.8 | S87: 31.27 | T87: 31.3 | U87: 30 | V87: 65.88K | W87: -0.0153 | Y87: 07.05.2023 | Z87: 54948.34 | AA87: 54989.64 | AB87: 55626.51 | AC87: 54724.18 | AD87: 859.49M | AE87: 0.0002 | AG87: 45793 | AH87: 4.62
Q88: 05/14/2023 | R88: 30.54 | S88: 30.84 | T88: 31.26 | U88: 30.02 | V88: 61.40K | W88: -0.0084 | Y88: 14.05.2023 | Z88: 54296.05 | AA88: 54993.48 | AB88: 55589.72 | AC88: 54244.79 | AD88: 874.45M | AE88: -0.0119 | AG88: 45809 | AH88: 4.51
Q89: 05/21/2023 | R89: 30.3 | S89: 30.9 | T89: 31.17 | U89: 29.5 | V89: 14.32K | W89: -0.0079 | Y89: 21.05.2023 | Z89: 54025.45 | AA89: 54305.68 | AB89: 54746.26 | AC89: 52997.32 | AD89: 995.32M | AE89: -0.005 | AG89: 45824 | AH89: 4.13
Q90: 05/28/2023 | R90: 30.17 | S90: 30.05 | T90: 30.2 | U90: 29.88 | V90: 37.96K | W90: -0.0043 | Y90: 28.05.2023 | Z90: 53232.71 | AA90: 54002.65 | AB90: 54347.85 | AC90: 52575.14 | AD90: 2.53B | AE90: -0.0147 | AG90: 45839 | AH90: 3.55
Q91: 45022 | R91: 30.05 | S91: 30 | T91: 30.1 | U91: 29.8 | V91: 23.34K | W91: -0.004 | Y91: 04.06.2023 | Z91: 54512.14 | AA91: 53262.27 | AB91: 54796.94 | AC91: 53238.63 | AD91: 1.09B | AE91: 0.024 | AG91: 45854 | AH91: 3.48
Q92: 45236 | R92: 29.07 | S92: 30.1 | T92: 30.1 | U92: 28.6 | V92: 50.68K | W92: -0.0326 | Y92: 11.06.2023 | Z92: 54842.51 | AA92: 54475.19 | AB92: 55407.72 | AC92: 54149.9 | AD92: 1.51B | AE92: 0.0061 | AG92: 45870 | AH92: 3.49
Q93: 06/18/2023 | R93: 28.86 | S93: 29.08 | T93: 29.6 | U93: 28.16 | V93: 45.58K | W93: -0.0072 | Y93: 18.06.2023 | Z93: 53341.91 | AA93: 54953.82 | AB93: 55074.79 | AC93: 53127.22 | AD93: 717.07M | AE93: -0.0274 | AG93: 45885 | AH93: 3.65
Q94: 06/25/2023 | R94: 28.49 | S94: 29.4 | T94: 29.48 | U94: 27.3 | V94: 93.95K | W94: -0.0128 | Y94: 25.06.2023 | Z94: 53526.1 | AA94: 53354.29 | AB94: 54008.03 | AC94: 53212.73 | AD94: 932.90M | AE94: 0.0035 | AG94: 45901 | AH94: 3.74
Q95: 44964 | R95: 27.74 | S95: 28.5 | T95: 28.98 | U95: 27.2 | V95: 37.55K | W95: -0.0263 | Y95: 02.07.2023 | Z95: 53904.29 | AA95: 53536.94 | AB95: 54501.58 | AC95: 53117.59 | AD95: 676.41M | AE95: 0.0071 | AG95: 45916 | AH95: 3.78
Q96: 45176 | R96: 27.69 | S96: 27.92 | T96: 28 | U96: 27.02 | V96: 19.62K | W96: -0.0018 | Y96: 09.07.2023 | Z96: 53770.8 | AA96: 53991.75 | AB96: 54605.5 | AC96: 53339.38 | AD96: 888.09M | AE96: -0.0025 | AG96: 45931 | AH96: 3.63
Q97: 07/16/2023 | R97: 27.24 | S97: 27.69 | T97: 27.69 | U97: 27.24 | V97: 5.37K | W97: -0.0163 | Y97: 16.07.2023 | Z97: 53702.16 | AA97: 53652.12 | AB97: 54333.02 | AC97: 53336.24 | AD97: 736.05M | AE97: -0.0013 | AG97: 45946 | AH97: 3.5
Q98: 07/23/2023 | R98: 27.38 | S98: 26.52 | T98: 28 | U98: 26.52 | V98: 14.50K | W98: 0.0051 | Y98: 23.07.2023 | Z98: 54910.93 | AA98: 53701.46 | AB98: 55169.49 | AC98: 53329.97 | AD98: 1.23B | AE98: 0.0225 | AG98: 45962 | AH98: 3.61
Q99: 07/30/2023 | R99: 26.99 | S99: 27.48 | T99: 27.53 | U99: 26.98 | V99: 5.91K | W99: -0.0142 | Y99: 30.07.2023 | Z99: 53991.42 | AA99: 54998.42 | AB99: 55244.82 | AC99: 53019.22 | AD99: 1.02B | AE99: -0.0167 | AG99: 45977 | AH99: 3.99
Q100: 45085 | R100: 27.19 | S100: 26.99 | T100: 27.2 | U100: 26.54 | V100: 74.31K | W100: 0.0074 | Y100: 06.08.2023 | Z100: 53242.16 | AA100: 54014.74 | AB100: 54435.43 | AC100: 53171.02 | AD100: 1.17B | AE100: -0.0139 | AG100: 45992 | AH100: 3.72
Q101: 08/13/2023 | R101: 27.2 | S101: 27.19 | T101: 27.2 | U101: 26.69 | V101: 864.74K | W101: 0.0004 | Y101: 13.08.2023 | Z101: 53194.39 | AA101: 53244.42 | AB101: 53968.96 | AC101: 52610.14 | AD101: 1.25B | AE101: -0.0009 | AG101: 46007 | AH101: 3.66
...

Sheet Rendimientos
A1: RENDIMIENTOS
B4: Soriana diario | C4: IPC diario | D4: Soriana semanal | E4: IPC semanal | G4: Precio actual de Soriana B para el modelo | H4: Valor
A5: Datos n | B5: =COUNT($AD$10:$AD$509) -> 63 | C5: =COUNT($AF$10:$AF$509) -> 73 | D5: =COUNT($AH$10:$AH$409) -> 259 | E5: =COUNT($AJ$10:$AJ$409) -> 261 | G5: Precio de cierre más reciente (MXN) | H5: =IF(B5>0,INDEX($T$10:$T$509,MATCH(MAX($S$10:$S$509),$S$10:$S$509,0)),IF(D5>0,INDEX($C$10:$C$409,MATCH(MAX($B$10:$B$409),$B$10:$B$409,0)),H8)) -> 33.1
A6: Primera fecha | B6: =IF(B5=0,"",MIN($AD$10:$AD$509)) -> 46204 | C6: =IF(C5=0,"",MIN($AF$10:$AF$509)) -> 46204 | D6: =IF(D5=0,"",MIN($AH$10:$AH$409)) -> 44486 | E6: =IF(E5=0,"",MIN($AJ$10:$AJ$409)) -> 44486 | G6: Fecha del precio | H6: =IF(B5>0,MAX($S$10:$S$509),IF(D5>0,MAX($B$10:$B$409),H9)) -> 46302
A7: Última fecha | B7: =IF(B5=0,"",MAX($AD$10:$AD$509)) -> 46302 | C7: =IF(C5=0,"",MAX($AF$10:$AF$509)) -> 46307 | D7: =IF(D5=0,"",MAX($AH$10:$AH$409)) -> 46299 | E7: =IF(E5=0,"",MAX($AJ$10:$AJ$409)) -> 46306 | G7: Fuente del precio | H7: =IF(B5>0,"Investing, diario",IF(D5>0,"Investing, semanal","RESPALDO: modelo anterior (25-sep-2026). Pega datos diarios en Base de Datos.")) -> Investing, diario
G8: Precio de respaldo (último registrado en el modelo anterior, MXN) | H8: 33.48 | AD8: LECTURA DE LO PEGADO
G9: Fecha de respaldo del precio | H9: 46290 | AD9: Fecha Soriana D | AE9: Último Soriana D | AF9: Fecha IPC D | AG9: Último IPC D | AH9: Fecha Soriana S | AI9: Último Soriana S | AJ9: Fecha IPC S | AK9: Último IPC S
G10: Fecha de valuación del modelo (= fecha del precio; respaldo 01-oct-2026) | H10: =IF(OR(B5>0,D5>0),H6,DATE(2026,10,1)) -> 46302 | AD10: =IF(ISNUMBER(AE10),IF(ISNUMBER('Base de Datos'!A6),IF('Base de Datos'!A6>20000,DATE(YEAR('Base de Datos'!A6),DAY('Base de Datos'!A6),MONTH('Base de Datos'!A6)),""),IF(TRIM('Base de Datos'!A6)="","",IFERROR(DATE(VALUE(RIGHT(TRIM('Base de Datos'!A6),4)),VALUE(LEFT(TRIM('Base de Datos'!A6),2)),VALUE(MID(TRIM('Base de Datos'!A6),4,2))),""))),"") -> 46204 | AE10: =IF(ISNUMBER('Base de Datos'!B6),'Base de Datos'!B6,IF(TRIM('Base de Datos'!B6)="","",IFERROR(IF(IFERROR(FIND("@",SUBSTITUTE(TRIM('Base de Datos'!B6),",","@",LEN(TRIM('Base de Datos'!B6))-LEN(SUBSTITUTE(TRIM('Base de Datos'!B6),",","")))),0)>IFERROR(FIND("@",SUBSTITUTE(TRIM('Base de Datos'!B6),".","@",LEN(TRIM('Base de Datos'!B6))-LEN(SUBSTITUTE(TRIM('Base de Datos'!B6),".","")))),0),_xlfn.NUMBERVALUE(SUBSTITUTE(SUBSTITUTE(TRIM('Base de Datos'!B6),".",""),",","."),".",","),_xlfn.NUMBERVALUE(SUBSTITUTE(TRIM('Base de Datos'!B6),",",""),".",",")),""))) -> 30.34 | AF10: =IF(ISNUMBER(AG10),IF(ISNUMBER('Base de Datos'!I6),IF('Base de Datos'!I6>20000,INT('Base de Datos'!I6),""),IF(TRIM('Base de Datos'!I6)="","",IFERROR(DATE(VALUE(RIGHT(TRIM('Base de Datos'!I6),4)),VALUE(MID(TRIM('Base de Datos'!I6),4,2)),VALUE(LEFT(TRIM('Base de Datos'!I6),2))),IFERROR(DATEVALUE(TRIM('Base de Datos'!I6)),"")))),"") -> 46204 | AG10: =IF(ISNUMBER('Base de Datos'!J6),'Base de Datos'!J6,IF(TRIM('Base de Datos'!J6)="","",IFERROR(IF(IFERROR(FIND("@",SUBSTITUTE(TRIM('Base de Datos'!J6),",","@",LEN(TRIM('Base de Datos'!J6))-LEN(SUBSTITUTE(TRIM('Base de Datos'!J6),",","")))),0)>IFERROR(FIND("@",SUBSTITUTE(TRIM('Base de Datos'!J6),".","@",LEN(TRIM('Base de Datos'!J6))-LEN(SUBSTITUTE(TRIM('Base de Datos'!J6),".","")))),0),_xlfn.NUMBERVALUE(SUBSTITUTE(SUBSTITUTE(TRIM('Base de Datos'!J6),".",""),",","."),".",","),_xlfn.NUMBERVALUE(SUBSTITUTE(TRIM('Base de Datos'!J6),",",""),".",",")),""))) -> 67247.79 | AH10: =IF(ISNUMBER(AI10),IF(ISNUMBER('Base de Datos'!Q6),IF('Base de Datos'!Q6>20000,DATE(YEAR('Base de Datos'!Q6),DAY('Base de Datos'!Q6),MONTH('Base de Datos'!Q6)),""),IF(TRIM('Base de Datos'!Q6)="","",IFERROR(DATE(VALUE(RIGHT(TRIM('Base de Datos'!Q6),4)),VALUE(LEFT(TRIM('Base de Datos'!Q6),2)),VALUE(MID(TRIM('Base de Datos'!Q6),4,2))),""))),"") -> 44486 | AI10: =IF(ISNUMBER('Base de Datos'!R6),'Base de Datos'!R6,IF(TRIM('Base de Datos'!R6)="","",IFERROR(IF(IFERROR(FIND("@",SUBSTITUTE(TRIM('Base de Datos'!R6),",","@",LEN(TRIM('Base de Datos'!R6))-LEN(SUBSTITUTE(TRIM('Base de Datos'!R6),",","")))),0)>IFERROR(FIND("@",SUBSTITUTE(TRIM('Base de Datos'!R6),".","@",LEN(TRIM('Base de Datos'!R6))-LEN(SUBSTITUTE(TRIM('Base de Datos'!R6),".","")))),0),_xlfn.NUMBERVALUE(SUBSTITUTE(SUBSTITUTE(TRIM('Base de Datos'!R6),".",""),",","."),".",","),_xlfn.NUMBERVALUE(SUBSTITUTE(TRIM('Base de Datos'!R6),",",""),".",",")),""))) -> 25 | AJ10: =IF(ISNUMBER(AK10),IF(ISNUMBER('Base de Datos'!Y6),IF('Base de Datos'!Y6>20000,INT('Base de Datos'!Y6),""),IF(TRIM('Base de Datos'!Y6)="","",IFERROR(DATE(VALUE(RIGHT(TRIM('Base de Datos'!Y6),4)),VALUE(MID(TRIM('Base de Datos'!Y6),4,2)),VALUE(LEFT(TRIM('Base de Datos'!Y6),2))),IFERROR(DATEVALUE(TRIM('Base de Datos'!Y6)),"")))),"") -> 44486 | AK10: =IF(ISNUMBER('Base de Datos'!Z6),'Base de Datos'!Z6,IF(TRIM('Base de Datos'!Z6)="","",IFERROR(IF(IFERROR(FIND("@",SUBSTITUTE(TRIM('Base de Datos'!Z6),",","@",LEN(TRIM('Base de Datos'!Z6))-LEN(SUBSTITUTE(TRIM('Base de Datos'!Z6),",","")))),0)>IFERROR(FIND("@",SUBSTITUTE(TRIM('Base de Datos'!Z6),".","@",LEN(TRIM('Base de Datos'!Z6))-LEN(SUBSTITUTE(TRIM('Base de Datos'!Z6),".","")))),0),_xlfn.NUMBERVALUE(SUBSTITUTE(SUBSTITUTE(TRIM('Base de Datos'!Z6),".",""),",","."),".",","),_xlfn.NUMBERVALUE(SUBSTITUTE(TRIM('Base de Datos'!Z6),",",""),".",",")),""))) -> 51889.66
A11: SEMANAL (base para la beta) | R11: DIARIO (precio actual y comparación) | AD11: =IF(ISNUMBER(AE11),IF(ISNUMBER('Base de Datos'!A7),IF('Base de Datos'!A7>20000,DATE(YEAR('Base de Datos'!A7),DAY('Base de Datos'!A7),MONTH('Base de Datos'!A7)),""),IF(TRIM('Base de Datos'!A7)="","",IFERROR(DATE(VALUE(RIGHT(TRIM('Base de Datos'!A7),4)),VALUE(LEFT(TRIM('Base de Datos'!A7),2)),VALUE(MID(TRIM('Base de Datos'!A7),4,2))),""))),"") -> 46205 | AE11: =IF(ISNUMBER('Base de Datos'!B7),'Base de Datos'!B7,IF(TRIM('Base de Datos'!B7)="","",IFERROR(IF(IFERROR(FIND("@",SUBSTITUTE(TRIM('Base de Datos'!B7),",","@",LEN(TRIM('Base de Datos'!B7))-LEN(SUBSTITUTE(TRIM('Base de Datos'!B7),",","")))),0)>IFERROR(FIND("@",SUBSTITUTE(TRIM('Base de Datos'!B7),".","@",LEN(TRIM('Base de Datos'!B7))-LEN(SUBSTITUTE(TRIM('Base de Datos'!B7),".","")))),0),_xlfn.NUMBERVALUE(SUBSTITUTE(SUBSTITUTE(TRIM('Base de Datos'!B7),".",""),",","."),".",","),_xlfn.NUMBERVALUE(SUBSTITUTE(TRIM('Base de Datos'!B7),",",""),".",",")),""))) -> 30.7 | AF11: =IF(ISNUMBER(AG11),IF(ISNUMBER('Base de Datos'!I7),IF('Base de Datos'!I7>20000,INT('Base de Datos'!I7),""),IF(TRIM('Base de Datos'!I7)="","",IFERROR(DATE(VALUE(RIGHT(TRIM('Base de Datos'!I7),4)),VALUE(MID(TRIM('Base de Datos'!I7),4,2)),VALUE(LEFT(TRIM('Base de Datos'!I7),2))),IFERROR(DATEVALUE(TRIM('Base de Datos'!I7)),"")))),"") -> 46205 | AG11: =IF(ISNUMBER('Base de Datos'!J7),'Base de Datos'!J7,IF(TRIM('Base de Datos'!J7)="","",IFERROR(IF(IFERROR(FIND("@",SUBSTITUTE(TRIM('Base de Datos'!J7),",","@",LEN(TRIM('Base de Datos'!J7))-LEN(SUBSTITUTE(TRIM('Base de Datos'!J7),",","")))),0)>IFERROR(FIND("@",SUBSTITUTE(TRIM('Base de Datos'!J7),".","@",LEN(TRIM('Base de Datos'!J7))-LEN(SUBSTITUTE(TRIM('Base de Datos'!J7),".","")))),0),_xlfn.NUMBERVALUE(SUBSTITUTE(SUBSTITUTE(TRIM('Base de Datos'!J7),".",""),",","."),".",","),_xlfn.NUMBERVALUE(SUBSTITUTE(TRIM('Base de Datos'!J7),",",""),".",",")),""))) -> 67071.11 | AH11: =IF(ISNUMBER(AI11),IF(ISNUMBER('Base de Datos'!Q7),IF('Base de Datos'!Q7>20000,DATE(YEAR('Base de Datos'!Q7),DAY('Base de Datos'!Q7),MONTH('Base de Datos'!Q7)),""),IF(TRIM('Base de Datos'!Q7)="","",IFERROR(DATE(VALUE(RIGHT(TRIM('Base de Datos'!Q7),4)),VALUE(LEFT(TRIM('Base de Datos'!Q7),2)),VALUE(MID(TRIM('Base de Datos'!Q7),4,2))),""))),"") -> 44493 | AI11: =IF(ISNUMBER('Base de Datos'!R7),'Base de Datos'!R7,IF(TRIM('Base de Datos'!R7)="","",IFERROR(IF(IFERROR(FIND("@",SUBSTITUTE(TRIM('Base de Datos'!R7),",","@",LEN(TRIM('Base de Datos'!R7))-LEN(SUBSTITUTE(TRIM('Base de Datos'!R7),",","")))),0)>IFERROR(FIND("@",SUBSTITUTE(TRIM('Base de Datos'!R7),".","@",LEN(TRIM('Base de Datos'!R7))-LEN(SUBSTITUTE(TRIM('Base de Datos'!R7),".","")))),0),_xlfn.NUMBERVALUE(SUBSTITUTE(SUBSTITUTE(TRIM('Base de Datos'!R7),".",""),",","."),".",","),_xlfn.NUMBERVALUE(SUBSTITUTE(TRIM('Base de Datos'!R7),",",""),".",",")),""))) -> 24.77 | AJ11: =IF(ISNUMBER(AK11),IF(ISNUMBER('Base de Datos'!Y7),IF('Base de Datos'!Y7>20000,INT('Base de Datos'!Y7),""),IF(TRIM('Base de Datos'!Y7)="","",IFERROR(DATE(VALUE(RIGHT(TRIM('Base de Datos'!Y7),4)),VALUE(MID(TRIM('Base de Datos'!Y7),4,2)),VALUE(LEFT(TRIM('Base de Datos'!Y7),2))),IFERROR(DATEVALUE(TRIM('Base de Datos'!Y7)),"")))),"") -> 44493 | AK11: =IF(ISNUMBER('Base de Datos'!Z7),'Base de Datos'!Z7,IF(TRIM('Base de Datos'!Z7)="","",IFERROR(IF(IFERROR(FIND("@",SUBSTITUTE(TRIM('Base de Datos'!Z7),",","@",LEN(TRIM('Base de Datos'!Z7))-LEN(SUBSTITUTE(TRIM('Base de Datos'!Z7),",","")))),0)>IFERROR(FIND("@",SUBSTITUTE(TRIM('Base de Datos'!Z7),".","@",LEN(TRIM('Base de Datos'!Z7))-LEN(SUBSTITUTE(TRIM('Base de Datos'!Z7),".","")))),0),_xlfn.NUMBERVALUE(SUBSTITUTE(SUBSTITUTE(TRIM('Base de Datos'!Z7),".",""),",","."),".",","),_xlfn.NUMBERVALUE(SUBSTITUTE(TRIM('Base de Datos'!Z7),",",""),".",",")),""))) -> 51309.84
A12: k | B12: Fecha | C12: Soriana B | D12: IPC | E12: Rend Soriana | F12: Rend IPC | G12: Par válido | J12: y: Rend. Soriana (ventana) | K12: x: Rend. IPC (ventana) | L12: No. en ventana | M12: Y compacto (Análisis de datos) | N12: X compacto (Análisis de datos) | O12: y gráfica | P12: x gráfica | R12: k | S12: Fecha | T12: Soriana B | U12: IPC | V12: Rend. Soriana | W12: Rend. IPC | X12: Par válido | Y12: y: Rend. Soriana | Z12: x: Rend. IPC | AA12: y gráfica | AB12: x gráfica | AD12: =IF(ISNUMBER(AE12),IF(ISNUMBER('Base de Datos'!A8),IF('Base de Datos'!A8>20000,DATE(YEAR('Base de Datos'!A8),DAY('Base de Datos'!A8),MONTH('Base de Datos'!A8)),""),IF(TRIM('Base de Datos'!A8)="","",IFERROR(DATE(VALUE(RIGHT(TRIM('Base de Datos'!A8),4)),VALUE(LEFT(TRIM('Base de Datos'!A8),2)),VALUE(MID(TRIM('Base de Datos'!A8),4,2))),""))),"") -> 46206 | AE12: =IF(ISNUMBER('Base de Datos'!B8),'Base de Datos'!B8,IF(TRIM('Base de Datos'!B8)="","",IFERROR(IF(IFERROR(FIND("@",SUBSTITUTE(TRIM('Base de Datos'!B8),",","@",LEN(TRIM('Base de Datos'!B8))-LEN(SUBSTITUTE(TRIM('Base de Datos'!B8),",","")))),0)>IFERROR(FIND("@",SUBSTITUTE(TRIM('Base de Datos'!B8),".","@",LEN(TRIM('Base de Datos'!B8))-LEN(SUBSTITUTE(TRIM('Base de Datos'!B8),".","")))),0),_xlfn.NUMBERVALUE(SUBSTITUTE(SUBSTITUTE(TRIM('Base de Datos'!B8),".",""),",","."),".",","),_xlfn.NUMBERVALUE(SUBSTITUTE(TRIM('Base de Datos'!B8),",",""),".",",")),""))) -> 29.91 | AF12: =IF(ISNUMBER(AG12),IF(ISNUMBER('Base de Datos'!I8),IF('Base de Datos'!I8>20000,INT('Base de Datos'!I8),""),IF(TRIM('Base de Datos'!I8)="","",IFERROR(DATE(VALUE(RIGHT(TRIM('Base de Datos'!I8),4)),VALUE(MID(TRIM('Base de Datos'!I8),4,2)),VALUE(LEFT(TRIM('Base de Datos'!I8),2))),IFERROR(DATEVALUE(TRIM('Base de Datos'!I8)),"")))),"") -> 46206 | AG12: =IF(ISNUMBER('Base de Datos'!J8),'Base de Datos'!J8,IF(TRIM('Base de Datos'!J8)="","",IFERROR(IF(IFERROR(FIND("@",SUBSTITUTE(TRIM('Base de Datos'!J8),",","@",LEN(TRIM('Base de Datos'!J8))-LEN(SUBSTITUTE(TRIM('Base de Datos'!J8),",","")))),0)>IFERROR(FIND("@",SUBSTITUTE(TRIM('Base de Datos'!J8),".","@",LEN(TRIM('Base de Datos'!J8))-LEN(SUBSTITUTE(TRIM('Base de Datos'!J8),".","")))),0),_xlfn.NUMBERVALUE(SUBSTITUTE(SUBSTITUTE(TRIM('Base de Datos'!J8),".",""),",","."),".",","),_xlfn.NUMBERVALUE(SUBSTITUTE(TRIM('Base de Datos'!J8),",",""),".",",")),""))) -> 67060.49 | AH12: =IF(ISNUMBER(AI12),IF(ISNUMBER('Base de Datos'!Q8),IF('Base de Datos'!Q8>20000,DATE(YEAR('Base de Datos'!Q8),DAY('Base de Datos'!Q8),MONTH('Base de Datos'!Q8)),""),IF(TRIM('Base de Datos'!Q8)="","",IFERROR(DATE(VALUE(RIGHT(TRIM('Base de Datos'!Q8),4)),VALUE(LEFT(TRIM('Base de Datos'!Q8),2)),VALUE(MID(TRIM('Base de Datos'!Q8),4,2))),""))),"") -> 44500 | AI12: =IF(ISNUMBER('Base de Datos'!R8),'Base de Datos'!R8,IF(TRIM('Base de Datos'!R8)="","",IFERROR(IF(IFERROR(FIND("@",SUBSTITUTE(TRIM('Base de Datos'!R8),",","@",LEN(TRIM('Base de Datos'!R8))-LEN(SUBSTITUTE(TRIM('Base de Datos'!R8),",","")))),0)>IFERROR(FIND("@",SUBSTITUTE(TRIM('Base de Datos'!R8),".","@",LEN(TRIM('Base de Datos'!R8))-LEN(SUBSTITUTE(TRIM('Base de Datos'!R8),".","")))),0),_xlfn.NUMBERVALUE(SUBSTITUTE(SUBSTITUTE(TRIM('Base de Datos'!R8),".",""),",","."),".",","),_xlfn.NUMBERVALUE(SUBSTITUTE(TRIM('Base de Datos'!R8),",",""),".",",")),""))) -> 24.48 | AJ12: =IF(ISNUMBER(AK12),IF(ISNUMBER('Base de Datos'!Y8),IF('Base de Datos'!Y8>20000,INT('Base de Datos'!Y8),""),IF(TRIM('Base de Datos'!Y8)="","",IFERROR(DATE(VALUE(RIGHT(TRIM('Base de Datos'!Y8),4)),VALUE(MID(TRIM('Base de Datos'!Y8),4,2)),VALUE(LEFT(TRIM('Base de Datos'!Y8),2))),IFERROR(DATEVALUE(TRIM('Base de Datos'!Y8)),"")))),"") -> 44500 | AK12: =IF(ISNUMBER('Base de Datos'!Z8),'Base de Datos'!Z8,IF(TRIM('Base de Datos'!Z8)="","",IFERROR(IF(IFERROR(FIND("@",SUBSTITUTE(TRIM('Base de Datos'!Z8),",","@",LEN(TRIM('Base de Datos'!Z8))-LEN(SUBSTITUTE(TRIM('Base de Datos'!Z8),",","")))),0)>IFERROR(FIND("@",SUBSTITUTE(TRIM('Base de Datos'!Z8),".","@",LEN(TRIM('Base de Datos'!Z8))-LEN(SUBSTITUTE(TRIM('Base de Datos'!Z8),".","")))),0),_xlfn.NUMBERVALUE(SUBSTITUTE(SUBSTITUTE(TRIM('Base de Datos'!Z8),".",""),",","."),".",","),_xlfn.NUMBERVALUE(SUBSTITUTE(TRIM('Base de Datos'!Z8),",",""),".",",")),""))) -> 51977.96
A13: =ROWS(A$13:A13) -> 1 | B13: =IF(COUNT($AH$10:$AH$409)=0,"",MIN($AH$10:$AH$409)) -> 44486 | C13: =IF(B13="","",INDEX($AI$10:$AI$409,MATCH(B13,$AH$10:$AH$409,0))) -> 25 | D13: =IF(B13="","",IFERROR(INDEX($AK$10:$AK$409,MATCH(B13,$AJ$10:$AJ$409,0)),"")) -> 51889.66 | E13: ="" | F13: ="" | G13: =IF(AND(ISNUMBER(E13),ISNUMBER(F13)),1,"") | H13: =IF(G13=1,COUNT(G13:G$412),"") | I13: =IF(G13=1,IF(H13<='Beta Regresión'!$B$5,1,""),"") | J13: =IF(I13=1,E13,"") | K13: =IF(I13=1,F13,"") | L13: =IF(I13=1,COUNT(I$13:I13),"") | M13: =IFERROR(INDEX($J$13:$J$412,MATCH(A13,$L$13:$L$412,0)),"") -> -0.0092 | N13: =IFERROR(INDEX($K$13:$K$412,MATCH(A13,$L$13:$L$412,0)),"") -> -0.011174095 | O13: =IF(I13=1,E13,NA()) -> #N/A | P13: =IF(I13=1,F13,NA()) -> #N/A | R13: =ROWS(R$13:R13) -> 1 | S13: =IF(COUNT($AD$10:$AD$509)=0,"",MIN($AD$10:$AD$509)) -> 46204 | T13: =IF(S13="","",INDEX($AE$10:$AE$509,MATCH(S13,$AD$10:$AD$509,0))) -> 30.34 | U13: =IF(S13="","",IFERROR(INDEX($AG$10:$AG$509,MATCH(S13,$AF$10:$AF$509,0)),"")) -> 67247.79 | V13: ="" | W13: ="" | X13: =IF(AND(ISNUMBER(V13),ISNUMBER(W13)),1,"") | Y13: =IF(X13=1,V13,"") | Z13: =IF(X13=1,W13,"") | AA13: =IF(X13=1,V13,NA()) -> #N/A | AB13: =IF(X13=1,W13,NA()) -> #N/A | AD13: =IF(ISNUMBER(AE13),IF(ISNUMBER('Base de Datos'!A9),IF('Base de Datos'!A9>20000,DATE(YEAR('Base de Datos'!A9),DAY('Base de Datos'!A9),MONTH('Base de Datos'!A9)),""),IF(TRIM('Base de Datos'!A9)="","",IFERROR(DATE(VALUE(RIGHT(TRIM('Base de Datos'!A9),4)),VALUE(LEFT(TRIM('Base de Datos'!A9),2)),VALUE(MID(TRIM('Base de Datos'!A9),4,2))),""))),"") -> 46209 | AE13: =IF(ISNUMBER('Base de Datos'!B9),'Base de Datos'!B9,IF(TRIM('Base de Datos'!B9)="","",IFERROR(IF(IFERROR(FIND("@",SUBSTITUTE(TRIM('Base de Datos'!B9),",","@",LEN(TRIM('Base de Datos'!B9))-LEN(SUBSTITUTE(TRIM('Base de Datos'!B9),",","")))),0)>IFERROR(FIND("@",SUBSTITUTE(TRIM('Base de Datos'!B9),".","@",LEN(TRIM('Base de Datos'!B9))-LEN(SUBSTITUTE(TRIM('Base de Datos'!B9),".","")))),0),_xlfn.NUMBERVALUE(SUBSTITUTE(SUBSTITUTE(TRIM('Base de Datos'!B9),".",""),",","."),".",","),_xlfn.NUMBERVALUE(SUBSTITUTE(TRIM('Base de Datos'!B9),",",""),".",",")),""))) -> 29.6 | AF13: =IF(ISNUMBER(AG13),IF(ISNUMBER('Base de Datos'!I9),IF('Base de Datos'!I9>20000,INT('Base de Datos'!I9),""),IF(TRIM('Base de Datos'!I9)="","",IFERROR(DATE(VALUE(RIGHT(TRIM('Base de Datos'!I9),4)),VALUE(MID(TRIM('Base de Datos'!I9),4,2)),VALUE(LEFT(TRIM('Base de Datos'!I9),2))),IFERROR(DATEVALUE(TRIM('Base de Datos'!I9)),"")))),"") -> 46209 | AG13: =IF(ISNUMBER('Base de Datos'!J9),'Base de Datos'!J9,IF(TRIM('Base de Datos'!J9)="","",IFERROR(IF(IFERROR(FIND("@",SUBSTITUTE(TRIM('Base de Datos'!J9),",","@",LEN(TRIM('Base de Datos'!J9))-LEN(SUBSTITUTE(TRIM('Base de Datos'!J9),",","")))),0)>IFERROR(FIND("@",SUBSTITUTE(TRIM('Base de Datos'!J9),".","@",LEN(TRIM('Base de Datos'!J9))-LEN(SUBSTITUTE(TRIM('Base de Datos'!J9),".","")))),0),_xlfn.NUMBERVALUE(SUBSTITUTE(SUBSTITUTE(TRIM('Base de Datos'!J9),".",""),",","."),".",","),_xlfn.NUMBERVALUE(SUBSTITUTE(TRIM('Base de Datos'!J9),",",""),".",",")),""))) -> 67466.46 | AH13: =IF(ISNUMBER(AI13),IF(ISNUMBER('Base de Datos'!Q9),IF('Base de Datos'!Q9>20000,DATE(YEAR('Base de Datos'!Q9),DAY('Base de Datos'!Q9),MONTH('Base de Datos'!Q9)),""),IF(TRIM('Base de Datos'!Q9)="","",IFERROR(DATE(VALUE(RIGHT(TRIM('Base de Datos'!Q9),4)),VALUE(LEFT(TRIM('Base de Datos'!Q9),2)),VALUE(MID(TRIM('Base de Datos'!Q9),4,2))),""))),"") -> 44507 | AI13: =IF(ISNUMBER('Base de Datos'!R9),'Base de Datos'!R9,IF(TRIM('Base de Datos'!R9)="","",IFERROR(IF(IFERROR(FIND("@",SUBSTITUTE(TRIM('Base de Datos'!R9),",","@",LEN(TRIM('Base de Datos'!R9))-LEN(SUBSTITUTE(TRIM('Base de Datos'!R9),",","")))),0)>IFERROR(FIND("@",SUBSTITUTE(TRIM('Base de Datos'!R9),".","@",LEN(TRIM('Base de Datos'!R9))-LEN(SUBSTITUTE(TRIM('Base de Datos'!R9),".","")))),0),_xlfn.NUMBERVALUE(SUBSTITUTE(SUBSTITUTE(TRIM('Base de Datos'!R9),".",""),",","."),".",","),_xlfn.NUMBERVALUE(SUBSTITUTE(TRIM('Base de Datos'!R9),",",""),".",",")),""))) -> 23.77 | AJ13: =IF(ISNUMBER(AK13),IF(ISNUMBER('Base de Datos'!Y9),IF('Base de Datos'!Y9>20000,INT('Base de Datos'!Y9),""),IF(TRIM('Base de Datos'!Y9)="","",IFERROR(DATE(VALUE(RIGHT(TRIM('Base de Datos'!Y9),4)),VALUE(MID(TRIM('Base de Datos'!Y9),4,2)),VALUE(LEFT(TRIM('Base de Datos'!Y9),2))),IFERROR(DATEVALUE(TRIM('Base de Datos'!Y9)),"")))),"") -> 44507 | AK13: =IF(ISNUMBER('Base de Datos'!Z9),'Base de Datos'!Z9,IF(TRIM('Base de Datos'!Z9)="","",IFERROR(IF(IFERROR(FIND("@",SUBSTITUTE(TRIM('Base de Datos'!Z9),",","@",LEN(TRIM('Base de Datos'!Z9))-LEN(SUBSTITUTE(TRIM('Base de Datos'!Z9),",","")))),0)>IFERROR(FIND("@",SUBSTITUTE(TRIM('Base de Datos'!Z9),".","@",LEN(TRIM('Base de Datos'!Z9))-LEN(SUBSTITUTE(TRIM('Base de Datos'!Z9),".","")))),0),_xlfn.NUMBERVALUE(SUBSTITUTE(SUBSTITUTE(TRIM('Base de Datos'!Z9),".",""),",","."),".",","),_xlfn.NUMBERVALUE(SUBSTITUTE(TRIM('Base de Datos'!Z9),",",""),".",",")),""))) -> 51432.54
A14: =ROWS(A$13:A14) -> 2 | B14: =IF(B13="","",IFERROR(SMALL($AH$10:$AH$409,COUNTIF($AH$10:$AH$409,"<="&B13)+1),"")) -> 44493 | C14: =IF(B14="","",INDEX($AI$10:$AI$409,MATCH(B14,$AH$10:$AH$409,0))) -> 24.77 | D14: =IF(B14="","",IFERROR(INDEX($AK$10:$AK$409,MATCH(B14,$AJ$10:$AJ$409,0)),"")) -> 51309.84 | E14: =IF(AND(ISNUMBER(C14),ISNUMBER(C13)),C14/C13-1,"") -> -0.0092 | F14: =IF(AND(ISNUMBER(D14),ISNUMBER(D13)),D14/D13-1,"") -> -0.011174095 | G14: =IF(AND(ISNUMBER(E14),ISNUMBER(F14)),1,"") -> 1 | H14: =IF(G14=1,COUNT(G14:G$412),"") -> 258 | I14: =IF(G14=1,IF(H14<='Beta Regresión'!$B$5,1,""),"") -> 1 | J14: =IF(I14=1,E14,"") -> -0.0092 | K14: =IF(I14=1,F14,"") -> -0.011174095 | L14: =IF(I14=1,COUNT(I$13:I14),"") -> 1 | M14: =IFERROR(INDEX($J$13:$J$412,MATCH(A14,$L$13:$L$412,0)),"") -> -0.011707711 | N14: =IFERROR(INDEX($K$13:$K$412,MATCH(A14,$L$13:$L$412,0)),"") -> 0.013021284 | O14: =IF(I14=1,E14,NA()) -> -0.0092 | P14: =IF(I14=1,F14,NA()) -> -0.011174095 | R14: =ROWS(R$13:R14) -> 2 | S14: =IF(S13="","",IFERROR(SMALL($AD$10:$AD$509,COUNTIF($AD$10:$AD$509,"<="&S13)+1),"")) -> 46205 | T14: =IF(S14="","",INDEX($AE$10:$AE$509,MATCH(S14,$AD$10:$AD$509,0))) -> 30.7 | U14: =IF(S14="","",IFERROR(INDEX($AG$10:$AG$509,MATCH(S14,$AF$10:$AF$509,0)),"")) -> 67071.11 | V14: =IF(AND(ISNUMBER(T14),ISNUMBER(T13)),T14/T13-1,"") -> 0.011865524 | W14: =IF(AND(ISNUMBER(U14),ISNUMBER(U13)),U14/U13-1,"") -> -0.0026272982 | X14: =IF(AND(ISNUMBER(V14),ISNUMBER(W14)),1,"") -> 1 | Y14: =IF(X14=1,V14,"") -> 0.011865524 | Z14: =IF(X14=1,W14,"") -> -0.0026272982 | AA14: =IF(X14=1,V14,NA()) -> 0.011865524 | AB14: =IF(X14=1,W14,NA()) -> -0.0026272982 | AD14: =IF(ISNUMBER(AE14),IF(ISNUMBER('Base de Datos'!A10),IF('Base de Datos'!A10>20000,DATE(YEAR('Base de Datos'!A10),DAY('Base de Datos'!A10),MONTH('Base de Datos'!A10)),""),IF(TRIM('Base de Datos'!A10)="","",IFERROR(DATE(VALUE(RIGHT(TRIM('Base de Datos'!A10),4)),VALUE(LEFT(TRIM('Base de Datos'!A10),2)),VALUE(MID(TRIM('Base de Datos'!A10),4,2))),""))),"") -> 46210 | AE14: =IF(ISNUMBER('Base de Datos'!B10),'Base de Datos'!B10,IF(TRIM('Base de Datos'!B10)="","",IFERROR(IF(IFERROR(FIND("@",SUBSTITUTE(TRIM('Base de Datos'!B10),",","@",LEN(TRIM('Base de Datos'!B10))-LEN(SUBSTITUTE(TRIM('Base de Datos'!B10),",","")))),0)>IFERROR(FIND("@",SUBSTITUTE(TRIM('Base de Datos'!B10),".","@",LEN(TRIM('Base de Datos'!B10))-LEN(SUBSTITUTE(TRIM('Base de Datos'!B10),".","")))),0),_xlfn.NUMBERVALUE(SUBSTITUTE(SUBSTITUTE(TRIM('Base de Datos'!B10),".",""),",","."),".",","),_xlfn.NUMBERVALUE(SUBSTITUTE(TRIM('Base de Datos'!B10),",",""),".",",")),""))) -> 30.29 | AF14: =IF(ISNUMBER(AG14),IF(ISNUMBER('Base de Datos'!I10),IF('Base de Datos'!I10>20000,INT('Base de Datos'!I10),""),IF(TRIM('Base de Datos'!I10)="","",IFERROR(DATE(VALUE(RIGHT(TRIM('Base de Datos'!I10),4)),VALUE(MID(TRIM('Base de Datos'!I10),4,2)),VALUE(LEFT(TRIM('Base de Datos'!I10),2))),IFERROR(DATEVALUE(TRIM('Base de Datos'!I10)),"")))),"") -> 46210 | AG14: =IF(ISNUMBER('Base de Datos'!J10),'Base de Datos'!J10,IF(TRIM('Base de Datos'!J10)="","",IFERROR(IF(IFERROR(FIND("@",SUBSTITUTE(TRIM('Base de Datos'!J10),",","@",LEN(TRIM('Base de Datos'!J10))-LEN(SUBSTITUTE(TRIM('Base de Datos'!J10),",","")))),0)>IFERROR(FIND("@",SUBSTITUTE(TRIM('Base de Datos'!J10),".","@",LEN(TRIM('Base de Datos'!J10))-LEN(SUBSTITUTE(TRIM('Base de Datos'!J10),".","")))),0),_xlfn.NUMBERVALUE(SUBSTITUTE(SUBSTITUTE(TRIM('Base de Datos'!J10),".",""),",","."),".",","),_xlfn.NUMBERVALUE(SUBSTITUTE(TRIM('Base de Datos'!J10),",",""),".",",")),""))) -> 66674.7 | AH14: =IF(ISNUMBER(AI14),IF(ISNUMBER('Base de Datos'!Q10),IF('Base de Datos'!Q10>20000,DATE(YEAR('Base de Datos'!Q10),DAY('Base de Datos'!Q10),MONTH('Base de Datos'!Q10)),""),IF(TRIM('Base de Datos'!Q10)="","",IFERROR(DATE(VALUE(RIGHT(TRIM('Base de Datos'!Q10),4)),VALUE(LEFT(TRIM('Base de Datos'!Q10),2)),VALUE(MID(TRIM('Base de Datos'!Q10),4,2))),""))),"") -> 44514 | AI14: =IF(ISNUMBER('Base de Datos'!R10),'Base de Datos'!R10,IF(TRIM('Base de Datos'!R10)="","",IFERROR(IF(IFERROR(FIND("@",SUBSTITUTE(TRIM('Base de Datos'!R10),",","@",LEN(TRIM('Base de Datos'!R10))-LEN(SUBSTITUTE(TRIM('Base de Datos'!R10),",","")))),0)>IFERROR(FIND("@",SUBSTITUTE(TRIM('Base de Datos'!R10),".","@",LEN(TRIM('Base de Datos'!R10))-LEN(SUBSTITUTE(TRIM('Base de Datos'!R10),".","")))),0),_xlfn.NUMBERVALUE(SUBSTITUTE(SUBSTITUTE(TRIM('Base de Datos'!R10),".",""),",","."),".",","),_xlfn.NUMBERVALUE(SUBSTITUTE(TRIM('Base de Datos'!R10),",",""),".",",")),""))) -> 22.99 | AJ14: =IF(ISNUMBER(AK14),IF(ISNUMBER('Base de Datos'!Y10),IF('Base de Datos'!Y10>20000,INT('Base de Datos'!Y10),""),IF(TRIM('Base de Datos'!Y10)="","",IFERROR(DATE(VALUE(RIGHT(TRIM('Base de Datos'!Y10),4)),VALUE(MID(TRIM('Base de Datos'!Y10),4,2)),VALUE(LEFT(TRIM('Base de Datos'!Y10),2))),IFERROR(DATEVALUE(TRIM('Base de Datos'!Y10)),"")))),"") -> 44514 | AK14: =IF(ISNUMBER('Base de Datos'!Z10),'Base de Datos'!Z10,IF(TRIM('Base de Datos'!Z10)="","",IFERROR(IF(IFERROR(FIND("@",SUBSTITUTE(TRIM('Base de Datos'!Z10),",","@",LEN(TRIM('Base de Datos'!Z10))-LEN(SUBSTITUTE(TRIM('Base de Datos'!Z10),",","")))),0)>IFERROR(FIND("@",SUBSTITUTE(TRIM('Base de Datos'!Z10),".","@",LEN(TRIM('Base de Datos'!Z10))-LEN(SUBSTITUTE(TRIM('Base de Datos'!Z10),".","")))),0),_xlfn.NUMBERVALUE(SUBSTITUTE(SUBSTITUTE(TRIM('Base de Datos'!Z10),".",""),",","."),".",","),_xlfn.NUMBERVALUE(SUBSTITUTE(TRIM('Base de Datos'!Z10),",",""),".",",")),""))) -> 50811.3
A15: =ROWS(A$13:A15) -> 3 | B15: =IF(B14="","",IFERROR(SMALL($AH$10:$AH$409,COUNTIF($AH$10:$AH$409,"<="&B14)+1),"")) -> 44500 | C15: =IF(B15="","",INDEX($AI$10:$AI$409,MATCH(B15,$AH$10:$AH$409,0))) -> 24.48 | D15: =IF(B15="","",IFERROR(INDEX($AK$10:$AK$409,MATCH(B15,$AJ$10:$AJ$409,0)),"")) -> 51977.96 | E15: =IF(AND(ISNUMBER(C15),ISNUMBER(C14)),C15/C14-1,"") -> -0.011707711 | F15: =IF(AND(ISNUMBER(D15),ISNUMBER(D14)),D15/D14-1,"") -> 0.013021284 | G15: =IF(AND(ISNUMBER(E15),ISNUMBER(F15)),1,"") -> 1 | H15: =IF(G15=1,COUNT(G15:G$412),"") -> 257 | I15: =IF(G15=1,IF(H15<='Beta Regresión'!$B$5,1,""),"") -> 1 | J15: =IF(I15=1,E15,"") -> -0.011707711 | K15: =IF(I15=1,F15,"") -> 0.013021284 | L15: =IF(I15=1,COUNT(I$13:I15),"") -> 2 | M15: =IFERROR(INDEX($J$13:$J$412,MATCH(A15,$L$13:$L$412,0)),"") -> -0.029003268 | N15: =IFERROR(INDEX($K$13:$K$412,MATCH(A15,$L$13:$L$412,0)),"") -> -0.010493294 | O15: =IF(I15=1,E15,NA()) -> -0.011707711 | P15: =IF(I15=1,F15,NA()) -> 0.013021284 | R15: =ROWS(R$13:R15) -> 3 | S15: =IF(S14="","",IFERROR(SMALL($AD$10:$AD$509,COUNTIF($AD$10:$AD$509,"<="&S14)+1),"")) -> 46206 | T15: =IF(S15="","",INDEX($AE$10:$AE$509,MATCH(S15,$AD$10:$AD$509,0))) -> 29.91 | U15: =IF(S15="","",IFERROR(INDEX($AG$10:$AG$509,MATCH(S15,$AF$10:$AF$509,0)),"")) -> 67060.49 | V15: =IF(AND(ISNUMBER(T15),ISNUMBER(T14)),T15/T14-1,"") -> -0.025732899 | W15: =IF(AND(ISNUMBER(U15),ISNUMBER(U14)),U15/U14-1,"") -> -0.00015833941 | X15: =IF(AND(ISNUMBER(V15),ISNUMBER(W15)),1,"") -> 1 | Y15: =IF(X15=1,V15,"") -> -0.025732899 | Z15: =IF(X15=1,W15,"") -> -0.00015833941 | AA15: =IF(X15=1,V15,NA()) -> -0.025732899 | AB15: =IF(X15=1,W15,NA()) -> -0.00015833941 | AD15: =IF(ISNUMBER(AE15),IF(ISNUMBER('Base de Datos'!A11),IF('Base de Datos'!A11>20000,DATE(YEAR('Base de Datos'!A11),DAY('Base de Datos'!A11),MONTH('Base de Datos'!A11)),""),IF(TRIM('Base de Datos'!A11)="","",IFERROR(DATE(VALUE(RIGHT(TRIM('Base de Datos'!A11),4)),VALUE(LEFT(TRIM('Base de Datos'!A11),2)),VALUE(MID(TRIM('Base de Datos'!A11),4,2))),""))),"") -> 46211 | AE15: =IF(ISNUMBER('Base de Datos'!B11),'Base de Datos'!B11,IF(TRIM('Base de Datos'!B11)="","",IFERROR(IF(IFERROR(FIND("@",SUBSTITUTE(TRIM('Base de Datos'!B11),",","@",LEN(TRIM('Base de Datos'!B11))-LEN(SUBSTITUTE(TRIM('Base de Datos'!B11),",","")))),0)>IFERROR(FIND("@",SUBSTITUTE(TRIM('Base de Datos'!B11),".","@",LEN(TRIM('Base de Datos'!B11))-LEN(SUBSTITUTE(TRIM('Base de Datos'!B11),".","")))),0),_xlfn.NUMBERVALUE(SUBSTITUTE(SUBSTITUTE(TRIM('Base de Datos'!B11),".",""),",","."),".",","),_xlfn.NUMBERVALUE(SUBSTITUTE(TRIM('Base de Datos'!B11),",",""),".",",")),""))) -> 30 | AF15: =IF(ISNUMBER(AG15),IF(ISNUMBER('Base de Datos'!I11),IF('Base de Datos'!I11>20000,INT('Base de Datos'!I11),""),IF(TRIM('Base de Datos'!I11)="","",IFERROR(DATE(VALUE(RIGHT(TRIM('Base de Datos'!I11),4)),VALUE(MID(TRIM('Base de Datos'!I11),4,2)),VALUE(LEFT(TRIM('Base de Datos'!I11),2))),IFERROR(DATEVALUE(TRIM('Base de Datos'!I11)),"")))),"") -> 46211 | AG15: =IF(ISNUMBER('Base de Datos'!J11),'Base de Datos'!J11,IF(TRIM('Base de Datos'!J11)="","",IFERROR(IF(IFERROR(FIND("@",SUBSTITUTE(TRIM('Base de Datos'!J11),",","@",LEN(TRIM('Base de Datos'!J11))-LEN(SUBSTITUTE(TRIM('Base de Datos'!J11),",","")))),0)>IFERROR(FIND("@",SUBSTITUTE(TRIM('Base de Datos'!J11),".","@",LEN(TRIM('Base de Datos'!J11))-LEN(SUBSTITUTE(TRIM('Base de Datos'!J11),".","")))),0),_xlfn.NUMBERVALUE(SUBSTITUTE(SUBSTITUTE(TRIM('Base de Datos'!J11),".",""),",","."),".",","),_xlfn.NUMBERVALUE(SUBSTITUTE(TRIM('Base de Datos'!J11),",",""),".",",")),""))) -> 66609.64 | AH15: =IF(ISNUMBER(AI15),IF(ISNUMBER('Base de Datos'!Q11),IF('Base de Datos'!Q11>20000,DATE(YEAR('Base de Datos'!Q11),DAY('Base de Datos'!Q11),MONTH('Base de Datos'!Q11)),""),IF(TRIM('Base de Datos'!Q11)="","",IFERROR(DATE(VALUE(RIGHT(TRIM('Base de Datos'!Q11),4)),VALUE(LEFT(TRIM('Base de Datos'!Q11),2)),VALUE(MID(TRIM('Base de Datos'!Q11),4,2))),""))),"") -> 44521 | AI15: =IF(ISNUMBER('Base de Datos'!R11),'Base de Datos'!R11,IF(TRIM('Base de Datos'!R11)="","",IFERROR(IF(IFERROR(FIND("@",SUBSTITUTE(TRIM('Base de Datos'!R11),",","@",LEN(TRIM('Base de Datos'!R11))-LEN(SUBSTITUTE(TRIM('Base de Datos'!R11),",","")))),0)>IFERROR(FIND("@",SUBSTITUTE(TRIM('Base de Datos'!R11),".","@",LEN(TRIM('Base de Datos'!R11))-LEN(SUBSTITUTE(TRIM('Base de Datos'!R11),".","")))),0),_xlfn.NUMBERVALUE(SUBSTITUTE(SUBSTITUTE(TRIM('Base de Datos'!R11),".",""),",","."),".",","),_xlfn.NUMBERVALUE(SUBSTITUTE(TRIM('Base de Datos'!R11),",",""),".",",")),""))) -> 22.73 | AJ15: =IF(ISNUMBER(AK15),IF(ISNUMBER('Base de Datos'!Y11),IF('Base de Datos'!Y11>20000,INT('Base de Datos'!Y11),""),IF(TRIM('Base de Datos'!Y11)="","",IFERROR(DATE(VALUE(RIGHT(TRIM('Base de Datos'!Y11),4)),VALUE(MID(TRIM('Base de Datos'!Y11),4,2)),VALUE(LEFT(TRIM('Base de Datos'!Y11),2))),IFERROR(DATEVALUE(TRIM('Base de Datos'!Y11)),"")))),"") -> 44521 | AK15: =IF(ISNUMBER('Base de Datos'!Z11),'Base de Datos'!Z11,IF(TRIM('Base de Datos'!Z11)="","",IFERROR(IF(IFERROR(FIND("@",SUBSTITUTE(TRIM('Base de Datos'!Z11),",","@",LEN(TRIM('Base de Datos'!Z11))-LEN(SUBSTITUTE(TRIM('Base de Datos'!Z11),",","")))),0)>IFERROR(FIND("@",SUBSTITUTE(TRIM('Base de Datos'!Z11),".","@",LEN(TRIM('Base de Datos'!Z11))-LEN(SUBSTITUTE(TRIM('Base de Datos'!Z11),".","")))),0),_xlfn.NUMBERVALUE(SUBSTITUTE(SUBSTITUTE(TRIM('Base de Datos'!Z11),".",""),",","."),".",","),_xlfn.NUMBERVALUE(SUBSTITUTE(TRIM('Base de Datos'!Z11),",",""),".",",")),""))) -> 49492.52
A16: =ROWS(A$13:A16) -> 4 | B16: =IF(B15="","",IFERROR(SMALL($AH$10:$AH$409,COUNTIF($AH$10:$AH$409,"<="&B15)+1),"")) -> 44507 | C16: =IF(B16="","",INDEX($AI$10:$AI$409,MATCH(B16,$AH$10:$AH$409,0))) -> 23.77 | D16: =IF(B16="","",IFERROR(INDEX($AK$10:$AK$409,MATCH(B16,$AJ$10:$AJ$409,0)),"")) -> 51432.54 | E16: =IF(AND(ISNUMBER(C16),ISNUMBER(C15)),C16/C15-1,"") -> -0.029003268 | F16: =IF(AND(ISNUMBER(D16),ISNUMBER(D15)),D16/D15-1,"") -> -0.010493294 | G16: =IF(AND(ISNUMBER(E16),ISNUMBER(F16)),1,"") -> 1 | H16: =IF(G16=1,COUNT(G16:G$412),"") -> 256 | I16: =IF(G16=1,IF(H16<='Beta Regresión'!$B$5,1,""),"") -> 1 | J16: =IF(I16=1,E16,"") -> -0.029003268 | K16: =IF(I16=1,F16,"") -> -0.010493294 | L16: =IF(I16=1,COUNT(I$13:I16),"") -> 3 | M16: =IFERROR(INDEX($J$13:$J$412,MATCH(A16,$L$13:$L$412,0)),"") -> -0.032814472 | N16: =IFERROR(INDEX($K$13:$K$412,MATCH(A16,$L$13:$L$412,0)),"") -> -0.012078735 | O16: =IF(I16=1,E16,NA()) -> -0.029003268 | P16: =IF(I16=1,F16,NA()) -> -0.010493294 | R16: =ROWS(R$13:R16) -> 4 | S16: =IF(S15="","",IFERROR(SMALL($AD$10:$AD$509,COUNTIF($AD$10:$AD$509,"<="&S15)+1),"")) -> 46209 | T16: =IF(S16="","",INDEX($AE$10:$AE$509,MATCH(S16,$AD$10:$AD$509,0))) -> 29.6 | U16: =IF(S16="","",IFERROR(INDEX($AG$10:$AG$509,MATCH(S16,$AF$10:$AF$509,0)),"")) -> 67466.46 | V16: =IF(AND(ISNUMBER(T16),ISNUMBER(T15)),T16/T15-1,"") -> -0.010364427 | W16: =IF(AND(ISNUMBER(U16),ISNUMBER(U15)),U16/U15-1,"") -> 0.0060537882 | X16: =IF(AND(ISNUMBER(V16),ISNUMBER(W16)),1,"") -> 1 | Y16: =IF(X16=1,V16,"") -> -0.010364427 | Z16: =IF(X16=1,W16,"") -> 0.0060537882 | AA16: =IF(X16=1,V16,NA()) -> -0.010364427 | AB16: =IF(X16=1,W16,NA()) -> 0.0060537882 | AD16: =IF(ISNUMBER(AE16),IF(ISNUMBER('Base de Datos'!A12),IF('Base de Datos'!A12>20000,DATE(YEAR('Base de Datos'!A12),DAY('Base de Datos'!A12),MONTH('Base de Datos'!A12)),""),IF(TRIM('Base de Datos'!A12)="","",IFERROR(DATE(VALUE(RIGHT(TRIM('Base de Datos'!A12),4)),VALUE(LEFT(TRIM('Base de Datos'!A12),2)),VALUE(MID(TRIM('Base de Datos'!A12),4,2))),""))),"") -> 46212 | AE16: =IF(ISNUMBER('Base de Datos'!B12),'Base de Datos'!B12,IF(TRIM('Base de Datos'!B12)="","",IFERROR(IF(IFERROR(FIND("@",SUBSTITUTE(TRIM('Base de Datos'!B12),",","@",LEN(TRIM('Base de Datos'!B12))-LEN(SUBSTITUTE(TRIM('Base de Datos'!B12),",","")))),0)>IFERROR(FIND("@",SUBSTITUTE(TRIM('Base de Datos'!B12),".","@",LEN(TRIM('Base de Datos'!B12))-LEN(SUBSTITUTE(TRIM('Base de Datos'!B12),".","")))),0),_xlfn.NUMBERVALUE(SUBSTITUTE(SUBSTITUTE(TRIM('Base de Datos'!B12),".",""),",","."),".",","),_xlfn.NUMBERVALUE(SUBSTITUTE(TRIM('Base de Datos'!B12),",",""),".",",")),""))) -> 30.76 | AF16: =IF(ISNUMBER(AG16),IF(ISNUMBER('Base de Datos'!I12),IF('Base de Datos'!I12>20000,INT('Base de Datos'!I12),""),IF(TRIM('Base de Datos'!I12)="","",IFERROR(DATE(VALUE(RIGHT(TRIM('Base de Datos'!I12),4)),VALUE(MID(TRIM('Base de Datos'!I12),4,2)),VALUE(LEFT(TRIM('Base de Datos'!I12),2))),IFERROR(DATEVALUE(TRIM('Base de Datos'!I12)),"")))),"") -> 46212 | AG16: =IF(ISNUMBER('Base de Datos'!J12),'Base de Datos'!J12,IF(TRIM('Base de Datos'!J12)="","",IFERROR(IF(IFERROR(FIND("@",SUBSTITUTE(TRIM('Base de Datos'!J12),",","@",LEN(TRIM('Base de Datos'!J12))-LEN(SUBSTITUTE(TRIM('Base de Datos'!J12),",","")))),0)>IFERROR(FIND("@",SUBSTITUTE(TRIM('Base de Datos'!J12),".","@",LEN(TRIM('Base de Datos'!J12))-LEN(SUBSTITUTE(TRIM('Base de Datos'!J12),".","")))),0),_xlfn.NUMBERVALUE(SUBSTITUTE(SUBSTITUTE(TRIM('Base de Datos'!J12),".",""),",","."),".",","),_xlfn.NUMBERVALUE(SUBSTITUTE(TRIM('Base de Datos'!J12),",",""),".",",")),""))) -> 66107.28 | AH16: =IF(ISNUMBER(AI16),IF(ISNUMBER('Base de Datos'!Q12),IF('Base de Datos'!Q12>20000,DATE(YEAR('Base de Datos'!Q12),DAY('Base de Datos'!Q12),MONTH('Base de Datos'!Q12)),""),IF(TRIM('Base de Datos'!Q12)="","",IFERROR(DATE(VALUE(RIGHT(TRIM('Base de Datos'!Q12),4)),VALUE(LEFT(TRIM('Base de Datos'!Q12),2)),VALUE(MID(TRIM('Base de Datos'!Q12),4,2))),""))),"") -> 44528 | AI16: =IF(ISNUMBER('Base de Datos'!R12),'Base de Datos'!R12,IF(TRIM('Base de Datos'!R12)="","",IFERROR(IF(IFERROR(FIND("@",SUBSTITUTE(TRIM('Base de Datos'!R12),",","@",LEN(TRIM('Base de Datos'!R12))-LEN(SUBSTITUTE(TRIM('Base de Datos'!R12),",","")))),0)>IFERROR(FIND("@",SUBSTITUTE(TRIM('Base de Datos'!R12),".","@",LEN(TRIM('Base de Datos'!R12))-LEN(SUBSTITUTE(TRIM('Base de Datos'!R12),".","")))),0),_xlfn.NUMBERVALUE(SUBSTITUTE(SUBSTITUTE(TRIM('Base de Datos'!R12),".",""),",","."),".",","),_xlfn.NUMBERVALUE(SUBSTITUTE(TRIM('Base de Datos'!R12),",",""),".",",")),""))) -> 23.94 | AJ16: =IF(ISNUMBER(AK16),IF(ISNUMBER('Base de Datos'!Y12),IF('Base de Datos'!Y12>20000,INT('Base de Datos'!Y12),""),IF(TRIM('Base de Datos'!Y12)="","",IFERROR(DATE(VALUE(RIGHT(TRIM('Base de Datos'!Y12),4)),VALUE(MID(TRIM('Base de Datos'!Y12),4,2)),VALUE(LEFT(TRIM('Base de Datos'!Y12),2))),IFERROR(DATEVALUE(TRIM('Base de Datos'!Y12)),"")))),"") -> 44528 | AK16: =IF(ISNUMBER('Base de Datos'!Z12),'Base de Datos'!Z12,IF(TRIM('Base de Datos'!Z12)="","",IFERROR(IF(IFERROR(FIND("@",SUBSTITUTE(TRIM('Base de Datos'!Z12),",","@",LEN(TRIM('Base de Datos'!Z12))-LEN(SUBSTITUTE(TRIM('Base de Datos'!Z12),",","")))),0)>IFERROR(FIND("@",SUBSTITUTE(TRIM('Base de Datos'!Z12),".","@",LEN(TRIM('Base de Datos'!Z12))-LEN(SUBSTITUTE(TRIM('Base de Datos'!Z12),".","")))),0),_xlfn.NUMBERVALUE(SUBSTITUTE(SUBSTITUTE(TRIM('Base de Datos'!Z12),".",""),",","."),".",","),_xlfn.NUMBERVALUE(SUBSTITUTE(TRIM('Base de Datos'!Z12),",",""),".",",")),""))) -> 50597.29
A17: =ROWS(A$13:A17) -> 5 | B17: =IF(B16="","",IFERROR(SMALL($AH$10:$AH$409,COUNTIF($AH$10:$AH$409,"<="&B16)+1),"")) -> 44514 | C17: =IF(B17="","",INDEX($AI$10:$AI$409,MATCH(B17,$AH$10:$AH$409,0))) -> 22.99 | D17: =IF(B17="","",IFERROR(INDEX($AK$10:$AK$409,MATCH(B17,$AJ$10:$AJ$409,0)),"")) -> 50811.3 | E17: =IF(AND(ISNUMBER(C17),ISNUMBER(C16)),C17/C16-1,"") -> -0.032814472 | F17: =IF(AND(ISNUMBER(D17),ISNUMBER(D16)),D17/D16-1,"") -> -0.012078735 | G17: =IF(AND(ISNUMBER(E17),ISNUMBER(F17)),1,"") -> 1 | H17: =IF(G17=1,COUNT(G17:G$412),"") -> 255 | I17: =IF(G17=1,IF(H17<='Beta Regresión'!$B$5,1,""),"") -> 1 | J17: =IF(I17=1,E17,"") -> -0.032814472 | K17: =IF(I17=1,F17,"") -> -0.012078735 | L17: =IF(I17=1,COUNT(I$13:I17),"") -> 4 | M17: =IFERROR(INDEX($J$13:$J$412,MATCH(A17,$L$13:$L$412,0)),"") -> -0.011309265 | N17: =IFERROR(INDEX($K$13:$K$412,MATCH(A17,$L$13:$L$412,0)),"") -> -0.025954463 | O17: =IF(I17=1,E17,NA()) -> -0.032814472 | P17: =IF(I17=1,F17,NA()) -> -0.012078735 | R17: =ROWS(R$13:R17) -> 5 | S17: =IF(S16="","",IFERROR(SMALL($AD$10:$AD$509,COUNTIF($AD$10:$AD$509,"<="&S16)+1),"")) -> 46210 | T17: =IF(S17="","",INDEX($AE$10:$AE$509,MATCH(S17,$AD$10:$AD$509,0))) -> 30.29 | U17: =IF(S17="","",IFERROR(INDEX($AG$10:$AG$509,MATCH(S17,$AF$10:$AF$509,0)),"")) -> 66674.7 | V17: =IF(AND(ISNUMBER(T17),ISNUMBER(T16)),T17/T16-1,"") -> 0.023310811 | W17: =IF(AND(ISNUMBER(U17),ISNUMBER(U16)),U17/U16-1,"") -> -0.011735609 | X17: =IF(AND(ISNUMBER(V17),ISNUMBER(W17)),1,"") -> 1 | Y17: =IF(X17=1,V17,"") -> 0.023310811 | Z17: =IF(X17=1,W17,"") -> -0.011735609 | AA17: =IF(X17=1,V17,NA()) -> 0.023310811 | AB17: =IF(X17=1,W17,NA()) -> -0.011735609 | AD17: =IF(ISNUMBER(AE17),IF(ISNUMBER('Base de Datos'!A13),IF('Base de Datos'!A13>20000,DATE(YEAR('Base de Datos'!A13),DAY('Base de Datos'!A13),MONTH('Base de Datos'!A13)),""),IF(TRIM('Base de Datos'!A13)="","",IFERROR(DATE(VALUE(RIGHT(TRIM('Base de Datos'!A13),4)),VALUE(LEFT(TRIM('Base de Datos'!A13),2)),VALUE(MID(TRIM('Base de Datos'!A13),4,2))),""))),"") -> 46213 | AE17: =IF(ISNUMBER('Base de Datos'!B13),'Base de Datos'!B13,IF(TRIM('Base de Datos'!B13)="","",IFERROR(IF(IFERROR(FIND("@",SUBSTITUTE(TRIM('Base de Datos'!B13),",","@",LEN(TRIM('Base de Datos'!B13))-LEN(SUBSTITUTE(TRIM('Base de Datos'!B13),",","")))),0)>IFERROR(FIND("@",SUBSTITUTE(TRIM('Base de Datos'!B13),".","@",LEN(TRIM('Base de Datos'!B13))-LEN(SUBSTITUTE(TRIM('Base de Datos'!B13),".","")))),0),_xlfn.NUMBERVALUE(SUBSTITUTE(SUBSTITUTE(TRIM('Base de Datos'!B13),".",""),",","."),".",","),_xlfn.NUMBERVALUE(SUBSTITUTE(TRIM('Base de Datos'!B13),",",""),".",",")),""))) -> 30.6 | AF17: =IF(ISNUMBER(AG17),IF(ISNUMBER('Base de Datos'!I13),IF('Base de Datos'!I13>20000,INT('Base de Datos'!I13),""),IF(TRIM('Base de Datos'!I13)="","",IFERROR(DATE(VALUE(RIGHT(TRIM('Base de Datos'!I13),4)),VALUE(MID(TRIM('Base de Datos'!I13),4,2)),VALUE(LEFT(TRIM('Base de Datos'!I13),2))),IFERROR(DATEVALUE(TRIM('Base de Datos'!I13)),"")))),"") -> 46213 | AG17: =IF(ISNUMBER('Base de Datos'!J13),'Base de Datos'!J13,IF(TRIM('Base de Datos'!J13)="","",IFERROR(IF(IFERROR(FIND("@",SUBSTITUTE(TRIM('Base de Datos'!J13),",","@",LEN(TRIM('Base de Datos'!J13))-LEN(SUBSTITUTE(TRIM('Base de Datos'!J13),",","")))),0)>IFERROR(FIND("@",SUBSTITUTE(TRIM('Base de Datos'!J13),".","@",LEN(TRIM('Base de Datos'!J13))-LEN(SUBSTITUTE(TRIM('Base de Datos'!J13),".","")))),0),_xlfn.NUMBERVALUE(SUBSTITUTE(SUBSTITUTE(TRIM('Base de Datos'!J13),".",""),",","."),".",","),_xlfn.NUMBERVALUE(SUBSTITUTE(TRIM('Base de Datos'!J13),",",""),".",",")),""))) -> 66496.1 | AH17: =IF(ISNUMBER(AI17),IF(ISNUMBER('Base de Datos'!Q13),IF('Base de Datos'!Q13>20000,DATE(YEAR('Base de Datos'!Q13),DAY('Base de Datos'!Q13),MONTH('Base de Datos'!Q13)),""),IF(TRIM('Base de Datos'!Q13)="","",IFERROR(DATE(VALUE(RIGHT(TRIM('Base de Datos'!Q13),4)),VALUE(LEFT(TRIM('Base de Datos'!Q13),2)),VALUE(MID(TRIM('Base de Datos'!Q13),4,2))),""))),"") -> 44535 | AI17: =IF(ISNUMBER('Base de Datos'!R13),'Base de Datos'!R13,IF(TRIM('Base de Datos'!R13)="","",IFERROR(IF(IFERROR(FIND("@",SUBSTITUTE(TRIM('Base de Datos'!R13),",","@",LEN(TRIM('Base de Datos'!R13))-LEN(SUBSTITUTE(TRIM('Base de Datos'!R13),",","")))),0)>IFERROR(FIND("@",SUBSTITUTE(TRIM('Base de Datos'!R13),".","@",LEN(TRIM('Base de Datos'!R13))-LEN(SUBSTITUTE(TRIM('Base de Datos'!R13),".","")))),0),_xlfn.NUMBERVALUE(SUBSTITUTE(SUBSTITUTE(TRIM('Base de Datos'!R13),".",""),",","."),".",","),_xlfn.NUMBERVALUE(SUBSTITUTE(TRIM('Base de Datos'!R13),",",""),".",",")),""))) -> 23.26 | AJ17: =IF(ISNUMBER(AK17),IF(ISNUMBER('Base de Datos'!Y13),IF('Base de Datos'!Y13>20000,INT('Base de Datos'!Y13),""),IF(TRIM('Base de Datos'!Y13)="","",IFERROR(DATE(VALUE(RIGHT(TRIM('Base de Datos'!Y13),4)),VALUE(MID(TRIM('Base de Datos'!Y13),4,2)),VALUE(LEFT(TRIM('Base de Datos'!Y13),2))),IFERROR(DATEVALUE(TRIM('Base de Datos'!Y13)),"")))),"") -> 44535 | AK17: =IF(ISNUMBER('Base de Datos'!Z13),'Base de Datos'!Z13,IF(TRIM('Base de Datos'!Z13)="","",IFERROR(IF(IFERROR(FIND("@",SUBSTITUTE(TRIM('Base de Datos'!Z13),",","@",LEN(TRIM('Base de Datos'!Z13))-LEN(SUBSTITUTE(TRIM('Base de Datos'!Z13),",","")))),0)>IFERROR(FIND("@",SUBSTITUTE(TRIM('Base de Datos'!Z13),".","@",LEN(TRIM('Base de Datos'!Z13))-LEN(SUBSTITUTE(TRIM('Base de Datos'!Z13),".","")))),0),_xlfn.NUMBERVALUE(SUBSTITUTE(SUBSTITUTE(TRIM('Base de Datos'!Z13),".",""),",","."),".",","),_xlfn.NUMBERVALUE(SUBSTITUTE(TRIM('Base de Datos'!Z13),",",""),".",",")),""))) -> 51213.48
A18: =ROWS(A$13:A18) -> 6 | B18: =IF(B17="","",IFERROR(SMALL($AH$10:$AH$409,COUNTIF($AH$10:$AH$409,"<="&B17)+1),"")) -> 44521 | C18: =IF(B18="","",INDEX($AI$10:$AI$409,MATCH(B18,$AH$10:$AH$409,0))) -> 22.73 | D18: =IF(B18="","",IFERROR(INDEX($AK$10:$AK$409,MATCH(B18,$AJ$10:$AJ$409,0)),"")) -> 49492.52 | E18: =IF(AND(ISNUMBER(C18),ISNUMBER(C17)),C18/C17-1,"") -> -0.011309265 | F18: =IF(AND(ISNUMBER(D18),ISNUMBER(D17)),D18/D17-1,"") -> -0.025954463 | G18: =IF(AND(ISNUMBER(E18),ISNUMBER(F18)),1,"") -> 1 | H18: =IF(G18=1,COUNT(G18:G$412),"") -> 254 | I18: =IF(G18=1,IF(H18<='Beta Regresión'!$B$5,1,""),"") -> 1 | J18: =IF(I18=1,E18,"") -> -0.011309265 | K18: =IF(I18=1,F18,"") -> -0.025954463 | L18: =IF(I18=1,COUNT(I$13:I18),"") -> 5 | M18: =IFERROR(INDEX($J$13:$J$412,MATCH(A18,$L$13:$L$412,0)),"") -> 0.053233612 | N18: =IFERROR(INDEX($K$13:$K$412,MATCH(A18,$L$13:$L$412,0)),"") -> 0.022321959 | O18: =IF(I18=1,E18,NA()) -> -0.011309265 | P18: =IF(I18=1,F18,NA()) -> -0.025954463 | R18: =ROWS(R$13:R18) -> 6 | S18: =IF(S17="","",IFERROR(SMALL($AD$10:$AD$509,COUNTIF($AD$10:$AD$509,"<="&S17)+1),"")) -> 46211 | T18: =IF(S18="","",INDEX($AE$10:$AE$509,MATCH(S18,$AD$10:$AD$509,0))) -> 30 | U18: =IF(S18="","",IFERROR(INDEX($AG$10:$AG$509,MATCH(S18,$AF$10:$AF$509,0)),"")) -> 66609.64 | V18: =IF(AND(ISNUMBER(T18),ISNUMBER(T17)),T18/T17-1,"") -> -0.0095741169 | W18: =IF(AND(ISNUMBER(U18),ISNUMBER(U17)),U18/U17-1,"") -> -0.00097578242 | X18: =IF(AND(ISNUMBER(V18),ISNUMBER(W18)),1,"") -> 1 | Y18: =IF(X18=1,V18,"") -> -0.0095741169 | Z18: =IF(X18=1,W18,"") -> -0.00097578242 | AA18: =IF(X18=1,V18,NA()) -> -0.0095741169 | AB18: =IF(X18=1,W18,NA()) -> -0.00097578242 | AD18: =IF(ISNUMBER(AE18),IF(ISNUMBER('Base de Datos'!A14),IF('Base de Datos'!A14>20000,DATE(YEAR('Base de Datos'!A14),DAY('Base de Datos'!A14),MONTH('Base de Datos'!A14)),""),IF(TRIM('Base de Datos'!A14)="","",IFERROR(DATE(VALUE(RIGHT(TRIM('Base de Datos'!A14),4)),VALUE(LEFT(TRIM('Base de Datos'!A14),2)),VALUE(MID(TRIM('Base de Datos'!A14),4,2))),""))),"") -> 46216 | AE18: =IF(ISNUMBER('Base de Datos'!B14),'Base de Datos'!B14,IF(TRIM('Base de Datos'!B14)="","",IFERROR(IF(IFERROR(FIND("@",SUBSTITUTE(TRIM('Base de Datos'!B14),",","@",LEN(TRIM('Base de Datos'!B14))-LEN(SUBSTITUTE(TRIM('Base de Datos'!B14),",","")))),0)>IFERROR(FIND("@",SUBSTITUTE(TRIM('Base de Datos'!B14),".","@",LEN(TRIM('Base de Datos'!B14))-LEN(SUBSTITUTE(TRIM('Base de Datos'!B14),".","")))),0),_xlfn.NUMBERVALUE(SUBSTITUTE(SUBSTITUTE(TRIM('Base de Datos'!B14),".",""),",","."),".",","),_xlfn.NUMBERVALUE(SUBSTITUTE(TRIM('Base de Datos'!B14),",",""),".",",")),""))) -> 30 | AF18: =IF(ISNUMBER(AG18),IF(ISNUMBER('Base de Datos'!I14),IF('Base de Datos'!I14>20000,INT('Base de Datos'!I14),""),IF(TRIM('Base de Datos'!I14)="","",IFERROR(DATE(VALUE(RIGHT(TRIM('Base de Datos'!I14),4)),VALUE(MID(TRIM('Base de Datos'!I14),4,2)),VALUE(LEFT(TRIM('Base de Datos'!I14),2))),IFERROR(DATEVALUE(TRIM('Base de Datos'!I14)),"")))),"") -> 46216 | AG18: =IF(ISNUMBER('Base de Datos'!J14),'Base de Datos'!J14,IF(TRIM('Base de Datos'!J14)="","",IFERROR(IF(IFERROR(FIND("@",SUBSTITUTE(TRIM('Base de Datos'!J14),",","@",LEN(TRIM('Base de Datos'!J14))-LEN(SUBSTITUTE(TRIM('Base de Datos'!J14),",","")))),0)>IFERROR(FIND("@",SUBSTITUTE(TRIM('Base de Datos'!J14),".","@",LEN(TRIM('Base de Datos'!J14))-LEN(SUBSTITUTE(TRIM('Base de Datos'!J14),".","")))),0),_xlfn.NUMBERVALUE(SUBSTITUTE(SUBSTITUTE(TRIM('Base de Datos'!J14),".",""),",","."),".",","),_xlfn.NUMBERVALUE(SUBSTITUTE(TRIM('Base de Datos'!J14),",",""),".",",")),""))) -> 65973.08 | AH18: =IF(ISNUMBER(AI18),IF(ISNUMBER('Base de Datos'!Q14),IF('Base de Datos'!Q14>20000,DATE(YEAR('Base de Datos'!Q14),DAY('Base de Datos'!Q14),MONTH('Base de Datos'!Q14)),""),IF(TRIM('Base de Datos'!Q14)="","",IFERROR(DATE(VALUE(RIGHT(TRIM('Base de Datos'!Q14),4)),VALUE(LEFT(TRIM('Base de Datos'!Q14),2)),VALUE(MID(TRIM('Base de Datos'!Q14),4,2))),""))),"") -> 44542 | AI18: =IF(ISNUMBER('Base de Datos'!R14),'Base de Datos'!R14,IF(TRIM('Base de Datos'!R14)="","",IFERROR(IF(IFERROR(FIND("@",SUBSTITUTE(TRIM('Base de Datos'!R14),",","@",LEN(TRIM('Base de Datos'!R14))-LEN(SUBSTITUTE(TRIM('Base de Datos'!R14),",","")))),0)>IFERROR(FIND("@",SUBSTITUTE(TRIM('Base de Datos'!R14),".","@",LEN(TRIM('Base de Datos'!R14))-LEN(SUBSTITUTE(TRIM('Base de Datos'!R14),".","")))),0),_xlfn.NUMBERVALUE(SUBSTITUTE(SUBSTITUTE(TRIM('Base de Datos'!R14),".",""),",","."),".",","),_xlfn.NUMBERVALUE(SUBSTITUTE(TRIM('Base de Datos'!R14),",",""),".",",")),""))) -> 22.59 | AJ18: =IF(ISNUMBER(AK18),IF(ISNUMBER('Base de Datos'!Y14),IF('Base de Datos'!Y14>20000,INT('Base de Datos'!Y14),""),IF(TRIM('Base de Datos'!Y14)="","",IFERROR(DATE(VALUE(RIGHT(TRIM('Base de Datos'!Y14),4)),VALUE(MID(TRIM('Base de Datos'!Y14),4,2)),VALUE(LEFT(TRIM('Base de Datos'!Y14),2))),IFERROR(DATEVALUE(TRIM('Base de Datos'!Y14)),"")))),"") -> 44542 | AK18: =IF(ISNUMBER('Base de Datos'!Z14),'Base de Datos'!Z14,IF(TRIM('Base de Datos'!Z14)="","",IFERROR(IF(IFERROR(FIND("@",SUBSTITUTE(TRIM('Base de Datos'!Z14),",","@",LEN(TRIM('Base de Datos'!Z14))-LEN(SUBSTITUTE(TRIM('Base de Datos'!Z14),",","")))),0)>IFERROR(FIND("@",SUBSTITUTE(TRIM('Base de Datos'!Z14),".","@",LEN(TRIM('Base de Datos'!Z14))-LEN(SUBSTITUTE(TRIM('Base de Datos'!Z14),".","")))),0),_xlfn.NUMBERVALUE(SUBSTITUTE(SUBSTITUTE(TRIM('Base de Datos'!Z14),".",""),",","."),".",","),_xlfn.NUMBERVALUE(SUBSTITUTE(TRIM('Base de Datos'!Z14),",",""),".",",")),""))) -> 52379.37
A19: =ROWS(A$13:A19) -> 7 | B19: =IF(B18="","",IFERROR(SMALL($AH$10:$AH$409,COUNTIF($AH$10:$AH$409,"<="&B18)+1),"")) -> 44528 | C19: =IF(B19="","",INDEX($AI$10:$AI$409,MATCH(B19,$AH$10:$AH$409,0))) -> 23.94 | D19: =IF(B19="","",IFERROR(INDEX($AK$10:$AK$409,MATCH(B19,$AJ$10:$AJ$409,0)),"")) -> 50597.29 | E19: =IF(AND(ISNUMBER(C19),ISNUMBER(C18)),C19/C18-1,"") -> 0.053233612 | F19: =IF(AND(ISNUMBER(D19),ISNUMBER(D18)),D19/D18-1,"") -> 0.022321959 | G19: =IF(AND(ISNUMBER(E19),ISNUMBER(F19)),1,"") -> 1 | H19: =IF(G19=1,COUNT(G19:G$412),"") -> 253 | I19: =IF(G19=1,IF(H19<='Beta Regresión'!$B$5,1,""),"") -> 1 | J19: =IF(I19=1,E19,"") -> 0.053233612 | K19: =IF(I19=1,F19,"") -> 0.022321959 | L19: =IF(I19=1,COUNT(I$13:I19),"") -> 6 | M19: =IFERROR(INDEX($J$13:$J$412,MATCH(A19,$L$13:$L$412,0)),"") -> -0.028404344 | N19: =IFERROR(INDEX($K$13:$K$412,MATCH(A19,$L$13:$L$412,0)),"") -> 0.01217832 | O19: =IF(I19=1,E19,NA()) -> 0.053233612 | P19: =IF(I19=1,F19,NA()) -> 0.022321959 | R19: =ROWS(R$13:R19) -> 7 | S19: =IF(S18="","",IFERROR(SMALL($AD$10:$AD$509,COUNTIF($AD$10:$AD$509,"<="&S18)+1),"")) -> 46212 | T19: =IF(S19="","",INDEX($AE$10:$AE$509,MATCH(S19,$AD$10:$AD$509,0))) -> 30.76 | U19: =IF(S19="","",IFERROR(INDEX($AG$10:$AG$509,MATCH(S19,$AF$10:$AF$509,0)),"")) -> 66107.28 | V19: =IF(AND(ISNUMBER(T19),ISNUMBER(T18)),T19/T18-1,"") -> 0.025333333 | W19: =IF(AND(ISNUMBER(U19),ISNUMBER(U18)),U19/U18-1,"") -> -0.0075418513 | X19: =IF(AND(ISNUMBER(V19),ISNUMBER(W19)),1,"") -> 1 | Y19: =IF(X19=1,V19,"") -> 0.025333333 | Z19: =IF(X19=1,W19,"") -> -0.0075418513 | AA19: =IF(X19=1,V19,NA()) -> 0.025333333 | AB19: =IF(X19=1,W19,NA()) -> -0.0075418513 | AD19: =IF(ISNUMBER(AE19),IF(ISNUMBER('Base de Datos'!A15),IF('Base de Datos'!A15>20000,DATE(YEAR('Base de Datos'!A15),DAY('Base de Datos'!A15),MONTH('Base de Datos'!A15)),""),IF(TRIM('Base de Datos'!A15)="","",IFERROR(DATE(VALUE(RIGHT(TRIM('Base de Datos'!A15),4)),VALUE(LEFT(TRIM('Base de Datos'!A15),2)),VALUE(MID(TRIM('Base de Datos'!A15),4,2))),""))),"") -> 46218 | AE19: =IF(ISNUMBER('Base de Datos'!B15),'Base de Datos'!B15,IF(TRIM('Base de Datos'!B15)="","",IFERROR(IF(IFERROR(FIND("@",SUBSTITUTE(TRIM('Base de Datos'!B15),",","@",LEN(TRIM('Base de Datos'!B15))-LEN(SUBSTITUTE(TRIM('Base de Datos'!B15),",","")))),0)>IFERROR(FIND("@",SUBSTITUTE(TRIM('Base de Datos'!B15),".","@",LEN(TRIM('Base de Datos'!B15))-LEN(SUBSTITUTE(TRIM('Base de Datos'!B15),".","")))),0),_xlfn.NUMBERVALUE(SUBSTITUTE(SUBSTITUTE(TRIM('Base de Datos'!B15),".",""),",","."),".",","),_xlfn.NUMBERVALUE(SUBSTITUTE(TRIM('Base de Datos'!B15),",",""),".",",")),""))) -> 30.04 | AF19: =IF(ISNUMBER(AG19),IF(ISNUMBER('Base de Datos'!I15),IF('Base de Datos'!I15>20000,INT('Base de Datos'!I15),""),IF(TRIM('Base de Datos'!I15)="","",IFERROR(DATE(VALUE(RIGHT(TRIM('Base de Datos'!I15),4)),VALUE(MID(TRIM('Base de Datos'!I15),4,2)),VALUE(LEFT(TRIM('Base de Datos'!I15),2))),IFERROR(DATEVALUE(TRIM('Base de Datos'!I15)),"")))),"") -> 46217 | AG19: =IF(ISNUMBER('Base de Datos'!J15),'Base de Datos'!J15,IF(TRIM('Base de Datos'!J15)="","",IFERROR(IF(IFERROR(FIND("@",SUBSTITUTE(TRIM('Base de Datos'!J15),",","@",LEN(TRIM('Base de Datos'!J15))-LEN(SUBSTITUTE(TRIM('Base de Datos'!J15),",","")))),0)>IFERROR(FIND("@",SUBSTITUTE(TRIM('Base de Datos'!J15),".","@",LEN(TRIM('Base de Datos'!J15))-LEN(SUBSTITUTE(TRIM('Base de Datos'!J15),".","")))),0),_xlfn.NUMBERVALUE(SUBSTITUTE(SUBSTITUTE(TRIM('Base de Datos'!J15),".",""),",","."),".",","),_xlfn.NUMBERVALUE(SUBSTITUTE(TRIM('Base de Datos'!J15),",",""),".",",")),""))) -> 66514.3 | AH19: =IF(ISNUMBER(AI19),IF(ISNUMBER('Base de Datos'!Q15),IF('Base de Datos'!Q15>20000,DATE(YEAR('Base de Datos'!Q15),DAY('Base de Datos'!Q15),MONTH('Base de Datos'!Q15)),""),IF(TRIM('Base de Datos'!Q15)="","",IFERROR(DATE(VALUE(RIGHT(TRIM('Base de Datos'!Q15),4)),VALUE(LEFT(TRIM('Base de Datos'!Q15),2)),VALUE(MID(TRIM('Base de Datos'!Q15),4,2))),""))),"") -> 44549 | AI19: =IF(ISNUMBER('Base de Datos'!R15),'Base de Datos'!R15,IF(TRIM('Base de Datos'!R15)="","",IFERROR(IF(IFERROR(FIND("@",SUBSTITUTE(TRIM('Base de Datos'!R15),",","@",LEN(TRIM('Base de Datos'!R15))-LEN(SUBSTITUTE(TRIM('Base de Datos'!R15),",","")))),0)>IFERROR(FIND("@",SUBSTITUTE(TRIM('Base de Datos'!R15),".","@",LEN(TRIM('Base de Datos'!R15))-LEN(SUBSTITUTE(TRIM('Base de Datos'!R15),".","")))),0),_xlfn.NUMBERVALUE(SUBSTITUTE(SUBSTITUTE(TRIM('Base de Datos'!R15),".",""),",","."),".",","),_xlfn.NUMBERVALUE(SUBSTITUTE(TRIM('Base de Datos'!R15),",",""),".",",")),""))) -> 24.8 | AJ19: =IF(ISNUMBER(AK19),IF(ISNUMBER('Base de Datos'!Y15),IF('Base de Datos'!Y15>20000,INT('Base de Datos'!Y15),""),IF(TRIM('Base de Datos'!Y15)="","",IFERROR(DATE(VALUE(RIGHT(TRIM('Base de Datos'!Y15),4)),VALUE(MID(TRIM('Base de Datos'!Y15),4,2)),VALUE(LEFT(TRIM('Base de Datos'!Y15),2))),IFERROR(DATEVALUE(TRIM('Base de Datos'!Y15)),"")))),"") -> 44549 | AK19: =IF(ISNUMBER('Base de Datos'!Z15),'Base de Datos'!Z15,IF(TRIM('Base de Datos'!Z15)="","",IFERROR(IF(IFERROR(FIND("@",SUBSTITUTE(TRIM('Base de Datos'!Z15),",","@",LEN(TRIM('Base de Datos'!Z15))-LEN(SUBSTITUTE(TRIM('Base de Datos'!Z15),",","")))),0)>IFERROR(FIND("@",SUBSTITUTE(TRIM('Base de Datos'!Z15),".","@",LEN(TRIM('Base de Datos'!Z15))-LEN(SUBSTITUTE(TRIM('Base de Datos'!Z15),".","")))),0),_xlfn.NUMBERVALUE(SUBSTITUTE(SUBSTITUTE(TRIM('Base de Datos'!Z15),".",""),",","."),".",","),_xlfn.NUMBERVALUE(SUBSTITUTE(TRIM('Base de Datos'!Z15),",",""),".",",")),""))) -> 52853.38
A20: =ROWS(A$13:A20) -> 8 | B20: =IF(B19="","",IFERROR(SMALL($AH$10:$AH$409,COUNTIF($AH$10:$AH$409,"<="&B19)+1),"")) -> 44535 | C20: =IF(B20="","",INDEX($AI$10:$AI$409,MATCH(B20,$AH$10:$AH$409,0))) -> 23.26 | D20: =IF(B20="","",IFERROR(INDEX($AK$10:$AK$409,MATCH(B20,$AJ$10:$AJ$409,0)),"")) -> 51213.48 | E20: =IF(AND(ISNUMBER(C20),ISNUMBER(C19)),C20/C19-1,"") -> -0.028404344 | F20: =IF(AND(ISNUMBER(D20),ISNUMBER(D19)),D20/D19-1,"") -> 0.01217832 | G20: =IF(AND(ISNUMBER(E20),ISNUMBER(F20)),1,"") -> 1 | H20: =IF(G20=1,COUNT(G20:G$412),"") -> 252 | I20: =IF(G20=1,IF(H20<='Beta Regresión'!$B$5,1,""),"") -> 1 | J20: =IF(I20=1,E20,"") -> -0.028404344 | K20: =IF(I20=1,F20,"") -> 0.01217832 | L20: =IF(I20=1,COUNT(I$13:I20),"") -> 7 | M20: =IFERROR(INDEX($J$13:$J$412,MATCH(A20,$L$13:$L$412,0)),"") -> -0.028804815 | N20: =IFERROR(INDEX($K$13:$K$412,MATCH(A20,$L$13:$L$412,0)),"") -> 0.022765295 | O20: =IF(I20=1,E20,NA()) -> -0.028404344 | P20: =IF(I20=1,F20,NA()) -> 0.01217832 | R20: =ROWS(R$13:R20) -> 8 | S20: =IF(S19="","",IFERROR(SMALL($AD$10:$AD$509,COUNTIF($AD$10:$AD$509,"<="&S19)+1),"")) -> 46213 | T20: =IF(S20="","",INDEX($AE$10:$AE$509,MATCH(S20,$AD$10:$AD$509,0))) -> 30.6 | U20: =IF(S20="","",IFERROR(INDEX($AG$10:$AG$509,MATCH(S20,$AF$10:$AF$509,0)),"")) -> 66496.1 | V20: =IF(AND(ISNUMBER(T20),ISNUMBER(T19)),T20/T19-1,"") -> -0.0052015605 | W20: =IF(AND(ISNUMBER(U20),ISNUMBER(U19)),U20/U19-1,"") -> 0.0058816518 | X20: =IF(AND(ISNUMBER(V20),ISNUMBER(W20)),1,"") -> 1 | Y20: =IF(X20=1,V20,"") -> -0.0052015605 | Z20: =IF(X20=1,W20,"") -> 0.0058816518 | AA20: =IF(X20=1,V20,NA()) -> -0.0052015605 | AB20: =IF(X20=1,W20,NA()) -> 0.0058816518 | AD20: =IF(ISNUMBER(AE20),IF(ISNUMBER('Base de Datos'!A16),IF('Base de Datos'!A16>20000,DATE(YEAR('Base de Datos'!A16),DAY('Base de Datos'!A16),MONTH('Base de Datos'!A16)),""),IF(TRIM('Base de Datos'!A16)="","",IFERROR(DATE(VALUE(RIGHT(TRIM('Base de Datos'!A16),4)),VALUE(LEFT(TRIM('Base de Datos'!A16),2)),VALUE(MID(TRIM('Base de Datos'!A16),4,2))),""))),"") -> 46219 | AE20: =IF(ISNUMBER('Base de Datos'!B16),'Base de Datos'!B16,IF(TRIM('Base de Datos'!B16)="","",IFERROR(IF(IFERROR(FIND("@",SUBSTITUTE(TRIM('Base de Datos'!B16),",","@",LEN(TRIM('Base de Datos'!B16))-LEN(SUBSTITUTE(TRIM('Base de Datos'!B16),",","")))),0)>IFERROR(FIND("@",SUBSTITUTE(TRIM('Base de Datos'!B16),".","@",LEN(TRIM('Base de Datos'!B16))-LEN(SUBSTITUTE(TRIM('Base de Datos'!B16),".","")))),0),_xlfn.NUMBERVALUE(SUBSTITUTE(SUBSTITUTE(TRIM('Base de Datos'!B16),".",""),",","."),".",","),_xlfn.NUMBERVALUE(SUBSTITUTE(TRIM('Base de Datos'!B16),",",""),".",",")),""))) -> 29.96 | AF20: =IF(ISNUMBER(AG20),IF(ISNUMBER('Base de Datos'!I16),IF('Base de Datos'!I16>20000,INT('Base de Datos'!I16),""),IF(TRIM('Base de Datos'!I16)="","",IFERROR(DATE(VALUE(RIGHT(TRIM('Base de Datos'!I16),4)),VALUE(MID(TRIM('Base de Datos'!I16),4,2)),VALUE(LEFT(TRIM('Base de Datos'!I16),2))),IFERROR(DATEVALUE(TRIM('Base de Datos'!I16)),"")))),"") -> 46218 | AG20: =IF(ISNUMBER('Base de Datos'!J16),'Base de Datos'!J16,IF(TRIM('Base de Datos'!J16)="","",IFERROR(IF(IFERROR(FIND("@",SUBSTITUTE(TRIM('Base de Datos'!J16),",","@",LEN(TRIM('Base de Datos'!J16))-LEN(SUBSTITUTE(TRIM('Base de Datos'!J16),",","")))),0)>IFERROR(FIND("@",SUBSTITUTE(TRIM('Base de Datos'!J16),".","@",LEN(TRIM('Base de Datos'!J16))-LEN(SUBSTITUTE(TRIM('Base de Datos'!J16),".","")))),0),_xlfn.NUMBERVALUE(SUBSTITUTE(SUBSTITUTE(TRIM('Base de Datos'!J16),".",""),",","."),".",","),_xlfn.NUMBERVALUE(SUBSTITUTE(TRIM('Base de Datos'!J16),",",""),".",",")),""))) -> 66399.71 | AH20: =IF(ISNUMBER(AI20),IF(ISNUMBER('Base de Datos'!Q16),IF('Base de Datos'!Q16>20000,DATE(YEAR('Base de Datos'!Q16),DAY('Base de Datos'!Q16),MONTH('Base de Datos'!Q16)),""),IF(TRIM('Base de Datos'!Q16)="","",IFERROR(DATE(VALUE(RIGHT(TRIM('Base de Datos'!Q16),4)),VALUE(LEFT(TRIM('Base de Datos'!Q16),2)),VALUE(MID(TRIM('Base de Datos'!Q16),4,2))),""))),"") -> 44556 | AI20: =IF(ISNUMBER('Base de Datos'!R16),'Base de Datos'!R16,IF(TRIM('Base de Datos'!R16)="","",IFERROR(IF(IFERROR(FIND("@",SUBSTITUTE(TRIM('Base de Datos'!R16),",","@",LEN(TRIM('Base de Datos'!R16))-LEN(SUBSTITUTE(TRIM('Base de Datos'!R16),",","")))),0)>IFERROR(FIND("@",SUBSTITUTE(TRIM('Base de Datos'!R16),".","@",LEN(TRIM('Base de Datos'!R16))-LEN(SUBSTITUTE(TRIM('Base de Datos'!R16),".","")))),0),_xlfn.NUMBERVALUE(SUBSTITUTE(SUBSTITUTE(TRIM('Base de Datos'!R16),".",""),",","."),".",","),_xlfn.NUMBERVALUE(SUBSTITUTE(TRIM('Base de Datos'!R16),",",""),".",",")),""))) -> 25.98 | AJ20: =IF(ISNUMBER(AK20),IF(ISNUMBER('Base de Datos'!Y16),IF('Base de Datos'!Y16>20000,INT('Base de Datos'!Y16),""),IF(TRIM('Base de Datos'!Y16)="","",IFERROR(DATE(VALUE(RIGHT(TRIM('Base de Datos'!Y16),4)),VALUE(MID(TRIM('Base de Datos'!Y16),4,2)),VALUE(LEFT(TRIM('Base de Datos'!Y16),2))),IFERROR(DATEVALUE(TRIM('Base de Datos'!Y16)),"")))),"") -> 44556 | AK20: =IF(ISNUMBER('Base de Datos'!Z16),'Base de Datos'!Z16,IF(TRIM('Base de Datos'!Z16)="","",IFERROR(IF(IFERROR(FIND("@",SUBSTITUTE(TRIM('Base de Datos'!Z16),",","@",LEN(TRIM('Base de Datos'!Z16))-LEN(SUBSTITUTE(TRIM('Base de Datos'!Z16),",","")))),0)>IFERROR(FIND("@",SUBSTITUTE(TRIM('Base de Datos'!Z16),".","@",LEN(TRIM('Base de Datos'!Z16))-LEN(SUBSTITUTE(TRIM('Base de Datos'!Z16),".","")))),0),_xlfn.NUMBERVALUE(SUBSTITUTE(SUBSTITUTE(TRIM('Base de Datos'!Z16),".",""),",","."),".",","),_xlfn.NUMBERVALUE(SUBSTITUTE(TRIM('Base de Datos'!Z16),",",""),".",",")),""))) -> 53272.44
A21: =ROWS(A$13:A21) -> 9 | B21: =IF(B20="","",IFERROR(SMALL($AH$10:$AH$409,COUNTIF($AH$10:$AH$409,"<="&B20)+1),"")) -> 44542 | C21: =IF(B21="","",INDEX($AI$10:$AI$409,MATCH(B21,$AH$10:$AH$409,0))) -> 22.59 | D21: =IF(B21="","",IFERROR(INDEX($AK$10:$AK$409,MATCH(B21,$AJ$10:$AJ$409,0)),"")) -> 52379.37 | E21: =IF(AND(ISNUMBER(C21),ISNUMBER(C20)),C21/C20-1,"") -> -0.028804815 | F21: =IF(AND(ISNUMBER(D21),ISNUMBER(D20)),D21/D20-1,"") -> 0.022765295 | G21: =IF(AND(ISNUMBER(E21),ISNUMBER(F21)),1,"") -> 1 | H21: =IF(G21=1,COUNT(G21:G$412),"") -> 251 | I21: =IF(G21=1,IF(H21<='Beta Regresión'!$B$5,1,""),"") -> 1 | J21: =IF(I21=1,E21,"") -> -0.028804815 | K21: =IF(I21=1,F21,"") -> 0.022765295 | L21: =IF(I21=1,COUNT(I$13:I21),"") -> 8 | M21: =IFERROR(INDEX($J$13:$J$412,MATCH(A21,$L$13:$L$412,0)),"") -> 0.097830899 | N21: =IFERROR(INDEX($K$13:$K$412,MATCH(A21,$L$13:$L$412,0)),"") -> 0.0090495552 | O21: =IF(I21=1,E21,NA()) -> -0.028804815 | P21: =IF(I21=1,F21,NA()) -> 0.022765295 | R21: =ROWS(R$13:R21) -> 9 | S21: =IF(S20="","",IFERROR(SMALL($AD$10:$AD$509,COUNTIF($AD$10:$AD$509,"<="&S20)+1),"")) -> 46216 | T21: =IF(S21="","",INDEX($AE$10:$AE$509,MATCH(S21,$AD$10:$AD$509,0))) -> 30 | U21: =IF(S21="","",IFERROR(INDEX($AG$10:$AG$509,MATCH(S21,$AF$10:$AF$509,0)),"")) -> 65973.08 | V21: =IF(AND(ISNUMBER(T21),ISNUMBER(T20)),T21/T20-1,"") -> -0.019607843 | W21: =IF(AND(ISNUMBER(U21),ISNUMBER(U20)),U21/U20-1,"") -> -0.0078654237 | X21: =IF(AND(ISNUMBER(V21),ISNUMBER(W21)),1,"") -> 1 | Y21: =IF(X21=1,V21,"") -> -0.019607843 | Z21: =IF(X21=1,W21,"") -> -0.0078654237 | AA21: =IF(X21=1,V21,NA()) -> -0.019607843 | AB21: =IF(X21=1,W21,NA()) -> -0.0078654237 | AD21: =IF(ISNUMBER(AE21),IF(ISNUMBER('Base de Datos'!A17),IF('Base de Datos'!A17>20000,DATE(YEAR('Base de Datos'!A17),DAY('Base de Datos'!A17),MONTH('Base de Datos'!A17)),""),IF(TRIM('Base de Datos'!A17)="","",IFERROR(DATE(VALUE(RIGHT(TRIM('Base de Datos'!A17),4)),VALUE(LEFT(TRIM('Base de Datos'!A17),2)),VALUE(MID(TRIM('Base de Datos'!A17),4,2))),""))),"") -> 46220 | AE21: =IF(ISNUMBER('Base de Datos'!B17),'Base de Datos'!B17,IF(TRIM('Base de Datos'!B17)="","",IFERROR(IF(IFERROR(FIND("@",SUBSTITUTE(TRIM('Base de Datos'!B17),",","@",LEN(TRIM('Base de Datos'!B17))-LEN(SUBSTITUTE(TRIM('Base de Datos'!B17),",","")))),0)>IFERROR(FIND("@",SUBSTITUTE(TRIM('Base de Datos'!B17),".","@",LEN(TRIM('Base de Datos'!B17))-LEN(SUBSTITUTE(TRIM('Base de Datos'!B17),".","")))),0),_xlfn.NUMBERVALUE(SUBSTITUTE(SUBSTITUTE(TRIM('Base de Datos'!B17),".",""),",","."),".",","),_xlfn.NUMBERVALUE(SUBSTITUTE(TRIM('Base de Datos'!B17),",",""),".",",")),""))) -> 30.27 | AF21: =IF(ISNUMBER(AG21),IF(ISNUMBER('Base de Datos'!I17),IF('Base de Datos'!I17>20000,INT('Base de Datos'!I17),""),IF(TRIM('Base de Datos'!I17)="","",IFERROR(DATE(VALUE(RIGHT(TRIM('Base de Datos'!I17),4)),VALUE(MID(TRIM('Base de Datos'!I17),4,2)),VALUE(LEFT(TRIM('Base de Datos'!I17),2))),IFERROR(DATEVALUE(TRIM('Base de Datos'!I17)),"")))),"") -> 46219 | AG21: =IF(ISNUMBER('Base de Datos'!J17),'Base de Datos'!J17,IF(TRIM('Base de Datos'!J17)="","",IFERROR(IF(IFERROR(FIND("@",SUBSTITUTE(TRIM('Base de Datos'!J17),",","@",LEN(TRIM('Base de Datos'!J17))-LEN(SUBSTITUTE(TRIM('Base de Datos'!J17),",","")))),0)>IFERROR(FIND("@",SUBSTITUTE(TRIM('Base de Datos'!J17),".","@",LEN(TRIM('Base de Datos'!J17))-LEN(SUBSTITUTE(TRIM('Base de Datos'!J17),".","")))),0),_xlfn.NUMBERVALUE(SUBSTITUTE(SUBSTITUTE(TRIM('Base de Datos'!J17),".",""),",","."),".",","),_xlfn.NUMBERVALUE(SUBSTITUTE(TRIM('Base de Datos'!J17),",",""),".",",")),""))) -> 66356.09 | AH21: =IF(ISNUMBER(AI21),IF(ISNUMBER('Base de Datos'!Q17),IF('Base de Datos'!Q17>20000,DATE(YEAR('Base de Datos'!Q17),DAY('Base de Datos'!Q17),MONTH('Base de Datos'!Q17)),""),IF(TRIM('Base de Datos'!Q17)="","",IFERROR(DATE(VALUE(RIGHT(TRIM('Base de Datos'!Q17),4)),VALUE(LEFT(TRIM('Base de Datos'!Q17),2)),VALUE(MID(TRIM('Base de Datos'!Q17),4,2))),""))),"") -> 44563 | AI21: =IF(ISNUMBER('Base de Datos'!R17),'Base de Datos'!R17,IF(TRIM('Base de Datos'!R17)="","",IFERROR(IF(IFERROR(FIND("@",SUBSTITUTE(TRIM('Base de Datos'!R17),",","@",LEN(TRIM('Base de Datos'!R17))-LEN(SUBSTITUTE(TRIM('Base de Datos'!R17),",","")))),0)>IFERROR(FIND("@",SUBSTITUTE(TRIM('Base de Datos'!R17),".","@",LEN(TRIM('Base de Datos'!R17))-LEN(SUBSTITUTE(TRIM('Base de Datos'!R17),".","")))),0),_xlfn.NUMBERVALUE(SUBSTITUTE(SUBSTITUTE(TRIM('Base de Datos'!R17),".",""),",","."),".",","),_xlfn.NUMBERVALUE(SUBSTITUTE(TRIM('Base de Datos'!R17),",",""),".",",")),""))) -> 24.04 | AJ21: =IF(ISNUMBER(AK21),IF(ISNUMBER('Base de Datos'!Y17),IF('Base de Datos'!Y17>20000,INT('Base de Datos'!Y17),""),IF(TRIM('Base de Datos'!Y17)="","",IFERROR(DATE(VALUE(RIGHT(TRIM('Base de Datos'!Y17),4)),VALUE(MID(TRIM('Base de Datos'!Y17),4,2)),VALUE(LEFT(TRIM('Base de Datos'!Y17),2))),IFERROR(DATEVALUE(TRIM('Base de Datos'!Y17)),"")))),"") -> 44563 | AK21: =IF(ISNUMBER('Base de Datos'!Z17),'Base de Datos'!Z17,IF(TRIM('Base de Datos'!Z17)="","",IFERROR(IF(IFERROR(FIND("@",SUBSTITUTE(TRIM('Base de Datos'!Z17),",","@",LEN(TRIM('Base de Datos'!Z17))-LEN(SUBSTITUTE(TRIM('Base de Datos'!Z17),",","")))),0)>IFERROR(FIND("@",SUBSTITUTE(TRIM('Base de Datos'!Z17),".","@",LEN(TRIM('Base de Datos'!Z17))-LEN(SUBSTITUTE(TRIM('Base de Datos'!Z17),".","")))),0),_xlfn.NUMBERVALUE(SUBSTITUTE(SUBSTITUTE(TRIM('Base de Datos'!Z17),".",""),",","."),".",","),_xlfn.NUMBERVALUE(SUBSTITUTE(TRIM('Base de Datos'!Z17),",",""),".",",")),""))) -> 53202.11
A22: =ROWS(A$13:A22) -> 10 | B22: =IF(B21="","",IFERROR(SMALL($AH$10:$AH$409,COUNTIF($AH$10:$AH$409,"<="&B21)+1),"")) -> 44549 | C22: =IF(B22="","",INDEX($AI$10:$AI$409,MATCH(B22,$AH$10:$AH$409,0))) -> 24.8 | D22: =IF(B22="","",IFERROR(INDEX($AK$10:$AK$409,MATCH(B22,$AJ$10:$AJ$409,0)),"")) -> 52853.38 | E22: =IF(AND(ISNUMBER(C22),ISNUMBER(C21)),C22/C21-1,"") -> 0.097830899 | F22: =IF(AND(ISNUMBER(D22),ISNUMBER(D21)),D22/D21-1,"") -> 0.0090495552 | G22: =IF(AND(ISNUMBER(E22),ISNUMBER(F22)),1,"") -> 1 | H22: =IF(G22=1,COUNT(G22:G$412),"") -> 250 | I22: =IF(G22=1,IF(H22<='Beta Regresión'!$B$5,1,""),"") -> 1 | J22: =IF(I22=1,E22,"") -> 0.097830899 | K22: =IF(I22=1,F22,"") -> 0.0090495552 | L22: =IF(I22=1,COUNT(I$13:I22),"") -> 9 | M22: =IFERROR(INDEX($J$13:$J$412,MATCH(A22,$L$13:$L$412,0)),"") -> 0.047580645 | N22: =IFERROR(INDEX($K$13:$K$412,MATCH(A22,$L$13:$L$412,0)),"") -> 0.0079287266 | O22: =IF(I22=1,E22,NA()) -> 0.097830899 | P22: =IF(I22=1,F22,NA()) -> 0.0090495552 | R22: =ROWS(R$13:R22) -> 10 | S22: =IF(S21="","",IFERROR(SMALL($AD$10:$AD$509,COUNTIF($AD$10:$AD$509,"<="&S21)+1),"")) -> 46218 | T22: =IF(S22="","",INDEX($AE$10:$AE$509,MATCH(S22,$AD$10:$AD$509,0))) -> 30.04 | U22: =IF(S22="","",IFERROR(INDEX($AG$10:$AG$509,MATCH(S22,$AF$10:$AF$509,0)),"")) -> 66399.71 | V22: =IF(AND(ISNUMBER(T22),ISNUMBER(T21)),T22/T21-1,"") -> 0.0013333333 | W22: =IF(AND(ISNUMBER(U22),ISNUMBER(U21)),U22/U21-1,"") -> 0.0064667286 | X22: =IF(AND(ISNUMBER(V22),ISNUMBER(W22)),1,"") -> 1 | Y22: =IF(X22=1,V22,"") -> 0.0013333333 | Z22: =IF(X22=1,W22,"") -> 0.0064667286 | AA22: =IF(X22=1,V22,NA()) -> 0.0013333333 | AB22: =IF(X22=1,W22,NA()) -> 0.0064667286 | AD22: =IF(ISNUMBER(AE22),IF(ISNUMBER('Base de Datos'!A18),IF('Base de Datos'!A18>20000,DATE(YEAR('Base de Datos'!A18),DAY('Base de Datos'!A18),MONTH('Base de Datos'!A18)),""),IF(TRIM('Base de Datos'!A18)="","",IFERROR(DATE(VALUE(RIGHT(TRIM('Base de Datos'!A18),4)),VALUE(LEFT(TRIM('Base de Datos'!A18),2)),VALUE(MID(TRIM('Base de Datos'!A18),4,2))),""))),"") -> 46224 | AE22: =IF(ISNUMBER('Base de Datos'!B18),'Base de Datos'!B18,IF(TRIM('Base de Datos'!B18)="","",IFERROR(IF(IFERROR(FIND("@",SUBSTITUTE(TRIM('Base de Datos'!B18),",","@",LEN(TRIM('Base de Datos'!B18))-LEN(SUBSTITUTE(TRIM('Base de Datos'!B18),",","")))),0)>IFERROR(FIND("@",SUBSTITUTE(TRIM('Base de Datos'!B18),".","@",LEN(TRIM('Base de Datos'!B18))-LEN(SUBSTITUTE(TRIM('Base de Datos'!B18),".","")))),0),_xlfn.NUMBERVALUE(SUBSTITUTE(SUBSTITUTE(TRIM('Base de Datos'!B18),".",""),",","."),".",","),_xlfn.NUMBERVALUE(SUBSTITUTE(TRIM('Base de Datos'!B18),",",""),".",",")),""))) -> 29.8 | AF22: =IF(ISNUMBER(AG22),IF(ISNUMBER('Base de Datos'!I18),IF('Base de Datos'!I18>20000,INT('Base de Datos'!I18),""),IF(TRIM('Base de Datos'!I18)="","",IFERROR(DATE(VALUE(RIGHT(TRIM('Base de Datos'!I18),4)),VALUE(MID(TRIM('Base de Datos'!I18),4,2)),VALUE(LEFT(TRIM('Base de Datos'!I18),2))),IFERROR(DATEVALUE(TRIM('Base de Datos'!I18)),"")))),"") -> 46220 | AG22: =IF(ISNUMBER('Base de Datos'!J18),'Base de Datos'!J18,IF(TRIM('Base de Datos'!J18)="","",IFERROR(IF(IFERROR(FIND("@",SUBSTITUTE(TRIM('Base de Datos'!J18),",","@",LEN(TRIM('Base de Datos'!J18))-LEN(SUBSTITUTE(TRIM('Base de Datos'!J18),",","")))),0)>IFERROR(FIND("@",SUBSTITUTE(TRIM('Base de Datos'!J18),".","@",LEN(TRIM('Base de Datos'!J18))-LEN(SUBSTITUTE(TRIM('Base de Datos'!J18),".","")))),0),_xlfn.NUMBERVALUE(SUBSTITUTE(SUBSTITUTE(TRIM('Base de Datos'!J18),".",""),",","."),".",","),_xlfn.NUMBERVALUE(SUBSTITUTE(TRIM('Base de Datos'!J18),",",""),".",",")),""))) -> 66634.23 | AH22: =IF(ISNUMBER(AI22),IF(ISNUMBER('Base de Datos'!Q18),IF('Base de Datos'!Q18>20000,DATE(YEAR('Base de Datos'!Q18),DAY('Base de Datos'!Q18),MONTH('Base de Datos'!Q18)),""),IF(TRIM('Base de Datos'!Q18)="","",IFERROR(DATE(VALUE(RIGHT(TRIM('Base de Datos'!Q18),4)),VALUE(LEFT(TRIM('Base de Datos'!Q18),2)),VALUE(MID(TRIM('Base de Datos'!Q18),4,2))),""))),"") -> 44570 | AI22: =IF(ISNUMBER('Base de Datos'!R18),'Base de Datos'!R18,IF(TRIM('Base de Datos'!R18)="","",IFERROR(IF(IFERROR(FIND("@",SUBSTITUTE(TRIM('Base de Datos'!R18),",","@",LEN(TRIM('Base de Datos'!R18))-LEN(SUBSTITUTE(TRIM('Base de Datos'!R18),",","")))),0)>IFERROR(FIND("@",SUBSTITUTE(TRIM('Base de Datos'!R18),".","@",LEN(TRIM('Base de Datos'!R18))-LEN(SUBSTITUTE(TRIM('Base de Datos'!R18),".","")))),0),_xlfn.NUMBERVALUE(SUBSTITUTE(SUBSTITUTE(TRIM('Base de Datos'!R18),".",""),",","."),".",","),_xlfn.NUMBERVALUE(SUBSTITUTE(TRIM('Base de Datos'!R18),",",""),".",",")),""))) -> 23.98 | AJ22: =IF(ISNUMBER(AK22),IF(ISNUMBER('Base de Datos'!Y18),IF('Base de Datos'!Y18>20000,INT('Base de Datos'!Y18),""),IF(TRIM('Base de Datos'!Y18)="","",IFERROR(DATE(VALUE(RIGHT(TRIM('Base de Datos'!Y18),4)),VALUE(MID(TRIM('Base de Datos'!Y18),4,2)),VALUE(LEFT(TRIM('Base de Datos'!Y18),2))),IFERROR(DATEVALUE(TRIM('Base de Datos'!Y18)),"")))),"") -> 44570 | AK22: =IF(ISNUMBER('Base de Datos'!Z18),'Base de Datos'!Z18,IF(TRIM('Base de Datos'!Z18)="","",IFERROR(IF(IFERROR(FIND("@",SUBSTITUTE(TRIM('Base de Datos'!Z18),",","@",LEN(TRIM('Base de Datos'!Z18))-LEN(SUBSTITUTE(TRIM('Base de Datos'!Z18),",","")))),0)>IFERROR(FIND("@",SUBSTITUTE(TRIM('Base de Datos'!Z18),".","@",LEN(TRIM('Base de Datos'!Z18))-LEN(SUBSTITUTE(TRIM('Base de Datos'!Z18),".","")))),0),_xlfn.NUMBERVALUE(SUBSTITUTE(SUBSTITUTE(TRIM('Base de Datos'!Z18),".",""),",","."),".",","),_xlfn.NUMBERVALUE(SUBSTITUTE(TRIM('Base de Datos'!Z18),",",""),".",",")),""))) -> 53744.92
A23: =ROWS(A$13:A23) -> 11 | B23: =IF(B22="","",IFERROR(SMALL($AH$10:$AH$409,COUNTIF($AH$10:$AH$409,"<="&B22)+1),"")) -> 44556 | C23: =IF(B23="","",INDEX($AI$10:$AI$409,MATCH(B23,$AH$10:$AH$409,0))) -> 25.98 | D23: =IF(B23="","",IFERROR(INDEX($AK$10:$AK$409,MATCH(B23,$AJ$10:$AJ$409,0)),"")) -> 53272.44 | E23: =IF(AND(ISNUMBER(C23),ISNUMBER(C22)),C23/C22-1,"") -> 0.047580645 | F23: =IF(AND(ISNUMBER(D23),ISNUMBER(D22)),D23/D22-1,"") -> 0.0079287266 | G23: =IF(AND(ISNUMBER(E23),ISNUMBER(F23)),1,"") -> 1 | H23: =IF(G23=1,COUNT(G23:G$412),"") -> 249 | I23: =IF(G23=1,IF(H23<='Beta Regresión'!$B$5,1,""),"") -> 1 | J23: =IF(I23=1,E23,"") -> 0.047580645 | K23: =IF(I23=1,F23,"") -> 0.0079287266 | L23: =IF(I23=1,COUNT(I$13:I23),"") -> 10 | M23: =IFERROR(INDEX($J$13:$J$412,MATCH(A23,$L$13:$L$412,0)),"") -> -0.074672825 | N23: =IFERROR(INDEX($K$13:$K$412,MATCH(A23,$L$13:$L$412,0)),"") -> -0.0013201948 | O23: =IF(I23=1,E23,NA()) -> 0.047580645 | P23: =IF(I23=1,F23,NA()) -> 0.0079287266 | R23: =ROWS(R$13:R23) -> 11 | S23: =IF(S22="","",IFERROR(SMALL($AD$10:$AD$509,COUNTIF($AD$10:$AD$509,"<="&S22)+1),"")) -> 46219 | T23: =IF(S23="","",INDEX($AE$10:$AE$509,MATCH(S23,$AD$10:$AD$509,0))) -> 29.96 | U23: =IF(S23="","",IFERROR(INDEX($AG$10:$AG$509,MATCH(S23,$AF$10:$AF$509,0)),"")) -> 66356.09 | V23: =IF(AND(ISNUMBER(T23),ISNUMBER(T22)),T23/T22-1,"") -> -0.0026631158 | W23: =IF(AND(ISNUMBER(U23),ISNUMBER(U22)),U23/U22-1,"") -> -0.00065693058 | X23: =IF(AND(ISNUMBER(V23),ISNUMBER(W23)),1,"") -> 1 | Y23: =IF(X23=1,V23,"") -> -0.0026631158 | Z23: =IF(X23=1,W23,"") -> -0.00065693058 | AA23: =IF(X23=1,V23,NA()) -> -0.0026631158 | AB23: =IF(X23=1,W23,NA()) -> -0.00065693058 | AD23: =IF(ISNUMBER(AE23),IF(ISNUMBER('Base de Datos'!A19),IF('Base de Datos'!A19>20000,DATE(YEAR('Base de Datos'!A19),DAY('Base de Datos'!A19),MONTH('Base de Datos'!A19)),""),IF(TRIM('Base de Datos'!A19)="","",IFERROR(DATE(VALUE(RIGHT(TRIM('Base de Datos'!A19),4)),VALUE(LEFT(TRIM('Base de Datos'!A19),2)),VALUE(MID(TRIM('Base de Datos'!A19),4,2))),""))),"") -> 46225 | AE23: =IF(ISNUMBER('Base de Datos'!B19),'Base de Datos'!B19,IF(TRIM('Base de Datos'!B19)="","",IFERROR(IF(IFERROR(FIND("@",SUBSTITUTE(TRIM('Base de Datos'!B19),",","@",LEN(TRIM('Base de Datos'!B19))-LEN(SUBSTITUTE(TRIM('Base de Datos'!B19),",","")))),0)>IFERROR(FIND("@",SUBSTITUTE(TRIM('Base de Datos'!B19),".","@",LEN(TRIM('Base de Datos'!B19))-LEN(SUBSTITUTE(TRIM('Base de Datos'!B19),".","")))),0),_xlfn.NUMBERVALUE(SUBSTITUTE(SUBSTITUTE(TRIM('Base de Datos'!B19),".",""),",","."),".",","),_xlfn.NUMBERVALUE(SUBSTITUTE(TRIM('Base de Datos'!B19),",",""),".",",")),""))) -> 29.3 | AF23: =IF(ISNUMBER(AG23),IF(ISNUMBER('Base de Datos'!I19),IF('Base de Datos'!I19>20000,INT('Base de Datos'!I19),""),IF(TRIM('Base de Datos'!I19)="","",IFERROR(DATE(VALUE(RIGHT(TRIM('Base de Datos'!I19),4)),VALUE(MID(TRIM('Base de Datos'!I19),4,2)),VALUE(LEFT(TRIM('Base de Datos'!I19),2))),IFERROR(DATEVALUE(TRIM('Base de Datos'!I19)),"")))),"") -> 46223 | AG23: =IF(ISNUMBER('Base de Datos'!J19),'Base de Datos'!J19,IF(TRIM('Base de Datos'!J19)="","",IFERROR(IF(IFERROR(FIND("@",SUBSTITUTE(TRIM('Base de Datos'!J19),",","@",LEN(TRIM('Base de Datos'!J19))-LEN(SUBSTITUTE(TRIM('Base de Datos'!J19),",","")))),0)>IFERROR(FIND("@",SUBSTITUTE(TRIM('Base de Datos'!J19),".","@",LEN(TRIM('Base de Datos'!J19))-LEN(SUBSTITUTE(TRIM('Base de Datos'!J19),".","")))),0),_xlfn.NUMBERVALUE(SUBSTITUTE(SUBSTITUTE(TRIM('Base de Datos'!J19),".",""),",","."),".",","),_xlfn.NUMBERVALUE(SUBSTITUTE(TRIM('Base de Datos'!J19),",",""),".",",")),""))) -> 66122.78 | AH23: =IF(ISNUMBER(AI23),IF(ISNUMBER('Base de Datos'!Q19),IF('Base de Datos'!Q19>20000,DATE(YEAR('Base de Datos'!Q19),DAY('Base de Datos'!Q19),MONTH('Base de Datos'!Q19)),""),IF(TRIM('Base de Datos'!Q19)="","",IFERROR(DATE(VALUE(RIGHT(TRIM('Base de Datos'!Q19),4)),VALUE(LEFT(TRIM('Base de Datos'!Q19),2)),VALUE(MID(TRIM('Base de Datos'!Q19),4,2))),""))),"") -> 44577 | AI23: =IF(ISNUMBER('Base de Datos'!R19),'Base de Datos'!R19,IF(TRIM('Base de Datos'!R19)="","",IFERROR(IF(IFERROR(FIND("@",SUBSTITUTE(TRIM('Base de Datos'!R19),",","@",LEN(TRIM('Base de Datos'!R19))-LEN(SUBSTITUTE(TRIM('Base de Datos'!R19),",","")))),0)>IFERROR(FIND("@",SUBSTITUTE(TRIM('Base de Datos'!R19),".","@",LEN(TRIM('Base de Datos'!R19))-LEN(SUBSTITUTE(TRIM('Base de Datos'!R19),".","")))),0),_xlfn.NUMBERVALUE(SUBSTITUTE(SUBSTITUTE(TRIM('Base de Datos'!R19),".",""),",","."),".",","),_xlfn.NUMBERVALUE(SUBSTITUTE(TRIM('Base de Datos'!R19),",",""),".",",")),""))) -> 22.92 | AJ23: =IF(ISNUMBER(AK23),IF(ISNUMBER('Base de Datos'!Y19),IF('Base de Datos'!Y19>20000,INT('Base de Datos'!Y19),""),IF(TRIM('Base de Datos'!Y19)="","",IFERROR(DATE(VALUE(RIGHT(TRIM('Base de Datos'!Y19),4)),VALUE(MID(TRIM('Base de Datos'!Y19),4,2)),VALUE(LEFT(TRIM('Base de Datos'!Y19),2))),IFERROR(DATEVALUE(TRIM('Base de Datos'!Y19)),"")))),"") -> 44577 | AK23: =IF(ISNUMBER('Base de Datos'!Z19),'Base de Datos'!Z19,IF(TRIM('Base de Datos'!Z19)="","",IFERROR(IF(IFERROR(FIND("@",SUBSTITUTE(TRIM('Base de Datos'!Z19),",","@",LEN(TRIM('Base de Datos'!Z19))-LEN(SUBSTITUTE(TRIM('Base de Datos'!Z19),",","")))),0)>IFERROR(FIND("@",SUBSTITUTE(TRIM('Base de Datos'!Z19),".","@",LEN(TRIM('Base de Datos'!Z19))-LEN(SUBSTITUTE(TRIM('Base de Datos'!Z19),".","")))),0),_xlfn.NUMBERVALUE(SUBSTITUTE(SUBSTITUTE(TRIM('Base de Datos'!Z19),".",""),",","."),".",","),_xlfn.NUMBERVALUE(SUBSTITUTE(TRIM('Base de Datos'!Z19),",",""),".",",")),""))) -> 51599.38
A24: =ROWS(A$13:A24) -> 12 | B24: =IF(B23="","",IFERROR(SMALL($AH$10:$AH$409,COUNTIF($AH$10:$AH$409,"<="&B23)+1),"")) -> 44563 | C24: =IF(B24="","",INDEX($AI$10:$AI$409,MATCH(B24,$AH$10:$AH$409,0))) -> 24.04 | D24: =IF(B24="","",IFERROR(INDEX($AK$10:$AK$409,MATCH(B24,$AJ$10:$AJ$409,0)),"")) -> 53202.11 | E24: =IF(AND(ISNUMBER(C24),ISNUMBER(C23)),C24/C23-1,"") -> -0.074672825 | F24: =IF(AND(ISNUMBER(D24),ISNUMBER(D23)),D24/D23-1,"") -> -0.0013201948 | G24: =IF(AND(ISNUMBER(E24),ISNUMBER(F24)),1,"") -> 1 | H24: =IF(G24=1,COUNT(G24:G$412),"") -> 248 | I24: =IF(G24=1,IF(H24<='Beta Regresión'!$B$5,1,""),"") -> 1 | J24: =IF(I24=1,E24,"") -> -0.074672825 | K24: =IF(I24=1,F24,"") -> -0.0013201948 | L24: =IF(I24=1,COUNT(I$13:I24),"") -> 11 | M24: =IFERROR(INDEX($J$13:$J$412,MATCH(A24,$L$13:$L$412,0)),"") -> -0.0024958403 | N24: =IFERROR(INDEX($K$13:$K$412,MATCH(A24,$L$13:$L$412,0)),"") -> 0.010202791 | O24: =IF(I24=1,E24,NA()) -> -0.074672825 | P24: =IF(I24=1,F24,NA()) -> -0.0013201948 | R24: =ROWS(R$13:R24) -> 12 | S24: =IF(S23="","",IFERROR(SMALL($AD$10:$AD$509,COUNTIF($AD$10:$AD$509,"<="&S23)+1),"")) -> 46220 | T24: =IF(S24="","",INDEX($AE$10:$AE$509,MATCH(S24,$AD$10:$AD$509,0))) -> 30.27 | U24: =IF(S24="","",IFERROR(INDEX($AG$10:$AG$509,MATCH(S24,$AF$10:$AF$509,0)),"")) -> 66634.23 | V24: =IF(AND(ISNUMBER(T24),ISNUMBER(T23)),T24/T23-1,"") -> 0.01034713 | W24: =IF(AND(ISNUMBER(U24),ISNUMBER(U23)),U24/U23-1,"") -> 0.0041916273 | X24: =IF(AND(ISNUMBER(V24),ISNUMBER(W24)),1,"") -> 1 | Y24: =IF(X24=1,V24,"") -> 0.01034713 | Z24: =IF(X24=1,W24,"") -> 0.0041916273 | AA24: =IF(X24=1,V24,NA()) -> 0.01034713 | AB24: =IF(X24=1,W24,NA()) -> 0.0041916273 | AD24: =IF(ISNUMBER(AE24),IF(ISNUMBER('Base de Datos'!A20),IF('Base de Datos'!A20>20000,DATE(YEAR('Base de Datos'!A20),DAY('Base de Datos'!A20),MONTH('Base de Datos'!A20)),""),IF(TRIM('Base de Datos'!A20)="","",IFERROR(DATE(VALUE(RIGHT(TRIM('Base de Datos'!A20),4)),VALUE(LEFT(TRIM('Base de Datos'!A20),2)),VALUE(MID(TRIM('Base de Datos'!A20),4,2))),""))),"") -> 46227 | AE24: =IF(ISNUMBER('Base de Datos'!B20),'Base de Datos'!B20,IF(TRIM('Base de Datos'!B20)="","",IFERROR(IF(IFERROR(FIND("@",SUBSTITUTE(TRIM('Base de Datos'!B20),",","@",LEN(TRIM('Base de Datos'!B20))-LEN(SUBSTITUTE(TRIM('Base de Datos'!B20),",","")))),0)>IFERROR(FIND("@",SUBSTITUTE(TRIM('Base de Datos'!B20),".","@",LEN(TRIM('Base de Datos'!B20))-LEN(SUBSTITUTE(TRIM('Base de Datos'!B20),".","")))),0),_xlfn.NUMBERVALUE(SUBSTITUTE(SUBSTITUTE(TRIM('Base de Datos'!B20),".",""),",","."),".",","),_xlfn.NUMBERVALUE(SUBSTITUTE(TRIM('Base de Datos'!B20),",",""),".",",")),""))) -> 29.41 | AF24: =IF(ISNUMBER(AG24),IF(ISNUMBER('Base de Datos'!I20),IF('Base de Datos'!I20>20000,INT('Base de Datos'!I20),""),IF(TRIM('Base de Datos'!I20)="","",IFERROR(DATE(VALUE(RIGHT(TRIM('Base de Datos'!I20),4)),VALUE(MID(TRIM('Base de Datos'!I20),4,2)),VALUE(LEFT(TRIM('Base de Datos'!I20),2))),IFERROR(DATEVALUE(TRIM('Base de Datos'!I20)),"")))),"") -> 46224 | AG24: =IF(ISNUMBER('Base de Datos'!J20),'Base de Datos'!J20,IF(TRIM('Base de Datos'!J20)="","",IFERROR(IF(IFERROR(FIND("@",SUBSTITUTE(TRIM('Base de Datos'!J20),",","@",LEN(TRIM('Base de Datos'!J20))-LEN(SUBSTITUTE(TRIM('Base de Datos'!J20),",","")))),0)>IFERROR(FIND("@",SUBSTITUTE(TRIM('Base de Datos'!J20),".","@",LEN(TRIM('Base de Datos'!J20))-LEN(SUBSTITUTE(TRIM('Base de Datos'!J20),".","")))),0),_xlfn.NUMBERVALUE(SUBSTITUTE(SUBSTITUTE(TRIM('Base de Datos'!J20),".",""),",","."),".",","),_xlfn.NUMBERVALUE(SUBSTITUTE(TRIM('Base de Datos'!J20),",",""),".",",")),""))) -> 66713.83 | AH24: =IF(ISNUMBER(AI24),IF(ISNUMBER('Base de Datos'!Q20),IF('Base de Datos'!Q20>20000,DATE(YEAR('Base de Datos'!Q20),DAY('Base de Datos'!Q20),MONTH('Base de Datos'!Q20)),""),IF(TRIM('Base de Datos'!Q20)="","",IFERROR(DATE(VALUE(RIGHT(TRIM('Base de Datos'!Q20),4)),VALUE(LEFT(TRIM('Base de Datos'!Q20),2)),VALUE(MID(TRIM('Base de Datos'!Q20),4,2))),""))),"") -> 44584 | AI24: =IF(ISNUMBER('Base de Datos'!R20),'Base de Datos'!R20,IF(TRIM('Base de Datos'!R20)="","",IFERROR(IF(IFERROR(FIND("@",SUBSTITUTE(TRIM('Base de Datos'!R20),",","@",LEN(TRIM('Base de Datos'!R20))-LEN(SUBSTITUTE(TRIM('Base de Datos'!R20),",","")))),0)>IFERROR(FIND("@",SUBSTITUTE(TRIM('Base de Datos'!R20),".","@",LEN(TRIM('Base de Datos'!R20))-LEN(SUBSTITUTE(TRIM('Base de Datos'!R20),".","")))),0),_xlfn.NUMBERVALUE(SUBSTITUTE(SUBSTITUTE(TRIM('Base de Datos'!R20),".",""),",","."),".",","),_xlfn.NUMBERVALUE(SUBSTITUTE(TRIM('Base de Datos'!R20),",",""),".",",")),""))) -> 22.39 | AJ24: =IF(ISNUMBER(AK24),IF(ISNUMBER('Base de Datos'!Y20),IF('Base de Datos'!Y20>20000,INT('Base de Datos'!Y20),""),IF(TRIM('Base de Datos'!Y20)="","",IFERROR(DATE(VALUE(RIGHT(TRIM('Base de Datos'!Y20),4)),VALUE(MID(TRIM('Base de Datos'!Y20),4,2)),VALUE(LEFT(TRIM('Base de Datos'!Y20),2))),IFERROR(DATEVALUE(TRIM('Base de Datos'!Y20)),"")))),"") -> 44584 | AK24: =IF(ISNUMBER('Base de Datos'!Z20),'Base de Datos'!Z20,IF(TRIM('Base de Datos'!Z20)="","",IFERROR(IF(IFERROR(FIND("@",SUBSTITUTE(TRIM('Base de Datos'!Z20),",","@",LEN(TRIM('Base de Datos'!Z20))-LEN(SUBSTITUTE(TRIM('Base de Datos'!Z20),",","")))),0)>IFERROR(FIND("@",SUBSTITUTE(TRIM('Base de Datos'!Z20),".","@",LEN(TRIM('Base de Datos'!Z20))-LEN(SUBSTITUTE(TRIM('Base de Datos'!Z20),".","")))),0),_xlfn.NUMBERVALUE(SUBSTITUTE(SUBSTITUTE(TRIM('Base de Datos'!Z20),".",""),",","."),".",","),_xlfn.NUMBERVALUE(SUBSTITUTE(TRIM('Base de Datos'!Z20),",",""),".",",")),""))) -> 50661.86
A25: =ROWS(A$13:A25) -> 13 | B25: =IF(B24="","",IFERROR(SMALL($AH$10:$AH$409,COUNTIF($AH$10:$AH$409,"<="&B24)+1),"")) -> 44570 | C25: =IF(B25="","",INDEX($AI$10:$AI$409,MATCH(B25,$AH$10:$AH$409,0))) -> 23.98 | D25: =IF(B25="","",IFERROR(INDEX($AK$10:$AK$409,MATCH(B25,$AJ$10:$AJ$409,0)),"")) -> 53744.92 | E25: =IF(AND(ISNUMBER(C25),ISNUMBER(C24)),C25/C24-1,"") -> -0.0024958403 | F25: =IF(AND(ISNUMBER(D25),ISNUMBER(D24)),D25/D24-1,"") -> 0.010202791 | G25: =IF(AND(ISNUMBER(E25),ISNUMBER(F25)),1,"") -> 1 | H25: =IF(G25=1,COUNT(G25:G$412),"") -> 247 | I25: =IF(G25=1,IF(H25<='Beta Regresión'!$B$5,1,""),"") -> 1 | J25: =IF(I25=1,E25,"") -> -0.0024958403 | K25: =IF(I25=1,F25,"") -> 0.010202791 | L25: =IF(I25=1,COUNT(I$13:I25),"") -> 12 | M25: =IFERROR(INDEX($J$13:$J$412,MATCH(A25,$L$13:$L$412,0)),"") -> -0.044203503 | N25: =IFERROR(INDEX($K$13:$K$412,MATCH(A25,$L$13:$L$412,0)),"") -> -0.039920796 | O25: =IF(I25=1,E25,NA()) -> -0.0024958403 | P25: =IF(I25=1,F25,NA()) -> 0.010202791 | R25: =ROWS(R$13:R25) -> 13 | S25: =IF(S24="","",IFERROR(SMALL($AD$10:$AD$509,COUNTIF($AD$10:$AD$509,"<="&S24)+1),"")) -> 46224 | T25: =IF(S25="","",INDEX($AE$10:$AE$509,MATCH(S25,$AD$10:$AD$509,0))) -> 29.8 | U25: =IF(S25="","",IFERROR(INDEX($AG$10:$AG$509,MATCH(S25,$AF$10:$AF$509,0)),"")) -> 66713.83 | V25: =IF(AND(ISNUMBER(T25),ISNUMBER(T24)),T25/T24-1,"") -> -0.015526924 | W25: =IF(AND(ISNUMBER(U25),ISNUMBER(U24)),U25/U24-1,"") -> 0.0011945812 | X25: =IF(AND(ISNUMBER(V25),ISNUMBER(W25)),1,"") -> 1 | Y25: =IF(X25=1,V25,"") -> -0.015526924 | Z25: =IF(X25=1,W25,"") -> 0.0011945812 | AA25: =IF(X25=1,V25,NA()) -> -0.015526924 | AB25: =IF(X25=1,W25,NA()) -> 0.0011945812 | AD25: =IF(ISNUMBER(AE25),IF(ISNUMBER('Base de Datos'!A21),IF('Base de Datos'!A21>20000,DATE(YEAR('Base de Datos'!A21),DAY('Base de Datos'!A21),MONTH('Base de Datos'!A21)),""),IF(TRIM('Base de Datos'!A21)="","",IFERROR(DATE(VALUE(RIGHT(TRIM('Base de Datos'!A21),4)),VALUE(LEFT(TRIM('Base de Datos'!A21),2)),VALUE(MID(TRIM('Base de Datos'!A21),4,2))),""))),"") -> 46230 | AE25: =IF(ISNUMBER('Base de Datos'!B21),'Base de Datos'!B21,IF(TRIM('Base de Datos'!B21)="","",IFERROR(IF(IFERROR(FIND("@",SUBSTITUTE(TRIM('Base de Datos'!B21),",","@",LEN(TRIM('Base de Datos'!B21))-LEN(SUBSTITUTE(TRIM('Base de Datos'!B21),",","")))),0)>IFERROR(FIND("@",SUBSTITUTE(TRIM('Base de Datos'!B21),".","@",LEN(TRIM('Base de Datos'!B21))-LEN(SUBSTITUTE(TRIM('Base de Datos'!B21),".","")))),0),_xlfn.NUMBERVALUE(SUBSTITUTE(SUBSTITUTE(TRIM('Base de Datos'!B21),".",""),",","."),".",","),_xlfn.NUMBERVALUE(SUBSTITUTE(TRIM('Base de Datos'!B21),",",""),".",",")),""))) -> 29.03 | AF25: =IF(ISNUMBER(AG25),IF(ISNUMBER('Base de Datos'!I21),IF('Base de Datos'!I21>20000,INT('Base de Datos'!I21),""),IF(TRIM('Base de Datos'!I21)="","",IFERROR(DATE(VALUE(RIGHT(TRIM('Base de Datos'!I21),4)),VALUE(MID(TRIM('Base de Datos'!I21),4,2)),VALUE(LEFT(TRIM('Base de Datos'!I21),2))),IFERROR(DATEVALUE(TRIM('Base de Datos'!I21)),"")))),"") -> 46225 | AG25: =IF(ISNUMBER('Base de Datos'!J21),'Base de Datos'!J21,IF(TRIM('Base de Datos'!J21)="","",IFERROR(IF(IFERROR(FIND("@",SUBSTITUTE(TRIM('Base de Datos'!J21),",","@",LEN(TRIM('Base de Datos'!J21))-LEN(SUBSTITUTE(TRIM('Base de Datos'!J21),",","")))),0)>IFERROR(FIND("@",SUBSTITUTE(TRIM('Base de Datos'!J21),".","@",LEN(TRIM('Base de Datos'!J21))-LEN(SUBSTITUTE(TRIM('Base de Datos'!J21),".","")))),0),_xlfn.NUMBERVALUE(SUBSTITUTE(SUBSTITUTE(TRIM('Base de Datos'!J21),".",""),",","."),".",","),_xlfn.NUMBERVALUE(SUBSTITUTE(TRIM('Base de Datos'!J21),",",""),".",",")),""))) -> 67303.83 | AH25: =IF(ISNUMBER(AI25),IF(ISNUMBER('Base de Datos'!Q21),IF('Base de Datos'!Q21>20000,DATE(YEAR('Base de Datos'!Q21),DAY('Base de Datos'!Q21),MONTH('Base de Datos'!Q21)),""),IF(TRIM('Base de Datos'!Q21)="","",IFERROR(DATE(VALUE(RIGHT(TRIM('Base de Datos'!Q21),4)),VALUE(LEFT(TRIM('Base de Datos'!Q21),2)),VALUE(MID(TRIM('Base de Datos'!Q21),4,2))),""))),"") -> 44591 | AI25: =IF(ISNUMBER('Base de Datos'!R21),'Base de Datos'!R21,IF(TRIM('Base de Datos'!R21)="","",IFERROR(IF(IFERROR(FIND("@",SUBSTITUTE(TRIM('Base de Datos'!R21),",","@",LEN(TRIM('Base de Datos'!R21))-LEN(SUBSTITUTE(TRIM('Base de Datos'!R21),",","")))),0)>IFERROR(FIND("@",SUBSTITUTE(TRIM('Base de Datos'!R21),".","@",LEN(TRIM('Base de Datos'!R21))-LEN(SUBSTITUTE(TRIM('Base de Datos'!R21),".","")))),0),_xlfn.NUMBERVALUE(SUBSTITUTE(SUBSTITUTE(TRIM('Base de Datos'!R21),".",""),",","."),".",","),_xlfn.NUMBERVALUE(SUBSTITUTE(TRIM('Base de Datos'!R21),",",""),".",",")),""))) -> 23.24 | AJ25: =IF(ISNUMBER(AK25),IF(ISNUMBER('Base de Datos'!Y21),IF('Base de Datos'!Y21>20000,INT('Base de Datos'!Y21),""),IF(TRIM('Base de Datos'!Y21)="","",IFERROR(DATE(VALUE(RIGHT(TRIM('Base de Datos'!Y21),4)),VALUE(MID(TRIM('Base de Datos'!Y21),4,2)),VALUE(LEFT(TRIM('Base de Datos'!Y21),2))),IFERROR(DATEVALUE(TRIM('Base de Datos'!Y21)),"")))),"") -> 44591 | AK25: =IF(ISNUMBER('Base de Datos'!Z21),'Base de Datos'!Z21,IF(TRIM('Base de Datos'!Z21)="","",IFERROR(IF(IFERROR(FIND("@",SUBSTITUTE(TRIM('Base de Datos'!Z21),",","@",LEN(TRIM('Base de Datos'!Z21))-LEN(SUBSTITUTE(TRIM('Base de Datos'!Z21),",","")))),0)>IFERROR(FIND("@",SUBSTITUTE(TRIM('Base de Datos'!Z21),".","@",LEN(TRIM('Base de Datos'!Z21))-LEN(SUBSTITUTE(TRIM('Base de Datos'!Z21),".","")))),0),_xlfn.NUMBERVALUE(SUBSTITUTE(SUBSTITUTE(TRIM('Base de Datos'!Z21),".",""),",","."),".",","),_xlfn.NUMBERVALUE(SUBSTITUTE(TRIM('Base de Datos'!Z21),",",""),".",",")),""))) -> 51255.31
... A409: =ROWS(A$13:A409) -> 397 | B409: =IF(B408="","",IFERROR(SMALL($AH$10:$AH$409,COUNTIF($AH$10:$AH$409,"<="&B408)+1),"")) | C409: =IF(B409="","",INDEX($AI$10:$AI$409,MATCH(B409,$AH$10:$AH$409,0))) | D409: =IF(B409="","",IFERROR(INDEX($AK$10:$AK$409,MATCH(B409,$AJ$10:$AJ$409,0)),"")) | E409: =IF(AND(ISNUMBER(C409),ISNUMBER(C408)),C409/C408-1,"") | F409: =IF(AND(ISNUMBER(D409),ISNUMBER(D408)),D409/D408-1,"") | G409: =IF(AND(ISNUMBER(E409),ISNUMBER(F409)),1,"") | H409: =IF(G409=1,COUNT(G409:G$412),"") | I409: =IF(G409=1,IF(H409<='Beta Regresión'!$B$5,1,""),"") | J409: =IF(I409=1,E409,"") | K409: =IF(I409=1,F409,"") | L409: =IF(I409=1,COUNT(I$13:I409),"") | M409: =IFERROR(INDEX($J$13:$J$412,MATCH(A409,$L$13:$L$412,0)),"") | N409: =IFERROR(INDEX($K$13:$K$412,MATCH(A409,$L$13:$L$412,0)),"") | O409: =IF(I409=1,E409,NA()) -> #N/A | P409: =IF(I409=1,F409,NA()) -> #N/A | R409: =ROWS(R$13:R409) -> 397 | S409: =IF(S408="","",IFERROR(SMALL($AD$10:$AD$509,COUNTIF($AD$10:$AD$509,"<="&S408)+1),"")) | T409: =IF(S409="","",INDEX($AE$10:$AE$509,MATCH(S409,$AD$10:$AD$509,0))) | U409: =IF(S409="","",IFERROR(INDEX($AG$10:$AG$509,MATCH(S409,$AF$10:$AF$509,0)),"")) | V409: =IF(AND(ISNUMBER(T409),ISNUMBER(T408)),T409/T408-1,"") | W409: =IF(AND(ISNUMBER(U409),ISNUMBER(U408)),U409/U408-1,"") | X409: =IF(AND(ISNUMBER(V409),ISNUMBER(W409)),1,"") | Y409: =IF(X409=1,V409,"") | Z409: =IF(X409=1,W409,"") | AA409: =IF(X409=1,V409,NA()) -> #N/A | AB409: =IF(X409=1,W409,NA()) -> #N/A | AD409: =IF(ISNUMBER(AE409),IF(ISNUMBER('Base de Datos'!A405),IF('Base de Datos'!A405>20000,DATE(YEAR('Base de Datos'!A405),DAY('Base de Datos'!A405),MONTH('Base de Datos'!A405)),""),IF(TRIM('Base de Datos'!A405)="","",IFERROR(DATE(VALUE(RIGHT(TRIM('Base de Datos'!A405),4)),VALUE(LEFT(TRIM('Base de Datos'!A405),2)),VALUE(MID(TRIM('Base de Datos'!A405),4,2))),""))),"") | AE409: =IF(ISNUMBER('Base de Datos'!B405),'Base de Datos'!B405,IF(TRIM('Base de Datos'!B405)="","",IFERROR(IF(IFERROR(FIND("@",SUBSTITUTE(TRIM('Base de Datos'!B405),",","@",LEN(TRIM('Base de Datos'!B405))-LEN(SUBSTITUTE(TRIM('Base de Datos'!B405),",","")))),0)>IFERROR(FIND("@",SUBSTITUTE(TRIM('Base de Datos'!B405),".","@",LEN(TRIM('Base de Datos'!B405))-LEN(SUBSTITUTE(TRIM('Base de Datos'!B405),".","")))),0),_xlfn.NUMBERVALUE(SUBSTITUTE(SUBSTITUTE(TRIM('Base de Datos'!B405),".",""),",","."),".",","),_xlfn.NUMBERVALUE(SUBSTITUTE(TRIM('Base de Datos'!B405),",",""),".",",")),""))) | AF409: =IF(ISNUMBER(AG409),IF(ISNUMBER('Base de Datos'!I405),IF('Base de Datos'!I405>20000,INT('Base de Datos'!I405),""),IF(TRIM('Base de Datos'!I405)="","",IFERROR(DATE(VALUE(RIGHT(TRIM('Base de Datos'!I405),4)),VALUE(MID(TRIM('Base de Datos'!I405),4,2)),VALUE(LEFT(TRIM('Base de Datos'!I405),2))),IFERROR(DATEVALUE(TRIM('Base de Datos'!I405)),"")))),"") | AG409: =IF(ISNUMBER('Base de Datos'!J405),'Base de Datos'!J405,IF(TRIM('Base de Datos'!J405)="","",IFERROR(IF(IFERROR(FIND("@",SUBSTITUTE(TRIM('Base de Datos'!J405),",","@",LEN(TRIM('Base de Datos'!J405))-LEN(SUBSTITUTE(TRIM('Base de Datos'!J405),",","")))),0)>IFERROR(FIND("@",SUBSTITUTE(TRIM('Base de Datos'!J405),".","@",LEN(TRIM('Base de Datos'!J405))-LEN(SUBSTITUTE(TRIM('Base de Datos'!J405),".","")))),0),_xlfn.NUMBERVALUE(SUBSTITUTE(SUBSTITUTE(TRIM('Base de Datos'!J405),".",""),",","."),".",","),_xlfn.NUMBERVALUE(SUBSTITUTE(TRIM('Base de Datos'!J405),",",""),".",",")),""))) | AH409: =IF(ISNUMBER(AI409),IF(ISNUMBER('Base de Datos'!Q405),IF('Base de Datos'!Q405>20000,DATE(YEAR('Base de Datos'!Q405),DAY('Base de Datos'!Q405),MONTH('Base de Datos'!Q405)),""),IF(TRIM('Base de Datos'!Q405)="","",IFERROR(DATE(VALUE(RIGHT(TRIM('Base de Datos'!Q405),4)),VALUE(LEFT(TRIM('Base de Datos'!Q405),2)),VALUE(MID(TRIM('Base de Datos'!Q405),4,2))),""))),"") | AI409: =IF(ISNUMBER('Base de Datos'!R405),'Base de Datos'!R405,IF(TRIM('Base de Datos'!R405)="","",IFERROR(IF(IFERROR(FIND("@",SUBSTITUTE(TRIM('Base de Datos'!R405),",","@",LEN(TRIM('Base de Datos'!R405))-LEN(SUBSTITUTE(TRIM('Base de Datos'!R405),",","")))),0)>IFERROR(FIND("@",SUBSTITUTE(TRIM('Base de Datos'!R405),".","@",LEN(TRIM('Base de Datos'!R405))-LEN(SUBSTITUTE(TRIM('Base de Datos'!R405),".","")))),0),_xlfn.NUMBERVALUE(SUBSTITUTE(SUBSTITUTE(TRIM('Base de Datos'!R405),".",""),",","."),".",","),_xlfn.NUMBERVALUE(SUBSTITUTE(TRIM('Base de Datos'!R405),",",""),".",",")),""))) | AJ409: =IF(ISNUMBER(AK409),IF(ISNUMBER('Base de Datos'!Y405),IF('Base de Datos'!Y405>20000,INT('Base de Datos'!Y405),""),IF(TRIM('Base de Datos'!Y405)="","",IFERROR(DATE(VALUE(RIGHT(TRIM('Base de Datos'!Y405),4)),VALUE(MID(TRIM('Base de Datos'!Y405),4,2)),VALUE(LEFT(TRIM('Base de Datos'!Y405),2))),IFERROR(DATEVALUE(TRIM('Base de Datos'!Y405)),"")))),"") | AK409: =IF(ISNUMBER('Base de Datos'!Z405),'Base de Datos'!Z405,IF(TRIM('Base de Datos'!Z405)="","",IFERROR(IF(IFERROR(FIND("@",SUBSTITUTE(TRIM('Base de Datos'!Z405),",","@",LEN(TRIM('Base de Datos'!Z405))-LEN(SUBSTITUTE(TRIM('Base de Datos'!Z405),",","")))),0)>IFERROR(FIND("@",SUBSTITUTE(TRIM('Base de Datos'!Z405),".","@",LEN(TRIM('Base de Datos'!Z405))-LEN(SUBSTITUTE(TRIM('Base de Datos'!Z405),".","")))),0),_xlfn.NUMBERVALUE(SUBSTITUTE(SUBSTITUTE(TRIM('Base de Datos'!Z405),".",""),",","."),".",","),_xlfn.NUMBERVALUE(SUBSTITUTE(TRIM('Base de Datos'!Z405),",",""),".",",")),"")))
A410: =ROWS(A$13:A410) -> 398 | B410: =IF(B409="","",IFERROR(SMALL($AH$10:$AH$409,COUNTIF($AH$10:$AH$409,"<="&B409)+1),"")) | C410: =IF(B410="","",INDEX($AI$10:$AI$409,MATCH(B410,$AH$10:$AH$409,0))) | D410: =IF(B410="","",IFERROR(INDEX($AK$10:$AK$409,MATCH(B410,$AJ$10:$AJ$409,0)),"")) | E410: =IF(AND(ISNUMBER(C410),ISNUMBER(C409)),C410/C409-1,"") | F410: =IF(AND(ISNUMBER(D410),ISNUMBER(D409)),D410/D409-1,"") | G410: =IF(AND(ISNUMBER(E410),ISNUMBER(F410)),1,"") | H410: =IF(G410=1,COUNT(G410:G$412),"") | I410: =IF(G410=1,IF(H410<='Beta Regresión'!$B$5,1,""),"") | J410: =IF(I410=1,E410,"") | K410: =IF(I410=1,F410,"") | L410: =IF(I410=1,COUNT(I$13:I410),"") | M410: =IFERROR(INDEX($J$13:$J$412,MATCH(A410,$L$13:$L$412,0)),"") | N410: =IFERROR(INDEX($K$13:$K$412,MATCH(A410,$L$13:$L$412,0)),"") | O410: =IF(I410=1,E410,NA()) -> #N/A | P410: =IF(I410=1,F410,NA()) -> #N/A | R410: =ROWS(R$13:R410) -> 398 | S410: =IF(S409="","",IFERROR(SMALL($AD$10:$AD$509,COUNTIF($AD$10:$AD$509,"<="&S409)+1),"")) | T410: =IF(S410="","",INDEX($AE$10:$AE$509,MATCH(S410,$AD$10:$AD$509,0))) | U410: =IF(S410="","",IFERROR(INDEX($AG$10:$AG$509,MATCH(S410,$AF$10:$AF$509,0)),"")) | V410: =IF(AND(ISNUMBER(T410),ISNUMBER(T409)),T410/T409-1,"") | W410: =IF(AND(ISNUMBER(U410),ISNUMBER(U409)),U410/U409-1,"") | X410: =IF(AND(ISNUMBER(V410),ISNUMBER(W410)),1,"") | Y410: =IF(X410=1,V410,"") | Z410: =IF(X410=1,W410,"") | AA410: =IF(X410=1,V410,NA()) -> #N/A | AB410: =IF(X410=1,W410,NA()) -> #N/A | AD410: =IF(ISNUMBER(AE410),IF(ISNUMBER('Base de Datos'!A406),IF('Base de Datos'!A406>20000,DATE(YEAR('Base de Datos'!A406),DAY('Base de Datos'!A406),MONTH('Base de Datos'!A406)),""),IF(TRIM('Base de Datos'!A406)="","",IFERROR(DATE(VALUE(RIGHT(TRIM('Base de Datos'!A406),4)),VALUE(LEFT(TRIM('Base de Datos'!A406),2)),VALUE(MID(TRIM('Base de Datos'!A406),4,2))),""))),"") | AE410: =IF(ISNUMBER('Base de Datos'!B406),'Base de Datos'!B406,IF(TRIM('Base de Datos'!B406)="","",IFERROR(IF(IFERROR(FIND("@",SUBSTITUTE(TRIM('Base de Datos'!B406),",","@",LEN(TRIM('Base de Datos'!B406))-LEN(SUBSTITUTE(TRIM('Base de Datos'!B406),",","")))),0)>IFERROR(FIND("@",SUBSTITUTE(TRIM('Base de Datos'!B406),".","@",LEN(TRIM('Base de Datos'!B406))-LEN(SUBSTITUTE(TRIM('Base de Datos'!B406),".","")))),0),_xlfn.NUMBERVALUE(SUBSTITUTE(SUBSTITUTE(TRIM('Base de Datos'!B406),".",""),",","."),".",","),_xlfn.NUMBERVALUE(SUBSTITUTE(TRIM('Base de Datos'!B406),",",""),".",",")),""))) | AF410: =IF(ISNUMBER(AG410),IF(ISNUMBER('Base de Datos'!I406),IF('Base de Datos'!I406>20000,INT('Base de Datos'!I406),""),IF(TRIM('Base de Datos'!I406)="","",IFERROR(DATE(VALUE(RIGHT(TRIM('Base de Datos'!I406),4)),VALUE(MID(TRIM('Base de Datos'!I406),4,2)),VALUE(LEFT(TRIM('Base de Datos'!I406),2))),IFERROR(DATEVALUE(TRIM('Base de Datos'!I406)),"")))),"") | AG410: =IF(ISNUMBER('Base de Datos'!J406),'Base de Datos'!J406,IF(TRIM('Base de Datos'!J406)="","",IFERROR(IF(IFERROR(FIND("@",SUBSTITUTE(TRIM('Base de Datos'!J406),",","@",LEN(TRIM('Base de Datos'!J406))-LEN(SUBSTITUTE(TRIM('Base de Datos'!J406),",","")))),0)>IFERROR(FIND("@",SUBSTITUTE(TRIM('Base de Datos'!J406),".","@",LEN(TRIM('Base de Datos'!J406))-LEN(SUBSTITUTE(TRIM('Base de Datos'!J406),".","")))),0),_xlfn.NUMBERVALUE(SUBSTITUTE(SUBSTITUTE(TRIM('Base de Datos'!J406),".",""),",","."),".",","),_xlfn.NUMBERVALUE(SUBSTITUTE(TRIM('Base de Datos'!J406),",",""),".",",")),"")))
A411: =ROWS(A$13:A411) -> 399 | B411: =IF(B410="","",IFERROR(SMALL($AH$10:$AH$409,COUNTIF($AH$10:$AH$409,"<="&B410)+1),"")) | C411: =IF(B411="","",INDEX($AI$10:$AI$409,MATCH(B411,$AH$10:$AH$409,0))) | D411: =IF(B411="","",IFERROR(INDEX($AK$10:$AK$409,MATCH(B411,$AJ$10:$AJ$409,0)),"")) | E411: =IF(AND(ISNUMBER(C411),ISNUMBER(C410)),C411/C410-1,"") | F411: =IF(AND(ISNUMBER(D411),ISNUMBER(D410)),D411/D410-1,"") | G411: =IF(AND(ISNUMBER(E411),ISNUMBER(F411)),1,"") | H411: =IF(G411=1,COUNT(G411:G$412),"") | I411: =IF(G411=1,IF(H411<='Beta Regresión'!$B$5,1,""),"") | J411: =IF(I411=1,E411,"") | K411: =IF(I411=1,F411,"") | L411: =IF(I411=1,COUNT(I$13:I411),"") | M411: =IFERROR(INDEX($J$13:$J$412,MATCH(A411,$L$13:$L$412,0)),"") | N411: =IFERROR(INDEX($K$13:$K$412,MATCH(A411,$L$13:$L$412,0)),"") | O411: =IF(I411=1,E411,NA()) -> #N/A | P411: =IF(I411=1,F411,NA()) -> #N/A | R411: =ROWS(R$13:R411) -> 399 | S411: =IF(S410="","",IFERROR(SMALL($AD$10:$AD$509,COUNTIF($AD$10:$AD$509,"<="&S410)+1),"")) | T411: =IF(S411="","",INDEX($AE$10:$AE$509,MATCH(S411,$AD$10:$AD$509,0))) | U411: =IF(S411="","",IFERROR(INDEX($AG$10:$AG$509,MATCH(S411,$AF$10:$AF$509,0)),"")) | V411: =IF(AND(ISNUMBER(T411),ISNUMBER(T410)),T411/T410-1,"") | W411: =IF(AND(ISNUMBER(U411),ISNUMBER(U410)),U411/U410-1,"") | X411: =IF(AND(ISNUMBER(V411),ISNUMBER(W411)),1,"") | Y411: =IF(X411=1,V411,"") | Z411: =IF(X411=1,W411,"") | AA411: =IF(X411=1,V411,NA()) -> #N/A | AB411: =IF(X411=1,W411,NA()) -> #N/A | AD411: =IF(ISNUMBER(AE411),IF(ISNUMBER('Base de Datos'!A407),IF('Base de Datos'!A407>20000,DATE(YEAR('Base de Datos'!A407),DAY('Base de Datos'!A407),MONTH('Base de Datos'!A407)),""),IF(TRIM('Base de Datos'!A407)="","",IFERROR(DATE(VALUE(RIGHT(TRIM('Base de Datos'!A407),4)),VALUE(LEFT(TRIM('Base de Datos'!A407),2)),VALUE(MID(TRIM('Base de Datos'!A407),4,2))),""))),"") | AE411: =IF(ISNUMBER('Base de Datos'!B407),'Base de Datos'!B407,IF(TRIM('Base de Datos'!B407)="","",IFERROR(IF(IFERROR(FIND("@",SUBSTITUTE(TRIM('Base de Datos'!B407),",","@",LEN(TRIM('Base de Datos'!B407))-LEN(SUBSTITUTE(TRIM('Base de Datos'!B407),",","")))),0)>IFERROR(FIND("@",SUBSTITUTE(TRIM('Base de Datos'!B407),".","@",LEN(TRIM('Base de Datos'!B407))-LEN(SUBSTITUTE(TRIM('Base de Datos'!B407),".","")))),0),_xlfn.NUMBERVALUE(SUBSTITUTE(SUBSTITUTE(TRIM('Base de Datos'!B407),".",""),",","."),".",","),_xlfn.NUMBERVALUE(SUBSTITUTE(TRIM('Base de Datos'!B407),",",""),".",",")),""))) | AF411: =IF(ISNUMBER(AG411),IF(ISNUMBER('Base de Datos'!I407),IF('Base de Datos'!I407>20000,INT('Base de Datos'!I407),""),IF(TRIM('Base de Datos'!I407)="","",IFERROR(DATE(VALUE(RIGHT(TRIM('Base de Datos'!I407),4)),VALUE(MID(TRIM('Base de Datos'!I407),4,2)),VALUE(LEFT(TRIM('Base de Datos'!I407),2))),IFERROR(DATEVALUE(TRIM('Base de Datos'!I407)),"")))),"") | AG411: =IF(ISNUMBER('Base de Datos'!J407),'Base de Datos'!J407,IF(TRIM('Base de Datos'!J407)="","",IFERROR(IF(IFERROR(FIND("@",SUBSTITUTE(TRIM('Base de Datos'!J407),",","@",LEN(TRIM('Base de Datos'!J407))-LEN(SUBSTITUTE(TRIM('Base de Datos'!J407),",","")))),0)>IFERROR(FIND("@",SUBSTITUTE(TRIM('Base de Datos'!J407),".","@",LEN(TRIM('Base de Datos'!J407))-LEN(SUBSTITUTE(TRIM('Base de Datos'!J407),".","")))),0),_xlfn.NUMBERVALUE(SUBSTITUTE(SUBSTITUTE(TRIM('Base de Datos'!J407),".",""),",","."),".",","),_xlfn.NUMBERVALUE(SUBSTITUTE(TRIM('Base de Datos'!J407),",",""),".",",")),"")))
A412: =ROWS(A$13:A412) -> 400 | B412: =IF(B411="","",IFERROR(SMALL($AH$10:$AH$409,COUNTIF($AH$10:$AH$409,"<="&B411)+1),"")) | C412: =IF(B412="","",INDEX($AI$10:$AI$409,MATCH(B412,$AH$10:$AH$409,0))) | D412: =IF(B412="","",IFERROR(INDEX($AK$10:$AK$409,MATCH(B412,$AJ$10:$AJ$409,0)),"")) | E412: =IF(AND(ISNUMBER(C412),ISNUMBER(C411)),C412/C411-1,"") | F412: =IF(AND(ISNUMBER(D412),ISNUMBER(D411)),D412/D411-1,"") | G412: =IF(AND(ISNUMBER(E412),ISNUMBER(F412)),1,"") | H412: =IF(G412=1,COUNT(G412:G$412),"") | I412: =IF(G412=1,IF(H412<='Beta Regresión'!$B$5,1,""),"") | J412: =IF(I412=1,E412,"") | K412: =IF(I412=1,F412,"") | L412: =IF(I412=1,COUNT(I$13:I412),"") | M412: =IFERROR(INDEX($J$13:$J$412,MATCH(A412,$L$13:$L$412,0)),"") | N412: =IFERROR(INDEX($K$13:$K$412,MATCH(A412,$L$13:$L$412,0)),"") | O412: =IF(I412=1,E412,NA()) -> #N/A | P412: =IF(I412=1,F412,NA()) -> #N/A | R412: =ROWS(R$13:R412) -> 400 | S412: =IF(S411="","",IFERROR(SMALL($AD$10:$AD$509,COUNTIF($AD$10:$AD$509,"<="&S411)+1),"")) | T412: =IF(S412="","",INDEX($AE$10:$AE$509,MATCH(S412,$AD$10:$AD$509,0))) | U412: =IF(S412="","",IFERROR(INDEX($AG$10:$AG$509,MATCH(S412,$AF$10:$AF$509,0)),"")) | V412: =IF(AND(ISNUMBER(T412),ISNUMBER(T411)),T412/T411-1,"") | W412: =IF(AND(ISNUMBER(U412),ISNUMBER(U411)),U412/U411-1,"") | X412: =IF(AND(ISNUMBER(V412),ISNUMBER(W412)),1,"") | Y412: =IF(X412=1,V412,"") | Z412: =IF(X412=1,W412,"") | AA412: =IF(X412=1,V412,NA()) -> #N/A | AB412: =IF(X412=1,W412,NA()) -> #N/A | AD412: =IF(ISNUMBER(AE412),IF(ISNUMBER('Base de Datos'!A408),IF('Base de Datos'!A408>20000,DATE(YEAR('Base de Datos'!A408),DAY('Base de Datos'!A408),MONTH('Base de Datos'!A408)),""),IF(TRIM('Base de Datos'!A408)="","",IFERROR(DATE(VALUE(RIGHT(TRIM('Base de Datos'!A408),4)),VALUE(LEFT(TRIM('Base de Datos'!A408),2)),VALUE(MID(TRIM('Base de Datos'!A408),4,2))),""))),"") | AE412: =IF(ISNUMBER('Base de Datos'!B408),'Base de Datos'!B408,IF(TRIM('Base de Datos'!B408)="","",IFERROR(IF(IFERROR(FIND("@",SUBSTITUTE(TRIM('Base de Datos'!B408),",","@",LEN(TRIM('Base de Datos'!B408))-LEN(SUBSTITUTE(TRIM('Base de Datos'!B408),",","")))),0)>IFERROR(FIND("@",SUBSTITUTE(TRIM('Base de Datos'!B408),".","@",LEN(TRIM('Base de Datos'!B408))-LEN(SUBSTITUTE(TRIM('Base de Datos'!B408),".","")))),0),_xlfn.NUMBERVALUE(SUBSTITUTE(SUBSTITUTE(TRIM('Base de Datos'!B408),".",""),",","."),".",","),_xlfn.NUMBERVALUE(SUBSTITUTE(TRIM('Base de Datos'!B408),",",""),".",",")),""))) | AF412: =IF(ISNUMBER(AG412),IF(ISNUMBER('Base de Datos'!I408),IF('Base de Datos'!I408>20000,INT('Base de Datos'!I408),""),IF(TRIM('Base de Datos'!I408)="","",IFERROR(DATE(VALUE(RIGHT(TRIM('Base de Datos'!I408),4)),VALUE(MID(TRIM('Base de Datos'!I408),4,2)),VALUE(LEFT(TRIM('Base de Datos'!I408),2))),IFERROR(DATEVALUE(TRIM('Base de Datos'!I408)),"")))),"") | AG412: =IF(ISNUMBER('Base de Datos'!J408),'Base de Datos'!J408,IF(TRIM('Base de Datos'!J408)="","",IFERROR(IF(IFERROR(FIND("@",SUBSTITUTE(TRIM('Base de Datos'!J408),",","@",LEN(TRIM('Base de Datos'!J408))-LEN(SUBSTITUTE(TRIM('Base de Datos'!J408),",","")))),0)>IFERROR(FIND("@",SUBSTITUTE(TRIM('Base de Datos'!J408),".","@",LEN(TRIM('Base de Datos'!J408))-LEN(SUBSTITUTE(TRIM('Base de Datos'!J408),".","")))),0),_xlfn.NUMBERVALUE(SUBSTITUTE(SUBSTITUTE(TRIM('Base de Datos'!J408),".",""),",","."),".",","),_xlfn.NUMBERVALUE(SUBSTITUTE(TRIM('Base de Datos'!J408),",",""),".",",")),"")))
R413: =ROWS(R$13:R413) -> 401 | S413: =IF(S412="","",IFERROR(SMALL($AD$10:$AD$509,COUNTIF($AD$10:$AD$509,"<="&S412)+1),"")) | T413: =IF(S413="","",INDEX($AE$10:$AE$509,MATCH(S413,$AD$10:$AD$509,0))) | U413: =IF(S413="","",IFERROR(INDEX($AG$10:$AG$509,MATCH(S413,$AF$10:$AF$509,0)),"")) | V413: =IF(AND(ISNUMBER(T413),ISNUMBER(T412)),T413/T412-1,"") | W413: =IF(AND(ISNUMBER(U413),ISNUMBER(U412)),U413/U412-1,"") | X413: =IF(AND(ISNUMBER(V413),ISNUMBER(W413)),1,"") | Y413: =IF(X413=1,V413,"") | Z413: =IF(X413=1,W413,"") | AA413: =IF(X413=1,V413,NA()) -> #N/A | AB413: =IF(X413=1,W413,NA()) -> #N/A | AD413: =IF(ISNUMBER(AE413),IF(ISNUMBER('Base de Datos'!A409),IF('Base de Datos'!A409>20000,DATE(YEAR('Base de Datos'!A409),DAY('Base de Datos'!A409),MONTH('Base de Datos'!A409)),""),IF(TRIM('Base de Datos'!A409)="","",IFERROR(DATE(VALUE(RIGHT(TRIM('Base de Datos'!A409),4)),VALUE(LEFT(TRIM('Base de Datos'!A409),2)),VALUE(MID(TRIM('Base de Datos'!A409),4,2))),""))),"") | AE413: =IF(ISNUMBER('Base de Datos'!B409),'Base de Datos'!B409,IF(TRIM('Base de Datos'!B409)="","",IFERROR(IF(IFERROR(FIND("@",SUBSTITUTE(TRIM('Base de Datos'!B409),",","@",LEN(TRIM('Base de Datos'!B409))-LEN(SUBSTITUTE(TRIM('Base de Datos'!B409),",","")))),0)>IFERROR(FIND("@",SUBSTITUTE(TRIM('Base de Datos'!B409),".","@",LEN(TRIM('Base de Datos'!B409))-LEN(SUBSTITUTE(TRIM('Base de Datos'!B409),".","")))),0),_xlfn.NUMBERVALUE(SUBSTITUTE(SUBSTITUTE(TRIM('Base de Datos'!B409),".",""),",","."),".",","),_xlfn.NUMBERVALUE(SUBSTITUTE(TRIM('Base de Datos'!B409),",",""),".",",")),""))) | AF413: =IF(ISNUMBER(AG413),IF(ISNUMBER('Base de Datos'!I409),IF('Base de Datos'!I409>20000,INT('Base de Datos'!I409),""),IF(TRIM('Base de Datos'!I409)="","",IFERROR(DATE(VALUE(RIGHT(TRIM('Base de Datos'!I409),4)),VALUE(MID(TRIM('Base de Datos'!I409),4,2)),VALUE(LEFT(TRIM('Base de Datos'!I409),2))),IFERROR(DATEVALUE(TRIM('Base de Datos'!I409)),"")))),"") | AG413: =IF(ISNUMBER('Base de Datos'!J409),'Base de Datos'!J409,IF(TRIM('Base de Datos'!J409)="","",IFERROR(IF(IFERROR(FIND("@",SUBSTITUTE(TRIM('Base de Datos'!J409),",","@",LEN(TRIM('Base de Datos'!J409))-LEN(SUBSTITUTE(TRIM('Base de Datos'!J409),",","")))),0)>IFERROR(FIND("@",SUBSTITUTE(TRIM('Base de Datos'!J409),".","@",LEN(TRIM('Base de Datos'!J409))-LEN(SUBSTITUTE(TRIM('Base de Datos'!J409),".","")))),0),_xlfn.NUMBERVALUE(SUBSTITUTE(SUBSTITUTE(TRIM('Base de Datos'!J409),".",""),",","."),".",","),_xlfn.NUMBERVALUE(SUBSTITUTE(TRIM('Base de Datos'!J409),",",""),".",",")),"")))
R414: =ROWS(R$13:R414) -> 402 | S414: =IF(S413="","",IFERROR(SMALL($AD$10:$AD$509,COUNTIF($AD$10:$AD$509,"<="&S413)+1),"")) | T414: =IF(S414="","",INDEX($AE$10:$AE$509,MATCH(S414,$AD$10:$AD$509,0))) | U414: =IF(S414="","",IFERROR(INDEX($AG$10:$AG$509,MATCH(S414,$AF$10:$AF$509,0)),"")) | V414: =IF(AND(ISNUMBER(T414),ISNUMBER(T413)),T414/T413-1,"") | W414: =IF(AND(ISNUMBER(U414),ISNUMBER(U413)),U414/U413-1,"") | X414: =IF(AND(ISNUMBER(V414),ISNUMBER(W414)),1,"") | Y414: =IF(X414=1,V414,"") | Z414: =IF(X414=1,W414,"") | AA414: =IF(X414=1,V414,NA()) -> #N/A | AB414: =IF(X414=1,W414,NA()) -> #N/A | AD414: =IF(ISNUMBER(AE414),IF(ISNUMBER('Base de Datos'!A410),IF('Base de Datos'!A410>20000,DATE(YEAR('Base de Datos'!A410),DAY('Base de Datos'!A410),MONTH('Base de Datos'!A410)),""),IF(TRIM('Base de Datos'!A410)="","",IFERROR(DATE(VALUE(RIGHT(TRIM('Base de Datos'!A410),4)),VALUE(LEFT(TRIM('Base de Datos'!A410),2)),VALUE(MID(TRIM('Base de Datos'!A410),4,2))),""))),"") | AE414: =IF(ISNUMBER('Base de Datos'!B410),'Base de Datos'!B410,IF(TRIM('Base de Datos'!B410)="","",IFERROR(IF(IFERROR(FIND("@",SUBSTITUTE(TRIM('Base de Datos'!B410),",","@",LEN(TRIM('Base de Datos'!B410))-LEN(SUBSTITUTE(TRIM('Base de Datos'!B410),",","")))),0)>IFERROR(FIND("@",SUBSTITUTE(TRIM('Base de Datos'!B410),".","@",LEN(TRIM('Base de Datos'!B410))-LEN(SUBSTITUTE(TRIM('Base de Datos'!B410),".","")))),0),_xlfn.NUMBERVALUE(SUBSTITUTE(SUBSTITUTE(TRIM('Base de Datos'!B410),".",""),",","."),".",","),_xlfn.NUMBERVALUE(SUBSTITUTE(TRIM('Base de Datos'!B410),",",""),".",",")),""))) | AF414: =IF(ISNUMBER(AG414),IF(ISNUMBER('Base de Datos'!I410),IF('Base de Datos'!I410>20000,INT('Base de Datos'!I410),""),IF(TRIM('Base de Datos'!I410)="","",IFERROR(DATE(VALUE(RIGHT(TRIM('Base de Datos'!I410),4)),VALUE(MID(TRIM('Base de Datos'!I410),4,2)),VALUE(LEFT(TRIM('Base de Datos'!I410),2))),IFERROR(DATEVALUE(TRIM('Base de Datos'!I410)),"")))),"") | AG414: =IF(ISNUMBER('Base de Datos'!J410),'Base de Datos'!J410,IF(TRIM('Base de Datos'!J410)="","",IFERROR(IF(IFERROR(FIND("@",SUBSTITUTE(TRIM('Base de Datos'!J410),",","@",LEN(TRIM('Base de Datos'!J410))-LEN(SUBSTITUTE(TRIM('Base de Datos'!J410),",","")))),0)>IFERROR(FIND("@",SUBSTITUTE(TRIM('Base de Datos'!J410),".","@",LEN(TRIM('Base de Datos'!J410))-LEN(SUBSTITUTE(TRIM('Base de Datos'!J410),".","")))),0),_xlfn.NUMBERVALUE(SUBSTITUTE(SUBSTITUTE(TRIM('Base de Datos'!J410),".",""),",","."),".",","),_xlfn.NUMBERVALUE(SUBSTITUTE(TRIM('Base de Datos'!J410),",",""),".",",")),"")))
R415: =ROWS(R$13:R415) -> 403 | S415: =IF(S414="","",IFERROR(SMALL($AD$10:$AD$509,COUNTIF($AD$10:$AD$509,"<="&S414)+1),"")) | T415: =IF(S415="","",INDEX($AE$10:$AE$509,MATCH(S415,$AD$10:$AD$509,0))) | U415: =IF(S415="","",IFERROR(INDEX($AG$10:$AG$509,MATCH(S415,$AF$10:$AF$509,0)),"")) | V415: =IF(AND(ISNUMBER(T415),ISNUMBER(T414)),T415/T414-1,"") | W415: =IF(AND(ISNUMBER(U415),ISNUMBER(U414)),U415/U414-1,"") | X415: =IF(AND(ISNUMBER(V415),ISNUMBER(W415)),1,"") | Y415: =IF(X415=1,V415,"") | Z415: =IF(X415=1,W415,"") | AA415: =IF(X415=1,V415,NA()) -> #N/A | AB415: =IF(X415=1,W415,NA()) -> #N/A | AD415: =IF(ISNUMBER(AE415),IF(ISNUMBER('Base de Datos'!A411),IF('Base de Datos'!A411>20000,DATE(YEAR('Base de Datos'!A411),DAY('Base de Datos'!A411),MONTH('Base de Datos'!A411)),""),IF(TRIM('Base de Datos'!A411)="","",IFERROR(DATE(VALUE(RIGHT(TRIM('Base de Datos'!A411),4)),VALUE(LEFT(TRIM('Base de Datos'!A411),2)),VALUE(MID(TRIM('Base de Datos'!A411),4,2))),""))),"") | AE415: =IF(ISNUMBER('Base de Datos'!B411),'Base de Datos'!B411,IF(TRIM('Base de Datos'!B411)="","",IFERROR(IF(IFERROR(FIND("@",SUBSTITUTE(TRIM('Base de Datos'!B411),",","@",LEN(TRIM('Base de Datos'!B411))-LEN(SUBSTITUTE(TRIM('Base de Datos'!B411),",","")))),0)>IFERROR(FIND("@",SUBSTITUTE(TRIM('Base de Datos'!B411),".","@",LEN(TRIM('Base de Datos'!B411))-LEN(SUBSTITUTE(TRIM('Base de Datos'!B411),".","")))),0),_xlfn.NUMBERVALUE(SUBSTITUTE(SUBSTITUTE(TRIM('Base de Datos'!B411),".",""),",","."),".",","),_xlfn.NUMBERVALUE(SUBSTITUTE(TRIM('Base de Datos'!B411),",",""),".",",")),""))) | AF415: =IF(ISNUMBER(AG415),IF(ISNUMBER('Base de Datos'!I411),IF('Base de Datos'!I411>20000,INT('Base de Datos'!I411),""),IF(TRIM('Base de Datos'!I411)="","",IFERROR(DATE(VALUE(RIGHT(TRIM('Base de Datos'!I411),4)),VALUE(MID(TRIM('Base de Datos'!I411),4,2)),VALUE(LEFT(TRIM('Base de Datos'!I411),2))),IFERROR(DATEVALUE(TRIM('Base de Datos'!I411)),"")))),"") | AG415: =IF(ISNUMBER('Base de Datos'!J411),'Base de Datos'!J411,IF(TRIM('Base de Datos'!J411)="","",IFERROR(IF(IFERROR(FIND("@",SUBSTITUTE(TRIM('Base de Datos'!J411),",","@",LEN(TRIM('Base de Datos'!J411))-LEN(SUBSTITUTE(TRIM('Base de Datos'!J411),",","")))),0)>IFERROR(FIND("@",SUBSTITUTE(TRIM('Base de Datos'!J411),".","@",LEN(TRIM('Base de Datos'!J411))-LEN(SUBSTITUTE(TRIM('Base de Datos'!J411),".","")))),0),_xlfn.NUMBERVALUE(SUBSTITUTE(SUBSTITUTE(TRIM('Base de Datos'!J411),".",""),",","."),".",","),_xlfn.NUMBERVALUE(SUBSTITUTE(TRIM('Base de Datos'!J411),",",""),".",",")),"")))
R416: =ROWS(R$13:R416) -> 404 | S416: =IF(S415="","",IFERROR(SMALL($AD$10:$AD$509,COUNTIF($AD$10:$AD$509,"<="&S415)+1),"")) | T416: =IF(S416="","",INDEX($AE$10:$AE$509,MATCH(S416,$AD$10:$AD$509,0))) | U416: =IF(S416="","",IFERROR(INDEX($AG$10:$AG$509,MATCH(S416,$AF$10:$AF$509,0)),"")) | V416: =IF(AND(ISNUMBER(T416),ISNUMBER(T415)),T416/T415-1,"") | W416: =IF(AND(ISNUMBER(U416),ISNUMBER(U415)),U416/U415-1,"") | X416: =IF(AND(ISNUMBER(V416),ISNUMBER(W416)),1,"") | Y416: =IF(X416=1,V416,"") | Z416: =IF(X416=1,W416,"") | AA416: =IF(X416=1,V416,NA()) -> #N/A | AB416: =IF(X416=1,W416,NA()) -> #N/A | AD416: =IF(ISNUMBER(AE416),IF(ISNUMBER('Base de Datos'!A412),IF('Base de Datos'!A412>20000,DATE(YEAR('Base de Datos'!A412),DAY('Base de Datos'!A412),MONTH('Base de Datos'!A412)),""),IF(TRIM('Base de Datos'!A412)="","",IFERROR(DATE(VALUE(RIGHT(TRIM('Base de Datos'!A412),4)),VALUE(LEFT(TRIM('Base de Datos'!A412),2)),VALUE(MID(TRIM('Base de Datos'!A412),4,2))),""))),"") | AE416: =IF(ISNUMBER('Base de Datos'!B412),'Base de Datos'!B412,IF(TRIM('Base de Datos'!B412)="","",IFERROR(IF(IFERROR(FIND("@",SUBSTITUTE(TRIM('Base de Datos'!B412),",","@",LEN(TRIM('Base de Datos'!B412))-LEN(SUBSTITUTE(TRIM('Base de Datos'!B412),",","")))),0)>IFERROR(FIND("@",SUBSTITUTE(TRIM('Base de Datos'!B412),".","@",LEN(TRIM('Base de Datos'!B412))-LEN(SUBSTITUTE(TRIM('Base de Datos'!B412),".","")))),0),_xlfn.NUMBERVALUE(SUBSTITUTE(SUBSTITUTE(TRIM('Base de Datos'!B412),".",""),",","."),".",","),_xlfn.NUMBERVALUE(SUBSTITUTE(TRIM('Base de Datos'!B412),",",""),".",",")),""))) | AF416: =IF(ISNUMBER(AG416),IF(ISNUMBER('Base de Datos'!I412),IF('Base de Datos'!I412>20000,INT('Base de Datos'!I412),""),IF(TRIM('Base de Datos'!I412)="","",IFERROR(DATE(VALUE(RIGHT(TRIM('Base de Datos'!I412),4)),VALUE(MID(TRIM('Base de Datos'!I412),4,2)),VALUE(LEFT(TRIM('Base de Datos'!I412),2))),IFERROR(DATEVALUE(TRIM('Base de Datos'!I412)),"")))),"") | AG416: =IF(ISNUMBER('Base de Datos'!J412),'Base de Datos'!J412,IF(TRIM('Base de Datos'!J412)="","",IFERROR(IF(IFERROR(FIND("@",SUBSTITUTE(TRIM('Base de Datos'!J412),",","@",LEN(TRIM('Base de Datos'!J412))-LEN(SUBSTITUTE(TRIM('Base de Datos'!J412),",","")))),0)>IFERROR(FIND("@",SUBSTITUTE(TRIM('Base de Datos'!J412),".","@",LEN(TRIM('Base de Datos'!J412))-LEN(SUBSTITUTE(TRIM('Base de Datos'!J412),".","")))),0),_xlfn.NUMBERVALUE(SUBSTITUTE(SUBSTITUTE(TRIM('Base de Datos'!J412),".",""),",","."),".",","),_xlfn.NUMBERVALUE(SUBSTITUTE(TRIM('Base de Datos'!J412),",",""),".",",")),"")))
R417: =ROWS(R$13:R417) -> 405 | S417: =IF(S416="","",IFERROR(SMALL($AD$10:$AD$509,COUNTIF($AD$10:$AD$509,"<="&S416)+1),"")) | T417: =IF(S417="","",INDEX($AE$10:$AE$509,MATCH(S417,$AD$10:$AD$509,0))) | U417: =IF(S417="","",IFERROR(INDEX($AG$10:$AG$509,MATCH(S417,$AF$10:$AF$509,0)),"")) | V417: =IF(AND(ISNUMBER(T417),ISNUMBER(T416)),T417/T416-1,"") | W417: =IF(AND(ISNUMBER(U417),ISNUMBER(U416)),U417/U416-1,"") | X417: =IF(AND(ISNUMBER(V417),ISNUMBER(W417)),1,"") | Y417: =IF(X417=1,V417,"") | Z417: =IF(X417=1,W417,"") | AA417: =IF(X417=1,V417,NA()) -> #N/A | AB417: =IF(X417=1,W417,NA()) -> #N/A | AD417: =IF(ISNUMBER(AE417),IF(ISNUMBER('Base de Datos'!A413),IF('Base de Datos'!A413>20000,DATE(YEAR('Base de Datos'!A413),DAY('Base de Datos'!A413),MONTH('Base de Datos'!A413)),""),IF(TRIM('Base de Datos'!A413)="","",IFERROR(DATE(VALUE(RIGHT(TRIM('Base de Datos'!A413),4)),VALUE(LEFT(TRIM('Base de Datos'!A413),2)),VALUE(MID(TRIM('Base de Datos'!A413),4,2))),""))),"") | AE417: =IF(ISNUMBER('Base de Datos'!B413),'Base de Datos'!B413,IF(TRIM('Base de Datos'!B413)="","",IFERROR(IF(IFERROR(FIND("@",SUBSTITUTE(TRIM('Base de Datos'!B413),",","@",LEN(TRIM('Base de Datos'!B413))-LEN(SUBSTITUTE(TRIM('Base de Datos'!B413),",","")))),0)>IFERROR(FIND("@",SUBSTITUTE(TRIM('Base de Datos'!B413),".","@",LEN(TRIM('Base de Datos'!B413))-LEN(SUBSTITUTE(TRIM('Base de Datos'!B413),".","")))),0),_xlfn.NUMBERVALUE(SUBSTITUTE(SUBSTITUTE(TRIM('Base de Datos'!B413),".",""),",","."),".",","),_xlfn.NUMBERVALUE(SUBSTITUTE(TRIM('Base de Datos'!B413),",",""),".",",")),""))) | AF417: =IF(ISNUMBER(AG417),IF(ISNUMBER('Base de Datos'!I413),IF('Base de Datos'!I413>20000,INT('Base de Datos'!I413),""),IF(TRIM('Base de Datos'!I413)="","",IFERROR(DATE(VALUE(RIGHT(TRIM('Base de Datos'!I413),4)),VALUE(MID(TRIM('Base de Datos'!I413),4,2)),VALUE(LEFT(TRIM('Base de Datos'!I413),2))),IFERROR(DATEVALUE(TRIM('Base de Datos'!I413)),"")))),"") | AG417: =IF(ISNUMBER('Base de Datos'!J413),'Base de Datos'!J413,IF(TRIM('Base de Datos'!J413)="","",IFERROR(IF(IFERROR(FIND("@",SUBSTITUTE(TRIM('Base de Datos'!J413),",","@",LEN(TRIM('Base de Datos'!J413))-LEN(SUBSTITUTE(TRIM('Base de Datos'!J413),",","")))),0)>IFERROR(FIND("@",SUBSTITUTE(TRIM('Base de Datos'!J413),".","@",LEN(TRIM('Base de Datos'!J413))-LEN(SUBSTITUTE(TRIM('Base de Datos'!J413),".","")))),0),_xlfn.NUMBERVALUE(SUBSTITUTE(SUBSTITUTE(TRIM('Base de Datos'!J413),".",""),",","."),".",","),_xlfn.NUMBERVALUE(SUBSTITUTE(TRIM('Base de Datos'!J413),",",""),".",",")),"")))
R418: =ROWS(R$13:R418) -> 406 | S418: =IF(S417="","",IFERROR(SMALL($AD$10:$AD$509,COUNTIF($AD$10:$AD$509,"<="&S417)+1),"")) | T418: =IF(S418="","",INDEX($AE$10:$AE$509,MATCH(S418,$AD$10:$AD$509,0))) | U418: =IF(S418="","",IFERROR(INDEX($AG$10:$AG$509,MATCH(S418,$AF$10:$AF$509,0)),"")) | V418: =IF(AND(ISNUMBER(T418),ISNUMBER(T417)),T418/T417-1,"") | W418: =IF(AND(ISNUMBER(U418),ISNUMBER(U417)),U418/U417-1,"") | X418: =IF(AND(ISNUMBER(V418),ISNUMBER(W418)),1,"") | Y418: =IF(X418=1,V418,"") | Z418: =IF(X418=1,W418,"") | AA418: =IF(X418=1,V418,NA()) -> #N/A | AB418: =IF(X418=1,W418,NA()) -> #N/A | AD418: =IF(ISNUMBER(AE418),IF(ISNUMBER('Base de Datos'!A414),IF('Base de Datos'!A414>20000,DATE(YEAR('Base de Datos'!A414),DAY('Base de Datos'!A414),MONTH('Base de Datos'!A414)),""),IF(TRIM('Base de Datos'!A414)="","",IFERROR(DATE(VALUE(RIGHT(TRIM('Base de Datos'!A414),4)),VALUE(LEFT(TRIM('Base de Datos'!A414),2)),VALUE(MID(TRIM('Base de Datos'!A414),4,2))),""))),"") | AE418: =IF(ISNUMBER('Base de Datos'!B414),'Base de Datos'!B414,IF(TRIM('Base de Datos'!B414)="","",IFERROR(IF(IFERROR(FIND("@",SUBSTITUTE(TRIM('Base de Datos'!B414),",","@",LEN(TRIM('Base de Datos'!B414))-LEN(SUBSTITUTE(TRIM('Base de Datos'!B414),",","")))),0)>IFERROR(FIND("@",SUBSTITUTE(TRIM('Base de Datos'!B414),".","@",LEN(TRIM('Base de Datos'!B414))-LEN(SUBSTITUTE(TRIM('Base de Datos'!B414),".","")))),0),_xlfn.NUMBERVALUE(SUBSTITUTE(SUBSTITUTE(TRIM('Base de Datos'!B414),".",""),",","."),".",","),_xlfn.NUMBERVALUE(SUBSTITUTE(TRIM('Base de Datos'!B414),",",""),".",",")),""))) | AF418: =IF(ISNUMBER(AG418),IF(ISNUMBER('Base de Datos'!I414),IF('Base de Datos'!I414>20000,INT('Base de Datos'!I414),""),IF(TRIM('Base de Datos'!I414)="","",IFERROR(DATE(VALUE(RIGHT(TRIM('Base de Datos'!I414),4)),VALUE(MID(TRIM('Base de Datos'!I414),4,2)),VALUE(LEFT(TRIM('Base de Datos'!I414),2))),IFERROR(DATEVALUE(TRIM('Base de Datos'!I414)),"")))),"") | AG418: =IF(ISNUMBER('Base de Datos'!J414),'Base de Datos'!J414,IF(TRIM('Base de Datos'!J414)="","",IFERROR(IF(IFERROR(FIND("@",SUBSTITUTE(TRIM('Base de Datos'!J414),",","@",LEN(TRIM('Base de Datos'!J414))-LEN(SUBSTITUTE(TRIM('Base de Datos'!J414),",","")))),0)>IFERROR(FIND("@",SUBSTITUTE(TRIM('Base de Datos'!J414),".","@",LEN(TRIM('Base de Datos'!J414))-LEN(SUBSTITUTE(TRIM('Base de Datos'!J414),".","")))),0),_xlfn.NUMBERVALUE(SUBSTITUTE(SUBSTITUTE(TRIM('Base de Datos'!J414),".",""),",","."),".",","),_xlfn.NUMBERVALUE(SUBSTITUTE(TRIM('Base de Datos'!J414),",",""),".",",")),"")))
R419: =ROWS(R$13:R419) -> 407 | S419: =IF(S418="","",IFERROR(SMALL($AD$10:$AD$509,COUNTIF($AD$10:$AD$509,"<="&S418)+1),"")) | T419: =IF(S419="","",INDEX($AE$10:$AE$509,MATCH(S419,$AD$10:$AD$509,0))) | U419: =IF(S419="","",IFERROR(INDEX($AG$10:$AG$509,MATCH(S419,$AF$10:$AF$509,0)),"")) | V419: =IF(AND(ISNUMBER(T419),ISNUMBER(T418)),T419/T418-1,"") | W419: =IF(AND(ISNUMBER(U419),ISNUMBER(U418)),U419/U418-1,"") | X419: =IF(AND(ISNUMBER(V419),ISNUMBER(W419)),1,"") | Y419: =IF(X419=1,V419,"") | Z419: =IF(X419=1,W419,"") | AA419: =IF(X419=1,V419,NA()) -> #N/A | AB419: =IF(X419=1,W419,NA()) -> #N/A | AD419: =IF(ISNUMBER(AE419),IF(ISNUMBER('Base de Datos'!A415),IF('Base de Datos'!A415>20000,DATE(YEAR('Base de Datos'!A415),DAY('Base de Datos'!A415),MONTH('Base de Datos'!A415)),""),IF(TRIM('Base de Datos'!A415)="","",IFERROR(DATE(VALUE(RIGHT(TRIM('Base de Datos'!A415),4)),VALUE(LEFT(TRIM('Base de Datos'!A415),2)),VALUE(MID(TRIM('Base de Datos'!A415),4,2))),""))),"") | AE419: =IF(ISNUMBER('Base de Datos'!B415),'Base de Datos'!B415,IF(TRIM('Base de Datos'!B415)="","",IFERROR(IF(IFERROR(FIND("@",SUBSTITUTE(TRIM('Base de Datos'!B415),",","@",LEN(TRIM('Base de Datos'!B415))-LEN(SUBSTITUTE(TRIM('Base de Datos'!B415),",","")))),0)>IFERROR(FIND("@",SUBSTITUTE(TRIM('Base de Datos'!B415),".","@",LEN(TRIM('Base de Datos'!B415))-LEN(SUBSTITUTE(TRIM('Base de Datos'!B415),".","")))),0),_xlfn.NUMBERVALUE(SUBSTITUTE(SUBSTITUTE(TRIM('Base de Datos'!B415),".",""),",","."),".",","),_xlfn.NUMBERVALUE(SUBSTITUTE(TRIM('Base de Datos'!B415),",",""),".",",")),""))) | AF419: =IF(ISNUMBER(AG419),IF(ISNUMBER('Base de Datos'!I415),IF('Base de Datos'!I415>20000,INT('Base de Datos'!I415),""),IF(TRIM('Base de Datos'!I415)="","",IFERROR(DATE(VALUE(RIGHT(TRIM('Base de Datos'!I415),4)),VALUE(MID(TRIM('Base de Datos'!I415),4,2)),VALUE(LEFT(TRIM('Base de Datos'!I415),2))),IFERROR(DATEVALUE(TRIM('Base de Datos'!I415)),"")))),"") | AG419: =IF(ISNUMBER('Base de Datos'!J415),'Base de Datos'!J415,IF(TRIM('Base de Datos'!J415)="","",IFERROR(IF(IFERROR(FIND("@",SUBSTITUTE(TRIM('Base de Datos'!J415),",","@",LEN(TRIM('Base de Datos'!J415))-LEN(SUBSTITUTE(TRIM('Base de Datos'!J415),",","")))),0)>IFERROR(FIND("@",SUBSTITUTE(TRIM('Base de Datos'!J415),".","@",LEN(TRIM('Base de Datos'!J415))-LEN(SUBSTITUTE(TRIM('Base de Datos'!J415),".","")))),0),_xlfn.NUMBERVALUE(SUBSTITUTE(SUBSTITUTE(TRIM('Base de Datos'!J415),".",""),",","."),".",","),_xlfn.NUMBERVALUE(SUBSTITUTE(TRIM('Base de Datos'!J415),",",""),".",",")),"")))
R420: =ROWS(R$13:R420) -> 408 | S420: =IF(S419="","",IFERROR(SMALL($AD$10:$AD$509,COUNTIF($AD$10:$AD$509,"<="&S419)+1),"")) | T420: =IF(S420="","",INDEX($AE$10:$AE$509,MATCH(S420,$AD$10:$AD$509,0))) | U420: =IF(S420="","",IFERROR(INDEX($AG$10:$AG$509,MATCH(S420,$AF$10:$AF$509,0)),"")) | V420: =IF(AND(ISNUMBER(T420),ISNUMBER(T419)),T420/T419-1,"") | W420: =IF(AND(ISNUMBER(U420),ISNUMBER(U419)),U420/U419-1,"") | X420: =IF(AND(ISNUMBER(V420),ISNUMBER(W420)),1,"") | Y420: =IF(X420=1,V420,"") | Z420: =IF(X420=1,W420,"") | AA420: =IF(X420=1,V420,NA()) -> #N/A | AB420: =IF(X420=1,W420,NA()) -> #N/A | AD420: =IF(ISNUMBER(AE420),IF(ISNUMBER('Base de Datos'!A416),IF('Base de Datos'!A416>20000,DATE(YEAR('Base de Datos'!A416),DAY('Base de Datos'!A416),MONTH('Base de Datos'!A416)),""),IF(TRIM('Base de Datos'!A416)="","",IFERROR(DATE(VALUE(RIGHT(TRIM('Base de Datos'!A416),4)),VALUE(LEFT(TRIM('Base de Datos'!A416),2)),VALUE(MID(TRIM('Base de Datos'!A416),4,2))),""))),"") | AE420: =IF(ISNUMBER('Base de Datos'!B416),'Base de Datos'!B416,IF(TRIM('Base de Datos'!B416)="","",IFERROR(IF(IFERROR(FIND("@",SUBSTITUTE(TRIM('Base de Datos'!B416),",","@",LEN(TRIM('Base de Datos'!B416))-LEN(SUBSTITUTE(TRIM('Base de Datos'!B416),",","")))),0)>IFERROR(FIND("@",SUBSTITUTE(TRIM('Base de Datos'!B416),".","@",LEN(TRIM('Base de Datos'!B416))-LEN(SUBSTITUTE(TRIM('Base de Datos'!B416),".","")))),0),_xlfn.NUMBERVALUE(SUBSTITUTE(SUBSTITUTE(TRIM('Base de Datos'!B416),".",""),",","."),".",","),_xlfn.NUMBERVALUE(SUBSTITUTE(TRIM('Base de Datos'!B416),",",""),".",",")),""))) | AF420: =IF(ISNUMBER(AG420),IF(ISNUMBER('Base de Datos'!I416),IF('Base de Datos'!I416>20000,INT('Base de Datos'!I416),""),IF(TRIM('Base de Datos'!I416)="","",IFERROR(DATE(VALUE(RIGHT(TRIM('Base de Datos'!I416),4)),VALUE(MID(TRIM('Base de Datos'!I416),4,2)),VALUE(LEFT(TRIM('Base de Datos'!I416),2))),IFERROR(DATEVALUE(TRIM('Base de Datos'!I416)),"")))),"") | AG420: =IF(ISNUMBER('Base de Datos'!J416),'Base de Datos'!J416,IF(TRIM('Base de Datos'!J416)="","",IFERROR(IF(IFERROR(FIND("@",SUBSTITUTE(TRIM('Base de Datos'!J416),",","@",LEN(TRIM('Base de Datos'!J416))-LEN(SUBSTITUTE(TRIM('Base de Datos'!J416),",","")))),0)>IFERROR(FIND("@",SUBSTITUTE(TRIM('Base de Datos'!J416),".","@",LEN(TRIM('Base de Datos'!J416))-LEN(SUBSTITUTE(TRIM('Base de Datos'!J416),".","")))),0),_xlfn.NUMBERVALUE(SUBSTITUTE(SUBSTITUTE(TRIM('Base de Datos'!J416),".",""),",","."),".",","),_xlfn.NUMBERVALUE(SUBSTITUTE(TRIM('Base de Datos'!J416),",",""),".",",")),"")))
R421: =ROWS(R$13:R421) -> 409 | S421: =IF(S420="","",IFERROR(SMALL($AD$10:$AD$509,COUNTIF($AD$10:$AD$509,"<="&S420)+1),"")) | T421: =IF(S421="","",INDEX($AE$10:$AE$509,MATCH(S421,$AD$10:$AD$509,0))) | U421: =IF(S421="","",IFERROR(INDEX($AG$10:$AG$509,MATCH(S421,$AF$10:$AF$509,0)),"")) | V421: =IF(AND(ISNUMBER(T421),ISNUMBER(T420)),T421/T420-1,"") | W421: =IF(AND(ISNUMBER(U421),ISNUMBER(U420)),U421/U420-1,"") | X421: =IF(AND(ISNUMBER(V421),ISNUMBER(W421)),1,"") | Y421: =IF(X421=1,V421,"") | Z421: =IF(X421=1,W421,"") | AA421: =IF(X421=1,V421,NA()) -> #N/A | AB421: =IF(X421=1,W421,NA()) -> #N/A | AD421: =IF(ISNUMBER(AE421),IF(ISNUMBER('Base de Datos'!A417),IF('Base de Datos'!A417>20000,DATE(YEAR('Base de Datos'!A417),DAY('Base de Datos'!A417),MONTH('Base de Datos'!A417)),""),IF(TRIM('Base de Datos'!A417)="","",IFERROR(DATE(VALUE(RIGHT(TRIM('Base de Datos'!A417),4)),VALUE(LEFT(TRIM('Base de Datos'!A417),2)),VALUE(MID(TRIM('Base de Datos'!A417),4,2))),""))),"") | AE421: =IF(ISNUMBER('Base de Datos'!B417),'Base de Datos'!B417,IF(TRIM('Base de Datos'!B417)="","",IFERROR(IF(IFERROR(FIND("@",SUBSTITUTE(TRIM('Base de Datos'!B417),",","@",LEN(TRIM('Base de Datos'!B417))-LEN(SUBSTITUTE(TRIM('Base de Datos'!B417),",","")))),0)>IFERROR(FIND("@",SUBSTITUTE(TRIM('Base de Datos'!B417),".","@",LEN(TRIM('Base de Datos'!B417))-LEN(SUBSTITUTE(TRIM('Base de Datos'!B417),".","")))),0),_xlfn.NUMBERVALUE(SUBSTITUTE(SUBSTITUTE(TRIM('Base de Datos'!B417),".",""),",","."),".",","),_xlfn.NUMBERVALUE(SUBSTITUTE(TRIM('Base de Datos'!B417),",",""),".",",")),""))) | AF421: =IF(ISNUMBER(AG421),IF(ISNUMBER('Base de Datos'!I417),IF('Base de Datos'!I417>20000,INT('Base de Datos'!I417),""),IF(TRIM('Base de Datos'!I417)="","",IFERROR(DATE(VALUE(RIGHT(TRIM('Base de Datos'!I417),4)),VALUE(MID(TRIM('Base de Datos'!I417),4,2)),VALUE(LEFT(TRIM('Base de Datos'!I417),2))),IFERROR(DATEVALUE(TRIM('Base de Datos'!I417)),"")))),"") | AG421: =IF(ISNUMBER('Base de Datos'!J417),'Base de Datos'!J417,IF(TRIM('Base de Datos'!J417)="","",IFERROR(IF(IFERROR(FIND("@",SUBSTITUTE(TRIM('Base de Datos'!J417),",","@",LEN(TRIM('Base de Datos'!J417))-LEN(SUBSTITUTE(TRIM('Base de Datos'!J417),",","")))),0)>IFERROR(FIND("@",SUBSTITUTE(TRIM('Base de Datos'!J417),".","@",LEN(TRIM('Base de Datos'!J417))-LEN(SUBSTITUTE(TRIM('Base de Datos'!J417),".","")))),0),_xlfn.NUMBERVALUE(SUBSTITUTE(SUBSTITUTE(TRIM('Base de Datos'!J417),".",""),",","."),".",","),_xlfn.NUMBERVALUE(SUBSTITUTE(TRIM('Base de Datos'!J417),",",""),".",",")),"")))
R422: =ROWS(R$13:R422) -> 410 | S422: =IF(S421="","",IFERROR(SMALL($AD$10:$AD$509,COUNTIF($AD$10:$AD$509,"<="&S421)+1),"")) | T422: =IF(S422="","",INDEX($AE$10:$AE$509,MATCH(S422,$AD$10:$AD$509,0))) | U422: =IF(S422="","",IFERROR(INDEX($AG$10:$AG$509,MATCH(S422,$AF$10:$AF$509,0)),"")) | V422: =IF(AND(ISNUMBER(T422),ISNUMBER(T421)),T422/T421-1,"") | W422: =IF(AND(ISNUMBER(U422),ISNUMBER(U421)),U422/U421-1,"") | X422: =IF(AND(ISNUMBER(V422),ISNUMBER(W422)),1,"") | Y422: =IF(X422=1,V422,"") | Z422: =IF(X422=1,W422,"") | AA422: =IF(X422=1,V422,NA()) -> #N/A | AB422: =IF(X422=1,W422,NA()) -> #N/A | AD422: =IF(ISNUMBER(AE422),IF(ISNUMBER('Base de Datos'!A418),IF('Base de Datos'!A418>20000,DATE(YEAR('Base de Datos'!A418),DAY('Base de Datos'!A418),MONTH('Base de Datos'!A418)),""),IF(TRIM('Base de Datos'!A418)="","",IFERROR(DATE(VALUE(RIGHT(TRIM('Base de Datos'!A418),4)),VALUE(LEFT(TRIM('Base de Datos'!A418),2)),VALUE(MID(TRIM('Base de Datos'!A418),4,2))),""))),"") | AE422: =IF(ISNUMBER('Base de Datos'!B418),'Base de Datos'!B418,IF(TRIM('Base de Datos'!B418)="","",IFERROR(IF(IFERROR(FIND("@",SUBSTITUTE(TRIM('Base de Datos'!B418),",","@",LEN(TRIM('Base de Datos'!B418))-LEN(SUBSTITUTE(TRIM('Base de Datos'!B418),",","")))),0)>IFERROR(FIND("@",SUBSTITUTE(TRIM('Base de Datos'!B418),".","@",LEN(TRIM('Base de Datos'!B418))-LEN(SUBSTITUTE(TRIM('Base de Datos'!B418),".","")))),0),_xlfn.NUMBERVALUE(SUBSTITUTE(SUBSTITUTE(TRIM('Base de Datos'!B418),".",""),",","."),".",","),_xlfn.NUMBERVALUE(SUBSTITUTE(TRIM('Base de Datos'!B418),",",""),".",",")),""))) | AF422: =IF(ISNUMBER(AG422),IF(ISNUMBER('Base de Datos'!I418),IF('Base de Datos'!I418>20000,INT('Base de Datos'!I418),""),IF(TRIM('Base de Datos'!I418)="","",IFERROR(DATE(VALUE(RIGHT(TRIM('Base de Datos'!I418),4)),VALUE(MID(TRIM('Base de Datos'!I418),4,2)),VALUE(LEFT(TRIM('Base de Datos'!I418),2))),IFERROR(DATEVALUE(TRIM('Base de Datos'!I418)),"")))),"") | AG422: =IF(ISNUMBER('Base de Datos'!J418),'Base de Datos'!J418,IF(TRIM('Base de Datos'!J418)="","",IFERROR(IF(IFERROR(FIND("@",SUBSTITUTE(TRIM('Base de Datos'!J418),",","@",LEN(TRIM('Base de Datos'!J418))-LEN(SUBSTITUTE(TRIM('Base de Datos'!J418),",","")))),0)>IFERROR(FIND("@",SUBSTITUTE(TRIM('Base de Datos'!J418),".","@",LEN(TRIM('Base de Datos'!J418))-LEN(SUBSTITUTE(TRIM('Base de Datos'!J418),".","")))),0),_xlfn.NUMBERVALUE(SUBSTITUTE(SUBSTITUTE(TRIM('Base de Datos'!J418),".",""),",","."),".",","),_xlfn.NUMBERVALUE(SUBSTITUTE(TRIM('Base de Datos'!J418),",",""),".",",")),"")))
R423: =ROWS(R$13:R423) -> 411 | S423: =IF(S422="","",IFERROR(SMALL($AD$10:$AD$509,COUNTIF($AD$10:$AD$509,"<="&S422)+1),"")) | T423: =IF(S423="","",INDEX($AE$10:$AE$509,MATCH(S423,$AD$10:$AD$509,0))) | U423: =IF(S423="","",IFERROR(INDEX($AG$10:$AG$509,MATCH(S423,$AF$10:$AF$509,0)),"")) | V423: =IF(AND(ISNUMBER(T423),ISNUMBER(T422)),T423/T422-1,"") | W423: =IF(AND(ISNUMBER(U423),ISNUMBER(U422)),U423/U422-1,"") | X423: =IF(AND(ISNUMBER(V423),ISNUMBER(W423)),1,"") | Y423: =IF(X423=1,V423,"") | Z423: =IF(X423=1,W423,"") | AA423: =IF(X423=1,V423,NA()) -> #N/A | AB423: =IF(X423=1,W423,NA()) -> #N/A | AD423: =IF(ISNUMBER(AE423),IF(ISNUMBER('Base de Datos'!A419),IF('Base de Datos'!A419>20000,DATE(YEAR('Base de Datos'!A419),DAY('Base de Datos'!A419),MONTH('Base de Datos'!A419)),""),IF(TRIM('Base de Datos'!A419)="","",IFERROR(DATE(VALUE(RIGHT(TRIM('Base de Datos'!A419),4)),VALUE(LEFT(TRIM('Base de Datos'!A419),2)),VALUE(MID(TRIM('Base de Datos'!A419),4,2))),""))),"") | AE423: =IF(ISNUMBER('Base de Datos'!B419),'Base de Datos'!B419,IF(TRIM('Base de Datos'!B419)="","",IFERROR(IF(IFERROR(FIND("@",SUBSTITUTE(TRIM('Base de Datos'!B419),",","@",LEN(TRIM('Base de Datos'!B419))-LEN(SUBSTITUTE(TRIM('Base de Datos'!B419),",","")))),0)>IFERROR(FIND("@",SUBSTITUTE(TRIM('Base de Datos'!B419),".","@",LEN(TRIM('Base de Datos'!B419))-LEN(SUBSTITUTE(TRIM('Base de Datos'!B419),".","")))),0),_xlfn.NUMBERVALUE(SUBSTITUTE(SUBSTITUTE(TRIM('Base de Datos'!B419),".",""),",","."),".",","),_xlfn.NUMBERVALUE(SUBSTITUTE(TRIM('Base de Datos'!B419),",",""),".",",")),""))) | AF423: =IF(ISNUMBER(AG423),IF(ISNUMBER('Base de Datos'!I419),IF('Base de Datos'!I419>20000,INT('Base de Datos'!I419),""),IF(TRIM('Base de Datos'!I419)="","",IFERROR(DATE(VALUE(RIGHT(TRIM('Base de Datos'!I419),4)),VALUE(MID(TRIM('Base de Datos'!I419),4,2)),VALUE(LEFT(TRIM('Base de Datos'!I419),2))),IFERROR(DATEVALUE(TRIM('Base de Datos'!I419)),"")))),"") | AG423: =IF(ISNUMBER('Base de Datos'!J419),'Base de Datos'!J419,IF(TRIM('Base de Datos'!J419)="","",IFERROR(IF(IFERROR(FIND("@",SUBSTITUTE(TRIM('Base de Datos'!J419),",","@",LEN(TRIM('Base de Datos'!J419))-LEN(SUBSTITUTE(TRIM('Base de Datos'!J419),",","")))),0)>IFERROR(FIND("@",SUBSTITUTE(TRIM('Base de Datos'!J419),".","@",LEN(TRIM('Base de Datos'!J419))-LEN(SUBSTITUTE(TRIM('Base de Datos'!J419),".","")))),0),_xlfn.NUMBERVALUE(SUBSTITUTE(SUBSTITUTE(TRIM('Base de Datos'!J419),".",""),",","."),".",","),_xlfn.NUMBERVALUE(SUBSTITUTE(TRIM('Base de Datos'!J419),",",""),".",",")),"")))
R424: =ROWS(R$13:R424) -> 412 | S424: =IF(S423="","",IFERROR(SMALL($AD$10:$AD$509,COUNTIF($AD$10:$AD$509,"<="&S423)+1),"")) | T424: =IF(S424="","",INDEX($AE$10:$AE$509,MATCH(S424,$AD$10:$AD$509,0))) | U424: =IF(S424="","",IFERROR(INDEX($AG$10:$AG$509,MATCH(S424,$AF$10:$AF$509,0)),"")) | V424: =IF(AND(ISNUMBER(T424),ISNUMBER(T423)),T424/T423-1,"") | W424: =IF(AND(ISNUMBER(U424),ISNUMBER(U423)),U424/U423-1,"") | X424: =IF(AND(ISNUMBER(V424),ISNUMBER(W424)),1,"") | Y424: =IF(X424=1,V424,"") | Z424: =IF(X424=1,W424,"") | AA424: =IF(X424=1,V424,NA()) -> #N/A | AB424: =IF(X424=1,W424,NA()) -> #N/A | AD424: =IF(ISNUMBER(AE424),IF(ISNUMBER('Base de Datos'!A420),IF('Base de Datos'!A420>20000,DATE(YEAR('Base de Datos'!A420),DAY('Base de Datos'!A420),MONTH('Base de Datos'!A420)),""),IF(TRIM('Base de Datos'!A420)="","",IFERROR(DATE(VALUE(RIGHT(TRIM('Base de Datos'!A420),4)),VALUE(LEFT(TRIM('Base de Datos'!A420),2)),VALUE(MID(TRIM('Base de Datos'!A420),4,2))),""))),"") | AE424: =IF(ISNUMBER('Base de Datos'!B420),'Base de Datos'!B420,IF(TRIM('Base de Datos'!B420)="","",IFERROR(IF(IFERROR(FIND("@",SUBSTITUTE(TRIM('Base de Datos'!B420),",","@",LEN(TRIM('Base de Datos'!B420))-LEN(SUBSTITUTE(TRIM('Base de Datos'!B420),",","")))),0)>IFERROR(FIND("@",SUBSTITUTE(TRIM('Base de Datos'!B420),".","@",LEN(TRIM('Base de Datos'!B420))-LEN(SUBSTITUTE(TRIM('Base de Datos'!B420),".","")))),0),_xlfn.NUMBERVALUE(SUBSTITUTE(SUBSTITUTE(TRIM('Base de Datos'!B420),".",""),",","."),".",","),_xlfn.NUMBERVALUE(SUBSTITUTE(TRIM('Base de Datos'!B420),",",""),".",",")),""))) | AF424: =IF(ISNUMBER(AG424),IF(ISNUMBER('Base de Datos'!I420),IF('Base de Datos'!I420>20000,INT('Base de Datos'!I420),""),IF(TRIM('Base de Datos'!I420)="","",IFERROR(DATE(VALUE(RIGHT(TRIM('Base de Datos'!I420),4)),VALUE(MID(TRIM('Base de Datos'!I420),4,2)),VALUE(LEFT(TRIM('Base de Datos'!I420),2))),IFERROR(DATEVALUE(TRIM('Base de Datos'!I420)),"")))),"") | AG424: =IF(ISNUMBER('Base de Datos'!J420),'Base de Datos'!J420,IF(TRIM('Base de Datos'!J420)="","",IFERROR(IF(IFERROR(FIND("@",SUBSTITUTE(TRIM('Base de Datos'!J420),",","@",LEN(TRIM('Base de Datos'!J420))-LEN(SUBSTITUTE(TRIM('Base de Datos'!J420),",","")))),0)>IFERROR(FIND("@",SUBSTITUTE(TRIM('Base de Datos'!J420),".","@",LEN(TRIM('Base de Datos'!J420))-LEN(SUBSTITUTE(TRIM('Base de Datos'!J420),".","")))),0),_xlfn.NUMBERVALUE(SUBSTITUTE(SUBSTITUTE(TRIM('Base de Datos'!J420),".",""),",","."),".",","),_xlfn.NUMBERVALUE(SUBSTITUTE(TRIM('Base de Datos'!J420),",",""),".",",")),"")))
... R509: =ROWS(R$13:R509) -> 497 | S509: =IF(S508="","",IFERROR(SMALL($AD$10:$AD$509,COUNTIF($AD$10:$AD$509,"<="&S508)+1),"")) | T509: =IF(S509="","",INDEX($AE$10:$AE$509,MATCH(S509,$AD$10:$AD$509,0))) | U509: =IF(S509="","",IFERROR(INDEX($AG$10:$AG$509,MATCH(S509,$AF$10:$AF$509,0)),"")) | V509: =IF(AND(ISNUMBER(T509),ISNUMBER(T508)),T509/T508-1,"") | W509: =IF(AND(ISNUMBER(U509),ISNUMBER(U508)),U509/U508-1,"") | X509: =IF(AND(ISNUMBER(V509),ISNUMBER(W509)),1,"") | Y509: =IF(X509=1,V509,"") | Z509: =IF(X509=1,W509,"") | AA509: =IF(X509=1,V509,NA()) -> #N/A | AB509: =IF(X509=1,W509,NA()) -> #N/A | AD509: =IF(ISNUMBER(AE509),IF(ISNUMBER('Base de Datos'!A505),IF('Base de Datos'!A505>20000,DATE(YEAR('Base de Datos'!A505),DAY('Base de Datos'!A505),MONTH('Base de Datos'!A505)),""),IF(TRIM('Base de Datos'!A505)="","",IFERROR(DATE(VALUE(RIGHT(TRIM('Base de Datos'!A505),4)),VALUE(LEFT(TRIM('Base de Datos'!A505),2)),VALUE(MID(TRIM('Base de Datos'!A505),4,2))),""))),"") | AE509: =IF(ISNUMBER('Base de Datos'!B505),'Base de Datos'!B505,IF(TRIM('Base de Datos'!B505)="","",IFERROR(IF(IFERROR(FIND("@",SUBSTITUTE(TRIM('Base de Datos'!B505),",","@",LEN(TRIM('Base de Datos'!B505))-LEN(SUBSTITUTE(TRIM('Base de Datos'!B505),",","")))),0)>IFERROR(FIND("@",SUBSTITUTE(TRIM('Base de Datos'!B505),".","@",LEN(TRIM('Base de Datos'!B505))-LEN(SUBSTITUTE(TRIM('Base de Datos'!B505),".","")))),0),_xlfn.NUMBERVALUE(SUBSTITUTE(SUBSTITUTE(TRIM('Base de Datos'!B505),".",""),",","."),".",","),_xlfn.NUMBERVALUE(SUBSTITUTE(TRIM('Base de Datos'!B505),",",""),".",",")),""))) | AF509: =IF(ISNUMBER(AG509),IF(ISNUMBER('Base de Datos'!I505),IF('Base de Datos'!I505>20000,INT('Base de Datos'!I505),""),IF(TRIM('Base de Datos'!I505)="","",IFERROR(DATE(VALUE(RIGHT(TRIM('Base de Datos'!I505),4)),VALUE(MID(TRIM('Base de Datos'!I505),4,2)),VALUE(LEFT(TRIM('Base de Datos'!I505),2))),IFERROR(DATEVALUE(TRIM('Base de Datos'!I505)),"")))),"") | AG509: =IF(ISNUMBER('Base de Datos'!J505),'Base de Datos'!J505,IF(TRIM('Base de Datos'!J505)="","",IFERROR(IF(IFERROR(FIND("@",SUBSTITUTE(TRIM('Base de Datos'!J505),",","@",LEN(TRIM('Base de Datos'!J505))-LEN(SUBSTITUTE(TRIM('Base de Datos'!J505),",","")))),0)>IFERROR(FIND("@",SUBSTITUTE(TRIM('Base de Datos'!J505),".","@",LEN(TRIM('Base de Datos'!J505))-LEN(SUBSTITUTE(TRIM('Base de Datos'!J505),".","")))),0),_xlfn.NUMBERVALUE(SUBSTITUTE(SUBSTITUTE(TRIM('Base de Datos'!J505),".",""),",","."),".",","),_xlfn.NUMBERVALUE(SUBSTITUTE(TRIM('Base de Datos'!J505),",",""),".",",")),"")))
R510: =ROWS(R$13:R510) -> 498 | S510: =IF(S509="","",IFERROR(SMALL($AD$10:$AD$509,COUNTIF($AD$10:$AD$509,"<="&S509)+1),"")) | T510: =IF(S510="","",INDEX($AE$10:$AE$509,MATCH(S510,$AD$10:$AD$509,0))) | U510: =IF(S510="","",IFERROR(INDEX($AG$10:$AG$509,MATCH(S510,$AF$10:$AF$509,0)),"")) | V510: =IF(AND(ISNUMBER(T510),ISNUMBER(T509)),T510/T509-1,"") | W510: =IF(AND(ISNUMBER(U510),ISNUMBER(U509)),U510/U509-1,"") | X510: =IF(AND(ISNUMBER(V510),ISNUMBER(W510)),1,"") | Y510: =IF(X510=1,V510,"") | Z510: =IF(X510=1,W510,"") | AA510: =IF(X510=1,V510,NA()) -> #N/A | AB510: =IF(X510=1,W510,NA()) -> #N/A
R511: =ROWS(R$13:R511) -> 499 | S511: =IF(S510="","",IFERROR(SMALL($AD$10:$AD$509,COUNTIF($AD$10:$AD$509,"<="&S510)+1),"")) | T511: =IF(S511="","",INDEX($AE$10:$AE$509,MATCH(S511,$AD$10:$AD$509,0))) | U511: =IF(S511="","",IFERROR(INDEX($AG$10:$AG$509,MATCH(S511,$AF$10:$AF$509,0)),"")) | V511: =IF(AND(ISNUMBER(T511),ISNUMBER(T510)),T511/T510-1,"") | W511: =IF(AND(ISNUMBER(U511),ISNUMBER(U510)),U511/U510-1,"") | X511: =IF(AND(ISNUMBER(V511),ISNUMBER(W511)),1,"") | Y511: =IF(X511=1,V511,"") | Z511: =IF(X511=1,W511,"") | AA511: =IF(X511=1,V511,NA()) -> #N/A | AB511: =IF(X511=1,W511,NA()) -> #N/A
R512: =ROWS(R$13:R512) -> 500 | S512: =IF(S511="","",IFERROR(SMALL($AD$10:$AD$509,COUNTIF($AD$10:$AD$509,"<="&S511)+1),"")) | T512: =IF(S512="","",INDEX($AE$10:$AE$509,MATCH(S512,$AD$10:$AD$509,0))) | U512: =IF(S512="","",IFERROR(INDEX($AG$10:$AG$509,MATCH(S512,$AF$10:$AF$509,0)),"")) | V512: =IF(AND(ISNUMBER(T512),ISNUMBER(T511)),T512/T511-1,"") | W512: =IF(AND(ISNUMBER(U512),ISNUMBER(U511)),U512/U511-1,"") | X512: =IF(AND(ISNUMBER(V512),ISNUMBER(W512)),1,"") | Y512: =IF(X512=1,V512,"") | Z512: =IF(X512=1,W512,"") | AA512: =IF(X512=1,V512,NA()) -> #N/A | AB512: =IF(X512=1,W512,NA()) -> #N/A

Sheet Razones
A3: Días del trimestre | B3: 91.25
A6: ORGANIZACIÓN SORIANA | B6: 2T25 | C6: 3T25 | D6: 4T25 | E6: 1T26 | F6: 2T26 | G6: Promedio 5T
A7: Circulante | B7: =Datos!B19/Datos!B21 -> 1.2694752 | C7: =Datos!C19/Datos!C21 -> 1.3031422 | D7: =Datos!D19/Datos!D21 -> 1.2373849 | E7: =Datos!E19/Datos!E21 -> 1.2869129 | F7: =Datos!F19/Datos!F21 -> 1.1740294 | G7: =AVERAGE(B7:F7) -> 1.2541889
A8: Prueba ácida | B8: =(Datos!B19-Datos!B18)/Datos!B21 -> 0.35821259 | C8: =(Datos!C19-Datos!C18)/Datos!C21 -> 0.3501702 | D8: =(Datos!D19-Datos!D18)/Datos!D21 -> 0.414238 | E8: =(Datos!E19-Datos!E18)/Datos!E21 -> 0.3228065 | F8: =(Datos!F19-Datos!F18)/Datos!F21 -> 0.32826179 | G8: =AVERAGE(B8:F8) -> 0.35473781
